Workbook
Name CurrentYear: #REF!
Name Estimate_Amount: #REF!
Name Estimated_Amount2: #REF!

Sheet Summary
A1: HHM JV Hotels-5-Year Capital Plan Summary
B17: Property Information
B18: Property Name: | D18: Hotel
B19: Key Count: | D19: 100
B20: State Tax %: | D20: 0.0725
B21: General Manager:
B22: RVP Approval:
B23: 5-Year Plan | D23: 2024-2028
B25: FF&E Reserve Projection
F27: 2023 | G27: =D23 -> 2024-2028 | H27: 2024 | I27: =H27+1 -> 2025 | J27: =I27+1 -> 2026 | K27: =J27+1 -> 2027 | L27: =K27+1 -> 2028
B28: Hotel Revenues | F28: INPUT 2023 FORECASTED REVENUE HERE | G28: =SUM(H28:L28) -> 6000000 | H28: =SUM('2024 Capex Plan'!$I$28:$T$28) -> 1200000 | I28: =SUM('2025 Capex Plan'!$I$28:$T$28) -> 1200000 | J28: =SUM('2026 Capex Plan'!$I$28:$T$28) -> 1200000 | K28: =SUM('2027 Capex Plan'!$I$28:$T$28) -> 1200000 | L28: =SUM('2028 Capex Plan'!$I$28:$T$28) -> 1200000
B29: FF&E Reserve % | F29: =$G$29 -> 0.04 | G29: =AVERAGE('2024 Capex Plan'!F29,'2025 Capex Plan'!F29,'2026 Capex Plan'!F29,'2027 Capex Plan'!F29,'2028 Capex Plan'!F29) -> 0.04 | H29: =$G$29 -> 0.04 | I29: =$G$29 -> 0.04 | J29: =$G$29 -> 0.04 | K29: =$G$29 -> 0.04 | L29: =$G$29 -> 0.04
B30: FF&E Reserve $ | F30: =F28*F29 -> #VALUE! | G30: =G28*G29 -> 240000 | H30: =H28*H29 -> 48000 | I30: =I28*I29 -> 48000 | J30: =J28*J29 -> 48000 | K30: =K28*K29 -> 48000 | L30: =L28*L29 -> 48000
B31: Total Estimated Capital Expenditures | F31: INPUT 2023 FORECASTED CAPEX SPEND | G31: =SUM(H31:L31) -> 175628.2 | H31: =H50 -> 35125.641 | I31: =I50 -> 35125.641 | J31: =J50 -> 35125.641 | K31: =K50 -> 35125.641 | L31: =L50 -> 35125.641
B32: Carryover FF&E Reserve | F32: =F30-F31 -> #VALUE! | G32: =G30-G31 -> 64371.797 | H32: =H30-H31 -> 12874.359 | I32: =I30-I31 -> 12874.359 | J32: =J30-J31 -> 12874.359 | K32: =K30-K31 -> 12874.359 | L32: =L30-L31 -> 12874.359
B33: FF&E Reserve % of Revenue | F33: =F31/F28 -> #VALUE! | G33: =G31/G28 -> 0.029271367 | H33: =H31/H28 -> 0.029271367 | I33: =I31/I28 -> 0.029271367 | J33: =J31/J28 -> 0.029271367 | K33: =K31/K28 -> 0.029271367 | L33: =L31/L28 -> 0.029271367
B35: =D23&" "& D18 & " " & "Non-PIP Capital Plan" -> 2024-2028 Hotel Non-PIP Capital Plan
B37: Item Description | E37: Comments | G37: =G27 -> 2024-2028 | H37: 2024 | I37: =H37+1 -> 2025 | J37: =I37+1 -> 2026 | K37: =J37+1 -> 2027 | L37: =K37+1 -> 2028
B38: (A) Guestrooms - Bathroom, Kitchen | G38: =SUM(H38:L38) -> 68417.724 | H38: ='2024 Capex Plan'!$L$37 -> 13683.545 | I38: ='2025 Capex Plan'!$L$37 -> 13683.545 | J38: ='2026 Capex Plan'!$L$37 -> 13683.545 | K38: ='2027 Capex Plan'!$L$37 -> 13683.545 | L38: ='2028 Capex Plan'!$L$37 -> 13683.545
B39: (B) Function Space - Meeting Banquet Space | G39: =SUM(H39:L39) -> 36041.631 | H39: ='2024 Capex Plan'!$L$50 -> 7208.3261 | I39: ='2025 Capex Plan'!$L$50 -> 7208.3261 | J39: ='2026 Capex Plan'!$L$50 -> 7208.3261 | K39: ='2027 Capex Plan'!$L$50 -> 7208.3261 | L39: ='2028 Capex Plan'!$L$50 -> 7208.3261
B40: (C) Public Areas - Lobby, Pool, Fitness, Corridors | G40: =SUM(H40:L40) -> 3384.0056 | H40: ='2024 Capex Plan'!$L$63 -> 676.80112 | I40: ='2025 Capex Plan'!$L$63 -> 676.80112 | J40: ='2026 Capex Plan'!$L$63 -> 676.80112 | K40: ='2027 Capex Plan'!$L$63 -> 676.80112 | L40: ='2028 Capex Plan'!$L$63 -> 676.80112
B41: (D) Technology - Computer Systems | G41: =SUM(H41:L41) -> 33789.381 | H41: ='2024 Capex Plan'!$L$76 -> 6757.8761 | I41: ='2025 Capex Plan'!$L$76 -> 6757.8761 | J41: ='2026 Capex Plan'!$L$76 -> 6757.8761 | K41: ='2027 Capex Plan'!$L$76 -> 6757.8761 | L41: ='2028 Capex Plan'!$L$76 -> 6757.8761
B42: (E) Back of House - Administrative, Laundry | G42: =SUM(H42:L42) -> 9014.6306 | H42: ='2024 Capex Plan'!$L$89 -> 1802.9261 | I42: ='2025 Capex Plan'!$L$89 -> 1802.9261 | J42: ='2026 Capex Plan'!$L$89 -> 1802.9261 | K42: ='2027 Capex Plan'!$L$89 -> 1802.9261 | L42: ='2028 Capex Plan'!$L$89 -> 1802.9261
B43: (F) Building - Site, Exterior, Mechanical | G43: =SUM(H43:L43) -> 9014.6306 | H43: ='2024 Capex Plan'!$L$102 -> 1802.9261 | I43: ='2025 Capex Plan'!$L$102 -> 1802.9261 | J43: ='2026 Capex Plan'!$L$102 -> 1802.9261 | K43: ='2027 Capex Plan'!$L$102 -> 1802.9261 | L43: ='2028 Capex Plan'!$L$102 -> 1802.9261
B44: QA Total | G44: =SUM(H44:L44) -> 77432.355 | H44: ='2024 Capex Plan'!$L$115 -> 15486.471 | I44: ='2025 Capex Plan'!$L$115 -> 15486.471 | J44: ='2026 Capex Plan'!$L$115 -> 15486.471 | K44: ='2027 Capex Plan'!$L$115 -> 15486.471 | L44: ='2028 Capex Plan'!$L$115 -> 15486.471
B45: PIP Total | G45: =SUM(H45:L45) -> 45056.261 | H45: ='2024 Capex Plan'!$L$116 -> 9011.2523 | I45: ='2025 Capex Plan'!$L$116 -> 9011.2523 | J45: ='2026 Capex Plan'!$L$116 -> 9011.2523 | K45: ='2027 Capex Plan'!$L$116 -> 9011.2523 | L45: ='2028 Capex Plan'!$L$116 -> 9011.2523
B46: PCA Total | G46: =SUM(H46:L46) -> 3384.0056 | H46: ='2024 Capex Plan'!$L$117 -> 676.80112 | I46: ='2025 Capex Plan'!$L$117 -> 676.80112 | J46: ='2026 Capex Plan'!$L$117 -> 676.80112 | K46: ='2027 Capex Plan'!$L$117 -> 676.80112 | L46: ='2028 Capex Plan'!$L$117 -> 676.80112
B47: Other Total | G47: =SUM(H47:L47) -> 33789.381 | H47: ='2024 Capex Plan'!$L$118 -> 6757.8761 | I47: ='2025 Capex Plan'!$L$118 -> 6757.8761 | J47: ='2026 Capex Plan'!$L$118 -> 6757.8761 | K47: ='2027 Capex Plan'!$L$118 -> 6757.8761 | L47: ='2028 Capex Plan'!$L$118 -> 6757.8761
B48: Total Capital Expenditures excl. Contingency | G48: =SUM(H48:L48) -> 159662 | H48: ='2024 Capex Plan'!$L$119 -> 31932.4 | I48: ='2025 Capex Plan'!$L$119 -> 31932.4 | J48: ='2026 Capex Plan'!$L$119 -> 31932.4 | K48: ='2027 Capex Plan'!$L$119 -> 31932.4 | L48: ='2028 Capex Plan'!$L$119 -> 31932.4
B49: Contingency | D49: Fixed % of Total Capital Expenditures excl. Contingency | E49: =AVERAGE('2024 Capex Plan'!E120,'2025 Capex Plan'!E120,'2026 Capex Plan'!E120,'2027 Capex Plan'!E120,'2028 Capex Plan'!E120) -> 0.1 | F49: =IF(D49="Method - $ per Key","Per Key",IF(D19="Method - $ Allowance","Total","")) | G49: =SUM(H49:L49) -> 15966.2 | H49: ='2024 Capex Plan'!$L$120 -> 3193.24 | I49: ='2025 Capex Plan'!$L$120 -> 3193.24 | J49: ='2026 Capex Plan'!$L$120 -> 3193.24 | K49: ='2027 Capex Plan'!$L$120 -> 3193.24 | L49: ='2028 Capex Plan'!$L$120 -> 3193.24
B50: Total Capital Expenditures | G50: =SUM(H50:L50) -> 175628.2 | H50: =SUM(H48:H49) -> 35125.641 | I50: =SUM(I48:I49) -> 35125.641 | J50: =SUM(J48:J49) -> 35125.641 | K50: =SUM(K48:K49) -> 35125.641 | L50: =SUM(L48:L49) -> 35125.641

Sheet 2024 Capex Plan
B2: Instructions
B3: 1. Fill out Property Name, Key Count, State Tax % , and General Manager in the Property Information Box 2. Input budget Total Revenues in row 28 columns I to T 3. Input current FF&E reserve balance in cell F32 4. Fill out all applicable data by hotel departments found in the Hotel Capital Plan section. Only fill in columns C to H and total amounts will calculate in columns I through M. Remember to select from Category dropdown options. 3. Spread the estimated capex amount by month in columns N though Y. 4. Capex plans should be reviewed with Regional VPs and Engineering. Once the plan has been approved, the RVP should initial in the RVP Approval box in the Property Information section. IMPORTANT: Do not add or delete rows or columns from the model.
B17: Property Information
B18: Property Name: | D18: Hotel
B19: Key Count: | D19: 100
B20: State Tax %: | D20: 0.0725
B21: General Manager:
B22: RVP Approval:
B23: Budget Year | D23: 2024
B25: FF&E Reserve Projection
F27: =D23 -> 2024 | I27: January | J27: February | K27: March | L27: April | M27: May | N27: June | O27: July | P27: August | Q27: September | R27: October | S27: November | T27: December
B28: Hotel Revenues | F28: =SUM(I28:T28) -> 1200000 | I28: 100000 | J28: 100000 | K28: 100000 | L28: 100000 | M28: 100000 | N28: 100000 | O28: 100000 | P28: 100000 | Q28: 100000 | R28: 100000 | S28: 100000 | T28: 100000
B29: FF&E Reserve % | F29: 0.04 | I29: =$F$29 -> 0.04 | J29: =$F$29 -> 0.04 | K29: =$F$29 -> 0.04 | L29: =$F$29 -> 0.04 | M29: =$F$29 -> 0.04 | N29: =$F$29 -> 0.04 | O29: =$F$29 -> 0.04 | P29: =$F$29 -> 0.04 | ... T29: =$F$29 -> 0.04
B30: Estimated FF&E Reserve | F30: =F28*F29 -> 48000 | I30: =I28*I29 -> 4000 | J30: =J28*J29 -> 4000 | K30: =K28*K29 -> 4000 | L30: =L28*L29 -> 4000 | M30: =M28*M29 -> 4000 | N30: =N28*N29 -> 4000 | O30: =O28*O29 -> 4000 | P30: =P28*P29 -> 4000 | ... T30: =T28*T29 -> 4000
B31: Total Estimated Capital Expenditures | F31: =SUM(I31:T31) -> 35125.641 | I31: =N121 -> 35125.641 | J31: =O121 -> 0 | K31: =P121 -> 0 | L31: =Q121 -> 0 | M31: =R121 -> 0 | N31: =S121 -> 0 | O31: =T121 -> 0 | P31: =U121 -> 0 | ... T31: =Y121 -> 0
B32: % of Revenue | F32: =F31/F28 -> 0.029271367 | I32: =I31/I28 -> 0.35125641 | J32: =J31/J28 -> 0 | K32: =K31/K28 -> 0 | L32: =L31/L28 -> 0 | M32: =M31/M28 -> 0 | N32: =N31/N28 -> 0 | O32: =O31/O28 -> 0 | P32: =P31/P28 -> 0 | ... T32: =T31/T28 -> 0
B34: =D23&" "& D18 & " " & "Capital Plan" -> 2024 Hotel Capital Plan
B36: Item Description | D36: Comments | E36: Category | F36: Quantity | G36: Unit Price | H36: Freight Cost | I36: Sub Total | J36: Tax | K36: Purchase Fee | L36: Estimate Amount | M36: Budget Amount | N36: January | O36: February | P36: March | Q36: April | R36: May | S36: June | T36: July | U36: August | V36: September | W36: October | X36: November | Y36: December
B37: (A) Guestrooms - Bathroom, Kitchen | H37: =SUM(H38:H49) -> 1 | I37: =SUM(I38:I49) -> 12151 | J37: =SUM(J38:J49) -> 880.9475 | K37: =SUM(K38:K49) -> 651.59738 | L37: =SUM(L38:L49) -> 13683.545 | M37: =SUM(M38:M49) -> 13683.545 | N37: =SUM(N38:N49) -> 13683.545 | O37: =SUM(O38:O49) -> 0 | ... Y37: =SUM(Y38:Y49) -> 0
B38: A1 | C38: Example | D38: Text | E38: QA | F38: 18 | G38: 675 | H38: 1 | I38: =(F38*G38)+H38 -> 12151 | J38: =I38*$D$20 -> 880.9475 | K38: =SUM(I38:J38)*5% -> 651.59738 | L38: =SUM(I38:K38) -> 13683.545 | M38: =SUM(N38, O38,P38,Q38,R38,S38,T38,U38,V38,W38,X38,Y38) -> 13683.545 | N38: =L38 -> 13683.545
B39: A2 | E39: PCA | I39: =(F39*G39)+H39 -> 0 | J39: =I39*$D$20 -> 0 | K39: =SUM(I39:J39)*5% -> 0 | L39: =SUM(I39:K39) -> 0 | M39: =SUM(N39, O39,P39,Q39,R39,S39,T39,U39,V39,W39,X39,Y39) -> 0
B40: A3 | I40: =(F40*G40)+H40 -> 0 | J40: =I40*$D$20 -> 0 | K40: =SUM(I40:J40)*5% -> 0 | L40: =SUM(I40:K40) -> 0 | M40: =SUM(N40, O40,P40,Q40,R40,S40,T40,U40,V40,W40,X40,Y40) -> 0
B41: A4 | I41: =(F41*G41)+H41 -> 0 | J41: =I41*$D$20 -> 0 | K41: =SUM(I41:J41)*5% -> 0 | L41: =SUM(I41:K41) -> 0 | M41: =SUM(N41, O41,P41,Q41,R41,S41,T41,U41,V41,W41,X41,Y41) -> 0
B42: A5 | I42: =(F42*G42)+H42 -> 0 | J42: =I42*$D$20 -> 0 | K42: =SUM(I42:J42)*5% -> 0 | L42: =SUM(I42:K42) -> 0 | M42: =SUM(N42, O42,P42,Q42,R42,S42,T42,U42,V42,W42,X42,Y42) -> 0
B43: A6 | I43: =(F43*G43)+H43 -> 0 | J43: =I43*$D$20 -> 0 | K43: =SUM(I43:J43)*5% -> 0 | L43: =SUM(I43:K43) -> 0 | M43: =SUM(N43, O43,P43,Q43,R43,S43,T43,U43,V43,W43,X43,Y43) -> 0
B44: A7 | I44: =(F44*G44)+H44 -> 0 | J44: =I44*$D$20 -> 0 | K44: =SUM(I44:J44)*5% -> 0 | L44: =SUM(I44:K44) -> 0 | M44: =SUM(N44, O44,P44,Q44,R44,S44,T44,U44,V44,W44,X44,Y44) -> 0
B45: A8 | I45: =(F45*G45)+H45 -> 0 | J45: =I45*$D$20 -> 0 | K45: =SUM(I45:J45)*5% -> 0 | L45: =SUM(I45:K45) -> 0 | M45: =SUM(N45, O45,P45,Q45,R45,S45,T45,U45,V45,W45,X45,Y45) -> 0
B46: A9 | I46: =(F46*G46)+H46 -> 0 | J46: =I46*$D$20 -> 0 | K46: =SUM(I46:J46)*5% -> 0 | L46: =SUM(I46:K46) -> 0 | M46: =SUM(N46, O46,P46,Q46,R46,S46,T46,U46,V46,W46,X46,Y46) -> 0
B47: A10 | I47: =(F47*G47)+H47 -> 0 | J47: =I47*$D$20 -> 0 | K47: =SUM(I47:J47)*5% -> 0 | L47: =SUM(I47:K47) -> 0 | M47: =SUM(N47, O47,P47,Q47,R47,S47,T47,U47,V47,W47,X47,Y47) -> 0
B48: A11 | I48: =(F48*G48)+H48 -> 0 | J48: =I48*$D$20 -> 0 | K48: =SUM(I48:J48)*5% -> 0 | L48: =SUM(I48:K48) -> 0 | M48: =SUM(N48, O48,P48,Q48,R48,S48,T48,U48,V48,W48,X48,Y48) -> 0
B49: A12 | I49: =(F49*G49)+H49 -> 0 | J49: =I49*$D$20 -> 0 | K49: =SUM(I49:J49)*5% -> 0 | L49: =SUM(I49:K49) -> 0 | M49: =SUM(N49, O49,P49,Q49,R49,S49,T49,U49,V49,W49,X49,Y49) -> 0
B50: (B) Function Space - Meeting Banquet Space | H50: =SUM(H51:H62) -> 1 | I50: =SUM(I51:I62) -> 6401 | J50: =SUM(J51:J62) -> 464.0725 | K50: =SUM(K51:K62) -> 343.25363 | L50: =SUM(L51:L62) -> 7208.3261 | M50: =SUM(M51:M62) -> 7208.3261 | N50: =SUM(N51:N62) -> 7208.3261 | O50: =SUM(O51:O62) -> 0 | ... Y50: =SUM(Y51:Y62) -> 0
B51: B1 | C51: Example | D51: Text | E51: PIP | F51: 4 | G51: 1600 | H51: 1 | I51: =(F51*G51)+H51 -> 6401 | J51: =I51*$D$20 -> 464.0725 | K51: =SUM(I51:J51)*5% -> 343.25363 | L51: =SUM(I51:K51) -> 7208.3261 | M51: =SUM(N51, O51,P51,Q51,R51,S51,T51,U51,V51,W51,X51,Y51) -> 7208.3261 | N51: =L51 -> 7208.3261
B52: B2 | I52: =(F52*G52)+H52 -> 0 | J52: =I52*$D$20 -> 0 | K52: =SUM(I52:J52)*5% -> 0 | L52: =SUM(I52:K52) -> 0 | M52: =SUM(N52, O52,P52,Q52,R52,S52,T52,U52,V52,W52,X52,Y52) -> 0
B53: B3 | I53: =(F53*G53)+H53 -> 0 | J53: =I53*$D$20 -> 0 | K53: =SUM(I53:J53)*5% -> 0 | L53: =SUM(I53:K53) -> 0 | M53: =SUM(N53, O53,P53,Q53,R53,S53,T53,U53,V53,W53,X53,Y53) -> 0
B54: B4 | I54: =(F54*G54)+H54 -> 0 | J54: =I54*$D$20 -> 0 | K54: =SUM(I54:J54)*5% -> 0 | L54: =SUM(I54:K54) -> 0 | M54: =SUM(N54, O54,P54,Q54,R54,S54,T54,U54,V54,W54,X54,Y54) -> 0
B55: B5 | I55: =(F55*G55)+H55 -> 0 | J55: =I55*$D$20 -> 0 | K55: =SUM(I55:J55)*5% -> 0 | L55: =SUM(I55:K55) -> 0 | M55: =SUM(N55, O55,P55,Q55,R55,S55,T55,U55,V55,W55,X55,Y55) -> 0
B56: B6 | I56: =(F56*G56)+H56 -> 0 | J56: =I56*$D$20 -> 0 | K56: =SUM(I56:J56)*5% -> 0 | L56: =SUM(I56:K56) -> 0 | M56: =SUM(N56, O56,P56,Q56,R56,S56,T56,U56,V56,W56,X56,Y56) -> 0
B57: B7 | I57: =(F57*G57)+H57 -> 0 | J57: =I57*$D$20 -> 0 | K57: =SUM(I57:J57)*5% -> 0 | L57: =SUM(I57:K57) -> 0 | M57: =SUM(N57, O57,P57,Q57,R57,S57,T57,U57,V57,W57,X57,Y57) -> 0
B58: B8 | I58: =(F58*G58)+H58 -> 0 | J58: =I58*$D$20 -> 0 | K58: =SUM(I58:J58)*5% -> 0 | L58: =SUM(I58:K58) -> 0 | M58: =SUM(N58, O58,P58,Q58,R58,S58,T58,U58,V58,W58,X58,Y58) -> 0
B59: B9 | I59: =(F59*G59)+H59 -> 0 | J59: =I59*$D$20 -> 0 | K59: =SUM(I59:J59)*5% -> 0 | L59: =SUM(I59:K59) -> 0 | M59: =SUM(N59, O59,P59,Q59,R59,S59,T59,U59,V59,W59,X59,Y59) -> 0
B60: B10 | I60: =(F60*G60)+H60 -> 0 | J60: =I60*$D$20 -> 0 | K60: =SUM(I60:J60)*5% -> 0 | L60: =SUM(I60:K60) -> 0 | M60: =SUM(N60, O60,P60,Q60,R60,S60,T60,U60,V60,W60,X60,Y60) -> 0
B61: B11 | I61: =(F61*G61)+H61 -> 0 | J61: =I61*$D$20 -> 0 | K61: =SUM(I61:J61)*5% -> 0 | L61: =SUM(I61:K61) -> 0 | M61: =SUM(N61, O61,P61,Q61,R61,S61,T61,U61,V61,W61,X61,Y61) -> 0
B62: B12 | I62: =(F62*G62)+H62 -> 0 | J62: =I62*$D$20 -> 0 | K62: =SUM(I62:J62)*5% -> 0 | L62: =SUM(I62:K62) -> 0 | M62: =SUM(N62, O62,P62,Q62,R62,S62,T62,U62,V62,W62,X62,Y62) -> 0
B63: (C) Public Areas - Lobby, Pool, Fitness, Corridors | H63: =SUM(H64:H75) -> 1 | I63: =SUM(I64:I75) -> 601 | J63: =SUM(J64:J75) -> 43.5725 | K63: =SUM(K64:K75) -> 32.228625 | L63: =SUM(L64:L75) -> 676.80112 | M63: =SUM(M64:M75) -> 676.80112 | N63: =SUM(N64:N75) -> 676.80112 | O63: =SUM(O64:O75) -> 0 | ... Y63: =SUM(Y64:Y75) -> 0
B64: C1 | C64: Example | D64: Text | E64: PCA | F64: 2 | G64: 300 | H64: 1 | I64: =(F64*G64)+H64 -> 601 | J64: =I64*$D$20 -> 43.5725 | K64: =SUM(I64:J64)*5% -> 32.228625 | L64: =SUM(I64:K64) -> 676.80112 | M64: =SUM(N64, O64,P64,Q64,R64,S64,T64,U64,V64,W64,X64,Y64) -> 676.80112 | N64: =L64 -> 676.80112
B65: C2 | I65: =(F65*G65)+H65 -> 0 | J65: =I65*$D$20 -> 0 | K65: =SUM(I65:J65)*5% -> 0 | L65: =SUM(I65:K65) -> 0 | M65: =SUM(N65, O65,P65,Q65,R65,S65,T65,U65,V65,W65,X65,Y65) -> 0
B66: C3 | I66: =(F66*G66)+H66 -> 0 | J66: =I66*$D$20 -> 0 | K66: =SUM(I66:J66)*5% -> 0 | L66: =SUM(I66:K66) -> 0 | M66: =SUM(N66, O66,P66,Q66,R66,S66,T66,U66,V66,W66,X66,Y66) -> 0
B67: C4 | I67: =(F67*G67)+H67 -> 0 | J67: =I67*$D$20 -> 0 | K67: =SUM(I67:J67)*5% -> 0 | L67: =SUM(I67:K67) -> 0 | M67: =SUM(N67, O67,P67,Q67,R67,S67,T67,U67,V67,W67,X67,Y67) -> 0
B68: C5 | I68: =(F68*G68)+H68 -> 0 | J68: =I68*$D$20 -> 0 | K68: =SUM(I68:J68)*5% -> 0 | L68: =SUM(I68:K68) -> 0 | M68: =SUM(N68, O68,P68,Q68,R68,S68,T68,U68,V68,W68,X68,Y68) -> 0
B69: C6 | I69: =(F69*G69)+H69 -> 0 | J69: =I69*$D$20 -> 0 | K69: =SUM(I69:J69)*5% -> 0 | L69: =SUM(I69:K69) -> 0 | M69: =SUM(N69, O69,P69,Q69,R69,S69,T69,U69,V69,W69,X69,Y69) -> 0
B70: C7 | I70: =(F70*G70)+H70 -> 0 | J70: =I70*$D$20 -> 0 | K70: =SUM(I70:J70)*5% -> 0 | L70: =SUM(I70:K70) -> 0 | M70: =SUM(N70, O70,P70,Q70,R70,S70,T70,U70,V70,W70,X70,Y70) -> 0
B71: C8 | I71: =(F71*G71)+H71 -> 0 | J71: =I71*$D$20 -> 0 | K71: =SUM(I71:J71)*5% -> 0 | L71: =SUM(I71:K71) -> 0 | M71: =SUM(N71, O71,P71,Q71,R71,S71,T71,U71,V71,W71,X71,Y71) -> 0
B72: C9 | I72: =(F72*G72)+H72 -> 0 | J72: =I72*$D$20 -> 0 | K72: =SUM(I72:J72)*5% -> 0 | L72: =SUM(I72:K72) -> 0 | M72: =SUM(N72, O72,P72,Q72,R72,S72,T72,U72,V72,W72,X72,Y72) -> 0
B73: C10 | I73: =(F73*G73)+H73 -> 0 | J73: =I73*$D$20 -> 0 | K73: =SUM(I73:J73)*5% -> 0 | L73: =SUM(I73:K73) -> 0 | M73: =SUM(N73, O73,P73,Q73,R73,S73,T73,U73,V73,W73,X73,Y73) -> 0
B74: C11 | I74: =(F74*G74)+H74 -> 0 | J74: =I74*$D$20 -> 0 | K74: =SUM(I74:J74)*5% -> 0 | L74: =SUM(I74:K74) -> 0 | M74: =SUM(N74, O74,P74,Q74,R74,S74,T74,U74,V74,W74,X74,Y74) -> 0
B75: C12 | I75: =(F75*G75)+H75 -> 0 | J75: =I75*$D$20 -> 0 | K75: =SUM(I75:J75)*5% -> 0 | L75: =SUM(I75:K75) -> 0 | M75: =SUM(N75, O75,P75,Q75,R75,S75,T75,U75,V75,W75,X75,Y75) -> 0
B76: (D) Technology - Computer Systems | H76: =SUM(H77:H88) -> 1 | I76: =SUM(I77:I88) -> 6001 | J76: =SUM(J77:J88) -> 435.0725 | K76: =SUM(K77:K88) -> 321.80363 | L76: =SUM(L77:L88) -> 6757.8761 | M76: =SUM(M77:M88) -> 6757.8761 | N76: =SUM(N77:N88) -> 6757.8761 | O76: =SUM(O77:O88) -> 0 | ... Y76: =SUM(Y77:Y88) -> 0
B77: D1 | C77: Example | D77: Text | E77: Other | F77: 2 | G77: 3000 | H77: 1 | I77: =(F77*G77)+H77 -> 6001 | J77: =I77*$D$20 -> 435.0725 | K77: =SUM(I77:J77)*5% -> 321.80363 | L77: =SUM(I77:K77) -> 6757.8761 | M77: =SUM(N77, O77,P77,Q77,R77,S77,T77,U77,V77,W77,X77,Y77) -> 6757.8761 | N77: =L77 -> 6757.8761
B78: D2 | I78: =(F78*G78)+H78 -> 0 | J78: =I78*$D$20 -> 0 | K78: =SUM(I78:J78)*5% -> 0 | L78: =SUM(I78:K78) -> 0 | M78: =SUM(N78, O78,P78,Q78,R78,S78,T78,U78,V78,W78,X78,Y78) -> 0
B79: D3 | I79: =(F79*G79)+H79 -> 0 | J79: =I79*$D$20 -> 0 | K79: =SUM(I79:J79)*5% -> 0 | L79: =SUM(I79:K79) -> 0 | M79: =SUM(N79, O79,P79,Q79,R79,S79,T79,U79,V79,W79,X79,Y79) -> 0
B80: D4 | I80: =(F80*G80)+H80 -> 0 | J80: =I80*$D$20 -> 0 | K80: =SUM(I80:J80)*5% -> 0 | L80: =SUM(I80:K80) -> 0 | M80: =SUM(N80, O80,P80,Q80,R80,S80,T80,U80,V80,W80,X80,Y80) -> 0
B81: D5 | I81: =(F81*G81)+H81 -> 0 | J81: =I81*$D$20 -> 0 | K81: =SUM(I81:J81)*5% -> 0 | L81: =SUM(I81:K81) -> 0 | M81: =SUM(N81, O81,P81,Q81,R81,S81,T81,U81,V81,W81,X81,Y81) -> 0
B82: D6 | I82: =(F82*G82)+H82 -> 0 | J82: =I82*$D$20 -> 0 | K82: =SUM(I82:J82)*5% -> 0 | L82: =SUM(I82:K82) -> 0 | M82: =SUM(N82, O82,P82,Q82,R82,S82,T82,U82,V82,W82,X82,Y82) -> 0
B83: D7 | I83: =(F83*G83)+H83 -> 0 | J83: =I83*$D$20 -> 0 | K83: =SUM(I83:J83)*5% -> 0 | L83: =SUM(I83:K83) -> 0 | M83: =SUM(N83, O83,P83,Q83,R83,S83,T83,U83,V83,W83,X83,Y83) -> 0
B84: D8 | I84: =(F84*G84)+H84 -> 0 | J84: =I84*$D$20 -> 0 | K84: =SUM(I84:J84)*5% -> 0 | L84: =SUM(I84:K84) -> 0 | M84: =SUM(N84, O84,P84,Q84,R84,S84,T84,U84,V84,W84,X84,Y84) -> 0
B85: D9 | I85: =(F85*G85)+H85 -> 0 | J85: =I85*$D$20 -> 0 | K85: =SUM(I85:J85)*5% -> 0 | L85: =SUM(I85:K85) -> 0 | M85: =SUM(N85, O85,P85,Q85,R85,S85,T85,U85,V85,W85,X85,Y85) -> 0
B86: D10 | I86: =(F86*G86)+H86 -> 0 | J86: =I86*$D$20 -> 0 | K86: =SUM(I86:J86)*5% -> 0 | L86: =SUM(I86:K86) -> 0 | M86: =SUM(N86, O86,P86,Q86,R86,S86,T86,U86,V86,W86,X86,Y86) -> 0
B87: D11 | I87: =(F87*G87)+H87 -> 0 | J87: =I87*$D$20 -> 0 | K87: =SUM(I87:J87)*5% -> 0 | L87: =SUM(I87:K87) -> 0 | M87: =SUM(N87, O87,P87,Q87,R87,S87,T87,U87,V87,W87,X87,Y87) -> 0
B88: D12 | I88: =(F88*G88)+H88 -> 0 | J88: =I88*$D$20 -> 0 | K88: =SUM(I88:J88)*5% -> 0 | L88: =SUM(I88:K88) -> 0 | M88: =SUM(N88, O88,P88,Q88,R88,S88,T88,U88,V88,W88,X88,Y88) -> 0
B89: (E) Back of House - Administrative, Laundry | H89: =SUM(H90:H101) -> 1 | I89: =SUM(I90:I101) -> 1601 | J89: =SUM(J90:J101) -> 116.0725 | K89: =SUM(K90:K101) -> 85.853625 | L89: =SUM(L90:L101) -> 1802.9261 | M89: =SUM(M90:M101) -> 1802.9261 | N89: =SUM(N90:N101) -> 1802.9261 | O89: =SUM(O90:O101) -> 0 | ... Y89: =SUM(Y90:Y101) -> 0
B90: E1 | C90: Example | D90: Text | E90: QA | F90: 1 | G90: 1600 | H90: 1 | I90: =(F90*G90)+H90 -> 1601 | J90: =I90*$D$20 -> 116.0725 | K90: =SUM(I90:J90)*5% -> 85.853625 | L90: =SUM(I90:K90) -> 1802.9261 | M90: =SUM(N90, O90,P90,Q90,R90,S90,T90,U90,V90,W90,X90,Y90) -> 1802.9261 | N90: =L90 -> 1802.9261
B91: E2 | I91: =(F91*G91)+H91 -> 0 | J91: =I91*$D$20 -> 0 | K91: =SUM(I91:J91)*5% -> 0 | L91: =SUM(I91:K91) -> 0 | M91: =SUM(N91, O91,P91,Q91,R91,S91,T91,U91,V91,W91,X91,Y91) -> 0
B92: E3 | I92: =(F92*G92)+H92 -> 0 | J92: =I92*$D$20 -> 0 | K92: =SUM(I92:J92)*5% -> 0 | L92: =SUM(I92:K92) -> 0 | M92: =SUM(N92, O92,P92,Q92,R92,S92,T92,U92,V92,W92,X92,Y92) -> 0
B93: E4 | I93: =(F93*G93)+H93 -> 0 | J93: =I93*$D$20 -> 0 | K93: =SUM(I93:J93)*5% -> 0 | L93: =SUM(I93:K93) -> 0 | M93: =SUM(N93, O93,P93,Q93,R93,S93,T93,U93,V93,W93,X93,Y93) -> 0
B94: E5 | I94: =(F94*G94)+H94 -> 0 | J94: =I94*$D$20 -> 0 | K94: =SUM(I94:J94)*5% -> 0 | L94: =SUM(I94:K94) -> 0 | M94: =SUM(N94, O94,P94,Q94,R94,S94,T94,U94,V94,W94,X94,Y94) -> 0
B95: E6 | I95: =(F95*G95)+H95 -> 0 | J95: =I95*$D$20 -> 0 | K95: =SUM(I95:J95)*5% -> 0 | L95: =SUM(I95:K95) -> 0 | M95: =SUM(N95, O95,P95,Q95,R95,S95,T95,U95,V95,W95,X95,Y95) -> 0
B96: E7 | I96: =(F96*G96)+H96 -> 0 | J96: =I96*$D$20 -> 0 | K96: =SUM(I96:J96)*5% -> 0 | L96: =SUM(I96:K96) -> 0 | M96: =SUM(N96, O96,P96,Q96,R96,S96,T96,U96,V96,W96,X96,Y96) -> 0
B97: E8 | I97: =(F97*G97)+H97 -> 0 | J97: =I97*$D$20 -> 0 | K97: =SUM(I97:J97)*5% -> 0 | L97: =SUM(I97:K97) -> 0 | M97: =SUM(N97, O97,P97,Q97,R97,S97,T97,U97,V97,W97,X97,Y97) -> 0
B98: E9 | I98: =(F98*G98)+H98 -> 0 | J98: =I98*$D$20 -> 0 | K98: =SUM(I98:J98)*5% -> 0 | L98: =SUM(I98:K98) -> 0 | M98: =SUM(N98, O98,P98,Q98,R98,S98,T98,U98,V98,W98,X98,Y98) -> 0
B99: E10 | I99: =(F99*G99)+H99 -> 0 | J99: =I99*$D$20 -> 0 | K99: =SUM(I99:J99)*5% -> 0 | L99: =SUM(I99:K99) -> 0 | M99: =SUM(N99, O99,P99,Q99,R99,S99,T99,U99,V99,W99,X99,Y99) -> 0
B100: E11 | I100: =(F100*G100)+H100 -> 0 | J100: =I100*$D$20 -> 0 | K100: =SUM(I100:J100)*5% -> 0 | L100: =SUM(I100:K100) -> 0 | M100: =SUM(N100, O100,P100,Q100,R100,S100,T100,U100,V100,W100,X100,Y100) -> 0
B101: E12 | I101: =(F101*G101)+H101 -> 0 | J101: =I101*$D$20 -> 0 | K101: =SUM(I101:J101)*5% -> 0 | L101: =SUM(I101:K101) -> 0 | M101: =SUM(N101, O101,P101,Q101,R101,S101,T101,U101,V101,W101,X101,Y101) -> 0
B102: (F) Building - Site, Exterior, Mechanical | H102: =SUM(H103:H114) -> 1 | I102: =SUM(I103:I114) -> 1601 | J102: =SUM(J103:J114) -> 116.0725 | K102: =SUM(K103:K114) -> 85.853625 | L102: =SUM(L103:L114) -> 1802.9261 | M102: =SUM(M103:M114) -> 1802.9261 | N102: =SUM(N103:N114) -> 1802.9261 | O102: =SUM(O103:O114) -> 0 | ... Y102: =SUM(Y103:Y114) -> 0
B103: F1 | C103: Example | D103: Text | E103: PIP | F103: 1 | G103: 1600 | H103: 1 | I103: =(F103*G103)+H103 -> 1601 | J103: =I103*$D$20 -> 116.0725 | K103: =SUM(I103:J103)*5% -> 85.853625 | L103: =SUM(I103:K103) -> 1802.9261 | M103: =SUM(N103, O103,P103,Q103,R103,S103,T103,U103,V103,W103,X103,Y103) -> 1802.9261 | N103: =L103 -> 1802.9261
B104: F2 | I104: =(F104*G104)+H104 -> 0 | J104: =I104*$D$20 -> 0 | K104: =SUM(I104:J104)*5% -> 0 | L104: =SUM(I104:K104) -> 0 | M104: =SUM(N104, O104,P104,Q104,R104,S104,T104,U104,V104,W104,X104,Y104) -> 0
B105: F3 | I105: =(F105*G105)+H105 -> 0 | J105: =I105*$D$20 -> 0 | K105: =SUM(I105:J105)*5% -> 0 | L105: =SUM(I105:K105) -> 0 | M105: =SUM(N105, O105,P105,Q105,R105,S105,T105,U105,V105,W105,X105,Y105) -> 0
B106: F4 | I106: =(F106*G106)+H106 -> 0 | J106: =I106*$D$20 -> 0 | K106: =SUM(I106:J106)*5% -> 0 | L106: =SUM(I106:K106) -> 0 | M106: =SUM(N106, O106,P106,Q106,R106,S106,T106,U106,V106,W106,X106,Y106) -> 0
B107: F5 | I107: =(F107*G107)+H107 -> 0 | J107: =I107*$D$20 -> 0 | K107: =SUM(I107:J107)*5% -> 0 | L107: =SUM(I107:K107) -> 0 | M107: =SUM(N107, O107,P107,Q107,R107,S107,T107,U107,V107,W107,X107,Y107) -> 0
B108: F6 | I108: =(F108*G108)+H108 -> 0 | J108: =I108*$D$20 -> 0 | K108: =SUM(I108:J108)*5% -> 0 | L108: =SUM(I108:K108) -> 0 | M108: =SUM(N108, O108,P108,Q108,R108,S108,T108,U108,V108,W108,X108,Y108) -> 0
B109: F7 | I109: =(F109*G109)+H109 -> 0 | J109: =I109*$D$20 -> 0 | K109: =SUM(I109:J109)*5% -> 0 | L109: =SUM(I109:K109) -> 0 | M109: =SUM(N109, O109,P109,Q109,R109,S109,T109,U109,V109,W109,X109,Y109) -> 0
B110: F8 | I110: =(F110*G110)+H110 -> 0 | J110: =I110*$D$20 -> 0 | K110: =SUM(I110:J110)*5% -> 0 | L110: =SUM(I110:K110) -> 0 | M110: =SUM(N110, O110,P110,Q110,R110,S110,T110,U110,V110,W110,X110,Y110) -> 0
B111: F9 | I111: =(F111*G111)+H111 -> 0 | J111: =I111*$D$20 -> 0 | K111: =SUM(I111:J111)*5% -> 0 | L111: =SUM(I111:K111) -> 0 | M111: =SUM(N111, O111,P111,Q111,R111,S111,T111,U111,V111,W111,X111,Y111) -> 0
B112: F10 | I112: =(F112*G112)+H112 -> 0 | J112: =I112*$D$20 -> 0 | K112: =SUM(I112:J112)*5% -> 0 | L112: =SUM(I112:K112) -> 0 | M112: =SUM(N112, O112,P112,Q112,R112,S112,T112,U112,V112,W112,X112,Y112) -> 0
B113: F11 | I113: =(F113*G113)+H113 -> 0 | J113: =I113*$D$20 -> 0 | K113: =SUM(I113:J113)*5% -> 0 | L113: =SUM(I113:K113) -> 0 | M113: =SUM(N113, O113,P113,Q113,R113,S113,T113,U113,V113,W113,X113,Y113) -> 0
B114: F12 | I114: =(F114*G114)+H114 -> 0 | J114: =I114*$D$20 -> 0 | K114: =SUM(I114:J114)*5% -> 0 | L114: =SUM(I114:K114) -> 0 | M114: =SUM(N114, O114,P114,Q114,R114,S114,T114,U114,V114,W114,X114,Y114) -> 0
B115: QA Total | H115: =SUMIF($E$38:$E$49:$E$51:$E$62:$E$64:$E$75:$E$77:$E$88:$E$90:$E$101:$E$103:$E$114,"QA",H$38:H$49:H$51:H$62:H$64:H$75:H$77:H$88:H$90:H$101:H$103:H$114) -> 2 | I115: =SUMIF($E$38:$E$49:$E$51:$E$62:$E$64:$E$75:$E$77:$E$88:$E$90:$E$101:$E$103:$E$114,"QA",I$38:I$49:I$51:I$62:I$64:I$75:I$77:I$88:I$90:I$101:I$103:I$114) -> 13752 | J115: =SUMIF($E$38:$E$49:$E$51:$E$62:$E$64:$E$75:$E$77:$E$88:$E$90:$E$101:$E$103:$E$114,"QA",J$38:J$49:J$51:J$62:J$64:J$75:J$77:J$88:J$90:J$101:J$103:J$114) -> 997.02 | K115: =SUMIF($E$38:$E$49:$E$51:$E$62:$E$64:$E$75:$E$77:$E$88:$E$90:$E$101:$E$103:$E$114,"QA",K$38:K$49:K$51:K$62:K$64:K$75:K$77:K$88:K$90:K$101:K$103:K$114) -> 737.451 | L115: =SUMIF($E$38:$E$49:$E$51:$E$62:$E$64:$E$75:$E$77:$E$88:$E$90:$E$101:$E$103:$E$114,"QA",L$38:L$49:L$51:L$62:L$64:L$75:L$77:L$88:L$90:L$101:L$103:L$114) -> 15486.471 | M115: =SUMIF($E$38:$E$49:$E$51:$E$62:$E$64:$E$75:$E$77:$E$88:$E$90:$E$101:$E$103:$E$114,"QA",M$38:M$49:M$51:M$62:M$64:M$75:M$77:M$88:M$90:M$101:M$103:M$114) -> 15486.471 | N115: =SUMIF($E$38:$E$49:$E$51:$E$62:$E$64:$E$75:$E$77:$E$88:$E$90:$E$101:$E$103:$E$114,"QA",N$38:N$49:N$51:N$62:N$64:N$75:N$77:N$88:N$90:N$101:N$103:N$114) -> 15486.471 | O115: =SUMIF($E$38:$E$49:$E$51:$E$62:$E$64:$E$75:$E$77:$E$88:$E$90:$E$101:$E$103:$E$114,"QA",O$38:O$49:O$51:O$62:O$64:O$75:O$77:O$88:O$90:O$101:O$103:O$114) -> 0 | ... Y115: =SUMIF($E$38:$E$49:$E$51:$E$62:$E$64:$E$75:$E$77:$E$88:$E$90:$E$101:$E$103:$E$114,"QA",Y$38:Y$49:Y$51:Y$62:Y$64:Y$75:Y$77:Y$88:Y$90:Y$101:Y$103:Y$114) -> 0
B116: PIP Total | H116: =SUMIF($E$38:$E$49:$E$51:$E$62:$E$64:$E$75:$E$77:$E$88:$E$90:$E$101:$E$103:$E$114,"PIP",H$38:H$49:H$51:H$62:H$64:H$75:H$77:H$88:H$90:H$101:H$103:H$114) -> 2 | I116: =SUMIF($E$38:$E$49:$E$51:$E$62:$E$64:$E$75:$E$77:$E$88:$E$90:$E$101:$E$103:$E$114,"PIP",I$38:I$49:I$51:I$62:I$64:I$75:I$77:I$88:I$90:I$101:I$103:I$114) -> 8002 | J116: =SUMIF($E$38:$E$49:$E$51:$E$62:$E$64:$E$75:$E$77:$E$88:$E$90:$E$101:$E$103:$E$114,"PIP",J$38:J$49:J$51:J$62:J$64:J$75:J$77:J$88:J$90:J$101:J$103:J$114) -> 580.145 | K116: =SUMIF($E$38:$E$49:$E$51:$E$62:$E$64:$E$75:$E$77:$E$88:$E$90:$E$101:$E$103:$E$114,"PIP",K$38:K$49:K$51:K$62:K$64:K$75:K$77:K$88:K$90:K$101:K$103:K$114) -> 429.10725 | L116: =SUMIF($E$38:$E$49:$E$51:$E$62:$E$64:$E$75:$E$77:$E$88:$E$90:$E$101:$E$103:$E$114,"PIP",L$38:L$49:L$51:L$62:L$64:L$75:L$77:L$88:L$90:L$101:L$103:L$114) -> 9011.2523 | M116: =SUMIF($E$38:$E$49:$E$51:$E$62:$E$64:$E$75:$E$77:$E$88:$E$90:$E$101:$E$103:$E$114,"PIP",M$38:M$49:M$51:M$62:M$64:M$75:M$77:M$88:M$90:M$101:M$103:M$114) -> 9011.2523 | N116: =SUMIF($E$38:$E$49:$E$51:$E$62:$E$64:$E$75:$E$77:$E$88:$E$90:$E$101:$E$103:$E$114,"PIP",N$38:N$49:N$51:N$62:N$64:N$75:N$77:N$88:N$90:N$101:N$103:N$114) -> 9011.2523 | O116: =SUMIF($E$38:$E$49:$E$51:$E$62:$E$64:$E$75:$E$77:$E$88:$E$90:$E$101:$E$103:$E$114,"PIP",O$38:O$49:O$51:O$62:O$64:O$75:O$77:O$88:O$90:O$101:O$103:O$114) -> 0 | ... Y116: =SUMIF($E$38:$E$49:$E$51:$E$62:$E$64:$E$75:$E$77:$E$88:$E$90:$E$101:$E$103:$E$114,"PIP",Y$38:Y$49:Y$51:Y$62:Y$64:Y$75:Y$77:Y$88:Y$90:Y$101:Y$103:Y$114) -> 0
B117: PCA Total | H117: =SUMIF($E$38:$E$49:$E$51:$E$62:$E$64:$E$75:$E$77:$E$88:$E$90:$E$101:$E$103:$E$114,"PCA",H$38:H$49:H$51:H$62:H$64:H$75:H$77:H$88:H$90:H$101:H$103:H$114) -> 1 | I117: =SUMIF($E$38:$E$49:$E$51:$E$62:$E$64:$E$75:$E$77:$E$88:$E$90:$E$101:$E$103:$E$114,"PCA",I$38:I$49:I$51:I$62:I$64:I$75:I$77:I$88:I$90:I$101:I$103:I$114) -> 601 | J117: =SUMIF($E$38:$E$49:$E$51:$E$62:$E$64:$E$75:$E$77:$E$88:$E$90:$E$101:$E$103:$E$114,"PCA",J$38:J$49:J$51:J$62:J$64:J$75:J$77:J$88:J$90:J$101:J$103:J$114) -> 43.5725 | K117: =SUMIF($E$38:$E$49:$E$51:$E$62:$E$64:$E$75:$E$77:$E$88:$E$90:$E$101:$E$103:$E$114,"PCA",K$38:K$49:K$51:K$62:K$64:K$75:K$77:K$88:K$90:K$101:K$103:K$114) -> 32.228625 | L117: =SUMIF($E$38:$E$49:$E$51:$E$62:$E$64:$E$75:$E$77:$E$88:$E$90:$E$101:$E$103:$E$114,"PCA",L$38:L$49:L$51:L$62:L$64:L$75:L$77:L$88:L$90:L$101:L$103:L$114) -> 676.80112 | M117: =SUMIF($E$38:$E$49:$E$51:$E$62:$E$64:$E$75:$E$77:$E$88:$E$90:$E$101:$E$103:$E$114,"PCA",M$38:M$49:M$51:M$62:M$64:M$75:M$77:M$88:M$90:M$101:M$103:M$114) -> 676.80112 | N117: =SUMIF($E$38:$E$49:$E$51:$E$62:$E$64:$E$75:$E$77:$E$88:$E$90:$E$101:$E$103:$E$114,"PCA",N$38:N$49:N$51:N$62:N$64:N$75:N$77:N$88:N$90:N$101:N$103:N$114) -> 676.80112 | O117: =SUMIF($E$38:$E$49:$E$51:$E$62:$E$64:$E$75:$E$77:$E$88:$E$90:$E$101:$E$103:$E$114,"PCA",O$38:O$49:O$51:O$62:O$64:O$75:O$77:O$88:O$90:O$101:O$103:O$114) -> 0 | ... Y117: =SUMIF($E$38:$E$49:$E$51:$E$62:$E$64:$E$75:$E$77:$E$88:$E$90:$E$101:$E$103:$E$114,"PCA",Y$38:Y$49:Y$51:Y$62:Y$64:Y$75:Y$77:Y$88:Y$90:Y$101:Y$103:Y$114) -> 0
B118: Other Total | H118: =SUMIF($E$38:$E$49:$E$51:$E$62:$E$64:$E$75:$E$77:$E$88:$E$90:$E$101:$E$103:$E$114,"Other",H$38:H$49:H$51:H$62:H$64:H$75:H$77:H$88:H$90:H$101:H$103:H$114) -> 1 | I118: =SUMIF($E$38:$E$49:$E$51:$E$62:$E$64:$E$75:$E$77:$E$88:$E$90:$E$101:$E$103:$E$114,"Other",I$38:I$49:I$51:I$62:I$64:I$75:I$77:I$88:I$90:I$101:I$103:I$114) -> 6001 | J118: =SUMIF($E$38:$E$49:$E$51:$E$62:$E$64:$E$75:$E$77:$E$88:$E$90:$E$101:$E$103:$E$114,"Other",J$38:J$49:J$51:J$62:J$64:J$75:J$77:J$88:J$90:J$101:J$103:J$114) -> 435.0725 | K118: =SUMIF($E$38:$E$49:$E$51:$E$62:$E$64:$E$75:$E$77:$E$88:$E$90:$E$101:$E$103:$E$114,"Other",K$38:K$49:K$51:K$62:K$64:K$75:K$77:K$88:K$90:K$101:K$103:K$114) -> 321.80363 | L118: =SUMIF($E$38:$E$49:$E$51:$E$62:$E$64:$E$75:$E$77:$E$88:$E$90:$E$101:$E$103:$E$114,"Other",L$38:L$49:L$51:L$62:L$64:L$75:L$77:L$88:L$90:L$101:L$103:L$114) -> 6757.8761 | M118: =SUMIF($E$38:$E$49:$E$51:$E$62:$E$64:$E$75:$E$77:$E$88:$E$90:$E$101:$E$103:$E$114,"Other",M$38:M$49:M$51:M$62:M$64:M$75:M$77:M$88:M$90:M$101:M$103:M$114) -> 6757.8761 | N118: =SUMIF($E$38:$E$49:$E$51:$E$62:$E$64:$E$75:$E$77:$E$88:$E$90:$E$101:$E$103:$E$114,"Other",N$38:N$49:N$51:N$62:N$64:N$75:N$77:N$88:N$90:N$101:N$103:N$114) -> 6757.8761 | O118: =SUMIF($E$38:$E$49:$E$51:$E$62:$E$64:$E$75:$E$77:$E$88:$E$90:$E$101:$E$103:$E$114,"Other",O$38:O$49:O$51:O$62:O$64:O$75:O$77:O$88:O$90:O$101:O$103:O$114) -> 0 | ... Y118: =SUMIF($E$38:$E$49:$E$51:$E$62:$E$64:$E$75:$E$77:$E$88:$E$90:$E$101:$E$103:$E$114,"Other",Y$38:Y$49:Y$51:Y$62:Y$64:Y$75:Y$77:Y$88:Y$90:Y$101:Y$103:Y$114) -> 0
...

Sheet 2025 Capex Plan
B2: Instructions
B3: 1. Fill out Property Name, Key Count, State Tax % , and General Manager in the Property Information Box 2. Input budget Total Revenues in row 28 columns I to T 3. Input current FF&E reserve balance in cell F32 4. Fill out all applicable data by hotel departments found in the Hotel Capital Plan section. Only fill in columns C to H and total amounts will calculate in columns I through M. Remember to select from Category dropdown options. 3. Spread the estimated capex amount by month in columns N though Y. 4. Capex plans should be reviewed with Regional VPs and Engineering. Once the plan has been approved, the RVP should initial in the RVP Approval box in the Property Information section. IMPORTANT: Do not add or delete rows or columns from the model.
B17: Property Information
B18: Property Name: | D18: Hotel
B19: Key Count: | D19: 100
B20: State Tax %: | D20: 0.0725
B21: General Manager:
B22: RVP Approval:
B23: Budget Year | D23: 2025
B25: FF&E Reserve Projection
F27: =D23 -> 2025 | I27: January | J27: February | K27: March | L27: April | M27: May | N27: June | O27: July | P27: August | Q27: September | R27: October | S27: November | T27: December
B28: Hotel Revenues | F28: =SUM(I28:T28) -> 1200000 | I28: 100000 | J28: 100000 | K28: 100000 | L28: 100000 | M28: 100000 | N28: 100000 | O28: 100000 | P28: 100000 | Q28: 100000 | R28: 100000 | S28: 100000 | T28: 100000
B29: FF&E Reserve % | F29: 0.04 | I29: =$F$29 -> 0.04 | J29: =$F$29 -> 0.04 | K29: =$F$29 -> 0.04 | L29: =$F$29 -> 0.04 | M29: =$F$29 -> 0.04 | N29: =$F$29 -> 0.04 | O29: =$F$29 -> 0.04 | P29: =$F$29 -> 0.04 | ... T29: =$F$29 -> 0.04
B30: Estimated FF&E Reserve | F30: =F28*F29 -> 48000 | I30: =I28*I29 -> 4000 | J30: =J28*J29 -> 4000 | K30: =K28*K29 -> 4000 | L30: =L28*L29 -> 4000 | M30: =M28*M29 -> 4000 | N30: =N28*N29 -> 4000 | O30: =O28*O29 -> 4000 | P30: =P28*P29 -> 4000 | ... T30: =T28*T29 -> 4000
B31: Total Estimated Capital Expenditures | F31: =SUM(I31:T31) -> 35125.641 | I31: =N121 -> 35125.641 | J31: =O121 -> 0 | K31: =P121 -> 0 | L31: =Q121 -> 0 | M31: =R121 -> 0 | N31: =S121 -> 0 | O31: =T121 -> 0 | P31: =U121 -> 0 | ... T31: =Y121 -> 0
B32: % of Revenue | F32: =F31/F28 -> 0.029271367 | I32: =I31/I28 -> 0.35125641 | J32: =J31/J28 -> 0 | K32: =K31/K28 -> 0 | L32: =L31/L28 -> 0 | M32: =M31/M28 -> 0 | N32: =N31/N28 -> 0 | O32: =O31/O28 -> 0 | P32: =P31/P28 -> 0 | ... T32: =T31/T28 -> 0
B34: =D23&" "& D18 & " " & "Capital Plan" -> 2025 Hotel Capital Plan
B36: Item Description | D36: Comments | E36: Category | F36: Quantity | G36: Unit Price | H36: Freight Cost | I36: Sub Total | J36: Tax | K36: Purchase Fee | L36: Estimate Amount | M36: Budget Amount | N36: January | O36: February | P36: March | Q36: April | R36: May | S36: June | T36: July | U36: August | V36: September | W36: October | X36: November | Y36: December
B37: (A) Guestrooms - Bathroom, Kitchen | H37: =SUM(H38:H49) -> 1 | I37: =SUM(I38:I49) -> 12151 | J37: =SUM(J38:J49) -> 880.9475 | K37: =SUM(K38:K49) -> 651.59738 | L37: =SUM(L38:L49) -> 13683.545 | M37: =SUM(M38:M49) -> 13683.545 | N37: =SUM(N38:N49) -> 13683.545 | O37: =SUM(O38:O49) -> 0 | ... Y37: =SUM(Y38:Y49) -> 0
B38: A1 | C38: Example | D38: Text | E38: QA | F38: 18 | G38: 675 | H38: 1 | I38: =(F38*G38)+H38 -> 12151 | J38: =I38*$D$20 -> 880.9475 | K38: =SUM(I38:J38)*5% -> 651.59738 | L38: =SUM(I38:K38) -> 13683.545 | M38: =SUM(N38, O38,P38,Q38,R38,S38,T38,U38,V38,W38,X38,Y38) -> 13683.545 | N38: =L38 -> 13683.545
B39: A2 | I39: =(F39*G39)+H39 -> 0 | J39: =I39*$D$20 -> 0 | K39: =SUM(I39:J39)*5% -> 0 | L39: =SUM(I39:K39) -> 0 | M39: =SUM(N39, O39,P39,Q39,R39,S39,T39,U39,V39,W39,X39,Y39) -> 0
B40: A3 | I40: =(F40*G40)+H40 -> 0 | J40: =I40*$D$20 -> 0 | K40: =SUM(I40:J40)*5% -> 0 | L40: =SUM(I40:K40) -> 0 | M40: =SUM(N40, O40,P40,Q40,R40,S40,T40,U40,V40,W40,X40,Y40) -> 0
B41: A4 | C41: PM Fee | D41: Third Party PM | I41: =(F41*G41)+H41 -> 0 | J41: =I41*$D$20 -> 0 | K41: =SUM(I41:J41)*5% -> 0 | L41: =SUM(I41:K41) -> 0 | M41: =SUM(N41, O41,P41,Q41,R41,S41,T41,U41,V41,W41,X41,Y41) -> 0
B42: A5 | I42: =(F42*G42)+H42 -> 0 | J42: =I42*$D$20 -> 0 | K42: =SUM(I42:J42)*5% -> 0 | L42: =SUM(I42:K42) -> 0 | M42: =SUM(N42, O42,P42,Q42,R42,S42,T42,U42,V42,W42,X42,Y42) -> 0
B43: A6 | I43: =(F43*G43)+H43 -> 0 | J43: =I43*$D$20 -> 0 | K43: =SUM(I43:J43)*5% -> 0 | L43: =SUM(I43:K43) -> 0 | M43: =SUM(N43, O43,P43,Q43,R43,S43,T43,U43,V43,W43,X43,Y43) -> 0
B44: A7 | I44: =(F44*G44)+H44 -> 0 | J44: =I44*$D$20 -> 0 | K44: =SUM(I44:J44)*5% -> 0 | L44: =SUM(I44:K44) -> 0 | M44: =SUM(N44, O44,P44,Q44,R44,S44,T44,U44,V44,W44,X44,Y44) -> 0
B45: A8 | I45: =(F45*G45)+H45 -> 0 | J45: =I45*$D$20 -> 0 | K45: =SUM(I45:J45)*5% -> 0 | L45: =SUM(I45:K45) -> 0 | M45: =SUM(N45, O45,P45,Q45,R45,S45,T45,U45,V45,W45,X45,Y45) -> 0
B46: A9 | I46: =(F46*G46)+H46 -> 0 | J46: =I46*$D$20 -> 0 | K46: =SUM(I46:J46)*5% -> 0 | L46: =SUM(I46:K46) -> 0 | M46: =SUM(N46, O46,P46,Q46,R46,S46,T46,U46,V46,W46,X46,Y46) -> 0
B47: A10 | I47: =(F47*G47)+H47 -> 0 | J47: =I47*$D$20 -> 0 | K47: =SUM(I47:J47)*5% -> 0 | L47: =SUM(I47:K47) -> 0 | M47: =SUM(N47, O47,P47,Q47,R47,S47,T47,U47,V47,W47,X47,Y47) -> 0
B48: A11 | I48: =(F48*G48)+H48 -> 0 | J48: =I48*$D$20 -> 0 | K48: =SUM(I48:J48)*5% -> 0 | L48: =SUM(I48:K48) -> 0 | M48: =SUM(N48, O48,P48,Q48,R48,S48,T48,U48,V48,W48,X48,Y48) -> 0
B49: A12 | I49: =(F49*G49)+H49 -> 0 | J49: =I49*$D$20 -> 0 | K49: =SUM(I49:J49)*5% -> 0 | L49: =SUM(I49:K49) -> 0 | M49: =SUM(N49, O49,P49,Q49,R49,S49,T49,U49,V49,W49,X49,Y49) -> 0
B50: (B) Function Space - Meeting Banquet Space | H50: =SUM(H51:H62) -> 1 | I50: =SUM(I51:I62) -> 6401 | J50: =SUM(J51:J62) -> 464.0725 | K50: =SUM(K51:K62) -> 343.25363 | L50: =SUM(L51:L62) -> 7208.3261 | M50: =SUM(M51:M62) -> 7208.3261 | N50: =SUM(N51:N62) -> 7208.3261 | O50: =SUM(O51:O62) -> 0 | ... Y50: =SUM(Y51:Y62) -> 0
B51: B1 | C51: Example | D51: Text | E51: PIP | F51: 4 | G51: 1600 | H51: 1 | I51: =(F51*G51)+H51 -> 6401 | J51: =I51*$D$20 -> 464.0725 | K51: =SUM(I51:J51)*5% -> 343.25363 | L51: =SUM(I51:K51) -> 7208.3261 | M51: =SUM(N51, O51,P51,Q51,R51,S51,T51,U51,V51,W51,X51,Y51) -> 7208.3261 | N51: =L51 -> 7208.3261
B52: B2 | I52: =(F52*G52)+H52 -> 0 | J52: =I52*$D$20 -> 0 | K52: =SUM(I52:J52)*5% -> 0 | L52: =SUM(I52:K52) -> 0 | M52: =SUM(N52, O52,P52,Q52,R52,S52,T52,U52,V52,W52,X52,Y52) -> 0
B53: B3 | I53: =(F53*G53)+H53 -> 0 | J53: =I53*$D$20 -> 0 | K53: =SUM(I53:J53)*5% -> 0 | L53: =SUM(I53:K53) -> 0 | M53: =SUM(N53, O53,P53,Q53,R53,S53,T53,U53,V53,W53,X53,Y53) -> 0
B54: B4 | I54: =(F54*G54)+H54 -> 0 | J54: =I54*$D$20 -> 0 | K54: =SUM(I54:J54)*5% -> 0 | L54: =SUM(I54:K54) -> 0 | M54: =SUM(N54, O54,P54,Q54,R54,S54,T54,U54,V54,W54,X54,Y54) -> 0
B55: B5 | I55: =(F55*G55)+H55 -> 0 | J55: =I55*$D$20 -> 0 | K55: =SUM(I55:J55)*5% -> 0 | L55: =SUM(I55:K55) -> 0 | M55: =SUM(N55, O55,P55,Q55,R55,S55,T55,U55,V55,W55,X55,Y55) -> 0
B56: B6 | I56: =(F56*G56)+H56 -> 0 | J56: =I56*$D$20 -> 0 | K56: =SUM(I56:J56)*5% -> 0 | L56: =SUM(I56:K56) -> 0 | M56: =SUM(N56, O56,P56,Q56,R56,S56,T56,U56,V56,W56,X56,Y56) -> 0
B57: B7 | I57: =(F57*G57)+H57 -> 0 | J57: =I57*$D$20 -> 0 | K57: =SUM(I57:J57)*5% -> 0 | L57: =SUM(I57:K57) -> 0 | M57: =SUM(N57, O57,P57,Q57,R57,S57,T57,U57,V57,W57,X57,Y57) -> 0
B58: B8 | I58: =(F58*G58)+H58 -> 0 | J58: =I58*$D$20 -> 0 | K58: =SUM(I58:J58)*5% -> 0 | L58: =SUM(I58:K58) -> 0 | M58: =SUM(N58, O58,P58,Q58,R58,S58,T58,U58,V58,W58,X58,Y58) -> 0
B59: B9 | I59: =(F59*G59)+H59 -> 0 | J59: =I59*$D$20 -> 0 | K59: =SUM(I59:J59)*5% -> 0 | L59: =SUM(I59:K59) -> 0 | M59: =SUM(N59, O59,P59,Q59,R59,S59,T59,U59,V59,W59,X59,Y59) -> 0
B60: B10 | I60: =(F60*G60)+H60 -> 0 | J60: =I60*$D$20 -> 0 | K60: =SUM(I60:J60)*5% -> 0 | L60: =SUM(I60:K60) -> 0 | M60: =SUM(N60, O60,P60,Q60,R60,S60,T60,U60,V60,W60,X60,Y60) -> 0
B61: B11 | I61: =(F61*G61)+H61 -> 0 | J61: =I61*$D$20 -> 0 | K61: =SUM(I61:J61)*5% -> 0 | L61: =SUM(I61:K61) -> 0 | M61: =SUM(N61, O61,P61,Q61,R61,S61,T61,U61,V61,W61,X61,Y61) -> 0
B62: B12 | I62: =(F62*G62)+H62 -> 0 | J62: =I62*$D$20 -> 0 | K62: =SUM(I62:J62)*5% -> 0 | L62: =SUM(I62:K62) -> 0 | M62: =SUM(N62, O62,P62,Q62,R62,S62,T62,U62,V62,W62,X62,Y62) -> 0
B63: (C) Public Areas - Lobby, Pool, Fitness, Corridors | H63: =SUM(H64:H75) -> 1 | I63: =SUM(I64:I75) -> 601 | J63: =SUM(J64:J75) -> 43.5725 | K63: =SUM(K64:K75) -> 32.228625 | L63: =SUM(L64:L75) -> 676.80112 | M63: =SUM(M64:M75) -> 676.80112 | N63: =SUM(N64:N75) -> 676.80112 | O63: =SUM(O64:O75) -> 0 | ... Y63: =SUM(Y64:Y75) -> 0
B64: C1 | C64: Example | D64: Text | E64: PCA | F64: 2 | G64: 300 | H64: 1 | I64: =(F64*G64)+H64 -> 601 | J64: =I64*$D$20 -> 43.5725 | K64: =SUM(I64:J64)*5% -> 32.228625 | L64: =SUM(I64:K64) -> 676.80112 | M64: =SUM(N64, O64,P64,Q64,R64,S64,T64,U64,V64,W64,X64,Y64) -> 676.80112 | N64: =L64 -> 676.80112
B65: C2 | I65: =(F65*G65)+H65 -> 0 | J65: =I65*$D$20 -> 0 | K65: =SUM(I65:J65)*5% -> 0 | L65: =SUM(I65:K65) -> 0 | M65: =SUM(N65, O65,P65,Q65,R65,S65,T65,U65,V65,W65,X65,Y65) -> 0
B66: C3 | I66: =(F66*G66)+H66 -> 0 | J66: =I66*$D$20 -> 0 | K66: =SUM(I66:J66)*5% -> 0 | L66: =SUM(I66:K66) -> 0 | M66: =SUM(N66, O66,P66,Q66,R66,S66,T66,U66,V66,W66,X66,Y66) -> 0
B67: C4 | I67: =(F67*G67)+H67 -> 0 | J67: =I67*$D$20 -> 0 | K67: =SUM(I67:J67)*5% -> 0 | L67: =SUM(I67:K67) -> 0 | M67: =SUM(N67, O67,P67,Q67,R67,S67,T67,U67,V67,W67,X67,Y67) -> 0
B68: C5 | I68: =(F68*G68)+H68 -> 0 | J68: =I68*$D$20 -> 0 | K68: =SUM(I68:J68)*5% -> 0 | L68: =SUM(I68:K68) -> 0 | M68: =SUM(N68, O68,P68,Q68,R68,S68,T68,U68,V68,W68,X68,Y68) -> 0
B69: C6 | I69: =(F69*G69)+H69 -> 0 | J69: =I69*$D$20 -> 0 | K69: =SUM(I69:J69)*5% -> 0 | L69: =SUM(I69:K69) -> 0 | M69: =SUM(N69, O69,P69,Q69,R69,S69,T69,U69,V69,W69,X69,Y69) -> 0
B70: C7 | I70: =(F70*G70)+H70 -> 0 | J70: =I70*$D$20 -> 0 | K70: =SUM(I70:J70)*5% -> 0 | L70: =SUM(I70:K70) -> 0 | M70: =SUM(N70, O70,P70,Q70,R70,S70,T70,U70,V70,W70,X70,Y70) -> 0
B71: C8 | I71: =(F71*G71)+H71 -> 0 | J71: =I71*$D$20 -> 0 | K71: =SUM(I71:J71)*5% -> 0 | L71: =SUM(I71:K71) -> 0 | M71: =SUM(N71, O71,P71,Q71,R71,S71,T71,U71,V71,W71,X71,Y71) -> 0
B72: C9 | I72: =(F72*G72)+H72 -> 0 | J72: =I72*$D$20 -> 0 | K72: =SUM(I72:J72)*5% -> 0 | L72: =SUM(I72:K72) -> 0 | M72: =SUM(N72, O72,P72,Q72,R72,S72,T72,U72,V72,W72,X72,Y72) -> 0
B73: C10 | I73: =(F73*G73)+H73 -> 0 | J73: =I73*$D$20 -> 0 | K73: =SUM(I73:J73)*5% -> 0 | L73: =SUM(I73:K73) -> 0 | M73: =SUM(N73, O73,P73,Q73,R73,S73,T73,U73,V73,W73,X73,Y73) -> 0
B74: C11 | I74: =(F74*G74)+H74 -> 0 | J74: =I74*$D$20 -> 0 | K74: =SUM(I74:J74)*5% -> 0 | L74: =SUM(I74:K74) -> 0 | M74: =SUM(N74, O74,P74,Q74,R74,S74,T74,U74,V74,W74,X74,Y74) -> 0
B75: C12 | I75: =(F75*G75)+H75 -> 0 | J75: =I75*$D$20 -> 0 | K75: =SUM(I75:J75)*5% -> 0 | L75: =SUM(I75:K75) -> 0 | M75: =SUM(N75, O75,P75,Q75,R75,S75,T75,U75,V75,W75,X75,Y75) -> 0
B76: (D) Technology - Computer Systems | H76: =SUM(H77:H88) -> 1 | I76: =SUM(I77:I88) -> 6001 | J76: =SUM(J77:J88) -> 435.0725 | K76: =SUM(K77:K88) -> 321.80363 | L76: =SUM(L77:L88) -> 6757.8761 | M76: =SUM(M77:M88) -> 6757.8761 | N76: =SUM(N77:N88) -> 6757.8761 | O76: =SUM(O77:O88) -> 0 | ... Y76: =SUM(Y77:Y88) -> 0
B77: D1 | C77: Example | D77: Text | E77: Other | F77: 2 | G77: 3000 | H77: 1 | I77: =(F77*G77)+H77 -> 6001 | J77: =I77*$D$20 -> 435.0725 | K77: =SUM(I77:J77)*5% -> 321.80363 | L77: =SUM(I77:K77) -> 6757.8761 | M77: =SUM(N77, O77,P77,Q77,R77,S77,T77,U77,V77,W77,X77,Y77) -> 6757.8761 | N77: =L77 -> 6757.8761
B78: D2 | I78: =(F78*G78)+H78 -> 0 | J78: =I78*$D$20 -> 0 | K78: =SUM(I78:J78)*5% -> 0 | L78: =SUM(I78:K78) -> 0 | M78: =SUM(N78, O78,P78,Q78,R78,S78,T78,U78,V78,W78,X78,Y78) -> 0
B79: D3 | I79: =(F79*G79)+H79 -> 0 | J79: =I79*$D$20 -> 0 | K79: =SUM(I79:J79)*5% -> 0 | L79: =SUM(I79:K79) -> 0 | M79: =SUM(N79, O79,P79,Q79,R79,S79,T79,U79,V79,W79,X79,Y79) -> 0
B80: D4 | I80: =(F80*G80)+H80 -> 0 | J80: =I80*$D$20 -> 0 | K80: =SUM(I80:J80)*5% -> 0 | L80: =SUM(I80:K80) -> 0 | M80: =SUM(N80, O80,P80,Q80,R80,S80,T80,U80,V80,W80,X80,Y80) -> 0
B81: D5 | I81: =(F81*G81)+H81 -> 0 | J81: =I81*$D$20 -> 0 | K81: =SUM(I81:J81)*5% -> 0 | L81: =SUM(I81:K81) -> 0 | M81: =SUM(N81, O81,P81,Q81,R81,S81,T81,U81,V81,W81,X81,Y81) -> 0
B82: D6 | I82: =(F82*G82)+H82 -> 0 | J82: =I82*$D$20 -> 0 | K82: =SUM(I82:J82)*5% -> 0 | L82: =SUM(I82:K82) -> 0 | M82: =SUM(N82, O82,P82,Q82,R82,S82,T82,U82,V82,W82,X82,Y82) -> 0
B83: D7 | I83: =(F83*G83)+H83 -> 0 | J83: =I83*$D$20 -> 0 | K83: =SUM(I83:J83)*5% -> 0 | L83: =SUM(I83:K83) -> 0 | M83: =SUM(N83, O83,P83,Q83,R83,S83,T83,U83,V83,W83,X83,Y83) -> 0
B84: D8 | I84: =(F84*G84)+H84 -> 0 | J84: =I84*$D$20 -> 0 | K84: =SUM(I84:J84)*5% -> 0 | L84: =SUM(I84:K84) -> 0 | M84: =SUM(N84, O84,P84,Q84,R84,S84,T84,U84,V84,W84,X84,Y84) -> 0
B85: D9 | I85: =(F85*G85)+H85 -> 0 | J85: =I85*$D$20 -> 0 | K85: =SUM(I85:J85)*5% -> 0 | L85: =SUM(I85:K85) -> 0 | M85: =SUM(N85, O85,P85,Q85,R85,S85,T85,U85,V85,W85,X85,Y85) -> 0
B86: D10 | I86: =(F86*G86)+H86 -> 0 | J86: =I86*$D$20 -> 0 | K86: =SUM(I86:J86)*5% -> 0 | L86: =SUM(I86:K86) -> 0 | M86: =SUM(N86, O86,P86,Q86,R86,S86,T86,U86,V86,W86,X86,Y86) -> 0
B87: D11 | I87: =(F87*G87)+H87 -> 0 | J87: =I87*$D$20 -> 0 | K87: =SUM(I87:J87)*5% -> 0 | L87: =SUM(I87:K87) -> 0 | M87: =SUM(N87, O87,P87,Q87,R87,S87,T87,U87,V87,W87,X87,Y87) -> 0
B88: D12 | I88: =(F88*G88)+H88 -> 0 | J88: =I88*$D$20 -> 0 | K88: =SUM(I88:J88)*5% -> 0 | L88: =SUM(I88:K88) -> 0 | M88: =SUM(N88, O88,P88,Q88,R88,S88,T88,U88,V88,W88,X88,Y88) -> 0
B89: (E) Back of House - Administrative, Laundry | H89: =SUM(H90:H101) -> 1 | I89: =SUM(I90:I101) -> 1601 | J89: =SUM(J90:J101) -> 116.0725 | K89: =SUM(K90:K101) -> 85.853625 | L89: =SUM(L90:L101) -> 1802.9261 | M89: =SUM(M90:M101) -> 1802.9261 | N89: =SUM(N90:N101) -> 1802.9261 | O89: =SUM(O90:O101) -> 0 | ... Y89: =SUM(Y90:Y101) -> 0
B90: E1 | C90: Example | D90: Text | E90: QA | F90: 1 | G90: 1600 | H90: 1 | I90: =(F90*G90)+H90 -> 1601 | J90: =I90*$D$20 -> 116.0725 | K90: =SUM(I90:J90)*5% -> 85.853625 | L90: =SUM(I90:K90) -> 1802.9261 | M90: =SUM(N90, O90,P90,Q90,R90,S90,T90,U90,V90,W90,X90,Y90) -> 1802.9261 | N90: =L90 -> 1802.9261
B91: E2 | I91: =(F91*G91)+H91 -> 0 | J91: =I91*$D$20 -> 0 | K91: =SUM(I91:J91)*5% -> 0 | L91: =SUM(I91:K91) -> 0 | M91: =SUM(N91, O91,P91,Q91,R91,S91,T91,U91,V91,W91,X91,Y91) -> 0
B92: E3 | I92: =(F92*G92)+H92 -> 0 | J92: =I92*$D$20 -> 0 | K92: =SUM(I92:J92)*5% -> 0 | L92: =SUM(I92:K92) -> 0 | M92: =SUM(N92, O92,P92,Q92,R92,S92,T92,U92,V92,W92,X92,Y92) -> 0
B93: E4 | I93: =(F93*G93)+H93 -> 0 | J93: =I93*$D$20 -> 0 | K93: =SUM(I93:J93)*5% -> 0 | L93: =SUM(I93:K93) -> 0 | M93: =SUM(N93, O93,P93,Q93,R93,S93,T93,U93,V93,W93,X93,Y93) -> 0
B94: E5 | I94: =(F94*G94)+H94 -> 0 | J94: =I94*$D$20 -> 0 | K94: =SUM(I94:J94)*5% -> 0 | L94: =SUM(I94:K94) -> 0 | M94: =SUM(N94, O94,P94,Q94,R94,S94,T94,U94,V94,W94,X94,Y94) -> 0
B95: E6 | I95: =(F95*G95)+H95 -> 0 | J95: =I95*$D$20 -> 0 | K95: =SUM(I95:J95)*5% -> 0 | L95: =SUM(I95:K95) -> 0 | M95: =SUM(N95, O95,P95,Q95,R95,S95,T95,U95,V95,W95,X95,Y95) -> 0
B96: E7 | I96: =(F96*G96)+H96 -> 0 | J96: =I96*$D$20 -> 0 | K96: =SUM(I96:J96)*5% -> 0 | L96: =SUM(I96:K96) -> 0 | M96: =SUM(N96, O96,P96,Q96,R96,S96,T96,U96,V96,W96,X96,Y96) -> 0
B97: E8 | I97: =(F97*G97)+H97 -> 0 | J97: =I97*$D$20 -> 0 | K97: =SUM(I97:J97)*5% -> 0 | L97: =SUM(I97:K97) -> 0 | M97: =SUM(N97, O97,P97,Q97,R97,S97,T97,U97,V97,W97,X97,Y97) -> 0
B98: E9 | I98: =(F98*G98)+H98 -> 0 | J98: =I98*$D$20 -> 0 | K98: =SUM(I98:J98)*5% -> 0 | L98: =SUM(I98:K98) -> 0 | M98: =SUM(N98, O98,P98,Q98,R98,S98,T98,U98,V98,W98,X98,Y98) -> 0
B99: E10 | I99: =(F99*G99)+H99 -> 0 | J99: =I99*$D$20 -> 0 | K99: =SUM(I99:J99)*5% -> 0 | L99: =SUM(I99:K99) -> 0 | M99: =SUM(N99, O99,P99,Q99,R99,S99,T99,U99,V99,W99,X99,Y99) -> 0
B100: E11 | I100: =(F100*G100)+H100 -> 0 | J100: =I100*$D$20 -> 0 | K100: =SUM(I100:J100)*5% -> 0 | L100: =SUM(I100:K100) -> 0 | M100: =SUM(N100, O100,P100,Q100,R100,S100,T100,U100,V100,W100,X100,Y100) -> 0
B101: E12 | I101: =(F101*G101)+H101 -> 0 | J101: =I101*$D$20 -> 0 | K101: =SUM(I101:J101)*5% -> 0 | L101: =SUM(I101:K101) -> 0 | M101: =SUM(N101, O101,P101,Q101,R101,S101,T101,U101,V101,W101,X101,Y101) -> 0
B102: (F) Building - Site, Exterior, Mechanical | H102: =SUM(H103:H114) -> 1 | I102: =SUM(I103:I114) -> 1601 | J102: =SUM(J103:J114) -> 116.0725 | K102: =SUM(K103:K114) -> 85.853625 | L102: =SUM(L103:L114) -> 1802.9261 | M102: =SUM(M103:M114) -> 1802.9261 | N102: =SUM(N103:N114) -> 1802.9261 | O102: =SUM(O103:O114) -> 0 | ... Y102: =SUM(Y103:Y114) -> 0
B103: F1 | C103: Example | D103: Text | E103: PIP | F103: 1 | G103: 1600 | H103: 1 | I103: =(F103*G103)+H103 -> 1601 | J103: =I103*$D$20 -> 116.0725 | K103: =SUM(I103:J103)*5% -> 85.853625 | L103: =SUM(I103:K103) -> 1802.9261 | M103: =SUM(N103, O103,P103,Q103,R103,S103,T103,U103,V103,W103,X103,Y103) -> 1802.9261 | N103: =L103 -> 1802.9261
B104: F2 | I104: =(F104*G104)+H104 -> 0 | J104: =I104*$D$20 -> 0 | K104: =SUM(I104:J104)*5% -> 0 | L104: =SUM(I104:K104) -> 0 | M104: =SUM(N104, O104,P104,Q104,R104,S104,T104,U104,V104,W104,X104,Y104) -> 0
B105: F3 | I105: =(F105*G105)+H105 -> 0 | J105: =I105*$D$20 -> 0 | K105: =SUM(I105:J105)*5% -> 0 | L105: =SUM(I105:K105) -> 0 | M105: =SUM(N105, O105,P105,Q105,R105,S105,T105,U105,V105,W105,X105,Y105) -> 0
B106: F4 | I106: =(F106*G106)+H106 -> 0 | J106: =I106*$D$20 -> 0 | K106: =SUM(I106:J106)*5% -> 0 | L106: =SUM(I106:K106) -> 0 | M106: =SUM(N106, O106,P106,Q106,R106,S106,T106,U106,V106,W106,X106,Y106) -> 0
B107: F5 | I107: =(F107*G107)+H107 -> 0 | J107: =I107*$D$20 -> 0 | K107: =SUM(I107:J107)*5% -> 0 | L107: =SUM(I107:K107) -> 0 | M107: =SUM(N107, O107,P107,Q107,R107,S107,T107,U107,V107,W107,X107,Y107) -> 0
B108: F6 | I108: =(F108*G108)+H108 -> 0 | J108: =I108*$D$20 -> 0 | K108: =SUM(I108:J108)*5% -> 0 | L108: =SUM(I108:K108) -> 0 | M108: =SUM(N108, O108,P108,Q108,R108,S108,T108,U108,V108,W108,X108,Y108) -> 0
B109: F7 | I109: =(F109*G109)+H109 -> 0 | J109: =I109*$D$20 -> 0 | K109: =SUM(I109:J109)*5% -> 0 | L109: =SUM(I109:K109) -> 0 | M109: =SUM(N109, O109,P109,Q109,R109,S109,T109,U109,V109,W109,X109,Y109) -> 0
B110: F8 | I110: =(F110*G110)+H110 -> 0 | J110: =I110*$D$20 -> 0 | K110: =SUM(I110:J110)*5% -> 0 | L110: =SUM(I110:K110) -> 0 | M110: =SUM(N110, O110,P110,Q110,R110,S110,T110,U110,V110,W110,X110,Y110) -> 0
B111: F9 | I111: =(F111*G111)+H111 -> 0 | J111: =I111*$D$20 -> 0 | K111: =SUM(I111:J111)*5% -> 0 | L111: =SUM(I111:K111) -> 0 | M111: =SUM(N111, O111,P111,Q111,R111,S111,T111,U111,V111,W111,X111,Y111) -> 0
B112: F10 | I112: =(F112*G112)+H112 -> 0 | J112: =I112*$D$20 -> 0 | K112: =SUM(I112:J112)*5% -> 0 | L112: =SUM(I112:K112) -> 0 | M112: =SUM(N112, O112,P112,Q112,R112,S112,T112,U112,V112,W112,X112,Y112) -> 0
B113: F11 | I113: =(F113*G113)+H113 -> 0 | J113: =I113*$D$20 -> 0 | K113: =SUM(I113:J113)*5% -> 0 | L113: =SUM(I113:K113) -> 0 | M113: =SUM(N113, O113,P113,Q113,R113,S113,T113,U113,V113,W113,X113,Y113) -> 0
B114: F12 | I114: =(F114*G114)+H114 -> 0 | J114: =I114*$D$20 -> 0 | K114: =SUM(I114:J114)*5% -> 0 | L114: =SUM(I114:K114) -> 0 | M114: =SUM(N114, O114,P114,Q114,R114,S114,T114,U114,V114,W114,X114,Y114) -> 0
B115: QA Total | H115: =SUMIF($E$38:$E$49:$E$51:$E$62:$E$64:$E$75:$E$77:$E$88:$E$90:$E$101:$E$103:$E$114,"QA",H$38:H$49:H$51:H$62:H$64:H$75:H$77:H$88:H$90:H$101:H$103:H$114) -> 2 | I115: =SUMIF($E$38:$E$49:$E$51:$E$62:$E$64:$E$75:$E$77:$E$88:$E$90:$E$101:$E$103:$E$114,"QA",I$38:I$49:I$51:I$62:I$64:I$75:I$77:I$88:I$90:I$101:I$103:I$114) -> 13752 | J115: =SUMIF($E$38:$E$49:$E$51:$E$62:$E$64:$E$75:$E$77:$E$88:$E$90:$E$101:$E$103:$E$114,"QA",J$38:J$49:J$51:J$62:J$64:J$75:J$77:J$88:J$90:J$101:J$103:J$114) -> 997.02 | K115: =SUMIF($E$38:$E$49:$E$51:$E$62:$E$64:$E$75:$E$77:$E$88:$E$90:$E$101:$E$103:$E$114,"QA",K$38:K$49:K$51:K$62:K$64:K$75:K$77:K$88:K$90:K$101:K$103:K$114) -> 737.451 | L115: =SUMIF($E$38:$E$49:$E$51:$E$62:$E$64:$E$75:$E$77:$E$88:$E$90:$E$101:$E$103:$E$114,"QA",L$38:L$49:L$51:L$62:L$64:L$75:L$77:L$88:L$90:L$101:L$103:L$114) -> 15486.471 | M115: =SUMIF($E$38:$E$49:$E$51:$E$62:$E$64:$E$75:$E$77:$E$88:$E$90:$E$101:$E$103:$E$114,"QA",M$38:M$49:M$51:M$62:M$64:M$75:M$77:M$88:M$90:M$101:M$103:M$114) -> 15486.471 | N115: =SUMIF($E$38:$E$49:$E$51:$E$62:$E$64:$E$75:$E$77:$E$88:$E$90:$E$101:$E$103:$E$114,"QA",N$38:N$49:N$51:N$62:N$64:N$75:N$77:N$88:N$90:N$101:N$103:N$114) -> 15486.471 | O115: =SUMIF($E$38:$E$49:$E$51:$E$62:$E$64:$E$75:$E$77:$E$88:$E$90:$E$101:$E$103:$E$114,"QA",O$38:O$49:O$51:O$62:O$64:O$75:O$77:O$88:O$90:O$101:O$103:O$114) -> 0 | ... Y115: =SUMIF($E$38:$E$49:$E$51:$E$62:$E$64:$E$75:$E$77:$E$88:$E$90:$E$101:$E$103:$E$114,"QA",Y$38:Y$49:Y$51:Y$62:Y$64:Y$75:Y$77:Y$88:Y$90:Y$101:Y$103:Y$114) -> 0
B116: PIP Total | H116: =SUMIF($E$38:$E$49:$E$51:$E$62:$E$64:$E$75:$E$77:$E$88:$E$90:$E$101:$E$103:$E$114,"PIP",H$38:H$49:H$51:H$62:H$64:H$75:H$77:H$88:H$90:H$101:H$103:H$114) -> 2 | I116: =SUMIF($E$38:$E$49:$E$51:$E$62:$E$64:$E$75:$E$77:$E$88:$E$90:$E$101:$E$103:$E$114,"PIP",I$38:I$49:I$51:I$62:I$64:I$75:I$77:I$88:I$90:I$101:I$103:I$114) -> 8002 | J116: =SUMIF($E$38:$E$49:$E$51:$E$62:$E$64:$E$75:$E$77:$E$88:$E$90:$E$101:$E$103:$E$114,"PIP",J$38:J$49:J$51:J$62:J$64:J$75:J$77:J$88:J$90:J$101:J$103:J$114) -> 580.145 | K116: =SUMIF($E$38:$E$49:$E$51:$E$62:$E$64:$E$75:$E$77:$E$88:$E$90:$E$101:$E$103:$E$114,"PIP",K$38:K$49:K$51:K$62:K$64:K$75:K$77:K$88:K$90:K$101:K$103:K$114) -> 429.10725 | L116: =SUMIF($E$38:$E$49:$E$51:$E$62:$E$64:$E$75:$E$77:$E$88:$E$90:$E$101:$E$103:$E$114,"PIP",L$38:L$49:L$51:L$62:L$64:L$75:L$77:L$88:L$90:L$101:L$103:L$114) -> 9011.2523 | M116: =SUMIF($E$38:$E$49:$E$51:$E$62:$E$64:$E$75:$E$77:$E$88:$E$90:$E$101:$E$103:$E$114,"PIP",M$38:M$49:M$51:M$62:M$64:M$75:M$77:M$88:M$90:M$101:M$103:M$114) -> 9011.2523 | N116: =SUMIF($E$38:$E$49:$E$51:$E$62:$E$64:$E$75:$E$77:$E$88:$E$90:$E$101:$E$103:$E$114,"PIP",N$38:N$49:N$51:N$62:N$64:N$75:N$77:N$88:N$90:N$101:N$103:N$114) -> 9011.2523 | O116: =SUMIF($E$38:$E$49:$E$51:$E$62:$E$64:$E$75:$E$77:$E$88:$E$90:$E$101:$E$103:$E$114,"PIP",O$38:O$49:O$51:O$62:O$64:O$75:O$77:O$88:O$90:O$101:O$103:O$114) -> 0 | ... Y116: =SUMIF($E$38:$E$49:$E$51:$E$62:$E$64:$E$75:$E$77:$E$88:$E$90:$E$101:$E$103:$E$114,"PIP",Y$38:Y$49:Y$51:Y$62:Y$64:Y$75:Y$77:Y$88:Y$90:Y$101:Y$103:Y$114) -> 0
B117: PCA Total | H117: =SUMIF($E$38:$E$49:$E$51:$E$62:$E$64:$E$75:$E$77:$E$88:$E$90:$E$101:$E$103:$E$114,"PCA",H$38:H$49:H$51:H$62:H$64:H$75:H$77:H$88:H$90:H$101:H$103:H$114) -> 1 | I117: =SUMIF($E$38:$E$49:$E$51:$E$62:$E$64:$E$75:$E$77:$E$88:$E$90:$E$101:$E$103:$E$114,"PCA",I$38:I$49:I$51:I$62:I$64:I$75:I$77:I$88:I$90:I$101:I$103:I$114) -> 601 | J117: =SUMIF($E$38:$E$49:$E$51:$E$62:$E$64:$E$75:$E$77:$E$88:$E$90:$E$101:$E$103:$E$114,"PCA",J$38:J$49:J$51:J$62:J$64:J$75:J$77:J$88:J$90:J$101:J$103:J$114) -> 43.5725 | K117: =SUMIF($E$38:$E$49:$E$51:$E$62:$E$64:$E$75:$E$77:$E$88:$E$90:$E$101:$E$103:$E$114,"PCA",K$38:K$49:K$51:K$62:K$64:K$75:K$77:K$88:K$90:K$101:K$103:K$114) -> 32.228625 | L117: =SUMIF($E$38:$E$49:$E$51:$E$62:$E$64:$E$75:$E$77:$E$88:$E$90:$E$101:$E$103:$E$114,"PCA",L$38:L$49:L$51:L$62:L$64:L$75:L$77:L$88:L$90:L$101:L$103:L$114) -> 676.80112 | M117: =SUMIF($E$38:$E$49:$E$51:$E$62:$E$64:$E$75:$E$77:$E$88:$E$90:$E$101:$E$103:$E$114,"PCA",M$38:M$49:M$51:M$62:M$64:M$75:M$77:M$88:M$90:M$101:M$103:M$114) -> 676.80112 | N117: =SUMIF($E$38:$E$49:$E$51:$E$62:$E$64:$E$75:$E$77:$E$88:$E$90:$E$101:$E$103:$E$114,"PCA",N$38:N$49:N$51:N$62:N$64:N$75:N$77:N$88:N$90:N$101:N$103:N$114) -> 676.80112 | O117: =SUMIF($E$38:$E$49:$E$51:$E$62:$E$64:$E$75:$E$77:$E$88:$E$90:$E$101:$E$103:$E$114,"PCA",O$38:O$49:O$51:O$62:O$64:O$75:O$77:O$88:O$90:O$101:O$103:O$114) -> 0 | ... Y117: =SUMIF($E$38:$E$49:$E$51:$E$62:$E$64:$E$75:$E$77:$E$88:$E$90:$E$101:$E$103:$E$114,"PCA",Y$38:Y$49:Y$51:Y$62:Y$64:Y$75:Y$77:Y$88:Y$90:Y$101:Y$103:Y$114) -> 0
B118: Other Total | H118: =SUMIF($E$38:$E$49:$E$51:$E$62:$E$64:$E$75:$E$77:$E$88:$E$90:$E$101:$E$103:$E$114,"Other",H$38:H$49:H$51:H$62:H$64:H$75:H$77:H$88:H$90:H$101:H$103:H$114) -> 1 | I118: =SUMIF($E$38:$E$49:$E$51:$E$62:$E$64:$E$75:$E$77:$E$88:$E$90:$E$101:$E$103:$E$114,"Other",I$38:I$49:I$51:I$62:I$64:I$75:I$77:I$88:I$90:I$101:I$103:I$114) -> 6001 | J118: =SUMIF($E$38:$E$49:$E$51:$E$62:$E$64:$E$75:$E$77:$E$88:$E$90:$E$101:$E$103:$E$114,"Other",J$38:J$49:J$51:J$62:J$64:J$75:J$77:J$88:J$90:J$101:J$103:J$114) -> 435.0725 | K118: =SUMIF($E$38:$E$49:$E$51:$E$62:$E$64:$E$75:$E$77:$E$88:$E$90:$E$101:$E$103:$E$114,"Other",K$38:K$49:K$51:K$62:K$64:K$75:K$77:K$88:K$90:K$101:K$103:K$114) -> 321.80363 | L118: =SUMIF($E$38:$E$49:$E$51:$E$62:$E$64:$E$75:$E$77:$E$88:$E$90:$E$101:$E$103:$E$114,"Other",L$38:L$49:L$51:L$62:L$64:L$75:L$77:L$88:L$90:L$101:L$103:L$114) -> 6757.8761 | M118: =SUMIF($E$38:$E$49:$E$51:$E$62:$E$64:$E$75:$E$77:$E$88:$E$90:$E$101:$E$103:$E$114,"Other",M$38:M$49:M$51:M$62:M$64:M$75:M$77:M$88:M$90:M$101:M$103:M$114) -> 6757.8761 | N118: =SUMIF($E$38:$E$49:$E$51:$E$62:$E$64:$E$75:$E$77:$E$88:$E$90:$E$101:$E$103:$E$114,"Other",N$38:N$49:N$51:N$62:N$64:N$75:N$77:N$88:N$90:N$101:N$103:N$114) -> 6757.8761 | O118: =SUMIF($E$38:$E$49:$E$51:$E$62:$E$64:$E$75:$E$77:$E$88:$E$90:$E$101:$E$103:$E$114,"Other",O$38:O$49:O$51:O$62:O$64:O$75:O$77:O$88:O$90:O$101:O$103:O$114) -> 0 | ... Y118: =SUMIF($E$38:$E$49:$E$51:$E$62:$E$64:$E$75:$E$77:$E$88:$E$90:$E$101:$E$103:$E$114,"Other",Y$38:Y$49:Y$51:Y$62:Y$64:Y$75:Y$77:Y$88:Y$90:Y$101:Y$103:Y$114) -> 0
...

Sheet 2026 Capex Plan
B2: Instructions
B3: 1. Fill out Property Name, Key Count, State Tax % , and General Manager in the Property Information Box 2. Input budget Total Revenues in row 28 columns I to T 3. Input current FF&E reserve balance in cell F32 4. Fill out all applicable data by hotel departments found in the Hotel Capital Plan section. Only fill in columns C to H and total amounts will calculate in columns I through M. Remember to select from Category dropdown options. 3. Spread the estimated capex amount by month in columns N though Y. 4. Capex plans should be reviewed with Regional VPs and Engineering. Once the plan has been approved, the RVP should initial in the RVP Approval box in the Property Information section. IMPORTANT: Do not add or delete rows or columns from the model.
B17: Property Information
B18: Property Name: | D18: Hotel
B19: Key Count: | D19: 100
B20: State Tax %: | D20: 0.0725
B21: General Manager:
B22: RVP Approval:
B23: Budget Year | D23: 2026
B25: FF&E Reserve Projection
F27: =D23 -> 2026 | I27: January | J27: February | K27: March | L27: April | M27: May | N27: June | O27: July | P27: August | Q27: September | R27: October | S27: November | T27: December
B28: Hotel Revenues | F28: =SUM(I28:T28) -> 1200000 | I28: 100000 | J28: 100000 | K28: 100000 | L28: 100000 | M28: 100000 | N28: 100000 | O28: 100000 | P28: 100000 | Q28: 100000 | R28: 100000 | S28: 100000 | T28: 100000
B29: FF&E Reserve % | F29: 0.04 | I29: =$F$29 -> 0.04 | J29: =$F$29 -> 0.04 | K29: =$F$29 -> 0.04 | L29: =$F$29 -> 0.04 | M29: =$F$29 -> 0.04 | N29: =$F$29 -> 0.04 | O29: =$F$29 -> 0.04 | P29: =$F$29 -> 0.04 | ... T29: =$F$29 -> 0.04
B30: Estimated FF&E Reserve | F30: =F28*F29 -> 48000 | I30: =I28*I29 -> 4000 | J30: =J28*J29 -> 4000 | K30: =K28*K29 -> 4000 | L30: =L28*L29 -> 4000 | M30: =M28*M29 -> 4000 | N30: =N28*N29 -> 4000 | O30: =O28*O29 -> 4000 | P30: =P28*P29 -> 4000 | ... T30: =T28*T29 -> 4000
B31: Total Estimated Capital Expenditures | F31: =SUM(I31:T31) -> 35125.641 | I31: =N121 -> 35125.641 | J31: =O121 -> 0 | K31: =P121 -> 0 | L31: =Q121 -> 0 | M31: =R121 -> 0 | N31: =S121 -> 0 | O31: =T121 -> 0 | P31: =U121 -> 0 | ... T31: =Y121 -> 0
B32: % of Revenue | F32: =F31/F28 -> 0.029271367 | I32: =I31/I28 -> 0.35125641 | J32: =J31/J28 -> 0 | K32: =K31/K28 -> 0 | L32: =L31/L28 -> 0 | M32: =M31/M28 -> 0 | N32: =N31/N28 -> 0 | O32: =O31/O28 -> 0 | P32: =P31/P28 -> 0 | ... T32: =T31/T28 -> 0
B34: =D23&" "& D18 & " " & "Capital Plan" -> 2026 Hotel Capital Plan
B36: Item Description | D36: Comments | E36: Category | F36: Quantity | G36: Unit Price | H36: Freight Cost | I36: Sub Total | J36: Tax | K36: Purchase Fee | L36: Estimate Amount | M36: Budget Amount | N36: January | O36: February | P36: March | Q36: April | R36: May | S36: June | T36: July | U36: August | V36: September | W36: October | X36: November | Y36: December
B37: (A) Guestrooms - Bathroom, Kitchen | H37: =SUM(H38:H49) -> 1 | I37: =SUM(I38:I49) -> 12151 | J37: =SUM(J38:J49) -> 880.9475 | K37: =SUM(K38:K49) -> 651.59738 | L37: =SUM(L38:L49) -> 13683.545 | M37: =SUM(M38:M49) -> 13683.545 | N37: =SUM(N38:N49) -> 13683.545 | O37: =SUM(O38:O49) -> 0 | ... Y37: =SUM(Y38:Y49) -> 0
B38: A1 | C38: Example | D38: Text | E38: QA | F38: 18 | G38: 675 | H38: 1 | I38: =(F38*G38)+H38 -> 12151 | J38: =I38*$D$20 -> 880.9475 | K38: =SUM(I38:J38)*5% -> 651.59738 | L38: =SUM(I38:K38) -> 13683.545 | M38: =SUM(N38, O38,P38,Q38,R38,S38,T38,U38,V38,W38,X38,Y38) -> 13683.545 | N38: =L38 -> 13683.545
B39: A2 | I39: =(F39*G39)+H39 -> 0 | J39: =I39*$D$20 -> 0 | K39: =SUM(I39:J39)*5% -> 0 | L39: =SUM(I39:K39) -> 0 | M39: =SUM(N39, O39,P39,Q39,R39,S39,T39,U39,V39,W39,X39,Y39) -> 0
B40: A3 | I40: =(F40*G40)+H40 -> 0 | J40: =I40*$D$20 -> 0 | K40: =SUM(I40:J40)*5% -> 0 | L40: =SUM(I40:K40) -> 0 | M40: =SUM(N40, O40,P40,Q40,R40,S40,T40,U40,V40,W40,X40,Y40) -> 0
B41: A4 | I41: =(F41*G41)+H41 -> 0 | J41: =I41*$D$20 -> 0 | K41: =SUM(I41:J41)*5% -> 0 | L41: =SUM(I41:K41) -> 0 | M41: =SUM(N41, O41,P41,Q41,R41,S41,T41,U41,V41,W41,X41,Y41) -> 0
B42: A5 | I42: =(F42*G42)+H42 -> 0 | J42: =I42*$D$20 -> 0 | K42: =SUM(I42:J42)*5% -> 0 | L42: =SUM(I42:K42) -> 0 | M42: =SUM(N42, O42,P42,Q42,R42,S42,T42,U42,V42,W42,X42,Y42) -> 0
B43: A6 | I43: =(F43*G43)+H43 -> 0 | J43: =I43*$D$20 -> 0 | K43: =SUM(I43:J43)*5% -> 0 | L43: =SUM(I43:K43) -> 0 | M43: =SUM(N43, O43,P43,Q43,R43,S43,T43,U43,V43,W43,X43,Y43) -> 0
B44: A7 | I44: =(F44*G44)+H44 -> 0 | J44: =I44*$D$20 -> 0 | K44: =SUM(I44:J44)*5% -> 0 | L44: =SUM(I44:K44) -> 0 | M44: =SUM(N44, O44,P44,Q44,R44,S44,T44,U44,V44,W44,X44,Y44) -> 0
B45: A8 | I45: =(F45*G45)+H45 -> 0 | J45: =I45*$D$20 -> 0 | K45: =SUM(I45:J45)*5% -> 0 | L45: =SUM(I45:K45) -> 0 | M45: =SUM(N45, O45,P45,Q45,R45,S45,T45,U45,V45,W45,X45,Y45) -> 0
B46: A9 | I46: =(F46*G46)+H46 -> 0 | J46: =I46*$D$20 -> 0 | K46: =SUM(I46:J46)*5% -> 0 | L46: =SUM(I46:K46) -> 0 | M46: =SUM(N46, O46,P46,Q46,R46,S46,T46,U46,V46,W46,X46,Y46) -> 0
B47: A10 | I47: =(F47*G47)+H47 -> 0 | J47: =I47*$D$20 -> 0 | K47: =SUM(I47:J47)*5% -> 0 | L47: =SUM(I47:K47) -> 0 | M47: =SUM(N47, O47,P47,Q47,R47,S47,T47,U47,V47,W47,X47,Y47) -> 0
B48: A11 | I48: =(F48*G48)+H48 -> 0 | J48: =I48*$D$20 -> 0 | K48: =SUM(I48:J48)*5% -> 0 | L48: =SUM(I48:K48) -> 0 | M48: =SUM(N48, O48,P48,Q48,R48,S48,T48,U48,V48,W48,X48,Y48) -> 0
B49: A12 | I49: =(F49*G49)+H49 -> 0 | J49: =I49*$D$20 -> 0 | K49: =SUM(I49:J49)*5% -> 0 | L49: =SUM(I49:K49) -> 0 | M49: =SUM(N49, O49,P49,Q49,R49,S49,T49,U49,V49,W49,X49,Y49) -> 0
B50: (B) Function Space - Meeting Banquet Space | H50: =SUM(H51:H62) -> 1 | I50: =SUM(I51:I62) -> 6401 | J50: =SUM(J51:J62) -> 464.0725 | K50: =SUM(K51:K62) -> 343.25363 | L50: =SUM(L51:L62) -> 7208.3261 | M50: =SUM(M51:M62) -> 7208.3261 | N50: =SUM(N51:N62) -> 7208.3261 | O50: =SUM(O51:O62) -> 0 | ... Y50: =SUM(Y51:Y62) -> 0
B51: B1 | C51: Example | D51: Text | E51: PIP | F51: 4 | G51: 1600 | H51: 1 | I51: =(F51*G51)+H51 -> 6401 | J51: =I51*$D$20 -> 464.0725 | K51: =SUM(I51:J51)*5% -> 343.25363 | L51: =SUM(I51:K51) -> 7208.3261 | M51: =SUM(N51, O51,P51,Q51,R51,S51,T51,U51,V51,W51,X51,Y51) -> 7208.3261 | N51: =L51 -> 7208.3261
B52: B2 | I52: =(F52*G52)+H52 -> 0 | J52: =I52*$D$20 -> 0 | K52: =SUM(I52:J52)*5% -> 0 | L52: =SUM(I52:K52) -> 0 | M52: =SUM(N52, O52,P52,Q52,R52,S52,T52,U52,V52,W52,X52,Y52) -> 0
B53: B3 | I53: =(F53*G53)+H53 -> 0 | J53: =I53*$D$20 -> 0 | K53: =SUM(I53:J53)*5% -> 0 | L53: =SUM(I53:K53) -> 0 | M53: =SUM(N53, O53,P53,Q53,R53,S53,T53,U53,V53,W53,X53,Y53) -> 0
B54: B4 | I54: =(F54*G54)+H54 -> 0 | J54: =I54*$D$20 -> 0 | K54: =SUM(I54:J54)*5% -> 0 | L54: =SUM(I54:K54) -> 0 | M54: =SUM(N54, O54,P54,Q54,R54,S54,T54,U54,V54,W54,X54,Y54) -> 0
B55: B5 | I55: =(F55*G55)+H55 -> 0 | J55: =I55*$D$20 -> 0 | K55: =SUM(I55:J55)*5% -> 0 | L55: =SUM(I55:K55) -> 0 | M55: =SUM(N55, O55,P55,Q55,R55,S55,T55,U55,V55,W55,X55,Y55) -> 0
B56: B6 | I56: =(F56*G56)+H56 -> 0 | J56: =I56*$D$20 -> 0 | K56: =SUM(I56:J56)*5% -> 0 | L56: =SUM(I56:K56) -> 0 | M56: =SUM(N56, O56,P56,Q56,R56,S56,T56,U56,V56,W56,X56,Y56) -> 0
B57: B7 | I57: =(F57*G57)+H57 -> 0 | J57: =I57*$D$20 -> 0 | K57: =SUM(I57:J57)*5% -> 0 | L57: =SUM(I57:K57) -> 0 | M57: =SUM(N57, O57,P57,Q57,R57,S57,T57,U57,V57,W57,X57,Y57) -> 0
B58: B8 | I58: =(F58*G58)+H58 -> 0 | J58: =I58*$D$20 -> 0 | K58: =SUM(I58:J58)*5% -> 0 | L58: =SUM(I58:K58) -> 0 | M58: =SUM(N58, O58,P58,Q58,R58,S58,T58,U58,V58,W58,X58,Y58) -> 0
B59: B9 | I59: =(F59*G59)+H59 -> 0 | J59: =I59*$D$20 -> 0 | K59: =SUM(I59:J59)*5% -> 0 | L59: =SUM(I59:K59) -> 0 | M59: =SUM(N59, O59,P59,Q59,R59,S59,T59,U59,V59,W59,X59,Y59) -> 0
B60: B10 | I60: =(F60*G60)+H60 -> 0 | J60: =I60*$D$20 -> 0 | K60: =SUM(I60:J60)*5% -> 0 | L60: =SUM(I60:K60) -> 0 | M60: =SUM(N60, O60,P60,Q60,R60,S60,T60,U60,V60,W60,X60,Y60) -> 0
B61: B11 | I61: =(F61*G61)+H61 -> 0 | J61: =I61*$D$20 -> 0 | K61: =SUM(I61:J61)*5% -> 0 | L61: =SUM(I61:K61) -> 0 | M61: =SUM(N61, O61,P61,Q61,R61,S61,T61,U61,V61,W61,X61,Y61) -> 0
B62: B12 | I62: =(F62*G62)+H62 -> 0 | J62: =I62*$D$20 -> 0 | K62: =SUM(I62:J62)*5% -> 0 | L62: =SUM(I62:K62) -> 0 | M62: =SUM(N62, O62,P62,Q62,R62,S62,T62,U62,V62,W62,X62,Y62) -> 0
B63: (C) Public Areas - Lobby, Pool, Fitness, Corridors | H63: =SUM(H64:H75) -> 1 | I63: =SUM(I64:I75) -> 601 | J63: =SUM(J64:J75) -> 43.5725 | K63: =SUM(K64:K75) -> 32.228625 | L63: =SUM(L64:L75) -> 676.80112 | M63: =SUM(M64:M75) -> 676.80112 | N63: =SUM(N64:N75) -> 676.80112 | O63: =SUM(O64:O75) -> 0 | ... Y63: =SUM(Y64:Y75) -> 0
B64: C1 | C64: Example | D64: Text | E64: PCA | F64: 2 | G64: 300 | H64: 1 | I64: =(F64*G64)+H64 -> 601 | J64: =I64*$D$20 -> 43.5725 | K64: =SUM(I64:J64)*5% -> 32.228625 | L64: =SUM(I64:K64) -> 676.80112 | M64: =SUM(N64, O64,P64,Q64,R64,S64,T64,U64,V64,W64,X64,Y64) -> 676.80112 | N64: =L64 -> 676.80112
B65: C2 | I65: =(F65*G65)+H65 -> 0 | J65: =I65*$D$20 -> 0 | K65: =SUM(I65:J65)*5% -> 0 | L65: =SUM(I65:K65) -> 0 | M65: =SUM(N65, O65,P65,Q65,R65,S65,T65,U65,V65,W65,X65,Y65) -> 0
B66: C3 | I66: =(F66*G66)+H66 -> 0 | J66: =I66*$D$20 -> 0 | K66: =SUM(I66:J66)*5% -> 0 | L66: =SUM(I66:K66) -> 0 | M66: =SUM(N66, O66,P66,Q66,R66,S66,T66,U66,V66,W66,X66,Y66) -> 0
B67: C4 | I67: =(F67*G67)+H67 -> 0 | J67: =I67*$D$20 -> 0 | K67: =SUM(I67:J67)*5% -> 0 | L67: =SUM(I67:K67) -> 0 | M67: =SUM(N67, O67,P67,Q67,R67,S67,T67,U67,V67,W67,X67,Y67) -> 0
B68: C5 | I68: =(F68*G68)+H68 -> 0 | J68: =I68*$D$20 -> 0 | K68: =SUM(I68:J68)*5% -> 0 | L68: =SUM(I68:K68) -> 0 | M68: =SUM(N68, O68,P68,Q68,R68,S68,T68,U68,V68,W68,X68,Y68) -> 0
B69: C6 | I69: =(F69*G69)+H69 -> 0 | J69: =I69*$D$20 -> 0 | K69: =SUM(I69:J69)*5% -> 0 | L69: =SUM(I69:K69) -> 0 | M69: =SUM(N69, O69,P69,Q69,R69,S69,T69,U69,V69,W69,X69,Y69) -> 0
B70: C7 | I70: =(F70*G70)+H70 -> 0 | J70: =I70*$D$20 -> 0 | K70: =SUM(I70:J70)*5% -> 0 | L70: =SUM(I70:K70) -> 0 | M70: =SUM(N70, O70,P70,Q70,R70,S70,T70,U70,V70,W70,X70,Y70) -> 0
B71: C8 | I71: =(F71*G71)+H71 -> 0 | J71: =I71*$D$20 -> 0 | K71: =SUM(I71:J71)*5% -> 0 | L71: =SUM(I71:K71) -> 0 | M71: =SUM(N71, O71,P71,Q71,R71,S71,T71,U71,V71,W71,X71,Y71) -> 0
B72: C9 | I72: =(F72*G72)+H72 -> 0 | J72: =I72*$D$20 -> 0 | K72: =SUM(I72:J72)*5% -> 0 | L72: =SUM(I72:K72) -> 0 | M72: =SUM(N72, O72,P72,Q72,R72,S72,T72,U72,V72,W72,X72,Y72) -> 0
B73: C10 | I73: =(F73*G73)+H73 -> 0 | J73: =I73*$D$20 -> 0 | K73: =SUM(I73:J73)*5% -> 0 | L73: =SUM(I73:K73) -> 0 | M73: =SUM(N73, O73,P73,Q73,R73,S73,T73,U73,V73,W73,X73,Y73) -> 0
B74: C11 | I74: =(F74*G74)+H74 -> 0 | J74: =I74*$D$20 -> 0 | K74: =SUM(I74:J74)*5% -> 0 | L74: =SUM(I74:K74) -> 0 | M74: =SUM(N74, O74,P74,Q74,R74,S74,T74,U74,V74,W74,X74,Y74) -> 0
B75: C12 | I75: =(F75*G75)+H75 -> 0 | J75: =I75*$D$20 -> 0 | K75: =SUM(I75:J75)*5% -> 0 | L75: =SUM(I75:K75) -> 0 | M75: =SUM(N75, O75,P75,Q75,R75,S75,T75,U75,V75,W75,X75,Y75) -> 0
B76: (D) Technology - Computer Systems | H76: =SUM(H77:H88) -> 1 | I76: =SUM(I77:I88) -> 6001 | J76: =SUM(J77:J88) -> 435.0725 | K76: =SUM(K77:K88) -> 321.80363 | L76: =SUM(L77:L88) -> 6757.8761 | M76: =SUM(M77:M88) -> 6757.8761 | N76: =SUM(N77:N88) -> 6757.8761 | O76: =SUM(O77:O88) -> 0 | ... Y76: =SUM(Y77:Y88) -> 0
B77: D1 | C77: Example | D77: Text | E77: Other | F77: 2 | G77: 3000 | H77: 1 | I77: =(F77*G77)+H77 -> 6001 | J77: =I77*$D$20 -> 435.0725 | K77: =SUM(I77:J77)*5% -> 321.80363 | L77: =SUM(I77:K77) -> 6757.8761 | M77: =SUM(N77, O77,P77,Q77,R77,S77,T77,U77,V77,W77,X77,Y77) -> 6757.8761 | N77: =L77 -> 6757.8761
B78: D2 | I78: =(F78*G78)+H78 -> 0 | J78: =I78*$D$20 -> 0 | K78: =SUM(I78:J78)*5% -> 0 | L78: =SUM(I78:K78) -> 0 | M78: =SUM(N78, O78,P78,Q78,R78,S78,T78,U78,V78,W78,X78,Y78) -> 0
B79: D3 | I79: =(F79*G79)+H79 -> 0 | J79: =I79*$D$20 -> 0 | K79: =SUM(I79:J79)*5% -> 0 | L79: =SUM(I79:K79) -> 0 | M79: =SUM(N79, O79,P79,Q79,R79,S79,T79,U79,V79,W79,X79,Y79) -> 0
B80: D4 | I80: =(F80*G80)+H80 -> 0 | J80: =I80*$D$20 -> 0 | K80: =SUM(I80:J80)*5% -> 0 | L80: =SUM(I80:K80) -> 0 | M80: =SUM(N80, O80,P80,Q80,R80,S80,T80,U80,V80,W80,X80,Y80) -> 0
B81: D5 | I81: =(F81*G81)+H81 -> 0 | J81: =I81*$D$20 -> 0 | K81: =SUM(I81:J81)*5% -> 0 | L81: =SUM(I81:K81) -> 0 | M81: =SUM(N81, O81,P81,Q81,R81,S81,T81,U81,V81,W81,X81,Y81) -> 0
B82: D6 | I82: =(F82*G82)+H82 -> 0 | J82: =I82*$D$20 -> 0 | K82: =SUM(I82:J82)*5% -> 0 | L82: =SUM(I82:K82) -> 0 | M82: =SUM(N82, O82,P82,Q82,R82,S82,T82,U82,V82,W82,X82,Y82) -> 0
B83: D7 | I83: =(F83*G83)+H83 -> 0 | J83: =I83*$D$20 -> 0 | K83: =SUM(I83:J83)*5% -> 0 | L83: =SUM(I83:K83) -> 0 | M83: =SUM(N83, O83,P83,Q83,R83,S83,T83,U83,V83,W83,X83,Y83) -> 0
B84: D8 | I84: =(F84*G84)+H84 -> 0 | J84: =I84*$D$20 -> 0 | K84: =SUM(I84:J84)*5% -> 0 | L84: =SUM(I84:K84) -> 0 | M84: =SUM(N84, O84,P84,Q84,R84,S84,T84,U84,V84,W84,X84,Y84) -> 0
B85: D9 | I85: =(F85*G85)+H85 -> 0 | J85: =I85*$D$20 -> 0 | K85: =SUM(I85:J85)*5% -> 0 | L85: =SUM(I85:K85) -> 0 | M85: =SUM(N85, O85,P85,Q85,R85,S85,T85,U85,V85,W85,X85,Y85) -> 0
B86: D10 | I86: =(F86*G86)+H86 -> 0 | J86: =I86*$D$20 -> 0 | K86: =SUM(I86:J86)*5% -> 0 | L86: =SUM(I86:K86) -> 0 | M86: =SUM(N86, O86,P86,Q86,R86,S86,T86,U86,V86,W86,X86,Y86) -> 0
B87: D11 | I87: =(F87*G87)+H87 -> 0 | J87: =I87*$D$20 -> 0 | K87: =SUM(I87:J87)*5% -> 0 | L87: =SUM(I87:K87) -> 0 | M87: =SUM(N87, O87,P87,Q87,R87,S87,T87,U87,V87,W87,X87,Y87) -> 0
B88: D12 | I88: =(F88*G88)+H88 -> 0 | J88: =I88*$D$20 -> 0 | K88: =SUM(I88:J88)*5% -> 0 | L88: =SUM(I88:K88) -> 0 | M88: =SUM(N88, O88,P88,Q88,R88,S88,T88,U88,V88,W88,X88,Y88) -> 0
B89: (E) Back of House - Administrative, Laundry | H89: =SUM(H90:H101) -> 1 | I89: =SUM(I90:I101) -> 1601 | J89: =SUM(J90:J101) -> 116.0725 | K89: =SUM(K90:K101) -> 85.853625 | L89: =SUM(L90:L101) -> 1802.9261 | M89: =SUM(M90:M101) -> 1802.9261 | N89: =SUM(N90:N101) -> 1802.9261 | O89: =SUM(O90:O101) -> 0 | ... Y89: =SUM(Y90:Y101) -> 0
B90: E1 | C90: Example | D90: Text | E90: QA | F90: 1 | G90: 1600 | H90: 1 | I90: =(F90*G90)+H90 -> 1601 | J90: =I90*$D$20 -> 116.0725 | K90: =SUM(I90:J90)*5% -> 85.853625 | L90: =SUM(I90:K90) -> 1802.9261 | M90: =SUM(N90, O90,P90,Q90,R90,S90,T90,U90,V90,W90,X90,Y90) -> 1802.9261 | N90: =L90 -> 1802.9261
B91: E2 | I91: =(F91*G91)+H91 -> 0 | J91: =I91*$D$20 -> 0 | K91: =SUM(I91:J91)*5% -> 0 | L91: =SUM(I91:K91) -> 0 | M91: =SUM(N91, O91,P91,Q91,R91,S91,T91,U91,V91,W91,X91,Y91) -> 0
B92: E3 | I92: =(F92*G92)+H92 -> 0 | J92: =I92*$D$20 -> 0 | K92: =SUM(I92:J92)*5% -> 0 | L92: =SUM(I92:K92) -> 0 | M92: =SUM(N92, O92,P92,Q92,R92,S92,T92,U92,V92,W92,X92,Y92) -> 0
B93: E4 | I93: =(F93*G93)+H93 -> 0 | J93: =I93*$D$20 -> 0 | K93: =SUM(I93:J93)*5% -> 0 | L93: =SUM(I93:K93) -> 0 | M93: =SUM(N93, O93,P93,Q93,R93,S93,T93,U93,V93,W93,X93,Y93) -> 0
B94: E5 | I94: =(F94*G94)+H94 -> 0 | J94: =I94*$D$20 -> 0 | K94: =SUM(I94:J94)*5% -> 0 | L94: =SUM(I94:K94) -> 0 | M94: =SUM(N94, O94,P94,Q94,R94,S94,T94,U94,V94,W94,X94,Y94) -> 0
B95: E6 | I95: =(F95*G95)+H95 -> 0 | J95: =I95*$D$20 -> 0 | K95: =SUM(I95:J95)*5% -> 0 | L95: =SUM(I95:K95) -> 0 | M95: =SUM(N95, O95,P95,Q95,R95,S95,T95,U95,V95,W95,X95,Y95) -> 0
B96: E7 | I96: =(F96*G96)+H96 -> 0 | J96: =I96*$D$20 -> 0 | K96: =SUM(I96:J96)*5% -> 0 | L96: =SUM(I96:K96) -> 0 | M96: =SUM(N96, O96,P96,Q96,R96,S96,T96,U96,V96,W96,X96,Y96) -> 0
B97: E8 | I97: =(F97*G97)+H97 -> 0 | J97: =I97*$D$20 -> 0 | K97: =SUM(I97:J97)*5% -> 0 | L97: =SUM(I97:K97) -> 0 | M97: =SUM(N97, O97,P97,Q97,R97,S97,T97,U97,V97,W97,X97,Y97) -> 0
B98: E9 | I98: =(F98*G98)+H98 -> 0 | J98: =I98*$D$20 -> 0 | K98: =SUM(I98:J98)*5% -> 0 | L98: =SUM(I98:K98) -> 0 | M98: =SUM(N98, O98,P98,Q98,R98,S98,T98,U98,V98,W98,X98,Y98) -> 0
B99: E10 | I99: =(F99*G99)+H99 -> 0 | J99: =I99*$D$20 -> 0 | K99: =SUM(I99:J99)*5% -> 0 | L99: =SUM(I99:K99) -> 0 | M99: =SUM(N99, O99,P99,Q99,R99,S99,T99,U99,V99,W99,X99,Y99) -> 0
B100: E11 | I100: =(F100*G100)+H100 -> 0 | J100: =I100*$D$20 -> 0 | K100: =SUM(I100:J100)*5% -> 0 | L100: =SUM(I100:K100) -> 0 | M100: =SUM(N100, O100,P100,Q100,R100,S100,T100,U100,V100,W100,X100,Y100) -> 0
B101: E12 | I101: =(F101*G101)+H101 -> 0 | J101: =I101*$D$20 -> 0 | K101: =SUM(I101:J101)*5% -> 0 | L101: =SUM(I101:K101) -> 0 | M101: =SUM(N101, O101,P101,Q101,R101,S101,T101,U101,V101,W101,X101,Y101) -> 0
B102: (F) Building - Site, Exterior, Mechanical | H102: =SUM(H103:H114) -> 1 | I102: =SUM(I103:I114) -> 1601 | J102: =SUM(J103:J114) -> 116.0725 | K102: =SUM(K103:K114) -> 85.853625 | L102: =SUM(L103:L114) -> 1802.9261 | M102: =SUM(M103:M114) -> 1802.9261 | N102: =SUM(N103:N114) -> 1802.9261 | O102: =SUM(O103:O114) -> 0 | ... Y102: =SUM(Y103:Y114) -> 0
B103: F1 | C103: Example | D103: Text | E103: PIP | F103: 1 | G103: 1600 | H103: 1 | I103: =(F103*G103)+H103 -> 1601 | J103: =I103*$D$20 -> 116.0725 | K103: =SUM(I103:J103)*5% -> 85.853625 | L103: =SUM(I103:K103) -> 1802.9261 | M103: =SUM(N103, O103,P103,Q103,R103,S103,T103,U103,V103,W103,X103,Y103) -> 1802.9261 | N103: =L103 -> 1802.9261
B104: F2 | I104: =(F104*G104)+H104 -> 0 | J104: =I104*$D$20 -> 0 | K104: =SUM(I104:J104)*5% -> 0 | L104: =SUM(I104:K104) -> 0 | M104: =SUM(N104, O104,P104,Q104,R104,S104,T104,U104,V104,W104,X104,Y104) -> 0
B105: F3 | I105: =(F105*G105)+H105 -> 0 | J105: =I105*$D$20 -> 0 | K105: =SUM(I105:J105)*5% -> 0 | L105: =SUM(I105:K105) -> 0 | M105: =SUM(N105, O105,P105,Q105,R105,S105,T105,U105,V105,W105,X105,Y105) -> 0
B106: F4 | I106: =(F106*G106)+H106 -> 0 | J106: =I106*$D$20 -> 0 | K106: =SUM(I106:J106)*5% -> 0 | L106: =SUM(I106:K106) -> 0 | M106: =SUM(N106, O106,P106,Q106,R106,S106,T106,U106,V106,W106,X106,Y106) -> 0
B107: F5 | I107: =(F107*G107)+H107 -> 0 | J107: =I107*$D$20 -> 0 | K107: =SUM(I107:J107)*5% -> 0 | L107: =SUM(I107:K107) -> 0 | M107: =SUM(N107, O107,P107,Q107,R107,S107,T107,U107,V107,W107,X107,Y107) -> 0
B108: F6 | I108: =(F108*G108)+H108 -> 0 | J108: =I108*$D$20 -> 0 | K108: =SUM(I108:J108)*5% -> 0 | L108: =SUM(I108:K108) -> 0 | M108: =SUM(N108, O108,P108,Q108,R108,S108,T108,U108,V108,W108,X108,Y108) -> 0
B109: F7 | I109: =(F109*G109)+H109 -> 0 | J109: =I109*$D$20 -> 0 | K109: =SUM(I109:J109)*5% -> 0 | L109: =SUM(I109:K109) -> 0 | M109: =SUM(N109, O109,P109,Q109,R109,S109,T109,U109,V109,W109,X109,Y109) -> 0
B110: F8 | I110: =(F110*G110)+H110 -> 0 | J110: =I110*$D$20 -> 0 | K110: =SUM(I110:J110)*5% -> 0 | L110: =SUM(I110:K110) -> 0 | M110: =SUM(N110, O110,P110,Q110,R110,S110,T110,U110,V110,W110,X110,Y110) -> 0
B111: F9 | I111: =(F111*G111)+H111 -> 0 | J111: =I111*$D$20 -> 0 | K111: =SUM(I111:J111)*5% -> 0 | L111: =SUM(I111:K111) -> 0 | M111: =SUM(N111, O111,P111,Q111,R111,S111,T111,U111,V111,W111,X111,Y111) -> 0
B112: F10 | I112: =(F112*G112)+H112 -> 0 | J112: =I112*$D$20 -> 0 | K112: =SUM(I112:J112)*5% -> 0 | L112: =SUM(I112:K112) -> 0 | M112: =SUM(N112, O112,P112,Q112,R112,S112,T112,U112,V112,W112,X112,Y112) -> 0
B113: F11 | I113: =(F113*G113)+H113 -> 0 | J113: =I113*$D$20 -> 0 | K113: =SUM(I113:J113)*5% -> 0 | L113: =SUM(I113:K113) -> 0 | M113: =SUM(N113, O113,P113,Q113,R113,S113,T113,U113,V113,W113,X113,Y113) -> 0
B114: F12 | I114: =(F114*G114)+H114 -> 0 | J114: =I114*$D$20 -> 0 | K114: =SUM(I114:J114)*5% -> 0 | L114: =SUM(I114:K114) -> 0 | M114: =SUM(N114, O114,P114,Q114,R114,S114,T114,U114,V114,W114,X114,Y114) -> 0
B115: QA Total | H115: =SUMIF($E$38:$E$49:$E$51:$E$62:$E$64:$E$75:$E$77:$E$88:$E$90:$E$101:$E$103:$E$114,"QA",H$38:H$49:H$51:H$62:H$64:H$75:H$77:H$88:H$90:H$101:H$103:H$114) -> 2 | I115: =SUMIF($E$38:$E$49:$E$51:$E$62:$E$64:$E$75:$E$77:$E$88:$E$90:$E$101:$E$103:$E$114,"QA",I$38:I$49:I$51:I$62:I$64:I$75:I$77:I$88:I$90:I$101:I$103:I$114) -> 13752 | J115: =SUMIF($E$38:$E$49:$E$51:$E$62:$E$64:$E$75:$E$77:$E$88:$E$90:$E$101:$E$103:$E$114,"QA",J$38:J$49:J$51:J$62:J$64:J$75:J$77:J$88:J$90:J$101:J$103:J$114) -> 997.02 | K115: =SUMIF($E$38:$E$49:$E$51:$E$62:$E$64:$E$75:$E$77:$E$88:$E$90:$E$101:$E$103:$E$114,"QA",K$38:K$49:K$51:K$62:K$64:K$75:K$77:K$88:K$90:K$101:K$103:K$114) -> 737.451 | L115: =SUMIF($E$38:$E$49:$E$51:$E$62:$E$64:$E$75:$E$77:$E$88:$E$90:$E$101:$E$103:$E$114,"QA",L$38:L$49:L$51:L$62:L$64:L$75:L$77:L$88:L$90:L$101:L$103:L$114) -> 15486.471 | M115: =SUMIF($E$38:$E$49:$E$51:$E$62:$E$64:$E$75:$E$77:$E$88:$E$90:$E$101:$E$103:$E$114,"QA",M$38:M$49:M$51:M$62:M$64:M$75:M$77:M$88:M$90:M$101:M$103:M$114) -> 15486.471 | N115: =SUMIF($E$38:$E$49:$E$51:$E$62:$E$64:$E$75:$E$77:$E$88:$E$90:$E$101:$E$103:$E$114,"QA",N$38:N$49:N$51:N$62:N$64:N$75:N$77:N$88:N$90:N$101:N$103:N$114) -> 15486.471 | O115: =SUMIF($E$38:$E$49:$E$51:$E$62:$E$64:$E$75:$E$77:$E$88:$E$90:$E$101:$E$103:$E$114,"QA",O$38:O$49:O$51:O$62:O$64:O$75:O$77:O$88:O$90:O$101:O$103:O$114) -> 0 | ... Y115: =SUMIF($E$38:$E$49:$E$51:$E$62:$E$64:$E$75:$E$77:$E$88:$E$90:$E$101:$E$103:$E$114,"QA",Y$38:Y$49:Y$51:Y$62:Y$64:Y$75:Y$77:Y$88:Y$90:Y$101:Y$103:Y$114) -> 0
B116: PIP Total | H116: =SUMIF($E$38:$E$49:$E$51:$E$62:$E$64:$E$75:$E$77:$E$88:$E$90:$E$101:$E$103:$E$114,"PIP",H$38:H$49:H$51:H$62:H$64:H$75:H$77:H$88:H$90:H$101:H$103:H$114) -> 2 | I116: =SUMIF($E$38:$E$49:$E$51:$E$62:$E$64:$E$75:$E$77:$E$88:$E$90:$E$101:$E$103:$E$114,"PIP",I$38:I$49:I$51:I$62:I$64:I$75:I$77:I$88:I$90:I$101:I$103:I$114) -> 8002 | J116: =SUMIF($E$38:$E$49:$E$51:$E$62:$E$64:$E$75:$E$77:$E$88:$E$90:$E$101:$E$103:$E$114,"PIP",J$38:J$49:J$51:J$62:J$64:J$75:J$77:J$88:J$90:J$101:J$103:J$114) -> 580.145 | K116: =SUMIF($E$38:$E$49:$E$51:$E$62:$E$64:$E$75:$E$77:$E$88:$E$90:$E$101:$E$103:$E$114,"PIP",K$38:K$49:K$51:K$62:K$64:K$75:K$77:K$88:K$90:K$101:K$103:K$114) -> 429.10725 | L116: =SUMIF($E$38:$E$49:$E$51:$E$62:$E$64:$E$75:$E$77:$E$88:$E$90:$E$101:$E$103:$E$114,"PIP",L$38:L$49:L$51:L$62:L$64:L$75:L$77:L$88:L$90:L$101:L$103:L$114) -> 9011.2523 | M116: =SUMIF($E$38:$E$49:$E$51:$E$62:$E$64:$E$75:$E$77:$E$88:$E$90:$E$101:$E$103:$E$114,"PIP",M$38:M$49:M$51:M$62:M$64:M$75:M$77:M$88:M$90:M$101:M$103:M$114) -> 9011.2523 | N116: =SUMIF($E$38:$E$49:$E$51:$E$62:$E$64:$E$75:$E$77:$E$88:$E$90:$E$101:$E$103:$E$114,"PIP",N$38:N$49:N$51:N$62:N$64:N$75:N$77:N$88:N$90:N$101:N$103:N$114) -> 9011.2523 | O116: =SUMIF($E$38:$E$49:$E$51:$E$62:$E$64:$E$75:$E$77:$E$88:$E$90:$E$101:$E$103:$E$114,"PIP",O$38:O$49:O$51:O$62:O$64:O$75:O$77:O$88:O$90:O$101:O$103:O$114) -> 0 | ... Y116: =SUMIF($E$38:$E$49:$E$51:$E$62:$E$64:$E$75:$E$77:$E$88:$E$90:$E$101:$E$103:$E$114,"PIP",Y$38:Y$49:Y$51:Y$62:Y$64:Y$75:Y$77:Y$88:Y$90:Y$101:Y$103:Y$114) -> 0
B117: PCA Total | H117: =SUMIF($E$38:$E$49:$E$51:$E$62:$E$64:$E$75:$E$77:$E$88:$E$90:$E$101:$E$103:$E$114,"PCA",H$38:H$49:H$51:H$62:H$64:H$75:H$77:H$88:H$90:H$101:H$103:H$114) -> 1 | I117: =SUMIF($E$38:$E$49:$E$51:$E$62:$E$64:$E$75:$E$77:$E$88:$E$90:$E$101:$E$103:$E$114,"PCA",I$38:I$49:I$51:I$62:I$64:I$75:I$77:I$88:I$90:I$101:I$103:I$114) -> 601 | J117: =SUMIF($E$38:$E$49:$E$51:$E$62:$E$64:$E$75:$E$77:$E$88:$E$90:$E$101:$E$103:$E$114,"PCA",J$38:J$49:J$51:J$62:J$64:J$75:J$77:J$88:J$90:J$101:J$103:J$114) -> 43.5725 | K117: =SUMIF($E$38:$E$49:$E$51:$E$62:$E$64:$E$75:$E$77:$E$88:$E$90:$E$101:$E$103:$E$114,"PCA",K$38:K$49:K$51:K$62:K$64:K$75:K$77:K$88:K$90:K$101:K$103:K$114) -> 32.228625 | L117: =SUMIF($E$38:$E$49:$E$51:$E$62:$E$64:$E$75:$E$77:$E$88:$E$90:$E$101:$E$103:$E$114,"PCA",L$38:L$49:L$51:L$62:L$64:L$75:L$77:L$88:L$90:L$101:L$103:L$114) -> 676.80112 | M117: =SUMIF($E$38:$E$49:$E$51:$E$62:$E$64:$E$75:$E$77:$E$88:$E$90:$E$101:$E$103:$E$114,"PCA",M$38:M$49:M$51:M$62:M$64:M$75:M$77:M$88:M$90:M$101:M$103:M$114) -> 676.80112 | N117: =SUMIF($E$38:$E$49:$E$51:$E$62:$E$64:$E$75:$E$77:$E$88:$E$90:$E$101:$E$103:$E$114,"PCA",N$38:N$49:N$51:N$62:N$64:N$75:N$77:N$88:N$90:N$101:N$103:N$114) -> 676.80112 | O117: =SUMIF($E$38:$E$49:$E$51:$E$62:$E$64:$E$75:$E$77:$E$88:$E$90:$E$101:$E$103:$E$114,"PCA",O$38:O$49:O$51:O$62:O$64:O$75:O$77:O$88:O$90:O$101:O$103:O$114) -> 0 | ... Y117: =SUMIF($E$38:$E$49:$E$51:$E$62:$E$64:$E$75:$E$77:$E$88:$E$90:$E$101:$E$103:$E$114,"PCA",Y$38:Y$49:Y$51:Y$62:Y$64:Y$75:Y$77:Y$88:Y$90:Y$101:Y$103:Y$114) -> 0
B118: Other Total | H118: =SUMIF($E$38:$E$49:$E$51:$E$62:$E$64:$E$75:$E$77:$E$88:$E$90:$E$101:$E$103:$E$114,"Other",H$38:H$49:H$51:H$62:H$64:H$75:H$77:H$88:H$90:H$101:H$103:H$114) -> 1 | I118: =SUMIF($E$38:$E$49:$E$51:$E$62:$E$64:$E$75:$E$77:$E$88:$E$90:$E$101:$E$103:$E$114,"Other",I$38:I$49:I$51:I$62:I$64:I$75:I$77:I$88:I$90:I$101:I$103:I$114) -> 6001 | J118: =SUMIF($E$38:$E$49:$E$51:$E$62:$E$64:$E$75:$E$77:$E$88:$E$90:$E$101:$E$103:$E$114,"Other",J$38:J$49:J$51:J$62:J$64:J$75:J$77:J$88:J$90:J$101:J$103:J$114) -> 435.0725 | K118: =SUMIF($E$38:$E$49:$E$51:$E$62:$E$64:$E$75:$E$77:$E$88:$E$90:$E$101:$E$103:$E$114,"Other",K$38:K$49:K$51:K$62:K$64:K$75:K$77:K$88:K$90:K$101:K$103:K$114) -> 321.80363 | L118: =SUMIF($E$38:$E$49:$E$51:$E$62:$E$64:$E$75:$E$77:$E$88:$E$90:$E$101:$E$103:$E$114,"Other",L$38:L$49:L$51:L$62:L$64:L$75:L$77:L$88:L$90:L$101:L$103:L$114) -> 6757.8761 | M118: =SUMIF($E$38:$E$49:$E$51:$E$62:$E$64:$E$75:$E$77:$E$88:$E$90:$E$101:$E$103:$E$114,"Other",M$38:M$49:M$51:M$62:M$64:M$75:M$77:M$88:M$90:M$101:M$103:M$114) -> 6757.8761 | N118: =SUMIF($E$38:$E$49:$E$51:$E$62:$E$64:$E$75:$E$77:$E$88:$E$90:$E$101:$E$103:$E$114,"Other",N$38:N$49:N$51:N$62:N$64:N$75:N$77:N$88:N$90:N$101:N$103:N$114) -> 6757.8761 | O118: =SUMIF($E$38:$E$49:$E$51:$E$62:$E$64:$E$75:$E$77:$E$88:$E$90:$E$101:$E$103:$E$114,"Other",O$38:O$49:O$51:O$62:O$64:O$75:O$77:O$88:O$90:O$101:O$103:O$114) -> 0 | ... Y118: =SUMIF($E$38:$E$49:$E$51:$E$62:$E$64:$E$75:$E$77:$E$88:$E$90:$E$101:$E$103:$E$114,"Other",Y$38:Y$49:Y$51:Y$62:Y$64:Y$75:Y$77:Y$88:Y$90:Y$101:Y$103:Y$114) -> 0
...

Sheet 2027 Capex Plan
B2: Instructions
B3: 1. Fill out Property Name, Key Count, State Tax % , and General Manager in the Property Information Box 2. Input budget Total Revenues in row 28 columns I to T 3. Input current FF&E reserve balance in cell F32 4. Fill out all applicable data by hotel departments found in the Hotel Capital Plan section. Only fill in columns C to H and total amounts will calculate in columns I through M. Remember to select from Category dropdown options. 3. Spread the estimated capex amount by month in columns N though Y. 4. Capex plans should be reviewed with Regional VPs and Engineering. Once the plan has been approved, the RVP should initial in the RVP Approval box in the Property Information section. IMPORTANT: Do not add or delete rows or columns from the model.
B17: Property Information
B18: Property Name: | D18: Hotel
B19: Key Count: | D19: 100
B20: State Tax %: | D20: 0.0725
B21: General Manager:
B22: RVP Approval:
B23: Budget Year | D23: 2027
B25: FF&E Reserve Projection
F27: =D23 -> 2027 | I27: January | J27: February | K27: March | L27: April | M27: May | N27: June | O27: July | P27: August | Q27: September | R27: October | S27: November | T27: December
B28: Hotel Revenues | F28: =SUM(I28:T28) -> 1200000 | I28: 100000 | J28: 100000 | K28: 100000 | L28: 100000 | M28: 100000 | N28: 100000 | O28: 100000 | P28: 100000 | Q28: 100000 | R28: 100000 | S28: 100000 | T28: 100000
B29: FF&E Reserve % | F29: 0.04 | I29: =$F$29 -> 0.04 | J29: =$F$29 -> 0.04 | K29: =$F$29 -> 0.04 | L29: =$F$29 -> 0.04 | M29: =$F$29 -> 0.04 | N29: =$F$29 -> 0.04 | O29: =$F$29 -> 0.04 | P29: =$F$29 -> 0.04 | ... T29: =$F$29 -> 0.04
B30: Estimated FF&E Reserve | F30: =F28*F29 -> 48000 | I30: =I28*I29 -> 4000 | J30: =J28*J29 -> 4000 | K30: =K28*K29 -> 4000 | L30: =L28*L29 -> 4000 | M30: =M28*M29 -> 4000 | N30: =N28*N29 -> 4000 | O30: =O28*O29 -> 4000 | P30: =P28*P29 -> 4000 | ... T30: =T28*T29 -> 4000
B31: Total Estimated Capital Expenditures | F31: =SUM(I31:T31) -> 35125.641 | I31: =N121 -> 35125.641 | J31: =O121 -> 0 | K31: =P121 -> 0 | L31: =Q121 -> 0 | M31: =R121 -> 0 | N31: =S121 -> 0 | O31: =T121 -> 0 | P31: =U121 -> 0 | ... T31: =Y121 -> 0
B32: % of Revenue | F32: =F31/F28 -> 0.029271367 | I32: =I31/I28 -> 0.35125641 | J32: =J31/J28 -> 0 | K32: =K31/K28 -> 0 | L32: =L31/L28 -> 0 | M32: =M31/M28 -> 0 | N32: =N31/N28 -> 0 | O32: =O31/O28 -> 0 | P32: =P31/P28 -> 0 | ... T32: =T31/T28 -> 0
B34: =D23&" "& D18 & " " & "Capital Plan" -> 2027 Hotel Capital Plan
B36: Item Description | D36: Comments | E36: Category | F36: Quantity | G36: Unit Price | H36: Freight Cost | I36: Sub Total | J36: Tax | K36: Purchase Fee | L36: Estimate Amount | M36: Budget Amount | N36: January | O36: February | P36: March | Q36: April | R36: May | S36: June | T36: July | U36: August | V36: September | W36: October | X36: November | Y36: December
B37: (A) Guestrooms - Bathroom, Kitchen | H37: =SUM(H38:H49) -> 1 | I37: =SUM(I38:I49) -> 12151 | J37: =SUM(J38:J49) -> 880.9475 | K37: =SUM(K38:K49) -> 651.59738 | L37: =SUM(L38:L49) -> 13683.545 | M37: =SUM(M38:M49) -> 13683.545 | N37: =SUM(N38:N49) -> 13683.545 | O37: =SUM(O38:O49) -> 0 | ... Y37: =SUM(Y38:Y49) -> 0
B38: A1 | C38: Example | D38: Text | E38: QA | F38: 18 | G38: 675 | H38: 1 | I38: =(F38*G38)+H38 -> 12151 | J38: =I38*$D$20 -> 880.9475 | K38: =SUM(I38:J38)*5% -> 651.59738 | L38: =SUM(I38:K38) -> 13683.545 | M38: =SUM(N38, O38,P38,Q38,R38,S38,T38,U38,V38,W38,X38,Y38) -> 13683.545 | N38: =L38 -> 13683.545
B39: A2 | I39: =(F39*G39)+H39 -> 0 | J39: =I39*$D$20 -> 0 | K39: =SUM(I39:J39)*5% -> 0 | L39: =SUM(I39:K39) -> 0 | M39: =SUM(N39, O39,P39,Q39,R39,S39,T39,U39,V39,W39,X39,Y39) -> 0
B40: A3 | I40: =(F40*G40)+H40 -> 0 | J40: =I40*$D$20 -> 0 | K40: =SUM(I40:J40)*5% -> 0 | L40: =SUM(I40:K40) -> 0 | M40: =SUM(N40, O40,P40,Q40,R40,S40,T40,U40,V40,W40,X40,Y40) -> 0
B41: A4 | I41: =(F41*G41)+H41 -> 0 | J41: =I41*$D$20 -> 0 | K41: =SUM(I41:J41)*5% -> 0 | L41: =SUM(I41:K41) -> 0 | M41: =SUM(N41, O41,P41,Q41,R41,S41,T41,U41,V41,W41,X41,Y41) -> 0
B42: A5 | I42: =(F42*G42)+H42 -> 0 | J42: =I42*$D$20 -> 0 | K42: =SUM(I42:J42)*5% -> 0 | L42: =SUM(I42:K42) -> 0 | M42: =SUM(N42, O42,P42,Q42,R42,S42,T42,U42,V42,W42,X42,Y42) -> 0
B43: A6 | I43: =(F43*G43)+H43 -> 0 | J43: =I43*$D$20 -> 0 | K43: =SUM(I43:J43)*5% -> 0 | L43: =SUM(I43:K43) -> 0 | M43: =SUM(N43, O43,P43,Q43,R43,S43,T43,U43,V43,W43,X43,Y43) -> 0
B44: A7 | I44: =(F44*G44)+H44 -> 0 | J44: =I44*$D$20 -> 0 | K44: =SUM(I44:J44)*5% -> 0 | L44: =SUM(I44:K44) -> 0 | M44: =SUM(N44, O44,P44,Q44,R44,S44,T44,U44,V44,W44,X44,Y44) -> 0
B45: A8 | I45: =(F45*G45)+H45 -> 0 | J45: =I45*$D$20 -> 0 | K45: =SUM(I45:J45)*5% -> 0 | L45: =SUM(I45:K45) -> 0 | M45: =SUM(N45, O45,P45,Q45,R45,S45,T45,U45,V45,W45,X45,Y45) -> 0
B46: A9 | I46: =(F46*G46)+H46 -> 0 | J46: =I46*$D$20 -> 0 | K46: =SUM(I46:J46)*5% -> 0 | L46: =SUM(I46:K46) -> 0 | M46: =SUM(N46, O46,P46,Q46,R46,S46,T46,U46,V46,W46,X46,Y46) -> 0
B47: A10 | I47: =(F47*G47)+H47 -> 0 | J47: =I47*$D$20 -> 0 | K47: =SUM(I47:J47)*5% -> 0 | L47: =SUM(I47:K47) -> 0 | M47: =SUM(N47, O47,P47,Q47,R47,S47,T47,U47,V47,W47,X47,Y47) -> 0
B48: A11 | I48: =(F48*G48)+H48 -> 0 | J48: =I48*$D$20 -> 0 | K48: =SUM(I48:J48)*5% -> 0 | L48: =SUM(I48:K48) -> 0 | M48: =SUM(N48, O48,P48,Q48,R48,S48,T48,U48,V48,W48,X48,Y48) -> 0
B49: A12 | I49: =(F49*G49)+H49 -> 0 | J49: =I49*$D$20 -> 0 | K49: =SUM(I49:J49)*5% -> 0 | L49: =SUM(I49:K49) -> 0 | M49: =SUM(N49, O49,P49,Q49,R49,S49,T49,U49,V49,W49,X49,Y49) -> 0
B50: (B) Function Space - Meeting Banquet Space | H50: =SUM(H51:H62) -> 1 | I50: =SUM(I51:I62) -> 6401 | J50: =SUM(J51:J62) -> 464.0725 | K50: =SUM(K51:K62) -> 343.25363 | L50: =SUM(L51:L62) -> 7208.3261 | M50: =SUM(M51:M62) -> 7208.3261 | N50: =SUM(N51:N62) -> 7208.3261 | O50: =SUM(O51:O62) -> 0 | ... Y50: =SUM(Y51:Y62) -> 0
B51: B1 | C51: Example | D51: Text | E51: PIP | F51: 4 | G51: 1600 | H51: 1 | I51: =(F51*G51)+H51 -> 6401 | J51: =I51*$D$20 -> 464.0725 | K51: =SUM(I51:J51)*5% -> 343.25363 | L51: =SUM(I51:K51) -> 7208.3261 | M51: =SUM(N51, O51,P51,Q51,R51,S51,T51,U51,V51,W51,X51,Y51) -> 7208.3261 | N51: =L51 -> 7208.3261
B52: B2 | I52: =(F52*G52)+H52 -> 0 | J52: =I52*$D$20 -> 0 | K52: =SUM(I52:J52)*5% -> 0 | L52: =SUM(I52:K52) -> 0 | M52: =SUM(N52, O52,P52,Q52,R52,S52,T52,U52,V52,W52,X52,Y52) -> 0
B53: B3 | I53: =(F53*G53)+H53 -> 0 | J53: =I53*$D$20 -> 0 | K53: =SUM(I53:J53)*5% -> 0 | L53: =SUM(I53:K53) -> 0 | M53: =SUM(N53, O53,P53,Q53,R53,S53,T53,U53,V53,W53,X53,Y53) -> 0
B54: B4 | I54: =(F54*G54)+H54 -> 0 | J54: =I54*$D$20 -> 0 | K54: =SUM(I54:J54)*5% -> 0 | L54: =SUM(I54:K54) -> 0 | M54: =SUM(N54, O54,P54,Q54,R54,S54,T54,U54,V54,W54,X54,Y54) -> 0
B55: B5 | I55: =(F55*G55)+H55 -> 0 | J55: =I55*$D$20 -> 0 | K55: =SUM(I55:J55)*5% -> 0 | L55: =SUM(I55:K55) -> 0 | M55: =SUM(N55, O55,P55,Q55,R55,S55,T55,U55,V55,W55,X55,Y55) -> 0
B56: B6 | I56: =(F56*G56)+H56 -> 0 | J56: =I56*$D$20 -> 0 | K56: =SUM(I56:J56)*5% -> 0 | L56: =SUM(I56:K56) -> 0 | M56: =SUM(N56, O56,P56,Q56,R56,S56,T56,U56,V56,W56,X56,Y56) -> 0
B57: B7 | I57: =(F57*G57)+H57 -> 0 | J57: =I57*$D$20 -> 0 | K57: =SUM(I57:J57)*5% -> 0 | L57: =SUM(I57:K57) -> 0 | M57: =SUM(N57, O57,P57,Q57,R57,S57,T57,U57,V57,W57,X57,Y57) -> 0
B58: B8 | I58: =(F58*G58)+H58 -> 0 | J58: =I58*$D$20 -> 0 | K58: =SUM(I58:J58)*5% -> 0 | L58: =SUM(I58:K58) -> 0 | M58: =SUM(N58, O58,P58,Q58,R58,S58,T58,U58,V58,W58,X58,Y58) -> 0
B59: B9 | I59: =(F59*G59)+H59 -> 0 | J59: =I59*$D$20 -> 0 | K59: =SUM(I59:J59)*5% -> 0 | L59: =SUM(I59:K59) -> 0 | M59: =SUM(N59, O59,P59,Q59,R59,S59,T59,U59,V59,W59,X59,Y59) -> 0
B60: B10 | I60: =(F60*G60)+H60 -> 0 | J60: =I60*$D$20 -> 0 | K60: =SUM(I60:J60)*5% -> 0 | L60: =SUM(I60:K60) -> 0 | M60: =SUM(N60, O60,P60,Q60,R60,S60,T60,U60,V60,W60,X60,Y60) -> 0
B61: B11 | I61: =(F61*G61)+H61 -> 0 | J61: =I61*$D$20 -> 0 | K61: =SUM(I61:J61)*5% -> 0 | L61: =SUM(I61:K61) -> 0 | M61: =SUM(N61, O61,P61,Q61,R61,S61,T61,U61,V61,W61,X61,Y61) -> 0
B62: B12 | I62: =(F62*G62)+H62 -> 0 | J62: =I62*$D$20 -> 0 | K62: =SUM(I62:J62)*5% -> 0 | L62: =SUM(I62:K62) -> 0 | M62: =SUM(N62, O62,P62,Q62,R62,S62,T62,U62,V62,W62,X62,Y62) -> 0
B63: (C) Public Areas - Lobby, Pool, Fitness, Corridors | H63: =SUM(H64:H75) -> 1 | I63: =SUM(I64:I75) -> 601 | J63: =SUM(J64:J75) -> 43.5725 | K63: =SUM(K64:K75) -> 32.228625 | L63: =SUM(L64:L75) -> 676.80112 | M63: =SUM(M64:M75) -> 676.80112 | N63: =SUM(N64:N75) -> 676.80112 | O63: =SUM(O64:O75) -> 0 | ... Y63: =SUM(Y64:Y75) -> 0
B64: C1 | C64: Example | D64: Text | E64: PCA | F64: 2 | G64: 300 | H64: 1 | I64: =(F64*G64)+H64 -> 601 | J64: =I64*$D$20 -> 43.5725 | K64: =SUM(I64:J64)*5% -> 32.228625 | L64: =SUM(I64:K64) -> 676.80112 | M64: =SUM(N64, O64,P64,Q64,R64,S64,T64,U64,V64,W64,X64,Y64) -> 676.80112 | N64: =L64 -> 676.80112
B65: C2 | I65: =(F65*G65)+H65 -> 0 | J65: =I65*$D$20 -> 0 | K65: =SUM(I65:J65)*5% -> 0 | L65: =SUM(I65:K65) -> 0 | M65: =SUM(N65, O65,P65,Q65,R65,S65,T65,U65,V65,W65,X65,Y65) -> 0
B66: C3 | I66: =(F66*G66)+H66 -> 0 | J66: =I66*$D$20 -> 0 | K66: =SUM(I66:J66)*5% -> 0 | L66: =SUM(I66:K66) -> 0 | M66: =SUM(N66, O66,P66,Q66,R66,S66,T66,U66,V66,W66,X66,Y66) -> 0
B67: C4 | I67: =(F67*G67)+H67 -> 0 | J67: =I67*$D$20 -> 0 | K67: =SUM(I67:J67)*5% -> 0 | L67: =SUM(I67:K67) -> 0 | M67: =SUM(N67, O67,P67,Q67,R67,S67,T67,U67,V67,W67,X67,Y67) -> 0
B68: C5 | I68: =(F68*G68)+H68 -> 0 | J68: =I68*$D$20 -> 0 | K68: =SUM(I68:J68)*5% -> 0 | L68: =SUM(I68:K68) -> 0 | M68: =SUM(N68, O68,P68,Q68,R68,S68,T68,U68,V68,W68,X68,Y68) -> 0
B69: C6 | I69: =(F69*G69)+H69 -> 0 | J69: =I69*$D$20 -> 0 | K69: =SUM(I69:J69)*5% -> 0 | L69: =SUM(I69:K69) -> 0 | M69: =SUM(N69, O69,P69,Q69,R69,S69,T69,U69,V69,W69,X69,Y69) -> 0
B70: C7 | I70: =(F70*G70)+H70 -> 0 | J70: =I70*$D$20 -> 0 | K70: =SUM(I70:J70)*5% -> 0 | L70: =SUM(I70:K70) -> 0 | M70: =SUM(N70, O70,P70,Q70,R70,S70,T70,U70,V70,W70,X70,Y70) -> 0
B71: C8 | I71: =(F71*G71)+H71 -> 0 | J71: =I71*$D$20 -> 0 | K71: =SUM(I71:J71)*5% -> 0 | L71: =SUM(I71:K71) -> 0 | M71: =SUM(N71, O71,P71,Q71,R71,S71,T71,U71,V71,W71,X71,Y71) -> 0
B72: C9 | I72: =(F72*G72)+H72 -> 0 | J72: =I72*$D$20 -> 0 | K72: =SUM(I72:J72)*5% -> 0 | L72: =SUM(I72:K72) -> 0 | M72: =SUM(N72, O72,P72,Q72,R72,S72,T72,U72,V72,W72,X72,Y72) -> 0
B73: C10 | I73: =(F73*G73)+H73 -> 0 | J73: =I73*$D$20 -> 0 | K73: =SUM(I73:J73)*5% -> 0 | L73: =SUM(I73:K73) -> 0 | M73: =SUM(N73, O73,P73,Q73,R73,S73,T73,U73,V73,W73,X73,Y73) -> 0
B74: C11 | I74: =(F74*G74)+H74 -> 0 | J74: =I74*$D$20 -> 0 | K74: =SUM(I74:J74)*5% -> 0 | L74: =SUM(I74:K74) -> 0 | M74: =SUM(N74, O74,P74,Q74,R74,S74,T74,U74,V74,W74,X74,Y74) -> 0
B75: C12 | I75: =(F75*G75)+H75 -> 0 | J75: =I75*$D$20 -> 0 | K75: =SUM(I75:J75)*5% -> 0 | L75: =SUM(I75:K75) -> 0 | M75: =SUM(N75, O75,P75,Q75,R75,S75,T75,U75,V75,W75,X75,Y75) -> 0
B76: (D) Technology - Computer Systems | H76: =SUM(H77:H88) -> 1 | I76: =SUM(I77:I88) -> 6001 | J76: =SUM(J77:J88) -> 435.0725 | K76: =SUM(K77:K88) -> 321.80363 | L76: =SUM(L77:L88) -> 6757.8761 | M76: =SUM(M77:M88) -> 6757.8761 | N76: =SUM(N77:N88) -> 6757.8761 | O76: =SUM(O77:O88) -> 0 | ... Y76: =SUM(Y77:Y88) -> 0
B77: D1 | C77: Example | D77: Text | E77: Other | F77: 2 | G77: 3000 | H77: 1 | I77: =(F77*G77)+H77 -> 6001 | J77: =I77*$D$20 -> 435.0725 | K77: =SUM(I77:J77)*5% -> 321.80363 | L77: =SUM(I77:K77) -> 6757.8761 | M77: =SUM(N77, O77,P77,Q77,R77,S77,T77,U77,V77,W77,X77,Y77) -> 6757.8761 | N77: =L77 -> 6757.8761
B78: D2 | I78: =(F78*G78)+H78 -> 0 | J78: =I78*$D$20 -> 0 | K78: =SUM(I78:J78)*5% -> 0 | L78: =SUM(I78:K78) -> 0 | M78: =SUM(N78, O78,P78,Q78,R78,S78,T78,U78,V78,W78,X78,Y78) -> 0
B79: D3 | I79: =(F79*G79)+H79 -> 0 | J79: =I79*$D$20 -> 0 | K79: =SUM(I79:J79)*5% -> 0 | L79: =SUM(I79:K79) -> 0 | M79: =SUM(N79, O79,P79,Q79,R79,S79,T79,U79,V79,W79,X79,Y79) -> 0
B80: D4 | I80: =(F80*G80)+H80 -> 0 | J80: =I80*$D$20 -> 0 | K80: =SUM(I80:J80)*5% -> 0 | L80: =SUM(I80:K80) -> 0 | M80: =SUM(N80, O80,P80,Q80,R80,S80,T80,U80,V80,W80,X80,Y80) -> 0
B81: D5 | I81: =(F81*G81)+H81 -> 0 | J81: =I81*$D$20 -> 0 | K81: =SUM(I81:J81)*5% -> 0 | L81: =SUM(I81:K81) -> 0 | M81: =SUM(N81, O81,P81,Q81,R81,S81,T81,U81,V81,W81,X81,Y81) -> 0
B82: D6 | I82: =(F82*G82)+H82 -> 0 | J82: =I82*$D$20 -> 0 | K82: =SUM(I82:J82)*5% -> 0 | L82: =SUM(I82:K82) -> 0 | M82: =SUM(N82, O82,P82,Q82,R82,S82,T82,U82,V82,W82,X82,Y82) -> 0
B83: D7 | I83: =(F83*G83)+H83 -> 0 | J83: =I83*$D$20 -> 0 | K83: =SUM(I83:J83)*5% -> 0 | L83: =SUM(I83:K83) -> 0 | M83: =SUM(N83, O83,P83,Q83,R83,S83,T83,U83,V83,W83,X83,Y83) -> 0
B84: D8 | I84: =(F84*G84)+H84 -> 0 | J84: =I84*$D$20 -> 0 | K84: =SUM(I84:J84)*5% -> 0 | L84: =SUM(I84:K84) -> 0 | M84: =SUM(N84, O84,P84,Q84,R84,S84,T84,U84,V84,W84,X84,Y84) -> 0
B85: D9 | I85: =(F85*G85)+H85 -> 0 | J85: =I85*$D$20 -> 0 | K85: =SUM(I85:J85)*5% -> 0 | L85: =SUM(I85:K85) -> 0 | M85: =SUM(N85, O85,P85,Q85,R85,S85,T85,U85,V85,W85,X85,Y85) -> 0
B86: D10 | I86: =(F86*G86)+H86 -> 0 | J86: =I86*$D$20 -> 0 | K86: =SUM(I86:J86)*5% -> 0 | L86: =SUM(I86:K86) -> 0 | M86: =SUM(N86, O86,P86,Q86,R86,S86,T86,U86,V86,W86,X86,Y86) -> 0
B87: D11 | I87: =(F87*G87)+H87 -> 0 | J87: =I87*$D$20 -> 0 | K87: =SUM(I87:J87)*5% -> 0 | L87: =SUM(I87:K87) -> 0 | M87: =SUM(N87, O87,P87,Q87,R87,S87,T87,U87,V87,W87,X87,Y87) -> 0
B88: D12 | I88: =(F88*G88)+H88 -> 0 | J88: =I88*$D$20 -> 0 | K88: =SUM(I88:J88)*5% -> 0 | L88: =SUM(I88:K88) -> 0 | M88: =SUM(N88, O88,P88,Q88,R88,S88,T88,U88,V88,W88,X88,Y88) -> 0
B89: (E) Back of House - Administrative, Laundry | H89: =SUM(H90:H101) -> 1 | I89: =SUM(I90:I101) -> 1601 | J89: =SUM(J90:J101) -> 116.0725 | K89: =SUM(K90:K101) -> 85.853625 | L89: =SUM(L90:L101) -> 1802.9261 | M89: =SUM(M90:M101) -> 1802.9261 | N89: =SUM(N90:N101) -> 1802.9261 | O89: =SUM(O90:O101) -> 0 | ... Y89: =SUM(Y90:Y101) -> 0
B90: E1 | C90: Example | D90: Text | E90: QA | F90: 1 | G90: 1600 | H90: 1 | I90: =(F90*G90)+H90 -> 1601 | J90: =I90*$D$20 -> 116.0725 | K90: =SUM(I90:J90)*5% -> 85.853625 | L90: =SUM(I90:K90) -> 1802.9261 | M90: =SUM(N90, O90,P90,Q90,R90,S90,T90,U90,V90,W90,X90,Y90) -> 1802.9261 | N90: =L90 -> 1802.9261
B91: E2 | I91: =(F91*G91)+H91 -> 0 | J91: =I91*$D$20 -> 0 | K91: =SUM(I91:J91)*5% -> 0 | L91: =SUM(I91:K91) -> 0 | M91: =SUM(N91, O91,P91,Q91,R91,S91,T91,U91,V91,W91,X91,Y91) -> 0
B92: E3 | I92: =(F92*G92)+H92 -> 0 | J92: =I92*$D$20 -> 0 | K92: =SUM(I92:J92)*5% -> 0 | L92: =SUM(I92:K92) -> 0 | M92: =SUM(N92, O92,P92,Q92,R92,S92,T92,U92,V92,W92,X92,Y92) -> 0
B93: E4 | I93: =(F93*G93)+H93 -> 0 | J93: =I93*$D$20 -> 0 | K93: =SUM(I93:J93)*5% -> 0 | L93: =SUM(I93:K93) -> 0 | M93: =SUM(N93, O93,P93,Q93,R93,S93,T93,U93,V93,W93,X93,Y93) -> 0
B94: E5 | I94: =(F94*G94)+H94 -> 0 | J94: =I94*$D$20 -> 0 | K94: =SUM(I94:J94)*5% -> 0 | L94: =SUM(I94:K94) -> 0 | M94: =SUM(N94, O94,P94,Q94,R94,S94,T94,U94,V94,W94,X94,Y94) -> 0
B95: E6 | I95: =(F95*G95)+H95 -> 0 | J95: =I95*$D$20 -> 0 | K95: =SUM(I95:J95)*5% -> 0 | L95: =SUM(I95:K95) -> 0 | M95: =SUM(N95, O95,P95,Q95,R95,S95,T95,U95,V95,W95,X95,Y95) -> 0
B96: E7 | I96: =(F96*G96)+H96 -> 0 | J96: =I96*$D$20 -> 0 | K96: =SUM(I96:J96)*5% -> 0 | L96: =SUM(I96:K96) -> 0 | M96: =SUM(N96, O96,P96,Q96,R96,S96,T96,U96,V96,W96,X96,Y96) -> 0
B97: E8 | I97: =(F97*G97)+H97 -> 0 | J97: =I97*$D$20 -> 0 | K97: =SUM(I97:J97)*5% -> 0 | L97: =SUM(I97:K97) -> 0 | M97: =SUM(N97, O97,P97,Q97,R97,S97,T97,U97,V97,W97,X97,Y97) -> 0
B98: E9 | I98: =(F98*G98)+H98 -> 0 | J98: =I98*$D$20 -> 0 | K98: =SUM(I98:J98)*5% -> 0 | L98: =SUM(I98:K98) -> 0 | M98: =SUM(N98, O98,P98,Q98,R98,S98,T98,U98,V98,W98,X98,Y98) -> 0
B99: E10 | I99: =(F99*G99)+H99 -> 0 | J99: =I99*$D$20 -> 0 | K99: =SUM(I99:J99)*5% -> 0 | L99: =SUM(I99:K99) -> 0 | M99: =SUM(N99, O99,P99,Q99,R99,S99,T99,U99,V99,W99,X99,Y99) -> 0
B100: E11 | I100: =(F100*G100)+H100 -> 0 | J100: =I100*$D$20 -> 0 | K100: =SUM(I100:J100)*5% -> 0 | L100: =SUM(I100:K100) -> 0 | M100: =SUM(N100, O100,P100,Q100,R100,S100,T100,U100,V100,W100,X100,Y100) -> 0
B101: E12 | I101: =(F101*G101)+H101 -> 0 | J101: =I101*$D$20 -> 0 | K101: =SUM(I101:J101)*5% -> 0 | L101: =SUM(I101:K101) -> 0 | M101: =SUM(N101, O101,P101,Q101,R101,S101,T101,U101,V101,W101,X101,Y101) -> 0
B102: (F) Building - Site, Exterior, Mechanical | H102: =SUM(H103:H114) -> 1 | I102: =SUM(I103:I114) -> 1601 | J102: =SUM(J103:J114) -> 116.0725 | K102: =SUM(K103:K114) -> 85.853625 | L102: =SUM(L103:L114) -> 1802.9261 | M102: =SUM(M103:M114) -> 1802.9261 | N102: =SUM(N103:N114) -> 1802.9261 | O102: =SUM(O103:O114) -> 0 | ... Y102: =SUM(Y103:Y114) -> 0
B103: F1 | C103: Example | D103: Text | E103: PIP | F103: 1 | G103: 1600 | H103: 1 | I103: =(F103*G103)+H103 -> 1601 | J103: =I103*$D$20 -> 116.0725 | K103: =SUM(I103:J103)*5% -> 85.853625 | L103: =SUM(I103:K103) -> 1802.9261 | M103: =SUM(N103, O103,P103,Q103,R103,S103,T103,U103,V103,W103,X103,Y103) -> 1802.9261 | N103: =L103 -> 1802.9261
B104: F2 | I104: =(F104*G104)+H104 -> 0 | J104: =I104*$D$20 -> 0 | K104: =SUM(I104:J104)*5% -> 0 | L104: =SUM(I104:K104) -> 0 | M104: =SUM(N104, O104,P104,Q104,R104,S104,T104,U104,V104,W104,X104,Y104) -> 0
B105: F3 | I105: =(F105*G105)+H105 -> 0 | J105: =I105*$D$20 -> 0 | K105: =SUM(I105:J105)*5% -> 0 | L105: =SUM(I105:K105) -> 0 | M105: =SUM(N105, O105,P105,Q105,R105,S105,T105,U105,V105,W105,X105,Y105) -> 0
B106: F4 | I106: =(F106*G106)+H106 -> 0 | J106: =I106*$D$20 -> 0 | K106: =SUM(I106:J106)*5% -> 0 | L106: =SUM(I106:K106) -> 0 | M106: =SUM(N106, O106,P106,Q106,R106,S106,T106,U106,V106,W106,X106,Y106) -> 0
B107: F5 | I107: =(F107*G107)+H107 -> 0 | J107: =I107*$D$20 -> 0 | K107: =SUM(I107:J107)*5% -> 0 | L107: =SUM(I107:K107) -> 0 | M107: =SUM(N107, O107,P107,Q107,R107,S107,T107,U107,V107,W107,X107,Y107) -> 0
B108: F6 | I108: =(F108*G108)+H108 -> 0 | J108: =I108*$D$20 -> 0 | K108: =SUM(I108:J108)*5% -> 0 | L108: =SUM(I108:K108) -> 0 | M108: =SUM(N108, O108,P108,Q108,R108,S108,T108,U108,V108,W108,X108,Y108) -> 0
B109: F7 | I109: =(F109*G109)+H109 -> 0 | J109: =I109*$D$20 -> 0 | K109: =SUM(I109:J109)*5% -> 0 | L109: =SUM(I109:K109) -> 0 | M109: =SUM(N109, O109,P109,Q109,R109,S109,T109,U109,V109,W109,X109,Y109) -> 0
B110: F8 | I110: =(F110*G110)+H110 -> 0 | J110: =I110*$D$20 -> 0 | K110: =SUM(I110:J110)*5% -> 0 | L110: =SUM(I110:K110) -> 0 | M110: =SUM(N110, O110,P110,Q110,R110,S110,T110,U110,V110,W110,X110,Y110) -> 0
B111: F9 | I111: =(F111*G111)+H111 -> 0 | J111: =I111*$D$20 -> 0 | K111: =SUM(I111:J111)*5% -> 0 | L111: =SUM(I111:K111) -> 0 | M111: =SUM(N111, O111,P111,Q111,R111,S111,T111,U111,V111,W111,X111,Y111) -> 0
B112: F10 | I112: =(F112*G112)+H112 -> 0 | J112: =I112*$D$20 -> 0 | K112: =SUM(I112:J112)*5% -> 0 | L112: =SUM(I112:K112) -> 0 | M112: =SUM(N112, O112,P112,Q112,R112,S112,T112,U112,V112,W112,X112,Y112) -> 0
B113: F11 | I113: =(F113*G113)+H113 -> 0 | J113: =I113*$D$20 -> 0 | K113: =SUM(I113:J113)*5% -> 0 | L113: =SUM(I113:K113) -> 0 | M113: =SUM(N113, O113,P113,Q113,R113,S113,T113,U113,V113,W113,X113,Y113) -> 0
B114: F12 | I114: =(F114*G114)+H114 -> 0 | J114: =I114*$D$20 -> 0 | K114: =SUM(I114:J114)*5% -> 0 | L114: =SUM(I114:K114) -> 0 | M114: =SUM(N114, O114,P114,Q114,R114,S114,T114,U114,V114,W114,X114,Y114) -> 0
B115: QA Total | H115: =SUMIF($E$38:$E$49:$E$51:$E$62:$E$64:$E$75:$E$77:$E$88:$E$90:$E$101:$E$103:$E$114,"QA",H$38:H$49:H$51:H$62:H$64:H$75:H$77:H$88:H$90:H$101:H$103:H$114) -> 2 | I115: =SUMIF($E$38:$E$49:$E$51:$E$62:$E$64:$E$75:$E$77:$E$88:$E$90:$E$101:$E$103:$E$114,"QA",I$38:I$49:I$51:I$62:I$64:I$75:I$77:I$88:I$90:I$101:I$103:I$114) -> 13752 | J115: =SUMIF($E$38:$E$49:$E$51:$E$62:$E$64:$E$75:$E$77:$E$88:$E$90:$E$101:$E$103:$E$114,"QA",J$38:J$49:J$51:J$62:J$64:J$75:J$77:J$88:J$90:J$101:J$103:J$114) -> 997.02 | K115: =SUMIF($E$38:$E$49:$E$51:$E$62:$E$64:$E$75:$E$77:$E$88:$E$90:$E$101:$E$103:$E$114,"QA",K$38:K$49:K$51:K$62:K$64:K$75:K$77:K$88:K$90:K$101:K$103:K$114) -> 737.451 | L115: =SUMIF($E$38:$E$49:$E$51:$E$62:$E$64:$E$75:$E$77:$E$88:$E$90:$E$101:$E$103:$E$114,"QA",L$38:L$49:L$51:L$62:L$64:L$75:L$77:L$88:L$90:L$101:L$103:L$114) -> 15486.471 | M115: =SUMIF($E$38:$E$49:$E$51:$E$62:$E$64:$E$75:$E$77:$E$88:$E$90:$E$101:$E$103:$E$114,"QA",M$38:M$49:M$51:M$62:M$64:M$75:M$77:M$88:M$90:M$101:M$103:M$114) -> 15486.471 | N115: =SUMIF($E$38:$E$49:$E$51:$E$62:$E$64:$E$75:$E$77:$E$88:$E$90:$E$101:$E$103:$E$114,"QA",N$38:N$49:N$51:N$62:N$64:N$75:N$77:N$88:N$90:N$101:N$103:N$114) -> 15486.471 | O115: =SUMIF($E$38:$E$49:$E$51:$E$62:$E$64:$E$75:$E$77:$E$88:$E$90:$E$101:$E$103:$E$114,"QA",O$38:O$49:O$51:O$62:O$64:O$75:O$77:O$88:O$90:O$101:O$103:O$114) -> 0 | ... Y115: =SUMIF($E$38:$E$49:$E$51:$E$62:$E$64:$E$75:$E$77:$E$88:$E$90:$E$101:$E$103:$E$114,"QA",Y$38:Y$49:Y$51:Y$62:Y$64:Y$75:Y$77:Y$88:Y$90:Y$101:Y$103:Y$114) -> 0
B116: PIP Total | H116: =SUMIF($E$38:$E$49:$E$51:$E$62:$E$64:$E$75:$E$77:$E$88:$E$90:$E$101:$E$103:$E$114,"PIP",H$38:H$49:H$51:H$62:H$64:H$75:H$77:H$88:H$90:H$101:H$103:H$114) -> 2 | I116: =SUMIF($E$38:$E$49:$E$51:$E$62:$E$64:$E$75:$E$77:$E$88:$E$90:$E$101:$E$103:$E$114,"PIP",I$38:I$49:I$51:I$62:I$64:I$75:I$77:I$88:I$90:I$101:I$103:I$114) -> 8002 | J116: =SUMIF($E$38:$E$49:$E$51:$E$62:$E$64:$E$75:$E$77:$E$88:$E$90:$E$101:$E$103:$E$114,"PIP",J$38:J$49:J$51:J$62:J$64:J$75:J$77:J$88:J$90:J$101:J$103:J$114) -> 580.145 | K116: =SUMIF($E$38:$E$49:$E$51:$E$62:$E$64:$E$75:$E$77:$E$88:$E$90:$E$101:$E$103:$E$114,"PIP",K$38:K$49:K$51:K$62:K$64:K$75:K$77:K$88:K$90:K$101:K$103:K$114) -> 429.10725 | L116: =SUMIF($E$38:$E$49:$E$51:$E$62:$E$64:$E$75:$E$77:$E$88:$E$90:$E$101:$E$103:$E$114,"PIP",L$38:L$49:L$51:L$62:L$64:L$75:L$77:L$88:L$90:L$101:L$103:L$114) -> 9011.2523 | M116: =SUMIF($E$38:$E$49:$E$51:$E$62:$E$64:$E$75:$E$77:$E$88:$E$90:$E$101:$E$103:$E$114,"PIP",M$38:M$49:M$51:M$62:M$64:M$75:M$77:M$88:M$90:M$101:M$103:M$114) -> 9011.2523 | N116: =SUMIF($E$38:$E$49:$E$51:$E$62:$E$64:$E$75:$E$77:$E$88:$E$90:$E$101:$E$103:$E$114,"PIP",N$38:N$49:N$51:N$62:N$64:N$75:N$77:N$88:N$90:N$101:N$103:N$114) -> 9011.2523 | O116: =SUMIF($E$38:$E$49:$E$51:$E$62:$E$64:$E$75:$E$77:$E$88:$E$90:$E$101:$E$103:$E$114,"PIP",O$38:O$49:O$51:O$62:O$64:O$75:O$77:O$88:O$90:O$101:O$103:O$114) -> 0 | ... Y116: =SUMIF($E$38:$E$49:$E$51:$E$62:$E$64:$E$75:$E$77:$E$88:$E$90:$E$101:$E$103:$E$114,"PIP",Y$38:Y$49:Y$51:Y$62:Y$64:Y$75:Y$77:Y$88:Y$90:Y$101:Y$103:Y$114) -> 0
B117: PCA Total | H117: =SUMIF($E$38:$E$49:$E$51:$E$62:$E$64:$E$75:$E$77:$E$88:$E$90:$E$101:$E$103:$E$114,"PCA",H$38:H$49:H$51:H$62:H$64:H$75:H$77:H$88:H$90:H$101:H$103:H$114) -> 1 | I117: =SUMIF($E$38:$E$49:$E$51:$E$62:$E$64:$E$75:$E$77:$E$88:$E$90:$E$101:$E$103:$E$114,"PCA",I$38:I$49:I$51:I$62:I$64:I$75:I$77:I$88:I$90:I$101:I$103:I$114) -> 601 | J117: =SUMIF($E$38:$E$49:$E$51:$E$62:$E$64:$E$75:$E$77:$E$88:$E$90:$E$101:$E$103:$E$114,"PCA",J$38:J$49:J$51:J$62:J$64:J$75:J$77:J$88:J$90:J$101:J$103:J$114) -> 43.5725 | K117: =SUMIF($E$38:$E$49:$E$51:$E$62:$E$64:$E$75:$E$77:$E$88:$E$90:$E$101:$E$103:$E$114,"PCA",K$38:K$49:K$51:K$62:K$64:K$75:K$77:K$88:K$90:K$101:K$103:K$114) -> 32.228625 | L117: =SUMIF($E$38:$E$49:$E$51:$E$62:$E$64:$E$75:$E$77:$E$88:$E$90:$E$101:$E$103:$E$114,"PCA",L$38:L$49:L$51:L$62:L$64:L$75:L$77:L$88:L$90:L$101:L$103:L$114) -> 676.80112 | M117: =SUMIF($E$38:$E$49:$E$51:$E$62:$E$64:$E$75:$E$77:$E$88:$E$90:$E$101:$E$103:$E$114,"PCA",M$38:M$49:M$51:M$62:M$64:M$75:M$77:M$88:M$90:M$101:M$103:M$114) -> 676.80112 | N117: =SUMIF($E$38:$E$49:$E$51:$E$62:$E$64:$E$75:$E$77:$E$88:$E$90:$E$101:$E$103:$E$114,"PCA",N$38:N$49:N$51:N$62:N$64:N$75:N$77:N$88:N$90:N$101:N$103:N$114) -> 676.80112 | O117: =SUMIF($E$38:$E$49:$E$51:$E$62:$E$64:$E$75:$E$77:$E$88:$E$90:$E$101:$E$103:$E$114,"PCA",O$38:O$49:O$51:O$62:O$64:O$75:O$77:O$88:O$90:O$101:O$103:O$114) -> 0 | ... Y117: =SUMIF($E$38:$E$49:$E$51:$E$62:$E$64:$E$75:$E$77:$E$88:$E$90:$E$101:$E$103:$E$114,"PCA",Y$38:Y$49:Y$51:Y$62:Y$64:Y$75:Y$77:Y$88:Y$90:Y$101:Y$103:Y$114) -> 0
B118: Other Total | H118: =SUMIF($E$38:$E$49:$E$51:$E$62:$E$64:$E$75:$E$77:$E$88:$E$90:$E$101:$E$103:$E$114,"Other",H$38:H$49:H$51:H$62:H$64:H$75:H$77:H$88:H$90:H$101:H$103:H$114) -> 1 | I118: =SUMIF($E$38:$E$49:$E$51:$E$62:$E$64:$E$75:$E$77:$E$88:$E$90:$E$101:$E$103:$E$114,"Other",I$38:I$49:I$51:I$62:I$64:I$75:I$77:I$88:I$90:I$101:I$103:I$114) -> 6001 | J118: =SUMIF($E$38:$E$49:$E$51:$E$62:$E$64:$E$75:$E$77:$E$88:$E$90:$E$101:$E$103:$E$114,"Other",J$38:J$49:J$51:J$62:J$64:J$75:J$77:J$88:J$90:J$101:J$103:J$114) -> 435.0725 | K118: =SUMIF($E$38:$E$49:$E$51:$E$62:$E$64:$E$75:$E$77:$E$88:$E$90:$E$101:$E$103:$E$114,"Other",K$38:K$49:K$51:K$62:K$64:K$75:K$77:K$88:K$90:K$101:K$103:K$114) -> 321.80363 | L118: =SUMIF($E$38:$E$49:$E$51:$E$62:$E$64:$E$75:$E$77:$E$88:$E$90:$E$101:$E$103:$E$114,"Other",L$38:L$49:L$51:L$62:L$64:L$75:L$77:L$88:L$90:L$101:L$103:L$114) -> 6757.8761 | M118: =SUMIF($E$38:$E$49:$E$51:$E$62:$E$64:$E$75:$E$77:$E$88:$E$90:$E$101:$E$103:$E$114,"Other",M$38:M$49:M$51:M$62:M$64:M$75:M$77:M$88:M$90:M$101:M$103:M$114) -> 6757.8761 | N118: =SUMIF($E$38:$E$49:$E$51:$E$62:$E$64:$E$75:$E$77:$E$88:$E$90:$E$101:$E$103:$E$114,"Other",N$38:N$49:N$51:N$62:N$64:N$75:N$77:N$88:N$90:N$101:N$103:N$114) -> 6757.8761 | O118: =SUMIF($E$38:$E$49:$E$51:$E$62:$E$64:$E$75:$E$77:$E$88:$E$90:$E$101:$E$103:$E$114,"Other",O$38:O$49:O$51:O$62:O$64:O$75:O$77:O$88:O$90:O$101:O$103:O$114) -> 0 | ... Y118: =SUMIF($E$38:$E$49:$E$51:$E$62:$E$64:$E$75:$E$77:$E$88:$E$90:$E$101:$E$103:$E$114,"Other",Y$38:Y$49:Y$51:Y$62:Y$64:Y$75:Y$77:Y$88:Y$90:Y$101:Y$103:Y$114) -> 0
...

Sheet 2028 Capex Plan
B2: Instructions
B3: 1. Fill out Property Name, Key Count, State Tax % , and General Manager in the Property Information Box 2. Input budget Total Revenues in row 28 columns I to T 3. Input current FF&E reserve balance in cell F32 4. Fill out all applicable data by hotel departments found in the Hotel Capital Plan section. Only fill in columns C to H and total amounts will calculate in columns I through M. Remember to select from Category dropdown options. 3. Spread the estimated capex amount by month in columns N though Y. 4. Capex plans should be reviewed with Regional VPs and Engineering. Once the plan has been approved, the RVP should initial in the RVP Approval box in the Property Information section. IMPORTANT: Do not add or delete rows or columns from the model.
B17: Property Information
B18: Property Name: | D18: Hotel
B19: Key Count: | D19: 100
B20: State Tax %: | D20: 0.0725
B21: General Manager:
B22: RVP Approval:
B23: Budget Year | D23: 2028
B25: FF&E Reserve Projection
F27: =D23 -> 2028 | I27: January | J27: February | K27: March | L27: April | M27: May | N27: June | O27: July | P27: August | Q27: September | R27: October | S27: November | T27: December
B28: Hotel Revenues | F28: =SUM(I28:T28) -> 1200000 | I28: 100000 | J28: 100000 | K28: 100000 | L28: 100000 | M28: 100000 | N28: 100000 | O28: 100000 | P28: 100000 | Q28: 100000 | R28: 100000 | S28: 100000 | T28: 100000
B29: FF&E Reserve % | F29: 0.04 | I29: =$F$29 -> 0.04 | J29: =$F$29 -> 0.04 | K29: =$F$29 -> 0.04 | L29: =$F$29 -> 0.04 | M29: =$F$29 -> 0.04 | N29: =$F$29 -> 0.04 | O29: =$F$29 -> 0.04 | P29: =$F$29 -> 0.04 | ... T29: =$F$29 -> 0.04
B30: Estimated FF&E Reserve | F30: =F28*F29 -> 48000 | I30: =I28*I29 -> 4000 | J30: =J28*J29 -> 4000 | K30: =K28*K29 -> 4000 | L30: =L28*L29 -> 4000 | M30: =M28*M29 -> 4000 | N30: =N28*N29 -> 4000 | O30: =O28*O29 -> 4000 | P30: =P28*P29 -> 4000 | ... T30: =T28*T29 -> 4000
B31: Total Estimated Capital Expenditures | F31: =SUM(I31:T31) -> 35125.641 | I31: =N121 -> 35125.641 | J31: =O121 -> 0 | K31: =P121 -> 0 | L31: =Q121 -> 0 | M31: =R121 -> 0 | N31: =S121 -> 0 | O31: =T121 -> 0 | P31: =U121 -> 0 | ... T31: =Y121 -> 0
B32: % of Revenue | F32: =F31/F28 -> 0.029271367 | I32: =I31/I28 -> 0.35125641 | J32: =J31/J28 -> 0 | K32: =K31/K28 -> 0 | L32: =L31/L28 -> 0 | M32: =M31/M28 -> 0 | N32: =N31/N28 -> 0 | O32: =O31/O28 -> 0 | P32: =P31/P28 -> 0 | ... T32: =T31/T28 -> 0
B34: =D23&" "& D18 & " " & "Capital Plan" -> 2028 Hotel Capital Plan
B36: Item Description | D36: Comments | E36: Category | F36: Quantity | G36: Unit Price | H36: Freight Cost | I36: Sub Total | J36: Tax | K36: Purchase Fee | L36: Estimate Amount | M36: Budget Amount | N36: January | O36: February | P36: March | Q36: April | R36: May | S36: June | T36: July | U36: August | V36: September | W36: October | X36: November | Y36: December
B37: (A) Guestrooms - Bathroom, Kitchen | H37: =SUM(H38:H49) -> 1 | I37: =SUM(I38:I49) -> 12151 | J37: =SUM(J38:J49) -> 880.9475 | K37: =SUM(K38:K49) -> 651.59738 | L37: =SUM(L38:L49) -> 13683.545 | M37: =SUM(M38:M49) -> 13683.545 | N37: =SUM(N38:N49) -> 13683.545 | O37: =SUM(O38:O49) -> 0 | ... Y37: =SUM(Y38:Y49) -> 0
B38: A1 | C38: Example | D38: Text | E38: QA | F38: 18 | G38: 675 | H38: 1 | I38: =(F38*G38)+H38 -> 12151 | J38: =I38*$D$20 -> 880.9475 | K38: =SUM(I38:J38)*5% -> 651.59738 | L38: =SUM(I38:K38) -> 13683.545 | M38: =SUM(N38, O38,P38,Q38,R38,S38,T38,U38,V38,W38,X38,Y38) -> 13683.545 | N38: =L38 -> 13683.545
B39: A2 | I39: =(F39*G39)+H39 -> 0 | J39: =I39*$D$20 -> 0 | K39: =SUM(I39:J39)*5% -> 0 | L39: =SUM(I39:K39) -> 0 | M39: =SUM(N39, O39,P39,Q39,R39,S39,T39,U39,V39,W39,X39,Y39) -> 0
B40: A3 | I40: =(F40*G40)+H40 -> 0 | J40: =I40*$D$20 -> 0 | K40: =SUM(I40:J40)*5% -> 0 | L40: =SUM(I40:K40) -> 0 | M40: =SUM(N40, O40,P40,Q40,R40,S40,T40,U40,V40,W40,X40,Y40) -> 0
B41: A4 | I41: =(F41*G41)+H41 -> 0 | J41: =I41*$D$20 -> 0 | K41: =SUM(I41:J41)*5% -> 0 | L41: =SUM(I41:K41) -> 0 | M41: =SUM(N41, O41,P41,Q41,R41,S41,T41,U41,V41,W41,X41,Y41) -> 0
B42: A5 | I42: =(F42*G42)+H42 -> 0 | J42: =I42*$D$20 -> 0 | K42: =SUM(I42:J42)*5% -> 0 | L42: =SUM(I42:K42) -> 0 | M42: =SUM(N42, O42,P42,Q42,R42,S42,T42,U42,V42,W42,X42,Y42) -> 0
B43: A6 | I43: =(F43*G43)+H43 -> 0 | J43: =I43*$D$20 -> 0 | K43: =SUM(I43:J43)*5% -> 0 | L43: =SUM(I43:K43) -> 0 | M43: =SUM(N43, O43,P43,Q43,R43,S43,T43,U43,V43,W43,X43,Y43) -> 0
B44: A7 | I44: =(F44*G44)+H44 -> 0 | J44: =I44*$D$20 -> 0 | K44: =SUM(I44:J44)*5% -> 0 | L44: =SUM(I44:K44) -> 0 | M44: =SUM(N44, O44,P44,Q44,R44,S44,T44,U44,V44,W44,X44,Y44) -> 0
B45: A8 | I45: =(F45*G45)+H45 -> 0 | J45: =I45*$D$20 -> 0 | K45: =SUM(I45:J45)*5% -> 0 | L45: =SUM(I45:K45) -> 0 | M45: =SUM(N45, O45,P45,Q45,R45,S45,T45,U45,V45,W45,X45,Y45) -> 0
B46: A9 | I46: =(F46*G46)+H46 -> 0 | J46: =I46*$D$20 -> 0 | K46: =SUM(I46:J46)*5% -> 0 | L46: =SUM(I46:K46) -> 0 | M46: =SUM(N46, O46,P46,Q46,R46,S46,T46,U46,V46,W46,X46,Y46) -> 0
B47: A10 | I47: =(F47*G47)+H47 -> 0 | J47: =I47*$D$20 -> 0 | K47: =SUM(I47:J47)*5% -> 0 | L47: =SUM(I47:K47) -> 0 | M47: =SUM(N47, O47,P47,Q47,R47,S47,T47,U47,V47,W47,X47,Y47) -> 0
B48: A11 | I48: =(F48*G48)+H48 -> 0 | J48: =I48*$D$20 -> 0 | K48: =SUM(I48:J48)*5% -> 0 | L48: =SUM(I48:K48) -> 0 | M48: =SUM(N48, O48,P48,Q48,R48,S48,T48,U48,V48,W48,X48,Y48) -> 0
B49: A12 | I49: =(F49*G49)+H49 -> 0 | J49: =I49*$D$20 -> 0 | K49: =SUM(I49:J49)*5% -> 0 | L49: =SUM(I49:K49) -> 0 | M49: =SUM(N49, O49,P49,Q49,R49,S49,T49,U49,V49,W49,X49,Y49) -> 0
B50: (B) Function Space - Meeting Banquet Space | H50: =SUM(H51:H62) -> 1 | I50: =SUM(I51:I62) -> 6401 | J50: =SUM(J51:J62) -> 464.0725 | K50: =SUM(K51:K62) -> 343.25363 | L50: =SUM(L51:L62) -> 7208.3261 | M50: =SUM(M51:M62) -> 7208.3261 | N50: =SUM(N51:N62) -> 7208.3261 | O50: =SUM(O51:O62) -> 0 | ... Y50: =SUM(Y51:Y62) -> 0
B51: B1 | C51: Example | D51: Text | E51: PIP | F51: 4 | G51: 1600 | H51: 1 | I51: =(F51*G51)+H51 -> 6401 | J51: =I51*$D$20 -> 464.0725 | K51: =SUM(I51:J51)*5% -> 343.25363 | L51: =SUM(I51:K51) -> 7208.3261 | M51: =SUM(N51, O51,P51,Q51,R51,S51,T51,U51,V51,W51,X51,Y51) -> 7208.3261 | N51: =L51 -> 7208.3261
B52: B2 | I52: =(F52*G52)+H52 -> 0 | J52: =I52*$D$20 -> 0 | K52: =SUM(I52:J52)*5% -> 0 | L52: =SUM(I52:K52) -> 0 | M52: =SUM(N52, O52,P52,Q52,R52,S52,T52,U52,V52,W52,X52,Y52) -> 0
B53: B3 | I53: =(F53*G53)+H53 -> 0 | J53: =I53*$D$20 -> 0 | K53: =SUM(I53:J53)*5% -> 0 | L53: =SUM(I53:K53) -> 0 | M53: =SUM(N53, O53,P53,Q53,R53,S53,T53,U53,V53,W53,X53,Y53) -> 0
B54: B4 | I54: =(F54*G54)+H54 -> 0 | J54: =I54*$D$20 -> 0 | K54: =SUM(I54:J54)*5% -> 0 | L54: =SUM(I54:K54) -> 0 | M54: =SUM(N54, O54,P54,Q54,R54,S54,T54,U54,V54,W54,X54,Y54) -> 0
B55: B5 | I55: =(F55*G55)+H55 -> 0 | J55: =I55*$D$20 -> 0 | K55: =SUM(I55:J55)*5% -> 0 | L55: =SUM(I55:K55) -> 0 | M55: =SUM(N55, O55,P55,Q55,R55,S55,T55,U55,V55,W55,X55,Y55) -> 0
B56: B6 | I56: =(F56*G56)+H56 -> 0 | J56: =I56*$D$20 -> 0 | K56: =SUM(I56:J56)*5% -> 0 | L56: =SUM(I56:K56) -> 0 | M56: =SUM(N56, O56,P56,Q56,R56,S56,T56,U56,V56,W56,X56,Y56) -> 0
B57: B7 | I57: =(F57*G57)+H57 -> 0 | J57: =I57*$D$20 -> 0 | K57: =SUM(I57:J57)*5% -> 0 | L57: =SUM(I57:K57) -> 0 | M57: =SUM(N57, O57,P57,Q57,R57,S57,T57,U57,V57,W57,X57,Y57) -> 0
B58: B8 | I58: =(F58*G58)+H58 -> 0 | J58: =I58*$D$20 -> 0 | K58: =SUM(I58:J58)*5% -> 0 | L58: =SUM(I58:K58) -> 0 | M58: =SUM(N58, O58,P58,Q58,R58,S58,T58,U58,V58,W58,X58,Y58) -> 0
B59: B9 | I59: =(F59*G59)+H59 -> 0 | J59: =I59*$D$20 -> 0 | K59: =SUM(I59:J59)*5% -> 0 | L59: =SUM(I59:K59) -> 0 | M59: =SUM(N59, O59,P59,Q59,R59,S59,T59,U59,V59,W59,X59,Y59) -> 0
B60: B10 | I60: =(F60*G60)+H60 -> 0 | J60: =I60*$D$20 -> 0 | K60: =SUM(I60:J60)*5% -> 0 | L60: =SUM(I60:K60) -> 0 | M60: =SUM(N60, O60,P60,Q60,R60,S60,T60,U60,V60,W60,X60,Y60) -> 0
B61: B11 | I61: =(F61*G61)+H61 -> 0 | J61: =I61*$D$20 -> 0 | K61: =SUM(I61:J61)*5% -> 0 | L61: =SUM(I61:K61) -> 0 | M61: =SUM(N61, O61,P61,Q61,R61,S61,T61,U61,V61,W61,X61,Y61) -> 0
B62: B12 | I62: =(F62*G62)+H62 -> 0 | J62: =I62*$D$20 -> 0 | K62: =SUM(I62:J62)*5% -> 0 | L62: =SUM(I62:K62) -> 0 | M62: =SUM(N62, O62,P62,Q62,R62,S62,T62,U62,V62,W62,X62,Y62) -> 0
B63: (C) Public Areas - Lobby, Pool, Fitness, Corridors | H63: =SUM(H64:H75) -> 1 | I63: =SUM(I64:I75) -> 601 | J63: =SUM(J64:J75) -> 43.5725 | K63: =SUM(K64:K75) -> 32.228625 | L63: =SUM(L64:L75) -> 676.80112 | M63: =SUM(M64:M75) -> 676.80112 | N63: =SUM(N64:N75) -> 676.80112 | O63: =SUM(O64:O75) -> 0 | ... Y63: =SUM(Y64:Y75) -> 0
B64: C1 | C64: Example | D64: Text | E64: PCA | F64: 2 | G64: 300 | H64: 1 | I64: =(F64*G64)+H64 -> 601 | J64: =I64*$D$20 -> 43.5725 | K64: =SUM(I64:J64)*5% -> 32.228625 | L64: =SUM(I64:K64) -> 676.80112 | M64: =SUM(N64, O64,P64,Q64,R64,S64,T64,U64,V64,W64,X64,Y64) -> 676.80112 | N64: =L64 -> 676.80112
B65: C2 | I65: =(F65*G65)+H65 -> 0 | J65: =I65*$D$20 -> 0 | K65: =SUM(I65:J65)*5% -> 0 | L65: =SUM(I65:K65) -> 0 | M65: =SUM(N65, O65,P65,Q65,R65,S65,T65,U65,V65,W65,X65,Y65) -> 0
B66: C3 | I66: =(F66*G66)+H66 -> 0 | J66: =I66*$D$20 -> 0 | K66: =SUM(I66:J66)*5% -> 0 | L66: =SUM(I66:K66) -> 0 | M66: =SUM(N66, O66,P66,Q66,R66,S66,T66,U66,V66,W66,X66,Y66) -> 0
B67: C4 | I67: =(F67*G67)+H67 -> 0 | J67: =I67*$D$20 -> 0 | K67: =SUM(I67:J67)*5% -> 0 | L67: =SUM(I67:K67) -> 0 | M67: =SUM(N67, O67,P67,Q67,R67,S67,T67,U67,V67,W67,X67,Y67) -> 0
B68: C5 | I68: =(F68*G68)+H68 -> 0 | J68: =I68*$D$20 -> 0 | K68: =SUM(I68:J68)*5% -> 0 | L68: =SUM(I68:K68) -> 0 | M68: =SUM(N68, O68,P68,Q68,R68,S68,T68,U68,V68,W68,X68,Y68) -> 0
B69: C6 | I69: =(F69*G69)+H69 -> 0 | J69: =I69*$D$20 -> 0 | K69: =SUM(I69:J69)*5% -> 0 | L69: =SUM(I69:K69) -> 0 | M69: =SUM(N69, O69,P69,Q69,R69,S69,T69,U69,V69,W69,X69,Y69) -> 0
B70: C7 | I70: =(F70*G70)+H70 -> 0 | J70: =I70*$D$20 -> 0 | K70: =SUM(I70:J70)*5% -> 0 | L70: =SUM(I70:K70) -> 0 | M70: =SUM(N70, O70,P70,Q70,R70,S70,T70,U70,V70,W70,X70,Y70) -> 0
B71: C8 | I71: =(F71*G71)+H71 -> 0 | J71: =I71*$D$20 -> 0 | K71: =SUM(I71:J71)*5% -> 0 | L71: =SUM(I71:K71) -> 0 | M71: =SUM(N71, O71,P71,Q71,R71,S71,T71,U71,V71,W71,X71,Y71) -> 0
B72: C9 | I72: =(F72*G72)+H72 -> 0 | J72: =I72*$D$20 -> 0 | K72: =SUM(I72:J72)*5% -> 0 | L72: =SUM(I72:K72) -> 0 | M72: =SUM(N72, O72,P72,Q72,R72,S72,T72,U72,V72,W72,X72,Y72) -> 0
B73: C10 | I73: =(F73*G73)+H73 -> 0 | J73: =I73*$D$20 -> 0 | K73: =SUM(I73:J73)*5% -> 0 | L73: =SUM(I73:K73) -> 0 | M73: =SUM(N73, O73,P73,Q73,R73,S73,T73,U73,V73,W73,X73,Y73) -> 0
B74: C11 | I74: =(F74*G74)+H74 -> 0 | J74: =I74*$D$20 -> 0 | K74: =SUM(I74:J74)*5% -> 0 | L74: =SUM(I74:K74) -> 0 | M74: =SUM(N74, O74,P74,Q74,R74,S74,T74,U74,V74,W74,X74,Y74) -> 0
B75: C12 | I75: =(F75*G75)+H75 -> 0 | J75: =I75*$D$20 -> 0 | K75: =SUM(I75:J75)*5% -> 0 | L75: =SUM(I75:K75) -> 0 | M75: =SUM(N75, O75,P75,Q75,R75,S75,T75,U75,V75,W75,X75,Y75) -> 0
B76: (D) Technology - Computer Systems | H76: =SUM(H77:H88) -> 1 | I76: =SUM(I77:I88) -> 6001 | J76: =SUM(J77:J88) -> 435.0725 | K76: =SUM(K77:K88) -> 321.80363 | L76: =SUM(L77:L88) -> 6757.8761 | M76: =SUM(M77:M88) -> 6757.8761 | N76: =SUM(N77:N88) -> 6757.8761 | O76: =SUM(O77:O88) -> 0 | ... Y76: =SUM(Y77:Y88) -> 0
B77: D1 | C77: Example | D77: Text | E77: Other | F77: 2 | G77: 3000 | H77: 1 | I77: =(F77*G77)+H77 -> 6001 | J77: =I77*$D$20 -> 435.0725 | K77: =SUM(I77:J77)*5% -> 321.80363 | L77: =SUM(I77:K77) -> 6757.8761 | M77: =SUM(N77, O77,P77,Q77,R77,S77,T77,U77,V77,W77,X77,Y77) -> 6757.8761 | N77: =L77 -> 6757.8761
B78: D2 | I78: =(F78*G78)+H78 -> 0 | J78: =I78*$D$20 -> 0 | K78: =SUM(I78:J78)*5% -> 0 | L78: =SUM(I78:K78) -> 0 | M78: =SUM(N78, O78,P78,Q78,R78,S78,T78,U78,V78,W78,X78,Y78) -> 0
B79: D3 | I79: =(F79*G79)+H79 -> 0 | J79: =I79*$D$20 -> 0 | K79: =SUM(I79:J79)*5% -> 0 | L79: =SUM(I79:K79) -> 0 | M79: =SUM(N79, O79,P79,Q79,R79,S79,T79,U79,V79,W79,X79,Y79) -> 0
B80: D4 | I80: =(F80*G80)+H80 -> 0 | J80: =I80*$D$20 -> 0 | K80: =SUM(I80:J80)*5% -> 0 | L80: =SUM(I80:K80) -> 0 | M80: =SUM(N80, O80,P80,Q80,R80,S80,T80,U80,V80,W80,X80,Y80) -> 0
B81: D5 | I81: =(F81*G81)+H81 -> 0 | J81: =I81*$D$20 -> 0 | K81: =SUM(I81:J81)*5% -> 0 | L81: =SUM(I81:K81) -> 0 | M81: =SUM(N81, O81,P81,Q81,R81,S81,T81,U81,V81,W81,X81,Y81) -> 0
B82: D6 | I82: =(F82*G82)+H82 -> 0 | J82: =I82*$D$20 -> 0 | K82: =SUM(I82:J82)*5% -> 0 | L82: =SUM(I82:K82) -> 0 | M82: =SUM(N82, O82,P82,Q82,R82,S82,T82,U82,V82,W82,X82,Y82) -> 0
B83: D7 | I83: =(F83*G83)+H83 -> 0 | J83: =I83*$D$20 -> 0 | K83: =SUM(I83:J83)*5% -> 0 | L83: =SUM(I83:K83) -> 0 | M83: =SUM(N83, O83,P83,Q83,R83,S83,T83,U83,V83,W83,X83,Y83) -> 0
B84: D8 | I84: =(F84*G84)+H84 -> 0 | J84: =I84*$D$20 -> 0 | K84: =SUM(I84:J84)*5% -> 0 | L84: =SUM(I84:K84) -> 0 | M84: =SUM(N84, O84,P84,Q84,R84,S84,T84,U84,V84,W84,X84,Y84) -> 0
B85: D9 | I85: =(F85*G85)+H85 -> 0 | J85: =I85*$D$20 -> 0 | K85: =SUM(I85:J85)*5% -> 0 | L85: =SUM(I85:K85) -> 0 | M85: =SUM(N85, O85,P85,Q85,R85,S85,T85,U85,V85,W85,X85,Y85) -> 0
B86: D10 | I86: =(F86*G86)+H86 -> 0 | J86: =I86*$D$20 -> 0 | K86: =SUM(I86:J86)*5% -> 0 | L86: =SUM(I86:K86) -> 0 | M86: =SUM(N86, O86,P86,Q86,R86,S86,T86,U86,V86,W86,X86,Y86) -> 0
B87: D11 | I87: =(F87*G87)+H87 -> 0 | J87: =I87*$D$20 -> 0 | K87: =SUM(I87:J87)*5% -> 0 | L87: =SUM(I87:K87) -> 0 | M87: =SUM(N87, O87,P87,Q87,R87,S87,T87,U87,V87,W87,X87,Y87) -> 0
B88: D12 | I88: =(F88*G88)+H88 -> 0 | J88: =I88*$D$20 -> 0 | K88: =SUM(I88:J88)*5% -> 0 | L88: =SUM(I88:K88) -> 0 | M88: =SUM(N88, O88,P88,Q88,R88,S88,T88,U88,V88,W88,X88,Y88) -> 0
B89: (E) Back of House - Administrative, Laundry | H89: =SUM(H90:H101) -> 1 | I89: =SUM(I90:I101) -> 1601 | J89: =SUM(J90:J101) -> 116.0725 | K89: =SUM(K90:K101) -> 85.853625 | L89: =SUM(L90:L101) -> 1802.9261 | M89: =SUM(M90:M101) -> 1802.9261 | N89: =SUM(N90:N101) -> 1802.9261 | O89: =SUM(O90:O101) -> 0 | ... Y89: =SUM(Y90:Y101) -> 0
B90: E1 | C90: Example | D90: Text | E90: QA | F90: 1 | G90: 1600 | H90: 1 | I90: =(F90*G90)+H90 -> 1601 | J90: =I90*$D$20 -> 116.0725 | K90: =SUM(I90:J90)*5% -> 85.853625 | L90: =SUM(I90:K90) -> 1802.9261 | M90: =SUM(N90, O90,P90,Q90,R90,S90,T90,U90,V90,W90,X90,Y90) -> 1802.9261 | N90: =L90 -> 1802.9261
B91: E2 | I91: =(F91*G91)+H91 -> 0 | J91: =I91*$D$20 -> 0 | K91: =SUM(I91:J91)*5% -> 0 | L91: =SUM(I91:K91) -> 0 | M91: =SUM(N91, O91,P91,Q91,R91,S91,T91,U91,V91,W91,X91,Y91) -> 0
B92: E3 | I92: =(F92*G92)+H92 -> 0 | J92: =I92*$D$20 -> 0 | K92: =SUM(I92:J92)*5% -> 0 | L92: =SUM(I92:K92) -> 0 | M92: =SUM(N92, O92,P92,Q92,R92,S92,T92,U92,V92,W92,X92,Y92) -> 0
B93: E4 | I93: =(F93*G93)+H93 -> 0 | J93: =I93*$D$20 -> 0 | K93: =SUM(I93:J93)*5% -> 0 | L93: =SUM(I93:K93) -> 0 | M93: =SUM(N93, O93,P93,Q93,R93,S93,T93,U93,V93,W93,X93,Y93) -> 0
B94: E5 | I94: =(F94*G94)+H94 -> 0 | J94: =I94*$D$20 -> 0 | K94: =SUM(I94:J94)*5% -> 0 | L94: =SUM(I94:K94) -> 0 | M94: =SUM(N94, O94,P94,Q94,R94,S94,T94,U94,V94,W94,X94,Y94) -> 0
B95: E6 | I95: =(F95*G95)+H95 -> 0 | J95: =I95*$D$20 -> 0 | K95: =SUM(I95:J95)*5% -> 0 | L95: =SUM(I95:K95) -> 0 | M95: =SUM(N95, O95,P95,Q95,R95,S95,T95,U95,V95,W95,X95,Y95) -> 0
B96: E7 | I96: =(F96*G96)+H96 -> 0 | J96: =I96*$D$20 -> 0 | K96: =SUM(I96:J96)*5% -> 0 | L96: =SUM(I96:K96) -> 0 | M96: =SUM(N96, O96,P96,Q96,R96,S96,T96,U96,V96,W96,X96,Y96) -> 0
B97: E8 | I97: =(F97*G97)+H97 -> 0 | J97: =I97*$D$20 -> 0 | K97: =SUM(I97:J97)*5% -> 0 | L97: =SUM(I97:K97) -> 0 | M97: =SUM(N97, O97,P97,Q97,R97,S97,T97,U97,V97,W97,X97,Y97) -> 0
B98: E9 | I98: =(F98*G98)+H98 -> 0 | J98: =I98*$D$20 -> 0 | K98: =SUM(I98:J98)*5% -> 0 | L98: =SUM(I98:K98) -> 0 | M98: =SUM(N98, O98,P98,Q98,R98,S98,T98,U98,V98,W98,X98,Y98) -> 0
B99: E10 | I99: =(F99*G99)+H99 -> 0 | J99: =I99*$D$20 -> 0 | K99: =SUM(I99:J99)*5% -> 0 | L99: =SUM(I99:K99) -> 0 | M99: =SUM(N99, O99,P99,Q99,R99,S99,T99,U99,V99,W99,X99,Y99) -> 0
B100: E11 | I100: =(F100*G100)+H100 -> 0 | J100: =I100*$D$20 -> 0 | K100: =SUM(I100:J100)*5% -> 0 | L100: =SUM(I100:K100) -> 0 | M100: =SUM(N100, O100,P100,Q100,R100,S100,T100,U100,V100,W100,X100,Y100) -> 0
B101: E12 | I101: =(F101*G101)+H101 -> 0 | J101: =I101*$D$20 -> 0 | K101: =SUM(I101:J101)*5% -> 0 | L101: =SUM(I101:K101) -> 0 | M101: =SUM(N101, O101,P101,Q101,R101,S101,T101,U101,V101,W101,X101,Y101) -> 0
B102: (F) Building - Site, Exterior, Mechanical | H102: =SUM(H103:H114) -> 1 | I102: =SUM(I103:I114) -> 1601 | J102: =SUM(J103:J114) -> 116.0725 | K102: =SUM(K103:K114) -> 85.853625 | L102: =SUM(L103:L114) -> 1802.9261 | M102: =SUM(M103:M114) -> 1802.9261 | N102: =SUM(N103:N114) -> 1802.9261 | O102: =SUM(O103:O114) -> 0 | ... Y102: =SUM(Y103:Y114) -> 0
B103: F1 | C103: Example | D103: Text | E103: PIP | F103: 1 | G103: 1600 | H103: 1 | I103: =(F103*G103)+H103 -> 1601 | J103: =I103*$D$20 -> 116.0725 | K103: =SUM(I103:J103)*5% -> 85.853625 | L103: =SUM(I103:K103) -> 1802.9261 | M103: =SUM(N103, O103,P103,Q103,R103,S103,T103,U103,V103,W103,X103,Y103) -> 1802.9261 | N103: =L103 -> 1802.9261
B104: F2 | I104: =(F104*G104)+H104 -> 0 | J104: =I104*$D$20 -> 0 | K104: =SUM(I104:J104)*5% -> 0 | L104: =SUM(I104:K104) -> 0 | M104: =SUM(N104, O104,P104,Q104,R104,S104,T104,U104,V104,W104,X104,Y104) -> 0
B105: F3 | I105: =(F105*G105)+H105 -> 0 | J105: =I105*$D$20 -> 0 | K105: =SUM(I105:J105)*5% -> 0 | L105: =SUM(I105:K105) -> 0 | M105: =SUM(N105, O105,P105,Q105,R105,S105,T105,U105,V105,W105,X105,Y105) -> 0
B106: F4 | I106: =(F106*G106)+H106 -> 0 | J106: =I106*$D$20 -> 0 | K106: =SUM(I106:J106)*5% -> 0 | L106: =SUM(I106:K106) -> 0 | M106: =SUM(N106, O106,P106,Q106,R106,S106,T106,U106,V106,W106,X106,Y106) -> 0
B107: F5 | I107: =(F107*G107)+H107 -> 0 | J107: =I107*$D$20 -> 0 | K107: =SUM(I107:J107)*5% -> 0 | L107: =SUM(I107:K107) -> 0 | M107: =SUM(N107, O107,P107,Q107,R107,S107,T107,U107,V107,W107,X107,Y107) -> 0
B108: F6 | I108: =(F108*G108)+H108 -> 0 | J108: =I108*$D$20 -> 0 | K108: =SUM(I108:J108)*5% -> 0 | L108: =SUM(I108:K108) -> 0 | M108: =SUM(N108, O108,P108,Q108,R108,S108,T108,U108,V108,W108,X108,Y108) -> 0
B109: F7 | I109: =(F109*G109)+H109 -> 0 | J109: =I109*$D$20 -> 0 | K109: =SUM(I109:J109)*5% -> 0 | L109: =SUM(I109:K109) -> 0 | M109: =SUM(N109, O109,P109,Q109,R109,S109,T109,U109,V109,W109,X109,Y109) -> 0
B110: F8 | I110: =(F110*G110)+H110 -> 0 | J110: =I110*$D$20 -> 0 | K110: =SUM(I110:J110)*5% -> 0 | L110: =SUM(I110:K110) -> 0 | M110: =SUM(N110, O110,P110,Q110,R110,S110,T110,U110,V110,W110,X110,Y110) -> 0
B111: F9 | I111: =(F111*G111)+H111 -> 0 | J111: =I111*$D$20 -> 0 | K111: =SUM(I111:J111)*5% -> 0 | L111: =SUM(I111:K111) -> 0 | M111: =SUM(N111, O111,P111,Q111,R111,S111,T111,U111,V111,W111,X111,Y111) -> 0
B112: F10 | I112: =(F112*G112)+H112 -> 0 | J112: =I112*$D$20 -> 0 | K112: =SUM(I112:J112)*5% -> 0 | L112: =SUM(I112:K112) -> 0 | M112: =SUM(N112, O112,P112,Q112,R112,S112,T112,U112,V112,W112,X112,Y112) -> 0
B113: F11 | I113: =(F113*G113)+H113 -> 0 | J113: =I113*$D$20 -> 0 | K113: =SUM(I113:J113)*5% -> 0 | L113: =SUM(I113:K113) -> 0 | M113: =SUM(N113, O113,P113,Q113,R113,S113,T113,U113,V113,W113,X113,Y113) -> 0
B114: F12 | I114: =(F114*G114)+H114 -> 0 | J114: =I114*$D$20 -> 0 | K114: =SUM(I114:J114)*5% -> 0 | L114: =SUM(I114:K114) -> 0 | M114: =SUM(N114, O114,P114,Q114,R114,S114,T114,U114,V114,W114,X114,Y114) -> 0
B115: QA Total | H115: =SUMIF($E$38:$E$49:$E$51:$E$62:$E$64:$E$75:$E$77:$E$88:$E$90:$E$101:$E$103:$E$114,"QA",H$38:H$49:H$51:H$62:H$64:H$75:H$77:H$88:H$90:H$101:H$103:H$114) -> 2 | I115: =SUMIF($E$38:$E$49:$E$51:$E$62:$E$64:$E$75:$E$77:$E$88:$E$90:$E$101:$E$103:$E$114,"QA",I$38:I$49:I$51:I$62:I$64:I$75:I$77:I$88:I$90:I$101:I$103:I$114) -> 13752 | J115: =SUMIF($E$38:$E$49:$E$51:$E$62:$E$64:$E$75:$E$77:$E$88:$E$90:$E$101:$E$103:$E$114,"QA",J$38:J$49:J$51:J$62:J$64:J$75:J$77:J$88:J$90:J$101:J$103:J$114) -> 997.02 | K115: =SUMIF($E$38:$E$49:$E$51:$E$62:$E$64:$E$75:$E$77:$E$88:$E$90:$E$101:$E$103:$E$114,"QA",K$38:K$49:K$51:K$62:K$64:K$75:K$77:K$88:K$90:K$101:K$103:K$114) -> 737.451 | L115: =SUMIF($E$38:$E$49:$E$51:$E$62:$E$64:$E$75:$E$77:$E$88:$E$90:$E$101:$E$103:$E$114,"QA",L$38:L$49:L$51:L$62:L$64:L$75:L$77:L$88:L$90:L$101:L$103:L$114) -> 15486.471 | M115: =SUMIF($E$38:$E$49:$E$51:$E$62:$E$64:$E$75:$E$77:$E$88:$E$90:$E$101:$E$103:$E$114,"QA",M$38:M$49:M$51:M$62:M$64:M$75:M$77:M$88:M$90:M$101:M$103:M$114) -> 15486.471 | N115: =SUMIF($E$38:$E$49:$E$51:$E$62:$E$64:$E$75:$E$77:$E$88:$E$90:$E$101:$E$103:$E$114,"QA",N$38:N$49:N$51:N$62:N$64:N$75:N$77:N$88:N$90:N$101:N$103:N$114) -> 15486.471 | O115: =SUMIF($E$38:$E$49:$E$51:$E$62:$E$64:$E$75:$E$77:$E$88:$E$90:$E$101:$E$103:$E$114,"QA",O$38:O$49:O$51:O$62:O$64:O$75:O$77:O$88:O$90:O$101:O$103:O$114) -> 0 | ... Y115: =SUMIF($E$38:$E$49:$E$51:$E$62:$E$64:$E$75:$E$77:$E$88:$E$90:$E$101:$E$103:$E$114,"QA",Y$38:Y$49:Y$51:Y$62:Y$64:Y$75:Y$77:Y$88:Y$90:Y$101:Y$103:Y$114) -> 0
B116: PIP Total | H116: =SUMIF($E$38:$E$49:$E$51:$E$62:$E$64:$E$75:$E$77:$E$88:$E$90:$E$101:$E$103:$E$114,"PIP",H$38:H$49:H$51:H$62:H$64:H$75:H$77:H$88:H$90:H$101:H$103:H$114) -> 2 | I116: =SUMIF($E$38:$E$49:$E$51:$E$62:$E$64:$E$75:$E$77:$E$88:$E$90:$E$101:$E$103:$E$114,"PIP",I$38:I$49:I$51:I$62:I$64:I$75:I$77:I$88:I$90:I$101:I$103:I$114) -> 8002 | J116: =SUMIF($E$38:$E$49:$E$51:$E$62:$E$64:$E$75:$E$77:$E$88:$E$90:$E$101:$E$103:$E$114,"PIP",J$38:J$49:J$51:J$62:J$64:J$75:J$77:J$88:J$90:J$101:J$103:J$114) -> 580.145 | K116: =SUMIF($E$38:$E$49:$E$51:$E$62:$E$64:$E$75:$E$77:$E$88:$E$90:$E$101:$E$103:$E$114,"PIP",K$38:K$49:K$51:K$62:K$64:K$75:K$77:K$88:K$90:K$101:K$103:K$114) -> 429.10725 | L116: =SUMIF($E$38:$E$49:$E$51:$E$62:$E$64:$E$75:$E$77:$E$88:$E$90:$E$101:$E$103:$E$114,"PIP",L$38:L$49:L$51:L$62:L$64:L$75:L$77:L$88:L$90:L$101:L$103:L$114) -> 9011.2523 | M116: =SUMIF($E$38:$E$49:$E$51:$E$62:$E$64:$E$75:$E$77:$E$88:$E$90:$E$101:$E$103:$E$114,"PIP",M$38:M$49:M$51:M$62:M$64:M$75:M$77:M$88:M$90:M$101:M$103:M$114) -> 9011.2523 | N116: =SUMIF($E$38:$E$49:$E$51:$E$62:$E$64:$E$75:$E$77:$E$88:$E$90:$E$101:$E$103:$E$114,"PIP",N$38:N$49:N$51:N$62:N$64:N$75:N$77:N$88:N$90:N$101:N$103:N$114) -> 9011.2523 | O116: =SUMIF($E$38:$E$49:$E$51:$E$62:$E$64:$E$75:$E$77:$E$88:$E$90:$E$101:$E$103:$E$114,"PIP",O$38:O$49:O$51:O$62:O$64:O$75:O$77:O$88:O$90:O$101:O$103:O$114) -> 0 | ... Y116: =SUMIF($E$38:$E$49:$E$51:$E$62:$E$64:$E$75:$E$77:$E$88:$E$90:$E$101:$E$103:$E$114,"PIP",Y$38:Y$49:Y$51:Y$62:Y$64:Y$75:Y$77:Y$88:Y$90:Y$101:Y$103:Y$114) -> 0
B117: PCA Total | H117: =SUMIF($E$38:$E$49:$E$51:$E$62:$E$64:$E$75:$E$77:$E$88:$E$90:$E$101:$E$103:$E$114,"PCA",H$38:H$49:H$51:H$62:H$64:H$75:H$77:H$88:H$90:H$101:H$103:H$114) -> 1 | I117: =SUMIF($E$38:$E$49:$E$51:$E$62:$E$64:$E$75:$E$77:$E$88:$E$90:$E$101:$E$103:$E$114,"PCA",I$38:I$49:I$51:I$62:I$64:I$75:I$77:I$88:I$90:I$101:I$103:I$114) -> 601 | J117: =SUMIF($E$38:$E$49:$E$51:$E$62:$E$64:$E$75:$E$77:$E$88:$E$90:$E$101:$E$103:$E$114,"PCA",J$38:J$49:J$51:J$62:J$64:J$75:J$77:J$88:J$90:J$101:J$103:J$114) -> 43.5725 | K117: =SUMIF($E$38:$E$49:$E$51:$E$62:$E$64:$E$75:$E$77:$E$88:$E$90:$E$101:$E$103:$E$114,"PCA",K$38:K$49:K$51:K$62:K$64:K$75:K$77:K$88:K$90:K$101:K$103:K$114) -> 32.228625 | L117: =SUMIF($E$38:$E$49:$E$51:$E$62:$E$64:$E$75:$E$77:$E$88:$E$90:$E$101:$E$103:$E$114,"PCA",L$38:L$49:L$51:L$62:L$64:L$75:L$77:L$88:L$90:L$101:L$103:L$114) -> 676.80112 | M117: =SUMIF($E$38:$E$49:$E$51:$E$62:$E$64:$E$75:$E$77:$E$88:$E$90:$E$101:$E$103:$E$114,"PCA",M$38:M$49:M$51:M$62:M$64:M$75:M$77:M$88:M$90:M$101:M$103:M$114) -> 676.80112 | N117: =SUMIF($E$38:$E$49:$E$51:$E$62:$E$64:$E$75:$E$77:$E$88:$E$90:$E$101:$E$103:$E$114,"PCA",N$38:N$49:N$51:N$62:N$64:N$75:N$77:N$88:N$90:N$101:N$103:N$114) -> 676.80112 | O117: =SUMIF($E$38:$E$49:$E$51:$E$62:$E$64:$E$75:$E$77:$E$88:$E$90:$E$101:$E$103:$E$114,"PCA",O$38:O$49:O$51:O$62:O$64:O$75:O$77:O$88:O$90:O$101:O$103:O$114) -> 0 | ... Y117: =SUMIF($E$38:$E$49:$E$51:$E$62:$E$64:$E$75:$E$77:$E$88:$E$90:$E$101:$E$103:$E$114,"PCA",Y$38:Y$49:Y$51:Y$62:Y$64:Y$75:Y$77:Y$88:Y$90:Y$101:Y$103:Y$114) -> 0
B118: Other Total | H118: =SUMIF($E$38:$E$49:$E$51:$E$62:$E$64:$E$75:$E$77:$E$88:$E$90:$E$101:$E$103:$E$114,"Other",H$38:H$49:H$51:H$62:H$64:H$75:H$77:H$88:H$90:H$101:H$103:H$114) -> 1 | I118: =SUMIF($E$38:$E$49:$E$51:$E$62:$E$64:$E$75:$E$77:$E$88:$E$90:$E$101:$E$103:$E$114,"Other",I$38:I$49:I$51:I$62:I$64:I$75:I$77:I$88:I$90:I$101:I$103:I$114) -> 6001 | J118: =SUMIF($E$38:$E$49:$E$51:$E$62:$E$64:$E$75:$E$77:$E$88:$E$90:$E$101:$E$103:$E$114,"Other",J$38:J$49:J$51:J$62:J$64:J$75:J$77:J$88:J$90:J$101:J$103:J$114) -> 435.0725 | K118: =SUMIF($E$38:$E$49:$E$51:$E$62:$E$64:$E$75:$E$77:$E$88:$E$90:$E$101:$E$103:$E$114,"Other",K$38:K$49:K$51:K$62:K$64:K$75:K$77:K$88:K$90:K$101:K$103:K$114) -> 321.80363 | L118: =SUMIF($E$38:$E$49:$E$51:$E$62:$E$64:$E$75:$E$77:$E$88:$E$90:$E$101:$E$103:$E$114,"Other",L$38:L$49:L$51:L$62:L$64:L$75:L$77:L$88:L$90:L$101:L$103:L$114) -> 6757.8761 | M118: =SUMIF($E$38:$E$49:$E$51:$E$62:$E$64:$E$75:$E$77:$E$88:$E$90:$E$101:$E$103:$E$114,"Other",M$38:M$49:M$51:M$62:M$64:M$75:M$77:M$88:M$90:M$101:M$103:M$114) -> 6757.8761 | N118: =SUMIF($E$38:$E$49:$E$51:$E$62:$E$64:$E$75:$E$77:$E$88:$E$90:$E$101:$E$103:$E$114,"Other",N$38:N$49:N$51:N$62:N$64:N$75:N$77:N$88:N$90:N$101:N$103:N$114) -> 6757.8761 | O118: =SUMIF($E$38:$E$49:$E$51:$E$62:$E$64:$E$75:$E$77:$E$88:$E$90:$E$101:$E$103:$E$114,"Other",O$38:O$49:O$51:O$62:O$64:O$75:O$77:O$88:O$90:O$101:O$103:O$114) -> 0 | ... Y118: =SUMIF($E$38:$E$49:$E$51:$E$62:$E$64:$E$75:$E$77:$E$88:$E$90:$E$101:$E$103:$E$114,"Other",Y$38:Y$49:Y$51:Y$62:Y$64:Y$75:Y$77:Y$88:Y$90:Y$101:Y$103:Y$114) -> 0
...
