Workbook
Name Month: Summary!$V$2
Name Property: Summary!$V$1
Name Property_Code: Summary!$V$1
Name Year: Summary!$V$3
Name YTDMonth: Summary!$V$4

Sheet Summary
V1: ANG | W1: <- Property Code
C2: Angler's | V2: Apr | W2: <- Month
C3: STATEMENT OF INCOME | V3: 2025 | W3: <- Year
C4: ="FOR THE PERIOD ENDING "&UPPER($V$2)&" "&Year -> FOR THE PERIOD ENDING APR 2025 | V4: =Month&"YTD" -> AprYTD
D6: =Year&" "&UPPER(Month)&" - PERIODIC" -> 2025 APR - PERIODIC | M6: =Year&" "&UPPER(Month)&" - YEAR TO DATE" -> 2025 APR - YEAR TO DATE
D7: Actual | F7: Budget | H7: VARIANCE | I7: Actual - Last Year | K7: VARIANCE | M7: Actual | O7: Budget | Q7: VARIANCE | R7: Actual - Last Year | T7: VARIANCE
D8: $ | E8: % | F8: $ | G8: % | H8: $ | I8: Actual | J8: % | K8: $ | M8: $ | N8: % | O8: $ | P8: % | Q8: $ | R8: Actual | S8: % | T8: $
B9: Total Rooms Available - 100 | C9: Available Rooms | D9: 3960 | F9: 3960 | H9: =+D9-F9 -> 0 | I9: 3960 | K9: =+(D9-I9) -> 0 | M9: 15840 | O9: 15840 | Q9: =+M9-O9 -> 0 | R9: 15972 | T9: =+(M9-R9) -> -132
B10: Total Rooms Sold - 100 | C10: Total Rooms Sold | D10: 3684 | F10: 3645 | H10: =+D10-F10 -> 39 | I10: 3692 | K10: =+(D10-I10) -> -8 | M10: 14556 | O10: 14563 | Q10: =+M10-O10 -> -7 | R10: 14696 | T10: =+(M10-R10) -> -140
C11: Occupancy | D11: =D10/D9 -> 0.93030303 | F11: =F10/F9 -> 0.92045455 | H11: =+(D11-F11)*100 -> 0.98484848 | I11: =I10/I9 -> 0.93232323 | K11: =+(D11-I11)*100 -> -0.2020202 | M11: =M10/M9 -> 0.91893939 | O11: =O10/O9 -> 0.91938131 | Q11: =+(M11-O11)*100 -> -0.044191919 | R11: =R10/R9 -> 0.92011019 | T11: =+(M11-R11)*100 -> -0.11707989
C12: Average Daily Rate | D12: =D15/D10 -> 266.56628 | F12: =F15/F10 -> 263.2116 | H12: =+D12-F12 -> 3.3546817 | I12: =I15/I10 -> 258.44728 | K12: =+(D12-I12) -> 8.1190006 | M12: =M15/M10 -> 295.51506 | O12: =O15/O10 -> 307.02472 | Q12: =+M12-O12 -> -11.509669 | R12: =R15/R10 -> 301.98569 | T12: =+(M12-R12) -> -6.4706296
C13: Revenue per Available Room | D13: =D11*D12 -> 247.98742 | F13: =F11*F12 -> 242.27432 | H13: =+D13-F13 -> 5.7131061 | I13: =I11*I12 -> 240.95641 | K13: =+(D13-I13) -> 7.0310152 | M13: =M11*M12 -> 271.56043 | O13: =O11*O12 -> 282.27279 | Q13: =+M13-O13 -> -10.712369 | R13: =R11*R12 -> 277.86011 | T13: =+(M13-R13) -> -6.2996809
C14: Revenues
B15: Total Revenue - 100 | C15: Rooms | D15: 982030.19 | E15: =+IFERROR(D15/D$19,"") -> 0.65086039 | F15: 959406.29 | G15: =+IFERROR(F15/F$19,"") -> 0.631665 | H15: =+D15-F15 -> 22623.9 | I15: 954187.37 | J15: =+IFERROR(I15/I$19,"") -> 0.72319515 | K15: =+(D15-I15) -> 27842.82 | M15: 4301517.2 | N15: =+IFERROR(M15/M$19,"") -> 0.68394804 | O15: 4471201.1 | P15: =+IFERROR(O15/O$19,"") -> 0.66098689 | Q15: =+M15-O15 -> -169683.92 | R15: 4437981.6 | S15: =+IFERROR(R15/R$19,"") -> 0.75674011 | T15: =+(M15-R15) -> -136464.48
B16: Total Revenue - 200 | C16: Food & Beverage | D16: 379131.93 | E16: =+IFERROR(D16/D$19,"") -> 0.25127736 | F16: 437605.85 | G16: =+IFERROR(F16/F$19,"") -> 0.288116 | H16: =+D16-F16 -> -58473.92 | I16: 250971.01 | J16: =+IFERROR(I16/I$19,"") -> 0.19021528 | K16: =+(D16-I16) -> 128160.92 | M16: 1523965.8 | N16: =+IFERROR(M16/M$19,"") -> 0.24231297 | O16: 1792694 | P16: =+IFERROR(O16/O$19,"") -> 0.26501766 | Q16: =+M16-O16 -> -268728.2 | R16: 916590.74 | S16: =+IFERROR(R16/R$19,"") -> 0.15629199 | T16: =+(M16-R16) -> 607375.05
B17: Total Revenue - 300 | C17: Other Operated Departments | D17: 2948.44 | E17: =+IFERROR(D17/D$19,"") -> 0.0019541383 | F17: 1557.87 | G17: =+IFERROR(F17/F$19,"") -> 0.0010256885 | H17: =+D17-F17 -> 1390.57 | I17: 1461.55 | J17: =+IFERROR(I17/I$19,"") -> 0.0011077341 | K17: =+(D17-I17) -> 1486.89 | M17: 9874.14 | N17: =+IFERROR(M17/M$19,"") -> 0.0015700039 | O17: 6224.22 | P17: =+IFERROR(O17/O$19,"") -> 0.0009201393 | Q17: =+M17-O17 -> 3649.92 | R17: 7206.75 | S17: =+IFERROR(R17/R$19,"") -> 0.0012288552 | T17: =+(M17-R17) -> 2667.39
B18: Total Revenue - 400 | C18: Miscellaneous Income | D18: 144707.94 | E18: =+IFERROR(D18/D$19,"") -> 0.095908116 | F18: 120283 | G18: =+IFERROR(F18/F$19,"") -> 0.079193312 | H18: =+D18-F18 -> 24424.94 | I18: 112785.17 | J18: =+IFERROR(I18/I$19,"") -> 0.085481836 | K18: =+(D18-I18) -> 31922.77 | M18: 453888.45 | N18: =+IFERROR(M18/M$19,"") -> 0.072168982 | O18: 494313 | P18: =+IFERROR(O18/O$19,"") -> 0.073075312 | Q18: =+M18-O18 -> -40424.55 | R18: 502825.58 | S18: =+IFERROR(R18/R$19,"") -> 0.085739041 | T18: =+(M18-R18) -> -48937.13
B19: Total Revenue - 000 | C19: Total Revenues | D19: =+SUM(D15:D18) -> 1508818.5 | E19: =+IFERROR(D19/D$19,"") -> 1 | F19: =+SUM(F15:F18) -> 1518853 | G19: =+IFERROR(F19/F$19,"") -> 1 | H19: =+D19-F19 -> -10034.51 | I19: =+SUM(I15:I18) -> 1319405.1 | J19: =+IFERROR(I19/I$19,"") -> 1 | K19: =+(D19-I19) -> 189413.4 | M19: =+SUM(M15:M18) -> 6289245.5 | N19: =+IFERROR(M19/M$19,"") -> 1 | O19: =+SUM(O15:O18) -> 6764432.3 | P19: =+IFERROR(O19/O$19,"") -> 1 | Q19: =+M19-O19 -> -475186.75 | R19: =+SUM(R15:R18) -> 5864604.7 | S19: =+IFERROR(R19/R$19,"") -> 1 | T19: =+(M19-R19) -> 424640.83
E20: TRUE | G20: TRUE | J20: TRUE | N20: TRUE | P20: TRUE | S20: TRUE
C21: Departmental Expense
B22: Total Departmental Expenses - 100 | C22: Rooms | D22: 278444.2 | E22: =+IFERROR(D22/D15,"") -> 0.28353935 | F22: 245118.34 | G22: =+IFERROR(F22/F15,"") -> 0.25548961 | H22: =+D22-F22 -> 33325.86 | I22: 261858.86 | J22: =+IFERROR(I22/I15,"") -> 0.27443128 | K22: =+(D22-I22) -> 16585.34 | M22: 1048369.3 | N22: =+IFERROR(M22/M15,"") -> 0.24372082 | O22: 1019678.2 | P22: =+IFERROR(O22/O15,"") -> 0.22805465 | Q22: =+M22-O22 -> 28691.08 | R22: 1030793.9 | S22: =+IFERROR(R22/R15,"") -> 0.23226638 | T22: =+(M22-R22) -> 17575.33
B23: Total Departmental Expenses - 200 | C23: Food & Beverage | D23: 291396.9 | E23: =+IFERROR(D23/D16,"") -> 0.76858971 | F23: 298555.95 | G23: =+IFERROR(F23/F16,"") -> 0.68224854 | H23: =+D23-F23 -> -7159.054 | I23: 228871.12 | J23: =+IFERROR(I23/I16,"") -> 0.91194246 | K23: =+(D23-I23) -> 62525.78 | M23: 1080000.5 | N23: =+IFERROR(M23/M16,"") -> 0.70867763 | O23: 1223767.9 | P23: =+IFERROR(O23/O16,"") -> 0.68264185 | Q23: =+M23-O23 -> -143767.48 | R23: 774579.62 | S23: =+IFERROR(R23/R16,"") -> 0.84506595 | T23: =+(M23-R23) -> 305420.85
B24: Total Departmental Expenses - 300 | C24: Other Operated Departments | D24: 1105.98 | E24: =+IFERROR(D24/D17,"") -> 0.37510684 | F24: 531.38 | G24: =+IFERROR(F24/F17,"") -> 0.34109393 | H24: =+D24-F24 -> 574.6 | I24: 642.24 | J24: =+IFERROR(I24/I17,"") -> 0.4394239 | K24: =+(D24-I24) -> 463.74 | M24: 5073 | N24: =+IFERROR(M24/M17,"") -> 0.51376626 | O24: 2123.05 | P24: =+IFERROR(O24/O17,"") -> 0.34109495 | Q24: =+M24-O24 -> 2949.95 | R24: 2321.77 | S24: =+IFERROR(R24/R17,"") -> 0.32216602 | T24: =+(M24-R24) -> 2751.23
B25: Total Departmental Expenses - 000 | C25: Total Departmental Expense | D25: =+SUM(D22:D24) -> 570947.08 | E25: =+IFERROR(D25/D$19,"") -> 0.37840673 | F25: =+SUM(F22:F24) -> 544205.67 | G25: =+IFERROR(F25/F$19,"") -> 0.35830042 | H25: =+D25-F25 -> 26741.406 | I25: =+SUM(I22:I24) -> 491372.22 | J25: =+IFERROR(I25/I$19,"") -> 0.37241952 | K25: =+(D25-I25) -> 79574.86 | M25: =+SUM(M22:M24) -> 2133442.7 | N25: =+IFERROR(M25/M$19,"") -> 0.33922077 | O25: =+SUM(O22:O24) -> 2245569.2 | P25: =+IFERROR(O25/O$19,"") -> 0.33196713 | Q25: =+M25-O25 -> -112126.45 | R25: =+SUM(R22:R24) -> 1807695.3 | S25: =+IFERROR(R25/R$19,"") -> 0.30823822 | T25: =+(M25-R25) -> 325747.41
C27: Total Departmental Profit | D27: =+D19-D25 -> 937871.42 | E27: =+IFERROR(D27/D$19,"") -> 0.62159327 | F27: =+F19-F25 -> 974647.34 | G27: =+IFERROR(F27/F$19,"") -> 0.64169958 | H27: =+D27-F27 -> -36775.916 | I27: =+I19-I25 -> 828032.88 | J27: =+IFERROR(I27/I$19,"") -> 0.62758048 | K27: =+(D27-I27) -> 109838.54 | M27: =+M19-M25 -> 4155802.8 | N27: =+IFERROR(M27/M$19,"") -> 0.66077923 | O27: =+O19-O25 -> 4518863.1 | P27: =+IFERROR(O27/O$19,"") -> 0.66803287 | Q27: =+M27-O27 -> -363060.3 | R27: =+R19-R25 -> 4056909.4 | S27: =+IFERROR(R27/R$19,"") -> 0.69176178 | T27: =+(M27-R27) -> 98893.42
E28: TRUE | G28: TRUE | J28: TRUE | N28: TRUE | P28: TRUE | S28: TRUE
C29: Undistributed Expenses
B30: Total Departmental Expenses - 500 | C30: Administrative & General | D30: 133968.94 | E30: =+IFERROR(D30/D$19,"") -> 0.088790627 | F30: 138401.36 | G30: =+IFERROR(F30/F$19,"") -> 0.091122285 | H30: =+D30-F30 -> -4432.4168 | I30: 118161.63 | J30: =+IFERROR(I30/I$19,"") -> 0.089556748 | K30: =+(D30-I30) -> 15807.31 | M30: 495671.28 | N30: =+IFERROR(M30/M$19,"") -> 0.078812519 | O30: 544392.4 | P30: =+IFERROR(O30/O$19,"") -> 0.080478653 | Q30: =+M30-O30 -> -48721.121 | R30: 457549.71 | S30: =+IFERROR(R30/R$19,"") -> 0.078018849 | T30: =+(M30-R30) -> 38121.57
B31: Total Departmental Expenses - 600 | C31: Information & Telecom Systems | D31: 16160.83 | E31: =+IFERROR(D31/D$19,"") -> 0.010710917 | F31: 15681.7 | G31: =+IFERROR(F31/F$19,"") -> 0.010324699 | H31: =+D31-F31 -> 479.13 | I31: 15829.8 | J31: =+IFERROR(I31/I$19,"") -> 0.01199768 | K31: =+(D31-I31) -> 331.03 | M31: 80361.22 | N31: =+IFERROR(M31/M$19,"") -> 0.012777561 | O31: 79636.02 | P31: =+IFERROR(O31/O$19,"") -> 0.011772757 | Q31: =+M31-O31 -> 725.2 | R31: 78045.46 | S31: =+IFERROR(R31/R$19,"") -> 0.013307881 | T31: =+(M31-R31) -> 2315.76
B32: Total Departmental Expenses - 700 | C32: Sales & Marketing | D32: 88393.96 | E32: =+IFERROR(D32/D$19,"") -> 0.058584886 | F32: 104759.66 | G32: =+IFERROR(F32/F$19,"") -> 0.068972876 | H32: =+D32-F32 -> -16365.7 | I32: 115727.72 | J32: =+IFERROR(I32/I$19,"") -> 0.087712045 | K32: =+(D32-I32) -> -27333.76 | M32: 381980.89 | N32: =+IFERROR(M32/M$19,"") -> 0.060735566 | O32: 470940.58 | P32: =+IFERROR(O32/O$19,"") -> 0.069620119 | Q32: =+M32-O32 -> -88959.69 | R32: 417390.76 | S32: =+IFERROR(R32/R$19,"") -> 0.071171167 | T32: =+(M32-R32) -> -35409.87
B33: Total Departmental Expenses - 800 | C33: ANGBF Operation & Maintenance | D33: 57358.85 | E33: =+IFERROR(D33/D$19,"") -> 0.038015739 | F33: 65333.87 | G33: =+IFERROR(F33/F$19,"") -> 0.043015268 | H33: =+D33-F33 -> -7975.0199 | I33: 37576.64 | J33: =+IFERROR(I33/I$19,"") -> 0.028479987 | K33: =+(D33-I33) -> 19782.21 | M33: 220794.79 | N33: =+IFERROR(M33/M$19,"") -> 0.035106721 | O33: 267358.96 | P33: =+IFERROR(O33/O$19,"") -> 0.039524228 | Q33: =+M33-O33 -> -46564.174 | R33: 225470.27 | S33: =+IFERROR(R33/R$19,"") -> 0.038445945 | T33: =+(M33-R33) -> -4675.48
B34: Total Utilities Expense - 810 | C34: Utilities | D34: 24121.87 | E34: =+IFERROR(D34/D$19,"") -> 0.015987258 | F34: 23162.39 | G34: =+IFERROR(F34/F$19,"") -> 0.015249922 | H34: =+D34-F34 -> 959.48 | I34: 25806.47 | J34: =+IFERROR(I34/I$19,"") -> 0.019559171 | K34: =+(D34-I34) -> -1684.6 | M34: 93445.37 | N34: =+IFERROR(M34/M$19,"") -> 0.014857962 | O34: 90217.04 | P34: =+IFERROR(O34/O$19,"") -> 0.013336971 | Q34: =+M34-O34 -> 3228.33 | R34: 95974.61 | S34: =+IFERROR(R34/R$19,"") -> 0.01636506 | T34: =+(M34-R34) -> -2529.24
B35: Total Undistributed Expenses - 000 | C35: Total Undistributed Expenses | D35: =+SUM(D30:D34) -> 320004.45 | E35: =+IFERROR(D35/D$19,"") -> 0.21208943 | F35: =+SUM(F30:F34) -> 347338.98 | G35: =+IFERROR(F35/F$19,"") -> 0.22868505 | H35: =+D35-F35 -> -27334.527 | I35: =+SUM(I30:I34) -> 313102.26 | J35: =+IFERROR(I35/I$19,"") -> 0.23730563 | K35: =+(D35-I35) -> 6902.19 | M35: =+SUM(M30:M34) -> 1272253.5 | N35: =+IFERROR(M35/M$19,"") -> 0.20229033 | O35: =+SUM(O30:O34) -> 1452545 | P35: =+IFERROR(O35/O$19,"") -> 0.21473273 | Q35: =+M35-O35 -> -180291.45 | R35: =+SUM(R30:R34) -> 1274430.8 | S35: =+IFERROR(R35/R$19,"") -> 0.2173089 | T35: =+(M35-R35) -> -2177.26
B37: Total Hotel GOP - 000 | C37: Gross Operating Profit | D37: =+D27-D35 -> 617866.97 | E37: =+IFERROR(D37/D$19,"") -> 0.40950384 | F37: =+F27-F35 -> 627308.36 | G37: =+IFERROR(F37/F$19,"") -> 0.41301453 | H37: =+D37-F37 -> -9441.3894 | I37: =+I27-I35 -> 514930.62 | J37: =+IFERROR(I37/I$19,"") -> 0.39027484 | K37: =+(D37-I37) -> 102936.35 | M37: =+M27-M35 -> 2883549.2 | N37: =+IFERROR(M37/M$19,"") -> 0.4584889 | O37: =+O27-O35 -> 3066318.1 | P37: =+IFERROR(O37/O$19,"") -> 0.45330014 | Q37: =+M37-O37 -> -182768.85 | R37: =+R27-R35 -> 2782478.6 | S37: =+IFERROR(R37/R$19,"") -> 0.47445287 | T37: =+(M37-R37) -> 101070.68
B39: Total Management Fees - 920 | C39: Management Fees | D39: 68430.22 | E39: =+IFERROR(D39/D$19,"") -> 0.045353513 | F39: 70783.77 | G39: =+IFERROR(F39/F$19,"") -> 0.046603437 | H39: =+D39-F39 -> -2353.55 | I39: 56917.53 | J39: =+IFERROR(I39/I$19,"") -> 0.043138783 | K39: =+(D39-I39) -> 11512.69 | M39: 273972.26 | N39: =+IFERROR(M39/M$19,"") -> 0.043562023 | O39: 306966.13 | P39: =+IFERROR(O39/O$19,"") -> 0.045379437 | Q39: =+M39-O39 -> -32993.87 | R39: 243369.3 | S39: =+IFERROR(R39/R$19,"") -> 0.041497989 | T39: =+(M39-R39) -> 30602.96
C40: Income before non-operating inc & expense | D40: =+D37-D39 -> 549436.75 | E40: =+IFERROR(D40/D$19,"") -> 0.36415033 | F40: =+F37-F39 -> 556524.59 | G40: =+IFERROR(F40/F$19,"") -> 0.36641109 | H40: =+D40-F40 -> -7087.8394 | I40: =+I37-I39 -> 458013.09 | J40: =+IFERROR(I40/I$19,"") -> 0.34713606 | K40: =+(D40-I40) -> 91423.66 | M40: =+M37-M39 -> 2609577 | N40: =+IFERROR(M40/M$19,"") -> 0.41492687 | O40: =+O37-O39 -> 2759352 | P40: =+IFERROR(O40/O$19,"") -> 0.4079207 | Q40: =+M40-O40 -> -149774.98 | R40: =+R37-R39 -> 2539109.3 | S40: =+IFERROR(R40/R$19,"") -> 0.43295489 | T40: =+(M40-R40) -> 70467.72
E41: TRUE | G41: TRUE | J41: TRUE | N41: TRUE | P41: TRUE | S41: TRUE
C42: Non-Operating Income & Expenses
B43: Total Non-Operating Income - 900 | C43: Income | D43: 1631.67 | E43: =+IFERROR(D43/D$19,"") -> 0.0010814223 | F43: 2031 | G43: =+IFERROR(F43/F$19,"") -> 0.0013371933 | H43: =+D43-F43 -> -399.33 | I43: 1967.65 | J43: =+IFERROR(I43/I$19,"") -> 0.001491316 | K43: =+(D43-I43) -> -335.98 | M43: 9884.92 | N43: =+IFERROR(M43/M$19,"") -> 0.0015717179 | O43: 8124 | P43: =+IFERROR(O43/O$19,"") -> 0.0012009877 | Q43: =+M43-O43 -> 1760.92 | R43: 7748.25 | S43: =+IFERROR(R43/R$19,"") -> 0.0013211888 | T43: =+(M43-R43) -> 2136.67
B44: Total Rent - 900 | C44: Rent | D44: 277.09 | E44: =+IFERROR(D44/D$19,"") -> 0.00018364701 | F44: 1100.5 | G44: =+IFERROR(F44/F$19,"") -> 0.00072455991 | H44: =+D44-F44 -> -823.41 | I44: -196.17 | J44: =+IFERROR(I44/I$19,"") -> -0.00014868064 | K44: =+(D44-I44) -> 473.26 | M44: 3931.72 | N44: =+IFERROR(M44/M$19,"") -> 0.00062514971 | O44: 4615 | P44: =+IFERROR(O44/O$19,"") -> 0.00068224499 | Q44: =+M44-O44 -> -683.28 | R44: 4172.12 | S44: =+IFERROR(R44/R$19,"") -> 0.00071140686 | T44: =+(M44-R44) -> -240.4
B45: Total Taxes - 900 | C45: ANGBF & Other Taxes | D45: 33677.12 | E45: =+IFERROR(D45/D$19,"") -> 0.022320193 | F45: 64957 | G45: =+IFERROR(F45/F$19,"") -> 0.04276714 | H45: =+D45-F45 -> -31279.88 | I45: 62050.2 | J45: =+IFERROR(I45/I$19,"") -> 0.047028922 | K45: =+(D45-I45) -> -28373.08 | M45: 178781.12 | N45: =+IFERROR(M45/M$19,"") -> 0.028426481 | O45: 210061 | P45: =+IFERROR(O45/O$19,"") -> 0.031053752 | Q45: =+M45-O45 -> -31279.88 | R45: 201899.2 | S45: =+IFERROR(R45/R$19,"") -> 0.034426736 | T45: =+(M45-R45) -> -23118.08
B46: Total Insurance - 900 | C46: Insurance | D46: 115207.8 | E46: =+IFERROR(D46/D$19,"") -> 0.076356301 | F46: 120639.82 | G46: =+IFERROR(F46/F$19,"") -> 0.079428239 | H46: =+D46-F46 -> -5432.02 | I46: 130984.32 | J46: =+IFERROR(I46/I$19,"") -> 0.099275287 | K46: =+(D46-I46) -> -15776.52 | M46: 461216.33 | N46: =+IFERROR(M46/M$19,"") -> 0.073334127 | O46: 482770.78 | P46: =+IFERROR(O46/O$19,"") -> 0.071369002 | Q46: =+M46-O46 -> -21554.45 | R46: 521879.55 | S46: =+IFERROR(R46/R$19,"") -> 0.088988018 | T46: =+(M46-R46) -> -60663.22
B47: Total Other Expenses - 900 | C47: Other | D47: 0 | E47: =+IFERROR(D47/D$19,"") -> 0 | F47: 0 | G47: =+IFERROR(F47/F$19,"") -> 0 | H47: =+D47-F47 -> 0 | I47: 0 | J47: =+IFERROR(I47/I$19,"") -> 0 | K47: =+(D47-I47) -> 0 | M47: 0 | N47: =+IFERROR(M47/M$19,"") -> 0 | O47: 0 | P47: =+IFERROR(O47/O$19,"") -> 0 | Q47: =+M47-O47 -> 0 | R47: 0 | S47: =+IFERROR(R47/R$19,"") -> 0 | T47: =+(M47-R47) -> 0
C48: Total non-operating income & expenses | D48: =+SUM(D44:D47)-D43 -> 147530.34 | E48: =+IFERROR(D48/D$19,"") -> 0.097778719 | F48: =+SUM(F44:F47)-F43 -> 184666.32 | G48: =+IFERROR(F48/F$19,"") -> 0.12158275 | H48: =+D48-F48 -> -37135.98 | I48: =+SUM(I44:I47)-I43 -> 190870.7 | J48: =+IFERROR(I48/I$19,"") -> 0.14466421 | K48: =+(D48-I48) -> -43340.36 | M48: =+SUM(M44:M47)-M43 -> 634044.25 | N48: =+IFERROR(M48/M$19,"") -> 0.10081404 | O48: =+SUM(O44:O47)-O43 -> 689322.78 | P48: =+IFERROR(O48/O$19,"") -> 0.10190401 | Q48: =+M48-O48 -> -55278.53 | R48: =+SUM(R44:R47)-R43 -> 720202.62 | S48: =+IFERROR(R48/R$19,"") -> 0.12280497 | T48: =+(M48-R48) -> -86158.37
C50: EBITDA | D50: =+D40-D48 -> 401906.41 | E50: =+IFERROR(D50/D$19,"") -> 0.26637161 | F50: =+F40-F48 -> 371858.27 | G50: =+IFERROR(F50/F$19,"") -> 0.24482835 | H50: =+D50-F50 -> 30048.141 | I50: =+I40-I48 -> 267142.39 | J50: =+IFERROR(I50/I$19,"") -> 0.20247185 | K50: =+(D50-I50) -> 134764.02 | M50: =+M40-M48 -> 1975532.7 | N50: =+IFERROR(M50/M$19,"") -> 0.31411283 | O50: =+O40-O48 -> 2070029.2 | P50: =+IFERROR(O50/O$19,"") -> 0.30601669 | Q50: =+M50-O50 -> -94496.445 | R50: =+R40-R48 -> 1818906.6 | S50: =+IFERROR(R50/R$19,"") -> 0.31014991 | T50: =+(M50-R50) -> 156626.09
B52: FF&E - 930 | C52: FF&E ProForma Calculation | D52: 60772.54 | E52: =+IFERROR(D52/D$19,"") -> 0.040278231 | F52: 60754.121 | G52: =+IFERROR(F52/F$19,"") -> 0.04 | H52: =+D52-F52 -> 18.4192 | I52: 53126.037 | J52: =+IFERROR(I52/I$19,"") -> 0.040265145 | K52: =+(D52-I52) -> 7646.5028 | M52: 253245.64 | N52: =+IFERROR(M52/M$19,"") -> 0.040266458 | O52: 270577.29 | P52: =+IFERROR(O52/O$19,"") -> 0.04 | Q52: =+M52-O52 -> -17331.648 | R52: 231966.63 | S52: =+IFERROR(R52/R$19,"") -> 0.039553668 | T52: =+(M52-R52) -> 21279.018
C53: EBITDA: Less Replacement Reserve | D53: =+D50-D52 -> 341133.87 | E53: =+IFERROR(D53/D$19,"") -> 0.22609338 | F53: =+F50-F52 -> 311104.15 | G53: =+IFERROR(F53/F$19,"") -> 0.20482835 | H53: =+D53-F53 -> 30029.721 | I53: =+I50-I52 -> 214016.35 | J53: =+IFERROR(I53/I$19,"") -> 0.1622067 | K53: =+(D53-I53) -> 127117.52 | M53: =+M50-M52 -> 1722287.1 | N53: =+IFERROR(M53/M$19,"") -> 0.27384637 | O53: =+O50-O52 -> 1799451.9 | P53: =+IFERROR(O53/O$19,"") -> 0.26601669 | Q53: =+M53-O53 -> -77164.798 | R53: =+R50-R52 -> 1586940 | S53: =+IFERROR(R53/R$19,"") -> 0.27059625 | T53: =+(M53-R53) -> 135347.07

Sheet Rooms
V1: ANG
C2: =+Summary!$C$2 -> Angler's | V2: Apr
C3: =+Summary!$C$3 -> STATEMENT OF INCOME
C4: =+Summary!$C$4 -> FOR THE PERIOD ENDING APR 2025
D6: =Year&" "&UPPER(Month)&" - PERIODIC" -> 2025 APR - PERIODIC | M6: =Year&" "&UPPER(Month)&" - YEAR TO DATE" -> 2025 APR - YEAR TO DATE
D7: Actual | F7: Budget | H7: VARIANCE | I7: Actual - Last Year | K7: VARIANCE | M7: Actual | O7: Budget | Q7: VARIANCE | R7: Actual - Last Year | T7: VARIANCE
D8: $ | E8: % | F8: $ | G8: % | H8: $ | I8: Actual | J8: % | K8: $ | M8: $ | N8: % | O8: $ | P8: % | Q8: $ | R8: Actual | S8: % | T8: $
C9: Revenues
C10: Transient Rooms Revenue
B11: Transient Retail - 100 | C11: Retail | D11: 403851.73 | E11: =IFERROR(D11/D$31,"") -> 0.41124166 | F11: 339220 | G11: =IFERROR(F11/F$31,"") -> 0.35357283 | H11: =+D11-F11 -> 64631.73 | I11: 337486.78 | J11: =IFERROR(I11/I$31,"") -> 0.35369026 | K11: =+D11-I11 -> 66364.95 | M11: 1422080.2 | N11: =IFERROR(M11/M$31,"") -> 0.33059969 | O11: 1637641.7 | P11: =IFERROR(O11/O$31,"") -> 0.36626438 | Q11: =+M11-O11 -> -215561.46 | R11: 1558853.7 | S11: =IFERROR(R11/R$31,"") -> 0.35125284 | T11: =+M11-R11 -> -136773.42
B12: Transient Discount - 100 | C12: Discount | D12: 341627.81 | E12: =IFERROR(D12/D$31,"") -> 0.34787913 | F12: 433204.3 | G12: =IFERROR(F12/F$31,"") -> 0.45153373 | H12: =+D12-F12 -> -91576.49 | I12: 425759.58 | J12: =IFERROR(I12/I$31,"") -> 0.44620123 | K12: =+D12-I12 -> -84131.77 | M12: 1630075.8 | N12: =IFERROR(M12/M$31,"") -> 0.3789537 | O12: 1587492.8 | P12: =IFERROR(O12/O$31,"") -> 0.35504841 | Q12: =+M12-O12 -> 42583.02 | R12: 1572469.1 | S12: =IFERROR(R12/R$31,"") -> 0.35432079 | T12: =+M12-R12 -> 57606.7
B13: Transient Negotiated - 100 | C13: Negotiated | D13: 38606.91 | E13: =IFERROR(D13/D$31,"") -> 0.039313364 | F13: 28728.9 | G13: =IFERROR(F13/F$31,"") -> 0.029944457 | H13: =+D13-F13 -> 9878.01 | I13: 23549.12 | J13: =IFERROR(I13/I$31,"") -> 0.024679765 | K13: =+D13-I13 -> 15057.79 | M13: 171189.25 | N13: =IFERROR(M13/M$31,"") -> 0.039797412 | O13: 194782.3 | P13: =IFERROR(O13/O$31,"") -> 0.043563753 | Q13: =+M13-O13 -> -23593.05 | R13: 272607.32 | S13: =IFERROR(R13/R$31,"") -> 0.061425969 | T13: =+M13-R13 -> -101418.07
B14: Transient Qualified - 100 | C14: Qualified | D14: 24633.45 | E14: =IFERROR(D14/D$31,"") -> 0.025084208 | F14: 28222.09 | G14: =IFERROR(F14/F$31,"") -> 0.029416203 | H14: =+D14-F14 -> -3588.64 | I14: 35901.32 | J14: =IFERROR(I14/I$31,"") -> 0.037625021 | K14: =+D14-I14 -> -11267.87 | M14: 95191.05 | N14: =IFERROR(M14/M$31,"") -> 0.022129646 | O14: 104260.69 | P14: =IFERROR(O14/O$31,"") -> 0.023318274 | Q14: =+M14-O14 -> -9069.64 | R14: 129886.92 | S14: =IFERROR(R14/R$31,"") -> 0.029267115 | T14: =+M14-R14 -> -34695.87
B15: Transient Wholesale - 100 | C15: Wholesale | D15: 53616.2 | E15: =IFERROR(D15/D$31,"") -> 0.054597303 | F15: 82110 | G15: =IFERROR(F15/F$31,"") -> 0.085584179 | H15: =+D15-F15 -> -28493.8 | I15: 91534.72 | J15: =IFERROR(I15/I$31,"") -> 0.095929503 | K15: =+D15-I15 -> -37918.52 | M15: 217306.6 | N15: =IFERROR(M15/M$31,"") -> 0.050518594 | O15: 304824.8 | P15: =IFERROR(O15/O$31,"") -> 0.068175149 | Q15: =+M15-O15 -> -87518.2 | R15: 302662.4 | S15: =IFERROR(R15/R$31,"") -> 0.068198209 | T15: =+M15-R15 -> -85355.8
B16: Transient Rebates and Subsidies - 100 | C16: Rebates | D16: 0 | E16: =IFERROR(D16/D$31,"") -> 0 | F16: 0 | G16: =IFERROR(F16/F$31,"") -> 0 | H16: =+D16-F16 -> 0 | I16: 0 | J16: =IFERROR(I16/I$31,"") -> 0 | K16: =+D16-I16 -> 0 | M16: 0 | N16: =IFERROR(M16/M$31,"") -> 0 | O16: 0 | P16: =IFERROR(O16/O$31,"") -> 0 | Q16: =+M16-O16 -> 0 | R16: 0 | S16: =IFERROR(R16/R$31,"") -> 0 | T16: =+M16-R16 -> 0
B17: Transient Rooms Revenue - 100 | C17: Total Transient Room Rev | D17: =SUM(D11:D16) -> 862336.1 | E17: =IFERROR(D17/D$31,"") -> 0.87811567 | F17: =SUM(F11:F16) -> 911485.29 | G17: =IFERROR(F17/F$31,"") -> 0.9500514 | H17: =+D17-F17 -> -49149.19 | I17: =SUM(I11:I16) -> 914231.52 | J17: =IFERROR(I17/I$31,"") -> 0.95812578 | K17: =+D17-I17 -> -51895.42 | M17: =SUM(M11:M16) -> 3535843 | N17: =IFERROR(M17/M$31,"") -> 0.82199904 | O17: =SUM(O11:O16) -> 3829002.3 | P17: =IFERROR(O17/O$31,"") -> 0.85636997 | Q17: =+M17-O17 -> -293159.33 | R17: =SUM(R11:R16) -> 3836479.4 | S17: =IFERROR(R17/R$31,"") -> 0.86446492 | T17: =+M17-R17 -> -300636.46
C19: Group Rooms Revenue
B20: Group Corporate - 100 | C20: Corporate | D20: 69181.6 | E20: =IFERROR(D20/D$31,"") -> 0.070447529 | F20: 38440 | G20: =IFERROR(F20/F$31,"") -> 0.040066446 | H20: =+D20-F20 -> 30741.6 | I20: 25733 | J20: =IFERROR(I20/I$31,"") -> 0.026968498 | K20: =+D20-I20 -> 43448.6 | M20: 623870.28 | N20: =IFERROR(M20/M$31,"") -> 0.14503494 | O20: 563653.26 | P20: =IFERROR(O20/O$31,"") -> 0.12606305 | Q20: =+M20-O20 -> 60217.02 | R20: 545977 | S20: =IFERROR(R20/R$31,"") -> 0.12302372 | T20: =+M20-R20 -> 77893.28
B21: Group Association/Convention - 100 | C21: Association/Convention | D21: 50749 | E21: =IFERROR(D21/D$31,"") -> 0.051677637 | F21: 0 | G21: =IFERROR(F21/F$31,"") -> 0 | H21: =+D21-F21 -> 50749 | I21: 0.05 | J21: =IFERROR(I21/I$31,"") -> 5.240061e-08 | K21: =+D21-I21 -> 50748.95 | M21: 101354.42 | N21: =IFERROR(M21/M$31,"") -> 0.023562482 | O21: 28090.56 | P21: =IFERROR(O21/O$31,"") -> 0.0062825535 | Q21: =+M21-O21 -> 73263.86 | R21: 8802.7 | S21: =IFERROR(R21/R$31,"") -> 0.0019834918 | T21: =+M21-R21 -> 92551.72
B22: Group Government - 100 | C22: Government | D22: 0 | E22: =IFERROR(D22/D$31,"") -> 0 | F22: 0 | G22: =IFERROR(F22/F$31,"") -> 0 | H22: =+D22-F22 -> 0 | I22: 0 | J22: =IFERROR(I22/I$31,"") -> 0 | K22: =+D22-I22 -> 0 | M22: 0 | N22: =IFERROR(M22/M$31,"") -> 0 | O22: 0 | P22: =IFERROR(O22/O$31,"") -> 0 | Q22: =+M22-O22 -> 0 | R22: 0 | S22: =IFERROR(R22/R$31,"") -> 0 | T22: =+M22-R22 -> 0
B23: Group Tour/Wholesalers - 100 | C23: Tour/Wholesalers | D23: 0 | E23: =IFERROR(D23/D$31,"") -> 0 | F23: 0 | G23: =IFERROR(F23/F$31,"") -> 0 | H23: =+D23-F23 -> 0 | I23: 0 | J23: =IFERROR(I23/I$31,"") -> 0 | K23: =+D23-I23 -> 0 | M23: 2640 | N23: =IFERROR(M23/M$31,"") -> 0.00061373695 | O23: 6077.94 | P23: =IFERROR(O23/O$31,"") -> 0.0013593529 | Q23: =+M23-O23 -> -3437.94 | R23: 6229 | S23: =IFERROR(R23/R$31,"") -> 0.001403566 | T23: =+M23-R23 -> -3589
B24: Group SMERF - 100 | C24: SMERF | D24: -0.02 | E24: =IFERROR(D24/D$31,"") -> -2.0365973e-08 | F24: 5980 | G24: =IFERROR(F24/F$31,"") -> 0.0062330215 | H24: =+D24-F24 -> -5980.02 | I24: 10825 | J24: =IFERROR(I24/I$31,"") -> 0.011344732 | K24: =+D24-I24 -> -10825.02 | M24: 19434.98 | N24: =IFERROR(M24/M$31,"") -> 0.0045181687 | O24: 13815 | P24: =IFERROR(O24/O$31,"") -> 0.0030897738 | Q24: =+M24-O24 -> 5619.98 | R24: 10825 | S24: =IFERROR(R24/R$31,"") -> 0.0024391719 | T24: =+M24-R24 -> 8609.98
B25: Group Other - 100 | C25: Other Group | D25: 0 | E25: =IFERROR(D25/D$31,"") -> 0 | F25: 0 | G25: =IFERROR(F25/F$31,"") -> 0 | H25: =+D25-F25 -> 0 | I25: 0 | J25: =IFERROR(I25/I$31,"") -> 0 | K25: =+D25-I25 -> 0 | M25: 0 | N25: =IFERROR(M25/M$31,"") -> 0 | O25: 0 | P25: =IFERROR(O25/O$31,"") -> 0 | Q25: =+M25-O25 -> 0 | R25: 0 | S25: =IFERROR(R25/R$31,"") -> 0 | T25: =+M25-R25 -> 0
B26: Group Rebates and Subsidies - 100 | C26: Group Rebates | D26: 0 | E26: =IFERROR(D26/D$31,"") -> 0 | F26: 0 | G26: =IFERROR(F26/F$31,"") -> 0 | H26: =+D26-F26 -> 0 | I26: 0 | J26: =IFERROR(I26/I$31,"") -> 0 | K26: =+D26-I26 -> 0 | M26: 0 | N26: =IFERROR(M26/M$31,"") -> 0 | O26: 0 | P26: =IFERROR(O26/O$31,"") -> 0 | Q26: =+M26-O26 -> 0 | R26: 0 | S26: =IFERROR(R26/R$31,"") -> 0 | T26: =+M26-R26 -> 0
B27: Group Rooms Revenue - 100 | C27: Total Group Room Rev | D27: =SUM(D20:D26) -> 119930.58 | E27: =IFERROR(D27/D$31,"") -> 0.12212515 | F27: =SUM(F20:F26) -> 44420 | G27: =IFERROR(F27/F$31,"") -> 0.046299467 | H27: =+D27-F27 -> 75510.58 | I27: =SUM(I20:I26) -> 36558.05 | J27: =IFERROR(I27/I$31,"") -> 0.038313282 | K27: =+D27-I27 -> 83372.53 | M27: =SUM(M20:M26) -> 747299.68 | N27: =IFERROR(M27/M$31,"") -> 0.17372933 | O27: =SUM(O20:O26) -> 611636.76 | P27: =IFERROR(O27/O$31,"") -> 0.13679473 | Q27: =+M27-O27 -> 135662.92 | R27: =SUM(R20:R26) -> 571833.7 | S27: =IFERROR(R27/R$31,"") -> 0.12884995 | T27: =+M27-R27 -> 175465.98
B28: Contract Rooms Revenue - 100 | C28: Contract Rooms Revenue | D28: 0 | E28: =IFERROR(D28/D$31,"") -> 0 | F28: 0 | G28: =IFERROR(F28/F$31,"") -> 0 | H28: =+D28-F28 -> 0 | I28: 0 | J28: =IFERROR(I28/I$31,"") -> 0 | K28: =+D28-I28 -> 0 | M28: 0 | N28: =IFERROR(M28/M$31,"") -> 0 | O28: 0 | P28: =IFERROR(O28/O$31,"") -> 0 | Q28: =+M28-O28 -> 0 | R28: 0 | S28: =IFERROR(R28/R$31,"") -> 0 | T28: =+M28-R28 -> 0
B29: Other Rooms Revenue - 100 | C29: Other Rooms Revenue | D29: -236.49 | E29: =IFERROR(D29/D$31,"") -> -0.00024081744 | F29: 3501 | G29: =IFERROR(F29/F$31,"") -> 0.0036491318 | H29: =+D29-F29 -> -3737.49 | I29: 5024.12 | J29: =IFERROR(I29/I$31,"") -> 0.005265339 | K29: =+D29-I29 -> -5260.61 | M29: 18374.49 | N29: =IFERROR(M29/M$31,"") -> 0.0042716301 | O29: 30562 | P29: =IFERROR(O29/O$31,"") -> 0.0068352998 | Q29: =+M29-O29 -> -12187.51 | R29: 35119.86 | S29: =IFERROR(R29/R$31,"") -> 0.0079134757 | T29: =+M29-R29 -> -16745.37
B30: Allowances - 100 | C30: Rooms: Allowances | D30: 0 | E30: =IFERROR(D30/D$31,"") -> 0 | F30: 0 | G30: =IFERROR(F30/F$31,"") -> 0 | H30: =+D30-F30 -> 0 | I30: -1626.32 | J30: =IFERROR(I30/I$31,"") -> -0.0017044032 | K30: =+D30-I30 -> 1626.32 | M30: 0 | N30: =IFERROR(M30/M$31,"") -> 0 | O30: 0 | P30: =IFERROR(O30/O$31,"") -> 0 | Q30: =+M30-O30 -> 0 | R30: -5451.37 | S30: =IFERROR(R30/R$31,"") -> -0.0012283444 | T30: =+M30-R30 -> 5451.37
B31: Total Revenue - 100 | C31: Total Rooms Revenue | D31: =+D17+D27+SUM(D28:D30) -> 982030.19 | E31: =IFERROR(D31/D$31,"") -> 1 | F31: =+F17+F27+SUM(F28:F30) -> 959406.29 | G31: =IFERROR(F31/F$31,"") -> 1 | H31: =+D31-F31 -> 22623.9 | I31: =+I17+I27+SUM(I28:I30) -> 954187.37 | J31: =IFERROR(I31/I$31,"") -> 1 | K31: =+D31-I31 -> 27842.82 | M31: =+M17+M27+SUM(M28:M30) -> 4301517.2 | N31: =IFERROR(M31/M$31,"") -> 1 | O31: =+O17+O27+SUM(O28:O30) -> 4471201.1 | P31: =IFERROR(O31/O$31,"") -> 1 | Q31: =+M31-O31 -> -169683.92 | R31: =+R17+R27+SUM(R28:R30) -> 4437981.6 | S31: =IFERROR(R31/R$31,"") -> 1 | T31: =+M31-R31 -> -136464.48
C33: Labor & Related Expenses
B34: S&W Management - 100 | C34: Salaries & Wages
B35: Housekeeping Management Reg S&W - 100 | C35: Housekeeping Mgmt | D35: 0 | E35: =IFERROR(D35/D$31,"") -> 0 | F35: 0 | G35: =IFERROR(F35/F$31,"") -> 0 | H35: =+D35-F35 -> 0 | I35: 0 | J35: =IFERROR(I35/I$31,"") -> 0 | K35: =+D35-I35 -> 0 | M35: 0 | N35: =IFERROR(M35/M$31,"") -> 0 | O35: 0 | P35: =IFERROR(O35/O$31,"") -> 0 | Q35: =+M35-O35 -> 0 | R35: 0 | S35: =IFERROR(R35/R$31,"") -> 0 | T35: =+M35-R35 -> 0
B36: Front Desk Management Reg S&W - 100 | C36: Front Desk Mgmt | D36: 0 | E36: =IFERROR(D36/D$31,"") -> 0 | F36: 0 | G36: =IFERROR(F36/F$31,"") -> 0 | H36: =+D36-F36 -> 0 | I36: 0 | J36: =IFERROR(I36/I$31,"") -> 0 | K36: =+D36-I36 -> 0 | M36: 0 | N36: =IFERROR(M36/M$31,"") -> 0 | O36: 0 | P36: =IFERROR(O36/O$31,"") -> 0 | Q36: =+M36-O36 -> 0 | R36: 0 | S36: =IFERROR(R36/R$31,"") -> 0 | T36: =+M36-R36 -> 0
B37: Unassigned Management Reg S&W - 100 | C37: Management | D37: 13751.46 | E37: =IFERROR(D37/D$31,"") -> 0.014003093 | F37: 12527.78 | G37: =IFERROR(F37/F$31,"") -> 0.013057846 | H37: =+D37-F37 -> 1223.68 | I37: 12785.27 | J37: =IFERROR(I37/I$31,"") -> 0.013399119 | K37: =+D37-I37 -> 966.19 | M37: 48557.38 | N37: =IFERROR(M37/M$31,"") -> 0.011288431 | O37: 47981.36 | P37: =IFERROR(O37/O$31,"") -> 0.010731202 | Q37: =+M37-O37 -> 576.02 | R37: 34728.11 | S37: =IFERROR(R37/R$31,"") -> 0.0078252036 | T37: =+M37-R37 -> 13829.27
B38: S&W Non-Management - 100 | C38: Non-Management
B39: Front Desk Reg S&W - 100 | C39: Front Office | D39: 14600.75 | E39: =IFERROR(D39/D$31,"") -> 0.014867924 | F39: 17168.31 | G39: =IFERROR(F39/F$31,"") -> 0.017894723 | H39: =+D39-F39 -> -2567.56 | I39: 14397.6 | J39: =IFERROR(I39/I$31,"") -> 0.01508886 | K39: =+D39-I39 -> 203.15 | M39: 53276.41 | N39: =IFERROR(M39/M$31,"") -> 0.012385493 | O39: 67417.02 | P39: =IFERROR(O39/O$31,"") -> 0.015078056 | Q39: =+M39-O39 -> -14140.61 | R39: 37882.2 | S39: =IFERROR(R39/R$31,"") -> 0.0085359073 | T39: =+M39-R39 -> 15394.21
B40: Housekeeping Reg S&W - 100 | C40: Housekeeping | D40: 43562.57 | E40: =IFERROR(D40/D$31,"") -> 0.044359705 | F40: 46054.89 | G40: =IFERROR(F40/F$31,"") -> 0.048003531 | H40: =+D40-F40 -> -2492.32 | I40: 44186.67 | J40: =IFERROR(I40/I$31,"") -> 0.046308169 | K40: =+D40-I40 -> -624.1 | M40: 174126.5 | N40: =IFERROR(M40/M$31,"") -> 0.040480252 | O40: 180684.69 | P40: =IFERROR(O40/O$31,"") -> 0.040410773 | Q40: =+M40-O40 -> -6558.19 | R40: 150761.34 | S40: =IFERROR(R40/R$31,"") -> 0.033970699 | T40: =+M40-R40 -> 23365.16
B41: Reservations Reg S&W - 100 | C41: Reservations | D41: 0 | E41: =IFERROR(D41/D$31,"") -> 0 | F41: 0 | G41: =IFERROR(F41/F$31,"") -> 0 | H41: =+D41-F41 -> 0 | I41: 0 | J41: =IFERROR(I41/I$31,"") -> 0 | K41: =+D41-I41 -> 0 | M41: 0 | N41: =IFERROR(M41/M$31,"") -> 0 | O41: 0 | P41: =IFERROR(O41/O$31,"") -> 0 | Q41: =+M41-O41 -> 0 | R41: 0 | S41: =IFERROR(R41/R$31,"") -> 0 | T41: =+M41-R41 -> 0
B42: Comp F&B Reg S&W - 100 | C42: Comp F&B | D42: 0 | E42: =IFERROR(D42/D$31,"") -> 0 | F42: 0 | G42: =IFERROR(F42/F$31,"") -> 0 | H42: =+D42-F42 -> 0 | I42: 0 | J42: =IFERROR(I42/I$31,"") -> 0 | K42: =+D42-I42 -> 0 | M42: 0 | N42: =IFERROR(M42/M$31,"") -> 0 | O42: 0 | P42: =IFERROR(O42/O$31,"") -> 0 | Q42: =+M42-O42 -> 0 | R42: 0 | S42: =IFERROR(R42/R$31,"") -> 0 | T42: =+M42-R42 -> 0
B43: Rooms Unassigned Reg S&W - 100 | C43: Unassigned | D43: 0 | E43: =IFERROR(D43/D$31,"") -> 0 | F43: 0 | G43: =IFERROR(F43/F$31,"") -> 0 | H43: =+D43-F43 -> 0 | I43: 0 | J43: =IFERROR(I43/I$31,"") -> 0 | K43: =+D43-I43 -> 0 | M43: 0 | N43: =IFERROR(M43/M$31,"") -> 0 | O43: 0 | P43: =IFERROR(O43/O$31,"") -> 0 | Q43: =+M43-O43 -> 0 | R43: 0 | S43: =IFERROR(R43/R$31,"") -> 0 | T43: =+M43-R43 -> 0
B44: Total Salaries & Wages - 100 | C44: Total Salaries and Wages | D44: =SUM(D35:D43) -> 71914.78 | E44: =IFERROR(D44/D$31,"") -> 0.073230722 | F44: =SUM(F35:F43) -> 75750.98 | G44: =IFERROR(F44/F$31,"") -> 0.078956101 | H44: =+D44-F44 -> -3836.2 | I44: =SUM(I35:I43) -> 71369.54 | J44: =IFERROR(I44/I$31,"") -> 0.074796148 | K44: =+D44-I44 -> 545.24 | M44: =SUM(M35:M43) -> 275960.29 | N44: =IFERROR(M44/M$31,"") -> 0.064154176 | O44: =SUM(O35:O43) -> 296083.07 | P44: =IFERROR(O44/O$31,"") -> 0.06622003 | Q44: =+M44-O44 -> -20122.78 | R44: =SUM(R35:R43) -> 223371.65 | S44: =IFERROR(R44/R$31,"") -> 0.05033181 | T44: =+M44-R44 -> 52588.64
B45: Total Service Charge Distribution - 100 | C45: Service Charge Distribution | D45: 0 | E45: =IFERROR(D45/D$31,"") -> 0 | F45: 0 | G45: =IFERROR(F45/F$31,"") -> 0 | H45: =+D45-F45 -> 0 | I45: 0 | J45: =IFERROR(I45/I$31,"") -> 0 | K45: =+D45-I45 -> 0 | M45: 0 | N45: =IFERROR(M45/M$31,"") -> 0 | O45: 0 | P45: =IFERROR(O45/O$31,"") -> 0 | Q45: =+M45-O45 -> 0 | R45: 0 | S45: =IFERROR(R45/R$31,"") -> 0 | T45: =+M45-R45 -> 0
B46: Total Contracted Leased & Outsourced Labor - 100 | C46: Contracted & Leased Labor | D46: 47588.82 | E46: =IFERROR(D46/D$31,"") -> 0.04845963 | F46: 34183.44 | G46: =IFERROR(F46/F$31,"") -> 0.035629785 | H46: =+D46-F46 -> 13405.38 | I46: 42248.9 | J46: =IFERROR(I46/I$31,"") -> 0.044277362 | K46: =+D46-I46 -> 5339.92 | M46: 168635.6 | N46: =IFERROR(M46/M$31,"") -> 0.039203749 | O46: 136701.76 | P46: =IFERROR(O46/O$31,"") -> 0.030573834 | Q46: =+M46-O46 -> 31933.84 | R46: 247616.46 | S46: =IFERROR(R46/R$31,"") -> 0.055794837 | T46: =+M46-R46 -> -78980.86
B47: Total Bonuses & Incentives - 100 | C47: Bonuses & Incentives | D47: 1701.65 | E47: =IFERROR(D47/D$31,"") -> 0.0017327879 | F47: 3247.37 | G47: =IFERROR(F47/F$31,"") -> 0.0033847704 | H47: =+D47-F47 -> -1545.72 | I47: 2262.78 | J47: =IFERROR(I47/I$31,"") -> 0.002371421 | K47: =+D47-I47 -> -561.13 | M47: 7337.28 | N47: =IFERROR(M47/M$31,"") -> 0.0017057424 | O47: 12825.05 | P47: =IFERROR(O47/O$31,"") -> 0.002868368 | Q47: =+M47-O47 -> -5487.77 | R47: 5933.31 | S47: =IFERROR(R47/R$31,"") -> 0.0013369388 | T47: =+M47-R47 -> 1403.97
B48: Total Salaries Wages & Bonuses - 100 | C48: Total Labor Expense | D48: =+SUM(D44:D47) -> 121205.25 | E48: =IFERROR(D48/D$31,"") -> 0.12342314 | F48: =+SUM(F44:F47) -> 113181.79 | G48: =IFERROR(F48/F$31,"") -> 0.11797066 | H48: =+D48-F48 -> 8023.46 | I48: =+SUM(I44:I47) -> 115881.22 | J48: =IFERROR(I48/I$31,"") -> 0.12144493 | K48: =+D48-I48 -> 5324.03 | M48: =+SUM(M44:M47) -> 451933.17 | N48: =IFERROR(M48/M$31,"") -> 0.10506367 | O48: =+SUM(O44:O47) -> 445609.88 | P48: =IFERROR(O48/O$31,"") -> 0.099662232 | Q48: =+M48-O48 -> 6323.29 | R48: =+SUM(R44:R47) -> 476921.42 | S48: =IFERROR(R48/R$31,"") -> 0.10746359 | T48: =+M48-R48 -> -24988.25
B49: Total Payroll Taxes - 100 | C49: Payroll Taxes | D49: 5371.64 | E49: =IFERROR(D49/D$31,"") -> 0.0054699337 | F49: 6890.19 | G49: =IFERROR(F49/F$31,"") -> 0.0071817228 | H49: =+D49-F49 -> -1518.55 | I49: 5896.52 | J49: =IFERROR(I49/I$31,"") -> 0.0061796249 | K49: =+D49-I49 -> -524.88 | M49: 21828.82 | N49: =IFERROR(M49/M$31,"") -> 0.0050746793 | O49: 29012.55 | P49: =IFERROR(O49/O$31,"") -> 0.0064887599 | Q49: =+M49-O49 -> -7183.73 | R49: 18732.77 | S49: =IFERROR(R49/R$31,"") -> 0.0042210112 | T49: =+M49-R49 -> 3096.05
B50: Total Supplemental Pay - 100 | C50: Supplemental Pay | D50: 4408.31 | E50: =IFERROR(D50/D$31,"") -> 0.004488976 | F50: 4519.16 | G50: =IFERROR(F50/F$31,"") -> 0.0047103715 | H50: =+D50-F50 -> -110.85 | I50: 3428.29 | J50: =IFERROR(I50/I$31,"") -> 0.0035928897 | K50: =+D50-I50 -> 980.02 | M50: 30509.77 | N50: =IFERROR(M50/M$31,"") -> 0.0070927928 | O50: 24115.26 | P50: =IFERROR(O50/O$31,"") -> 0.0053934636 | Q50: =+M50-O50 -> 6394.51 | R50: 16727.75 | S50: =IFERROR(R50/R$31,"") -> 0.0037692247 | T50: =+M50-R50 -> 13782.02
B51: Total Employee Benefits - 100 | C51: Employee Benefits | D51: 7939.84 | E51: =IFERROR(D51/D$31,"") -> 0.0080851282 | F51: 10269.42 | G51: =IFERROR(F51/F$31,"") -> 0.010703932 | H51: =+D51-F51 -> -2329.58 | I51: 8947.57 | J51: =IFERROR(I51/I$31,"") -> 0.0093771625 | K51: =+D51-I51 -> -1007.73 | M51: 31621.14 | N51: =IFERROR(M51/M$31,"") -> 0.0073511598 | O51: 40660.38 | P51: =IFERROR(O51/O$31,"") -> 0.0090938384 | Q51: =+M51-O51 -> -9039.24 | R51: 36313.45 | S51: =IFERROR(R51/R$31,"") -> 0.0081824246 | T51: =+M51-R51 -> -4692.31
B52: Total Payroll-Related Expenses - 100 | C52: Total Payroll Related | D52: =SUM(D49:D51) -> 17719.79 | E52: =IFERROR(D52/D$31,"") -> 0.018044038 | F52: =SUM(F49:F51) -> 21678.77 | G52: =IFERROR(F52/F$31,"") -> 0.022596027 | H52: =+D52-F52 -> -3958.98 | I52: =SUM(I49:I51) -> 18272.38 | J52: =IFERROR(I52/I$31,"") -> 0.019149677 | K52: =+D52-I52 -> -552.59 | M52: =SUM(M49:M51) -> 83959.73 | N52: =IFERROR(M52/M$31,"") -> 0.019518632 | O52: =SUM(O49:O51) -> 93788.19 | P52: =IFERROR(O52/O$31,"") -> 0.020976062 | Q52: =+M52-O52 -> -9828.46 | R52: =SUM(R49:R51) -> 71773.97 | S52: =IFERROR(R52/R$31,"") -> 0.01617266 | T52: =+M52-R52 -> 12185.76
B53: Total Labor Costs & Related Expenses - 100 | C53: Total Labor & Related Exp | D53: =+D52+D48 -> 138925.04 | E53: =IFERROR(D53/D$31,"") -> 0.14146718 | F53: =+F52+F48 -> 134860.56 | G53: =IFERROR(F53/F$31,"") -> 0.14056668 | H53: =+D53-F53 -> 4064.48 | I53: =+I52+I48 -> 134153.6 | J53: =IFERROR(I53/I$31,"") -> 0.14059461 | K53: =+D53-I53 -> 4771.44 | M53: =+M52+M48 -> 535892.9 | N53: =IFERROR(M53/M$31,"") -> 0.1245823 | O53: =+O52+O48 -> 539398.07 | P53: =IFERROR(O53/O$31,"") -> 0.12063829 | Q53: =+M53-O53 -> -3505.17 | R53: =+R52+R48 -> 548695.39 | S53: =IFERROR(R53/R$31,"") -> 0.12363625 | T53: =+M53-R53 -> -12802.49
C55: Other Expenses
B56: Dues & Subscriptions - 100 | C56: Dues and Subscriptions | D56: 0 | E56: =IFERROR(D56/D$31,"") -> 0 | F56: 0 | G56: =IFERROR(F56/F$31,"") -> 0 | H56: =+D56-F56 -> 0 | I56: 0 | J56: =IFERROR(I56/I$31,"") -> 0 | K56: =+D56-I56 -> 0 | M56: 0 | N56: =IFERROR(M56/M$31,"") -> 0 | O56: 0 | P56: =IFERROR(O56/O$31,"") -> 0 | Q56: =+M56-O56 -> 0 | R56: 0 | S56: =IFERROR(R56/R$31,"") -> 0 | T56: =+M56-R56 -> 0
B57: Licenses & Permits - 100 | C57: Licenses & Permits | D57: 0 | E57: =IFERROR(D57/D$31,"") -> 0 | F57: 0 | G57: =IFERROR(F57/F$31,"") -> 0 | H57: =+D57-F57 -> 0 | I57: 0 | J57: =IFERROR(I57/I$31,"") -> 0 | K57: =+D57-I57 -> 0 | M57: 0 | N57: =IFERROR(M57/M$31,"") -> 0 | O57: 0 | P57: =IFERROR(O57/O$31,"") -> 0 | Q57: =+M57-O57 -> 0 | R57: 0 | S57: =IFERROR(R57/R$31,"") -> 0 | T57: =+M57-R57 -> 0
B58: Postage & Overnight Delivery Charges - 100 | C58: Postage and Overnight Delivery | D58: 0 | E58: =IFERROR(D58/D$31,"") -> 0 | F58: 0 | G58: =IFERROR(F58/F$31,"") -> 0 | H58: =+D58-F58 -> 0 | I58: 0 | J58: =IFERROR(I58/I$31,"") -> 0 | K58: =+D58-I58 -> 0 | M58: 0 | N58: =IFERROR(M58/M$31,"") -> 0 | O58: 0 | P58: =IFERROR(O58/O$31,"") -> 0 | Q58: =+M58-O58 -> 0 | R58: 0 | S58: =IFERROR(R58/R$31,"") -> 0 | T58: =+M58-R58 -> 0
B59: Printing & Stationary - 100 | C59: Printing & Stationery | D59: 412.75 | E59: =IFERROR(D59/D$31,"") -> 0.00042030276 | F59: 583.2 | G59: =IFERROR(F59/F$31,"") -> 0.00060787594 | H59: =+D59-F59 -> -170.45 | I59: 297.08 | J59: =IFERROR(I59/I$31,"") -> 0.00031134346 | K59: =+D59-I59 -> 115.67 | M59: 1726.8 | N59: =IFERROR(M59/M$31,"") -> 0.00040143976 | O59: 2330.08 | P59: =IFERROR(O59/O$31,"") -> 0.00052113067 | Q59: =+M59-O59 -> -603.28 | R59: 1842.08 | S59: =IFERROR(R59/R$31,"") -> 0.00041507157 | T59: =+M59-R59 -> -115.28
B60: Operating Supplies - 100 | C60: Operating Supplies | D60: 4683.44 | E60: =IFERROR(D60/D$31,"") -> 0.0047691405 | F60: 3936.6 | G60: =IFERROR(F60/F$31,"") -> 0.0041031626 | H60: =+D60-F60 -> 746.84 | I60: 5256.29 | J60: =IFERROR(I60/I$31,"") -> 0.005508656 | K60: =+D60-I60 -> -572.85 | M60: 15231.05 | N60: =IFERROR(M60/M$31,"") -> 0.0035408553 | O60: 15728.04 | P60: =IFERROR(O60/O$31,"") -> 0.003517632 | Q60: =+M60-O60 -> -496.99 | R60: 16704.27 | S60: =IFERROR(R60/R$31,"") -> 0.003763934 | T60: =+M60-R60 -> -1473.22
B61: Cleaning Supplies - 100 | C61: Cleaning Supplies | D61: 1166.91 | E61: =IFERROR(D61/D$31,"") -> 0.0011882629 | F61: 1640.25 | G61: =IFERROR(F61/F$31,"") -> 0.0017096511 | H61: =+D61-F61 -> -473.34 | I61: 1881.25 | J61: =IFERROR(I61/I$31,"") -> 0.0019715729 | K61: =+D61-I61 -> -714.34 | M61: 5620.51 | N61: =IFERROR(M61/M$31,"") -> 0.0013066343 | O61: 6553.35 | P61: =IFERROR(O61/O$31,"") -> 0.00146568 | Q61: =+M61-O61 -> -932.84 | R61: 6576.28 | S61: =IFERROR(R61/R$31,"") -> 0.0014818178 | T61: =+M61-R61 -> -955.77
B62: Guest Supplies - 100 | C62: Guest Supplies | D62: 3721.3 | E62: =IFERROR(D62/D$31,"") -> 0.0037893947 | F62: 3499.2 | G62: =IFERROR(F62/F$31,"") -> 0.0036472556 | H62: =+D62-F62 -> 222.1 | I62: 4136.93 | J62: =IFERROR(I62/I$31,"") -> 0.0043355531 | K62: =+D62-I62 -> -415.63 | M62: 13428.3 | N62: =IFERROR(M62/M$31,"") -> 0.003121759 | O62: 13980.48 | P62: =IFERROR(O62/O$31,"") -> 0.003126784 | Q62: =+M62-O62 -> -552.18 | R62: 13503.74 | S62: =IFERROR(R62/R$31,"") -> 0.0030427661 | T62: =+M62-R62 -> -75.44
B63: Decorations - 100 | C63: Decorations | D63: 0 | E63: =IFERROR(D63/D$31,"") -> 0 | F63: 0 | G63: =IFERROR(F63/F$31,"") -> 0 | H63: =+D63-F63 -> 0 | I63: 0 | J63: =IFERROR(I63/I$31,"") -> 0 | K63: =+D63-I63 -> 0 | M63: 0 | N63: =IFERROR(M63/M$31,"") -> 0 | O63: 0 | P63: =IFERROR(O63/O$31,"") -> 0 | Q63: =+M63-O63 -> 0 | R63: -3600 | S63: =IFERROR(R63/R$31,"") -> -0.00081117956 | T63: =+M63-R63 -> 3600
B64: Entertainment- In-House - 100 | C64: Entertainment - In-House | D64: 0 | E64: =IFERROR(D64/D$31,"") -> 0 | F64: 0 | G64: =IFERROR(F64/F$31,"") -> 0 | H64: =+D64-F64 -> 0 | I64: 0 | J64: =IFERROR(I64/I$31,"") -> 0 | K64: =+D64-I64 -> 0 | M64: 0 | N64: =IFERROR(M64/M$31,"") -> 0 | O64: 0 | P64: =IFERROR(O64/O$31,"") -> 0 | Q64: =+M64-O64 -> 0 | R64: 0 | S64: =IFERROR(R64/R$31,"") -> 0 | T64: =+M64-R64 -> 0
B65: Equipment Rental - 100 | C65: Equipment Rental | D65: 0 | E65: =IFERROR(D65/D$31,"") -> 0 | F65: 0 | G65: =IFERROR(F65/F$31,"") -> 0 | H65: =+D65-F65 -> 0 | I65: 0 | J65: =IFERROR(I65/I$31,"") -> 0 | K65: =+D65-I65 -> 0 | M65: 0 | N65: =IFERROR(M65/M$31,"") -> 0 | O65: 0 | P65: =IFERROR(O65/O$31,"") -> 0 | Q65: =+M65-O65 -> 0 | R65: 0 | S65: =IFERROR(R65/R$31,"") -> 0 | T65: =+M65-R65 -> 0
B66: Laundry & Dry Cleaning - 100 | C66: Laundry & Dry Cleaning | D66: 23555.6 | E66: =IFERROR(D66/D$31,"") -> 0.023986635 | F66: 22927.05 | G66: =IFERROR(F66/F$31,"") -> 0.023897123 | H66: =+D66-F66 -> 628.55 | I66: 24484.8 | J66: =IFERROR(I66/I$31,"") -> 0.025660369 | K66: =+D66-I66 -> -929.2 | M66: 82537.05 | N66: =IFERROR(M66/M$31,"") -> 0.019187893 | O66: 91601.27 | P66: =IFERROR(O66/O$31,"") -> 0.020486949 | Q66: =+M66-O66 -> -9064.22 | R66: 92465.62 | S66: =IFERROR(R66/R$31,"") -> 0.020835061 | T66: =+M66-R66 -> -9928.57
B67: Contract Services - 100 | C67: Contract Services | D67: 2503 | E67: =IFERROR(D67/D$31,"") -> 0.0025488015 | F67: 2388 | G67: =IFERROR(F67/F$31,"") -> 0.0024890393 | H67: =+D67-F67 -> 115 | I67: 2160 | J67: =IFERROR(I67/I$31,"") -> 0.0022637063 | K67: =+D67-I67 -> 343 | M67: 13041.25 | N67: =IFERROR(M67/M$31,"") -> 0.0030317791 | O67: 15252 | P67: =IFERROR(O67/O$31,"") -> 0.003411164 | Q67: =+M67-O67 -> -2210.75 | R67: 11005.49 | S67: =IFERROR(R67/R$31,"") -> 0.0024798413 | T67: =+M67-R67 -> 2035.76
... B83: Reservations - 100 | C83: Total Reservations Fees & Other Exp | D83: 217.6 | E83: =IFERROR(D83/D$31,"") -> 0.00022158178 | F83: 320 | G83: =IFERROR(F83/F$31,"") -> 0.00033353961 | H83: =+D83-F83 -> -102.4 | I83: 518.4 | J83: =IFERROR(I83/I$31,"") -> 0.00054328952 | K83: =+D83-I83 -> -300.8 | M83: 1913.6 | N83: =IFERROR(M83/M$31,"") -> 0.0004448663 | O83: 1324.8 | P83: =IFERROR(O83/O$31,"") -> 0.00029629623 | Q83: =+M83-O83 -> 588.8 | R83: 1253.6 | S83: =IFERROR(R83/R$31,"") -> 0.00028247075 | T83: =+M83-R83 -> 660
B84: Total Other Expenses - 100 | C84: Total Operations Expense | D84: =SUM(D56:D83) -> 139519.16 | E84: =IFERROR(D84/D$31,"") -> 0.14207217 | F84: =SUM(F56:F83) -> 110257.79 | G84: =IFERROR(F84/F$31,"") -> 0.11492294 | H84: =+D84-F84 -> 29261.37 | I84: =SUM(I56:I83) -> 127705.26 | J84: =IFERROR(I84/I$31,"") -> 0.13383667 | K84: =+D84-I84 -> 11813.9 | M84: =SUM(M56:M83) -> 512476.37 | N84: =IFERROR(M84/M$31,"") -> 0.11913852 | O84: =SUM(O56:O83) -> 480280.16 | P84: =IFERROR(O84/O$31,"") -> 0.10741636 | Q84: =+M84-O84 -> 32196.21 | R84: =SUM(R56:R83) -> 482098.55 | S84: =IFERROR(R84/R$31,"") -> 0.10863014 | T84: =+M84-R84 -> 30377.82
B86: Total Departmental Expenses - 100 | C86: Total Expenses | D86: =+D53+D84 -> 278444.2 | E86: =IFERROR(D86/D$31,"") -> 0.28353935 | F86: =+F53+F84 -> 245118.35 | G86: =IFERROR(F86/F$31,"") -> 0.25548962 | H86: =+D86-F86 -> 33325.85 | I86: =+I53+I84 -> 261858.86 | J86: =IFERROR(I86/I$31,"") -> 0.27443128 | K86: =+D86-I86 -> 16585.34 | M86: =+M53+M84 -> 1048369.3 | N86: =IFERROR(M86/M$31,"") -> 0.24372082 | O86: =+O53+O84 -> 1019678.2 | P86: =IFERROR(O86/O$31,"") -> 0.22805466 | Q86: =+M86-O86 -> 28691.04 | R86: =+R53+R84 -> 1030793.9 | S86: =IFERROR(R86/R$31,"") -> 0.23226638 | T86: =+M86-R86 -> 17575.33
B87: Dept Profit - 100 | C87: Department Profit (Loss) | D87: =+D31-D86 -> 703585.99 | E87: =IFERROR(D87/D$31,"") -> 0.71646065 | F87: =+F31-F86 -> 714287.94 | G87: =IFERROR(F87/F$31,"") -> 0.74451038 | H87: =+D87-F87 -> -10701.95 | I87: =+I31-I86 -> 692328.51 | J87: =IFERROR(I87/I$31,"") -> 0.72556872 | K87: =+D87-I87 -> 11257.48 | M87: =+M31-M86 -> 3253147.9 | N87: =IFERROR(M87/M$31,"") -> 0.75627918 | O87: =+O31-O86 -> 3451522.8 | P87: =IFERROR(O87/O$31,"") -> 0.77194534 | Q87: =+M87-O87 -> -198374.96 | R87: =+R31-R86 -> 3407187.7 | S87: =IFERROR(R87/R$31,"") -> 0.76773362 | T87: =+M87-R87 -> -154039.81

Sheet F&B_CONS
V1: ANG
C2: =+Summary!$C$2 -> Angler's | V2: Apr
C3: =+Summary!$C$3 -> STATEMENT OF INCOME
C4: =+Summary!$C$4 -> FOR THE PERIOD ENDING APR 2025
D6: =Year&" "&UPPER(Month)&" - PERIODIC" -> 2025 APR - PERIODIC | M6: =Year&" "&UPPER(Month)&" - YEAR TO DATE" -> 2025 APR - YEAR TO DATE
D7: Actual | F7: Budget | H7: VARIANCE | I7: Actual - Last Year | K7: VARIANCE | M7: Actual | O7: Budget | Q7: VARIANCE | R7: Actual - Last Year | T7: VARIANCE
D8: $ | E8: % | F8: $ | G8: % | H8: $ | I8: Actual | J8: % | K8: $ | M8: $ | N8: % | O8: $ | P8: % | Q8: $ | R8: Actual | S8: % | T8: $
C9: Revenues
C10: Food Revenue
B11: Venues Food - 200 | C11: Venues Food Rev | D11: 226705.51 | E11: =IFERROR(D11/D$35,"") -> 0.59795942 | F11: 219945 | G11: =IFERROR(F11/F$35,"") -> 0.50260983 | H11: =+D11-F11 -> 6760.51 | I11: 133831.43 | J11: =IFERROR(I11/I$35,"") -> 0.53325454 | K11: =+D11-I11 -> 92874.08 | M11: 905806.53 | N11: =IFERROR(M11/M$35,"") -> 0.59437458 | O11: 901635 | P11: =IFERROR(O11/O$35,"") -> 0.50294975 | Q11: =+M11-O11 -> 4171.53 | R11: 497713.29 | S11: =IFERROR(R11/R$35,"") -> 0.54294023 | T11: =+M11-R11 -> 408093.24
B12: Venue Food - Minibar Revenue - 200 | C12: Mini Bar Food Rev | D12: 2867.56 | E12: =IFERROR(D12/D$35,"") -> 0.0075634885 | F12: 2587.95 | G12: =IFERROR(F12/F$35,"") -> 0.0059138835 | H12: =+D12-F12 -> 279.61 | I12: 2434 | J12: =IFERROR(I12/I$35,"") -> 0.0096983313 | K12: =+D12-I12 -> 433.56 | M12: 12080.25 | N12: =IFERROR(M12/M$35,"") -> 0.0079268512 | O12: 10339.73 | P12: =IFERROR(O12/O$35,"") -> 0.005767705 | Q12: =+M12-O12 -> 1740.52 | R12: 10012.09 | S12: =IFERROR(R12/R$35,"") -> 0.010921883 | T12: =+M12-R12 -> 2068.16
B13: Food Revenue - 205 | C13: Pool Bar Food Rev | D13: 0 | E13: =IFERROR(D13/D$35,"") -> 0 | F13: 0 | G13: =IFERROR(F13/F$35,"") -> 0 | H13: =+D13-F13 -> 0 | I13: 0 | J13: =IFERROR(I13/I$35,"") -> 0 | K13: =+D13-I13 -> 0 | M13: 0 | N13: =IFERROR(M13/M$35,"") -> 0 | O13: 0 | P13: =IFERROR(O13/O$35,"") -> 0 | Q13: =+M13-O13 -> 0 | R13: 0 | S13: =IFERROR(R13/R$35,"") -> 0 | T13: =+M13-R13 -> 0
B14: Food Revenue - 204 | C14: Market Bar Food Rev | D14: 0 | E14: =IFERROR(D14/D$35,"") -> 0 | F14: 0 | G14: =IFERROR(F14/F$35,"") -> 0 | H14: =+D14-F14 -> 0 | I14: 0 | J14: =IFERROR(I14/I$35,"") -> 0 | K14: =+D14-I14 -> 0 | M14: 0 | N14: =IFERROR(M14/M$35,"") -> 0 | O14: 0 | P14: =IFERROR(O14/O$35,"") -> 0 | Q14: =+M14-O14 -> 0 | R14: 0 | S14: =IFERROR(R14/R$35,"") -> 0 | T14: =+M14-R14 -> 0
B15: Room Service Food - 200 | C15: In Room Dining Food Rev | D15: 0 | E15: =IFERROR(D15/D$35,"") -> 0 | F15: 0 | G15: =IFERROR(F15/F$35,"") -> 0 | H15: =+D15-F15 -> 0 | I15: 0 | J15: =IFERROR(I15/I$35,"") -> 0 | K15: =+D15-I15 -> 0 | M15: 0 | N15: =IFERROR(M15/M$35,"") -> 0 | O15: 0 | P15: =IFERROR(O15/O$35,"") -> 0 | Q15: =+M15-O15 -> 0 | R15: 0 | S15: =IFERROR(R15/R$35,"") -> 0 | T15: =+M15-R15 -> 0
B16: Total Banquets Food - 200 | C16: Banquet-Catering & CS Food Rev | D16: 0 | E16: =IFERROR(D16/D$35,"") -> 0 | F16: 0 | G16: =IFERROR(F16/F$35,"") -> 0 | H16: =+D16-F16 -> 0 | I16: 0 | J16: =IFERROR(I16/I$35,"") -> 0 | K16: =+D16-I16 -> 0 | M16: 0 | N16: =IFERROR(M16/M$35,"") -> 0 | O16: 0 | P16: =IFERROR(O16/O$35,"") -> 0 | Q16: =+M16-O16 -> 0 | R16: 8277.21 | S16: =IFERROR(R16/R$35,"") -> 0.0090293557 | T16: =+M16-R16 -> -8277.21
B17: Total Food Revenue - 200 | C17: Total Food Revenue | D17: =SUM(D11:D16) -> 229573.07 | E17: =IFERROR(D17/D$35,"") -> 0.60552291 | F17: =SUM(F11:F16) -> 222532.95 | G17: =IFERROR(F17/F$35,"") -> 0.50852371 | H17: =+D17-F17 -> 7040.12 | I17: =SUM(I11:I16) -> 136265.43 | J17: =IFERROR(I17/I$35,"") -> 0.54295287 | K17: =+D17-I17 -> 93307.64 | M17: =SUM(M11:M16) -> 917886.78 | N17: =IFERROR(M17/M$35,"") -> 0.60230143 | O17: =SUM(O11:O16) -> 911974.73 | P17: =IFERROR(O17/O$35,"") -> 0.50871746 | Q17: =+M17-O17 -> 5912.05 | R17: =SUM(R11:R16) -> 516002.59 | S17: =IFERROR(R17/R$35,"") -> 0.56289147 | T17: =+M17-R17 -> 401884.19
C18: Beverage Revenue
B19: Venues Beverage - 200 | C19: Venues Beverage Rev | D19: 85269.01 | E19: =IFERROR(D19/D$35,"") -> 0.22490591 | F19: 134805 | G19: =IFERROR(F19/F$35,"") -> 0.30805118 | H19: =+D19-F19 -> -49535.99 | I19: 76097.09 | J19: =IFERROR(I19/I$35,"") -> 0.30321068 | K19: =+D19-I19 -> 9171.92 | M19: 346194.51 | N19: =IFERROR(M19/M$35,"") -> 0.22716685 | O19: 552615 | P19: =IFERROR(O19/O$35,"") -> 0.30825953 | Q19: =+M19-O19 -> -206420.49 | R19: 235369.46 | S19: =IFERROR(R19/R$35,"") -> 0.25675736 | T19: =+M19-R19 -> 110825.05
B20: Venue Beverage - Minibar Revenue - 200 | C20: Mini Bar Beverage Rev | D20: 2343.12 | E20: =IFERROR(D20/D$35,"") -> 0.0061802233 | F20: 2879.55 | G20: =IFERROR(F20/F$35,"") -> 0.0065802365 | H20: =+D20-F20 -> -536.43 | I20: 2374 | J20: =IFERROR(I20/I$35,"") -> 0.0094592599 | K20: =+D20-I20 -> -30.88 | M20: 11789.51 | N20: =IFERROR(M20/M$35,"") -> 0.0077360726 | O20: 11504.77 | P20: =IFERROR(O20/O$35,"") -> 0.0064175872 | Q20: =+M20-O20 -> 284.74 | R20: 12103.67 | S20: =IFERROR(R20/R$35,"") -> 0.013203524 | T20: =+M20-R20 -> -314.16
B21: Beverage Revenue - 205 | C21: Pool Bar Beverage Rev | D21: 0 | E21: =IFERROR(D21/D$35,"") -> 0 | F21: 0 | G21: =IFERROR(F21/F$35,"") -> 0 | H21: =+D21-F21 -> 0 | I21: 0 | J21: =IFERROR(I21/I$35,"") -> 0 | K21: =+D21-I21 -> 0 | M21: 0 | N21: =IFERROR(M21/M$35,"") -> 0 | O21: 0 | P21: =IFERROR(O21/O$35,"") -> 0 | Q21: =+M21-O21 -> 0 | R21: 0 | S21: =IFERROR(R21/R$35,"") -> 0 | T21: =+M21-R21 -> 0
B22: Beverage Revenue - 204 | C22: Market Bar Beverage Rev | D22: 0 | E22: =IFERROR(D22/D$35,"") -> 0 | F22: 0 | G22: =IFERROR(F22/F$35,"") -> 0 | H22: =+D22-F22 -> 0 | I22: 0 | J22: =IFERROR(I22/I$35,"") -> 0 | K22: =+D22-I22 -> 0 | M22: 0 | N22: =IFERROR(M22/M$35,"") -> 0 | O22: 0 | P22: =IFERROR(O22/O$35,"") -> 0 | Q22: =+M22-O22 -> 0 | R22: 0 | S22: =IFERROR(R22/R$35,"") -> 0 | T22: =+M22-R22 -> 0
B23: Room Service Beverage - 200 | C23: In Room Dining Beverage Rev | D23: 0 | E23: =IFERROR(D23/D$35,"") -> 0 | F23: 0 | G23: =IFERROR(F23/F$35,"") -> 0 | H23: =+D23-F23 -> 0 | I23: 0 | J23: =IFERROR(I23/I$35,"") -> 0 | K23: =+D23-I23 -> 0 | M23: 0 | N23: =IFERROR(M23/M$35,"") -> 0 | O23: 0 | P23: =IFERROR(O23/O$35,"") -> 0 | Q23: =+M23-O23 -> 0 | R23: 0 | S23: =IFERROR(R23/R$35,"") -> 0 | T23: =+M23-R23 -> 0
B24: Total Banquets Beverage- 200 | C24: Banquet-Catering & CS Beverage Rev | D24: 0 | E24: =IFERROR(D24/D$35,"") -> 0 | F24: 0 | G24: =IFERROR(F24/F$35,"") -> 0 | H24: =+D24-F24 -> 0 | I24: 0 | J24: =IFERROR(I24/I$35,"") -> 0 | K24: =+D24-I24 -> 0 | M24: 0 | N24: =IFERROR(M24/M$35,"") -> 0 | O24: 0 | P24: =IFERROR(O24/O$35,"") -> 0 | Q24: =+M24-O24 -> 0 | R24: 0 | S24: =IFERROR(R24/R$35,"") -> 0 | T24: =+M24-R24 -> 0
B25: Total Beverage Revenue - 200 | C25: Total Beverage Revenue | D25: =SUM(D19:D24) -> 87612.13 | E25: =IFERROR(D25/D$35,"") -> 0.23108613 | F25: =SUM(F19:F24) -> 137684.55 | G25: =IFERROR(F25/F$35,"") -> 0.31463142 | H25: =+D25-F25 -> -50072.42 | I25: =SUM(I19:I24) -> 78471.09 | J25: =IFERROR(I25/I$35,"") -> 0.31266994 | K25: =+D25-I25 -> 9141.04 | M25: =SUM(M19:M24) -> 357984.02 | N25: =IFERROR(M25/M$35,"") -> 0.23490292 | O25: =SUM(O19:O24) -> 564119.77 | P25: =IFERROR(O25/O$35,"") -> 0.31467711 | Q25: =+M25-O25 -> -206135.75 | R25: =SUM(R19:R24) -> 247473.13 | S25: =IFERROR(R25/R$35,"") -> 0.26996088 | T25: =+M25-R25 -> 110510.89
B26: Other - Allowances - 200 | C26: Food & Beverage: Allowances | D26: -38 | E26: =IFERROR(D26/D$35,"") -> -0.00010022896 | F26: 0 | G26: =IFERROR(F26/F$35,"") -> 0 | H26: =+D26-F26 -> -38 | I26: 0 | J26: =IFERROR(I26/I$35,"") -> 0 | K26: =+D26-I26 -> -38 | M26: -727.2 | N26: =IFERROR(M26/M$35,"") -> -0.00047717607 | O26: 0 | P26: =IFERROR(O26/O$35,"") -> 0 | Q26: =+M26-O26 -> -727.2 | R26: -43.18 | S26: =IFERROR(R26/R$35,"") -> -4.7103744e-05 | T26: =+M26-R26 -> -684.02
B27: Total F&B Division Revenue - 200 | C27: Total Food & Beverage Revenue | D27: =+D17+D25+D26 -> 317147.2 | E27: =IFERROR(D27/D$35,"") -> 0.83650881 | F27: =F17+F25+F26 -> 360217.5 | G27: =IFERROR(F27/F$35,"") -> 0.82315513 | H27: =+D27-F27 -> -43070.3 | I27: =I17+I25+I26 -> 214736.52 | J27: =IFERROR(I27/I$35,"") -> 0.85562281 | K27: =+D27-I27 -> 102410.68 | M27: =+M17+M25+M26 -> 1275143.6 | N27: =IFERROR(M27/M$35,"") -> 0.83672718 | O27: =O17+O25+O26 -> 1476094.5 | P27: =IFERROR(O27/O$35,"") -> 0.82339457 | Q27: =+M27-O27 -> -200950.9 | R27: =R17+R25+R26 -> 763432.54 | S27: =IFERROR(R27/R$35,"") -> 0.83280525 | T27: =+M27-R27 -> 511711.06
C28: Other Revenue
B29: Other - Audiovisual Revenue - 200 | C29: Audio/Visual Rentals | D29: 9457 | E29: =IFERROR(D29/D$35,"") -> 0.024943824 | F29: 6000 | G29: =IFERROR(F29/F$35,"") -> 0.013710968 | H29: =+D29-F29 -> 3457 | I29: 1062 | J29: =IFERROR(I29/I$35,"") -> 0.0042315644 | K29: =+D29-I29 -> 8395 | M29: 37729 | N29: =IFERROR(M29/M$35,"") -> 0.024757117 | O29: 24000 | P29: =IFERROR(O29/O$35,"") -> 0.013387672 | Q29: =+M29-O29 -> 13729 | R29: 26047 | S29: =IFERROR(R29/R$35,"") -> 0.028413877 | T29: =+M29-R29 -> 11682
B30: Other - Function Room Rental & Setup Charges - 200 | C30: Public Room Rental | D30: 0 | E30: =IFERROR(D30/D$35,"") -> 0 | F30: 0 | G30: =IFERROR(F30/F$35,"") -> 0 | H30: =+D30-F30 -> 0 | I30: 0 | J30: =IFERROR(I30/I$35,"") -> 0 | K30: =+D30-I30 -> 0 | M30: 0 | N30: =IFERROR(M30/M$35,"") -> 0 | O30: 0 | P30: =IFERROR(O30/O$35,"") -> 0 | Q30: =+M30-O30 -> 0 | R30: 1000 | S30: =IFERROR(R30/R$35,"") -> 0.0010908695 | T30: =+M30-R30 -> -1000
B31: Other - Surcharges & Service Charges - 200 | C31: Surcharges & Services Charges | D31: 60636.74 | E31: =IFERROR(D31/D$35,"") -> 0.15993572 | F31: 70950 | G31: =IFERROR(F31/F$35,"") -> 0.1621322 | H31: =+D31-F31 -> -10313.26 | I31: 37778.19 | J31: =IFERROR(I31/I$35,"") -> 0.1505281 | K31: =+D31-I31 -> 22858.55 | M31: 244198.1 | N31: =IFERROR(M31/M$35,"") -> 0.16023857 | O31: 290850 | P31: =IFERROR(O31/O$35,"") -> 0.16224186 | Q31: =+M31-O31 -> -46651.9 | R31: 130447.39 | S31: =IFERROR(R31/R$35,"") -> 0.14230108 | T31: =+M31-R31 -> 113750.71
B32: Other - Other Revenue - 200 | C32: Miscellaneous Other Revenue | D32: -8109.01 | E32: =IFERROR(D32/D$35,"") -> -0.021388359 | F32: 438.35 | G32: =IFERROR(F32/F$35,"") -> 0.0010017005 | H32: =+D32-F32 -> -8547.36 | I32: -2605.7 | J32: =IFERROR(I32/I$35,"") -> -0.010382474 | K32: =+D32-I32 -> -5503.31 | M32: -33104.91 | N32: =IFERROR(M32/M$35,"") -> -0.02172287 | O32: 1749.49 | P32: =IFERROR(O32/O$35,"") -> 0.00097589996 | Q32: =+M32-O32 -> -34854.4 | R32: -4226.97 | S32: =IFERROR(R32/R$35,"") -> -0.0046110725 | T32: =+M32-R32 -> -28877.94
B33: Total Other F&B Revenue - 200 | C33: Total Other Revenue | D33: =SUM(D29:D32) -> 61984.73 | E33: =IFERROR(D33/D$35,"") -> 0.16349119 | F33: =SUM(F29:F32) -> 77388.35 | G33: =IFERROR(F33/F$35,"") -> 0.17684487 | H33: =+D33-F33 -> -15403.62 | I33: =SUM(I29:I32) -> 36234.49 | J33: =IFERROR(I33/I$35,"") -> 0.14437719 | K33: =+D33-I33 -> 25750.24 | M33: =SUM(M29:M32) -> 248822.19 | N33: =IFERROR(M33/M$35,"") -> 0.16327282 | O33: =SUM(O29:O32) -> 316599.49 | P33: =IFERROR(O33/O$35,"") -> 0.17660543 | Q33: =+M33-O33 -> -67777.3 | R33: =SUM(R29:R32) -> 153267.42 | S33: =IFERROR(R33/R$35,"") -> 0.16719475 | T33: =+M33-R33 -> 95554.77
B35: Total Revenue - 200 | C35: Total Revenue | D35: =+D27+D33 -> 379131.93 | E35: =IFERROR(D35/D$35,"") -> 1 | F35: =+F27+F33 -> 437605.85 | G35: =IFERROR(F35/F$35,"") -> 1 | H35: =+D35-F35 -> -58473.92 | I35: =+I27+I33 -> 250971.01 | J35: =IFERROR(I35/I$35,"") -> 1 | K35: =+D35-I35 -> 128160.92 | M35: =+M27+M33 -> 1523965.8 | N35: =IFERROR(M35/M$35,"") -> 1 | O35: =+O27+O33 -> 1792694 | P35: =IFERROR(O35/O$35,"") -> 1 | Q35: =+M35-O35 -> -268728.2 | R35: =+R27+R33 -> 916699.96 | S35: =IFERROR(R35/R$35,"") -> 1 | T35: =+M35-R35 -> 607265.83
C37: Cost of Sales
C38: Cost of Food & Beverage Sales
B39: Cost of Food Sales - 200 | C39: Cost of Food Sales | D39: 65514.91 | E39: =IFERROR(D39/D$17,"") -> 0.28537716 | F39: 66687.42 | G39: =IFERROR(F39/F$17,"") -> 0.29967436 | H39: =+D39-F39 -> -1172.51 | I39: 55246.67 | J39: =IFERROR(I39/I$17,"") -> 0.40543423 | K39: =+D39-I39 -> 10268.24 | M39: 262051.14 | N39: =IFERROR(M39/M$17,"") -> 0.28549397 | O39: 273302.9 | P39: =IFERROR(O39/O$17,"") -> 0.29968254 | Q39: =+M39-O39 -> -11251.76 | R39: 172398.03 | S39: =IFERROR(R39/R$17,"") -> 0.33410303 | T39: =+M39-R39 -> 89653.11
B40: Cost of Beverage Sales - 200 | C40: Cost of Beverage Sales | D40: 21381.25 | E40: =+IFERROR(D40/D$25,"") -> 0.2440444 | F40: 24975.35 | G40: =+IFERROR(F40/F$25,"") -> 0.18139544 | H40: =+D40-F40 -> -3594.1 | I40: 23380.27 | J40: =+IFERROR(I40/I$25,"") -> 0.29794756 | K40: =+D40-I40 -> -1999.02 | M40: 63521.14 | N40: =+IFERROR(M40/M$25,"") -> 0.17744127 | O40: 102294.42 | P40: =+IFERROR(O40/O$25,"") -> 0.18133458 | Q40: =+M40-O40 -> -38773.28 | R40: 62470.6 | S40: =+IFERROR(R40/R$25,"") -> 0.25243387 | T40: =+M40-R40 -> 1050.54
B41: Cost of Food & Beverage Sales - 200 | C41: Total Cost of Food & Beverage Sales | D41: =+SUM(D39:D40) -> 86896.16 | E41: =+IFERROR(D41/D$27,"") -> 0.27399315 | F41: =+SUM(F39:F40) -> 91662.77 | G41: =+IFERROR(F41/F$27,"") -> 0.25446507 | H41: =+D41-F41 -> -4766.61 | I41: =+SUM(I39:I40) -> 78626.94 | J41: =+IFERROR(I41/I$27,"") -> 0.36615542 | K41: =+D41-I41 -> 8269.22 | M41: =+SUM(M39:M40) -> 325572.28 | N41: =+IFERROR(M41/M$27,"") -> 0.25532205 | O41: =+SUM(O39:O40) -> 375597.32 | P41: =+IFERROR(O41/O$27,"") -> 0.25445344 | Q41: =+M41-O41 -> -50025.04 | R41: =+SUM(R39:R40) -> 234868.63 | S41: =+IFERROR(R41/R$27,"") -> 0.30764818 | T41: =+M41-R41 -> 90703.65
C42: Cost of Other Revenue
B43: Cost of Other Sales - 200 | C43: Total Cost of Other Revenue | D43: 2090.84 | E43: =+IFERROR(D43/D$33,"") -> 0.033731534 | F43: 474.51 | G43: =+IFERROR(F43/F$33,"") -> 0.0061315431 | H43: =+D43-F43 -> 1616.33 | I43: 1545.89 | J43: =+IFERROR(I43/I$33,"") -> 0.042663495 | K43: =+D43-I43 -> 544.95 | M43: 11058.76 | N43: =+IFERROR(M43/M$33,"") -> 0.044444428 | O43: 1895.82 | P43: =+IFERROR(O43/O$33,"") -> 0.0059880703 | Q43: =+M43-O43 -> 9162.94 | R43: 8297.37 | S43: =+IFERROR(R43/R$33,"") -> 0.054136554 | T43: =+M43-R43 -> 2761.39
B44: Total Cost of F&B Division Sales - 200 | C44: Total Cost of Sales | D44: =+D41+D43 -> 88987 | E44: =IFERROR(D44/D$35,"") -> 0.23471249 | F44: =+F41+F43 -> 92137.28 | G44: =IFERROR(F44/F$35,"") -> 0.21054856 | H44: =+D44-F44 -> -3150.28 | I44: =+I41+I43 -> 80172.83 | J44: =IFERROR(I44/I$35,"") -> 0.31945056 | K44: =+D44-I44 -> 8814.17 | M44: =+M41+M43 -> 336631.04 | N44: =IFERROR(M44/M$35,"") -> 0.22089147 | O44: =+O41+O43 -> 377493.14 | P44: =IFERROR(O44/O$35,"") -> 0.21057311 | Q44: =+M44-O44 -> -40862.1 | R44: =+R41+R43 -> 243166 | S44: =IFERROR(R44/R$35,"") -> 0.26526237 | T44: =+M44-R44 -> 93465.04
C46: Gross Profit | D46: =+D35-D44 -> 290144.93 | E46: =IFERROR(D46/D$35,"") -> 0.76528751 | F46: =+F35-F44 -> 345468.57 | G46: =IFERROR(F46/F$35,"") -> 0.78945144 | H46: =+D46-F46 -> -55323.64 | I46: =+I35-I44 -> 170798.18 | J46: =IFERROR(I46/I$35,"") -> 0.68054944 | K46: =+D46-I46 -> 119346.75 | M46: =+M35-M44 -> 1187334.8 | N46: =IFERROR(M46/M$35,"") -> 0.77910853 | O46: =+O35-O44 -> 1415200.9 | P46: =IFERROR(O46/O$35,"") -> 0.78942689 | Q46: =+M46-O46 -> -227866.1 | R46: =+R35-R44 -> 673533.96 | S46: =IFERROR(R46/R$35,"") -> 0.73473763 | T46: =+M46-R46 -> 513800.79
C48: Labor & Related Expenses
C49: Salaries & Wages
B50: S&W Management - 200 | C50: Management | D50: 0 | E50: =IFERROR(D50/D$35,"") -> 0 | F50: 0 | G50: =IFERROR(F50/F$35,"") -> 0 | H50: =+D50-F50 -> 0 | I50: 0 | J50: =IFERROR(I50/I$35,"") -> 0 | K50: =+D50-I50 -> 0 | M50: 0 | N50: =IFERROR(M50/M$35,"") -> 0 | O50: 0 | P50: =IFERROR(O50/O$35,"") -> 0 | Q50: =+M50-O50 -> 0 | R50: 0 | S50: =IFERROR(R50/R$35,"") -> 0 | T50: =+M50-R50 -> 0
C51: Non-Management
B52: S&W Non-Management - 200 | C52: Non-Management | D52: 132895.06 | E52: =IFERROR(D52/D$35,"") -> 0.35052458 | F52: 81078.75 | G52: =IFERROR(F52/F$35,"") -> 0.18527803 | H52: =+D52-F52 -> 51816.31 | I52: 65571.63 | J52: =IFERROR(I52/I$35,"") -> 0.26127173 | K52: =+D52-I52 -> 67323.43 | M52: 443822.13 | N52: =IFERROR(M52/M$35,"") -> 0.29122841 | O52: 332246.25 | P52: =IFERROR(O52/O$35,"") -> 0.1853335 | Q52: =+M52-O52 -> 111575.88 | R52: 213209.98 | S52: =IFERROR(R52/R$35,"") -> 0.23258426 | T52: =+M52-R52 -> 230612.15
B53: S&W Other - 200 | C53: Other S&W | D53: 0 | E53: =IFERROR(D53/D$35,"") -> 0 | F53: 0 | G53: =IFERROR(F53/F$35,"") -> 0 | H53: =+D53-F53 -> 0 | I53: 0 | J53: =IFERROR(I53/I$35,"") -> 0 | K53: =+D53-I53 -> 0 | M53: 0 | N53: =IFERROR(M53/M$35,"") -> 0 | O53: 0 | P53: =IFERROR(O53/O$35,"") -> 0 | Q53: =+M53-O53 -> 0 | R53: 0 | S53: =IFERROR(R53/R$35,"") -> 0 | T53: =+M53-R53 -> 0
B54: Total Salaries & Wages - 200 | C54: Total Salaries and Wages | D54: =+D50+D52+D53 -> 132895.06 | E54: =IFERROR(D54/D$35,"") -> 0.35052458 | F54: =+F50+F52+F53 -> 81078.75 | G54: =IFERROR(F54/F$35,"") -> 0.18527803 | H54: =+D54-F54 -> 51816.31 | I54: =+I50+I52+I53 -> 65571.63 | J54: =IFERROR(I54/I$35,"") -> 0.26127173 | K54: =+D54-I54 -> 67323.43 | M54: =+M50+M52+M53 -> 443822.13 | N54: =IFERROR(M54/M$35,"") -> 0.29122841 | O54: =+O50+O52+O53 -> 332246.25 | P54: =IFERROR(O54/O$35,"") -> 0.1853335 | Q54: =+M54-O54 -> 111575.88 | R54: =+R50+R52+R53 -> 213209.98 | S54: =IFERROR(R54/R$35,"") -> 0.23258426 | T54: =+M54-R54 -> 230612.15
B55: Total Service Charge Distribution - 200 | C55: Service Charge Distribution | D55: 45128.81 | E55: =IFERROR(D55/D$35,"") -> 0.11903194 | F55: 60307.5 | G55: =IFERROR(F55/F$35,"") -> 0.13781237 | H55: =+D55-F55 -> -15178.69 | I55: 31378.56 | J55: =IFERROR(I55/I$35,"") -> 0.12502862 | K55: =+D55-I55 -> 13750.25 | M55: 183575.95 | N55: =IFERROR(M55/M$35,"") -> 0.12045936 | O55: 247222.5 | P55: =IFERROR(O55/O$35,"") -> 0.13790558 | Q55: =+M55-O55 -> -63646.55 | R55: 114942.61 | S55: =IFERROR(R55/R$35,"") -> 0.12538738 | T55: =+M55-R55 -> 68633.34
B56: Total Contracted Leased & Outsourced Labor - 200 | C56: Contracted & Leased Labor | D56: 0 | E56: =IFERROR(D56/D$35,"") -> 0 | F56: 28828 | G56: =IFERROR(F56/F$35,"") -> 0.065876633 | H56: =+D56-F56 -> -28828 | I56: 27591.22 | J56: =IFERROR(I56/I$35,"") -> 0.10993788 | K56: =+D56-I56 -> -27591.22 | M56: 0 | N56: =IFERROR(M56/M$35,"") -> 0 | O56: 118132 | P56: =IFERROR(O56/O$35,"") -> 0.065896355 | Q56: =+M56-O56 -> -118132 | R56: 115814.18 | S56: =IFERROR(R56/R$35,"") -> 0.12633815 | T56: =+M56-R56 -> -115814.18
B57: Total Bonuses & Incentives - 200 | C57: Bonuses & Incentives | D57: 0 | E57: =IFERROR(D57/D$35,"") -> 0 | F57: 0 | G57: =IFERROR(F57/F$35,"") -> 0 | H57: =+D57-F57 -> 0 | I57: 0 | J57: =IFERROR(I57/I$35,"") -> 0 | K57: =+D57-I57 -> 0 | M57: 0 | N57: =IFERROR(M57/M$35,"") -> 0 | O57: 0 | P57: =IFERROR(O57/O$35,"") -> 0 | Q57: =+M57-O57 -> 0 | R57: 0 | S57: =IFERROR(R57/R$35,"") -> 0 | T57: =+M57-R57 -> 0
B58: Total Salaries Wages & Bonuses - 200 | C58: Total Labor Expense | D58: =+D54+SUM(D55:D57) -> 178023.87 | E58: =IFERROR(D58/D$35,"") -> 0.46955652 | F58: =+F54+SUM(F55:F57) -> 170214.25 | G58: =IFERROR(F58/F$35,"") -> 0.38896704 | H58: =+D58-F58 -> 7809.62 | I58: =+I54+SUM(I55:I57) -> 124541.41 | J58: =IFERROR(I58/I$35,"") -> 0.49623823 | K58: =+D58-I58 -> 53482.46 | M58: =+M54+SUM(M55:M57) -> 627398.08 | N58: =IFERROR(M58/M$35,"") -> 0.41168777 | O58: =+O54+SUM(O55:O57) -> 697600.75 | P58: =IFERROR(O58/O$35,"") -> 0.38913543 | Q58: =+M58-O58 -> -70202.67 | R58: =+R54+SUM(R55:R57) -> 443966.77 | S58: =IFERROR(R58/R$35,"") -> 0.4843098 | T58: =+M58-R58 -> 183431.31
B59: Total Payroll Taxes - 200 | C59: Payroll Taxes | D59: 4279 | E59: =IFERROR(D59/D$35,"") -> 0.011286309 | F59: 12071.725 | G59: =IFERROR(F59/F$35,"") -> 0.02758584 | H59: =+D59-F59 -> -7792.725 | I59: 7715.42 | J59: =IFERROR(I59/I$35,"") -> 0.030742276 | K59: =+D59-I59 -> -3436.42 | M59: 27101.41 | N59: =IFERROR(M59/M$35,"") -> 0.017783477 | O59: 49467.775 | P59: =IFERROR(O59/O$35,"") -> 0.027594099 | Q59: =+M59-O59 -> -22366.365 | R59: 29475.68 | S59: =IFERROR(R59/R$35,"") -> 0.032154119 | T59: =+M59-R59 -> -2374.27
B60: Total Supplemental Pay - 200 | C60: Supplemental Pay | D60: 0 | E60: =IFERROR(D60/D$35,"") -> 0 | F60: 0 | G60: =IFERROR(F60/F$35,"") -> 0 | H60: =+D60-F60 -> 0 | I60: 0 | J60: =IFERROR(I60/I$35,"") -> 0 | K60: =+D60-I60 -> 0 | M60: 0 | N60: =IFERROR(M60/M$35,"") -> 0 | O60: 0 | P60: =IFERROR(O60/O$35,"") -> 0 | Q60: =+M60-O60 -> 0 | R60: 2493.94 | S60: =IFERROR(R60/R$35,"") -> 0.002720563 | T60: =+M60-R60 -> -2493.94
B61: Total Employee Benefits - 200 | C61: Employee Benefits | D61: 825.11 | E61: =IFERROR(D61/D$35,"") -> 0.0021763137 | F61: 2156.5 | G61: =IFERROR(F61/F$35,"") -> 0.0049279506 | H61: =+D61-F61 -> -1331.39 | I61: 1209.98 | J61: =IFERROR(I61/I$35,"") -> 0.0048211943 | K61: =+D61-I61 -> -384.87 | M61: 3246.64 | N61: =IFERROR(M61/M$35,"") -> 0.002130389 | O61: 8837.5 | P61: =IFERROR(O61/O$35,"") -> 0.0049297315 | Q61: =+M61-O61 -> -5590.86 | R61: 6842.81 | S61: =IFERROR(R61/R$35,"") -> 0.0074646125 | T61: =+M61-R61 -> -3596.17
B62: Total Payroll-Related Expenses - 200 | C62: Total Payroll Related | D62: =SUM(D59:D61) -> 5104.11 | E62: =IFERROR(D62/D$35,"") -> 0.013462622 | F62: =SUM(F59:F61) -> 14228.225 | G62: =IFERROR(F62/F$35,"") -> 0.032513791 | H62: =+D62-F62 -> -9124.115 | I62: =SUM(I59:I61) -> 8925.4 | J62: =IFERROR(I62/I$35,"") -> 0.03556347 | K62: =+D62-I62 -> -3821.29 | M62: =SUM(M59:M61) -> 30348.05 | N62: =IFERROR(M62/M$35,"") -> 0.019913866 | O62: =SUM(O59:O61) -> 58305.275 | P62: =IFERROR(O62/O$35,"") -> 0.03252383 | Q62: =+M62-O62 -> -27957.225 | R62: =SUM(R59:R61) -> 38812.43 | S62: =IFERROR(R62/R$35,"") -> 0.042339295 | T62: =+M62-R62 -> -8464.38
B63: Total Labor Costs & Related Expenses - 200 | C63: Total Labor & Related Exp | D63: =+D58+D62 -> 183127.98 | E63: =IFERROR(D63/D$35,"") -> 0.48301914 | F63: =+F58+F62 -> 184442.48 | G63: =IFERROR(F63/F$35,"") -> 0.42148083 | H63: =+D63-F63 -> -1314.495 | I63: =+I58+I62 -> 133466.81 | J63: =IFERROR(I63/I$35,"") -> 0.5318017 | K63: =+D63-I63 -> 49661.17 | M63: =+M58+M62 -> 657746.13 | N63: =IFERROR(M63/M$35,"") -> 0.43160164 | O63: =+O58+O62 -> 755906.03 | P63: =IFERROR(O63/O$35,"") -> 0.42165926 | Q63: =+M63-O63 -> -98159.895 | R63: =+R58+R62 -> 482779.2 | S63: =IFERROR(R63/R$35,"") -> 0.52664909 | T63: =+M63-R63 -> 174966.93
C65: Other Expenses
B66: Printing & Stationary - 200 | C66: Printing & Stationery | D66: 0 | E66: =IFERROR(D66/D$35,"") -> 0 | F66: 0 | G66: =IFERROR(F66/F$35,"") -> 0 | H66: =+D66-F66 -> 0 | I66: 0 | J66: =IFERROR(I66/I$35,"") -> 0 | K66: =+D66-I66 -> 0 | M66: 0 | N66: =IFERROR(M66/M$35,"") -> 0 | O66: 0 | P66: =IFERROR(O66/O$35,"") -> 0 | Q66: =+M66-O66 -> 0 | R66: 0 | S66: =IFERROR(R66/R$35,"") -> 0 | T66: =+M66-R66 -> 0
B67: Operating Supplies - 200 | C67: Operating Supplies | D67: 4387.52 | E67: =IFERROR(D67/D$35,"") -> 0.011572542 | F67: 1396.5803 | G67: =IFERROR(F67/F$35,"") -> 0.0031914113 | H67: =+D67-F67 -> 2990.9397 | I67: 3553.17 | J67: =IFERROR(I67/I$35,"") -> 0.014157691 | K67: =+D67-I67 -> 834.35 | M67: 19303.49 | N67: =IFERROR(M67/M$35,"") -> 0.012666616 | O67: 6032.2915 | P67: =IFERROR(O67/O$35,"") -> 0.003364931 | Q67: =+M67-O67 -> 13271.198 | R67: 4478.15 | S67: =IFERROR(R67/R$35,"") -> 0.0048850771 | T67: =+M67-R67 -> 14825.34
B68: Cleaning Supplies - 200 | C68: Cleaning Supplies | D68: 3689.19 | E68: =IFERROR(D68/D$35,"") -> 0.0097306233 | F68: 1737.8453 | G68: =IFERROR(F68/F$35,"") -> 0.0039712571 | H68: =+D68-F68 -> 1951.3447 | I68: 2129.18 | J68: =IFERROR(I68/I$35,"") -> 0.0084837687 | K68: =+D68-I68 -> 1560.01 | M68: 9758.3 | N68: =IFERROR(M68/M$35,"") -> 0.0064032277 | O68: 7121.8215 | P68: =IFERROR(O68/O$35,"") -> 0.0039726922 | Q68: =+M68-O68 -> 2636.4785 | R68: 6740.63 | S68: =IFERROR(R68/R$35,"") -> 0.0073531475 | T68: =+M68-R68 -> 3017.67
B69: Dishwashing Supplies - 200 | C69: Dishwashing Supplies | D69: 0 | E69: =IFERROR(D69/D$35,"") -> 0 | F69: 0 | G69: =IFERROR(F69/F$35,"") -> 0 | H69: =+D69-F69 -> 0 | I69: 0 | J69: =IFERROR(I69/I$35,"") -> 0 | K69: =+D69-I69 -> 0 | M69: 0 | N69: =IFERROR(M69/M$35,"") -> 0 | O69: 0 | P69: =IFERROR(O69/O$35,"") -> 0 | Q69: =+M69-O69 -> 0 | R69: 0 | S69: =IFERROR(R69/R$35,"") -> 0 | T69: =+M69-R69 -> 0
B70: Kitchen Smallwares - 200 | C70: Kitchen Smallwares | D70: 209.55 | E70: =IFERROR(D70/D$35,"") -> 0.00055270998 | F70: 2259.7546 | G70: =IFERROR(F70/F$35,"") -> 0.0051639039 | H70: =+D70-F70 -> -2050.2046 | I70: 1941.16 | J70: =IFERROR(I70/I$35,"") -> 0.0077345985 | K70: =+D70-I70 -> -1731.61 | M70: 2770.45 | N70: =IFERROR(M70/M$35,"") -> 0.0018179214 | O70: 9260.645 | P70: =IFERROR(O70/O$35,"") -> 0.0051657701 | Q70: =+M70-O70 -> -6490.195 | R70: 5217.1 | S70: =IFERROR(R70/R$35,"") -> 0.0056911751 | T70: =+M70-R70 -> -2446.65
B71: Kitchen Allocation - 200 | C71: Kitchen Allocation | D71: 0 | E71: =IFERROR(D71/D$35,"") -> 0 | F71: 0 | G71: =IFERROR(F71/F$35,"") -> 0 | H71: =+D71-F71 -> 0 | I71: 0 | J71: =IFERROR(I71/I$35,"") -> 0 | K71: =+D71-I71 -> 0 | M71: 0 | N71: =IFERROR(M71/M$35,"") -> 0 | O71: 0 | P71: =IFERROR(O71/O$35,"") -> 0 | Q71: =+M71-O71 -> 0 | R71: 0 | S71: =IFERROR(R71/R$35,"") -> 0 | T71: =+M71-R71 -> 0
B72: Kitchen Fuel - 200 | C72: Kitchen Fuel | D72: 0 | E72: =IFERROR(D72/D$35,"") -> 0 | F72: 0 | G72: =IFERROR(F72/F$35,"") -> 0 | H72: =+D72-F72 -> 0 | I72: 0 | J72: =IFERROR(I72/I$35,"") -> 0 | K72: =+D72-I72 -> 0 | M72: 0 | N72: =IFERROR(M72/M$35,"") -> 0 | O72: 0 | P72: =IFERROR(O72/O$35,"") -> 0 | Q72: =+M72-O72 -> 0 | R72: 0 | S72: =IFERROR(R72/R$35,"") -> 0 | T72: =+M72-R72 -> 0
B73: Banquet Expenses - 200 | C73: Banquet Expense | D73: 1012.5 | E73: =IFERROR(D73/D$35,"") -> 0.0026705743 | F73: 3881.7 | G73: =IFERROR(F73/F$35,"") -> 0.008870311 | H73: =+D73-F73 -> -2869.2 | I73: 0 | J73: =IFERROR(I73/I$35,"") -> 0 | K73: =+D73-I73 -> 1012.5 | M73: 12425.1 | N73: =IFERROR(M73/M$35,"") -> 0.0081531358 | O73: 15907.5 | P73: =IFERROR(O73/O$35,"") -> 0.0088735167 | Q73: =+M73-O73 -> -3482.4 | R73: 1889.97 | S73: =IFERROR(R73/R$35,"") -> 0.0020617106 | T73: =+M73-R73 -> 10535.13
B74: Paper & Plastics - 200 | C74: Paper and Plastics | D74: 0 | E74: =IFERROR(D74/D$35,"") -> 0 | F74: 1725.2 | G74: =IFERROR(F74/F$35,"") -> 0.0039423605 | H74: =+D74-F74 -> -1725.2 | I74: 366 | J74: =IFERROR(I74/I$35,"") -> 0.0014583358 | K74: =+D74-I74 -> -366 | M74: 0 | N74: =IFERROR(M74/M$35,"") -> 0 | O74: 7070 | P74: =IFERROR(O74/O$35,"") -> 0.0039437852 | Q74: =+M74-O74 -> -7070 | R74: 629.48 | S74: =IFERROR(R74/R$35,"") -> 0.00068668051 | T74: =+M74-R74 -> -629.48
B75: Postage & Overnight Delivery - 200 | C75: Postage & Overnight Delivery | D75: 0 | E75: =IFERROR(D75/D$35,"") -> 0 | F75: 0 | G75: =IFERROR(F75/F$35,"") -> 0 | H75: =+D75-F75 -> 0 | I75: 0 | J75: =IFERROR(I75/I$35,"") -> 0 | K75: =+D75-I75 -> 0 | M75: 0 | N75: =IFERROR(M75/M$35,"") -> 0 | O75: 0 | P75: =IFERROR(O75/O$35,"") -> 0 | Q75: =+M75-O75 -> 0 | R75: 0 | S75: =IFERROR(R75/R$35,"") -> 0 | T75: =+M75-R75 -> 0
B76: Decorations - 200 | C76: Decorations | D76: 0 | E76: =IFERROR(D76/D$35,"") -> 0 | F76: 124.59974 | G76: =IFERROR(F76/F$35,"") -> 0.00028473052 | H76: =+D76-F76 -> -124.59974 | I76: 0 | J76: =IFERROR(I76/I$35,"") -> 0 | K76: =+D76-I76 -> 0 | M76: 0 | N76: =IFERROR(M76/M$35,"") -> 0 | O76: 510.61916 | P76: =IFERROR(O76/O$35,"") -> 0.00028483342 | Q76: =+M76-O76 -> -510.61916 | R76: 0 | S76: =IFERROR(R76/R$35,"") -> 0 | T76: =+M76-R76 -> 0
B77: Reservations - 200 | C77: Reservations | D77: 0 | E77: =IFERROR(D77/D$35,"") -> 0 | F77: 0 | G77: =IFERROR(F77/F$35,"") -> 0 | H77: =+D77-F77 -> 0 | I77: 0 | J77: =IFERROR(I77/I$35,"") -> 0 | K77: =+D77-I77 -> 0 | M77: 0 | N77: =IFERROR(M77/M$35,"") -> 0 | O77: 0 | P77: =IFERROR(O77/O$35,"") -> 0 | Q77: =+M77-O77 -> 0 | R77: 20 | S77: =IFERROR(R77/R$35,"") -> 2.1817389e-05 | T77: =+M77-R77 -> -20
... B103: Management Fees - 200 | C103: Management Fees | D103: 0 | E103: =IFERROR(D103/D$35,"") -> 0 | F103: 0 | G103: =IFERROR(F103/F$35,"") -> 0 | H103: =+D103-F103 -> 0 | I103: 0 | J103: =IFERROR(I103/I$35,"") -> 0 | K103: =+D103-I103 -> 0 | M103: 0 | N103: =IFERROR(M103/M$35,"") -> 0 | O103: 0 | P103: =IFERROR(O103/O$35,"") -> 0 | Q103: =+M103-O103 -> 0 | R103: 0 | S103: =IFERROR(R103/R$35,"") -> 0 | T103: =+M103-R103 -> 0
B104: Total Other Expenses - 200 | C104: Total Operations Expense | D104: =+SUM(D66:D103) -> 19281.92 | E104: =IFERROR(D104/D$35,"") -> 0.050858075 | F104: =+SUM(F66:F103) -> 23787.659 | G104: =IFERROR(F104/F$35,"") -> 0.05435864 | H104: =+D104-F104 -> -4505.739 | I104: =+SUM(I66:I103) -> 15231.48 | J104: =IFERROR(I104/I$35,"") -> 0.060690197 | K104: =+D104-I104 -> 4050.44 | M104: =+SUM(M66:M103) -> 85623.3 | N104: =IFERROR(M104/M$35,"") -> 0.056184529 | O104: =+SUM(O66:O103) -> 97792.295 | P104: =IFERROR(O104/O$35,"") -> 0.054550467 | Q104: =+M104-O104 -> -12168.995 | R104: =+SUM(R66:R103) -> 48743.64 | S104: =IFERROR(R104/R$35,"") -> 0.053172949 | T104: =+M104-R104 -> 36879.66
B106: Total Departmental Expenses - 200 | C106: Total Expenses | D106: =+D63+D104+D44 -> 291396.9 | E106: =IFERROR(D106/D$35,"") -> 0.76858971 | F106: =F44+F63+F104 -> 300367.41 | G106: =IFERROR(F106/F$35,"") -> 0.68638802 | H106: =+D106-F106 -> -8970.514 | I106: =I44+I63+I104 -> 228871.12 | J106: =IFERROR(I106/I$35,"") -> 0.91194246 | K106: =+D106-I106 -> 62525.78 | M106: =+M63+M104+M44 -> 1080000.5 | N106: =IFERROR(M106/M$35,"") -> 0.70867763 | O106: =O44+O63+O104 -> 1231191.5 | P106: =IFERROR(O106/O$35,"") -> 0.68678283 | Q106: =+M106-O106 -> -151190.99 | R106: =R44+R63+R104 -> 774688.84 | S106: =IFERROR(R106/R$35,"") -> 0.8450844 | T106: =+M106-R106 -> 305311.63
C107: Department Profit (Loss) | D107: =+D46-D106 -> -1251.97 | E107: =IFERROR(D107/D$35,"") -> -0.0033022014 | F107: =+F46-F106 -> 45101.156 | G107: =IFERROR(F107/F$35,"") -> 0.10306342 | H107: =+D107-F107 -> -46353.126 | I107: =+I46-I106 -> -58072.94 | J107: =IFERROR(I107/I$35,"") -> -0.23139302 | K107: =+D107-I107 -> 56820.97 | M107: =+M46-M106 -> 107334.28 | N107: =IFERROR(M107/M$35,"") -> 0.070430899 | O107: =+O46-O106 -> 184009.39 | P107: =IFERROR(O107/O$35,"") -> 0.10264406 | Q107: =+M107-O107 -> -76675.11 | R107: =+R46-R106 -> -101154.88 | S107: =IFERROR(R107/R$35,"") -> -0.11034677 | T107: =+M107-R107 -> 208489.16

Sheet OTH_OP
V1: ANG
C2: =+Summary!$C$2 -> Angler's | V2: Apr
C3: =+Summary!$C$3 -> STATEMENT OF INCOME
C4: =+Summary!$C$4 -> FOR THE PERIOD ENDING APR 2025
D6: =Year&" "&UPPER(Month)&" - PERIODIC" -> 2025 APR - PERIODIC | M6: =Year&" "&UPPER(Month)&" - YEAR TO DATE" -> 2025 APR - YEAR TO DATE
D7: Actual | F7: Budget | H7: VARIANCE | I7: Actual - Last Year | K7: VARIANCE | M7: Actual | O7: Budget | Q7: VARIANCE | R7: Actual - Last Year | T7: VARIANCE
D8: $ | E8: % | F8: $ | G8: % | H8: $ | I8: Actual | J8: % | K8: $ | M8: $ | N8: % | O8: $ | P8: % | Q8: $ | R8: Actual | S8: % | T8: $
C9: Revenues
B10: Total Guest Communications Revenue - 350 | C10: Guest Communications | D10: 79.07 | E10: =+IFERROR(D10/D$17,"") -> 0.026817571 | F10: 88.94 | G10: =+IFERROR(F10/F$17,"") -> 0.057090405 | H10: =+D10-F10 -> -9.87 | I10: 49.53 | J10: =+IFERROR(I10/I$17,"") -> 0.03388868 | K10: =+D10-I10 -> 29.54 | M10: 388.26 | N10: =+IFERROR(M10/M$17,"") -> 0.039320893 | O10: 355.33 | P10: =+IFERROR(O10/O$17,"") -> 0.057088278 | Q10: =+M10-O10 -> 32.93 | R10: 149.69 | S10: =+IFERROR(R10/R$17,"") -> 0.020770805 | T10: =+M10-R10 -> 238.57
B11: Total Health Club/Spa Revenue - 310 | C11: Health Club/Spa | D11: 0 | E11: =+IFERROR(D11/D$17,"") -> 0 | F11: 0 | G11: =+IFERROR(F11/F$17,"") -> 0 | H11: =+D11-F11 -> 0 | I11: 0 | J11: =+IFERROR(I11/I$17,"") -> 0 | K11: =+D11-I11 -> 0 | M11: 0 | N11: =+IFERROR(M11/M$17,"") -> 0 | O11: 0 | P11: =+IFERROR(O11/O$17,"") -> 0 | Q11: =+M11-O11 -> 0 | R11: 0 | S11: =+IFERROR(R11/R$17,"") -> 0 | T11: =+M11-R11 -> 0
B12: Total Parking Revenue - 320 | C12: Parking | D12: 0 | E12: =+IFERROR(D12/D$17,"") -> 0 | F12: 0 | G12: =+IFERROR(F12/F$17,"") -> 0 | H12: =+D12-F12 -> 0 | I12: 0 | J12: =+IFERROR(I12/I$17,"") -> 0 | K12: =+D12-I12 -> 0 | M12: 0 | N12: =+IFERROR(M12/M$17,"") -> 0 | O12: 0 | P12: =+IFERROR(O12/O$17,"") -> 0 | Q12: =+M12-O12 -> 0 | R12: 0 | S12: =+IFERROR(R12/R$17,"") -> 0 | T12: =+M12-R12 -> 0
B13: Total Laundry & Dry Cleaning Revenue - 360 | C13: Laundry & Dry Cleaning | D13: 1605.37 | E13: =+IFERROR(D13/D$17,"") -> 0.54448115 | F13: 583.2 | G13: =+IFERROR(F13/F$17,"") -> 0.37435489 | H13: =+D13-F13 -> 1022.17 | I13: 764.02 | J13: =+IFERROR(I13/I$17,"") -> 0.5227464 | K13: =+D13-I13 -> 841.35 | M13: 6304.88 | N13: =+IFERROR(M13/M$17,"") -> 0.63852447 | O13: 2330.08 | P13: =+IFERROR(O13/O$17,"") -> 0.37435695 | Q13: =+M13-O13 -> 3974.8 | R13: 2717.06 | S13: =+IFERROR(R13/R$17,"") -> 0.37701599 | T13: =+M13-R13 -> 3587.82
B14: Total Retail Revenue - 340 | C14: Retail Shop | D14: 0 | E14: =+IFERROR(D14/D$17,"") -> 0 | F14: 0 | G14: =+IFERROR(F14/F$17,"") -> 0 | H14: =+D14-F14 -> 0 | I14: 0 | J14: =+IFERROR(I14/I$17,"") -> 0 | K14: =+D14-I14 -> 0 | M14: 0 | N14: =+IFERROR(M14/M$17,"") -> 0 | O14: 0 | P14: =+IFERROR(O14/O$17,"") -> 0 | Q14: =+M14-O14 -> 0 | R14: 0 | S14: =+IFERROR(R14/R$17,"") -> 0 | T14: =+M14-R14 -> 0
B15: Total Minor Operated Department-3 Revenue - 370 | C15: Misc. Minor Operated Departments | D15: 0 | E15: =+IFERROR(D15/D$17,"") -> 0 | F15: 0 | G15: =+IFERROR(F15/F$17,"") -> 0 | H15: =+D15-F15 -> 0 | I15: 0 | J15: =+IFERROR(I15/I$17,"") -> 0 | K15: =+D15-I15 -> 0 | M15: 0 | N15: =+IFERROR(M15/M$17,"") -> 0 | O15: 0 | P15: =+IFERROR(O15/O$17,"") -> 0 | Q15: =+M15-O15 -> 0 | R15: 0 | S15: =+IFERROR(R15/R$17,"") -> 0 | T15: =+M15-R15 -> 0
B16: Total Minor Operated Department-4 Revenue - 380 | C16: Minor Other Operated Departments | D16: 1264 | E16: =+IFERROR(D16/D$17,"") -> 0.42870128 | F16: 885.74 | G16: =+IFERROR(F16/F$17,"") -> 0.5685547 | H16: =+D16-F16 -> 378.26 | I16: 648 | J16: =+IFERROR(I16/I$17,"") -> 0.44336492 | K16: =+D16-I16 -> 616 | M16: 3181 | N16: =+IFERROR(M16/M$17,"") -> 0.32215464 | O16: 3538.81 | P16: =+IFERROR(O16/O$17,"") -> 0.56855477 | Q16: =+M16-O16 -> -357.81 | R16: 4340 | S16: =+IFERROR(R16/R$17,"") -> 0.6022132 | T16: =+M16-R16 -> -1159
B17: Total Revenue - 300 | C17: Total Departmental Revenues | D17: =SUM(D10:D16) -> 2948.44 | E17: =+IFERROR(D17/D$17,"") -> 1 | F17: =SUM(F10:F16) -> 1557.88 | G17: =+IFERROR(F17/F$17,"") -> 1 | H17: =+D17-F17 -> 1390.56 | I17: =SUM(I10:I16) -> 1461.55 | J17: =+IFERROR(I17/I$17,"") -> 1 | K17: =+D17-I17 -> 1486.89 | M17: =SUM(M10:M16) -> 9874.14 | N17: =+IFERROR(M17/M$17,"") -> 1 | O17: =SUM(O10:O16) -> 6224.22 | P17: =+IFERROR(O17/O$17,"") -> 1 | Q17: =+M17-O17 -> 3649.92 | R17: =SUM(R10:R16) -> 7206.75 | S17: =+IFERROR(R17/R$17,"") -> 1 | T17: =+M17-R17 -> 2667.39
C19: Departmental Expenses (Incl COS)
B20: Total Departmental Expenses - 350 | C20: Guest Communications | D20: 36 | E20: =+IFERROR(D20/D10,"") -> 0.45529278 | F20: 40.91 | G20: =+IFERROR(F20/F10,"") -> 0.45997302 | H20: =+D20-F20 -> -4.91 | I20: 23 | J20: =+IFERROR(I20/I10,"") -> 0.46436503 | K20: =+D20-I20 -> 13 | M20: 178 | N20: =+IFERROR(M20/M10,"") -> 0.45845567 | O20: 163.45 | P20: =+IFERROR(O20/O10,"") -> 0.45999493 | Q20: =+M20-O20 -> 14.55 | R20: 71 | S20: =+IFERROR(R20/R10,"") -> 0.47431358 | T20: =+M20-R20 -> 107
B21: Total Departmental Expenses - 310 | C21: Health Club/Spa | D21: 0 | E21: =+IFERROR(D21/D11,"") | F21: 0 | G21: =+IFERROR(F21/F11,"") | H21: =+D21-F21 -> 0 | I21: 0 | J21: =+IFERROR(I21/I11,"") | K21: =+D21-I21 -> 0 | M21: 0 | N21: =+IFERROR(M21/M11,"") | O21: 0 | P21: =+IFERROR(O21/O11,"") | Q21: =+M21-O21 -> 0 | R21: 0 | S21: =+IFERROR(R21/R11,"") | T21: =+M21-R21 -> 0
B22: Total Departmental Expenses - 320 | C22: Parking | D22: 0 | E22: =+IFERROR(D22/D12,"") | F22: 0 | G22: =+IFERROR(F22/F12,"") | H22: =+D22-F22 -> 0 | I22: 0 | J22: =+IFERROR(I22/I12,"") | K22: =+D22-I22 -> 0 | M22: 0 | N22: =+IFERROR(M22/M12,"") | O22: 0 | P22: =+IFERROR(O22/O12,"") | Q22: =+M22-O22 -> 0 | R22: 0 | S22: =+IFERROR(R22/R12,"") | T22: =+M22-R22 -> 0
B23: Total Departmental Expenses - 360 | C23: Laundry & Dry Cleaning | D23: 1069.98 | E23: =+IFERROR(D23/D13,"") -> 0.66650056 | F23: 490.47 | G23: =+IFERROR(F23/F13,"") -> 0.84099794 | H23: =+D23-F23 -> 579.51 | I23: 619.24 | J23: =+IFERROR(I23/I13,"") -> 0.81050234 | K23: =+D23-I23 -> 450.74 | M23: 4895 | N23: =+IFERROR(M23/M13,"") -> 0.77638274 | O23: 1959.6 | P23: =+IFERROR(O23/O13,"") -> 0.84100117 | Q23: =+M23-O23 -> 2935.4 | R23: 2250.77 | S23: =+IFERROR(R23/R13,"") -> 0.82838436 | T23: =+M23-R23 -> 2644.23
B24: Total Departmental Expenses - 340 | C24: Retail Shop | D24: 0 | E24: =+IFERROR(D24/D14,"") | F24: 0 | G24: =+IFERROR(F24/F14,"") | H24: =+D24-F24 -> 0 | I24: 0 | J24: =+IFERROR(I24/I14,"") | K24: =+D24-I24 -> 0 | M24: 0 | N24: =+IFERROR(M24/M14,"") | O24: 0 | P24: =+IFERROR(O24/O14,"") | Q24: =+M24-O24 -> 0 | R24: 0 | S24: =+IFERROR(R24/R14,"") | T24: =+M24-R24 -> 0
B25: Total Departmental Expenses - 370 | C25: Misc. Minor Operated Departments | D25: 0 | E25: =+IFERROR(D25/D15,"") | F25: 0 | G25: =+IFERROR(F25/F15,"") | H25: =+D25-F25 -> 0 | I25: 0 | J25: =+IFERROR(I25/I15,"") | K25: =+D25-I25 -> 0 | M25: 0 | N25: =+IFERROR(M25/M15,"") | O25: 0 | P25: =+IFERROR(O25/O15,"") | Q25: =+M25-O25 -> 0 | R25: 0 | S25: =+IFERROR(R25/R15,"") | T25: =+M25-R25 -> 0
B26: Total Departmental Expenses - 380 | C26: Minor Other Operated Departments | D26: 0 | E26: =+IFERROR(D26/D16,"") -> 0 | F26: 0 | G26: =+IFERROR(F26/F16,"") -> 0 | H26: =+D26-F26 -> 0 | I26: 0 | J26: =+IFERROR(I26/I16,"") -> 0 | K26: =+D26-I26 -> 0 | M26: 0 | N26: =+IFERROR(M26/M16,"") -> 0 | O26: 0 | P26: =+IFERROR(O26/O16,"") -> 0 | Q26: =+M26-O26 -> 0 | R26: 0 | S26: =+IFERROR(R26/R16,"") -> 0 | T26: =+M26-R26 -> 0
B27: Total Departmental Expenses - 300 | C27: Total Departmental Expenses | D27: =SUM(D20:D26) -> 1105.98 | E27: =+IFERROR(D27/D17,"") -> 0.37510684 | F27: =SUM(F20:F26) -> 531.38 | G27: =+IFERROR(F27/F17,"") -> 0.34109174 | H27: =+D27-F27 -> 574.6 | I27: =SUM(I20:I26) -> 642.24 | J27: =+IFERROR(I27/I17,"") -> 0.4394239 | K27: =+D27-I27 -> 463.74 | M27: =SUM(M20:M26) -> 5073 | N27: =+IFERROR(M27/M17,"") -> 0.51376626 | O27: =SUM(O20:O26) -> 2123.05 | P27: =+IFERROR(O27/O17,"") -> 0.34109495 | Q27: =+M27-O27 -> 2949.95 | R27: =SUM(R20:R26) -> 2321.77 | S27: =+IFERROR(R27/R17,"") -> 0.32216602 | T27: =+M27-R27 -> 2751.23
C29: Department Profit (Loss)
C30: Guest Communications | D30: 0 | E30: =+IFERROR(D30/D10,"") -> 0 | F30: 0 | G30: =+IFERROR(F30/F10,"") -> 0 | H30: =+D30-F30 -> 0 | I30: 0 | J30: =+IFERROR(I30/I10,"") -> 0 | K30: =+D30-I30 -> 0 | M30: 0 | N30: =+IFERROR(M30/M10,"") -> 0 | O30: 0 | P30: =+IFERROR(O30/O10,"") -> 0 | Q30: =+M30-O30 -> 0 | R30: 0 | S30: =+IFERROR(R30/R10,"") -> 0 | T30: =+M30-R30 -> 0
C31: Health Club/Spa | D31: 0 | E31: =+IFERROR(D31/D11,"") | F31: 0 | G31: =+IFERROR(F31/F11,"") | H31: =+D31-F31 -> 0 | I31: 0 | J31: =+IFERROR(I31/I11,"") | K31: =+D31-I31 -> 0 | M31: 0 | N31: =+IFERROR(M31/M11,"") | O31: 0 | P31: =+IFERROR(O31/O11,"") | Q31: =+M31-O31 -> 0 | R31: 0 | S31: =+IFERROR(R31/R11,"") | T31: =+M31-R31 -> 0
C32: Parking | D32: 0 | E32: =+IFERROR(D32/D12,"") | F32: 0 | G32: =+IFERROR(F32/F12,"") | H32: =+D32-F32 -> 0 | I32: 0 | J32: =+IFERROR(I32/I12,"") | K32: =+D32-I32 -> 0 | M32: 0 | N32: =+IFERROR(M32/M12,"") | O32: 0 | P32: =+IFERROR(O32/O12,"") | Q32: =+M32-O32 -> 0 | R32: 0 | S32: =+IFERROR(R32/R12,"") | T32: =+M32-R32 -> 0
C33: Laundry & Dry Cleaning | D33: 0 | E33: =+IFERROR(D33/D13,"") -> 0 | F33: 0 | G33: =+IFERROR(F33/F13,"") -> 0 | H33: =+D33-F33 -> 0 | I33: 0 | J33: =+IFERROR(I33/I13,"") -> 0 | K33: =+D33-I33 -> 0 | M33: 0 | N33: =+IFERROR(M33/M13,"") -> 0 | O33: 0 | P33: =+IFERROR(O33/O13,"") -> 0 | Q33: =+M33-O33 -> 0 | R33: 0 | S33: =+IFERROR(R33/R13,"") -> 0 | T33: =+M33-R33 -> 0
C34: Retail Shop | D34: 0 | E34: =+IFERROR(D34/D14,"") | F34: 0 | G34: =+IFERROR(F34/F14,"") | H34: =+D34-F34 -> 0 | I34: 0 | J34: =+IFERROR(I34/I14,"") | K34: =+D34-I34 -> 0 | M34: 0 | N34: =+IFERROR(M34/M14,"") | O34: 0 | P34: =+IFERROR(O34/O14,"") | Q34: =+M34-O34 -> 0 | R34: 0 | S34: =+IFERROR(R34/R14,"") | T34: =+M34-R34 -> 0
C35: Misc. Minor Operated Departments | D35: 0 | E35: =+IFERROR(D35/D15,"") | F35: 0 | G35: =+IFERROR(F35/F15,"") | H35: =+D35-F35 -> 0 | I35: 0 | J35: =+IFERROR(I35/I15,"") | K35: =+D35-I35 -> 0 | M35: 0 | N35: =+IFERROR(M35/M15,"") | O35: 0 | P35: =+IFERROR(O35/O15,"") | Q35: =+M35-O35 -> 0 | R35: 0 | S35: =+IFERROR(R35/R15,"") | T35: =+M35-R35 -> 0
C36: Minor Other Operated Departments | D36: 0 | E36: =+IFERROR(D36/D16,"") -> 0 | F36: 0 | G36: =+IFERROR(F36/F16,"") -> 0 | H36: =+D36-F36 -> 0 | I36: 0 | J36: =+IFERROR(I36/I16,"") -> 0 | K36: =+D36-I36 -> 0 | M36: 0 | N36: =+IFERROR(M36/M16,"") -> 0 | O36: 0 | P36: =+IFERROR(O36/O16,"") -> 0 | Q36: =+M36-O36 -> 0 | R36: 0 | S36: =+IFERROR(R36/R16,"") -> 0 | T36: =+M36-R36 -> 0
C37: Total Departmental Profit | D37: =+D17-D27 -> 1842.46 | E37: =+IFERROR(D37/D17,"") -> 0.62489316 | F37: =+F17-F27 -> 1026.5 | G37: =+IFERROR(F37/F17,"") -> 0.65890826 | H37: =+D37-F37 -> 815.96 | I37: =+I17-I27 -> 819.31 | J37: =+IFERROR(I37/I17,"") -> 0.5605761 | K37: =+D37-I37 -> 1023.15 | M37: =+M17-M27 -> 4801.14 | N37: =+IFERROR(M37/M17,"") -> 0.48623374 | O37: =+O17-O27 -> 4101.17 | P37: =+IFERROR(O37/O17,"") -> 0.65890505 | Q37: =+M37-O37 -> 699.97 | R37: =+R17-R27 -> 4884.98 | S37: =+IFERROR(R37/R17,"") -> 0.67783398 | T37: =+M37-R37 -> -83.84
B39: Dept Profit - 300 | C39: Department Profit (Loss) | D39: =D37 -> 1842.46 | E39: =+IFERROR(D39/D17,"") -> 0.62489316 | F39: =F37 -> 1026.5 | G39: =+IFERROR(F39/F17,"") -> 0.65890826 | H39: =+D39-F39 -> 815.96 | I39: =I37 -> 819.31 | J39: =+IFERROR(I39/I17,"") -> 0.5605761 | K39: =+D39-I39 -> 1023.15 | M39: =M37 -> 4801.14 | N39: =+IFERROR(M39/M17,"") -> 0.48623374 | O39: =O37 -> 4101.17 | P39: =+IFERROR(O39/O17,"") -> 0.65890505 | Q39: =+M39-O39 -> 699.97 | R39: =R37 -> 4884.98 | S39: =+IFERROR(R39/R17,"") -> 0.67783398 | T39: =+M39-R39 -> -83.84

Sheet MISC_INC
V1: ANG
C2: =+Summary!$C$2 -> Angler's | V2: Apr
C3: =+Summary!$C$3 -> STATEMENT OF INCOME
C4: =+Summary!$C$4 -> FOR THE PERIOD ENDING APR 2025
D6: =Year&" "&UPPER(Month)&" - PERIODIC" -> 2025 APR - PERIODIC | M6: =Year&" "&UPPER(Month)&" - YEAR TO DATE" -> 2025 APR - YEAR TO DATE
D7: Actual | F7: Budget | H7: VARIANCE | I7: Actual - Last Year | K7: VARIANCE | M7: Actual | O7: Budget | Q7: VARIANCE | R7: Actual - Last Year | T7: VARIANCE
D8: $ | E8: % | F8: $ | G8: % | H8: $ | I8: Actual | J8: % | K8: $ | M8: $ | N8: % | O8: $ | P8: % | Q8: $ | R8: Actual | S8: % | T8: $
C9: Revenues
B10: Misc. Space Rental & Concessions - 400 | C10: Space Rent & Concessions | D10: 0 | E10: =IFERROR(D10/D$22,"") -> 0 | F10: 0 | G10: =IFERROR(F10/F$22,"") -> 0 | H10: =D10-F10 -> 0 | I10: 0 | J10: =IFERROR(I10/I$22,"") -> 0 | K10: =D10-I10 -> 0 | M10: 0 | N10: =IFERROR(M10/M$22,"") -> 0 | O10: 0 | P10: =IFERROR(O10/O$22,"") -> 0 | Q10: =M10-O10 -> 0 | R10: 0 | S10: =IFERROR(R10/R$22,"") -> 0 | T10: =M10-R10 -> 0
B11: Misc. Commissions - 400 | C11: Commissions | D11: 12790.04 | E11: =IFERROR(D11/D$22,"") -> 0.088385198 | F11: 7700 | G11: =IFERROR(F11/F$22,"") -> 0.064015696 | H11: =D11-F11 -> 5090.04 | I11: 930.4 | J11: =IFERROR(I11/I$22,"") -> 0.0076556599 | K11: =D11-I11 -> 11859.64 | M11: 19344.7 | N11: =IFERROR(M11/M$22,"") -> 0.039018402 | O11: 30800 | P11: =IFERROR(O11/O$22,"") -> 0.062308699 | Q11: =M11-O11 -> -11455.3 | R11: -1144.7 | S11: =IFERROR(R11/R$22,"") -> -0.0026171359 | T11: =M11-R11 -> 20489.4
B12: Misc. Cash Discounts Earned - 400 | C12: Cash Discounts Earned | D12: 0 | E12: =IFERROR(D12/D$22,"") -> 0 | F12: 0 | G12: =IFERROR(F12/F$22,"") -> 0 | H12: =D12-F12 -> 0 | I12: 0 | J12: =IFERROR(I12/I$22,"") -> 0 | K12: =D12-I12 -> 0 | M12: 0 | N12: =IFERROR(M12/M$22,"") -> 0 | O12: 0 | P12: =IFERROR(O12/O$22,"") -> 0 | Q12: =M12-O12 -> 0 | R12: 0 | S12: =IFERROR(R12/R$22,"") -> 0 | T12: =M12-R12 -> 0
B13: Misc. Attrition Fees - 400 | C13: Attrition Penalties | D13: 27727 | E13: =IFERROR(D13/D$22,"") -> 0.19160663 | F13: 0 | G13: =IFERROR(F13/F$22,"") -> 0 | H13: =D13-F13 -> 27727 | I13: 0 | J13: =IFERROR(I13/I$22,"") -> 0 | K13: =D13-I13 -> 27727 | M13: 32135.3 | N13: =IFERROR(M13/M$22,"") -> 0.064817137 | O13: 1950 | P13: =IFERROR(O13/O$22,"") -> 0.0039448689 | Q13: =M13-O13 -> 30185.3 | R13: 1946.8 | S13: =IFERROR(R13/R$22,"") -> 0.004450983 | T13: =M13-R13 -> 30188.5
B14: Misc. Cancellation Fees - 400 | C14: Cancellation Penalties | D14: 611.42 | E14: =IFERROR(D14/D$22,"") -> 0.0042252001 | F14: 6592 | G14: =IFERROR(F14/F$22,"") -> 0.054804087 | H14: =D14-F14 -> -5980.58 | I14: 6592.02 | J14: =IFERROR(I14/I$22,"") -> 0.054241469 | K14: =D14-I14 -> -5980.6 | M14: 6891.75 | N14: =IFERROR(M14/M$22,"") -> 0.013900711 | O14: 38093 | P14: =IFERROR(O14/O$22,"") -> 0.077062509 | Q14: =M14-O14 -> -31201.25 | R14: 38092.61 | S14: =IFERROR(R14/R$22,"") -> 0.087091411 | T14: =M14-R14 -> -31200.86
B15: Misc. Guest Laundry & Dry Cleaning - 400 | C15: Guest Laundry & Dry Cleaning | D15: 0 | E15: =IFERROR(D15/D$22,"") -> 0 | F15: 0 | G15: =IFERROR(F15/F$22,"") -> 0 | H15: =D15-F15 -> 0 | I15: 0 | J15: =IFERROR(I15/I$22,"") -> 0 | K15: =D15-I15 -> 0 | M15: 0 | N15: =IFERROR(M15/M$22,"") -> 0 | O15: 0 | P15: =IFERROR(O15/O$22,"") -> 0 | Q15: =M15-O15 -> 0 | R15: 0 | S15: =IFERROR(R15/R$22,"") -> 0 | T15: =M15-R15 -> 0
B16: Misc. Interest Income - 400 | C16: Interest Income | D16: 0 | E16: =IFERROR(D16/D$22,"") -> 0 | F16: 0 | G16: =IFERROR(F16/F$22,"") -> 0 | H16: =D16-F16 -> 0 | I16: 8745.83 | J16: =IFERROR(I16/I$22,"") -> 0.071963779 | K16: =D16-I16 -> -8745.83 | M16: 41895.56 | N16: =IFERROR(M16/M$22,"") -> 0.084503653 | O16: 0 | P16: =IFERROR(O16/O$22,"") -> 0 | Q16: =M16-O16 -> 41895.56 | R16: 34560.95 | S16: =IFERROR(R16/R$22,"") -> 0.079016951 | T16: =M16-R16 -> 7334.61
B17: Misc. Other Breakage - 400 | C17: Other Breakage | D17: 0 | E17: =IFERROR(D17/D$22,"") -> 0 | F17: 0 | G17: =IFERROR(F17/F$22,"") -> 0 | H17: =D17-F17 -> 0 | I17: 0 | J17: =IFERROR(I17/I$22,"") -> 0 | K17: =D17-I17 -> 0 | M17: 0 | N17: =IFERROR(M17/M$22,"") -> 0 | O17: 0 | P17: =IFERROR(O17/O$22,"") -> 0 | Q17: =M17-O17 -> 0 | R17: 0 | S17: =IFERROR(R17/R$22,"") -> 0 | T17: =M17-R17 -> 0
B18: Misc. Package Breakage - 400 | C18: Package Breakage | D18: 0 | E18: =IFERROR(D18/D$22,"") -> 0 | F18: 0 | G18: =IFERROR(F18/F$22,"") -> 0 | H18: =D18-F18 -> 0 | I18: 0 | J18: =IFERROR(I18/I$22,"") -> 0 | K18: =D18-I18 -> 0 | M18: 0 | N18: =IFERROR(M18/M$22,"") -> 0 | O18: 0 | P18: =IFERROR(O18/O$22,"") -> 0 | Q18: =M18-O18 -> 0 | R18: 0 | S18: =IFERROR(R18/R$22,"") -> 0 | T18: =M18-R18 -> 0
B19: Misc. Resort Fees - 400 | C19: Resort Fees | D19: 103437.12 | E19: =IFERROR(D19/D$22,"") -> 0.7147992 | F19: 105991 | G19: =IFERROR(F19/F$22,"") -> 0.88118022 | H19: =D19-F19 -> -2553.88 | I19: 105262.75 | J19: =IFERROR(I19/I$22,"") -> 0.86613909 | K19: =D19-I19 -> -1825.63 | M19: 395156.87 | N19: =IFERROR(M19/M$22,"") -> 0.79703432 | O19: 423470 | P19: =IFERROR(O19/O$22,"") -> 0.85668392 | Q19: =M19-O19 -> -28313.13 | R19: 363930.87 | S19: =IFERROR(R19/R$22,"") -> 0.83205779 | T19: =M19-R19 -> 31226
B20: Misc. Proceeds from Business Interruption Insurance - 400 | C20: Proceeds from BI Insurance | D20: 0 | E20: =IFERROR(D20/D$22,"") -> 0 | F20: 0 | G20: =IFERROR(F20/F$22,"") -> 0 | H20: =D20-F20 -> 0 | I20: 0 | J20: =IFERROR(I20/I$22,"") -> 0 | K20: =D20-I20 -> 0 | M20: 0 | N20: =IFERROR(M20/M$22,"") -> 0 | O20: 0 | P20: =IFERROR(O20/O$22,"") -> 0 | Q20: =M20-O20 -> 0 | R20: 0 | S20: =IFERROR(R20/R$22,"") -> 0 | T20: =M20-R20 -> 0
B21: Misc. Other Income - 400 | C21: Other | D21: 142.36 | E21: =IFERROR(D21/D$22,"") -> 0.00098377463 | F21: 0 | G21: =IFERROR(F21/F$22,"") -> 0 | H21: =D21-F21 -> 142.36 | I21: 0 | J21: =IFERROR(I21/I$22,"") -> 0 | K21: =D21-I21 -> 142.36 | M21: 359.83 | N21: =IFERROR(M21/M$22,"") -> 0.00072577976 | O21: 0 | P21: =IFERROR(O21/O$22,"") -> 0 | Q21: =M21-O21 -> 359.83 | R21: 0 | S21: =IFERROR(R21/R$22,"") -> 0 | T21: =M21-R21 -> 359.83
B22: Total Revenue - 400 | C22: Total Revenue | D22: =SUM(D10:D21) -> 144707.94 | E22: =IFERROR(D22/D$22,"") -> 1 | F22: =SUM(F10:F21) -> 120283 | G22: =IFERROR(F22/F$22,"") -> 1 | H22: =D22-F22 -> 24424.94 | I22: =SUM(I10:I21) -> 121531 | J22: =IFERROR(I22/I$22,"") -> 1 | K22: =D22-I22 -> 23176.94 | M22: =SUM(M10:M21) -> 495784.01 | N22: =IFERROR(M22/M$22,"") -> 1 | O22: =SUM(O10:O21) -> 494313 | P22: =IFERROR(O22/O$22,"") -> 1 | Q22: =M22-O22 -> 1471.01 | R22: =SUM(R10:R21) -> 437386.53 | S22: =IFERROR(R22/R$22,"") -> 1 | T22: =M22-R22 -> 58397.48
B24: Total Revenue - 400 | C24: Department Profit (Loss) | D24: =D22 -> 144707.94 | E24: =IFERROR(D24/D$22,"") -> 1 | F24: =F22 -> 120283 | G24: =IFERROR(F24/F$22,"") -> 1 | H24: =D24-F24 -> 24424.94 | I24: =I22 -> 121531 | J24: =IFERROR(I24/I$22,"") -> 1 | K24: =D24-I24 -> 23176.94 | M24: =M22 -> 495784.01 | N24: =IFERROR(M24/M$22,"") -> 1 | O24: =O22 -> 494313 | P24: =IFERROR(O24/O$22,"") -> 1 | Q24: =M24-O24 -> 1471.01 | R24: =R22 -> 437386.53 | S24: =IFERROR(R24/R$22,"") -> 1 | T24: =M24-R24 -> 58397.48

Sheet AG
V1: ANG
C2: =+Summary!$C$2 -> Angler's | V2: Apr
C3: =+Summary!$C$3 -> STATEMENT OF INCOME
C4: =+Summary!$C$4 -> FOR THE PERIOD ENDING APR 2025
D6: =Year&" "&UPPER(Month)&" - PERIODIC" -> 2025 APR - PERIODIC | M6: =Year&" "&UPPER(Month)&" - YEAR TO DATE" -> 2025 APR - YEAR TO DATE
D7: Actual | F7: Budget | H7: VARIANCE | I7: Actual - Last Year | K7: VARIANCE | M7: Actual | O7: Budget | Q7: VARIANCE | R7: Actual - Last Year | T7: VARIANCE
D8: $ | E8: % | F8: $ | G8: % | H8: $ | I8: Actual | J8: % | K8: $ | M8: $ | N8: % | O8: $ | P8: % | Q8: $ | R8: Actual | S8: % | T8: $
C9: Labor & Related Expenses
C10: Salaries & Wages
B11: S&W Management - 500 | C11: Management | D11: 31914.39 | E11: =+D11/Summary!$D$19 -> 0.021151908 | F11: 27750.3 | G11: =F11/Summary!F$19 -> 0.018270563 | H11: =+D11-F11 -> 4164.09 | I11: 30963.43 | J11: =I11/Summary!I$19 -> 0.02346772 | K11: =+D11-I11 -> 950.96 | M11: 128272.63 | N11: =+M11/Summary!$D$19 -> 0.085015282 | O11: 106634.75 | P11: =O11/Summary!O$19 -> 0.015764035 | Q11: =+M11-O11 -> 21637.88 | R11: 106447.6 | S11: =R11/Summary!R$19 -> 0.018150857 | T11: =+M11-R11 -> 21825.03
C12: Non-Management
B13: Non-Mgmt Accounting Regular S&W - 500 | C13: Accounting | D13: 5071.75 | E13: =+D13/Summary!$D$19 -> 0.003361405 | F13: 9242.3 | G13: =F13/Summary!F$19 -> 0.0060850523 | H13: =+D13-F13 -> -4170.55 | I13: 7524.69 | J13: =I13/Summary!I$19 -> 0.005703093 | K13: =+D13-I13 -> -2452.94 | M13: 16081.44 | N13: =+M13/Summary!$D$19 -> 0.0106583 | O13: 35014.95 | P13: =O13/Summary!O$19 -> 0.0051763324 | Q13: =+M13-O13 -> -18933.51 | R13: 34747.51 | S13: =R13/Summary!R$19 -> 0.0059249535 | T13: =+M13-R13 -> -18666.07
B14: Non-Mgmt Security Regular S&W - 500 | C14: Security | D14: 0 | E14: =+D14/Summary!$D$19 -> 0 | F14: 0 | G14: =F14/Summary!F$19 -> 0 | H14: =+D14-F14 -> 0 | I14: 0 | J14: =I14/Summary!I$19 -> 0 | K14: =+D14-I14 -> 0 | M14: 0 | N14: =+M14/Summary!$D$19 -> 0 | O14: 0 | P14: =O14/Summary!O$19 -> 0 | Q14: =+M14-O14 -> 0 | R14: 0 | S14: =R14/Summary!R$19 -> 0 | T14: =+M14-R14 -> 0
B15: Non-Mgmt Executive Regular S&W - 500 | C15: Executive | D15: 0 | E15: =+D15/Summary!$D$19 -> 0 | F15: 0 | G15: =F15/Summary!F$19 -> 0 | H15: =+D15-F15 -> 0 | I15: 0 | J15: =I15/Summary!I$19 -> 0 | K15: =+D15-I15 -> 0 | M15: 0 | N15: =+M15/Summary!$D$19 -> 0 | O15: 0 | P15: =O15/Summary!O$19 -> 0 | Q15: =+M15-O15 -> 0 | R15: 0 | S15: =R15/Summary!R$19 -> 0 | T15: =+M15-R15 -> 0
B16: Non-Mgmt HR Regular S&W - 500 | C16: HR | D16: 2412.52 | E16: =+D16/Summary!$D$19 -> 0.0015989465 | F16: 2445.94 | G16: =F16/Summary!F$19 -> 0.0016103862 | H16: =+D16-F16 -> -33.42 | I16: 1759.8 | J16: =I16/Summary!I$19 -> 0.0013337829 | K16: =+D16-I16 -> 652.72 | M16: 8841.64 | N16: =+M16/Summary!$D$19 -> 0.0058599759 | O16: 9604.8 | P16: =O16/Summary!O$19 -> 0.0014198974 | Q16: =+M16-O16 -> -763.16 | R16: 8404.6 | S16: =R16/Summary!R$19 -> 0.001433106 | T16: =+M16-R16 -> 437.04
B17: Non-Mgmt Unassigned Regular S&W - 500 | C17: Unassigned | D17: 0 | E17: =+D17/Summary!$D$19 -> 0 | F17: 0 | G17: =F17/Summary!F$19 -> 0 | H17: =+D17-F17 -> 0 | I17: 0 | J17: =I17/Summary!I$19 -> 0 | K17: =+D17-I17 -> 0 | M17: 0 | N17: =+M17/Summary!$D$19 -> 0 | O17: 0 | P17: =O17/Summary!O$19 -> 0 | Q17: =+M17-O17 -> 0 | R17: 0 | S17: =R17/Summary!R$19 -> 0 | T17: =+M17-R17 -> 0
B18: S&W Other - 500 | C18: Other S&W | D18: 0 | E18: =+D18/Summary!$D$19 -> 0 | F18: 0 | G18: =F18/Summary!F$19 -> 0 | H18: =+D18-F18 -> 0 | I18: 0 | J18: =I18/Summary!I$19 -> 0 | K18: =+D18-I18 -> 0 | M18: 0 | N18: =+M18/Summary!$D$19 -> 0 | O18: 0 | P18: =O18/Summary!O$19 -> 0 | Q18: =+M18-O18 -> 0 | R18: 0 | S18: =R18/Summary!R$19 -> 0 | T18: =+M18-R18 -> 0
B19: Total Salaries & Wages - 500 | C19: Total Salaries and Wages | D19: =SUM(D13:D18)+D11 -> 39398.66 | E19: =+D19/Summary!$D$19 -> 0.026112259 | F19: =SUM(F13:F18) -> 11688.24 | G19: =F19/Summary!F$19 -> 0.0076954385 | H19: =+D19-F19 -> 27710.42 | I19: =SUM(I13:I18) -> 9284.49 | J19: =I19/Summary!I$19 -> 0.0070368759 | K19: =+D19-I19 -> 30114.17 | M19: =SUM(M13:M18)+M11 -> 153195.71 | N19: =+M19/Summary!$D$19 -> 0.10153356 | O19: =SUM(O13:O18) -> 44619.75 | P19: =O19/Summary!O$19 -> 0.0065962298 | Q19: =+M19-O19 -> 108575.96 | R19: =SUM(R13:R18) -> 43152.11 | S19: =R19/Summary!R$19 -> 0.0073580594 | T19: =+M19-R19 -> 110043.6
B20: Total Contracted Leased & Outsourced Labor - 500 | C20: Contracted & Leased Labor | D20: 0 | E20: =+D20/Summary!$D$19 -> 0 | F20: 0 | G20: =F20/Summary!F$19 -> 0 | H20: =+D20-F20 -> 0 | I20: 0 | J20: =I20/Summary!I$19 -> 0 | K20: =+D20-I20 -> 0 | M20: 7086.8 | N20: =+M20/Summary!$D$19 -> 0.0046969201 | O20: 0 | P20: =O20/Summary!O$19 -> 0 | Q20: =+M20-O20 -> 7086.8 | R20: 0 | S20: =R20/Summary!R$19 -> 0 | T20: =+M20-R20 -> 7086.8
B21: Total Bonuses & Incentives - 500 | C21: Bonuses & Incentives | D21: 6767.38 | E21: =+D21/Summary!$D$19 -> 0.0044852181 | F21: 7027.77 | G21: =F21/Summary!F$19 -> 0.0046270244 | H21: =+D21-F21 -> -260.39 | I21: 5156.07 | J21: =I21/Summary!I$19 -> 0.0039078748 | K21: =+D21-I21 -> 1611.31 | M21: 18639.2 | N21: =+M21/Summary!$D$19 -> 0.012353507 | O21: 27596.82 | P21: =O21/Summary!O$19 -> 0.0040796949 | Q21: =+M21-O21 -> -8957.62 | R21: 16843.19 | S21: =R21/Summary!R$19 -> 0.0028720077 | T21: =+M21-R21 -> 1796.01
C22: Total Labor Expense | D22: =+D19+SUM(D20:D21) -> 46166.04 | E22: =+D22/Summary!$D$19 -> 0.030597477 | F22: =+F11+F19+SUM(F20:F21) -> 46466.31 | H22: =+D22-F22 -> -300.27 | I22: =+I11+I19+SUM(I20:I21) -> 45403.99 | K22: =+D22-I22 -> 762.05 | M22: =+M19+SUM(M20:M21) -> 178921.71 | N22: =+M22/Summary!$D$19 -> 0.11858398 | O22: =+O11+O19+SUM(O20:O21) -> 178851.32 | Q22: =+M22-O22 -> 70.39 | R22: =+R11+R19+SUM(R20:R21) -> 166442.9 | T22: =+M22-R22 -> 12478.81
B23: Total Payroll Taxes - 500 | C23: Payroll Taxes | D23: 4934.24 | E23: =+D23/Summary!$D$19 -> 0.0032702674 | F23: 3550.77 | G23: =F23/Summary!F$19 -> 0.002337797 | H23: =+D23-F23 -> 1383.47 | I23: 3474.63 | J23: =I23/Summary!I$19 -> 0.0026334823 | K23: =+D23-I23 -> 1459.61 | M23: 15429.19 | N23: =+M23/Summary!$D$19 -> 0.010226008 | O23: 14265.27 | P23: =O23/Summary!O$19 -> 0.0021088643 | Q23: =+M23-O23 -> 1163.92 | R23: 14411.13 | S23: =R23/Summary!R$19 -> 0.0024573063 | T23: =+M23-R23 -> 1018.06
B24: Total Supplemental Pay - 500 | C24: Supplemental Pay | D24: 2477.43 | E24: =+D24/Summary!$D$19 -> 0.0016419669 | F24: 3299.82 | G24: =F24/Summary!F$19 -> 0.0021725736 | H24: =+D24-F24 -> -822.39 | I24: 5159.54 | J24: =I24/Summary!I$19 -> 0.0039105048 | K24: =+D24-I24 -> -2682.11 | M24: 19202.61 | N24: =+M24/Summary!$D$19 -> 0.012726918 | O24: 16629.2 | P24: =O24/Summary!O$19 -> 0.002458329 | Q24: =+M24-O24 -> 2573.41 | R24: 16231.47 | S24: =R24/Summary!R$19 -> 0.0027677006 | T24: =+M24-R24 -> 2971.14
B25: Total Employee Benefits - 500 | C25: Employee Benefits | D25: 6115.19 | E25: =+D25/Summary!$D$19 -> 0.0040529659 | F25: 6617.07 | G25: =F25/Summary!F$19 -> 0.004356623 | H25: =+D25-F25 -> -501.88 | I25: 5342.15 | J25: =I25/Summary!I$19 -> 0.0040489081 | K25: =+D25-I25 -> 773.04 | M25: 21997.17 | N25: =+M25/Summary!$D$19 -> 0.01457907 | O25: 26201.44 | P25: =O25/Summary!O$19 -> 0.003873413 | Q25: =+M25-O25 -> -4204.27 | R25: 26423.39 | S25: =R25/Summary!R$19 -> 0.0045055705 | T25: =+M25-R25 -> -4426.22
B26: Total Payroll-Related Expenses - 500 | C26: Total Payroll Related | D26: =SUM(D23:D25) -> 13526.86 | E26: =+D26/Summary!$D$19 -> 0.0089652003 | F26: =SUM(F23:F25) -> 13467.66 | G26: =F26/Summary!F$19 -> 0.0088669937 | H26: =+D26-F26 -> 59.2 | I26: =SUM(I23:I25) -> 13976.32 | J26: =I26/Summary!I$19 -> 0.010592895 | K26: =+D26-I26 -> -449.46 | M26: =SUM(M23:M25) -> 56628.97 | N26: =+M26/Summary!$D$19 -> 0.037531996 | O26: =SUM(O23:O25) -> 57095.91 | P26: =O26/Summary!O$19 -> 0.0084406063 | Q26: =+M26-O26 -> -466.94 | R26: =SUM(R23:R25) -> 57065.99 | S26: =R26/Summary!R$19 -> 0.0097305774 | T26: =+M26-R26 -> -437.02
B27: Total Labor Costs & Related Expenses - 500 | C27: Total Labor & Related Exp | D27: =+D22+D26 -> 59692.9 | E27: =+D27/Summary!$D$19 -> 0.039562678 | F27: =+F22+F26 -> 59933.97 | G27: =F27/Summary!F$19 -> 0.03946002 | H27: =+D27-F27 -> -241.07 | I27: =+I22+I26 -> 59380.31 | J27: =I27/Summary!I$19 -> 0.045005366 | K27: =+D27-I27 -> 312.59 | M27: =+M22+M26 -> 235550.68 | N27: =+M27/Summary!$D$19 -> 0.15611598 | O27: =+O22+O26 -> 235947.23 | P27: =O27/Summary!O$19 -> 0.034880567 | Q27: =+M27-O27 -> -396.55 | R27: =+R22+R26 -> 223508.89 | S27: =R27/Summary!R$19 -> 0.038111501 | T27: =+M27-R27 -> 12041.79
C29: Other Expenses
B30: Dues & Subscriptions - 500 | C30: Dues and Subscriptions | D30: 3721.46 | E30: =+D30/Summary!$D$19 -> 0.0024664729 | F30: 1659 | G30: =F30/Summary!F$19 -> 0.0010922716 | H30: =+D30-F30 -> 2062.46 | I30: 374.18 | J30: =I30/Summary!I$19 -> 0.00028359751 | K30: =+D30-I30 -> 3347.28 | M30: 9989.58 | N30: =+M30/Summary!$D$19 -> 0.0066207963 | O30: 6733 | P30: =O30/Summary!O$19 -> 0.0009953533 | Q30: =+M30-O30 -> 3256.58 | R30: 1948.87 | S30: =R30/Summary!R$19 -> 0.00033231055 | T30: =+M30-R30 -> 8040.71
B31: Postage & Overnight Delivery - 500 | C31: Postage and Overnight Delivery | D31: 176.68 | E31: =+D31/Summary!$D$19 -> 0.00011709825 | F31: 280.5 | G31: =F31/Summary!F$19 -> 0.00018467883 | H31: =+D31-F31 -> -103.82 | I31: -31.32 | J31: =I31/Summary!I$19 -> -2.3737971e-05 | K31: =+D31-I31 -> 208 | M31: 383.73 | N31: =+M31/Summary!$D$19 -> 0.00025432482 | O31: 1122 | P31: =O31/Summary!O$19 -> 0.00016586758 | Q31: =+M31-O31 -> -738.27 | R31: 572.37 | S31: =R31/Summary!R$19 -> 9.7597371e-05 | T31: =+M31-R31 -> -188.64
B32: Printing & Stationary - 500 | C32: Printing & Stationary | D32: 0 | E32: =+D32/Summary!$D$19 -> 0 | F32: 0 | G32: =F32/Summary!F$19 -> 0 | H32: =+D32-F32 -> 0 | I32: 0 | J32: =I32/Summary!I$19 -> 0 | K32: =+D32-I32 -> 0 | M32: 0 | N32: =+M32/Summary!$D$19 -> 0 | O32: 0 | P32: =O32/Summary!O$19 -> 0 | Q32: =+M32-O32 -> 0 | R32: 0 | S32: =R32/Summary!R$19 -> 0 | T32: =+M32-R32 -> 0
B33: Professional Fees - 500 | C33: Professional Fees | D33: 2086 | E33: =+D33/Summary!$D$19 -> 0.0013825387 | F33: 14344.55 | G33: =F33/Summary!F$19 -> 0.0094443306 | H33: =+D33-F33 -> -12258.55 | I33: 12720 | J33: =I33/Summary!I$19 -> 0.0096407085 | K33: =+D33-I33 -> -10634 | M33: 13301 | N33: =+M33/Summary!$D$19 -> 0.008815507 | O33: 19091.25 | P33: =O33/Summary!O$19 -> 0.0028222989 | Q33: =+M33-O33 -> -5790.25 | R33: 13525 | S33: =R33/Summary!R$19 -> 0.0023062083 | T33: =+M33-R33 -> -224
B34: Operating Supplies - 500 | C34: Operating Supplies | D34: 1745.22 | E34: =+D34/Summary!$D$19 -> 0.0011566799 | F34: 5454.6806 | G34: =F34/Summary!F$19 -> 0.0035913157 | H34: =+D34-F34 -> -3709.4606 | I34: 2858.02 | J34: =I34/Summary!I$19 -> 0.0021661429 | K34: =+D34-I34 -> -1112.8 | M34: 5945.63 | N34: =+M34/Summary!$D$19 -> 0.0039405866 | O34: 22095.136 | P34: =O34/Summary!O$19 -> 0.0032663696 | Q34: =+M34-O34 -> -16149.506 | R34: 7085.7 | S34: =R34/Summary!R$19 -> 0.0012082144 | T34: =+M34-R34 -> -1140.07
B35: Complimentary Services & Gifts - 500 | C35: Complimentary Services & Gifts | D35: 0 | E35: =+D35/Summary!$D$19 -> 0 | F35: 0 | G35: =F35/Summary!F$19 -> 0 | H35: =+D35-F35 -> 0 | I35: 0 | J35: =I35/Summary!I$19 -> 0 | K35: =+D35-I35 -> 0 | M35: 0 | N35: =+M35/Summary!$D$19 -> 0 | O35: 0 | P35: =O35/Summary!O$19 -> 0 | Q35: =+M35-O35 -> 0 | R35: 0 | S35: =R35/Summary!R$19 -> 0 | T35: =+M35-R35 -> 0
B36: Contract Services - 500 | C36: Contract Services | D36: 1131.39 | E36: =+D36/Summary!$D$19 -> 0.00074985162 | F36: 1426.5 | G36: =F36/Summary!F$19 -> 0.00093919556 | H36: =+D36-F36 -> -295.11 | I36: 1126.56 | J36: =I36/Summary!I$19 -> 0.00085383936 | K36: =+D36-I36 -> 4.83 | M36: 2095.56 | N36: =+M36/Summary!$D$19 -> 0.0013888748 | O36: 2781 | P36: =O36/Summary!O$19 -> 0.00041112098 | Q36: =+M36-O36 -> -685.44 | R36: 2406.24 | S36: =R36/Summary!R$19 -> 0.00041029875 | T36: =+M36-R36 -> -310.68
B37: Decorations - 500 | C37: Decorations | D37: 0 | E37: =+D37/Summary!$D$19 -> 0 | F37: 0 | G37: =F37/Summary!F$19 -> 0 | H37: =+D37-F37 -> 0 | I37: 0 | J37: =I37/Summary!I$19 -> 0 | K37: =+D37-I37 -> 0 | M37: 0 | N37: =+M37/Summary!$D$19 -> 0 | O37: 0 | P37: =O37/Summary!O$19 -> 0 | Q37: =+M37-O37 -> 0 | R37: 0 | S37: =R37/Summary!R$19 -> 0 | T37: =+M37-R37 -> 0
B38: Entertainment - In-House - 500 | C38: Entertainment In-House | D38: 0 | E38: =+D38/Summary!$D$19 -> 0 | F38: 0 | G38: =F38/Summary!F$19 -> 0 | H38: =+D38-F38 -> 0 | I38: 0 | J38: =I38/Summary!I$19 -> 0 | K38: =+D38-I38 -> 0 | M38: 0 | N38: =+M38/Summary!$D$19 -> 0 | O38: 0 | P38: =O38/Summary!O$19 -> 0 | Q38: =+M38-O38 -> 0 | R38: 0 | S38: =R38/Summary!R$19 -> 0 | T38: =+M38-R38 -> 0
B39: Equipment Rental - 500 | C39: Equipment Rental | D39: 0 | E39: =+D39/Summary!$D$19 -> 0 | F39: 0 | G39: =F39/Summary!F$19 -> 0 | H39: =+D39-F39 -> 0 | I39: 0 | J39: =I39/Summary!I$19 -> 0 | K39: =+D39-I39 -> 0 | M39: 0 | N39: =+M39/Summary!$D$19 -> 0 | O39: 0 | P39: =O39/Summary!O$19 -> 0 | Q39: =+M39-O39 -> 0 | R39: 0 | S39: =R39/Summary!R$19 -> 0 | T39: =+M39-R39 -> 0
B40: Travel - Other - 500 | C40: Travel - Other | D40: 852.65 | E40: =+D40/Summary!$D$19 -> 0.00056511105 | F40: 220 | G40: =F40/Summary!F$19 -> 0.00014484614 | H40: =+D40-F40 -> 632.65 | I40: 70.35 | J40: =I40/Summary!I$19 -> 5.3319485e-05 | K40: =+D40-I40 -> 782.3 | M40: 824.97 | N40: =+M40/Summary!$D$19 -> 0.00054676557 | O40: 637 | P40: =O40/Summary!O$19 -> 9.4169026e-05 | Q40: =+M40-O40 -> 187.97 | R40: 207.25 | S40: =R40/Summary!R$19 -> 3.5339125e-05 | T40: =+M40-R40 -> 617.72
B41: Travel - Meals & Entertainment - 500 | C41: Travel - Meals & Entertainment | D41: -138.2 | E41: =+D41/Summary!$D$19 -> -9.1594847e-05 | F41: 420 | G41: =F41/Summary!F$19 -> 0.00027652445 | H41: =+D41-F41 -> -558.2 | I41: -160 | J41: =I41/Summary!I$19 -> -0.00012126677 | K41: =+D41-I41 -> 21.8 | M41: 996.29 | N41: =+M41/Summary!$D$19 -> 0.00066031136 | O41: 880 | P41: =O41/Summary!O$19 -> 0.00013009222 | Q41: =+M41-O41 -> 116.29 | R41: 58.95 | S41: =R41/Summary!R$19 -> 1.0051828e-05 | T41: =+M41-R41 -> 937.34
... B64: Human Resources - 500 | C64: Human Resources (Consolidated) | D64: 6957.45 | E64: =+D64/Summary!$D$19 -> 0.0046111908 | F64: 7963.33 | G64: =F64/Summary!F$19 -> 0.0052429892 | H64: =+D64-F64 -> -1005.88 | I64: 1723.62 | J64: =I64/Summary!I$19 -> 0.0013063615 | K64: =+D64-I64 -> 5233.83 | M64: 10418.02 | N64: =+M64/Summary!$D$19 -> 0.0069047536 | O64: 12400.32 | P64: =O64/Summary!O$19 -> 0.0018331649 | Q64: =+M64-O64 -> -1982.3 | R64: 8728.79 | S64: =R64/Summary!R$19 -> 0.0014883851 | T64: =+M64-R64 -> 1689.23
B65: Total Other Expenses - 500 | C65: Total Operations Expense | D65: =SUM(D30:D64) -> 74276.04 | E65: =+D65/Summary!$D$19 -> 0.049227949 | F65: =SUM(F30:F64) -> 89422.477 | G65: =F65/Summary!F$19 -> 0.058875004 | H65: =+D65-F65 -> -15146.437 | I65: =SUM(I30:I64) -> 69686.82 | J65: =I65/Summary!I$19 -> 0.052816849 | K65: =+D65-I65 -> 4589.22 | M65: =SUM(M30:M64) -> 271140.6 | N65: =+M65/Summary!$D$19 -> 0.17970392 | O65: =SUM(O30:O64) -> 320469.25 | P65: =O65/Summary!O$19 -> 0.047375631 | Q65: =+M65-O65 -> -49328.651 | R65: =SUM(R30:R64) -> 245208.82 | S65: =R65/Summary!R$19 -> 0.041811654 | T65: =+M65-R65 -> 25931.78
B67: Total Departmental Expenses - 500 | C67: Total Expenses | D67: =+D27+D65 -> 133968.94 | E67: =+D67/Summary!$D$19 -> 0.088790627 | F67: =+F27+F65 -> 149356.45 | G67: =F67/Summary!F$19 -> 0.098335024 | H67: =+D67-F67 -> -15387.507 | I67: =+I27+I65 -> 129067.13 | J67: =I67/Summary!I$19 -> 0.097822215 | K67: =+D67-I67 -> 4901.81 | M67: =+M27+M65 -> 506691.28 | N67: =+M67/Summary!$D$19 -> 0.3358199 | O67: =+O27+O65 -> 556416.48 | P67: =O67/Summary!O$19 -> 0.082256198 | Q67: =+M67-O67 -> -49725.201 | R67: =+R27+R65 -> 468717.71 | S67: =R67/Summary!R$19 -> 0.079923155 | T67: =+M67-R67 -> 37973.57
C68: Department Profit (Loss) | D68: =0-D67 -> -133968.94 | E68: =+D68/Summary!$D$19 -> -0.088790627 | F68: =0-F67 -> -149356.45 | G68: =F68/Summary!F$19 -> -0.098335024 | H68: =+D68-F68 -> 15387.507 | I68: =0-I67 -> -129067.13 | J68: =I68/Summary!I$19 -> -0.097822215 | K68: =+D68-I68 -> -4901.81 | M68: =0-M67 -> -506691.28 | N68: =+M68/Summary!$D$19 -> -0.3358199 | O68: =0-O67 -> -556416.48 | P68: =O68/Summary!O$19 -> -0.082256198 | Q68: =+M68-O68 -> 49725.201 | R68: =0-R67 -> -468717.71 | S68: =R68/Summary!R$19 -> -0.079923155 | T68: =+M68-R68 -> -37973.57

Sheet IT
V1: ANG
C2: =+Summary!$C$2 -> Angler's | V2: Apr
C3: =+Summary!$C$3 -> STATEMENT OF INCOME
C4: =+Summary!$C$4 -> FOR THE PERIOD ENDING APR 2025
D6: =Year&" "&UPPER(Month)&" - PERIODIC" -> 2025 APR - PERIODIC | M6: =Year&" "&UPPER(Month)&" - YEAR TO DATE" -> 2025 APR - YEAR TO DATE
D7: Actual | F7: Budget | H7: VARIANCE | I7: Actual - Last Year | K7: VARIANCE | M7: Actual | O7: Budget | Q7: VARIANCE | R7: Actual - Last Year | T7: VARIANCE
D8: $ | E8: % | F8: $ | G8: % | H8: $ | I8: Actual | J8: % | K8: $ | M8: $ | N8: % | O8: $ | P8: % | Q8: $ | R8: Actual | S8: % | T8: $
C9: Labor & Related Expenses
C10: Salaries & Wages
B11: S&W Management Reg - 600 | C11: Management | D11: 0 | E11: =+IFERROR(D11/Summary!D$19,"") -> 0 | F11: 0 | G11: =+IFERROR(F11/Summary!F$19,"") -> 0 | H11: =+D11-F11 -> 0 | I11: 0 | J11: =+IFERROR(I11/Summary!I$19,"") -> 0 | K11: =+D11-I11 -> 0 | M11: 0 | N11: =+IFERROR(M11/Summary!M$19,"") -> 0 | O11: 0 | P11: =+IFERROR(O11/Summary!O$19,"") -> 0 | Q11: =+M11-O11 -> 0 | R11: 0 | S11: =+IFERROR(R11/Summary!R$19,"") -> 0 | T11: =+M11-R11 -> 0
C12: Non-Management
B13: S&W Non-Management - 600 | C13: Accounting | D13: 0 | E13: =+IFERROR(D13/Summary!D$19,"") -> 0 | F13: 0 | G13: =+IFERROR(F13/Summary!F$19,"") -> 0 | H13: =+D13-F13 -> 0 | I13: 0 | J13: =+IFERROR(I13/Summary!I$19,"") -> 0 | K13: =+D13-I13 -> 0 | M13: 0 | N13: =+IFERROR(M13/Summary!M$19,"") -> 0 | O13: 0 | P13: =+IFERROR(O13/Summary!O$19,"") -> 0 | Q13: =+M13-O13 -> 0 | R13: 0 | S13: =+IFERROR(R13/Summary!R$19,"") -> 0 | T13: =+M13-R13 -> 0
B14: Total Salaries & Wages - 600 | C14: Total Salaries and Wages | D14: =+D11+D13 -> 0 | E14: =+IFERROR(D14/Summary!D$19,"") -> 0 | F14: =+F11+F13 -> 0 | G14: =+IFERROR(F14/Summary!F$19,"") -> 0 | H14: =+D14-F14 -> 0 | I14: =+I11+I13 -> 0 | J14: =+IFERROR(I14/Summary!I$19,"") -> 0 | K14: =+D14-I14 -> 0 | M14: =+M11+M13 -> 0 | N14: =+IFERROR(M14/Summary!M$19,"") -> 0 | O14: =+O11+O13 -> 0 | P14: =+IFERROR(O14/Summary!O$19,"") -> 0 | Q14: =+M14-O14 -> 0 | R14: =+R11+R13 -> 0 | S14: =+IFERROR(R14/Summary!R$19,"") -> 0 | T14: =+M14-R14 -> 0
B15: Total Contracted Leased & Outsourced Labor - 600 | C15: Contracted & Leased Labor | D15: 0 | E15: =+IFERROR(D15/Summary!D$19,"") -> 0 | F15: 0 | G15: =+IFERROR(F15/Summary!F$19,"") -> 0 | H15: =+D15-F15 -> 0 | I15: 0 | J15: =+IFERROR(I15/Summary!I$19,"") -> 0 | K15: =+D15-I15 -> 0 | M15: 0 | N15: =+IFERROR(M15/Summary!M$19,"") -> 0 | O15: 0 | P15: =+IFERROR(O15/Summary!O$19,"") -> 0 | Q15: =+M15-O15 -> 0 | R15: 0 | S15: =+IFERROR(R15/Summary!R$19,"") -> 0 | T15: =+M15-R15 -> 0
B16: Total Bonuses & Incentives - 600 | C16: Bonuses & Incentives | D16: 0 | E16: =+IFERROR(D16/Summary!D$19,"") -> 0 | F16: 0 | G16: =+IFERROR(F16/Summary!F$19,"") -> 0 | H16: =+D16-F16 -> 0 | I16: 0 | J16: =+IFERROR(I16/Summary!I$19,"") -> 0 | K16: =+D16-I16 -> 0 | M16: 0 | N16: =+IFERROR(M16/Summary!M$19,"") -> 0 | O16: 0 | P16: =+IFERROR(O16/Summary!O$19,"") -> 0 | Q16: =+M16-O16 -> 0 | R16: 0 | S16: =+IFERROR(R16/Summary!R$19,"") -> 0 | T16: =+M16-R16 -> 0
C17: Total Labor Expense | D17: =SUM(D14:D16) -> 0 | E17: =+IFERROR(D17/Summary!D$19,"") -> 0 | F17: =SUM(F14:F16) -> 0 | G17: =+IFERROR(F17/Summary!F$19,"") -> 0 | H17: =+D17-F17 -> 0 | I17: =SUM(I14:I16) -> 0 | J17: =+IFERROR(I17/Summary!I$19,"") -> 0 | K17: =+D17-I17 -> 0 | M17: =SUM(M14:M16) -> 0 | N17: =+IFERROR(M17/Summary!M$19,"") -> 0 | O17: =SUM(O14:O16) -> 0 | P17: =+IFERROR(O17/Summary!O$19,"") -> 0 | Q17: =+M17-O17 -> 0 | R17: =SUM(R14:R16) -> 0 | S17: =+IFERROR(R17/Summary!R$19,"") -> 0 | T17: =+M17-R17 -> 0
B18: Total Payroll Taxes - 600 | C18: Payroll Taxes | D18: 0 | E18: =+IFERROR(D18/Summary!D$19,"") -> 0 | F18: 0 | G18: =+IFERROR(F18/Summary!F$19,"") -> 0 | H18: =+D18-F18 -> 0 | I18: 0 | J18: =+IFERROR(I18/Summary!I$19,"") -> 0 | K18: =+D18-I18 -> 0 | M18: 0 | N18: =+IFERROR(M18/Summary!M$19,"") -> 0 | O18: 0 | P18: =+IFERROR(O18/Summary!O$19,"") -> 0 | Q18: =+M18-O18 -> 0 | R18: 0 | S18: =+IFERROR(R18/Summary!R$19,"") -> 0 | T18: =+M18-R18 -> 0
B19: Total Supplemental Pay - 600 | C19: Supplemental Pay | D19: 0 | E19: =+IFERROR(D19/Summary!D$19,"") -> 0 | F19: 0 | G19: =+IFERROR(F19/Summary!F$19,"") -> 0 | H19: =+D19-F19 -> 0 | I19: 0 | J19: =+IFERROR(I19/Summary!I$19,"") -> 0 | K19: =+D19-I19 -> 0 | M19: 0 | N19: =+IFERROR(M19/Summary!M$19,"") -> 0 | O19: 0 | P19: =+IFERROR(O19/Summary!O$19,"") -> 0 | Q19: =+M19-O19 -> 0 | R19: 0 | S19: =+IFERROR(R19/Summary!R$19,"") -> 0 | T19: =+M19-R19 -> 0
B20: Total Employee Benefits - 600 | C20: Employee Benefits | D20: 0 | E20: =+IFERROR(D20/Summary!D$19,"") -> 0 | F20: 0 | G20: =+IFERROR(F20/Summary!F$19,"") -> 0 | H20: =+D20-F20 -> 0 | I20: 0 | J20: =+IFERROR(I20/Summary!I$19,"") -> 0 | K20: =+D20-I20 -> 0 | M20: 0 | N20: =+IFERROR(M20/Summary!M$19,"") -> 0 | O20: 0 | P20: =+IFERROR(O20/Summary!O$19,"") -> 0 | Q20: =+M20-O20 -> 0 | R20: 0 | S20: =+IFERROR(R20/Summary!R$19,"") -> 0 | T20: =+M20-R20 -> 0
B21: Total Payroll-Related Expenses - 600 | C21: Total Payroll Related | D21: =SUM(D18:D20) -> 0 | E21: =+IFERROR(D21/Summary!D$19,"") -> 0 | F21: =SUM(F18:F20) -> 0 | G21: =+IFERROR(F21/Summary!F$19,"") -> 0 | H21: =+D21-F21 -> 0 | I21: =SUM(I18:I20) -> 0 | J21: =+IFERROR(I21/Summary!I$19,"") -> 0 | K21: =+D21-I21 -> 0 | M21: =SUM(M18:M20) -> 0 | N21: =+IFERROR(M21/Summary!M$19,"") -> 0 | O21: =SUM(O18:O20) -> 0 | P21: =+IFERROR(O21/Summary!O$19,"") -> 0 | Q21: =+M21-O21 -> 0 | R21: =SUM(R18:R20) -> 0 | S21: =+IFERROR(R21/Summary!R$19,"") -> 0 | T21: =+M21-R21 -> 0
B22: Total Labor Costs & Related Expenses - 600 | C22: Total Labor & Related Exp | D22: =+D17+D21 -> 0 | E22: =+IFERROR(D22/Summary!D$19,"") -> 0 | F22: =+F17+F21 -> 0 | G22: =+IFERROR(F22/Summary!F$19,"") -> 0 | H22: =+D22-F22 -> 0 | I22: =+I17+I21 -> 0 | J22: =+IFERROR(I22/Summary!I$19,"") -> 0 | K22: =+D22-I22 -> 0 | M22: =+M17+M21 -> 0 | N22: =+IFERROR(M22/Summary!M$19,"") -> 0 | O22: =+O17+O21 -> 0 | P22: =+IFERROR(O22/Summary!O$19,"") -> 0 | Q22: =+M22-O22 -> 0 | R22: =+R17+R21 -> 0 | S22: =+IFERROR(R22/Summary!R$19,"") -> 0 | T22: =+M22-R22 -> 0
C24: Cost of Services
B25: Cost of Cell Phones - 600 | C25: Cost of Cell Phones | D25: 762.57 | E25: =+IFERROR(D25/Summary!D$19,"") -> 0.0005054087 | F25: 657 | G25: =+IFERROR(F25/Summary!F$19,"") -> 0.00043256325 | H25: =+D25-F25 -> 105.57 | I25: 604.19 | J25: =+IFERROR(I25/Summary!I$19,"") -> 0.00045792608 | K25: =+D25-I25 -> 158.38 | M25: 2495.94 | N25: =+IFERROR(M25/Summary!M$19,"") -> 0.00039685841 | O25: 2628 | P25: =+IFERROR(O25/Summary!O$19,"") -> 0.00038850267 | Q25: =+M25-O25 -> -132.06 | R25: 2643.82 | S25: =+IFERROR(R25/Summary!R$19,"") -> 0.00045080958 | T25: =+M25-R25 -> -147.88
B26: Cost of Internet Services - 600 | C26: Cost of Internet Services | D26: 4146.02 | E26: =+IFERROR(D26/Summary!D$19,"") -> 0.0027478587 | F26: 4027 | G26: =+IFERROR(F26/Summary!F$19,"") -> 0.0026513428 | H26: =+D26-F26 -> 119.02 | I26: 3493.16 | J26: =+IFERROR(I26/Summary!I$19,"") -> 0.0026475265 | K26: =+D26-I26 -> 652.86 | M26: 17388.76 | N26: =+IFERROR(M26/Summary!M$19,"") -> 0.0027648404 | O26: 16108 | P26: =+IFERROR(O26/Summary!O$19,"") -> 0.0023812789 | Q26: =+M26-O26 -> 1280.76 | R26: 14431.72 | S26: =+IFERROR(R26/Summary!R$19,"") -> 0.0024608172 | T26: =+M26-R26 -> 2957.04
B27: Cost of Local Calls - 600 | C27: Cost of Local Calls | D27: 0 | E27: =+IFERROR(D27/Summary!D$19,"") -> 0 | F27: 0 | G27: =+IFERROR(F27/Summary!F$19,"") -> 0 | H27: =+D27-F27 -> 0 | I27: 0 | J27: =+IFERROR(I27/Summary!I$19,"") -> 0 | K27: =+D27-I27 -> 0 | M27: 0 | N27: =+IFERROR(M27/Summary!M$19,"") -> 0 | O27: 0 | P27: =+IFERROR(O27/Summary!O$19,"") -> 0 | Q27: =+M27-O27 -> 0 | R27: 0 | S27: =+IFERROR(R27/Summary!R$19,"") -> 0 | T27: =+M27-R27 -> 0
B28: Cost of Long Distance Calls - 600 | C28: Cost of Long Distance Calls | D28: 0 | E28: =+IFERROR(D28/Summary!D$19,"") -> 0 | F28: 0 | G28: =+IFERROR(F28/Summary!F$19,"") -> 0 | H28: =+D28-F28 -> 0 | I28: 0 | J28: =+IFERROR(I28/Summary!I$19,"") -> 0 | K28: =+D28-I28 -> 0 | M28: 0 | N28: =+IFERROR(M28/Summary!M$19,"") -> 0 | O28: 0 | P28: =+IFERROR(O28/Summary!O$19,"") -> 0 | Q28: =+M28-O28 -> 0 | R28: 0 | S28: =+IFERROR(R28/Summary!R$19,"") -> 0 | T28: =+M28-R28 -> 0
B29: Other Cost of Services - 600 | C29: Other Cost of Services | D29: 0 | E29: =+IFERROR(D29/Summary!D$19,"") -> 0 | F29: 0 | G29: =+IFERROR(F29/Summary!F$19,"") -> 0 | H29: =+D29-F29 -> 0 | I29: 0 | J29: =+IFERROR(I29/Summary!I$19,"") -> 0 | K29: =+D29-I29 -> 0 | M29: 0 | N29: =+IFERROR(M29/Summary!M$19,"") -> 0 | O29: 0 | P29: =+IFERROR(O29/Summary!O$19,"") -> 0 | Q29: =+M29-O29 -> 0 | R29: 0 | S29: =+IFERROR(R29/Summary!R$19,"") -> 0 | T29: =+M29-R29 -> 0
B30: Cost of Services - 600 | C30: Total Cost of Services | D30: =SUM(D25:D29) -> 4908.59 | E30: =+IFERROR(D30/Summary!D$19,"") -> 0.0032532674 | F30: =SUM(F25:F29) -> 4684 | G30: =+IFERROR(F30/Summary!F$19,"") -> 0.0030839061 | H30: =+D30-F30 -> 224.59 | I30: =SUM(I25:I29) -> 4097.35 | J30: =+IFERROR(I30/Summary!I$19,"") -> 0.0031054526 | K30: =+D30-I30 -> 811.24 | M30: =SUM(M25:M29) -> 19884.7 | N30: =+IFERROR(M30/Summary!M$19,"") -> 0.0031616988 | O30: =SUM(O25:O29) -> 18736 | P30: =+IFERROR(O30/Summary!O$19,"") -> 0.0027697816 | Q30: =+M30-O30 -> 1148.7 | R30: =SUM(R25:R29) -> 17075.54 | S30: =+IFERROR(R30/Summary!R$19,"") -> 0.0029116268 | T30: =+M30-R30 -> 2809.16
C32: System Expenses
B33: Administrative & General - 600 | C33: Administrative and General | D33: 475 | E33: =+IFERROR(D33/Summary!D$19,"") -> 0.00031481586 | F33: 460 | G33: =+IFERROR(F33/Summary!F$19,"") -> 0.00030286012 | H33: =+D33-F33 -> 15 | I33: 255 | J33: =+IFERROR(I33/Summary!I$19,"") -> 0.00019326892 | K33: =+D33-I33 -> 220 | M33: 2175 | N33: =+IFERROR(M33/Summary!M$19,"") -> 0.00034582844 | O33: 1840 | P33: =+IFERROR(O33/Summary!O$19,"") -> 0.000272011 | Q33: =+M33-O33 -> 335 | R33: 1020 | S33: =+IFERROR(R33/Summary!R$19,"") -> 0.00017392477 | T33: =+M33-R33 -> 1155
B34: Centralized Information System Charges - 600 | C34: Human Resources | D34: 0 | E34: =+IFERROR(D34/Summary!D$19,"") -> 0 | F34: 0 | G34: =+IFERROR(F34/Summary!F$19,"") -> 0 | H34: =+D34-F34 -> 0 | I34: 0 | J34: =+IFERROR(I34/Summary!I$19,"") -> 0 | K34: =+D34-I34 -> 0 | M34: 0 | N34: =+IFERROR(M34/Summary!M$19,"") -> 0 | O34: 0 | P34: =+IFERROR(O34/Summary!O$19,"") -> 0 | Q34: =+M34-O34 -> 0 | R34: 0 | S34: =+IFERROR(R34/Summary!R$19,"") -> 0 | T34: =+M34-R34 -> 0
B35: Energy Management - 600 | C35: Energy Management | D35: 0 | E35: =+IFERROR(D35/Summary!D$19,"") -> 0 | F35: 0 | G35: =+IFERROR(F35/Summary!F$19,"") -> 0 | H35: =+D35-F35 -> 0 | I35: 0 | J35: =+IFERROR(I35/Summary!I$19,"") -> 0 | K35: =+D35-I35 -> 0 | M35: 0 | N35: =+IFERROR(M35/Summary!M$19,"") -> 0 | O35: 0 | P35: =+IFERROR(O35/Summary!O$19,"") -> 0 | Q35: =+M35-O35 -> 0 | R35: 0 | S35: =+IFERROR(R35/Summary!R$19,"") -> 0 | T35: =+M35-R35 -> 0
B36: Food & Beverage - 600 | C36: Food & Beverage | D36: 0 | E36: =+IFERROR(D36/Summary!D$19,"") -> 0 | F36: 0 | G36: =+IFERROR(F36/Summary!F$19,"") -> 0 | H36: =+D36-F36 -> 0 | I36: 0 | J36: =+IFERROR(I36/Summary!I$19,"") -> 0 | K36: =+D36-I36 -> 0 | M36: 0 | N36: =+IFERROR(M36/Summary!M$19,"") -> 0 | O36: 0 | P36: =+IFERROR(O36/Summary!O$19,"") -> 0 | Q36: =+M36-O36 -> 0 | R36: 168.53 | S36: =+IFERROR(R36/Summary!R$19,"") -> 2.8736805e-05 | T36: =+M36-R36 -> -168.53
B37: Golf - 600 | C37: Golf | D37: 0 | E37: =+IFERROR(D37/Summary!D$19,"") -> 0 | F37: 0 | G37: =+IFERROR(F37/Summary!F$19,"") -> 0 | H37: =+D37-F37 -> 0 | I37: 0 | J37: =+IFERROR(I37/Summary!I$19,"") -> 0 | K37: =+D37-I37 -> 0 | M37: 0 | N37: =+IFERROR(M37/Summary!M$19,"") -> 0 | O37: 0 | P37: =+IFERROR(O37/Summary!O$19,"") -> 0 | Q37: =+M37-O37 -> 0 | R37: 0 | S37: =+IFERROR(R37/Summary!R$19,"") -> 0 | T37: =+M37-R37 -> 0
B38: Hardware - 600 | C38: Hardware | D38: 277.5 | E38: =+IFERROR(D38/Summary!D$19,"") -> 0.00018391874 | F38: 0 | G38: =+IFERROR(F38/Summary!F$19,"") -> 0 | H38: =+D38-F38 -> 277.5 | I38: 0 | J38: =+IFERROR(I38/Summary!I$19,"") -> 0 | K38: =+D38-I38 -> 277.5 | M38: 2124 | N38: =+IFERROR(M38/Summary!M$19,"") -> 0.00033771936 | O38: 1600 | P38: =+IFERROR(O38/Summary!O$19,"") -> 0.00023653131 | Q38: =+M38-O38 -> 524 | R38: 1639.2 | S38: =+IFERROR(R38/Summary!R$19,"") -> 0.00027950733 | T38: =+M38-R38 -> 484.8
B39: Health Club/Spa - 600 | C39: Health Club/Spa | D39: 0 | E39: =+IFERROR(D39/Summary!D$19,"") -> 0 | F39: 0 | G39: =+IFERROR(F39/Summary!F$19,"") -> 0 | H39: =+D39-F39 -> 0 | I39: 0 | J39: =+IFERROR(I39/Summary!I$19,"") -> 0 | K39: =+D39-I39 -> 0 | M39: 0 | N39: =+IFERROR(M39/Summary!M$19,"") -> 0 | O39: 0 | P39: =+IFERROR(O39/Summary!O$19,"") -> 0 | Q39: =+M39-O39 -> 0 | R39: 0 | S39: =+IFERROR(R39/Summary!R$19,"") -> 0 | T39: =+M39-R39 -> 0
B40: Human Resources - 600 | C40: Human Resources | D40: 523.92 | E40: =+IFERROR(D40/Summary!D$19,"") -> 0.00034723858 | F40: 613.5 | G40: =+IFERROR(F40/Summary!F$19,"") -> 0.00040392322 | H40: =+D40-F40 -> -89.58 | I40: 3091.68 | J40: =+IFERROR(I40/Summary!I$19,"") -> 0.0023432379 | K40: =+D40-I40 -> -2567.76 | M40: 3389.52 | N40: =+IFERROR(M40/Summary!M$19,"") -> 0.00053893905 | O40: 2454 | P40: =+IFERROR(O40/Summary!O$19,"") -> 0.00036277989 | Q40: =+M40-O40 -> 935.52 | R40: 6041.11 | S40: =+IFERROR(R40/Summary!R$19,"") -> 0.0010300967 | T40: =+M40-R40 -> -2651.59
B41: Information Security - 600 | C41: Information Security | D41: 0 | E41: =+IFERROR(D41/Summary!D$19,"") -> 0 | F41: 0 | G41: =+IFERROR(F41/Summary!F$19,"") -> 0 | H41: =+D41-F41 -> 0 | I41: 0 | J41: =+IFERROR(I41/Summary!I$19,"") -> 0 | K41: =+D41-I41 -> 0 | M41: 0 | N41: =+IFERROR(M41/Summary!M$19,"") -> 0 | O41: 0 | P41: =+IFERROR(O41/Summary!O$19,"") -> 0 | Q41: =+M41-O41 -> 0 | R41: 0 | S41: =+IFERROR(R41/Summary!R$19,"") -> 0 | T41: =+M41-R41 -> 0
B42: Information Systems - 600 | C42: Information Systems | D42: 0 | E42: =+IFERROR(D42/Summary!D$19,"") -> 0 | F42: 0 | G42: =+IFERROR(F42/Summary!F$19,"") -> 0 | H42: =+D42-F42 -> 0 | I42: 0 | J42: =+IFERROR(I42/Summary!I$19,"") -> 0 | K42: =+D42-I42 -> 0 | M42: 0 | N42: =+IFERROR(M42/Summary!M$19,"") -> 0 | O42: 0 | P42: =+IFERROR(O42/Summary!O$19,"") -> 0 | Q42: =+M42-O42 -> 0 | R42: -1287.51 | S42: =+IFERROR(R42/Summary!R$19,"") -> -0.00021953909 | T42: =+M42-R42 -> 1287.51
B43: Other - 600 | C43: Other | D43: 749.32 | E43: =+IFERROR(D43/Summary!D$19,"") -> 0.000496627 | F43: 1023.83 | G43: =+IFERROR(F43/Summary!F$19,"") -> 0.00067408103 | H43: =+D43-F43 -> -274.51 | I43: 1270 | J43: =+IFERROR(I43/Summary!I$19,"") -> 0.00096255502 | K43: =+D43-I43 -> -520.68 | M43: 1534.32 | N43: =+IFERROR(M43/Summary!M$19,"") -> 0.00024395931 | O43: 2595.32 | P43: =+IFERROR(O43/Summary!O$19,"") -> 0.00038367152 | Q43: =+M43-O43 -> -1061 | R43: 3756 | S43: =+IFERROR(R43/Summary!R$19,"") -> 0.00064045237 | T43: =+M43-R43 -> -2221.68
B44: Parking - 600 | C44: Parking | D44: 0 | E44: =+IFERROR(D44/Summary!D$19,"") -> 0 | F44: 0 | G44: =+IFERROR(F44/Summary!F$19,"") -> 0 | H44: =+D44-F44 -> 0 | I44: 0 | J44: =+IFERROR(I44/Summary!I$19,"") -> 0 | K44: =+D44-I44 -> 0 | M44: 0 | N44: =+IFERROR(M44/Summary!M$19,"") -> 0 | O44: 0 | P44: =+IFERROR(O44/Summary!O$19,"") -> 0 | Q44: =+M44-O44 -> 0 | R44: 0 | S44: =+IFERROR(R44/Summary!R$19,"") -> 0 | T44: =+M44-R44 -> 0
... B48: Telecommunications - 600 | C48: Telecommunications | D48: 0 | E48: =+IFERROR(D48/Summary!D$19,"") -> 0 | F48: 0 | G48: =+IFERROR(F48/Summary!F$19,"") -> 0 | H48: =+D48-F48 -> 0 | I48: 0 | J48: =+IFERROR(I48/Summary!I$19,"") -> 0 | K48: =+D48-I48 -> 0 | M48: 0 | N48: =+IFERROR(M48/Summary!M$19,"") -> 0 | O48: 0 | P48: =+IFERROR(O48/Summary!O$19,"") -> 0 | Q48: =+M48-O48 -> 0 | R48: 0 | S48: =+IFERROR(R48/Summary!R$19,"") -> 0 | T48: =+M48-R48 -> 0
B49: Systems Expenses - 600 | C49: Total System Expenses | D49: =SUM(D33:D48) -> 3830.68 | E49: =+IFERROR(D49/Summary!D$19,"") -> 0.0025388607 | F49: =SUM(F33:F48) -> 3812.33 | G49: =+IFERROR(F49/Summary!F$19,"") -> 0.0025100059 | H49: =+D49-F49 -> 18.35 | I49: =SUM(I33:I48) -> 4907.31 | J49: =+IFERROR(I49/Summary!I$19,"") -> 0.0037193353 | K49: =+D49-I49 -> -1076.63 | M49: =SUM(M33:M48) -> 29504.14 | N49: =+IFERROR(M49/Summary!M$19,"") -> 0.004691205 | O49: =SUM(O33:O48) -> 27956.32 | P49: =+IFERROR(O49/Summary!O$19,"") -> 0.0041328405 | Q49: =+M49-O49 -> 1547.82 | R49: =SUM(R33:R48) -> 29022.94 | S49: =+IFERROR(R49/Summary!R$19,"") -> 0.0049488314 | T49: =+M49-R49 -> 481.2
C51: Other Expenses
B52: Cluster Services - 600 | C52: Cluster Services | D52: 0 | E52: =+IFERROR(D52/Summary!D$19,"") -> 0 | F52: 0 | G52: =+IFERROR(F52/Summary!F$19,"") -> 0 | H52: =+D52-F52 -> 0 | I52: 0 | J52: =+IFERROR(I52/Summary!I$19,"") -> 0 | K52: =+D52-I52 -> 0 | M52: 0 | N52: =+IFERROR(M52/Summary!M$19,"") -> 0 | O52: 0 | P52: =+IFERROR(O52/Summary!O$19,"") -> 0 | Q52: =+M52-O52 -> 0 | R52: 0 | S52: =+IFERROR(R52/Summary!R$19,"") -> 0 | T52: =+M52-R52 -> 0
B53: Contract Services - 600 | C53: Contract Services | D53: 56.12 | E53: =+IFERROR(D53/Summary!D$19,"") -> 3.7194666e-05 | F53: 118.75 | G53: =+IFERROR(F53/Summary!F$19,"") -> 7.8183998e-05 | H53: =+D53-F53 -> -62.63 | I53: 91.42 | J53: =+IFERROR(I53/Summary!I$19,"") -> 6.9288803e-05 | K53: =+D53-I53 -> -35.3 | M53: 273.26 | N53: =+IFERROR(M53/Summary!M$19,"") -> 4.3448773e-05 | O53: 475 | P53: =+IFERROR(O53/Summary!O$19,"") -> 7.0220231e-05 | Q53: =+M53-O53 -> -201.74 | R53: 368.53 | S53: =+IFERROR(R53/Summary!R$19,"") -> 6.28397e-05 | T53: =+M53-R53 -> -95.27
B54: Corporate Office Reimbursables - 600 | C54: Corporate Office Reimbursables | D54: 7365.44 | E54: =+IFERROR(D54/Summary!D$19,"") -> 0.0048815944 | F54: 7066.62 | G54: =+IFERROR(F54/Summary!F$19,"") -> 0.004652603 | H54: =+D54-F54 -> 298.82 | I54: 6695.29 | J54: =+IFERROR(I54/Summary!I$19,"") -> 0.0050744764 | K54: =+D54-I54 -> 670.15 | M54: 30699.12 | N54: =+IFERROR(M54/Summary!M$19,"") -> 0.0048812087 | O54: 32468.69 | P54: =+IFERROR(O54/Summary!O$19,"") -> 0.0047999135 | Q54: =+M54-O54 -> -1769.57 | R54: 31540.02 | S54: =+IFERROR(R54/Summary!R$19,"") -> 0.00537803 | T54: =+M54-R54 -> -840.9
B55: Dues & Subscriptions - 600 | C55: Dues & Subscriptions | D55: 0 | E55: =+IFERROR(D55/Summary!D$19,"") -> 0 | F55: 0 | G55: =+IFERROR(F55/Summary!F$19,"") -> 0 | H55: =+D55-F55 -> 0 | I55: 0 | J55: =+IFERROR(I55/Summary!I$19,"") -> 0 | K55: =+D55-I55 -> 0 | M55: 0 | N55: =+IFERROR(M55/Summary!M$19,"") -> 0 | O55: 0 | P55: =+IFERROR(O55/Summary!O$19,"") -> 0 | Q55: =+M55-O55 -> 0 | R55: 0 | S55: =+IFERROR(R55/Summary!R$19,"") -> 0 | T55: =+M55-R55 -> 0
B56: Entertainment- In-House - 600 | C56: Entertainment- In-House | D56: 0 | E56: =+IFERROR(D56/Summary!D$19,"") -> 0 | F56: 0 | G56: =+IFERROR(F56/Summary!F$19,"") -> 0 | H56: =+D56-F56 -> 0 | I56: 0 | J56: =+IFERROR(I56/Summary!I$19,"") -> 0 | K56: =+D56-I56 -> 0 | M56: 0 | N56: =+IFERROR(M56/Summary!M$19,"") -> 0 | O56: 0 | P56: =+IFERROR(O56/Summary!O$19,"") -> 0 | Q56: =+M56-O56 -> 0 | R56: 0 | S56: =+IFERROR(R56/Summary!R$19,"") -> 0 | T56: =+M56-R56 -> 0
B57: Equipment Rental - 600 | C57: Equipment Rental | D57: 0 | E57: =+IFERROR(D57/Summary!D$19,"") -> 0 | F57: 0 | G57: =+IFERROR(F57/Summary!F$19,"") -> 0 | H57: =+D57-F57 -> 0 | I57: 0 | J57: =+IFERROR(I57/Summary!I$19,"") -> 0 | K57: =+D57-I57 -> 0 | M57: 0 | N57: =+IFERROR(M57/Summary!M$19,"") -> 0 | O57: 0 | P57: =+IFERROR(O57/Summary!O$19,"") -> 0 | Q57: =+M57-O57 -> 0 | R57: 0 | S57: =+IFERROR(R57/Summary!R$19,"") -> 0 | T57: =+M57-R57 -> 0
B58: Miscellaneous - 600 | C58: Miscellaneous | D58: 0 | E58: =+IFERROR(D58/Summary!D$19,"") -> 0 | F58: 0 | G58: =+IFERROR(F58/Summary!F$19,"") -> 0 | H58: =+D58-F58 -> 0 | I58: 0 | J58: =+IFERROR(I58/Summary!I$19,"") -> 0 | K58: =+D58-I58 -> 0 | M58: 0 | N58: =+IFERROR(M58/Summary!M$19,"") -> 0 | O58: 0 | P58: =+IFERROR(O58/Summary!O$19,"") -> 0 | Q58: =+M58-O58 -> 0 | R58: 0 | S58: =+IFERROR(R58/Summary!R$19,"") -> 0 | T58: =+M58-R58 -> 0
B59: Operating Supplies - 600 | C59: Operating Supplies | D59: 0 | E59: =+IFERROR(D59/Summary!D$19,"") -> 0 | F59: 0 | G59: =+IFERROR(F59/Summary!F$19,"") -> 0 | H59: =+D59-F59 -> 0 | I59: 0 | J59: =+IFERROR(I59/Summary!I$19,"") -> 0 | K59: =+D59-I59 -> 0 | M59: 0 | N59: =+IFERROR(M59/Summary!M$19,"") -> 0 | O59: 0 | P59: =+IFERROR(O59/Summary!O$19,"") -> 0 | Q59: =+M59-O59 -> 0 | R59: 0 | S59: =+IFERROR(R59/Summary!R$19,"") -> 0 | T59: =+M59-R59 -> 0
B60: Other Equipment - 600 | C60: Other Equipment | D60: 0 | E60: =+IFERROR(D60/Summary!D$19,"") -> 0 | F60: 0 | G60: =+IFERROR(F60/Summary!F$19,"") -> 0 | H60: =+D60-F60 -> 0 | I60: 0 | J60: =+IFERROR(I60/Summary!I$19,"") -> 0 | K60: =+D60-I60 -> 0 | M60: 0 | N60: =+IFERROR(M60/Summary!M$19,"") -> 0 | O60: 0 | P60: =+IFERROR(O60/Summary!O$19,"") -> 0 | Q60: =+M60-O60 -> 0 | R60: 0 | S60: =+IFERROR(R60/Summary!R$19,"") -> 0 | T60: =+M60-R60 -> 0
B61: System Storage & Optimization - 600 | C61: System Storage & Optimization | D61: 0 | E61: =+IFERROR(D61/Summary!D$19,"") -> 0 | F61: 0 | G61: =+IFERROR(F61/Summary!F$19,"") -> 0 | H61: =+D61-F61 -> 0 | I61: 0 | J61: =+IFERROR(I61/Summary!I$19,"") -> 0 | K61: =+D61-I61 -> 0 | M61: 0 | N61: =+IFERROR(M61/Summary!M$19,"") -> 0 | O61: 0 | P61: =+IFERROR(O61/Summary!O$19,"") -> 0 | Q61: =+M61-O61 -> 0 | R61: 0 | S61: =+IFERROR(R61/Summary!R$19,"") -> 0 | T61: =+M61-R61 -> 0
B62: Training - 600 | C62: Training | D62: 0 | E62: =+IFERROR(D62/Summary!D$19,"") -> 0 | F62: 0 | G62: =+IFERROR(F62/Summary!F$19,"") -> 0 | H62: =+D62-F62 -> 0 | I62: 0 | J62: =+IFERROR(I62/Summary!I$19,"") -> 0 | K62: =+D62-I62 -> 0 | M62: 0 | N62: =+IFERROR(M62/Summary!M$19,"") -> 0 | O62: 0 | P62: =+IFERROR(O62/Summary!O$19,"") -> 0 | Q62: =+M62-O62 -> 0 | R62: 0 | S62: =+IFERROR(R62/Summary!R$19,"") -> 0 | T62: =+M62-R62 -> 0
B63: Travel - Meals & Entertainment - 600 | C63: Travel - Meals & Entertainment | D63: 0 | E63: =+IFERROR(D63/Summary!D$19,"") -> 0 | F63: 0 | G63: =+IFERROR(F63/Summary!F$19,"") -> 0 | H63: =+D63-F63 -> 0 | I63: 0 | J63: =+IFERROR(I63/Summary!I$19,"") -> 0 | K63: =+D63-I63 -> 0 | M63: 0 | N63: =+IFERROR(M63/Summary!M$19,"") -> 0 | O63: 0 | P63: =+IFERROR(O63/Summary!O$19,"") -> 0 | Q63: =+M63-O63 -> 0 | R63: 0 | S63: =+IFERROR(R63/Summary!R$19,"") -> 0 | T63: =+M63-R63 -> 0
... B66: Uniform Laundry - 600 | C66: Uniform Laundry | D66: 0 | E66: =+IFERROR(D66/Summary!D$19,"") -> 0 | F66: 0 | G66: =+IFERROR(F66/Summary!F$19,"") -> 0 | H66: =+D66-F66 -> 0 | I66: 0 | J66: =+IFERROR(I66/Summary!I$19,"") -> 0 | K66: =+D66-I66 -> 0 | M66: 0 | N66: =+IFERROR(M66/Summary!M$19,"") -> 0 | O66: 0 | P66: =+IFERROR(O66/Summary!O$19,"") -> 0 | Q66: =+M66-O66 -> 0 | R66: 0 | S66: =+IFERROR(R66/Summary!R$19,"") -> 0 | T66: =+M66-R66 -> 0
B67: Other Expenses - 600 | C67: Total Operations Expense | D67: =SUM(D52:D66) -> 7421.56 | E67: =+IFERROR(D67/Summary!D$19,"") -> 0.0049187891 | F67: =SUM(F52:F66) -> 7185.37 | G67: =+IFERROR(F67/Summary!F$19,"") -> 0.004730787 | H67: =+D67-F67 -> 236.19 | I67: =SUM(I52:I66) -> 6825.14 | J67: =+IFERROR(I67/Summary!I$19,"") -> 0.0051728919 | K67: =+D67-I67 -> 596.42 | M67: =SUM(M52:M66) -> 30972.38 | N67: =+IFERROR(M67/Summary!M$19,"") -> 0.0049246575 | O67: =SUM(O52:O66) -> 32943.69 | P67: =+IFERROR(O67/Summary!O$19,"") -> 0.0048701338 | Q67: =+M67-O67 -> -1971.31 | R67: =SUM(R52:R66) -> 31946.98 | S67: =+IFERROR(R67/Summary!R$19,"") -> 0.0054474226 | T67: =+M67-R67 -> -974.6
B69: Total Other Expenses - 600 | C69: Total Expenses | D69: =+D30+D49+D67 -> 16160.83 | E69: =+IFERROR(D69/Summary!D$19,"") -> 0.010710917 | F69: =+F30+F49+F67 -> 15681.7 | G69: =+IFERROR(F69/Summary!F$19,"") -> 0.010324699 | H69: =+D69-F69 -> 479.13 | I69: =+I30+I49+I67 -> 15829.8 | J69: =+IFERROR(I69/Summary!I$19,"") -> 0.01199768 | K69: =+D69-I69 -> 331.03 | M69: =+M30+M49+M67 -> 80361.22 | N69: =+IFERROR(M69/Summary!M$19,"") -> 0.012777561 | O69: =+O30+O49+O67 -> 79636.01 | P69: =+IFERROR(O69/Summary!O$19,"") -> 0.011772756 | Q69: =+M69-O69 -> 725.21 | R69: =+R30+R49+R67 -> 78045.46 | S69: =+IFERROR(R69/Summary!R$19,"") -> 0.013307881 | T69: =+M69-R69 -> 2315.76
C70: Department Profit (Loss) | D70: =0-D69 -> -16160.83 | E70: =+IFERROR(D70/Summary!D$19,"") -> -0.010710917 | F70: =0-F69 -> -15681.7 | G70: =+IFERROR(F70/Summary!F$19,"") -> -0.010324699 | H70: =+D70-F70 -> -479.13 | I70: =0-I69 -> -15829.8 | J70: =+IFERROR(I70/Summary!I$19,"") -> -0.01199768 | K70: =+D70-I70 -> -331.03 | M70: =0-M69 -> -80361.22 | N70: =+IFERROR(M70/Summary!M$19,"") -> -0.012777561 | O70: =0-O69 -> -79636.01 | P70: =+IFERROR(O70/Summary!O$19,"") -> -0.011772756 | Q70: =+M70-O70 -> -725.21 | R70: =0-R69 -> -78045.46 | S70: =+IFERROR(R70/Summary!R$19,"") -> -0.013307881 | T70: =+M70-R70 -> -2315.76

Sheet SM
V1: ANG
C2: =+Summary!$C$2 -> Angler's | V2: Apr
C3: =+Summary!$C$3 -> STATEMENT OF INCOME
C4: =+Summary!$C$4 -> FOR THE PERIOD ENDING APR 2025
D6: =Year&" "&UPPER(Month)&" - PERIODIC" -> 2025 APR - PERIODIC | M6: =Year&" "&UPPER(Month)&" - YEAR TO DATE" -> 2025 APR - YEAR TO DATE
D7: Actual | F7: Budget | H7: VARIANCE | I7: Actual - Last Year | K7: VARIANCE | M7: Actual | O7: Budget | Q7: VARIANCE | R7: Actual - Last Year | T7: VARIANCE
D8: $ | E8: % | F8: $ | G8: % | H8: $ | I8: Actual | J8: % | K8: $ | M8: $ | N8: % | O8: $ | P8: % | Q8: $ | R8: Actual | S8: % | T8: $
C9: Labor & Related Expenses
C10: Salaries & Wages
B11: S&W Management - 700 | C11: Management | D11: 21373.73 | E11: =+IFERROR(D11/Summary!D$19,"") -> 0.014165872 | F11: 25161.15 | G11: =+IFERROR(F11/Summary!F$19,"") -> 0.016565889 | H11: =+D11-F11 -> -3787.42 | I11: 24739.37 | J11: =+IFERROR(I11/Summary!I$19,"") -> 0.018750397 | K11: =+D11-I11 -> -3365.64 | M11: 82831.07 | N11: =+IFERROR(M11/Summary!M$19,"") -> 0.013170271 | O11: 95861.92 | P11: =+IFERROR(O11/Summary!O$19,"") -> 0.014171466 | Q11: =+M11-O11 -> -13030.85 | R11: 92384.27 | S11: =+IFERROR(R11/Summary!R$19,"") -> 0.015752855 | T11: =+M11-R11 -> -9553.2
C12: Non-Management | E12: =+IFERROR(D12/Summary!D$19,"") -> 0 | G12: =+IFERROR(F12/Summary!F$19,"") -> 0 | N12: =+IFERROR(M12/Summary!M$19,"") -> 0 | P12: =+IFERROR(O12/Summary!O$19,"") -> 0
B13: S&W Non-Management - 700 | C13: Non-Mgmt. (Sales & Marketing) | D13: 2161 | E13: =+IFERROR(D13/Summary!D$19,"") -> 0.0014322465 | F13: 1932.86 | G13: =+IFERROR(F13/Summary!F$19,"") -> 0.0012725787 | H13: =+D13-F13 -> 228.14 | I13: 3789.28 | J13: =+IFERROR(I13/Summary!I$19,"") -> 0.002871961 | K13: =+D13-I13 -> -1628.28 | M13: 11178.25 | N13: =+IFERROR(M13/Summary!M$19,"") -> 0.0017773595 | O13: 9617.77 | P13: =+IFERROR(O13/Summary!O$19,"") -> 0.0014218148 | Q13: =+M13-O13 -> 1560.48 | R13: 14220.66 | S13: =+IFERROR(R13/Summary!R$19,"") -> 0.0024248284 | T13: =+M13-R13 -> -3042.41
B14: Total Salaries & Wages - 700 | C14: Total Salaries and Wages | D14: =D11+D13 -> 23534.73 | E14: =+IFERROR(D14/Summary!D$19,"") -> 0.015598119 | F14: =F11+F13 -> 27094.01 | G14: =+IFERROR(F14/Summary!F$19,"") -> 0.017838467 | H14: =+D14-F14 -> -3559.28 | I14: =I11+I13 -> 28528.65 | J14: =+IFERROR(I14/Summary!I$19,"") -> 0.021622358 | K14: =+D14-I14 -> -4993.92 | M14: =M11+M13 -> 94009.32 | N14: =+IFERROR(M14/Summary!M$19,"") -> 0.014947631 | O14: =O11+O13 -> 105479.69 | P14: =+IFERROR(O14/Summary!O$19,"") -> 0.015593281 | Q14: =+M14-O14 -> -11470.37 | R14: =R11+R13 -> 106604.93 | S14: =+IFERROR(R14/Summary!R$19,"") -> 0.018177684 | T14: =+M14-R14 -> -12595.61
B15: Total Service Charge Distribution - 700 | C15: Service Charge Distribution | D15: 0 | E15: =+IFERROR(D15/Summary!D$19,"") -> 0 | F15: 0 | G15: =+IFERROR(F15/Summary!F$19,"") -> 0 | H15: =+D15-F15 -> 0 | I15: 0 | J15: =+IFERROR(I15/Summary!I$19,"") -> 0 | K15: =+D15-I15 -> 0 | M15: 0 | N15: =+IFERROR(M15/Summary!M$19,"") -> 0 | O15: 0 | P15: =+IFERROR(O15/Summary!O$19,"") -> 0 | Q15: =+M15-O15 -> 0 | R15: 0 | S15: =+IFERROR(R15/Summary!R$19,"") -> 0 | T15: =+M15-R15 -> 0
B16: Total Contracted Leased & Outsourced Labor - 700 | C16: Contracted & Leased Labor | D16: 3500 | E16: =+IFERROR(D16/Summary!D$19,"") -> 0.0023196958 | F16: 3500 | G16: =+IFERROR(F16/Summary!F$19,"") -> 0.0023043705 | H16: =+D16-F16 -> 0 | I16: 3500 | J16: =+IFERROR(I16/Summary!I$19,"") -> 0.0026527107 | K16: =+D16-I16 -> 0 | M16: 14000 | N16: =+IFERROR(M16/Summary!M$19,"") -> 0.0022260222 | O16: 14000 | P16: =+IFERROR(O16/Summary!O$19,"") -> 0.0020696489 | Q16: =+M16-O16 -> 0 | R16: 14000 | S16: =+IFERROR(R16/Summary!R$19,"") -> 0.0023872027 | T16: =+M16-R16 -> 0
B17: Total Bonuses & Incentives - 700 | C17: Bonuses & Incentives | D17: 3329.91 | E17: =+IFERROR(D17/Summary!D$19,"") -> 0.0022069653 | F17: 6203.73 | G17: =+IFERROR(F17/Summary!F$19,"") -> 0.0040844835 | H17: =+D17-F17 -> -2873.82 | I17: 3641.12 | J17: =+IFERROR(I17/Summary!I$19,"") -> 0.002759668 | K17: =+D17-I17 -> -311.21 | M17: 10835.23 | N17: =+IFERROR(M17/Summary!M$19,"") -> 0.0017228187 | O17: 24360.99 | P17: =+IFERROR(O17/Summary!O$19,"") -> 0.0036013355 | Q17: =+M17-O17 -> -13525.76 | R17: 11041.24 | S17: =+IFERROR(R17/Summary!R$19,"") -> 0.0018826913 | T17: =+M17-R17 -> -206.01
C18: Total Labor Expense | D18: =+D14+SUM(D15:D17) -> 30364.64 | E18: =+IFERROR(D18/Summary!D$19,"") -> 0.02012478 | F18: =+F14+SUM(F15:F17) -> 36797.74 | G18: =+IFERROR(F18/Summary!F$19,"") -> 0.024227321 | H18: =+D18-F18 -> -6433.1 | I18: =+I14+SUM(I15:I17) -> 35669.77 | J18: =+IFERROR(I18/Summary!I$19,"") -> 0.027034737 | K18: =+D18-I18 -> -5305.13 | M18: =+M14+SUM(M15:M17) -> 118844.55 | N18: =+IFERROR(M18/Summary!M$19,"") -> 0.018896472 | O18: =+O14+SUM(O15:O17) -> 143840.68 | P18: =+IFERROR(O18/Summary!O$19,"") -> 0.021264265 | Q18: =+M18-O18 -> -24996.13 | R18: =+R14+SUM(R15:R17) -> 131646.17 | S18: =+IFERROR(R18/Summary!R$19,"") -> 0.022447578 | T18: =+M18-R18 -> -12801.62
B19: Total Payroll Taxes - 700 | C19: Payroll Taxes | D19: 2021.04 | E19: =+IFERROR(D19/Summary!D$19,"") -> 0.0013394852 | F19: 2652.39 | G19: =+IFERROR(F19/Summary!F$19,"") -> 0.0017463112 | H19: =+D19-F19 -> -631.35 | I19: 2208.35 | J19: =+IFERROR(I19/Summary!I$19,"") -> 0.0016737468 | K19: =+D19-I19 -> -187.31 | M19: 7529.62 | N19: =+IFERROR(M19/Summary!M$19,"") -> 0.0011972215 | O19: 10444.66 | P19: =+IFERROR(O19/Summary!O$19,"") -> 0.0015440557 | Q19: =+M19-O19 -> -2915.04 | R19: 8872.6 | S19: =+IFERROR(R19/Summary!R$19,"") -> 0.0015129067 | T19: =+M19-R19 -> -1342.98
B20: Total Supplemental Pay - 700 | C20: Supplemental Pay | D20: 2213.4 | E20: =+IFERROR(D20/Summary!D$19,"") -> 0.0014669757 | F20: 2558.87 | G20: =+IFERROR(F20/Summary!F$19,"") -> 0.0016847384 | H20: =+D20-F20 -> -345.47 | I20: 2022.61 | J20: =+IFERROR(I20/Summary!I$19,"") -> 0.0015329712 | K20: =+D20-I20 -> 190.79 | M20: 9695.8 | N20: =+IFERROR(M20/Summary!M$19,"") -> 0.0015416476 | O20: 11568.84 | P20: =+IFERROR(O20/Summary!O$19,"") -> 0.0017102455 | Q20: =+M20-O20 -> -1873.04 | R20: 9658.29 | S20: =+IFERROR(R20/Summary!R$19,"") -> 0.0016468783 | T20: =+M20-R20 -> 37.51
B21: Total Employee Benefits - 700 | C21: Employee Benefits | D21: 4004.59 | E21: =+IFERROR(D21/Summary!D$19,"") -> 0.0026541231 | F21: 4849.19 | G21: =+IFERROR(F21/Summary!F$19,"") -> 0.0031926658 | H21: =+D21-F21 -> -844.6 | I21: 3502.44 | J21: =+IFERROR(I21/Summary!I$19,"") -> 0.00265456 | K21: =+D21-I21 -> 502.15 | M21: 12979.59 | N21: =+IFERROR(M21/Summary!M$19,"") -> 0.0020637754 | O21: 19330.61 | P21: =+IFERROR(O21/Summary!O$19,"") -> 0.002857684 | Q21: =+M21-O21 -> -6351.02 | R21: 19525.88 | S21: =+IFERROR(R21/Summary!R$19,"") -> 0.0033294452 | T21: =+M21-R21 -> -6546.29
B22: Total Payroll-Related Expenses - 700 | C22: Total Payroll Related | D22: =SUM(D19:D21) -> 8239.03 | E22: =+IFERROR(D22/Summary!D$19,"") -> 0.0054605839 | F22: =SUM(F19:F21) -> 10060.45 | G22: =+IFERROR(F22/Summary!F$19,"") -> 0.0066237154 | H22: =+D22-F22 -> -1821.42 | I22: =SUM(I19:I21) -> 7733.4 | J22: =+IFERROR(I22/Summary!I$19,"") -> 0.0058612779 | K22: =+D22-I22 -> 505.63 | M22: =SUM(M19:M21) -> 30205.01 | N22: =+IFERROR(M22/Summary!M$19,"") -> 0.0048026444 | O22: =SUM(O19:O21) -> 41344.11 | P22: =+IFERROR(O22/Summary!O$19,"") -> 0.0061119852 | Q22: =+M22-O22 -> -11139.1 | R22: =SUM(R19:R21) -> 38056.77 | S22: =+IFERROR(R22/Summary!R$19,"") -> 0.0064892302 | T22: =+M22-R22 -> -7851.76
B23: Total Labor Costs & Related Expenses - 700 | C23: Total Labor & Related Exp | D23: =+D18+D22 -> 38603.67 | E23: =+IFERROR(D23/Summary!D$19,"") -> 0.025585364 | F23: =+F18+F22 -> 46858.19 | G23: =+IFERROR(F23/Summary!F$19,"") -> 0.030851037 | H23: =+D23-F23 -> -8254.52 | I23: =+I18+I22 -> 43403.17 | J23: =+IFERROR(I23/Summary!I$19,"") -> 0.032896015 | K23: =+D23-I23 -> -4799.5 | M23: =+M18+M22 -> 149049.56 | N23: =+IFERROR(M23/Summary!M$19,"") -> 0.023699116 | O23: =+O18+O22 -> 185184.79 | P23: =+IFERROR(O23/Summary!O$19,"") -> 0.02737625 | Q23: =+M23-O23 -> -36135.23 | R23: =+R18+R22 -> 169702.94 | S23: =+IFERROR(R23/Summary!R$19,"") -> 0.028936808 | T23: =+M23-R23 -> -20653.38
C25: Other Expenses
B26: Cluster Services - 700 | C26: Cluster Services | D26: 0 | E26: =+IFERROR(D26/Summary!D$19,"") -> 0 | F26: 0 | G26: =+IFERROR(F26/Summary!F$19,"") -> 0 | H26: =+D26-F26 -> 0 | I26: 0 | J26: =+IFERROR(I26/Summary!I$19,"") -> 0 | K26: =+D26-I26 -> 0 | M26: 0 | N26: =+IFERROR(M26/Summary!M$19,"") -> 0 | O26: 0 | P26: =+IFERROR(O26/Summary!O$19,"") -> 0 | Q26: =+M26-O26 -> 0 | R26: 0 | S26: =+IFERROR(R26/Summary!R$19,"") -> 0 | T26: =+M26-R26 -> 0
B27: Decorations - 700 | C27: Decorations | D27: 0 | E27: =+IFERROR(D27/Summary!D$19,"") -> 0 | F27: 0 | G27: =+IFERROR(F27/Summary!F$19,"") -> 0 | H27: =+D27-F27 -> 0 | I27: 0 | J27: =+IFERROR(I27/Summary!I$19,"") -> 0 | K27: =+D27-I27 -> 0 | M27: 0 | N27: =+IFERROR(M27/Summary!M$19,"") -> 0 | O27: 0 | P27: =+IFERROR(O27/Summary!O$19,"") -> 0 | Q27: =+M27-O27 -> 0 | R27: 0 | S27: =+IFERROR(R27/Summary!R$19,"") -> 0 | T27: =+M27-R27 -> 0
B28: Dues & Subscriptions - 700 | C28: Dues and Subscriptions | D28: 3624.87 | E28: =+IFERROR(D28/Summary!D$19,"") -> 0.002402456 | F28: 2965 | G28: =+IFERROR(F28/Summary!F$19,"") -> 0.001952131 | H28: =+D28-F28 -> 659.87 | I28: 3429.21 | J28: =+IFERROR(I28/Summary!I$19,"") -> 0.0025990577 | K28: =+D28-I28 -> 195.66 | M28: 11513.4 | N28: =+IFERROR(M28/Summary!M$19,"") -> 0.0018306488 | O28: 11860 | P28: =+IFERROR(O28/Summary!O$19,"") -> 0.0017532883 | Q28: =+M28-O28 -> -346.6 | R28: 9681.9 | S28: =+IFERROR(R28/Summary!R$19,"") -> 0.0016509041 | T28: =+M28-R28 -> 1831.5
B29: Entertainment - In-House - 700 | C29: Entertainment In-House | D29: 0 | E29: =+IFERROR(D29/Summary!D$19,"") -> 0 | F29: 0 | G29: =+IFERROR(F29/Summary!F$19,"") -> 0 | H29: =+D29-F29 -> 0 | I29: 0 | J29: =+IFERROR(I29/Summary!I$19,"") -> 0 | K29: =+D29-I29 -> 0 | M29: 0 | N29: =+IFERROR(M29/Summary!M$19,"") -> 0 | O29: 0 | P29: =+IFERROR(O29/Summary!O$19,"") -> 0 | Q29: =+M29-O29 -> 0 | R29: 0 | S29: =+IFERROR(R29/Summary!R$19,"") -> 0 | T29: =+M29-R29 -> 0
B30: Equipment Rental - 700 | C30: Equipment Rental | D30: 562.5 | E30: =+IFERROR(D30/Summary!D$19,"") -> 0.00037280826 | F30: 0 | G30: =+IFERROR(F30/Summary!F$19,"") -> 0 | H30: =+D30-F30 -> 562.5 | I30: 0 | J30: =+IFERROR(I30/Summary!I$19,"") -> 0 | K30: =+D30-I30 -> 562.5 | M30: 3056 | N30: =+IFERROR(M30/Summary!M$19,"") -> 0.00048590884 | O30: 0 | P30: =+IFERROR(O30/Summary!O$19,"") -> 0 | Q30: =+M30-O30 -> 3056 | R30: 0 | S30: =+IFERROR(R30/Summary!R$19,"") -> 0 | T30: =+M30-R30 -> 3056
B31: Familiarization Trips - 700 | C31: Familiarization Trips | D31: 0 | E31: =+IFERROR(D31/Summary!D$19,"") -> 0 | F31: 0 | G31: =+IFERROR(F31/Summary!F$19,"") -> 0 | H31: =+D31-F31 -> 0 | I31: 0 | J31: =+IFERROR(I31/Summary!I$19,"") -> 0 | K31: =+D31-I31 -> 0 | M31: 0 | N31: =+IFERROR(M31/Summary!M$19,"") -> 0 | O31: 0 | P31: =+IFERROR(O31/Summary!O$19,"") -> 0 | Q31: =+M31-O31 -> 0 | R31: 0 | S31: =+IFERROR(R31/Summary!R$19,"") -> 0 | T31: =+M31-R31 -> 0
B32: Postage & Overnight Delivery - 700 | C32: Postage and Overnight Delivery | D32: 0 | E32: =+IFERROR(D32/Summary!D$19,"") -> 0 | F32: 0 | G32: =+IFERROR(F32/Summary!F$19,"") -> 0 | H32: =+D32-F32 -> 0 | I32: 0 | J32: =+IFERROR(I32/Summary!I$19,"") -> 0 | K32: =+D32-I32 -> 0 | M32: 0 | N32: =+IFERROR(M32/Summary!M$19,"") -> 0 | O32: 12 | P32: =+IFERROR(O32/Summary!O$19,"") -> 1.7739848e-06 | Q32: =+M32-O32 -> -12 | R32: 0 | S32: =+IFERROR(R32/Summary!R$19,"") -> 0 | T32: =+M32-R32 -> 0
B33: Printing & Stationary - 700 | C33: Printing & Stationery | D33: 0 | E33: =+IFERROR(D33/Summary!D$19,"") -> 0 | F33: 0 | G33: =+IFERROR(F33/Summary!F$19,"") -> 0 | H33: =+D33-F33 -> 0 | I33: 0 | J33: =+IFERROR(I33/Summary!I$19,"") -> 0 | K33: =+D33-I33 -> 0 | M33: 0 | N33: =+IFERROR(M33/Summary!M$19,"") -> 0 | O33: 0 | P33: =+IFERROR(O33/Summary!O$19,"") -> 0 | Q33: =+M33-O33 -> 0 | R33: 0 | S33: =+IFERROR(R33/Summary!R$19,"") -> 0 | T33: =+M33-R33 -> 0
B34: Operating Supplies - 700 | C34: Operating Supplies | D34: 59.9 | E34: =+IFERROR(D34/Summary!D$19,"") -> 3.9699937e-05 | F34: 0 | G34: =+IFERROR(F34/Summary!F$19,"") -> 0 | H34: =+D34-F34 -> 59.9 | I34: 0 | J34: =+IFERROR(I34/Summary!I$19,"") -> 0 | K34: =+D34-I34 -> 59.9 | M34: 104.82 | N34: =+IFERROR(M34/Summary!M$19,"") -> 1.6666546e-05 | O34: 66 | P34: =+IFERROR(O34/Summary!O$19,"") -> 9.7569164e-06 | Q34: =+M34-O34 -> 38.82 | R34: -33.41 | S34: =+IFERROR(R34/Summary!R$19,"") -> -5.6968887e-06 | T34: =+M34-R34 -> 138.23
B35: Contract Services - 700 | C35: Contract Services | D35: 429.14 | E35: =+IFERROR(D35/Summary!D$19,"") -> 0.00028442122 | F35: 519 | G35: =+IFERROR(F35/Summary!F$19,"") -> 0.00034170522 | H35: =+D35-F35 -> -89.86 | I35: 429 | J35: =+IFERROR(I35/Summary!I$19,"") -> 0.00032514654 | K35: =+D35-I35 -> 0.14 | M35: 1127.83 | N35: =+IFERROR(M35/Summary!M$19,"") -> 0.00017932676 | O35: 2676 | P35: =+IFERROR(O35/Summary!O$19,"") -> 0.00039559861 | Q35: =+M35-O35 -> -1548.17 | R35: 2362.48 | S35: =+IFERROR(R35/Summary!R$19,"") -> 0.00040283704 | T35: =+M35-R35 -> -1234.65
B36: Travel - Other - 700 | C36: Travel - Other | D36: 161.64 | E36: =+IFERROR(D36/Summary!D$19,"") -> 0.00010713018 | F36: 0 | G36: =+IFERROR(F36/Summary!F$19,"") -> 0 | H36: =+D36-F36 -> 161.64 | I36: 211.94 | J36: =+IFERROR(I36/Summary!I$19,"") -> 0.000160633 | K36: =+D36-I36 -> -50.3 | M36: 291.43 | N36: =+IFERROR(M36/Summary!M$19,"") -> 4.6337832e-05 | O36: 1050 | P36: =+IFERROR(O36/Summary!O$19,"") -> 0.00015522367 | Q36: =+M36-O36 -> -758.57 | R36: 365.75 | S36: =+IFERROR(R36/Summary!R$19,"") -> 6.236567e-05 | T36: =+M36-R36 -> -74.32
B37: Travel - Meals & Entertainment - 700 | C37: Travel - Meals & Entertainment | D37: 294.4 | E37: =+IFERROR(D37/Summary!D$19,"") -> 0.00019511956 | F37: 200 | G37: =+IFERROR(F37/Summary!F$19,"") -> 0.00013167831 | H37: =+D37-F37 -> 94.4 | I37: 242.5 | J37: =+IFERROR(I37/Summary!I$19,"") -> 0.00018379495 | K37: =+D37-I37 -> 51.9 | M37: 602.76 | N37: =+IFERROR(M37/Summary!M$19,"") -> 9.5839795e-05 | O37: 1100 | P37: =+IFERROR(O37/Summary!O$19,"") -> 0.00016261527 | Q37: =+M37-O37 -> -497.24 | R37: 428.62 | S37: =+IFERROR(R37/Summary!R$19,"") -> 7.3085915e-05 | T37: =+M37-R37 -> 174.14
... B56: Agency Fees - 700 | C56: Agency Fees | D56: 0 | E56: =+IFERROR(D56/Summary!D$19,"") -> 0 | F56: 0 | G56: =+IFERROR(F56/Summary!F$19,"") -> 0 | H56: =+D56-F56 -> 0 | I56: 0 | J56: =+IFERROR(I56/Summary!I$19,"") -> 0 | K56: =+D56-I56 -> 0 | M56: 0 | N56: =+IFERROR(M56/Summary!M$19,"") -> 0 | O56: 0 | P56: =+IFERROR(O56/Summary!O$19,"") -> 0 | Q56: =+M56-O56 -> 0 | R56: 0 | S56: =+IFERROR(R56/Summary!R$19,"") -> 0 | T56: =+M56-R56 -> 0
B57: Total Other Expenses - 700 | C57: Total Operations Expense | D57: =SUM(D26:D56) -> 49790.29 | E57: =+IFERROR(D57/Summary!D$19,"") -> 0.032999522 | F57: =SUM(F26:F56) -> 57901.46 | G57: =+IFERROR(F57/Summary!F$19,"") -> 0.038121832 | H57: =+D57-F57 -> -8111.17 | I57: =SUM(I26:I56) -> 72324.55 | J57: =+IFERROR(I57/Summary!I$19,"") -> 0.05481603 | K57: =+D57-I57 -> -22534.26 | M57: =SUM(M26:M56) -> 232931.33 | N57: =+IFERROR(M57/Summary!M$19,"") -> 0.03703645 | O57: =SUM(O26:O56) -> 285755.85 | P57: =+IFERROR(O57/Summary!O$19,"") -> 0.042243878 | Q57: =+M57-O57 -> -52824.52 | R57: =SUM(R26:R56) -> 247687.82 | S57: =+IFERROR(R57/Summary!R$19,"") -> 0.042234359 | T57: =+M57-R57 -> -14756.49
B59: Total Departmental Expenses - 700 | C59: Total Expenses | D59: =+D23+D57 -> 88393.96 | E59: =+IFERROR(D59/Summary!D$19,"") -> 0.058584886 | F59: =+F23+F57 -> 104759.65 | G59: =+IFERROR(F59/Summary!F$19,"") -> 0.068972869 | H59: =+D59-F59 -> -16365.69 | I59: =+I23+I57 -> 115727.72 | J59: =+IFERROR(I59/Summary!I$19,"") -> 0.087712045 | K59: =+D59-I59 -> -27333.76 | M59: =+M23+M57 -> 381980.89 | N59: =+IFERROR(M59/Summary!M$19,"") -> 0.060735566 | O59: =+O23+O57 -> 470940.64 | P59: =+IFERROR(O59/Summary!O$19,"") -> 0.069620128 | Q59: =+M59-O59 -> -88959.75 | R59: =+R23+R57 -> 417390.76 | S59: =+IFERROR(R59/Summary!R$19,"") -> 0.071171167 | T59: =+M59-R59 -> -35409.87
C60: Department Profit (Loss) | D60: =0-D59 -> -88393.96 | E60: =+IFERROR(D60/Summary!D$19,"") -> -0.058584886 | F60: =0-F59 -> -104759.65 | G60: =+IFERROR(F60/Summary!F$19,"") -> -0.068972869 | H60: =+D60-F60 -> 16365.69 | I60: =0-I59 -> -115727.72 | J60: =+IFERROR(I60/Summary!I$19,"") -> -0.087712045 | K60: =+D60-I60 -> 27333.76 | M60: =0-M59 -> -381980.89 | N60: =+IFERROR(M60/Summary!M$19,"") -> -0.060735566 | O60: =0-O59 -> -470940.64 | P60: =+IFERROR(O60/Summary!O$19,"") -> -0.069620128 | Q60: =+M60-O60 -> 88959.75 | R60: =0-R59 -> -417390.76 | S60: =+IFERROR(R60/Summary!R$19,"") -> -0.071171167 | T60: =+M60-R60 -> 35409.87

Sheet POM
V1: ANG
C2: =+Summary!$C$2 -> Angler's | V2: Apr
C3: =+Summary!$C$3 -> STATEMENT OF INCOME
C4: =+Summary!$C$4 -> FOR THE PERIOD ENDING APR 2025
D6: =Year&" "&UPPER(Month)&" - PERIODIC" -> 2025 APR - PERIODIC | M6: =Year&" "&UPPER(Month)&" - YEAR TO DATE" -> 2025 APR - YEAR TO DATE
D7: Actual | F7: Budget | H7: VARIANCE | I7: Actual - Last Year | K7: VARIANCE | M7: Actual | O7: Budget | Q7: VARIANCE | R7: Actual - Last Year | T7: VARIANCE
D8: $ | E8: % | F8: $ | G8: % | H8: $ | I8: Actual | J8: % | K8: $ | M8: $ | N8: % | O8: $ | P8: % | Q8: $ | R8: Actual | S8: % | T8: $
C9: Labor & Related Expenses
C10: Salaries & Wages
B11: S&W Management Reg - 800 | C11: Management | D11: 7466.01 | E11: =+IFERROR(D11/Summary!D$19,"") -> 0.0049482492 | F11: 5812.72 | G11: =+IFERROR(F11/Summary!F$19,"") -> 0.0038270458 | H11: =+D11-F11 -> 1653.29 | I11: 7367.73 | J11: =+IFERROR(I11/Summary!I$19,"") -> 0.0055841303 | K11: =+D11-I11 -> 98.28 | M11: 21841.34 | N11: =+IFERROR(M11/Summary!M$19,"") -> 0.0034728077 | O11: 22385.5 | P11: =+IFERROR(O11/Summary!O$19,"") -> 0.0033092947 | Q11: =+M11-O11 -> -544.16 | R11: 32002.69 | S11: =+IFERROR(R11/Summary!R$19,"") -> 0.0054569219 | T11: =+M11-R11 -> -10161.35
C12: Non-Management
B13: S&W Non-Management - 800 | C13: Non-Mgmt. (PO & M) | D13: 17840.4 | E13: =+IFERROR(D13/Summary!D$19,"") -> 0.011824086 | F13: 17366.18 | G13: =+IFERROR(F13/Summary!F$19,"") -> 0.011433746 | H13: =+D13-F13 -> 474.22 | I13: 18995.93 | J13: =+IFERROR(I13/Summary!I$19,"") -> 0.014397345 | K13: =+D13-I13 -> -1155.53 | M13: 64673.49 | N13: =+IFERROR(M13/Summary!M$19,"") -> 0.010283187 | O13: 68902.74 | P13: =+IFERROR(O13/Summary!O$19,"") -> 0.010186034 | Q13: =+M13-O13 -> -4229.25 | R13: 74969.95 | S13: =+IFERROR(R13/Summary!R$19,"") -> 0.012783462 | T13: =+M13-R13 -> -10296.46
B14: S&W Other - 800 | C14: Other S&W | D14: 0 | E14: =+IFERROR(D14/Summary!D$19,"") -> 0 | F14: 0 | G14: =+IFERROR(F14/Summary!F$19,"") -> 0 | H14: =+D14-F14 -> 0 | I14: 0 | J14: =+IFERROR(I14/Summary!I$19,"") -> 0 | K14: =+D14-I14 -> 0 | M14: 0 | N14: =+IFERROR(M14/Summary!M$19,"") -> 0 | O14: 0 | P14: =+IFERROR(O14/Summary!O$19,"") -> 0 | Q14: =+M14-O14 -> 0 | R14: 0 | S14: =+IFERROR(R14/Summary!R$19,"") -> 0 | T14: =+M14-R14 -> 0
B15: Total Salaries & Wages - 800 | C15: Total Salaries and Wages | D15: =SUM(D11,D13:D14) -> 25306.41 | E15: =+IFERROR(D15/Summary!D$19,"") -> 0.016772335 | F15: =SUM(F11,F13:F14) -> 23178.9 | G15: =+IFERROR(F15/Summary!F$19,"") -> 0.015260792 | H15: =+D15-F15 -> 2127.51 | I15: =SUM(I11,I13:I14) -> 26363.66 | J15: =+IFERROR(I15/Summary!I$19,"") -> 0.019981475 | K15: =+D15-I15 -> -1057.25 | M15: =SUM(M11,M13:M14) -> 86514.83 | N15: =+IFERROR(M15/Summary!M$19,"") -> 0.013755995 | O15: =SUM(O11,O13:O14) -> 91288.24 | P15: =+IFERROR(O15/Summary!O$19,"") -> 0.013495329 | Q15: =+M15-O15 -> -4773.41 | R15: =SUM(R11,R13:R14) -> 106972.64 | S15: =+IFERROR(R15/Summary!R$19,"") -> 0.018240384 | T15: =+M15-R15 -> -20457.81
B16: Total Contracted Leased & Outsourced Labor - 800 | C16: Contracted & Leased Labor | D16: 0 | E16: =+IFERROR(D16/Summary!D$19,"") -> 0 | F16: 0 | G16: =+IFERROR(F16/Summary!F$19,"") -> 0 | H16: =+D16-F16 -> 0 | I16: 0 | J16: =+IFERROR(I16/Summary!I$19,"") -> 0 | K16: =+D16-I16 -> 0 | M16: 4128 | N16: =+IFERROR(M16/Summary!M$19,"") -> 0.00065635854 | O16: 0 | P16: =+IFERROR(O16/Summary!O$19,"") -> 0 | Q16: =+M16-O16 -> 4128 | R16: 0 | S16: =+IFERROR(R16/Summary!R$19,"") -> 0 | T16: =+M16-R16 -> 4128
B17: Total Bonuses & Incentives - 800 | C17: Bonuses & Incentives | D17: 73.6 | E17: =+IFERROR(D17/Summary!D$19,"") -> 4.877989e-05 | F17: 581.27 | G17: =+IFERROR(F17/Summary!F$19,"") -> 0.00038270326 | H17: =+D17-F17 -> -507.67 | I17: -2362.5 | J17: =+IFERROR(I17/Summary!I$19,"") -> -0.0017905797 | K17: =+D17-I17 -> 2436.1 | M17: 623.54 | N17: =+IFERROR(M17/Summary!M$19,"") -> 9.9143848e-05 | O17: 2325.08 | P17: =+IFERROR(O17/Summary!O$19,"") -> 0.00034372138 | Q17: =+M17-O17 -> -1701.54 | R17: -2000 | S17: =+IFERROR(R17/Summary!R$19,"") -> -0.00034102895 | T17: =+M17-R17 -> 2623.54
C18: Total Labor Expense | D18: =+D15+SUM(D16:D17) -> 25380.01 | E18: =+IFERROR(D18/Summary!D$19,"") -> 0.016821115 | F18: =+F15+SUM(F16:F17) -> 23760.17 | G18: =+IFERROR(F18/Summary!F$19,"") -> 0.015643495 | H18: =+D18-F18 -> 1619.84 | I18: =+I15+SUM(I16:I17) -> 24001.16 | J18: =+IFERROR(I18/Summary!I$19,"") -> 0.018190895 | K18: =+D18-I18 -> 1378.85 | M18: =+M15+SUM(M16:M17) -> 91266.37 | N18: =+IFERROR(M18/Summary!M$19,"") -> 0.014511497 | O18: =+O15+SUM(O16:O17) -> 93613.32 | P18: =+IFERROR(O18/Summary!O$19,"") -> 0.013839051 | Q18: =+M18-O18 -> -2346.95 | R18: =+R15+SUM(R16:R17) -> 104972.64 | S18: =+IFERROR(R18/Summary!R$19,"") -> 0.017899355 | T18: =+M18-R18 -> -13706.27
B19: Total Payroll Taxes - 800 | C19: Payroll Taxes | D19: 1857.77 | E19: =+IFERROR(D19/Summary!D$19,"") -> 0.0012312747 | F19: 2356.74 | G19: =+IFERROR(F19/Summary!F$19,"") -> 0.0015516577 | H19: =+D19-F19 -> -498.97 | I19: 2404.15 | J19: =+IFERROR(I19/Summary!I$19,"") -> 0.001822147 | K19: =+D19-I19 -> -546.38 | M19: 7174.15 | N19: =+IFERROR(M19/Summary!M$19,"") -> 0.0011407012 | O19: 9468.45 | P19: =+IFERROR(O19/Summary!O$19,"") -> 0.0013997405 | Q19: =+M19-O19 -> -2294.3 | R19: 9101.3 | S19: =+IFERROR(R19/Summary!R$19,"") -> 0.0015519034 | T19: =+M19-R19 -> -1927.15
B20: Supplemental Pay - 800 | C20: Supplemental Pay | D20: 3221.14 | E20: =+IFERROR(D20/Summary!D$19,"") -> 0.0021348757 | F20: 2425.76 | G20: =+IFERROR(F20/Summary!F$19,"") -> 0.0015970999 | H20: =+D20-F20 -> 795.38 | I20: 1009.18 | J20: =+IFERROR(I20/Summary!I$19,"") -> 0.00076487502 | K20: =+D20-I20 -> 2211.96 | M20: 12131.29 | N20: =+IFERROR(M20/Summary!M$19,"") -> 0.0019288943 | O20: 11591.59 | P20: =+IFERROR(O20/Summary!O$19,"") -> 0.0017136087 | Q20: =+M20-O20 -> 539.7 | R20: 7831.73 | S20: =+IFERROR(R20/Summary!R$19,"") -> 0.0013354233 | T20: =+M20-R20 -> 4299.56
B21: Total Employee Benefits - 800 | C21: Employee Benefits | D21: 5441.09 | E21: =+IFERROR(D21/Summary!D$19,"") -> 0.0036061925 | F21: 5541.71 | G21: =+IFERROR(F21/Summary!F$19,"") -> 0.0036486151 | H21: =+D21-F21 -> -100.62 | I21: 7273.01 | J21: =+IFERROR(I21/Summary!I$19,"") -> 0.0055123404 | K21: =+D21-I21 -> -1831.92 | M21: 18976.24 | N21: =+IFERROR(M21/Summary!M$19,"") -> 0.0030172522 | O21: 22077.3 | P21: =+IFERROR(O21/Summary!O$19,"") -> 0.0032637329 | Q21: =+M21-O21 -> -3101.06 | R21: 26285.42 | S21: =+IFERROR(R21/Summary!R$19,"") -> 0.0044820446 | T21: =+M21-R21 -> -7309.18
B22: Total Payroll-Related Expenses - 800 | C22: Total Payroll Related | D22: =+SUM(D19:D21) -> 10520 | E22: =+IFERROR(D22/Summary!D$19,"") -> 0.0069723429 | F22: =+SUM(F19:F21) -> 10324.21 | G22: =+IFERROR(F22/Summary!F$19,"") -> 0.0067973727 | H22: =+D22-F22 -> 195.79 | I22: =+SUM(I19:I21) -> 10686.34 | J22: =+IFERROR(I22/Summary!I$19,"") -> 0.0080993624 | K22: =+D22-I22 -> -166.34 | M22: =+SUM(M19:M21) -> 38281.68 | N22: =+IFERROR(M22/Summary!M$19,"") -> 0.0060868477 | O22: =+SUM(O19:O21) -> 43137.34 | P22: =+IFERROR(O22/Summary!O$19,"") -> 0.0063770821 | Q22: =+M22-O22 -> -4855.66 | R22: =+SUM(R19:R21) -> 43218.45 | S22: =+IFERROR(R22/Summary!R$19,"") -> 0.0073693714 | T22: =+M22-R22 -> -4936.77
B23: Total Labor Costs & Related Expenses - 800 | C23: Total Labor & Related Exp | D23: =+D22+D18 -> 35900.01 | E23: =+IFERROR(D23/Summary!D$19,"") -> 0.023793458 | F23: =+F22+F18 -> 34084.38 | G23: =+IFERROR(F23/Summary!F$19,"") -> 0.022440868 | H23: =+D23-F23 -> 1815.63 | I23: =+I22+I18 -> 34687.5 | J23: =+IFERROR(I23/Summary!I$19,"") -> 0.026290258 | K23: =+D23-I23 -> 1212.51 | M23: =+M22+M18 -> 129548.05 | N23: =+IFERROR(M23/Summary!M$19,"") -> 0.020598345 | O23: =+O22+O18 -> 136750.66 | P23: =+IFERROR(O23/Summary!O$19,"") -> 0.020216133 | Q23: =+M23-O23 -> -7202.61 | R23: =+R22+R18 -> 148191.09 | S23: =+IFERROR(R23/Summary!R$19,"") -> 0.025268726 | T23: =+M23-R23 -> -18643.04
C25: Other Expenses
B26: Operating Supplies - 800 | C26: Operating Supplies | D26: 0 | E26: =+IFERROR(D26/Summary!D$19,"") -> 0 | F26: 100 | G26: =+IFERROR(F26/Summary!F$19,"") -> 6.5839156e-05 | H26: =+D26-F26 -> -100 | I26: 239.02 | J26: =+IFERROR(I26/Summary!I$19,"") -> 0.0001811574 | K26: =+D26-I26 -> -239.02 | M26: 51.13 | N26: =+IFERROR(M26/Summary!M$19,"") -> 8.129751e-06 | O26: 614 | P26: =+IFERROR(O26/Summary!O$19,"") -> 9.0768889e-05 | Q26: =+M26-O26 -> -562.87 | R26: 1407.02 | S26: =+IFERROR(R26/Summary!R$19,"") -> 0.00023991728 | T26: =+M26-R26 -> -1355.89
B27: Contract Services - 800 | C27: Contract Services | D27: 5461.78 | E27: =+IFERROR(D27/Summary!D$19,"") -> 0.0036199052 | F27: 4052.3999 | G27: =+IFERROR(F27/Summary!F$19,"") -> 0.0026680659 | H27: =+D27-F27 -> 1409.3801 | I27: 3286.04 | J27: =+IFERROR(I27/Summary!I$19,"") -> 0.0024905467 | K27: =+D27-I27 -> 2175.74 | M27: 21822.26 | N27: =+IFERROR(M27/Summary!M$19,"") -> 0.0034697739 | O27: 16462.674 | P27: =+IFERROR(O27/Summary!O$19,"") -> 0.0024337111 | Q27: =+M27-O27 -> 5359.5861 | R27: 13191.41 | S27: =+IFERROR(R27/Summary!R$19,"") -> 0.0022493264 | T27: =+M27-R27 -> 8630.85
B28: Cleaning Supplies - 800 | C28: Cleaning Supplies | D28: 0 | E28: =+IFERROR(D28/Summary!D$19,"") -> 0 | F28: 0 | G28: =+IFERROR(F28/Summary!F$19,"") -> 0 | H28: =+D28-F28 -> 0 | I28: 0 | J28: =+IFERROR(I28/Summary!I$19,"") -> 0 | K28: =+D28-I28 -> 0 | M28: 0 | N28: =+IFERROR(M28/Summary!M$19,"") -> 0 | O28: 0 | P28: =+IFERROR(O28/Summary!O$19,"") -> 0 | Q28: =+M28-O28 -> 0 | R28: 0 | S28: =+IFERROR(R28/Summary!R$19,"") -> 0 | T28: =+M28-R28 -> 0
B29: Dues & Subscriptions - 800 | C29: Dues & Subscriptions | D29: 0 | E29: =+IFERROR(D29/Summary!D$19,"") -> 0 | F29: 0 | G29: =+IFERROR(F29/Summary!F$19,"") -> 0 | H29: =+D29-F29 -> 0 | I29: 0 | J29: =+IFERROR(I29/Summary!I$19,"") -> 0 | K29: =+D29-I29 -> 0 | M29: 0 | N29: =+IFERROR(M29/Summary!M$19,"") -> 0 | O29: 0 | P29: =+IFERROR(O29/Summary!O$19,"") -> 0 | Q29: =+M29-O29 -> 0 | R29: 0 | S29: =+IFERROR(R29/Summary!R$19,"") -> 0 | T29: =+M29-R29 -> 0
B30: Travel - Other - 800 | C30: Travel - Other | D30: 0 | E30: =+IFERROR(D30/Summary!D$19,"") -> 0 | F30: 39.58 | G30: =+IFERROR(F30/Summary!F$19,"") -> 2.6059138e-05 | H30: =+D30-F30 -> -39.58 | I30: 0 | J30: =+IFERROR(I30/Summary!I$19,"") -> 0 | K30: =+D30-I30 -> 0 | M30: 120.78 | N30: =+IFERROR(M30/Summary!M$19,"") -> 1.9204211e-05 | O30: 258.32 | P30: =+IFERROR(O30/Summary!O$19,"") -> 3.8187979e-05 | Q30: =+M30-O30 -> -137.54 | R30: 221.1 | S30: =+IFERROR(R30/Summary!R$19,"") -> 3.7700751e-05 | T30: =+M30-R30 -> -100.32
B31: Travel - Meals & Entertainment - 800 | C31: Travel - Meals & Entertainment | D31: 0 | E31: =+IFERROR(D31/Summary!D$19,"") -> 0 | F31: 0 | G31: =+IFERROR(F31/Summary!F$19,"") -> 0 | H31: =+D31-F31 -> 0 | I31: 0 | J31: =+IFERROR(I31/Summary!I$19,"") -> 0 | K31: =+D31-I31 -> 0 | M31: 0 | N31: =+IFERROR(M31/Summary!M$19,"") -> 0 | O31: 0 | P31: =+IFERROR(O31/Summary!O$19,"") -> 0 | Q31: =+M31-O31 -> 0 | R31: 0 | S31: =+IFERROR(R31/Summary!R$19,"") -> 0 | T31: =+M31-R31 -> 0
B32: Training - 800 | C32: Training | D32: 0 | E32: =+IFERROR(D32/Summary!D$19,"") -> 0 | F32: 0 | G32: =+IFERROR(F32/Summary!F$19,"") -> 0 | H32: =+D32-F32 -> 0 | I32: 0 | J32: =+IFERROR(I32/Summary!I$19,"") -> 0 | K32: =+D32-I32 -> 0 | M32: 0 | N32: =+IFERROR(M32/Summary!M$19,"") -> 0 | O32: 0 | P32: =+IFERROR(O32/Summary!O$19,"") -> 0 | Q32: =+M32-O32 -> 0 | R32: 0 | S32: =+IFERROR(R32/Summary!R$19,"") -> 0 | T32: =+M32-R32 -> 0
B33: Uniform Costs - 800 | C33: Uniform Costs | D33: 0 | E33: =+IFERROR(D33/Summary!D$19,"") -> 0 | F33: 0 | G33: =+IFERROR(F33/Summary!F$19,"") -> 0 | H33: =+D33-F33 -> 0 | I33: 304.34 | J33: =+IFERROR(I33/Summary!I$19,"") -> 0.00023066456 | K33: =+D33-I33 -> -304.34 | M33: 308.99 | N33: =+IFERROR(M33/Summary!M$19,"") -> 4.9129899e-05 | O33: 225 | P33: =+IFERROR(O33/Summary!O$19,"") -> 3.3262215e-05 | Q33: =+M33-O33 -> 83.99 | R33: 530.28 | S33: =+IFERROR(R33/Summary!R$19,"") -> 9.0420417e-05 | T33: =+M33-R33 -> -221.29
B34: Uniform Laundry - 800 | C34: Uniforms Laundry | D34: 302.99 | E34: =+IFERROR(D34/Summary!D$19,"") -> 0.00020081276 | F34: 320.75 | G34: =+IFERROR(F34/Summary!F$19,"") -> 0.00021117909 | H34: =+D34-F34 -> -17.76 | I34: 472.73 | J34: =+IFERROR(I34/Summary!I$19,"") -> 0.00035829026 | K34: =+D34-I34 -> -169.74 | M34: 1190.44 | N34: =+IFERROR(M34/Summary!M$19,"") -> 0.00018928185 | O34: 1283 | P34: =+IFERROR(O34/Summary!O$19,"") -> 0.00018966854 | Q34: =+M34-O34 -> -92.56 | R34: 1328.57 | S34: =+IFERROR(R34/Summary!R$19,"") -> 0.00022654042 | T34: =+M34-R34 -> -138.13
B35: Equipment Rental - 800 | C35: Equipment Rental | D35: 0 | E35: =+IFERROR(D35/Summary!D$19,"") -> 0 | F35: 0 | G35: =+IFERROR(F35/Summary!F$19,"") -> 0 | H35: =+D35-F35 -> 0 | I35: 0 | J35: =+IFERROR(I35/Summary!I$19,"") -> 0 | K35: =+D35-I35 -> 0 | M35: 0 | N35: =+IFERROR(M35/Summary!M$19,"") -> 0 | O35: 0 | P35: =+IFERROR(O35/Summary!O$19,"") -> 0 | Q35: =+M35-O35 -> 0 | R35: 0 | S35: =+IFERROR(R35/Summary!R$19,"") -> 0 | T35: =+M35-R35 -> 0
B36: Floor Covering - 800 | C36: Floor Covering | D36: 0 | E36: =+IFERROR(D36/Summary!D$19,"") -> 0 | F36: 0 | G36: =+IFERROR(F36/Summary!F$19,"") -> 0 | H36: =+D36-F36 -> 0 | I36: 0 | J36: =+IFERROR(I36/Summary!I$19,"") -> 0 | K36: =+D36-I36 -> 0 | M36: 0 | N36: =+IFERROR(M36/Summary!M$19,"") -> 0 | O36: 0 | P36: =+IFERROR(O36/Summary!O$19,"") -> 0 | Q36: =+M36-O36 -> 0 | R36: 0 | S36: =+IFERROR(R36/Summary!R$19,"") -> 0 | T36: =+M36-R36 -> 0
B37: Licenses & Permits - 800 | C37: Licenses & Permits | D37: 0 | E37: =+IFERROR(D37/Summary!D$19,"") -> 0 | F37: 0 | G37: =+IFERROR(F37/Summary!F$19,"") -> 0 | H37: =+D37-F37 -> 0 | I37: -5300 | J37: =+IFERROR(I37/Summary!I$19,"") -> -0.0040169619 | K37: =+D37-I37 -> 5300 | M37: -3110 | N37: =+IFERROR(M37/Summary!M$19,"") -> -0.00049449493 | O37: 0 | P37: =+IFERROR(O37/Summary!O$19,"") -> 0 | Q37: =+M37-O37 -> -3110 | R37: -5300 | S37: =+IFERROR(R37/Summary!R$19,"") -> -0.00090372673 | T37: =+M37-R37 -> 2190
... B55: Waste Removal - 800 | C55: Waste Removal | D55: 4209.8 | E55: =+IFERROR(D55/Summary!D$19,"") -> 0.0027901302 | F55: 3560 | G55: =+IFERROR(F55/Summary!F$19,"") -> 0.0023438739 | H55: =+D55-F55 -> 649.8 | I55: 3670.45 | J55: =+IFERROR(I55/Summary!I$19,"") -> 0.0027818977 | K55: =+D55-I55 -> 539.35 | M55: 20374.24 | N55: =+IFERROR(M55/Summary!M$19,"") -> 0.0032395364 | O55: 14240 | P55: =+IFERROR(O55/Summary!O$19,"") -> 0.0021051286 | Q55: =+M55-O55 -> 6134.24 | R55: 14534.89 | S55: =+IFERROR(R55/Summary!R$19,"") -> 0.0024784092 | T55: =+M55-R55 -> 5839.35
B56: Total Other Expenses - 800 | C56: Total Operations Expense | D56: =SUM(D26:D55) -> 22219.27 | E56: =+IFERROR(D56/Summary!D$19,"") -> 0.014726271 | F56: =SUM(F26:F55) -> 31249.49 | G56: =+IFERROR(F56/Summary!F$19,"") -> 0.0205744 | H56: =+D56-F56 -> -9030.2199 | I56: =SUM(I26:I55) -> 5549.15 | J56: =+IFERROR(I56/Summary!I$19,"") -> 0.004205797 | K56: =+D56-I56 -> 16670.12 | M56: =SUM(M26:M55) -> 94277.01 | N56: =+IFERROR(M56/Summary!M$19,"") -> 0.014990194 | O56: =SUM(O26:O55) -> 130608.28 | P56: =+IFERROR(O56/Summary!O$19,"") -> 0.019308092 | Q56: =+M56-O56 -> -36331.274 | R56: =SUM(R26:R55) -> 83762.71 | S56: =+IFERROR(R56/Summary!R$19,"") -> 0.014282755 | T56: =+M56-R56 -> 10514.3
B58: Total Departmental Expenses - 800 | C58: Total Expenses | D58: =D23+D56 -> 58119.28 | E58: =+IFERROR(D58/Summary!D$19,"") -> 0.038519729 | F58: =F23+F56 -> 65333.87 | G58: =+IFERROR(F58/Summary!F$19,"") -> 0.043015268 | H58: =+D58-F58 -> -7214.5899 | I58: =I23+I56 -> 40236.65 | J58: =+IFERROR(I58/Summary!I$19,"") -> 0.030496055 | K58: =+D58-I58 -> 17882.63 | M58: =M23+M56 -> 223825.06 | N58: =+IFERROR(M58/Summary!M$19,"") -> 0.035588539 | O58: =O23+O56 -> 267358.94 | P58: =+IFERROR(O58/Summary!O$19,"") -> 0.039524225 | Q58: =+M58-O58 -> -43533.884 | R58: =R23+R56 -> 231953.8 | S58: =+IFERROR(R58/Summary!R$19,"") -> 0.039551481 | T58: =+M58-R58 -> -8128.74
C59: Department Profit (Loss) | D59: =0-D58 -> -58119.28 | E59: =+IFERROR(D59/Summary!D$19,"") -> -0.038519729 | F59: =0-F58 -> -65333.87 | G59: =+IFERROR(F59/Summary!F$19,"") -> -0.043015268 | H59: =+D59-F59 -> 7214.5899 | I59: =0-I58 -> -40236.65 | J59: =+IFERROR(I59/Summary!I$19,"") -> -0.030496055 | K59: =+D59-I59 -> -17882.63 | M59: =0-M58 -> -223825.06 | N59: =+IFERROR(M59/Summary!M$19,"") -> -0.035588539 | O59: =0-O58 -> -267358.94 | P59: =+IFERROR(O59/Summary!O$19,"") -> -0.039524225 | Q59: =+M59-O59 -> 43533.884 | R59: =0-R58 -> -231953.8 | S59: =+IFERROR(R59/Summary!R$19,"") -> -0.039551481 | T59: =+M59-R59 -> 8128.74

Sheet EC
V1: ANG
C2: =+Summary!$C$2 -> Angler's | V2: Apr
C3: =+Summary!$C$3 -> STATEMENT OF INCOME
C4: =+Summary!$C$4 -> FOR THE PERIOD ENDING APR 2025
D6: =Year&" "&UPPER(Month)&" - PERIODIC" -> 2025 APR - PERIODIC | M6: =Year&" "&UPPER(Month)&" - YEAR TO DATE" -> 2025 APR - YEAR TO DATE
D7: Actual | F7: Budget | H7: VARIANCE | I7: Actual - Last Year | K7: VARIANCE | M7: Actual | O7: Budget | Q7: VARIANCE | R7: Actual - Last Year | T7: VARIANCE
D8: $ | E8: % | F8: $ | G8: % | H8: $ | I8: Actual | J8: % | K8: $ | M8: $ | N8: % | O8: $ | P8: % | Q8: $ | R8: Actual | S8: % | T8: $
C9: Utilities
B10: Electricity - 810 | C10: Electricity | D10: 18685.07 | E10: =+IFERROR(D10/Summary!D$19,"") -> 0.012383908 | F10: 18926.39 | G10: =+IFERROR(F10/Summary!F$19,"") -> 0.012460975 | H10: =+D10-F10 -> -241.32 | I10: 18512.68 | J10: =+IFERROR(I10/Summary!I$19,"") -> 0.014031081 | K10: =+D10-I10 -> 172.39 | M10: 73774.56 | N10: =+IFERROR(M10/Summary!M$19,"") -> 0.011730272 | O10: 72404.74 | P10: =+IFERROR(O10/Summary!O$19,"") -> 0.010703742 | Q10: =+M10-O10 -> 1369.82 | R10: 70174.27 | S10: =+IFERROR(R10/Summary!R$19,"") -> 0.011965729 | T10: =+M10-R10 -> 3600.29
B11: Gas - 810 | C11: Gas | D11: 1908.87 | E11: =+IFERROR(D11/Summary!D$19,"") -> 0.0012651422 | F11: 3236 | G11: =+IFERROR(F11/Summary!F$19,"") -> 0.0021305551 | H11: =+D11-F11 -> -1327.13 | I11: 3143.23 | J11: =+IFERROR(I11/Summary!I$19,"") -> 0.0023823085 | K11: =+D11-I11 -> -1234.36 | M11: 10943.34 | N11: =+IFERROR(M11/Summary!M$19,"") -> 0.0017400084 | O11: 11262.92 | P11: =+IFERROR(O11/Summary!O$19,"") -> 0.0016650207 | Q11: =+M11-O11 -> -319.58 | R11: 10194.19 | S11: =+IFERROR(R11/Summary!R$19,"") -> 0.001738257 | T11: =+M11-R11 -> 749.15
B12: Water & Sewer - 810 | C12: Water / Sewer | D12: 7767.5 | E12: =+IFERROR(D12/Summary!D$19,"") -> 0.0051480678 | F12: 6000 | G12: =+IFERROR(F12/Summary!F$19,"") -> 0.0039503493 | H12: =+D12-F12 -> 1767.5 | I12: 5657.22 | J12: =+IFERROR(I12/Summary!I$19,"") -> 0.0042877051 | K12: =+D12-I12 -> 2110.28 | M12: 25697.2 | N12: =+IFERROR(M12/Summary!M$19,"") -> 0.0040858955 | O12: 26549.38 | P12: =+IFERROR(O12/Summary!O$19,"") -> 0.0039248497 | Q12: =+M12-O12 -> -852.18 | R12: 25117.53 | S12: =+IFERROR(R12/Summary!R$19,"") -> 0.0042829025 | T12: =+M12-R12 -> 579.67
B13: Credits - 810 | C13: Credits | D13: 0 | E13: =+IFERROR(D13/Summary!D$19,"") -> 0 | F13: 0 | G13: =+IFERROR(F13/Summary!F$19,"") -> 0 | H13: =+D13-F13 -> 0 | I13: 0 | J13: =+IFERROR(I13/Summary!I$19,"") -> 0 | K13: =+D13-I13 -> 0 | M13: 0 | N13: =+IFERROR(M13/Summary!M$19,"") -> 0 | O13: 0 | P13: =+IFERROR(O13/Summary!O$19,"") -> 0 | Q13: =+M13-O13 -> 0 | R13: 0 | S13: =+IFERROR(R13/Summary!R$19,"") -> 0 | T13: =+M13-R13 -> 0
B14: Steam - 810 | C14: Steam | D14: 0 | E14: =+IFERROR(D14/Summary!D$19,"") -> 0 | F14: 0 | G14: =+IFERROR(F14/Summary!F$19,"") -> 0 | H14: =+D14-F14 -> 0 | I14: 0 | J14: =+IFERROR(I14/Summary!I$19,"") -> 0 | K14: =+D14-I14 -> 0 | M14: 0 | N14: =+IFERROR(M14/Summary!M$19,"") -> 0 | O14: 0 | P14: =+IFERROR(O14/Summary!O$19,"") -> 0 | Q14: =+M14-O14 -> 0 | R14: 0 | S14: =+IFERROR(R14/Summary!R$19,"") -> 0 | T14: =+M14-R14 -> 0
B15: Other Fuels - 810 | C15: Other Fuels | D15: -5000 | E15: =+IFERROR(D15/Summary!D$19,"") -> -0.0033138512 | F15: -5000 | G15: =+IFERROR(F15/Summary!F$19,"") -> -0.0032919578 | H15: =+D15-F15 -> 0 | I15: -4166.67 | J15: =+IFERROR(I15/Summary!I$19,"") -> -0.0031579914 | K15: =+D15-I15 -> -833.33 | M15: -20000 | N15: =+IFERROR(M15/Summary!M$19,"") -> -0.0031800317 | O15: -20000 | P15: =+IFERROR(O15/Summary!O$19,"") -> -0.0029566413 | Q15: =+M15-O15 -> 0 | R15: -15994.91 | S15: =+IFERROR(R15/Summary!R$19,"") -> -0.0027273637 | T15: =+M15-R15 -> -4005.09
B16: Contract Services - 810 | C16: Contract Services | D16: 0 | E16: =+IFERROR(D16/Summary!D$19,"") -> 0 | F16: 0 | G16: =+IFERROR(F16/Summary!F$19,"") -> 0 | H16: =+D16-F16 -> 0 | I16: 0 | J16: =+IFERROR(I16/Summary!I$19,"") -> 0 | K16: =+D16-I16 -> 0 | M16: 0 | N16: =+IFERROR(M16/Summary!M$19,"") -> 0 | O16: 0 | P16: =+IFERROR(O16/Summary!O$19,"") -> 0 | Q16: =+M16-O16 -> 0 | R16: 0 | S16: =+IFERROR(R16/Summary!R$19,"") -> 0 | T16: =+M16-R16 -> 0
B17: Total Utilities Expense - 810 | C17: Total Operations Expense | D17: =SUM(D10:D16) -> 23361.44 | E17: =+IFERROR(D17/Summary!D$19,"") -> 0.015483267 | F17: =SUM(F10:F16) -> 23162.39 | G17: =+IFERROR(F17/Summary!F$19,"") -> 0.015249922 | H17: =+D17-F17 -> 199.05 | I17: =SUM(I10:I16) -> 23146.46 | J17: =+IFERROR(I17/Summary!I$19,"") -> 0.017543103 | K17: =+D17-I17 -> 214.98 | M17: =SUM(M10:M16) -> 90415.1 | N17: =+IFERROR(M17/Summary!M$19,"") -> 0.014376144 | O17: =SUM(O10:O16) -> 90217.04 | P17: =+IFERROR(O17/Summary!O$19,"") -> 0.013336971 | Q17: =+M17-O17 -> 198.06 | R17: =SUM(R10:R16) -> 89491.08 | S17: =+IFERROR(R17/Summary!R$19,"") -> 0.015259525 | T17: =+M17-R17 -> 924.02

Sheet Mgt_Fees
V1: ANG
C2: =+Summary!$C$2 -> Angler's | V2: Apr
C3: =+Summary!$C$3 -> STATEMENT OF INCOME
C4: =+Summary!$C$4 -> FOR THE PERIOD ENDING APR 2025
D6: =Year&" "&UPPER(Month)&" - PERIODIC" -> 2025 APR - PERIODIC | M6: =Year&" "&UPPER(Month)&" - YEAR TO DATE" -> 2025 APR - YEAR TO DATE
D7: Actual | F7: Budget | H7: VARIANCE | I7: Actual - Last Year | K7: VARIANCE | M7: Actual | O7: Budget | Q7: VARIANCE | R7: Actual - Last Year | T7: VARIANCE
D8: $ | E8: % | F8: $ | G8: % | H8: $ | I8: Actual | J8: % | K8: $ | M8: $ | N8: % | O8: $ | P8: % | Q8: $ | R8: Actual | S8: % | T8: $
C9: Management Fees
B10: Base Fee - 920 | C10: Base Management Fees | D10: 61919.55 | E10: =+IFERROR(D10/Summary!D$19,"") -> 0.041038435 | F10: 64273.1 | G10: =+IFERROR(F10/Summary!F$19,"") -> 0.042316866 | H10: =+D10-F10 -> -2353.55 | I10: 50584.2 | J10: =+IFERROR(I10/Summary!I$19,"") -> 0.038338642 | K10: =+D10-I10 -> 11335.35 | M10: 247929.58 | N10: =+IFERROR(M10/Summary!M$19,"") -> 0.039421196 | O10: 280923.46 | P10: =+IFERROR(O10/Summary!O$19,"") -> 0.041529496 | Q10: =+M10-O10 -> -32993.88 | R10: 218035.98 | S10: =+IFERROR(R10/Summary!R$19,"") -> 0.037178291 | T10: =+M10-R10 -> 29893.6
B11: Incentive Fee - 920 | C11: Incentive Management Fee | D11: 0 | E11: =+IFERROR(D11/Summary!D$19,"") -> 0 | F11: 0 | G11: =+IFERROR(F11/Summary!F$19,"") -> 0 | H11: =+D11-F11 -> 0 | I11: 0 | J11: =+IFERROR(I11/Summary!I$19,"") -> 0 | K11: =+D11-I11 -> 0 | M11: 0 | N11: =+IFERROR(M11/Summary!M$19,"") -> 0 | O11: 0 | P11: =+IFERROR(O11/Summary!O$19,"") -> 0 | Q11: =+M11-O11 -> 0 | R11: 0 | S11: =+IFERROR(R11/Summary!R$19,"") -> 0 | T11: =+M11-R11 -> 0
B12: Other Fee - 920 | C12: Other Management Fee | D12: 6510.67 | E12: =+IFERROR(D12/Summary!D$19,"") -> 0.0043150783 | F12: 6510.67 | G12: =+IFERROR(F12/Summary!F$19,"") -> 0.0042865702 | H12: =+D12-F12 -> 0 | I12: 6333.33 | J12: =+IFERROR(I12/Summary!I$19,"") -> 0.0048001406 | K12: =+D12-I12 -> 177.34 | M12: 26042.68 | N12: =+IFERROR(M12/Summary!M$19,"") -> 0.0041408274 | O12: 26042.68 | P12: =+IFERROR(O12/Summary!O$19,"") -> 0.0038499432 | Q12: =+M12-O12 -> 0 | R12: 25333.32 | S12: =+IFERROR(R12/Summary!R$19,"") -> 0.0043196978 | T12: =+M12-R12 -> 709.36
B13: Total Management Fees - 920 | C13: Total Operations Expense | D13: =SUM(D10:D12) -> 68430.22 | E13: 0.03284318 | F13: =SUM(F10:F12) -> 70783.77 | G13: =+IFERROR(F13/Summary!F$19,"") -> 0.046603437 | H13: =+D13-F13 -> -2353.55 | I13: =SUM(I10:I12) -> 56917.53 | J13: =+IFERROR(I13/Summary!I$19,"") -> 0.043138783 | K13: =+D13-I13 -> 11512.69 | M13: =SUM(M10:M12) -> 273972.26 | N13: 0.03284318 | O13: =SUM(O10:O12) -> 306966.14 | P13: =+IFERROR(O13/Summary!O$19,"") -> 0.045379439 | Q13: =+M13-O13 -> -32993.88 | R13: =SUM(R10:R12) -> 243369.3 | S13: =+IFERROR(R13/Summary!R$19,"") -> 0.041497989 | T13: =+M13-R13 -> 30602.96

Sheet Non_Op
V1: ANG
C2: =+Summary!$C$2 -> Angler's | V2: Apr
C3: =+Summary!$C$3 -> STATEMENT OF INCOME
C4: =+Summary!$C$4 -> FOR THE PERIOD ENDING APR 2025
D6: =Year&" "&UPPER(Month)&" - PERIODIC" -> 2025 APR - PERIODIC | M6: =Year&" "&UPPER(Month)&" - YEAR TO DATE" -> 2025 APR - YEAR TO DATE
D7: Actual | F7: Budget | H7: VARIANCE | I7: Actual - Last Year | K7: VARIANCE | M7: Actual | O7: Budget | Q7: VARIANCE | R7: Actual - Last Year | T7: VARIANCE
D8: $ | E8: % | F8: $ | G8: % | H8: $ | I8: Actual | J8: % | K8: $ | M8: $ | N8: % | O8: $ | P8: % | Q8: $ | R8: Actual | S8: % | T8: $
C9: Income
B10: Total Non-Operating Income - 900 | C10: Income | D10: 1631.67 | E10: =+D10/Summary!D$19 -> 0.0010814223 | F10: 2031 | G10: =+F10/Summary!F$19 -> 0.0013371933 | H10: =+D10-F10 -> -399.33 | I10: 1967.65 | J10: =+I10/Summary!I$19 -> 0.001491316 | K10: =+F10-I10 -> 63.35 | M10: 9884.92 | N10: =+M10/Summary!M$19 -> 0.0015717179 | O10: 8124 | P10: =+O10/Summary!O$19 -> 0.0012009877 | Q10: =+M10-O10 -> 1760.92 | R10: 7748.25 | S10: =+R10/Summary!R$19 -> 0.0013211888 | T10: =+O10-R10 -> 375.75
C11: Total Income | D11: =SUM(D10:D10) -> 1631.67 | E11: =+D11/Summary!D$19 -> 0.0010814223 | F11: =SUM(F10:F10) -> 2031 | G11: =+F11/Summary!F$19 -> 0.0013371933 | H11: =+D11-F11 -> -399.33 | I11: =SUM(I10:I10) -> 1967.65 | J11: =+I11/Summary!I$19 -> 0.001491316 | K11: =+F11-I11 -> 63.35 | M11: =SUM(M10:M10) -> 9884.92 | N11: =+M11/Summary!M$19 -> 0.0015717179 | O11: =SUM(O10:O10) -> 8124 | P11: =+O11/Summary!O$19 -> 0.0012009877 | Q11: =+M11-O11 -> 1760.92 | R11: =SUM(R10:R10) -> 7748.25 | S11: =+R11/Summary!R$19 -> 0.0013211888 | T11: =+O11-R11 -> 375.75
C12: Rent
B13: Land & Buildings - 900 | C13: Land & Buildings | D13: 0 | E13: =+D13/Summary!D$19 -> 0 | F13: 0 | G13: =+F13/Summary!F$19 -> 0 | H13: =+D13-F13 -> 0 | I13: 0 | J13: =+I13/Summary!I$19 -> 0 | K13: =+F13-I13 -> 0 | M13: 0 | N13: =+M13/Summary!M$19 -> 0 | O13: 0 | P13: =+O13/Summary!O$19 -> 0 | Q13: =+M13-O13 -> 0 | R13: 0 | S13: =+R13/Summary!R$19 -> 0 | T13: =+O13-R13 -> 0
B14: Other Property & Equipment - 900 | C14: Other Property & Equipment | D14: 277.09 | E14: =+D14/Summary!D$19 -> 0.00018364701 | F14: 1100.5 | G14: =+F14/Summary!F$19 -> 0.00072455991 | H14: =+D14-F14 -> -823.41 | I14: -196.17 | J14: =+I14/Summary!I$19 -> -0.00014868064 | K14: =+F14-I14 -> 1296.67 | M14: 3931.72 | N14: =+M14/Summary!M$19 -> 0.00062514971 | O14: 4615 | P14: =+O14/Summary!O$19 -> 0.00068224499 | Q14: =+M14-O14 -> -683.28 | R14: 4172.12 | S14: =+R14/Summary!R$19 -> 0.00071140686 | T14: =+O14-R14 -> 442.88
B15: Total Rent - 900 | C15: Total Rent | D15: =SUM(D13:D14) -> 277.09 | E15: =+D15/Summary!D$19 -> 0.00018364701 | F15: =SUM(F13:F14) -> 1100.5 | G15: =+F15/Summary!F$19 -> 0.00072455991 | H15: =+D15-F15 -> -823.41 | I15: =SUM(I13:I14) -> -196.17 | J15: =+I15/Summary!I$19 -> -0.00014868064 | K15: =+F15-I15 -> 1296.67 | M15: =SUM(M13:M14) -> 3931.72 | N15: =+M15/Summary!M$19 -> 0.00062514971 | O15: =SUM(O13:O14) -> 4615 | P15: =+O15/Summary!O$19 -> 0.00068224499 | Q15: =+M15-O15 -> -683.28 | R15: =SUM(R13:R14) -> 4172.12 | S15: =+R15/Summary!R$19 -> 0.00071140686 | T15: =+O15-R15 -> 442.88
C16: Property & Other Taxes
B17: Real Estate Taxes - 900 | C17: Real Estate Taxes | D17: 8724.92 | E17: =+D17/Summary!D$19 -> 0.0057826173 | F17: 40005 | G17: =+F17/Summary!F$19 -> 0.026338954 | H17: =+D17-F17 -> -31280.08 | I17: 37098 | J17: =+I17/Summary!I$19 -> 0.028117217 | K17: =+F17-I17 -> 2907 | M17: 128739.92 | N17: =+M17/Summary!M$19 -> 0.020469851 | O17: 160020 | P17: =+O17/Summary!O$19 -> 0.023656087 | Q17: =+M17-O17 -> -31280.08 | R17: 151858 | S17: =+R17/Summary!R$19 -> 0.025893987 | T17: =+O17-R17 -> 8162
B18: Personal Property Taxes - 900 | C18: Personal Property Taxes | D18: 8363 | E18: =+D18/Summary!D$19 -> 0.0055427475 | F18: 8363 | G18: =+F18/Summary!F$19 -> 0.0055061286 | H18: =+D18-F18 -> 0 | I18: 8363.2 | J18: =+I18/Summary!I$19 -> 0.0063386143 | K18: =+F18-I18 -> -0.2 | M18: 33452 | N18: =+M18/Summary!M$19 -> 0.005318921 | O18: 33452 | P18: =+O18/Summary!O$19 -> 0.0049452783 | Q18: =+M18-O18 -> 0 | R18: 33452.2 | S18: =+R18/Summary!R$19 -> 0.0057040844 | T18: =+O18-R18 -> -0.2
B19: Business & Occupation Taxes - 900 | C19: Business & Occupation Taxes | D19: 600 | E19: =+D19/Summary!D$19 -> 0.00039766214 | F19: 300 | G19: =+F19/Summary!F$19 -> 0.00019751747 | H19: =+D19-F19 -> 300 | I19: 600 | J19: =+I19/Summary!I$19 -> 0.0004547504 | K19: =+F19-I19 -> -300 | M19: 600 | N19: =+M19/Summary!M$19 -> 9.540095e-05 | O19: 300 | P19: =+O19/Summary!O$19 -> 4.434962e-05 | Q19: =+M19-O19 -> 300 | R19: 600 | S19: =+R19/Summary!R$19 -> 0.00010230869 | T19: =+O19-R19 -> -300
B20: Other Taxes & Assessments - 900 | C20: Other Taxes & Assesments | D20: 16589.2 | E20: =+D20/Summary!D$19 -> 0.010994828 | F20: 16589 | G20: =+F20/Summary!F$19 -> 0.010922058 | H20: =+D20-F20 -> 0.2 | I20: 16589 | J20: =+I20/Summary!I$19 -> 0.012573091 | K20: =+F20-I20 -> 0 | M20: 16589.2 | N20: =+M20/Summary!M$19 -> 0.0026377091 | O20: 16589 | P20: =+O20/Summary!O$19 -> 0.0024523861 | Q20: =+M20-O20 -> 0.2 | R20: 16589 | S20: =+R20/Summary!R$19 -> 0.0028286646 | T20: =+O20-R20 -> 0
B21: Total Taxes - 900 | C21: Total Property & Other Taxes | D21: =SUM(D17:D20) -> 34277.12 | E21: =+D21/Summary!D$19 -> 0.022717855 | F21: =SUM(F17:F20) -> 65257 | G21: =+F21/Summary!F$19 -> 0.042964658 | H21: =+D21-F21 -> -30979.88 | I21: =SUM(I17:I20) -> 62650.2 | J21: =+I21/Summary!I$19 -> 0.047483673 | K21: =+F21-I21 -> 2606.8 | M21: =SUM(M17:M20) -> 179381.12 | N21: =+M21/Summary!M$19 -> 0.028521882 | O21: =SUM(O17:O20) -> 210361 | P21: =+O21/Summary!O$19 -> 0.031098101 | Q21: =+M21-O21 -> -30979.88 | R21: =SUM(R17:R20) -> 202499.2 | S21: =+R21/Summary!R$19 -> 0.034529045 | T21: =+O21-R21 -> 7861.8
C22: Insurance
B23: Building & Contents - 900 | C23: Property Insurance | D23: 107063.27 | E23: =+D23/Summary!D$19 -> 0.070958349 | F23: 107065 | G23: =+F23/Summary!F$19 -> 0.070490692 | H23: =+D23-F23 -> -1.73 | I23: 120330.33 | J23: =+I23/Summary!I$19 -> 0.091200443 | K23: =+F23-I23 -> -13265.33 | M23: 428253.35 | N23: =+M23/Summary!M$19 -> 0.068092961 | O23: 428260 | P23: =+O23/Summary!O$19 -> 0.063310561 | Q23: =+M23-O23 -> -6.65 | R23: 480531.21 | S23: =+R23/Summary!R$19 -> 0.081937528 | T23: =+O23-R23 -> -52271.21
B24: Liability - 900 | C24: Liability Insurance | D24: 7704.69 | E24: =+D24/Summary!D$19 -> 0.0051064392 | F24: 10545.32 | G24: =+F24/Summary!F$19 -> 0.0069429497 | H24: =+D24-F24 -> -2840.63 | I24: 10303.48 | J24: =+I24/Summary!I$19 -> 0.0078091861 | K24: =+F24-I24 -> 241.84 | M24: 31114.29 | N24: =+M24/Summary!M$19 -> 0.0049472214 | O24: 42181.28 | P24: =+O24/Summary!O$19 -> 0.0062357458 | Q24: =+M24-O24 -> -11066.99 | R24: 39939.84 | S24: =+R24/Summary!R$19 -> 0.0068103209 | T24: =+O24-R24 -> 2241.44
B25: Deductible - 900 | C25: Deductible | D25: 0 | E25: =+D25/Summary!D$19 -> 0 | F25: 0 | G25: =+F25/Summary!F$19 -> 0 | H25: =+D25-F25 -> 0 | I25: 0 | J25: =+I25/Summary!I$19 -> 0 | K25: =+F25-I25 -> 0 | M25: 0 | N25: =+M25/Summary!M$19 -> 0 | O25: 0 | P25: =+O25/Summary!O$19 -> 0 | Q25: =+M25-O25 -> 0 | R25: 0 | S25: =+R25/Summary!R$19 -> 0 | T25: =+O25-R25 -> 0
B26: Other Insurance - 900 | C26: Other Insurance | D26: 439.84 | E26: =+D26/Summary!D$19 -> 0.00029151286 | F26: 873 | G26: =+F26/Summary!F$19 -> 0.00057477583 | H26: =+D26-F26 -> -433.16 | I26: 350.51 | J26: =+I26/Summary!I$19 -> 0.00026565761 | K26: =+F26-I26 -> 522.49 | M26: 1848.69 | N26: =+M26/Summary!M$19 -> 0.00029394464 | O26: 3492 | P26: =+O26/Summary!O$19 -> 0.00051622957 | Q26: =+M26-O26 -> -1643.31 | R26: 1408.5 | S26: =+R26/Summary!R$19 -> 0.00024016964 | T26: =+O26-R26 -> 2083.5
B27: Total Insurance - 900 | C27: Total Insurance | D27: =SUM(D23:D26) -> 115207.8 | E27: =+D27/Summary!D$19 -> 0.076356301 | F27: =SUM(F23:F26) -> 118483.32 | G27: =+F27/Summary!F$19 -> 0.078008418 | H27: =+D27-F27 -> -3275.52 | I27: =SUM(I23:I26) -> 130984.32 | J27: =+I27/Summary!I$19 -> 0.099275287 | K27: =+F27-I27 -> -12501 | M27: =SUM(M23:M26) -> 461216.33 | N27: =+M27/Summary!M$19 -> 0.073334127 | O27: =SUM(O23:O26) -> 473933.28 | P27: =+O27/Summary!O$19 -> 0.070062536 | Q27: =+M27-O27 -> -12716.95 | R27: =SUM(R23:R26) -> 521879.55 | S27: =+R27/Summary!R$19 -> 0.088988018 | T27: =+O27-R27 -> -47946.27
C28: Other
B29: Asset Management fees - 900 | C29: Asset Management Fee | D29: 0 | E29: =+D29/Summary!D$19 -> 0 | F29: 0 | G29: =+F29/Summary!F$19 -> 0 | H29: =+D29-F29 -> 0 | I29: 0 | J29: =+I29/Summary!I$19 -> 0 | K29: =+F29-I29 -> 0 | M29: 0 | N29: =+M29/Summary!M$19 -> 0 | O29: 0 | P29: =+O29/Summary!O$19 -> 0 | Q29: =+M29-O29 -> 0 | R29: 0 | S29: =+R29/Summary!R$19 -> 0 | T29: =+O29-R29 -> 0
B30: FX Gain Loss - 900 | C30: FX Gain Floss | D30: 0 | E30: =+D30/Summary!D$19 -> 0 | F30: 0 | G30: =+F30/Summary!F$19 -> 0 | H30: =+D30-F30 -> 0 | I30: 0 | J30: =+I30/Summary!I$19 -> 0 | K30: =+F30-I30 -> 0 | M30: 0 | N30: =+M30/Summary!M$19 -> 0 | O30: 0 | P30: =+O30/Summary!O$19 -> 0 | Q30: =+M30-O30 -> 0 | R30: 0 | S30: =+R30/Summary!R$19 -> 0 | T30: =+O30-R30 -> 0
B31: Legal fees - 900 | C31: Legal Fees | D31: 0 | E31: =+D31/Summary!D$19 -> 0 | F31: 0 | G31: =+F31/Summary!F$19 -> 0 | H31: =+D31-F31 -> 0 | I31: 0 | J31: =+I31/Summary!I$19 -> 0 | K31: =+F31-I31 -> 0 | M31: 0 | N31: =+M31/Summary!M$19 -> 0 | O31: 0 | P31: =+O31/Summary!O$19 -> 0 | Q31: =+M31-O31 -> 0 | R31: 0 | S31: =+R31/Summary!R$19 -> 0 | T31: =+O31-R31 -> 0
B32: Other Non-Operating Expenses - 900 | C32: Other Non-Operating Expenses | D32: 0 | E32: =+D32/Summary!D$19 -> 0 | F32: 0 | G32: =+F32/Summary!F$19 -> 0 | H32: =+D32-F32 -> 0 | I32: -185.5 | J32: =+I32/Summary!I$19 -> -0.00014059367 | K32: =+F32-I32 -> 185.5 | M32: 0 | N32: =+M32/Summary!M$19 -> 0 | O32: 0 | P32: =+O32/Summary!O$19 -> 0 | Q32: =+M32-O32 -> 0 | R32: -448 | S32: =+R32/Summary!R$19 -> -7.6390485e-05 | T32: =+O32-R32 -> 448
B33: Owner Expenses - 900 | C33: Owner's Expense | D33: 0 | E33: =+D33/Summary!D$19 -> 0 | F33: 0 | G33: =+F33/Summary!F$19 -> 0 | H33: =+D33-F33 -> 0 | I33: 0 | J33: =+I33/Summary!I$19 -> 0 | K33: =+F33-I33 -> 0 | M33: 0 | N33: =+M33/Summary!M$19 -> 0 | O33: 0 | P33: =+O33/Summary!O$19 -> 0 | Q33: =+M33-O33 -> 0 | R33: 0 | S33: =+R33/Summary!R$19 -> 0 | T33: =+O33-R33 -> 0
B34: Pre-Opening Expenses - 900 | C34: Pre-Opening Expenses | D34: 0 | E34: =+D34/Summary!D$19 -> 0 | F34: 0 | G34: =+F34/Summary!F$19 -> 0 | H34: =+D34-F34 -> 0 | I34: 0 | J34: =+I34/Summary!I$19 -> 0 | K34: =+F34-I34 -> 0 | M34: 0 | N34: =+M34/Summary!M$19 -> 0 | O34: 0 | P34: =+O34/Summary!O$19 -> 0 | Q34: =+M34-O34 -> 0 | R34: 0 | S34: =+R34/Summary!R$19 -> 0 | T34: =+O34-R34 -> 0
B35: Total Other Expenses - 900 | C35: Total Other | D35: =SUM(D29:D34) -> 0 | E35: =+D35/Summary!D$19 -> 0 | F35: =SUM(F29:F34) -> 0 | G35: =+F35/Summary!F$19 -> 0 | H35: =+D35-F35 -> 0 | I35: =SUM(I29:I34) -> -185.5 | J35: =+I35/Summary!I$19 -> -0.00014059367 | K35: =+F35-I35 -> 185.5 | M35: =SUM(M29:M34) -> 0 | N35: =+M35/Summary!M$19 -> 0 | O35: =SUM(O29:O34) -> 0 | P35: =+O35/Summary!O$19 -> 0 | Q35: =+M35-O35 -> 0 | R35: =SUM(R29:R34) -> -448 | S35: =+R35/Summary!R$19 -> -7.6390485e-05 | T35: =+O35-R35 -> 448
B37: Total Non-Op - 000 | C37: Total Non-Operating Income & Expense | D37: =+(-D11)+D15+D21+D27+D35 -> 148130.34 | E37: =+D37/Summary!D$19 -> 0.098176381 | F37: =+-F11+F15+F21+F27+F35 -> 182809.82 | G37: =+F37/Summary!F$19 -> 0.12036044 | H37: =+D37-F37 -> -34679.48 | I37: =+-I11+I15+I21+I27+I35 -> 191285.2 | J37: =+I37/Summary!I$19 -> 0.14497837 | K37: =+F37-I37 -> -8475.38 | M37: =+(-M11)+M15+M21+M27+M35 -> 634644.25 | N37: =+M37/Summary!M$19 -> 0.10090944 | O37: =+-O11+O15+O21+O27+O35 -> 680785.28 | P37: =+O37/Summary!O$19 -> 0.10064189 | Q37: =+M37-O37 -> -46141.03 | R37: =+-R11+R15+R21+R27+R35 -> 720354.62 | S37: =+R37/Summary!R$19 -> 0.12283089 | T37: =+O37-R37 -> -39569.34
