Workbook
Name _________________________________old2: {#N/A,#N/A,FALSE,"Chart 2 by Prop Type"}
Name _______________________________old2: {#N/A,#N/A,FALSE,"Chart 2 by Prop Type"}
Name _____________________________old2: {#N/A,#N/A,FALSE,"Chart 2 by Prop Type"}
Name _____________________________old2: {#N/A,#N/A,FALSE,"Chart 2 by Prop Type"}
Name _____________________________old2: {#N/A,#N/A,FALSE,"Chart 2 by Prop Type"}
Name ____________________________old2: {#N/A,#N/A,FALSE,"Chart 2 by Prop Type"}
Name ____________________________old2: {#N/A,#N/A,FALSE,"Chart 2 by Prop Type"}
Name ____________________________old2: {#N/A,#N/A,FALSE,"Chart 2 by Prop Type"}
Name ___________________________old2: {#N/A,#N/A,FALSE,"Chart 2 by Prop Type"}
Name ___________________________old2: {#N/A,#N/A,FALSE,"Chart 2 by Prop Type"}
Name ___________________________old2: {#N/A,#N/A,FALSE,"Chart 2 by Prop Type"}
Name __________________________old2: {#N/A,#N/A,FALSE,"Chart 2 by Prop Type"}
Name __________________________old2: {#N/A,#N/A,FALSE,"Chart 2 by Prop Type"}
Name __________________________old2: {#N/A,#N/A,FALSE,"Chart 2 by Prop Type"}
Name _________________________old2: {#N/A,#N/A,FALSE,"Chart 2 by Prop Type"}
Name _________________________old2: {#N/A,#N/A,FALSE,"Chart 2 by Prop Type"}
Name _________________________old2: {#N/A,#N/A,FALSE,"Chart 2 by Prop Type"}
Name ________________________old2: {#N/A,#N/A,FALSE,"Chart 2 by Prop Type"}
Name ________________________old2: {#N/A,#N/A,FALSE,"Chart 2 by Prop Type"}
Name ________________________old2: {#N/A,#N/A,FALSE,"Chart 2 by Prop Type"}
Name _______________________old2: {#N/A,#N/A,FALSE,"Chart 2 by Prop Type"}
Name _______________________old2: {#N/A,#N/A,FALSE,"Chart 2 by Prop Type"}
Name _______________________old2: {#N/A,#N/A,FALSE,"Chart 2 by Prop Type"}
Name ______________________old2: {#N/A,#N/A,FALSE,"Chart 2 by Prop Type"}
Name ______________________old2: {#N/A,#N/A,FALSE,"Chart 2 by Prop Type"}
Name ______________________old2: {#N/A,#N/A,FALSE,"Chart 2 by Prop Type"}
Name _____________________old2: {#N/A,#N/A,FALSE,"Chart 2 by Prop Type"}
Name _____________________old2: {#N/A,#N/A,FALSE,"Chart 2 by Prop Type"}
Name _____________________old2: {#N/A,#N/A,FALSE,"Chart 2 by Prop Type"}
Name ____________________old2: {#N/A,#N/A,FALSE,"Chart 2 by Prop Type"}
Name ____________________old2: {#N/A,#N/A,FALSE,"Chart 2 by Prop Type"}
Name ____________________old2: {#N/A,#N/A,FALSE,"Chart 2 by Prop Type"}
Name ___________________old2: {#N/A,#N/A,FALSE,"Chart 2 by Prop Type"}
Name ___________________old2: {#N/A,#N/A,FALSE,"Chart 2 by Prop Type"}
Name ___________________old2: {#N/A,#N/A,FALSE,"Chart 2 by Prop Type"}
Name __________________old2: {#N/A,#N/A,FALSE,"Chart 2 by Prop Type"}
Name __________________old2: {#N/A,#N/A,FALSE,"Chart 2 by Prop Type"}
Name __________________old2: {#N/A,#N/A,FALSE,"Chart 2 by Prop Type"}
Name _________________old2: {#N/A,#N/A,FALSE,"Chart 2 by Prop Type"}
Name _________________old2: {#N/A,#N/A,FALSE,"Chart 2 by Prop Type"}
Name _________________old2: {#N/A,#N/A,FALSE,"Chart 2 by Prop Type"}
Name ________________a1: {"Assump",#N/A,TRUE,"Proforma";"first",#N/A,TRUE,"Proforma";"second",#N/A,TRUE,"Proforma";"lease1",#N/A,TRUE,"Proforma";"lease2",#N/A,TRUE,"Proforma"}
Name ________________jo2: {#N/A,#N/A,FALSE,"DCF-COM";#N/A,#N/A,FALSE,"VAC-COM"}
Name ________________jo3: {"CASHFLOW",#N/A,FALSE,"Northpointe"}
Name ________________jo4: {#N/A,#N/A,FALSE,"SHEET1";#N/A,#N/A,FALSE,"SHEET2";#N/A,#N/A,FALSE,"SHEET3";#N/A,#N/A,FALSE,"SHEET4"}
Name ________________old2: {#N/A,#N/A,FALSE,"Chart 2 by Prop Type"}
Name ________________old2: {#N/A,#N/A,FALSE,"Chart 2 by Prop Type"}
Name ________________old2: {#N/A,#N/A,FALSE,"Chart 2 by Prop Type"}
Name _______________a1: {"Assump",#N/A,TRUE,"Proforma";"first",#N/A,TRUE,"Proforma";"second",#N/A,TRUE,"Proforma";"lease1",#N/A,TRUE,"Proforma";"lease2",#N/A,TRUE,"Proforma"}
Name _______________jo2: {#N/A,#N/A,FALSE,"DCF-COM";#N/A,#N/A,FALSE,"VAC-COM"}
Name _______________jo3: {"CASHFLOW",#N/A,FALSE,"Northpointe"}
Name _______________jo4: {#N/A,#N/A,FALSE,"SHEET1";#N/A,#N/A,FALSE,"SHEET2";#N/A,#N/A,FALSE,"SHEET3";#N/A,#N/A,FALSE,"SHEET4"}
Name _______________old2: {#N/A,#N/A,FALSE,"Chart 2 by Prop Type"}
Name _______________old2: {#N/A,#N/A,FALSE,"Chart 2 by Prop Type"}
Name _______________old2: {#N/A,#N/A,FALSE,"Chart 2 by Prop Type"}
Name ______________a1: {"Assump",#N/A,TRUE,"Proforma";"first",#N/A,TRUE,"Proforma";"second",#N/A,TRUE,"Proforma";"lease1",#N/A,TRUE,"Proforma";"lease2",#N/A,TRUE,"Proforma"}
Name ______________jo2: {#N/A,#N/A,FALSE,"DCF-COM";#N/A,#N/A,FALSE,"VAC-COM"}
Name ______________jo3: {"CASHFLOW",#N/A,FALSE,"Northpointe"}
Name ______________jo4: {#N/A,#N/A,FALSE,"SHEET1";#N/A,#N/A,FALSE,"SHEET2";#N/A,#N/A,FALSE,"SHEET3";#N/A,#N/A,FALSE,"SHEET4"}
Name ______________old2: {#N/A,#N/A,FALSE,"Chart 2 by Prop Type"}

Sheet Summary
B3: Sources | H3: Uses | O3: Proforma Operating Summary
D4: % of | L4: % of | T4: Renovation
B5: Investment | C5: Amount | D5: Category | E5: Per Room | F5: LTC | H5: Category | I5: Amount | J5: Per Room | K5: Per SF | L5: Category | T5: Complete
B6: First Mortgage | C6: =Model!I16 -> 23187000 | D6: =C6/$C$8 -> 1 | E6: =C6/Model!$C$10 -> 175659.09 | F6: =C6/$I$19 -> #ERROR! | H6: Historic Building Acquisition | I6: =Model!N4 -> 36436802 | J6: =I6/Model!$C$10 -> 276036.38 | K6: =I6/Model!$C$14 -> 259.54541 | L6: =I6/$I$17 -> #ERROR! | R6: CY | S6: CY | T6: CY | U6: CY | V6: CY | W6: CY | X6: CY | Y6: CY | AA6: CAGR
B7: C-PACE Financing | C7: =Model!J54 | D7: =C7/$C$8 -> 0 | E7: =C7/Model!$C$10 -> 0 | F7: =C7/$I$19 -> #ERROR! | H7: Working Capital First Year | I7: =Model!N6 -> 0 | J7: =I7/Model!$C$10 -> 0 | K7: =I7/Model!$C$14 -> 0 | L7: =I7/$I$17 -> #ERROR! | R7: 2026 | S7: =+R7+1 -> 2027 | T7: =+S7+1 -> 2028 | U7: =+T7+1 -> 2029 | V7: =+U7+1 -> 2030 | W7: =+V7+1 -> 2031 | X7: =+W7+1 -> 2032 | Y7: =+X7+1 -> 2033 | AA7: 26-'33
B8: Total Debt | C8: =SUM(C6:C7) -> 23187000 | D8: =SUM(D6:D7) -> 1 | E8: =C8/Model!$C$10 -> 175659.09 | F8: =C8/$I$19 -> #ERROR! | H8: Premiere Advisory Group Fees | I8: =Model!#REF! -> #ERROR! | J8: =I8/Model!$C$10 -> #ERROR! | K8: =I8/Model!$C$14 -> #ERROR! | L8: =I8/$I$17 -> #ERROR! | O8: OCC | R8: n/a | S8: n/a | T8: {=INDEX('Index Analysis'!$C$12:$R$12,MATCH(Summary!T$7,'Index Analysis'!$C$6:$R$6))} -> 0.74594 | U8: {=INDEX('Index Analysis'!$C$12:$R$12,MATCH(Summary!U$7,'Index Analysis'!$C$6:$R$6))} -> 0.7683182 | V8: {=INDEX('Index Analysis'!$C$12:$R$12,MATCH(Summary!V$7,'Index Analysis'!$C$6:$R$6))} -> 0.77215979 | W8: {=INDEX('Index Analysis'!$C$12:$R$12,MATCH(Summary!W$7,'Index Analysis'!$C$6:$R$6))} -> 0.77215979 | X8: {=INDEX('Index Analysis'!$C$12:$R$12,MATCH(Summary!X$7,'Index Analysis'!$C$6:$R$6))} -> 0.77215979 | Y8: {=INDEX('Index Analysis'!$C$12:$R$12,MATCH(Summary!Y$7,'Index Analysis'!$C$6:$R$6))} -> 0.77215979 | AA8: =IFERROR(+(Y8/T8)^(1/(Y$7-T$7))-1,0) -> 0.0069331928
H9: Development | I9: 3142555.3 | J9: =I9/Model!$C$10 -> 23807.237 | K9: =I9/Model!$C$14 -> 22.384945 | L9: =I9/$I$17 -> #ERROR! | O9: ADR | R9: n/a | S9: n/a | T9: {=INDEX('Index Analysis'!$C$13:$R$13,MATCH(Summary!T$7,'Index Analysis'!$C$6:$R$6))} -> 311.09861 | U9: {=INDEX('Index Analysis'!$C$13:$R$13,MATCH(Summary!U$7,'Index Analysis'!$C$6:$R$6))} -> 323.03977 | V9: {=INDEX('Index Analysis'!$C$13:$R$13,MATCH(Summary!V$7,'Index Analysis'!$C$6:$R$6))} -> 329.50056 | W9: {=INDEX('Index Analysis'!$C$13:$R$13,MATCH(Summary!W$7,'Index Analysis'!$C$6:$R$6))} -> 343.50434 | X9: {=INDEX('Index Analysis'!$C$13:$R$13,MATCH(Summary!X$7,'Index Analysis'!$C$6:$R$6))} -> 357.24451 | Y9: {=INDEX('Index Analysis'!$C$13:$R$13,MATCH(Summary!Y$7,'Index Analysis'!$C$6:$R$6))} -> 364.3894 | AA9: =IFERROR(+(Y9/T9)^(1/(Y$7-T$7))-1,0) -> 0.032127937
B10: LP Members | C10: =D10*C12 -> #ERROR! | D10: 0.9 | E10: =C10/Model!$C$10 -> #ERROR! | F10: =C10/$I$19 -> #ERROR! | H10: Design | I10: 2694240.1 | J10: =I10/Model!$C$10 -> 20410.91 | K10: =I10/Model!$C$14 -> 19.191521 | L10: =I10/$I$17 -> #ERROR! | O10: RevPAR | R10: n/a | S10: n/a | T10: {=INDEX('Index Analysis'!$C$14:$R$14,MATCH(Summary!T$7,'Index Analysis'!$C$6:$R$6))} -> 232.0609 | U10: {=INDEX('Index Analysis'!$C$14:$R$14,MATCH(Summary!U$7,'Index Analysis'!$C$6:$R$6))} -> 248.19733 | V10: {=INDEX('Index Analysis'!$C$14:$R$14,MATCH(Summary!V$7,'Index Analysis'!$C$6:$R$6))} -> 254.42709 | W10: {=INDEX('Index Analysis'!$C$14:$R$14,MATCH(Summary!W$7,'Index Analysis'!$C$6:$R$6))} -> 265.24024 | X10: {=INDEX('Index Analysis'!$C$14:$R$14,MATCH(Summary!X$7,'Index Analysis'!$C$6:$R$6))} -> 275.84985 | Y10: {=INDEX('Index Analysis'!$C$14:$R$14,MATCH(Summary!Y$7,'Index Analysis'!$C$6:$R$6))} -> 281.36684 | AA10: =IFERROR(+(Y10/T10)^(1/(Y$7-T$7))-1,0) -> 0.039283879
B11: GP | C11: =D11*C12 -> #ERROR! | D11: 0.1 | E11: =C11/Model!$C$10 -> #ERROR! | F11: =C11/$I$19 -> #ERROR! | H11: Construction | I11: 57063595 | J11: =I11/Model!$C$10 -> 432299.96 | K11: =I11/Model!$C$14 -> 406.4735 | L11: =I11/$I$17 -> #ERROR! | O11: RevPAR Growth | R11: n/a | S11: n/a | T11: n/a | U11: =+U10/T10-1 -> 0.069535354 | V11: =+V10/U10-1 -> 0.0251 | W11: =+W10/V10-1 -> 0.0425 | X11: =+X10/W10-1 -> 0.04 | Y11: =+Y10/X10-1 -> 0.02
B12: Total Equity | C12: =I17-C8 -> #ERROR! | D12: =SUM(D10:D11) -> 1 | E12: =C12/Model!$C$10 -> #ERROR! | F12: =C12/$I$19 -> #ERROR! | H12: FF&E | I12: 5241613.1 | J12: =I12/Model!$C$10 -> 39709.19 | K12: =I12/Model!$C$14 -> 37.336884 | L12: =I12/$I$17 -> #ERROR! | O12: RevPAR Index | R12: n/a | S12: n/a | T12: {=INDEX('Index Analysis'!$C$33:$R$33,MATCH(Summary!T$7,'Index Analysis'!$C$6:$R$6))} -> 0.99 | U12: {=INDEX('Index Analysis'!$C$33:$R$33,MATCH(Summary!U$7,'Index Analysis'!$C$6:$R$6))} -> 1 | V12: {=INDEX('Index Analysis'!$C$33:$R$33,MATCH(Summary!V$7,'Index Analysis'!$C$6:$R$6))} -> 1 | W12: {=INDEX('Index Analysis'!$C$33:$R$33,MATCH(Summary!W$7,'Index Analysis'!$C$6:$R$6))} -> 1 | X12: {=INDEX('Index Analysis'!$C$33:$R$33,MATCH(Summary!X$7,'Index Analysis'!$C$6:$R$6))} -> 1 | Y12: {=INDEX('Index Analysis'!$C$33:$R$33,MATCH(Summary!Y$7,'Index Analysis'!$C$6:$R$6))} -> 1 | AA12: =IFERROR(+(Y12/T12)^(1/(Y$7-T$7))-1,0) -> 0.0020120887
H13: OS&E and Systems | I13: 1893105.1 | J13: =I13/Model!$C$10 -> 14341.705 | K13: =I13/Model!$C$14 -> 13.484903 | L13: =I13/$I$17 -> #ERROR!
H14: Pre-Opening | I14: 1896183.6 | J14: =I14/Model!$C$10 -> 14365.027 | K14: =I14/Model!$C$14 -> 13.506832 | L14: =I14/$I$17 -> #ERROR! | O14: $000's
H15: Contingencies | I15: =Model!E42+I23 -> 323653.8 | J15: =I15/Model!$C$10 -> 2451.9227 | K15: =I15/Model!$C$14 -> 2.30544 | L15: =I15/$I$17 -> #ERROR!
H16: Financing Costs & Int. Reserves | I16: =SUM(Model!#REF!,Model!N8,Model!N13) -> #ERROR! | J16: =I16/Model!$C$10 -> #ERROR! | K16: =I16/Model!$C$14 -> #ERROR! | L16: =I16/$I$17 -> #ERROR! | O16: Rooms | R16: n/a | S16: n/a | T16: {=INDEX(Proforma!$J$22:$AL$22,MATCH(Summary!T$7,Proforma!$J$6:$AL$6))/1000} -> 11180.694 | U16: {=INDEX(Proforma!$J$22:$AL$22,MATCH(Summary!U$7,Proforma!$J$6:$AL$6))/1000} -> 11990.91 | V16: {=INDEX(Proforma!$J$22:$AL$22,MATCH(Summary!V$7,Proforma!$J$6:$AL$6))/1000} -> 12258.297 | W16: {=INDEX(Proforma!$J$22:$AL$22,MATCH(Summary!W$7,Proforma!$J$6:$AL$6))/1000} -> 12258.297 | X16: {=INDEX(Proforma!$J$22:$AL$22,MATCH(Summary!X$7,Proforma!$J$6:$AL$6))/1000} -> 12258.297 | Y16: {=INDEX(Proforma!$J$22:$AL$22,MATCH(Summary!Y$7,Proforma!$J$6:$AL$6))/1000} -> 12258.297 | AA16: =IFERROR(+(Y16/T16)^(1/(Y$7-T$7))-1,0) -> 0.018573272
H17: Total Debt | I17: =SUM(I6:I16) -> #ERROR! | J17: =I17/Model!$C$10 -> #ERROR! | K17: =I17/Model!$C$14 -> #ERROR! | L17: =SUM(L6:L16) -> #ERROR! | O17: Food & Beverage | R17: n/a | S17: n/a | T17: {=INDEX(Proforma!$J$23:$AL$23,MATCH(Summary!T$7,Proforma!$J$6:$AL$6))/1000} -> 3382.2938 | U17: {=INDEX(Proforma!$J$23:$AL$23,MATCH(Summary!U$7,Proforma!$J$6:$AL$6))/1000} -> 3545.7068 | V17: {=INDEX(Proforma!$J$23:$AL$23,MATCH(Summary!V$7,Proforma!$J$6:$AL$6))/1000} -> 3607.0046 | W17: {=INDEX(Proforma!$J$23:$AL$23,MATCH(Summary!W$7,Proforma!$J$6:$AL$6))/1000} -> 3607.0046 | X17: {=INDEX(Proforma!$J$23:$AL$23,MATCH(Summary!X$7,Proforma!$J$6:$AL$6))/1000} -> 3607.0046 | Y17: {=INDEX(Proforma!$J$23:$AL$23,MATCH(Summary!Y$7,Proforma!$J$6:$AL$6))/1000} -> 3607.0046 | AA17: =IFERROR(+(Y17/T17)^(1/(Y$7-T$7))-1,0) -> 0.01294782
O18: Parking | T18: {=INDEX(Proforma!$J$24:$AL$24,MATCH(Summary!T$7,Proforma!$J$6:$AL$6))/1000} -> 0 | U18: {=INDEX(Proforma!$J$24:$AL$24,MATCH(Summary!U$7,Proforma!$J$6:$AL$6))/1000} -> 0 | V18: {=INDEX(Proforma!$J$24:$AL$24,MATCH(Summary!V$7,Proforma!$J$6:$AL$6))/1000} -> 0 | W18: {=INDEX(Proforma!$J$24:$AL$24,MATCH(Summary!W$7,Proforma!$J$6:$AL$6))/1000} -> 0 | X18: {=INDEX(Proforma!$J$24:$AL$24,MATCH(Summary!X$7,Proforma!$J$6:$AL$6))/1000} -> 0 | Y18: {=INDEX(Proforma!$J$24:$AL$24,MATCH(Summary!Y$7,Proforma!$J$6:$AL$6))/1000} -> 0 | AA18: =IFERROR(+(Y18/T18)^(1/(Y$7-T$7))-1,0) -> 0
B19: Total | C19: =SUM(C12,C8) -> #ERROR! | D19: =SUM(C8,C12)/C19 -> #ERROR! | E19: =C19/Model!$C$10 -> #ERROR! | F19: =C19/$I$19 -> #ERROR! | H19: Total | I19: =I17 -> #ERROR! | J19: =I19/Model!$C$10 -> #ERROR! | K19: =I19/Model!$C$14 -> #ERROR! | L19: =I19/$I$17 -> #ERROR! | O19: Misc. Income | T19: {=INDEX(Proforma!$J$25:$AL$25,MATCH(Summary!T$7,Proforma!$J$6:$AL$6))/1000} -> 150.32417 | U19: {=INDEX(Proforma!$J$25:$AL$25,MATCH(Summary!U$7,Proforma!$J$6:$AL$6))/1000} -> 157.58697 | V19: {=INDEX(Proforma!$J$25:$AL$25,MATCH(Summary!V$7,Proforma!$J$6:$AL$6))/1000} -> 160.31132 | W19: {=INDEX(Proforma!$J$25:$AL$25,MATCH(Summary!W$7,Proforma!$J$6:$AL$6))/1000} -> 160.31132 | X19: {=INDEX(Proforma!$J$25:$AL$25,MATCH(Summary!X$7,Proforma!$J$6:$AL$6))/1000} -> 160.31132 | Y19: {=INDEX(Proforma!$J$25:$AL$25,MATCH(Summary!Y$7,Proforma!$J$6:$AL$6))/1000} -> 160.31132 | AA19: =IFERROR(+(Y19/T19)^(1/(Y$7-T$7))-1,0) -> 0.01294782
O20: Resort Fees | T20: {=INDEX(Proforma!$J$26:$AL$26,MATCH(Summary!T$7,Proforma!$J$6:$AL$6))/1000} -> 1352.9175 | U20: {=INDEX(Proforma!$J$26:$AL$26,MATCH(Summary!U$7,Proforma!$J$6:$AL$6))/1000} -> 1418.2827 | V20: {=INDEX(Proforma!$J$26:$AL$26,MATCH(Summary!V$7,Proforma!$J$6:$AL$6))/1000} -> 1442.8018 | W20: {=INDEX(Proforma!$J$26:$AL$26,MATCH(Summary!W$7,Proforma!$J$6:$AL$6))/1000} -> 1442.8018 | X20: {=INDEX(Proforma!$J$26:$AL$26,MATCH(Summary!X$7,Proforma!$J$6:$AL$6))/1000} -> 1442.8018 | Y20: {=INDEX(Proforma!$J$26:$AL$26,MATCH(Summary!Y$7,Proforma!$J$6:$AL$6))/1000} -> 1442.8018 | AA20: =IFERROR(+(Y20/T20)^(1/(Y$7-T$7))-1,0) -> 0.01294782
I21: =ROUND(I19,-3) -> #ERROR! | O21: Meetings & Events | T21: {=INDEX(Proforma!$J$27:$AL$27,MATCH(Summary!T$7,Proforma!$J$6:$AL$6))/1000} -> 503.80784 | U21: {=INDEX(Proforma!$J$27:$AL$27,MATCH(Summary!U$7,Proforma!$J$6:$AL$6))/1000} -> 512.76596 | V21: {=INDEX(Proforma!$J$27:$AL$27,MATCH(Summary!V$7,Proforma!$J$6:$AL$6))/1000} -> 519.03543 | W21: {=INDEX(Proforma!$J$27:$AL$27,MATCH(Summary!W$7,Proforma!$J$6:$AL$6))/1000} -> 519.03543 | X21: {=INDEX(Proforma!$J$27:$AL$27,MATCH(Summary!X$7,Proforma!$J$6:$AL$6))/1000} -> 519.03543 | Y21: {=INDEX(Proforma!$J$27:$AL$27,MATCH(Summary!Y$7,Proforma!$J$6:$AL$6))/1000} -> 519.03543 | AA21: =IFERROR(+(Y21/T21)^(1/(Y$7-T$7))-1,0) -> 0.0059732139
O22: Rent & Other (8th Floor 1,685 SF) | T22: {=INDEX(Proforma!$J$28:$AL$28,MATCH(Summary!T$7,Proforma!$J$6:$AL$6))/1000} -> 23.664806 | U22: {=INDEX(Proforma!$J$28:$AL$28,MATCH(Summary!U$7,Proforma!$J$6:$AL$6))/1000} -> 24.37475 | V22: {=INDEX(Proforma!$J$28:$AL$28,MATCH(Summary!V$7,Proforma!$J$6:$AL$6))/1000} -> 25.105993 | W22: {=INDEX(Proforma!$J$28:$AL$28,MATCH(Summary!W$7,Proforma!$J$6:$AL$6))/1000} -> 25.105993 | X22: {=INDEX(Proforma!$J$28:$AL$28,MATCH(Summary!X$7,Proforma!$J$6:$AL$6))/1000} -> 25.105993 | Y22: {=INDEX(Proforma!$J$28:$AL$28,MATCH(Summary!Y$7,Proforma!$J$6:$AL$6))/1000} -> 25.105993 | AA22: =IFERROR(+(Y22/T22)^(1/(Y$7-T$7))-1,0) -> 0.011893695
I23: 253.80117 | O23: Total Revenue | R23: n/a | S23: n/a | T23: {=INDEX(Proforma!$J$29:$AL$29,MATCH(Summary!T$7,Proforma!$J$6:$AL$6))/1000} -> 16593.702 | U23: {=INDEX(Proforma!$J$29:$AL$29,MATCH(Summary!U$7,Proforma!$J$6:$AL$6))/1000} -> 17649.627 | V23: {=INDEX(Proforma!$J$29:$AL$29,MATCH(Summary!V$7,Proforma!$J$6:$AL$6))/1000} -> 18012.556 | W23: {=INDEX(Proforma!$J$29:$AL$29,MATCH(Summary!W$7,Proforma!$J$6:$AL$6))/1000} -> 18012.556 | X23: {=INDEX(Proforma!$J$29:$AL$29,MATCH(Summary!X$7,Proforma!$J$6:$AL$6))/1000} -> 18012.556 | Y23: {=INDEX(Proforma!$J$29:$AL$29,MATCH(Summary!Y$7,Proforma!$J$6:$AL$6))/1000} -> 18012.556 | AA23: =IFERROR(+(Y23/T23)^(1/(Y$7-T$7))-1,0) -> 0.01654454
T24: =SUM(T16:T22)=T23 -> TRUE | U24: =SUM(U16:U22)=U23 -> TRUE | V24: =SUM(V16:V22)=V23 -> TRUE | W24: =SUM(W16:W22)=W23 -> TRUE | X24: =SUM(X16:X22)=X23 -> TRUE | Y24: =SUM(Y16:Y22)=Y23 -> TRUE
O26: GOP | R26: n/a | S26: n/a | T26: {=INDEX(Proforma!$J$63:$AL$63,MATCH(Summary!T$7,Proforma!$J$6:$AL$6))/1000} -> 7452.9547 | U26: {=INDEX(Proforma!$J$63:$AL$63,MATCH(Summary!U$7,Proforma!$J$6:$AL$6))/1000} -> 8063.7005 | V26: {=INDEX(Proforma!$J$63:$AL$63,MATCH(Summary!V$7,Proforma!$J$6:$AL$6))/1000} -> 8258.1976 | W26: {=INDEX(Proforma!$J$63:$AL$63,MATCH(Summary!W$7,Proforma!$J$6:$AL$6))/1000} -> 8258.1976 | X26: {=INDEX(Proforma!$J$63:$AL$63,MATCH(Summary!X$7,Proforma!$J$6:$AL$6))/1000} -> 8258.1976 | Y26: {=INDEX(Proforma!$J$63:$AL$63,MATCH(Summary!Y$7,Proforma!$J$6:$AL$6))/1000} -> 8258.1976 | AA26: =IFERROR(+(Y26/T26)^(1/(Y$7-T$7))-1,0) -> 0.020731126
O27: EBITDA | R27: n/a | S27: n/a | T27: {=INDEX(Proforma!$J$77:$AL$77,MATCH(Summary!T$7,Proforma!$J$6:$AL$6))/1000} -> 5056.307 | U27: {=INDEX(Proforma!$J$77:$AL$77,MATCH(Summary!U$7,Proforma!$J$6:$AL$6))/1000} -> 5577.0147 | V27: {=INDEX(Proforma!$J$77:$AL$77,MATCH(Summary!V$7,Proforma!$J$6:$AL$6))/1000} -> 5702.3244 | W27: {=INDEX(Proforma!$J$77:$AL$77,MATCH(Summary!W$7,Proforma!$J$6:$AL$6))/1000} -> 5702.3244 | X27: {=INDEX(Proforma!$J$77:$AL$77,MATCH(Summary!X$7,Proforma!$J$6:$AL$6))/1000} -> 5702.3244 | Y27: {=INDEX(Proforma!$J$77:$AL$77,MATCH(Summary!Y$7,Proforma!$J$6:$AL$6))/1000} -> 5702.3244 | AA27: =IFERROR(+(Y27/T27)^(1/(Y$7-T$7))-1,0) -> 0.024338975
O28: FF&E Reserve | T28: {=INDEX(Proforma!$J$79:$AL$79,MATCH(Summary!T$7,Proforma!$J$6:$AL$6))/1000} -> 663.74809 | U28: {=INDEX(Proforma!$J$79:$AL$79,MATCH(Summary!U$7,Proforma!$J$6:$AL$6))/1000} -> 705.98507 | V28: {=INDEX(Proforma!$J$79:$AL$79,MATCH(Summary!V$7,Proforma!$J$6:$AL$6))/1000} -> 720.50225 | W28: {=INDEX(Proforma!$J$79:$AL$79,MATCH(Summary!W$7,Proforma!$J$6:$AL$6))/1000} -> 720.50225 | X28: {=INDEX(Proforma!$J$79:$AL$79,MATCH(Summary!X$7,Proforma!$J$6:$AL$6))/1000} -> 720.50225 | Y28: {=INDEX(Proforma!$J$79:$AL$79,MATCH(Summary!Y$7,Proforma!$J$6:$AL$6))/1000} -> 720.50225 | AA28: =IFERROR(+(Y28/T28)^(1/(Y$7-T$7))-1,0) -> 0.01654454
O30: NOI | R30: n/a | S30: n/a | T30: {=INDEX(Proforma!$J$81:$AL$81,MATCH(Summary!T$7,Proforma!$J$6:$AL$6))/1000} -> 4392.5589 | U30: {=INDEX(Proforma!$J$81:$AL$81,MATCH(Summary!U$7,Proforma!$J$6:$AL$6))/1000} -> 4871.0297 | V30: {=INDEX(Proforma!$J$81:$AL$81,MATCH(Summary!V$7,Proforma!$J$6:$AL$6))/1000} -> 4981.8222 | W30: {=INDEX(Proforma!$J$81:$AL$81,MATCH(Summary!W$7,Proforma!$J$6:$AL$6))/1000} -> 4981.8222 | X30: {=INDEX(Proforma!$J$81:$AL$81,MATCH(Summary!X$7,Proforma!$J$6:$AL$6))/1000} -> 4981.8222 | Y30: {=INDEX(Proforma!$J$81:$AL$81,MATCH(Summary!Y$7,Proforma!$J$6:$AL$6))/1000} -> 4981.8222 | AA30: =IFERROR(+(Y30/T30)^(1/(Y$7-T$7))-1,0) -> 0.025496364
O31: Yield-On-Cost | T31: =+(T30*1000)/Model!$N$14 -> 0.10317789 | U31: =+(U30*1000)/Model!$N$14 -> 0.1144168 | V31: =+(V30*1000)/Model!$N$14 -> 0.11701924 | W31: =+(W30*1000)/Model!$N$14 -> 0.11701924 | X31: =+(X30*1000)/Model!$N$14 -> 0.11701924 | Y31: =+(Y30*1000)/Model!$N$14 -> 0.11701924

Sheet Model
B2: Property Overview | G2: Senior Loan Financing Assumptions | K2: Transaction Uses
B3: Name | C3: Kimpton Anglers | G3: Month Funding | I3: =O27 -> 0 | N3: Amount | O3: Per Key | P3: %
B4: Type | C4: Hotel | G4: Start Date | I4: =$P$27 -> 45930 | K4: Hotel Purchase Price | N4: =$C$21 -> 36436802 | O4: =N4/$C$10 -> 276036.38 | P4: =N4/$N$14 -> 0.85587291
B5: Location | C5: Miami, FL | G5: Term | I5: =4*12 -> 48 | K5: DD Closing Costs | M5: =$I$24 -> 0.02 | N5: =M5*N4 -> 728736.03 | O5: =N5/$C$10 -> 5520.7275 | P5: =N5/$N$14 -> 0.017117458
B6: Labor | C6: Non-Union | G6: Maturity Date | I6: =EOMONTH(I4,I5) -> 47391 | K6: Working Capital First Year | N6: =M6*N5 -> 0 | O6: =N6/$C$10 -> 0 | P6: =N6/$N$14 -> 0
B7: Title | C7: Fee-Simple | G7: Senior Acq. Cost | I7: =($N$4+$N$5+$N$6+$N$7+$N$10+$N$12) -> 42392979 | K7: Renovation Expense | N7: =E43 -> 4943400 | O7: =N7/$C$10 -> 37450 | P7: =N7/$N$14 -> 0.11611673
B8: Year Built | C8: 2027 | G8: LTC Amount | I8: =I9*I7 -> 27555436 | K8: Senior Loan Total Costs | N8: =SUM(N9) -> 463740 | O8: =N8/$C$10 -> 3513.1818 | P8: =N8/$N$14 -> 0.010892902
B9: Pre-Renovation Keys | C9: 132 | G9: LTC | I9: 0.65 | K9: Orgination Fee | M9: =$I$24 -> 0.02 | N9: =M9*$I$16 -> 463740 | O9: =N9/$C$10 -> 3513.1818 | P9: =N9/$N$14 -> 0.010892902
B10: Post-Renovation Keys | C10: 132 | G10: LTV Amount | I10: =$C$21*I11 -> 23683921 | K10: Tax Reserve - 6 Months of Year 1 | N10: =Proforma!O70/12*6 -> 284041.1 | O10: =N10/$C$10 -> 2151.8265 | P10: =N10/$N$14 -> 0.0066719107
B11: Pre-Renovation Floors | C11: 1 | G11: LTV Amount | I11: 0.65 | K11: Insurance Reserve - 3 Months of Year 1 | N11: =Proforma!O71/12*3 -> 299057.14 | O11: =N11/$C$10 -> 2265.5844 | P11: =N11/$N$14 -> 0.0070246262
B12: Post-Renovation Floors | C12: 5 | G12: DY Amount | I12: =I14/I15 -> 23187056 | K12: Capex Reserve | N12: 0 | O12: =N12/$C$10 -> 0 | P12: =N12/$N$14 -> 0
B13: Pre-Renovation Total SF | C13: 0 | G13: DY Date | I13: =C20 -> 45930 | K13: Senior Loan Cap. Interest Reserve | N13: 0 | O13: =N13/$C$10 -> 0 | P13: =N13/$N$14 -> 0 | Q13: ='Debt & Refi'!E23 -> 980000
B14: Post-Renovation Total SF | C14: 140387 | G14: DY NOI | I14: {=INDEX(Proforma!$AR$83:$DK$83,MATCH($I$13,Proforma!$AR$25:$DK$25))} -> 2550576.1 | K14: Total Uses | N14: =SUM(N4:N7,N8,N13) -> 42572678 | O14: =N14/$C$10 -> 322520.28 | P14: =SUM(P4:P7,P8,P13) -> 1
G15: DY % | I15: 0.11
B16: Entry Valuation | G16: Loan Amount | I16: =ROUND(MIN(I10,I12),-3) -> 23187000 | K16: Transaction Sources
B17: NOI | C17: 7620000 | G17: Variable (1) or Fixed (2) | I17: 1 | N17: Amount | O17: Per Key | P17: %
B18: Entry Cap Rate | C18: 0.07 | G18: Spread over SOFR | I18: 0.035 | K18: Debt | N18: =SUM(N19) -> 23187000 | O18: =N18/$C$10 -> 175659.09 | P18: =N18/$N$23 -> 0.54464509
B19: 2025 Run-Rate NOI | C19: {=INDEX(Proforma!$AR$83:$DK$83,MATCH($C$20,Proforma!$AR$25:$DK$25))} -> 2550576.1 | G19: SOFR Rate | I19: {=INDEX('1-month SOFR - UST '!$Q$9:$Q$1048576,MATCH(I$4,'1-month SOFR - UST '!$O$9:$O$1048576,0))} -> 0.0415518 | K19: Senior Loan | M19: =I18 -> 0.035 | N19: =I16 -> 23187000 | O19: =N19/$C$10 -> 175659.09 | P19: =N19/$N$23 -> 0.54464509
B20: FTM Date | C20: =I4 -> 45930 | G20: SOFR Floor | I20: 0 | K20: Tax Incentive Financing | N20: 0 | O20: =N20/$C$10 -> 0 | P20: =N20/$N$23 -> 0
B21: Hotel Purchase Price | C21: =C19/C18 -> 36436802 | G21: SOFR Ceiling | I21: 1 | K21: Key Money | N21: 0 | O21: =N21/$C$10 -> 0 | P21: =N21/$N$23 -> 0
B22: Per Key | C22: =$C$21/$C$9 -> 276036.38 | G22: Interest Only Period | I22: =4*12 -> 48 | K22: Equity | N22: =N14-SUM(N18,N20,N21) -> 19385678 | O22: =N22/$C$10 -> 146861.19 | P22: =N22/$N$23 -> 0.45535491
G23: Amortization Period | I23: 30 | K23: Total Sources | N23: =SUM(N18,N20:N22) -> 42572678 | O23: =N23/$C$10 -> 322520.28 | P23: =+N23/$N$23 -> 1
B24: Exit Valuation | G24: Origination Fee | I24: 0.02 | N24: =SUM(N18,N20:N22) -> 42572678
B25: Exit Month | C25: =O37 -> 52 | G25: Interest Only | I25: 1 | K25: Transaction Timeline
B26: Exit Date | C26: =$P$37 -> 47514 | N26: Start | O26: Duration | P26: Finish
B27: Fwd. 12 Months NOI | C27: =N39 -> 4440847.5 | G27: Senior Loan Refinancing Metrics | K27: Hotel Purchase | N27: 45930 | O27: 0 | P27: =+EOMONTH(N27,O27) -> 45930
B28: Exit Cap Rate | C28: 0.065 | G28: Month Funding | I28: =O29 -> 30 | K28: Senior Loan Interest-Only Period | N28: =P27 -> 45930 | O28: =I22 -> 48 | P28: =+EOMONTH(N28,O28) -> 47391
B29: Gross Exit Value | C29: =$C$27/$C$28 -> 68320731 | G29: Start Date | I29: =$P$35 -> 46843 | K29: Senior Loan Perm Loan Payoff | N29: =N27 -> 45930 | O29: =DATEDIF(N29,P29,"M") -> 30 | P29: =P35 -> 46843
B30: Per Key | C30: =$C$29/$C$10 -> 517581.3 | G30: Refi Term | I30: 360 | K30: Acq. To Renovation | N30: =P27 -> 45930 | P30: =+EOMONTH(N30,O30-1) -> 45900
B31: Exit Sales Cost | C31: 0.015 | G31: Maturity Date | I31: =EOMONTH(I29,I30) -> 57800 | K31: Renovation | N31: 46053 | O31: 8 | P31: =+EOMONTH(N31,O31-1) -> 46265
B32: Transfer Tax | C32: 0.5 | G32: LTV Amount | I32: =$I$33*O39 -> 51240548 | K32: Completed Renovation | N32: =+EOMONTH(P31,0) -> 46265 | O32: 0 | P32: =+EOMONTH(N32,O32) -> 46265
B33: Hold Years | C33: =$O$37/12 -> 4.3333333 | G33: LTV | I33: 0.75 | K33: Receive Key Money | N33: =+EOMONTH(P32,0) -> 46265 | O33: 2 | P33: =+EOMONTH(N33,O33) -> 46326
G34: Loan Proceeds | I34: =MIN('Debt & Refi'!$E$34:$E$36) -> 40371341 | K34: Ramp-Up Period | N34: =P32 -> 46265 | O34: 12 | P34: =+EOMONTH(N34,O34) -> 46630
G35: Loan Payoff | I35: =-I34 -> -40371341 | K35: Senior Loan Refi | N35: =+EOMONTH(P34,3) -> 46721 | O35: 4 | P35: =+EOMONTH(N35,O35) -> 46843
B36: Renovation Budget | G36: Cash Pulled Out | I36: =SUM(I34:I35) -> 0 | K36: Disposition After Refi | N36: =+EOMONTH(P35,0)+1 -> 46844 | O36: 8 | P36: =+EOMONTH(N36,O36) -> 47118
B37: =35000*C9 -> 4620000 | C37: Per Key | D37: Per SF | E37: Total | G37: Variable (1) or Fixed (2) | I37: 1 | K37: Investment Hold Period | N37: =N27 -> 45930 | O37: =DATEDIF(N37,P37,"M") -> 52 | P37: 47514
B38: Renovation | C38: =E38/$C$10 -> 35000 | D38: =E38/$C$14 -> 32.90903 | E38: =SUM(E39:E41) -> 4620000 | G38: Spread over SOFR | I38: 0.04 | K38: Practical Completion (FTM NOI, Value) | N38: {=INDEX(Proforma!$AR$83:$DK$83,MATCH(Model!$P$38,Proforma!$AR$25:$DK$25))} -> 4440847.5 | O38: {=INDEX(Proforma!$AR$83:$DK$83,MATCH(Model!$P$38,Proforma!$AR$25:$DK$25))/$C$28} -> 68320731 | P38: =EOMONTH(P27,36) -> 47026
B39: Hard Costs (75%) | C39: =E39/$C$10 -> 26250 | D39: =E39/$C$14 -> 24.681773 | E39: =75%*$B$37 -> 3465000 | G39: Interest Rate Type | I39: Floating | K39: Stabilized (FTM NOI, Value) | N39: {=INDEX(Proforma!$AR$83:$DK$83,MATCH(Model!$P$39,Proforma!$AR$25:$DK$25))} -> 4440847.5 | O39: =C29 -> 68320731 | P39: 47026
B40: Soft Costs (20%) | C40: =E40/$C$10 -> 7000 | D40: =E40/$C$14 -> 6.581806 | E40: =20%*$B$37 -> 924000 | G40: SOFR Rate | I40: {=INDEX('1-month SOFR - UST '!$Q$9:$Q$1048576,MATCH(I$29,'1-month SOFR - UST '!$O$9:$O$1048576,0))} -> 0.0327905
B41: Professional Fees (5%) | C41: =E41/$C$10 -> 1750 | D41: =E41/$C$14 -> 1.6454515 | E41: =5%*$B$37 -> 231000 | G41: SOFR Floor | I41: 0
B42: Contingency (7%) | C42: =E42/$C$10 -> 2450 | D42: =E42/$C$14 -> 2.3036321 | E42: =7%*$B$37 -> 323400 | G42: SOFR Ceiling | I42: 1
C43: =E43/$C$10 -> 37450 | D43: =E43/$C$14 -> 35.212662 | E43: =SUM(E38,E42) -> 4943400 | G43: Interest Only Period | I43: =4*12 -> 48
C44: =B37/C10 -> 35000 | D44: =B37/C14 -> 32.90903 | E44: =E42/E43 -> 0.065420561 | G44: Amortization Period | I44: 30
B45: Valuation Assumptions | G45: Origination Fee | I45: 0.01
B46: Total Development Cost | C46: =SUM(N4:N8) -> 42572678 | G46: Interest Only | I46: 1
B47: Per Key | C47: =C10 -> 132
B48: Investment Hold (years) | C48: =C33 -> 4.3333333
B49: Stabilized NOI FWD 12 Months | C49: =N39 -> 4440847.5
B50: Exit Cap Rate | C50: =C28 -> 0.065
B51: Sale Price | C51: =C29 -> 68320731
B52: Per Key | C52: =C30 -> 517581.3
B53: Disposition Fees | C53: =C51*$C$31 -> 1024811
B68: Cash Flows
C69: Year | D69: =YEAR($N$27) -> 2025 | E69: =D69+1 -> 2026 | F69: =E69+1 -> 2027 | G69: =F69+1 -> 2028 | H69: =G69+1 -> 2029 | I69: =H69+1 -> 2030 | J69: =I69+1 -> 2031 | K69: =J69+1 -> 2032 | L69: =K69+1 -> 2033 | ... O69: =N69+1 -> 2036 | Q69: Year | S69: =YEAR(S71) -> 2025 | T69: =YEAR(T71) -> 2025 | U69: =YEAR(U71) -> 2025 | V69: =YEAR(V71) -> 2025 | W69: =YEAR(W71) -> 2026 | X69: =YEAR(X71) -> 2026 | Y69: =YEAR(Y71) -> 2026 | Z69: =YEAR(Z71) -> 2026 | ... EU69: =YEAR(EU71) -> 2036
C70: Year # | D70: 0 | E70: =D70+1 -> 1 | F70: =E70+1 -> 2 | G70: =F70+1 -> 3 | H70: =G70+1 -> 4 | I70: =H70+1 -> 5 | J70: =I70+1 -> 6 | K70: =J70+1 -> 7 | L70: =K70+1 -> 8 | ... O70: =N70+1 -> 11 | Q70: Month | S70: 0 | T70: =S70+1 -> 1 | U70: =T70+1 -> 2 | V70: =U70+1 -> 3 | W70: =V70+1 -> 4 | X70: =W70+1 -> 5 | Y70: =X70+1 -> 6 | Z70: =Y70+1 -> 7 | AA70: =Z70+1 -> 8 | ... EU70: =ET70+1 -> 132
C71: Date | D71: 46022 | E71: =EOMONTH(D71,12) -> 46387 | F71: =EOMONTH(E71,12) -> 46752 | G71: =EOMONTH(F71,12) -> 47118 | H71: =EOMONTH(G71,12) -> 47483 | I71: =EOMONTH(H71,12) -> 47848 | J71: =EOMONTH(I71,12) -> 48213 | K71: =EOMONTH(J71,12) -> 48579 | L71: =EOMONTH(K71,12) -> 48944 | ... O71: =EOMONTH(N71,12) -> 50040 | Q71: Date | S71: =$N$27 -> 45930 | T71: =EOMONTH(S71,1) -> 45961 | U71: =EOMONTH(T71,1) -> 45991 | V71: =EOMONTH(U71,1) -> 46022 | W71: =EOMONTH(V71,1) -> 46053 | X71: =EOMONTH(W71,1) -> 46081 | Y71: =EOMONTH(X71,1) -> 46112 | Z71: =EOMONTH(Y71,1) -> 46142 | AA71: =EOMONTH(Z71,1) -> 46173 | ... EU71: =EOMONTH(ET71,1) -> 49948
B72: NOI | C72: =SUM(D72:O72) -> 17264784 | D72: =SUMIF($S$69:$EU$69,D$69,$S72:$EU72) -> 1013045.7 | E72: =SUMIF($S$69:$EU$69,E$69,$S72:$EU72) -> 3025953 | F72: =SUMIF($S$69:$EU$69,F$69,$S72:$EU72) -> 3995804.3 | G72: =SUMIF($S$69:$EU$69,G$69,$S72:$EU72) -> 4253257.7 | H72: =SUMIF($S$69:$EU$69,H$69,$S72:$EU72) -> 4594429.2 | I72: =SUMIF($S$69:$EU$69,I$69,$S72:$EU72) -> 382294.37 | J72: =SUMIF($S$69:$EU$69,J$69,$S72:$EU72) -> 0 | K72: =SUMIF($S$69:$EU$69,K$69,$S72:$EU72) -> 0 | ... O72: =SUMIF($S$69:$EU$69,O$69,$S72:$EU72) -> 0 | Q72: =B72 -> NOI | R72: =SUM(S72:EU72) -> 17264784 | S72: {=IFERROR(IF(S71<=$P$37,INDEX(Proforma!$AR$81:$DK$81,MATCH(S71,Proforma!$AR$25:$DK$25)),0),0)} -> 242326.76 | T72: {=IFERROR(IF(T71<=$P$37,INDEX(Proforma!$AR$81:$DK$81,MATCH(T71,Proforma!$AR$25:$DK$25)),0),0)} -> 271587.81 | U72: {=IFERROR(IF(U71<=$P$37,INDEX(Proforma!$AR$81:$DK$81,MATCH(U71,Proforma!$AR$25:$DK$25)),0),0)} -> 256096.89 | V72: {=IFERROR(IF(V71<=$P$37,INDEX(Proforma!$AR$81:$DK$81,MATCH(V71,Proforma!$AR$25:$DK$25)),0),0)} -> 243034.26 | W72: {=IFERROR(IF(W71<=$P$37,INDEX(Proforma!$AR$81:$DK$81,MATCH(W71,Proforma!$AR$25:$DK$25)),0),0)} -> 188446.96 | X72: {=IFERROR(IF(X71<=$P$37,INDEX(Proforma!$AR$81:$DK$81,MATCH(X71,Proforma!$AR$25:$DK$25)),0),0)} -> 147515.03 | Y72: {=IFERROR(IF(Y71<=$P$37,INDEX(Proforma!$AR$81:$DK$81,MATCH(Y71,Proforma!$AR$25:$DK$25)),0),0)} -> 148004.36 | Z72: {=IFERROR(IF(Z71<=$P$37,INDEX(Proforma!$AR$81:$DK$81,MATCH(Z71,Proforma!$AR$25:$DK$25)),0),0)} -> 136916.76 | ... EU72: {=IFERROR(IF(EU71<=$P$37,INDEX(Proforma!$AR$81:$DK$81,MATCH(EU71,Proforma!$AR$25:$DK$25)),0),0)} -> 0 | EW72: x
B73: Hotel Purchase Price | C73: =SUM(D73:O73) -> -36436802 | D73: =SUMIF($S$69:$EU$69,D$69,$S73:$EU73) -> -36436802 | E73: =SUMIF($S$69:$EU$69,E$69,$S73:$EU73) -> 0 | F73: =SUMIF($S$69:$EU$69,F$69,$S73:$EU73) -> 0 | G73: =SUMIF($S$69:$EU$69,G$69,$S73:$EU73) -> 0 | H73: =SUMIF($S$69:$EU$69,H$69,$S73:$EU73) -> 0 | I73: =SUMIF($S$69:$EU$69,I$69,$S73:$EU73) -> 0 | J73: =SUMIF($S$69:$EU$69,J$69,$S73:$EU73) -> 0 | K73: =SUMIF($S$69:$EU$69,K$69,$S73:$EU73) -> 0 | ... O73: =SUMIF($S$69:$EU$69,O$69,$S73:$EU73) -> 0 | Q73: =B73 -> Hotel Purchase Price | R73: =SUM(S73:EU73) -> -36436802 | S73: =-IF(S$71=$P$27,$C$21,0) -> -36436802 | T73: =-IF(T$71=$P$27,$C$21,0) -> 0 | U73: =-IF(U$71=$P$27,$C$21,0) -> 0 | V73: =-IF(V$71=$P$27,$C$21,0) -> 0 | W73: =-IF(W$71=$P$27,$C$21,0) -> 0 | X73: =-IF(X$71=$P$27,$C$21,0) -> 0 | Y73: =-IF(Y$71=$P$27,$C$21,0) -> 0 | Z73: =-IF(Z$71=$P$27,$C$21,0) -> 0 | ... EU73: =-IF(EU$71=$P$27,$C$21,0) -> 0 | EW73: x
B74: Working Capital | C74: =SUM(D74:O74) -> 0 | D74: =SUMIF($S$69:$EU$69,D$69,$S74:$EU74) -> 0 | E74: =SUMIF($S$69:$EU$69,E$69,$S74:$EU74) -> 0 | F74: =SUMIF($S$69:$EU$69,F$69,$S74:$EU74) -> 0 | G74: =SUMIF($S$69:$EU$69,G$69,$S74:$EU74) -> 0 | H74: =SUMIF($S$69:$EU$69,H$69,$S74:$EU74) -> 0 | I74: =SUMIF($S$69:$EU$69,I$69,$S74:$EU74) -> 0 | J74: =SUMIF($S$69:$EU$69,J$69,$S74:$EU74) -> 0 | K74: =SUMIF($S$69:$EU$69,K$69,$S74:$EU74) -> 0 | ... O74: =SUMIF($S$69:$EU$69,O$69,$S74:$EU74) -> 0 | Q74: =B74 -> Working Capital | R74: =SUM(S74:EU74) -> 0 | S74: =-IF(S$71=$P$32,$N$6,0) -> 0 | T74: =-IF(T$71=$P$32,$N$6,0) -> 0 | U74: =-IF(U$71=$P$32,$N$6,0) -> 0 | V74: =-IF(V$71=$P$32,$N$6,0) -> 0 | W74: =-IF(W$71=$P$32,$N$6,0) -> 0 | X74: =-IF(X$71=$P$32,$N$6,0) -> 0 | Y74: =-IF(Y$71=$P$32,$N$6,0) -> 0 | Z74: =-IF(Z$71=$P$32,$N$6,0) -> 0 | ... EU74: =-IF(EU$71=$P$32,$N$6,0) -> 0 | EW74: x
B75: Tax Reserve | C75: =SUM(D75:O75) -> -284041.1 | D75: =SUMIF($S$69:$EU$69,D$69,$S75:$EU75) -> -284041.1 | E75: =SUMIF($S$69:$EU$69,E$69,$S75:$EU75) -> 0 | F75: =SUMIF($S$69:$EU$69,F$69,$S75:$EU75) -> 0 | G75: =SUMIF($S$69:$EU$69,G$69,$S75:$EU75) -> 0 | H75: =SUMIF($S$69:$EU$69,H$69,$S75:$EU75) -> 0 | I75: =SUMIF($S$69:$EU$69,I$69,$S75:$EU75) -> 0 | J75: =SUMIF($S$69:$EU$69,J$69,$S75:$EU75) -> 0 | K75: =SUMIF($S$69:$EU$69,K$69,$S75:$EU75) -> 0 | ... O75: =SUMIF($S$69:$EU$69,O$69,$S75:$EU75) -> 0 | Q75: =B75 -> Tax Reserve | R75: =SUM(S75:EU75) -> -284041.1 | S75: =-IF(S$71=$I$4,$N$10,0) -> -284041.1 | T75: =-IF(T$71=$I$4,$N$10,0) -> 0 | U75: =-IF(U$71=$I$4,$N$10,0) -> 0 | V75: =-IF(V$71=$I$4,$N$10,0) -> 0 | W75: =-IF(W$71=$I$4,$N$10,0) -> 0 | X75: =-IF(X$71=$I$4,$N$10,0) -> 0 | Y75: =-IF(Y$71=$I$4,$N$10,0) -> 0 | Z75: =-IF(Z$71=$I$4,$N$10,0) -> 0 | ... EU75: =-IF(EU$71=$I$4,$N$10,0) -> 0 | EW75: x
B76: Insurance Reserve | C76: =SUM(D76:O76) -> -299057.14 | D76: =SUMIF($S$69:$EU$69,D$69,$S76:$EU76) -> -299057.14 | E76: =SUMIF($S$69:$EU$69,E$69,$S76:$EU76) -> 0 | F76: =SUMIF($S$69:$EU$69,F$69,$S76:$EU76) -> 0 | G76: =SUMIF($S$69:$EU$69,G$69,$S76:$EU76) -> 0 | H76: =SUMIF($S$69:$EU$69,H$69,$S76:$EU76) -> 0 | I76: =SUMIF($S$69:$EU$69,I$69,$S76:$EU76) -> 0 | J76: =SUMIF($S$69:$EU$69,J$69,$S76:$EU76) -> 0 | K76: =SUMIF($S$69:$EU$69,K$69,$S76:$EU76) -> 0 | ... O76: =SUMIF($S$69:$EU$69,O$69,$S76:$EU76) -> 0 | Q76: =B76 -> Insurance Reserve | R76: =SUM(S76:EU76) -> -299057.14 | S76: =-IF(S$71=$I$4,$N$11,0) -> -299057.14 | T76: =-IF(T$71=$I$4,$N$11,0) -> 0 | U76: =-IF(U$71=$I$4,$N$11,0) -> 0 | V76: =-IF(V$71=$I$4,$N$11,0) -> 0 | W76: =-IF(W$71=$I$4,$N$11,0) -> 0 | X76: =-IF(X$71=$I$4,$N$11,0) -> 0 | Y76: =-IF(Y$71=$I$4,$N$11,0) -> 0 | Z76: =-IF(Z$71=$I$4,$N$11,0) -> 0 | ... EU76: =-IF(EU$71=$I$4,$N$11,0) -> 0 | EW76: x
B77: Capex Reserve | C77: =SUM(D77:O77) -> 0 | D77: =SUMIF($S$69:$EU$69,D$69,$S77:$EU77) -> 0 | E77: =SUMIF($S$69:$EU$69,E$69,$S77:$EU77) -> 0 | F77: =SUMIF($S$69:$EU$69,F$69,$S77:$EU77) -> 0 | G77: =SUMIF($S$69:$EU$69,G$69,$S77:$EU77) -> 0 | H77: =SUMIF($S$69:$EU$69,H$69,$S77:$EU77) -> 0 | I77: =SUMIF($S$69:$EU$69,I$69,$S77:$EU77) -> 0 | J77: =SUMIF($S$69:$EU$69,J$69,$S77:$EU77) -> 0 | K77: =SUMIF($S$69:$EU$69,K$69,$S77:$EU77) -> 0 | ... O77: =SUMIF($S$69:$EU$69,O$69,$S77:$EU77) -> 0 | Q77: =B77 -> Capex Reserve | R77: =SUM(S77:EU77) -> 0 | S77: =-IF(S$71=$I$4,$N$12,0) -> 0 | T77: =-IF(T$71=$I$4,$N$12,0) -> 0 | U77: =-IF(U$71=$I$4,$N$12,0) -> 0 | V77: =-IF(V$71=$I$4,$N$12,0) -> 0 | W77: =-IF(W$71=$I$4,$N$12,0) -> 0 | X77: =-IF(X$71=$I$4,$N$12,0) -> 0 | Y77: =-IF(Y$71=$I$4,$N$12,0) -> 0 | Z77: =-IF(Z$71=$I$4,$N$12,0) -> 0 | ... EU77: =-IF(EU$71=$I$4,$N$12,0) -> 0 | EW77: x
B78: Renovation | C78: =SUM(D78:O78) -> -4943400 | D78: =SUMIF($S$69:$EU$69,D$69,$S78:$EU78) -> 0 | E78: =SUMIF($S$69:$EU$69,E$69,$S78:$EU78) -> -4943400 | F78: =SUMIF($S$69:$EU$69,F$69,$S78:$EU78) -> 0 | G78: =SUMIF($S$69:$EU$69,G$69,$S78:$EU78) -> 0 | H78: =SUMIF($S$69:$EU$69,H$69,$S78:$EU78) -> 0 | I78: =SUMIF($S$69:$EU$69,I$69,$S78:$EU78) -> 0 | J78: =SUMIF($S$69:$EU$69,J$69,$S78:$EU78) -> 0 | K78: =SUMIF($S$69:$EU$69,K$69,$S78:$EU78) -> 0 | ... O78: =SUMIF($S$69:$EU$69,O$69,$S78:$EU78) -> 0 | Q78: =B78 -> Renovation | R78: =SUM(S78:EU78) -> -4943400 | S78: =-IF(AND(S71>=$N$31,S71<=$P$31),$E$43/$O$31,0) -> 0 | T78: =-IF(AND(T71>=$N$31,T71<=$P$31),$E$43/$O$31,0) -> 0 | U78: =-IF(AND(U71>=$N$31,U71<=$P$31),$E$43/$O$31,0) -> 0 | V78: =-IF(AND(V71>=$N$31,V71<=$P$31),$E$43/$O$31,0) -> 0 | W78: =-IF(AND(W71>=$N$31,W71<=$P$31),$E$43/$O$31,0) -> -617925 | X78: =-IF(AND(X71>=$N$31,X71<=$P$31),$E$43/$O$31,0) -> -617925 | Y78: =-IF(AND(Y71>=$N$31,Y71<=$P$31),$E$43/$O$31,0) -> -617925 | Z78: =-IF(AND(Z71>=$N$31,Z71<=$P$31),$E$43/$O$31,0) -> -617925 | ... EU78: =-IF(AND(EU71>=$N$31,EU71<=$P$31),$E$43/$O$31,0) -> 0 | EW78: x
B79: Acq. Closing Costs | C79: =SUM(D79:O79) -> -728736.03 | D79: =SUMIF($S$69:$EU$69,D$69,$S79:$EU79) -> -728736.03 | E79: =SUMIF($S$69:$EU$69,E$69,$S79:$EU79) -> 0 | F79: =SUMIF($S$69:$EU$69,F$69,$S79:$EU79) -> 0 | G79: =SUMIF($S$69:$EU$69,G$69,$S79:$EU79) -> 0 | H79: =SUMIF($S$69:$EU$69,H$69,$S79:$EU79) -> 0 | I79: =SUMIF($S$69:$EU$69,I$69,$S79:$EU79) -> 0 | J79: =SUMIF($S$69:$EU$69,J$69,$S79:$EU79) -> 0 | K79: =SUMIF($S$69:$EU$69,K$69,$S79:$EU79) -> 0 | ... O79: =SUMIF($S$69:$EU$69,O$69,$S79:$EU79) -> 0 | Q79: =B79 -> Acq. Closing Costs | R79: =SUM(S79:EU79) -> -728736.03 | S79: =-IF(S73<0,$N$5,0) -> -728736.03 | T79: =-IF(T73<0,$N$5,0) -> 0 | U79: =-IF(U73<0,$N$5,0) -> 0 | V79: =-IF(V73<0,$N$5,0) -> 0 | W79: =-IF(W73<0,$N$5,0) -> 0 | X79: =-IF(X73<0,$N$5,0) -> 0 | Y79: =-IF(Y73<0,$N$5,0) -> 0 | Z79: =-IF(Z73<0,$N$5,0) -> 0 | ... EU79: =-IF(EU73<0,$N$5,0) -> 0 | EW79: x
B80: Tax Incentive Financing | C80: =SUM(D80:O80) -> 0 | D80: =SUMIF($S$69:$EU$69,D$69,$S80:$EU80) -> 0 | E80: =SUMIF($S$69:$EU$69,E$69,$S80:$EU80) -> 0 | F80: =SUMIF($S$69:$EU$69,F$69,$S80:$EU80) -> 0 | G80: =SUMIF($S$69:$EU$69,G$69,$S80:$EU80) -> 0 | H80: =SUMIF($S$69:$EU$69,H$69,$S80:$EU80) -> 0 | I80: =SUMIF($S$69:$EU$69,I$69,$S80:$EU80) -> 0 | J80: =SUMIF($S$69:$EU$69,J$69,$S80:$EU80) -> 0 | K80: =SUMIF($S$69:$EU$69,K$69,$S80:$EU80) -> 0 | ... O80: =SUMIF($S$69:$EU$69,O$69,$S80:$EU80) -> 0 | Q80: =B80 -> Tax Incentive Financing | R80: =SUM(S80:EU80) -> 0 | S80: =IF(S$71=$P$27,$N$20,0) -> 0 | T80: =IF(T$71=$P$27,$N$20,0) -> 0 | U80: =IF(U$71=$P$27,$N$20,0) -> 0 | V80: =IF(V$71=$P$27,$N$20,0) -> 0 | W80: =IF(W$71=$P$27,$N$20,0) -> 0 | X80: =IF(X$71=$P$27,$N$20,0) -> 0 | Y80: =IF(Y$71=$P$27,$N$20,0) -> 0 | Z80: =IF(Z$71=$P$27,$N$20,0) -> 0 | ... EU80: =IF(EU$71=$P$27,$N$20,0) -> 0 | EW80: x
B81: Key Money | C81: =SUM(D81:O81) -> 0 | D81: =SUMIF($S$69:$EU$69,D$69,$S81:$EU81) -> 0 | E81: =SUMIF($S$69:$EU$69,E$69,$S81:$EU81) -> 0 | F81: =SUMIF($S$69:$EU$69,F$69,$S81:$EU81) -> 0 | G81: =SUMIF($S$69:$EU$69,G$69,$S81:$EU81) -> 0 | H81: =SUMIF($S$69:$EU$69,H$69,$S81:$EU81) -> 0 | I81: =SUMIF($S$69:$EU$69,I$69,$S81:$EU81) -> 0 | J81: =SUMIF($S$69:$EU$69,J$69,$S81:$EU81) -> 0 | K81: =SUMIF($S$69:$EU$69,K$69,$S81:$EU81) -> 0 | ... O81: =SUMIF($S$69:$EU$69,O$69,$S81:$EU81) -> 0 | Q81: =B81 -> Key Money | R81: =SUM(S81:EU81) -> 0 | S81: =IF(S$71=$P$33,$N$21,0) -> 0 | T81: =IF(T$71=$P$33,$N$21,0) -> 0 | U81: =IF(U$71=$P$33,$N$21,0) -> 0 | V81: =IF(V$71=$P$33,$N$21,0) -> 0 | W81: =IF(W$71=$P$33,$N$21,0) -> 0 | X81: =IF(X$71=$P$33,$N$21,0) -> 0 | Y81: =IF(Y$71=$P$33,$N$21,0) -> 0 | Z81: =IF(Z$71=$P$33,$N$21,0) -> 0 | ... EU81: =IF(EU$71=$P$33,$N$21,0) -> 0 | EW81: x
B82: Sales Proceeds | C82: =SUM(D82:O82) -> 68320731 | D82: =SUMIF($S$69:$EU$69,D$69,$S82:$EU82) -> 0 | E82: =SUMIF($S$69:$EU$69,E$69,$S82:$EU82) -> 0 | F82: =SUMIF($S$69:$EU$69,F$69,$S82:$EU82) -> 0 | G82: =SUMIF($S$69:$EU$69,G$69,$S82:$EU82) -> 0 | H82: =SUMIF($S$69:$EU$69,H$69,$S82:$EU82) -> 0 | I82: =SUMIF($S$69:$EU$69,I$69,$S82:$EU82) -> 68320731 | J82: =SUMIF($S$69:$EU$69,J$69,$S82:$EU82) -> 0 | K82: =SUMIF($S$69:$EU$69,K$69,$S82:$EU82) -> 0 | ... O82: =SUMIF($S$69:$EU$69,O$69,$S82:$EU82) -> 0 | Q82: =B82 -> Sales Proceeds | R82: =SUM(S82:EU82) -> 68320731 | S82: =IF(S71=$P$37,$C$29,0) -> 0 | T82: =IF(T71=$P$37,$C$29,0) -> 0 | U82: =IF(U71=$P$37,$C$29,0) -> 0 | V82: =IF(V71=$P$37,$C$29,0) -> 0 | W82: =IF(W71=$P$37,$C$29,0) -> 0 | X82: =IF(X71=$P$37,$C$29,0) -> 0 | Y82: =IF(Y71=$P$37,$C$29,0) -> 0 | Z82: =IF(Z71=$P$37,$C$29,0) -> 0 | ... EU82: =IF(EU71=$P$37,$C$29,0) -> 0 | EW82: x
B83: Sales Costs | C83: =SUM(D83:O83) -> -1024811 | D83: =SUMIF($S$69:$EU$69,D$69,$S83:$EU83) -> 0 | E83: =SUMIF($S$69:$EU$69,E$69,$S83:$EU83) -> 0 | F83: =SUMIF($S$69:$EU$69,F$69,$S83:$EU83) -> 0 | G83: =SUMIF($S$69:$EU$69,G$69,$S83:$EU83) -> 0 | H83: =SUMIF($S$69:$EU$69,H$69,$S83:$EU83) -> 0 | I83: =SUMIF($S$69:$EU$69,I$69,$S83:$EU83) -> -1024811 | J83: =SUMIF($S$69:$EU$69,J$69,$S83:$EU83) -> 0 | K83: =SUMIF($S$69:$EU$69,K$69,$S83:$EU83) -> 0 | ... O83: =SUMIF($S$69:$EU$69,O$69,$S83:$EU83) -> 0 | Q83: =B83 -> Sales Costs | R83: =SUM(S83:EU83) -> -1024811 | S83: =-(S82*$C$31) -> 0 | T83: =-(T82*$C$31) -> 0 | U83: =-(U82*$C$31) -> 0 | V83: =-(V82*$C$31) -> 0 | W83: =-(W82*$C$31) -> 0 | X83: =-(X82*$C$31) -> 0 | Y83: =-(Y82*$C$31) -> 0 | Z83: =-(Z82*$C$31) -> 0 | ... EU83: =-(EU82*$C$31) -> 0 | EW83: x
B84: Transfer Tax | C84: =SUM(D84:O84) -> -717367.68 | D84: =SUMIF($S$69:$EU$69,D$69,$S84:$EU84) -> 0 | E84: =SUMIF($S$69:$EU$69,E$69,$S84:$EU84) -> 0 | F84: =SUMIF($S$69:$EU$69,F$69,$S84:$EU84) -> 0 | G84: =SUMIF($S$69:$EU$69,G$69,$S84:$EU84) -> 0 | H84: =SUMIF($S$69:$EU$69,H$69,$S84:$EU84) -> 0 | I84: =SUMIF($S$69:$EU$69,I$69,$S84:$EU84) -> -717367.68 | J84: =SUMIF($S$69:$EU$69,J$69,$S84:$EU84) -> 0 | K84: =SUMIF($S$69:$EU$69,K$69,$S84:$EU84) -> 0 | ... O84: =SUMIF($S$69:$EU$69,O$69,$S84:$EU84) -> 0 | Q84: =B84 -> Transfer Tax | R84: =SUM(S84:EU84) -> -717367.68 | S84: =-(S82/100)*1.05 -> 0 | T84: =-(T82/100)*1.05 -> 0 | U84: =-(U82/100)*1.05 -> 0 | V84: =-(V82/100)*1.05 -> 0 | W84: =-(W82/100)*1.05 -> 0 | X84: =-(X82/100)*1.05 -> 0 | Y84: =-(Y82/100)*1.05 -> 0 | Z84: =-(Z82/100)*1.05 -> 0 | ... EU84: =-(EU82/100)*1.05 -> 0 | EW84: x
B85: Unlevered CFs | C85: =SUM(D85:O85) -> 41151301 | D85: =SUM(D72:D84) -> -36735590 | E85: =SUM(E72:E84) -> -1917447 | F85: =SUM(F72:F84) -> 3995804.3 | G85: =SUM(G72:G84) -> 4253257.7 | H85: =SUM(H72:H84) -> 4594429.2 | I85: =SUM(I72:I84) -> 66960847 | J85: =SUM(J72:J84) -> 0 | K85: =SUM(K72:K84) -> 0 | ... O85: =SUM(O72:O84) -> 0 | Q85: =B85 -> Unlevered CFs | R85: =SUM(S85:EU85) -> 41151301 | S85: =IF(S71<=$C$26,SUM(S72:S84),0) -> -37506309 | T85: =IF(T71<=$C$26,SUM(T72:T84),0) -> 271587.81 | U85: =IF(U71<=$C$26,SUM(U72:U84),0) -> 256096.89 | V85: =IF(V71<=$C$26,SUM(V72:V84),0) -> 243034.26 | W85: =IF(W71<=$C$26,SUM(W72:W84),0) -> -429478.04 | X85: =IF(X71<=$C$26,SUM(X72:X84),0) -> -470409.97 | Y85: =IF(Y71<=$C$26,SUM(Y72:Y84),0) -> -469920.64 | Z85: =IF(Z71<=$C$26,SUM(Z72:Z84),0) -> -481008.24 | ... EU85: =IF(EU71<=$C$26,SUM(EU72:EU84),0) -> 0 | EW85: x
EW86: x
B87: Sr. Loan Addition | C87: =SUM(D87:O87) -> 23187000 | D87: =SUMIF($S$69:$EU$69,D$69,$S87:$EU87) -> 23187000 | E87: =SUMIF($S$69:$EU$69,E$69,$S87:$EU87) -> 0 | F87: =SUMIF($S$69:$EU$69,F$69,$S87:$EU87) -> 0 | G87: =SUMIF($S$69:$EU$69,G$69,$S87:$EU87) -> 0 | H87: =SUMIF($S$69:$EU$69,H$69,$S87:$EU87) -> 0 | I87: =SUMIF($S$69:$EU$69,I$69,$S87:$EU87) -> 0 | J87: =SUMIF($S$69:$EU$69,J$69,$S87:$EU87) -> 0 | K87: =SUMIF($S$69:$EU$69,K$69,$S87:$EU87) -> 0 | ... O87: =SUMIF($S$69:$EU$69,O$69,$S87:$EU87) -> 0 | Q87: =B87 -> Sr. Loan Addition | R87: =SUM(S87:EU87) -> 23187000 | S87: {=IF(S71>$P$37,0,INDEX('Debt & Refi'!$I$18:$NH$18,MATCH(S71,'Debt & Refi'!$I$4:$NH$4,0)))} -> 23187000 | T87: {=IF(T71>$P$37,0,INDEX('Debt & Refi'!$I$18:$NH$18,MATCH(T71,'Debt & Refi'!$I$4:$NH$4,0)))} -> 0 | U87: {=IF(U71>$P$37,0,INDEX('Debt & Refi'!$I$18:$NH$18,MATCH(U71,'Debt & Refi'!$I$4:$NH$4,0)))} -> 0 | V87: {=IF(V71>$P$37,0,INDEX('Debt & Refi'!$I$18:$NH$18,MATCH(V71,'Debt & Refi'!$I$4:$NH$4,0)))} -> 0 | W87: {=IF(W71>$P$37,0,INDEX('Debt & Refi'!$I$18:$NH$18,MATCH(W71,'Debt & Refi'!$I$4:$NH$4,0)))} -> 0 | X87: {=IF(X71>$P$37,0,INDEX('Debt & Refi'!$I$18:$NH$18,MATCH(X71,'Debt & Refi'!$I$4:$NH$4,0)))} -> 0 | Y87: {=IF(Y71>$P$37,0,INDEX('Debt & Refi'!$I$18:$NH$18,MATCH(Y71,'Debt & Refi'!$I$4:$NH$4,0)))} -> 0 | Z87: {=IF(Z71>$P$37,0,INDEX('Debt & Refi'!$I$18:$NH$18,MATCH(Z71,'Debt & Refi'!$I$4:$NH$4,0)))} -> 0 | ... EU87: {=IF(EU71>$P$37,0,INDEX('Debt & Refi'!$I$18:$NH$18,MATCH(EU71,'Debt & Refi'!$I$4:$NH$4,0)))} -> 0 | EW87: x
B88: Sr. Loan Costs | C88: =SUM(D88:O88) -> -463740 | D88: =SUMIF($S$69:$EU$69,D$69,$S88:$EU88) -> -463740 | E88: =SUMIF($S$69:$EU$69,E$69,$S88:$EU88) -> 0 | F88: =SUMIF($S$69:$EU$69,F$69,$S88:$EU88) -> 0 | G88: =SUMIF($S$69:$EU$69,G$69,$S88:$EU88) -> 0 | H88: =SUMIF($S$69:$EU$69,H$69,$S88:$EU88) -> 0 | I88: =SUMIF($S$69:$EU$69,I$69,$S88:$EU88) -> 0 | J88: =SUMIF($S$69:$EU$69,J$69,$S88:$EU88) -> 0 | K88: =SUMIF($S$69:$EU$69,K$69,$S88:$EU88) -> 0 | ... O88: =SUMIF($S$69:$EU$69,O$69,$S88:$EU88) -> 0 | Q88: =B88 -> Sr. Loan Costs | R88: =SUM(S88:EU88) -> -463740 | S88: =IF(S$71=$I$4,-$N$8,0) -> -463740 | T88: =IF(T$71=$I$4,-$N$8,0) -> 0 | U88: =IF(U$71=$I$4,-$N$8,0) -> 0 | V88: =IF(V$71=$I$4,-$N$8,0) -> 0 | W88: =IF(W$71=$I$4,-$N$8,0) -> 0 | X88: =IF(X$71=$I$4,-$N$8,0) -> 0 | Y88: =IF(Y$71=$I$4,-$N$8,0) -> 0 | Z88: =IF(Z$71=$I$4,-$N$8,0) -> 0 | ... EU88: =IF(EU$71=$I$4,-$N$8,0) -> 0 | EW88: x
B89: Sr. Loan Interest Reserve | C89: =SUM(D89:O89) -> 0 | D89: =SUMIF($S$69:$EU$69,D$69,$S89:$EU89) -> 0 | E89: =SUMIF($S$69:$EU$69,E$69,$S89:$EU89) -> 0 | F89: =SUMIF($S$69:$EU$69,F$69,$S89:$EU89) -> 0 | G89: =SUMIF($S$69:$EU$69,G$69,$S89:$EU89) -> 0 | H89: =SUMIF($S$69:$EU$69,H$69,$S89:$EU89) -> 0 | I89: =SUMIF($S$69:$EU$69,I$69,$S89:$EU89) -> 0 | J89: =SUMIF($S$69:$EU$69,J$69,$S89:$EU89) -> 0 | K89: =SUMIF($S$69:$EU$69,K$69,$S89:$EU89) -> 0 | ... O89: =SUMIF($S$69:$EU$69,O$69,$S89:$EU89) -> 0 | Q89: =B89 -> Sr. Loan Interest Reserve | R89: =SUM(S89:EU89) -> 0 | S89: =IF(S$71=$I$4,-$N$13,IF(S$71=$C$26,'Debt & Refi'!$AG$22,0)) -> 0 | T89: =IF(T$71=$I$4,-$N$13,IF(T$71=$C$26,'Debt & Refi'!$AG$22,0)) -> 0 | U89: =IF(U$71=$I$4,-$N$13,IF(U$71=$C$26,'Debt & Refi'!$AG$22,0)) -> 0 | V89: =IF(V$71=$I$4,-$N$13,IF(V$71=$C$26,'Debt & Refi'!$AG$22,0)) -> 0 | W89: =IF(W$71=$I$4,-$N$13,IF(W$71=$C$26,'Debt & Refi'!$AG$22,0)) -> 0 | X89: =IF(X$71=$I$4,-$N$13,IF(X$71=$C$26,'Debt & Refi'!$AG$22,0)) -> 0 | Y89: =IF(Y$71=$I$4,-$N$13,IF(Y$71=$C$26,'Debt & Refi'!$AG$22,0)) -> 0 | Z89: =IF(Z$71=$I$4,-$N$13,IF(Z$71=$C$26,'Debt & Refi'!$AG$22,0)) -> 0 | ... EU89: =IF(EU$71=$I$4,-$N$13,IF(EU$71=$C$26,'Debt & Refi'!$AG$22,0)) -> 0
B90: Sr. Loan Debt Service | C90: =SUM(D90:O90) -> -3967378.2 | D90: =SUMIF($S$69:$EU$69,D$69,$S90:$EU90) -> -429219.39 | E90: =SUMIF($S$69:$EU$69,E$69,$S90:$EU90) -> -1597891.9 | F90: =SUMIF($S$69:$EU$69,F$69,$S90:$EU90) -> -1548068.5 | G90: =SUMIF($S$69:$EU$69,G$69,$S90:$EU90) -> -392198.44 | H90: =SUMIF($S$69:$EU$69,H$69,$S90:$EU90) -> 0 | I90: =SUMIF($S$69:$EU$69,I$69,$S90:$EU90) -> 0 | J90: =SUMIF($S$69:$EU$69,J$69,$S90:$EU90) -> 0 | K90: =SUMIF($S$69:$EU$69,K$69,$S90:$EU90) -> 0 | ... O90: =SUMIF($S$69:$EU$69,O$69,$S90:$EU90) -> 0 | Q90: =B90 -> Sr. Loan Debt Service | R90: =SUM(S90:EU90) -> -3967378.2 | S90: {=IF(S71>$P$37,0,-INDEX('Debt & Refi'!$I$14:$NH$14,MATCH(S71,'Debt & Refi'!$I$4:$NH$4,0)))} -> 0 | T90: {=IF(T71>$P$37,0,-INDEX('Debt & Refi'!$I$14:$NH$14,MATCH(T71,'Debt & Refi'!$I$4:$NH$4,0)))} -> -145030.24 | U90: {=IF(U71>$P$37,0,-INDEX('Debt & Refi'!$I$14:$NH$14,MATCH(U71,'Debt & Refi'!$I$4:$NH$4,0)))} -> -144190.29 | V90: {=IF(V71>$P$37,0,-INDEX('Debt & Refi'!$I$14:$NH$14,MATCH(V71,'Debt & Refi'!$I$4:$NH$4,0)))} -> -139998.86 | W90: {=IF(W71>$P$37,0,-INDEX('Debt & Refi'!$I$14:$NH$14,MATCH(W71,'Debt & Refi'!$I$4:$NH$4,0)))} -> -139078.72 | X90: {=IF(X71>$P$37,0,-INDEX('Debt & Refi'!$I$14:$NH$14,MATCH(X71,'Debt & Refi'!$I$4:$NH$4,0)))} -> -138207.85 | Y90: {=IF(Y71>$P$37,0,-INDEX('Debt & Refi'!$I$14:$NH$14,MATCH(Y71,'Debt & Refi'!$I$4:$NH$4,0)))} -> -137219.89 | Z90: {=IF(Z71>$P$37,0,-INDEX('Debt & Refi'!$I$14:$NH$14,MATCH(Z71,'Debt & Refi'!$I$4:$NH$4,0)))} -> -135992.33 | ... EU90: {=IF(EU71>$P$37,0,-INDEX('Debt & Refi'!$I$14:$NH$14,MATCH(EU71,'Debt & Refi'!$I$4:$NH$4,0)))} -> 0 | EW90: x
B91: Sr. Loan Maturity | C91: =SUM(D91:O91) -> -23187000 | D91: =SUMIF($S$69:$EU$69,D$69,$S91:$EU91) -> 0 | E91: =SUMIF($S$69:$EU$69,E$69,$S91:$EU91) -> 0 | F91: =SUMIF($S$69:$EU$69,F$69,$S91:$EU91) -> 0 | G91: =SUMIF($S$69:$EU$69,G$69,$S91:$EU91) -> -23187000 | H91: =SUMIF($S$69:$EU$69,H$69,$S91:$EU91) -> 0 | I91: =SUMIF($S$69:$EU$69,I$69,$S91:$EU91) -> 0 | J91: =SUMIF($S$69:$EU$69,J$69,$S91:$EU91) -> 0 | K91: =SUMIF($S$69:$EU$69,K$69,$S91:$EU91) -> 0 | ... O91: =SUMIF($S$69:$EU$69,O$69,$S91:$EU91) -> 0 | Q91: =B91 -> Sr. Loan Maturity | R91: =SUM(S91:EU91) -> -23187000 | S91: {=IF(S71>$P$37,0,-INDEX('Debt & Refi'!$I$19:$NH$19,MATCH(S71,'Debt & Refi'!$I$4:$NH$4,0)))} -> 0 | T91: {=IF(T71>$P$37,0,-INDEX('Debt & Refi'!$I$19:$NH$19,MATCH(T71,'Debt & Refi'!$I$4:$NH$4,0)))} -> 0 | U91: {=IF(U71>$P$37,0,-INDEX('Debt & Refi'!$I$19:$NH$19,MATCH(U71,'Debt & Refi'!$I$4:$NH$4,0)))} -> 0 | V91: {=IF(V71>$P$37,0,-INDEX('Debt & Refi'!$I$19:$NH$19,MATCH(V71,'Debt & Refi'!$I$4:$NH$4,0)))} -> 0 | W91: {=IF(W71>$P$37,0,-INDEX('Debt & Refi'!$I$19:$NH$19,MATCH(W71,'Debt & Refi'!$I$4:$NH$4,0)))} -> 0 | X91: {=IF(X71>$P$37,0,-INDEX('Debt & Refi'!$I$19:$NH$19,MATCH(X71,'Debt & Refi'!$I$4:$NH$4,0)))} -> 0 | Y91: {=IF(Y71>$P$37,0,-INDEX('Debt & Refi'!$I$19:$NH$19,MATCH(Y71,'Debt & Refi'!$I$4:$NH$4,0)))} -> 0 | Z91: {=IF(Z71>$P$37,0,-INDEX('Debt & Refi'!$I$19:$NH$19,MATCH(Z71,'Debt & Refi'!$I$4:$NH$4,0)))} -> 0 | ... EU91: {=IF(EU71>$P$37,0,-INDEX('Debt & Refi'!$I$19:$NH$19,MATCH(EU71,'Debt & Refi'!$I$4:$NH$4,0)))} -> 0 | EW91: x
B92: Refi. Loan Additon | C92: =SUM(D92:O92) -> 51240548 | D92: =SUMIF($S$69:$EU$69,D$69,$S92:$EU92) -> 0 | E92: =SUMIF($S$69:$EU$69,E$69,$S92:$EU92) -> 0 | F92: =SUMIF($S$69:$EU$69,F$69,$S92:$EU92) -> 0 | G92: =SUMIF($S$69:$EU$69,G$69,$S92:$EU92) -> 51240548 | H92: =SUMIF($S$69:$EU$69,H$69,$S92:$EU92) -> 0 | I92: =SUMIF($S$69:$EU$69,I$69,$S92:$EU92) -> 0 | J92: =SUMIF($S$69:$EU$69,J$69,$S92:$EU92) -> 0 | K92: =SUMIF($S$69:$EU$69,K$69,$S92:$EU92) -> 0 | ... O92: =SUMIF($S$69:$EU$69,O$69,$S92:$EU92) -> 0 | Q92: =B92 -> Refi. Loan Additon | R92: =SUM(S92:EU92) -> 51240548 | S92: {=IF(S71>$P$37,0,INDEX('Debt & Refi'!$I$41:$NH$41,MATCH(Model!S71,'Debt & Refi'!$I$4:$NH$4,0)))} -> 0 | T92: {=IF(T71>$P$37,0,INDEX('Debt & Refi'!$I$41:$NH$41,MATCH(Model!T71,'Debt & Refi'!$I$4:$NH$4,0)))} -> 0 | U92: {=IF(U71>$P$37,0,INDEX('Debt & Refi'!$I$41:$NH$41,MATCH(Model!U71,'Debt & Refi'!$I$4:$NH$4,0)))} -> 0 | V92: {=IF(V71>$P$37,0,INDEX('Debt & Refi'!$I$41:$NH$41,MATCH(Model!V71,'Debt & Refi'!$I$4:$NH$4,0)))} -> 0 | W92: {=IF(W71>$P$37,0,INDEX('Debt & Refi'!$I$41:$NH$41,MATCH(Model!W71,'Debt & Refi'!$I$4:$NH$4,0)))} -> 0 | X92: {=IF(X71>$P$37,0,INDEX('Debt & Refi'!$I$41:$NH$41,MATCH(Model!X71,'Debt & Refi'!$I$4:$NH$4,0)))} -> 0 | Y92: {=IF(Y71>$P$37,0,INDEX('Debt & Refi'!$I$41:$NH$41,MATCH(Model!Y71,'Debt & Refi'!$I$4:$NH$4,0)))} -> 0 | Z92: {=IF(Z71>$P$37,0,INDEX('Debt & Refi'!$I$41:$NH$41,MATCH(Model!Z71,'Debt & Refi'!$I$4:$NH$4,0)))} -> 0 | ... EU92: {=IF(EU71>$P$37,0,INDEX('Debt & Refi'!$I$41:$NH$41,MATCH(Model!EU71,'Debt & Refi'!$I$4:$NH$4,0)))} -> 0 | EW92: x
B93: Refi. Loan Costs | C93: =SUM(D93:O93) -> -512405.48 | D93: =SUMIF($S$69:$EU$69,D$69,$S93:$EU93) -> 0 | E93: =SUMIF($S$69:$EU$69,E$69,$S93:$EU93) -> 0 | F93: =SUMIF($S$69:$EU$69,F$69,$S93:$EU93) -> 0 | G93: =SUMIF($S$69:$EU$69,G$69,$S93:$EU93) -> -512405.48 | H93: =SUMIF($S$69:$EU$69,H$69,$S93:$EU93) -> 0 | I93: =SUMIF($S$69:$EU$69,I$69,$S93:$EU93) -> 0 | J93: =SUMIF($S$69:$EU$69,J$69,$S93:$EU93) -> 0 | K93: =SUMIF($S$69:$EU$69,K$69,$S93:$EU93) -> 0 | ... O93: =SUMIF($S$69:$EU$69,O$69,$S93:$EU93) -> 0 | Q93: =B93 -> Refi. Loan Costs | R93: =SUM(S93:EU93) -> -512405.48 | S93: =-S92*$I$45 -> 0 | T93: =-T92*$I$45 -> 0 | U93: =-U92*$I$45 -> 0 | V93: =-V92*$I$45 -> 0 | W93: =-W92*$I$45 -> 0 | X93: =-X92*$I$45 -> 0 | Y93: =-Y92*$I$45 -> 0 | Z93: =-Z92*$I$45 -> 0 | ... EU93: =-EU92*$I$45 -> 0 | EW93: x
B94: Refi. Loan Debt Service | C94: =SUM(D94:O94) -> -7124733.6 | D94: =SUMIF($S$69:$EU$69,D$69,$S94:$EU94) -> 0 | E94: =SUMIF($S$69:$EU$69,E$69,$S94:$EU94) -> 0 | F94: =SUMIF($S$69:$EU$69,F$69,$S94:$EU94) -> 0 | G94: =SUMIF($S$69:$EU$69,G$69,$S94:$EU94) -> -2821966.9 | H94: =SUMIF($S$69:$EU$69,H$69,$S94:$EU94) -> -3942433 | I94: =SUMIF($S$69:$EU$69,I$69,$S94:$EU94) -> -360333.71 | J94: =SUMIF($S$69:$EU$69,J$69,$S94:$EU94) -> 0 | K94: =SUMIF($S$69:$EU$69,K$69,$S94:$EU94) -> 0 | ... O94: =SUMIF($S$69:$EU$69,O$69,$S94:$EU94) -> 0 | Q94: =B94 -> Refi. Loan Debt Service | R94: =SUM(S94:EU94) -> -7124733.6 | S94: {=IF(S71>$P$37,0,-INDEX('Debt & Refi'!$I$37:$NH$37,MATCH(S71,'Debt & Refi'!$I$4:$NH$4,0)))} -> 0 | T94: {=IF(T71>$P$37,0,-INDEX('Debt & Refi'!$I$37:$NH$37,MATCH(T71,'Debt & Refi'!$I$4:$NH$4,0)))} -> 0 | U94: {=IF(U71>$P$37,0,-INDEX('Debt & Refi'!$I$37:$NH$37,MATCH(U71,'Debt & Refi'!$I$4:$NH$4,0)))} -> 0 | V94: {=IF(V71>$P$37,0,-INDEX('Debt & Refi'!$I$37:$NH$37,MATCH(V71,'Debt & Refi'!$I$4:$NH$4,0)))} -> 0 | W94: {=IF(W71>$P$37,0,-INDEX('Debt & Refi'!$I$37:$NH$37,MATCH(W71,'Debt & Refi'!$I$4:$NH$4,0)))} -> 0 | X94: {=IF(X71>$P$37,0,-INDEX('Debt & Refi'!$I$37:$NH$37,MATCH(X71,'Debt & Refi'!$I$4:$NH$4,0)))} -> 0 | Y94: {=IF(Y71>$P$37,0,-INDEX('Debt & Refi'!$I$37:$NH$37,MATCH(Y71,'Debt & Refi'!$I$4:$NH$4,0)))} -> 0 | Z94: {=IF(Z71>$P$37,0,-INDEX('Debt & Refi'!$I$37:$NH$37,MATCH(Z71,'Debt & Refi'!$I$4:$NH$4,0)))} -> 0 | ... EU94: {=IF(EU71>$P$37,0,-INDEX('Debt & Refi'!$I$37:$NH$37,MATCH(EU71,'Debt & Refi'!$I$4:$NH$4,0)))} -> 0 | EW94: x
B95: Refi. Loan Maturity | C95: =SUM(D95:O95) -> -51088151 | D95: =SUMIF($S$69:$EU$69,D$69,$S95:$EU95) -> 0 | E95: =SUMIF($S$69:$EU$69,E$69,$S95:$EU95) -> 0 | F95: =SUMIF($S$69:$EU$69,F$69,$S95:$EU95) -> 0 | G95: =SUMIF($S$69:$EU$69,G$69,$S95:$EU95) -> 0 | H95: =SUMIF($S$69:$EU$69,H$69,$S95:$EU95) -> 0 | I95: =SUMIF($S$69:$EU$69,I$69,$S95:$EU95) -> -51088151 | J95: =SUMIF($S$69:$EU$69,J$69,$S95:$EU95) -> 0 | K95: =SUMIF($S$69:$EU$69,K$69,$S95:$EU95) -> 0 | ... O95: =SUMIF($S$69:$EU$69,O$69,$S95:$EU95) -> 0 | Q95: =B95 -> Refi. Loan Maturity | R95: =SUM(S95:EU95) -> -51088151 | S95: {=IF(S71>$P$37,0,-INDEX('Debt & Refi'!$I$42:$NH$42,MATCH(Model!S71,'Debt & Refi'!$I$4:$NH$4,0)))} -> 0 | T95: {=IF(T71>$P$37,0,-INDEX('Debt & Refi'!$I$42:$NH$42,MATCH(Model!T71,'Debt & Refi'!$I$4:$NH$4,0)))} -> 0 | U95: {=IF(U71>$P$37,0,-INDEX('Debt & Refi'!$I$42:$NH$42,MATCH(Model!U71,'Debt & Refi'!$I$4:$NH$4,0)))} -> 0 | V95: {=IF(V71>$P$37,0,-INDEX('Debt & Refi'!$I$42:$NH$42,MATCH(Model!V71,'Debt & Refi'!$I$4:$NH$4,0)))} -> 0 | W95: {=IF(W71>$P$37,0,-INDEX('Debt & Refi'!$I$42:$NH$42,MATCH(Model!W71,'Debt & Refi'!$I$4:$NH$4,0)))} -> 0 | X95: {=IF(X71>$P$37,0,-INDEX('Debt & Refi'!$I$42:$NH$42,MATCH(Model!X71,'Debt & Refi'!$I$4:$NH$4,0)))} -> 0 | Y95: {=IF(Y71>$P$37,0,-INDEX('Debt & Refi'!$I$42:$NH$42,MATCH(Model!Y71,'Debt & Refi'!$I$4:$NH$4,0)))} -> 0 | Z95: {=IF(Z71>$P$37,0,-INDEX('Debt & Refi'!$I$42:$NH$42,MATCH(Model!Z71,'Debt & Refi'!$I$4:$NH$4,0)))} -> 0 | ... EU95: {=IF(EU71>$P$37,0,-INDEX('Debt & Refi'!$I$42:$NH$42,MATCH(Model!EU71,'Debt & Refi'!$I$4:$NH$4,0)))} -> 0 | EW95: x
B96: Levered CFs | C96: =SUM(D96:O96) -> 29235441 | D96: =SUM(D85,D87:D95) -> -14441550 | E96: =SUM(E85,E87:E95) -> -3515338.9 | F96: =SUM(F85,F87:F95) -> 2447735.8 | G96: =SUM(G85,G87:G95) -> 28580235 | H96: =SUM(H85,H87:H95) -> 651996.24 | I96: =SUM(I85,I87:I95) -> 15512362 | J96: =SUM(J85,J87:J95) -> 0 | K96: =SUM(K85,K87:K95) -> 0 | ... O96: =SUM(O85,O87:O95) -> 0 | Q96: =B96 -> Levered CFs | R96: =SUM(S96:EU96) -> 29235441 | S96: =IF(S71<=$C$26,SUM(S85,S87:S95,),0) -> -14783049 | T96: =IF(T71<=$C$26,SUM(T85,T87:T95,),0) -> 126557.56 | U96: =IF(U71<=$C$26,SUM(U85,U87:U95,),0) -> 111906.6 | V96: =IF(V71<=$C$26,SUM(V85,V87:V95,),0) -> 103035.4 | W96: =IF(W71<=$C$26,SUM(W85,W87:W95,),0) -> -568556.76 | X96: =IF(X71<=$C$26,SUM(X85,X87:X95,),0) -> -608617.82 | Y96: =IF(Y71<=$C$26,SUM(Y85,Y87:Y95,),0) -> -607140.53 | Z96: =IF(Z71<=$C$26,SUM(Z85,Z87:Z95,),0) -> -617000.57 | ... EU96: =IF(EU71<=$C$26,SUM(EU85,EU87:EU95,),0) -> 0 | EW96: x
B98: =Q98 -> Unlevered IRR | C98: =R98 -> 0.19533386 | Q98: Unlevered IRR | R98: =XIRR($S$85:$EU$85,$S$71:$EU$71) -> 0.19533386
B99: =Q99 -> Peak Equity | C99: =R99 -> 41061645 | Q99: Peak Equity | R99: =-SUMIF($S$85:$EU$85,"<=0",$S$85:$EU$85) -> 41061645
B100: =Q100 -> Equity Multiple | C100: =R100 -> 2.0021835 | Q100: Equity Multiple | R100: =+R101/R99+1 -> 2.0021835
B101: =Q101 -> WDP | C101: =R101 -> 41151301 | Q101: WDP | R101: =+SUM($S$85:$EU$85) -> 41151301
B103: =Q103 -> Levered IRR | C103: =R103 -> 0.39585511 | Q103: Levered IRR | R103: =XIRR($S$96:$EU$96,$S$71:$EU$71) -> 0.39585511
B104: =Q104 -> Peak Equity | C104: =R104 -> 19852216 | Q104: Peak Equity | R104: =-SUMIF($S$96:$EU$96,"<=0",$S$96:$EU$96) -> 19852216
B105: =Q105 -> Equity Multiple | C105: =R105 -> 2.4726538 | Q105: Equity Multiple | R105: =+R106/R104+1 -> 2.4726538
B106: =Q106 -> WDP | C106: =R106 -> 29235441 | Q106: WDP | R106: =+SUM($S$96:$EU$96) -> 29235441
D111: Exit Cap | P111: Exit Cap | AB111: Exit Cap
B112: Equity Multiple | C112: =$R$105 -> 2.4726538 | D112: =E112-0.25% -> 0.055 | E112: =F112-0.25% -> 0.0575 | F112: =G112-0.25% -> 0.06 | G112: =H112-0.25% -> 0.0625 | H112: 0.065 | I112: =H112+0.25% -> 0.0675 | J112: =I112+0.25% -> 0.07 | K112: =J112+0.25% -> 0.0725 | L112: =K112+0.25% -> 0.075 | N112: WDP | O112: =$R$106 -> 29235441 | P112: =Q112-0.25% -> 0.055 | Q112: =R112-0.25% -> 0.0575 | R112: =S112-0.25% -> 0.06 | S112: =T112-0.25% -> 0.0625 | T112: 0.065 | U112: =T112+0.25% -> 0.0675 | V112: =U112+0.25% -> 0.07 | W112: =V112+0.25% -> 0.0725 | X112: =W112+0.25% -> 0.075 | Z112: Levered IRR | AA112: =$R$103 -> 0.39585511 | AB112: =AC112-0.25% -> 0.055 | AC112: =AD112-0.25% -> 0.0575 | AD112: =AE112-0.25% -> 0.06 | AE112: =AF112-0.25% -> 0.0625 | AF112: 0.065 | AG112: =AF112+0.25% -> 0.0675 | AH112: =AG112+0.25% -> 0.07 | AI112: =AH112+0.25% -> 0.0725 | AJ112: =AI112+0.25% -> 0.075
C113: =C114-250000 -> 64570731 | D113: 2.3166843 | E113: 2.3166843 | F113: 2.3166843 | G113: 2.3166843 | H113: 2.3166843 | I113: 2.3166843 | J113: 2.3166843 | K113: 2.3166843 | L113: 2.3166843 | O113: =O114-250000 -> 64570731 | P113: 25991890 | Q113: 25991890 | R113: 25991890 | S113: 25991890 | T113: 25991890 | U113: 25991890 | V113: 25991890 | W113: 25991890 | X113: 25991890 | AA113: =AA114-250000 -> 64570731 | AB113: 0.35836508 | AC113: 0.35836508 | AD113: 0.35836508 | AE113: 0.35836508 | AF113: 0.35836508 | AG113: 0.35836508 | AH113: 0.35836508 | AI113: 0.35836508 | AJ113: 0.35836508
C114: =C115-250000 -> 64820731 | D114: 2.3271726 | E114: 2.3271726 | F114: 2.3271726 | G114: 2.3271726 | H114: 2.3271726 | I114: 2.3271726 | J114: 2.3271726 | K114: 2.3271726 | L114: 2.3271726 | O114: =O115-250000 -> 64820731 | P114: 26208127 | Q114: 26208127 | R114: 26208127 | S114: 26208127 | T114: 26208127 | U114: 26208127 | V114: 26208127 | W114: 26208127 | X114: 26208127 | AA114: =AA115-250000 -> 64820731 | AB114: 0.36090394 | AC114: 0.36090394 | AD114: 0.36090394 | AE114: 0.36090394 | AF114: 0.36090394 | AG114: 0.36090394 | AH114: 0.36090394 | AI114: 0.36090394 | AJ114: 0.36090394
C115: =C116-250000 -> 65070731 | D115: 2.3376535 | E115: 2.3376535 | F115: 2.3376535 | G115: 2.3376535 | H115: 2.3376535 | I115: 2.3376535 | J115: 2.3376535 | K115: 2.3376535 | L115: 2.3376535 | O115: =O116-250000 -> 65070731 | P115: 26424364 | Q115: 26424364 | R115: 26424364 | S115: 26424364 | T115: 26424364 | U115: 26424364 | V115: 26424364 | W115: 26424364 | X115: 26424364 | AA115: =AA116-250000 -> 65070731 | AB115: 0.36343703 | AC115: 0.36343703 | AD115: 0.36343703 | AE115: 0.36343703 | AF115: 0.36343703 | AG115: 0.36343703 | AH115: 0.36343703 | AI115: 0.36343703 | AJ115: 0.36343703
C116: =C117-250000 -> 65320731 | D116: 2.3481271 | E116: 2.3481271 | F116: 2.3481271 | G116: 2.3481271 | H116: 2.3481271 | I116: 2.3481271 | J116: 2.3481271 | K116: 2.3481271 | L116: 2.3481271 | O116: =O117-250000 -> 65320731 | P116: 26640600 | Q116: 26640600 | R116: 26640600 | S116: 26640600 | T116: 26640600 | U116: 26640600 | V116: 26640600 | W116: 26640600 | X116: 26640600 | AA116: =AA117-250000 -> 65320731 | AB116: 0.36596437 | AC116: 0.36596437 | AD116: 0.36596437 | AE116: 0.36596437 | AF116: 0.36596437 | AG116: 0.36596437 | AH116: 0.36596437 | AI116: 0.36596437 | AJ116: 0.36596437
C117: =C118-250000 -> 65570731 | D117: 2.3585934 | E117: 2.3585934 | F117: 2.3585934 | G117: 2.3585934 | H117: 2.3585934 | I117: 2.3585934 | J117: 2.3585934 | K117: 2.3585934 | L117: 2.3585934 | O117: =O118-250000 -> 65570731 | P117: 26856837 | Q117: 26856837 | R117: 26856837 | S117: 26856837 | T117: 26856837 | U117: 26856837 | V117: 26856837 | W117: 26856837 | X117: 26856837 | AA117: =AA118-250000 -> 65570731 | AB117: 0.36848601 | AC117: 0.36848601 | AD117: 0.36848601 | AE117: 0.36848601 | AF117: 0.36848601 | AG117: 0.36848601 | AH117: 0.36848601 | AI117: 0.36848601 | AJ117: 0.36848601
C118: =C119-250000 -> 65820731 | D118: 2.3690523 | E118: 2.3690523 | F118: 2.3690523 | G118: 2.3690523 | H118: 2.3690523 | I118: 2.3690523 | J118: 2.3690523 | K118: 2.3690523 | L118: 2.3690523 | O118: =O119-250000 -> 65820731 | P118: 27073074 | Q118: 27073074 | R118: 27073074 | S118: 27073074 | T118: 27073074 | U118: 27073074 | V118: 27073074 | W118: 27073074 | X118: 27073074 | AA118: =AA119-250000 -> 65820731 | AB118: 0.37100194 | AC118: 0.37100194 | AD118: 0.37100194 | AE118: 0.37100194 | AF118: 0.37100194 | AG118: 0.37100194 | AH118: 0.37100194 | AI118: 0.37100194 | AJ118: 0.37100194
C119: =C120-250000 -> 66070731 | D119: 2.3795039 | E119: 2.3795039 | F119: 2.3795039 | G119: 2.3795039 | H119: 2.3795039 | I119: 2.3795039 | J119: 2.3795039 | K119: 2.3795039 | L119: 2.3795039 | O119: =O120-250000 -> 66070731 | P119: 27289311 | Q119: 27289311 | R119: 27289311 | S119: 27289311 | T119: 27289311 | U119: 27289311 | V119: 27289311 | W119: 27289311 | X119: 27289311 | AA119: =AA120-250000 -> 66070731 | AB119: 0.37351224 | AC119: 0.37351224 | AD119: 0.37351224 | AE119: 0.37351224 | AF119: 0.37351224 | AG119: 0.37351224 | AH119: 0.37351224 | AI119: 0.37351224 | AJ119: 0.37351224
C120: =C121-250000 -> 66320731 | D120: 2.3899481 | E120: 2.3899481 | F120: 2.3899481 | G120: 2.3899481 | H120: 2.3899481 | I120: 2.3899481 | J120: 2.3899481 | K120: 2.3899481 | L120: 2.3899481 | O120: =O121-250000 -> 66320731 | P120: 27505547 | Q120: 27505547 | R120: 27505547 | S120: 27505547 | T120: 27505547 | U120: 27505547 | V120: 27505547 | W120: 27505547 | X120: 27505547 | AA120: =AA121-250000 -> 66320731 | AB120: 0.3760169 | AC120: 0.3760169 | AD120: 0.3760169 | AE120: 0.3760169 | AF120: 0.3760169 | AG120: 0.3760169 | AH120: 0.3760169 | AI120: 0.3760169 | AJ120: 0.3760169
C121: =C122-250000 -> 66570731 | D121: 2.4003851 | E121: 2.4003851 | F121: 2.4003851 | G121: 2.4003851 | H121: 2.4003851 | I121: 2.4003851 | J121: 2.4003851 | K121: 2.4003851 | L121: 2.4003851 | O121: =O122-250000 -> 66570731 | P121: 27721784 | Q121: 27721784 | R121: 27721784 | S121: 27721784 | T121: 27721784 | U121: 27721784 | V121: 27721784 | W121: 27721784 | X121: 27721784 | AA121: =AA122-250000 -> 66570731 | AB121: 0.37851596 | AC121: 0.37851596 | AD121: 0.37851596 | AE121: 0.37851596 | AF121: 0.37851596 | AG121: 0.37851596 | AH121: 0.37851596 | AI121: 0.37851596 | AJ121: 0.37851596
...

Sheet Debt & Refi
B2: Senior Loan Financing | G2: Year | I2: =ROUNDUP(I3,12) -> 0 | J2: =ROUNDUP(J3/12,0) -> 1 | K2: =ROUNDUP(K3/12,0) -> 1 | L2: =ROUNDUP(L3/12,0) -> 1 | M2: =ROUNDUP(M3/12,0) -> 1 | N2: =ROUNDUP(N3/12,0) -> 1 | O2: =ROUNDUP(O3/12,0) -> 1 | P2: =ROUNDUP(P3/12,0) -> 1 | Q2: =ROUNDUP(Q3/12,0) -> 1 | ... NH2: =ROUNDUP(NH3/12,0) -> 31
B3: Funding Date | C3: Month | D3: =Model!I3 -> 0 | E3: {=(INDEX(Model!$S$71:$EU$71,MATCH($D$3,Model!$S$70:$EU$70,0)))} -> 45930 | G3: Month | I3: 0 | J3: =I3+1 -> 1 | K3: =J3+1 -> 2 | L3: =K3+1 -> 3 | M3: =L3+1 -> 4 | N3: =M3+1 -> 5 | O3: =N3+1 -> 6 | P3: =O3+1 -> 7 | Q3: =P3+1 -> 8 | ... NH3: =NG3+1 -> 363
B4: Development Cost | G4: Date | I4: =$E$3 -> 45930 | J4: =EOMONTH(I4,1) -> 45961 | K4: =EOMONTH(J4,1) -> 45991 | L4: =EOMONTH(K4,1) -> 46022 | M4: =EOMONTH(L4,1) -> 46053 | N4: =EOMONTH(M4,1) -> 46081 | O4: =EOMONTH(N4,1) -> 46112 | P4: =EOMONTH(O4,1) -> 46142 | Q4: =EOMONTH(P4,1) -> 46173 | ... NH4: =EOMONTH(NG4,1) -> 56979
B5: Stablized Value | E5: =Model!$O$39 -> 68320731 | G5: Senior Debt
G6: Interest Rate
B7: Senior Debt | G7: SOFR Ceiling | I7: =$E$14/12 -> 0.083333333 | J7: =$E$14/12 -> 0.083333333 | K7: =$E$14/12 -> 0.083333333 | L7: =$E$14/12 -> 0.083333333 | M7: =$E$14/12 -> 0.083333333 | N7: =$E$14/12 -> 0.083333333 | O7: =$E$14/12 -> 0.083333333 | P7: =$E$14/12 -> 0.083333333 | ... NH7: =$E$14/12 -> 0.083333333 | NI7: x
B8: New (1) or Assuming Loan (2) | E8: 1 | G8: Floating SOFR | I8: {=INDEX('1-month SOFR - UST '!$Q$9:$Q$1048576,MATCH(I$4,'1-month SOFR - UST '!$O$9:$O$1048576,0))/12} -> 0.00346265 | J8: {=INDEX('1-month SOFR - UST '!$Q$9:$Q$1048576,MATCH(J$4,'1-month SOFR - UST '!$O$9:$O$1048576,0))/12} -> 0.0033381417 | K8: {=INDEX('1-month SOFR - UST '!$Q$9:$Q$1048576,MATCH(K$4,'1-month SOFR - UST '!$O$9:$O$1048576,0))/12} -> 0.0033019167 | L8: {=INDEX('1-month SOFR - UST '!$Q$9:$Q$1048576,MATCH(L$4,'1-month SOFR - UST '!$O$9:$O$1048576,0))/12} -> 0.00312115 | M8: {=INDEX('1-month SOFR - UST '!$Q$9:$Q$1048576,MATCH(M$4,'1-month SOFR - UST '!$O$9:$O$1048576,0))/12} -> 0.0030814667 | N8: {=INDEX('1-month SOFR - UST '!$Q$9:$Q$1048576,MATCH(N$4,'1-month SOFR - UST '!$O$9:$O$1048576,0))/12} -> 0.0030439083 | O8: {=INDEX('1-month SOFR - UST '!$Q$9:$Q$1048576,MATCH(O$4,'1-month SOFR - UST '!$O$9:$O$1048576,0))/12} -> 0.0030013 | P8: {=INDEX('1-month SOFR - UST '!$Q$9:$Q$1048576,MATCH(P$4,'1-month SOFR - UST '!$O$9:$O$1048576,0))/12} -> 0.0029483583 | ... NH8: {=INDEX('1-month SOFR - UST '!$Q$9:$Q$1048576,MATCH(NH$4,'1-month SOFR - UST '!$O$9:$O$1048576,0))/12} -> #N/A | NI8: x
B9: Amount | C9: =$E$9/$E$4 -> #DIV/0! | D9: =$E$9/$E$5 -> 0.3466579 | E9: =MAX(Model!$I$10,Model!$I$12) -> 23683921 | G9: Spread over SOFR | I9: =$E$13/12 -> 0.0029166667 | J9: =$E$13/12 -> 0.0029166667 | K9: =$E$13/12 -> 0.0029166667 | L9: =$E$13/12 -> 0.0029166667 | M9: =$E$13/12 -> 0.0029166667 | N9: =$E$13/12 -> 0.0029166667 | O9: =$E$13/12 -> 0.0029166667 | P9: =$E$13/12 -> 0.0029166667 | ... NH9: =$E$13/12 -> 0.0029166667 | NI9: x
B10: Requested Amount | E10: =Model!$I$16 -> 23187000 | G10: SOFR Floor | I10: =$E$15/12 -> 0 | J10: =$E$15/12 -> 0 | K10: =$E$15/12 -> 0 | L10: =$E$15/12 -> 0 | M10: =$E$15/12 -> 0 | N10: =$E$15/12 -> 0 | O10: =$E$15/12 -> 0 | P10: =$E$15/12 -> 0 | ... NH10: =$E$15/12 -> 0 | NI10: x
B11: Loan Fees | C11: =Model!$I$24 -> 0.02 | E11: =$E$9*C11 -> 473678.42 | G11: Interest Rate Used | I11: =IF(C12=2,$E$12/12,MIN(MAX(I10,I8),I7)+I9) -> 0.0063793167 | J11: =IF(D12=2,$E$12/12,MIN(MAX(J10,J8),J7)+J9) -> 0.0062548083 | K11: =IF(E12=2,$E$12/12,MIN(MAX(K10,K8),K7)+K9) -> 0.0062185833 | L11: =IF(F12=2,$E$12/12,MIN(MAX(L10,L8),L7)+L9) -> 0.0060378167 | M11: =IF(G18=2,$E$12/12,MIN(MAX(M10,M8),M7)+M9) -> 0.0059981333 | N11: =IF(H18=2,$E$12/12,MIN(MAX(N10,N8),N7)+N9) -> 0.005960575 | O11: =IF(I18=2,$E$12/12,MIN(MAX(O10,O8),O7)+O9) -> 0.0059179667 | P11: =IF(J18=2,$E$12/12,MIN(MAX(P10,P8),P7)+P9) -> 0.005865025 | Q11: =IF(K18=2,$E$12/12,MIN(MAX(Q10,Q8),Q7)+Q9) -> 0.0058334167 | R11: =IF(L18=2,$E$12/12,MIN(MAX(R10,R8),R7)+R9) -> 0.0057108 | S11: =IF(M18=2,$E$12/12,MIN(MAX(S10,S8),S7)+S9) -> 0.0056870167 | T11: =IF(N18=2,$E$12/12,MIN(MAX(T10,T8),T7)+T9) -> 0.005687275 | ... NH11: =IF(NB18=2,$E$12/12,MIN(MAX(NH10,NH8),NH7)+NH9) -> #N/A | NI11: x
B12: Variable (1) or Fixed (2) | C12: =Model!$I$17 -> 1 | E12: =Model!$I$19 -> 0.0415518 | NI12: x
B13: Spread over SOFR | E13: =Model!$I$18 -> 0.035 | G13: Beginning Balance | I13: =H20 | J13: =I20 -> 23187000 | K13: =J20 -> 23187000 | L13: =K20 -> 23187000 | M13: =L20 -> 23187000 | N13: =M20 -> 23187000 | O13: =N20 -> 23187000 | P13: =O20 -> 23187000 | ... NH13: =NG20 -> #N/A | NI13: x
B14: SOFR Ceiling | E14: =Model!$I$21 -> 1 | G14: Payment | I14: =IF(I3="","",AND(I3>$E$17,I3<=$E$18)*((I3<=$E$19)*I13*I16+(I3>$E$19)*PMT(I16,$E$16,-$E$9))) -> 0 | J14: =IF(J3="","",AND(J3>$E$17,J3<=$E$18)*((J3<=$E$19)*J13*J16+(J3>$E$19)*PMT(J16,$E$16,-$E$9))) -> 145030.24 | K14: =IF(K3="","",AND(K3>$E$17,K3<=$E$18)*((K3<=$E$19)*K13*K16+(K3>$E$19)*PMT(K16,$E$16,-$E$9))) -> 144190.29 | L14: =IF(L3="","",AND(L3>$E$17,L3<=$E$18)*((L3<=$E$19)*L13*L16+(L3>$E$19)*PMT(L16,$E$16,-$E$9))) -> 139998.86 | M14: =IF(M3="","",AND(M3>$E$17,M3<=$E$18)*((M3<=$E$19)*M13*M16+(M3>$E$19)*PMT(M16,$E$16,-$E$9))) -> 139078.72 | N14: =IF(N3="","",AND(N3>$E$17,N3<=$E$18)*((N3<=$E$19)*N13*N16+(N3>$E$19)*PMT(N16,$E$16,-$E$9))) -> 138207.85 | O14: =IF(O3="","",AND(O3>$E$17,O3<=$E$18)*((O3<=$E$19)*O13*O16+(O3>$E$19)*PMT(O16,$E$16,-$E$9))) -> 137219.89 | P14: =IF(P3="","",AND(P3>$E$17,P3<=$E$18)*((P3<=$E$19)*P13*P16+(P3>$E$19)*PMT(P16,$E$16,-$E$9))) -> 135992.33 | ... NH14: =IF(NH3="","",AND(NH3>$E$17,NH3<=$E$18)*((NH3<=$E$19)*NH13*NH16+(NH3>$E$19)*PMT(NH16,$E$16,-$E$9))) -> #N/A | NI14: x
B15: SOFR Floor | E15: =Model!$I$20 -> 0 | G15: Interest | I15: =I13*I16 -> 0 | J15: =J13*J16 -> 145030.24 | K15: =K13*K16 -> 144190.29 | L15: =L13*L16 -> 139998.86 | M15: =M13*M16 -> 139078.72 | N15: =N13*N16 -> 138207.85 | O15: =O13*O16 -> 137219.89 | P15: =P13*P16 -> 135992.33 | ... NH15: =NH13*NH16 -> #N/A | NI15: x
B16: Amortization | D16: =$E$16/12 -> 30 | E16: =Model!$I$23*12 -> 360 | G16: Rate (Monthly) | I16: =I11 -> 0.0063793167 | J16: =J11 -> 0.0062548083 | K16: =K11 -> 0.0062185833 | L16: =L11 -> 0.0060378167 | M16: =M11 -> 0.0059981333 | N16: =N11 -> 0.005960575 | O16: =O11 -> 0.0059179667 | P16: =P11 -> 0.005865025 | ... NG16: =NG11 -> #N/A | NH16: =IF($C$12=1,NH6,$E$12/12) | NI16: x
B17: Funding Month | E17: =$D$3 -> 0 | G17: Principal | I17: =I14-I15 -> 0 | J17: =J14-J15 -> 0 | K17: =K14-K15 -> 0 | L17: =L14-L15 -> 0 | M17: =M14-M15 -> 0 | N17: =N14-N15 -> 0 | O17: =O14-O15 -> 0 | P17: =P14-P15 -> 0 | ... NH17: =NH14-NH15 -> #N/A | NI17: x
B18: Payoff Month | E18: =Model!$O$29 -> 30 | G18: Loan Funding | I18: =IF(I3=$D$3,$E$10,0) -> 23187000 | J18: =IF(J3=$D$3,$E$10,0) -> 0 | K18: =IF(K3=$D$3,$E$10,0) -> 0 | L18: =IF(L3=$D$3,$E$10,0) -> 0 | M18: =IF(M3=$D$3,$E$10,0) -> 0 | N18: =IF(N3=$D$3,$E$10,0) -> 0 | O18: =IF(O3=$D$3,$E$10,0) -> 0 | P18: =IF(P3=$D$3,$E$10,0) -> 0 | ... NH18: =IF(NH3=$D$3,$E$10,0) -> 0 | NI18: x
B19: Interest-Only Period | D19: =$E$19/12 -> 4 | E19: =Model!$O$28 -> 48 | G19: Loan Payoff | I19: =IF(I3=$E$18,H20-I17,0) -> 0 | J19: =IF(J3=$E$18,I20-J17,0) -> 0 | K19: =IF(K3=$E$18,J20-K17,0) -> 0 | L19: =IF(L3=$E$18,K20-L17,0) -> 0 | M19: =IF(M3=$E$18,L20-M17,0) -> 0 | N19: =IF(N3=$E$18,M20-N17,0) -> 0 | O19: =IF(O3=$E$18,N20-O17,0) -> 0 | P19: =IF(P3=$E$18,O20-P17,0) -> 0 | ... NH19: =IF(NH3=$E$18,NG20-NH17,0) -> 0 | NI19: x
B20: Fixed Amort. Payments (Monthly) | E20: =PMT(E12/12,E16,-E9) -> 115199.73 | G20: Ending Balance | I20: =I13-I17+I18-I19 -> 23187000 | J20: =J13-J17+J18-J19 -> 23187000 | K20: =K13-K17+K18-K19 -> 23187000 | L20: =L13-L17+L18-L19 -> 23187000 | M20: =M13-M17+M18-M19 -> 23187000 | N20: =N13-N17+N18-N19 -> 23187000 | O20: =O13-O17+O18-O19 -> 23187000 | P20: =P13-P17+P18-P19 -> 23187000 | ... NH20: =NH13-NH17+NH18-NH19 -> #N/A | NI20: x
B21: Fixed IO Payments (Monthly) | E21: =E9*(E12/12) -> 82009.129
B22: Payoff @ Loan Maturity | E22: =MAX(I19:DY19) -> 23187000
B23: Capitalized Interest - 6 Months Opening | E23: =ROUND(SUM(I14:P14),-3) -> 980000
B28: Senior Loan (Refinance) Financing | G28: Senior Debt (Refinance) | NI28: x
B29: Funding Date | C29: Month | D29: =Model!$I$28 -> 30 | E29: =Model!$P$35 -> 46843 | G29: Interest Rate | NI29: x
G30: SOFR Ceiling | I30: =$E$40/12 -> 0.083333333 | J30: =$E$40/12 -> 0.083333333 | K30: =$E$40/12 -> 0.083333333 | L30: =$E$40/12 -> 0.083333333 | M30: =$E$40/12 -> 0.083333333 | N30: =$E$40/12 -> 0.083333333 | O30: =$E$40/12 -> 0.083333333 | P30: =$E$40/12 -> 0.083333333 | ... NH30: =$E$40/12 -> 0.083333333 | NI30: x
G31: Floating SOFR | I31: {=INDEX('1-month SOFR - UST '!$Q$9:$Q$1048576,MATCH(I$4,'1-month SOFR - UST '!$O$9:$O$1048576,0))/12} -> 0.00346265 | J31: {=INDEX('1-month SOFR - UST '!$Q$9:$Q$1048576,MATCH(J$4,'1-month SOFR - UST '!$O$9:$O$1048576,0))/12} -> 0.0033381417 | K31: {=INDEX('1-month SOFR - UST '!$Q$9:$Q$1048576,MATCH(K$4,'1-month SOFR - UST '!$O$9:$O$1048576,0))/12} -> 0.0033019167 | L31: {=INDEX('1-month SOFR - UST '!$Q$9:$Q$1048576,MATCH(L$4,'1-month SOFR - UST '!$O$9:$O$1048576,0))/12} -> 0.00312115 | M31: {=INDEX('1-month SOFR - UST '!$Q$9:$Q$1048576,MATCH(M$4,'1-month SOFR - UST '!$O$9:$O$1048576,0))/12} -> 0.0030814667 | N31: {=INDEX('1-month SOFR - UST '!$Q$9:$Q$1048576,MATCH(N$4,'1-month SOFR - UST '!$O$9:$O$1048576,0))/12} -> 0.0030439083 | O31: {=INDEX('1-month SOFR - UST '!$Q$9:$Q$1048576,MATCH(O$4,'1-month SOFR - UST '!$O$9:$O$1048576,0))/12} -> 0.0030013 | P31: {=INDEX('1-month SOFR - UST '!$Q$9:$Q$1048576,MATCH(P$4,'1-month SOFR - UST '!$O$9:$O$1048576,0))/12} -> 0.0029483583 | ... NH31: {=INDEX('1-month SOFR - UST '!$Q$9:$Q$1048576,MATCH(NH$4,'1-month SOFR - UST '!$O$9:$O$1048576,0))/12} -> #N/A | NI31: {=INDEX('1-month SOFR - UST '!$Q$9:$Q$1048576,MATCH(NI$6,'1-month SOFR - UST '!$O$9:$O$1048576,0))} -> #N/A
B32: Senior Debt (Refinance) | G32: Spread over SOFR | I32: =$E$39/12 -> 0.0033333333 | J32: =$E$39/12 -> 0.0033333333 | K32: =$E$39/12 -> 0.0033333333 | L32: =$E$39/12 -> 0.0033333333 | M32: =$E$39/12 -> 0.0033333333 | N32: =$E$39/12 -> 0.0033333333 | O32: =$E$39/12 -> 0.0033333333 | P32: =$E$39/12 -> 0.0033333333 | ... NH32: =$E$39/12 -> 0.0033333333 | NI32: x
B33: Refinance | E33: =$E$18<(Model!$O$37) -> TRUE | G33: SOFR Floor | I33: =$E$15/12 -> 0 | J33: =$E$15/12 -> 0 | K33: =$E$15/12 -> 0 | L33: =$E$15/12 -> 0 | M33: =$E$15/12 -> 0 | N33: =$E$15/12 -> 0 | O33: =$E$15/12 -> 0 | P33: =$E$15/12 -> 0 | ... NH33: =$E$15/12 -> 0 | NI33: x
B34: Amount | E34: =E36 -> 51240548 | G34: Interest Rate Used | I34: =IF(C37=2,$E$12/12,MIN(MAX(I33,I31),I30)+I32) -> 0.0067959833 | J34: =IF(D37=2,$E$12/12,MIN(MAX(J33,J31),J30)+J32) -> 0.006671475 | K34: =IF(E37=2,$E$12/12,MIN(MAX(K33,K31),K30)+K32) -> 0.00663525 | L34: =IF(F36=2,$E$12/12,MIN(MAX(L33,L31),L30)+L32) -> 0.0064544833 | M34: =IF(G42=2,$E$12/12,MIN(MAX(M33,M31),M30)+M32) -> 0.0064148 | N34: =IF(H42=2,$E$12/12,MIN(MAX(N33,N31),N30)+N32) -> 0.0063772417 | O34: =IF(I42=2,$E$12/12,MIN(MAX(O33,O31),O30)+O32) -> 0.0063346333 | P34: =IF(J42=2,$E$12/12,MIN(MAX(P33,P31),P30)+P32) -> 0.0062816917 | Q34: =IF(K42=2,$E$12/12,MIN(MAX(Q33,Q31),Q30)+Q32) -> 0.0062500833 | R34: =IF(L42=2,$E$12/12,MIN(MAX(R33,R31),R30)+R32) -> 0.0061274667 | S34: =IF(M42=2,$E$12/12,MIN(MAX(S33,S31),S30)+S32) -> 0.0061036833 | T34: =IF(N42=2,$E$12/12,MIN(MAX(T33,T31),T30)+T32) -> 0.0061039417 | ... NH34: =IF(NB42=2,$E$12/12,MIN(MAX(NH33,NH31),NH30)+NH32) -> #N/A | NI34: x
B35: DY FTM NOI | C35: 0.11 | D35: =Model!$N$39 -> 4440847.5 | E35: =$D$35/$C$35 -> 40371341
B36: Stabilized Value | C36: =Model!I33 -> 0.75 | D36: =Model!$O$39 -> 68320731 | E36: =$C$36*$D$36 -> 51240548 | G36: Beginning Balance | I36: =H43 | J36: =I43 -> 0 | K36: =J43 -> 0 | L36: =K43 -> 0 | M36: =L43 -> 0 | N36: =M43 -> 0 | O36: =N43 -> 0 | P36: =O43 -> 0 | ... NH36: =NG43 -> #N/A | NI36: x
B37: Loan Fees | C37: =Model!$I$45 -> 0.01 | E37: =E34*'Debt & Refi'!$C$37 -> 512405.48 | G37: Payment | I37: =IF(I3="","",AND(I3>$E$43,I3<=$E$44)*((I3<=$E$45)*I36*I39+(I3>$E$45)*PMT(I39,$E$42,-$E$34))) -> 0 | J37: =IF(J3="","",AND(J3>$E$43,J3<=$E$44)*((J3<=$E$45)*J36*J39+(J3>$E$45)*PMT(J39,$E$42,-$E$34))) -> 0 | K37: =IF(K3="","",AND(K3>$E$43,K3<=$E$44)*((K3<=$E$45)*K36*K39+(K3>$E$45)*PMT(K39,$E$42,-$E$34))) -> 0 | L37: =IF(L3="","",AND(L3>$E$43,L3<=$E$44)*((L3<=$E$45)*L36*L39+(L3>$E$45)*PMT(L39,$E$42,-$E$34))) -> 0 | M37: =IF(M3="","",AND(M3>$E$43,M3<=$E$44)*((M3<=$E$45)*M36*M39+(M3>$E$45)*PMT(M39,$E$42,-$E$34))) -> 0 | N37: =IF(N3="","",AND(N3>$E$43,N3<=$E$44)*((N3<=$E$45)*N36*N39+(N3>$E$45)*PMT(N39,$E$42,-$E$34))) -> 0 | O37: =IF(O3="","",AND(O3>$E$43,O3<=$E$44)*((O3<=$E$45)*O36*O39+(O3>$E$45)*PMT(O39,$E$42,-$E$34))) -> 0 | P37: =IF(P3="","",AND(P3>$E$43,P3<=$E$44)*((P3<=$E$45)*P36*P39+(P3>$E$45)*PMT(P39,$E$42,-$E$34))) -> 0 | ... NH37: =IF(NH3="","",AND(NH3>$E$43,NH3<=$E$44)*((NH3<=$E$45)*NH36*NH39+(NH3>$E$45)*PMT(NH39,$E$42,-$E$34))) -> #N/A | NI37: =IF(NI22="","",AND(NI22>$E$43,NI22<=$E$44)*((NI22<=$E$45)*NI36*NI39+(NI22>$E$45)*PMT(NI39,$E$42,-$E$34)))
B38: Variable (1) or Fixed (2) | C38: =Model!$I$37 -> 1 | E38: =Model!$I$40 -> 0.0327905 | G38: Interest | I38: =I36*I39 -> 0 | J38: =J36*J39 -> 0 | K38: =K36*K39 -> 0 | L38: =L36*L39 -> 0 | M38: =M36*M39 -> 0 | N38: =N36*N39 -> 0 | O38: =O36*O39 -> 0 | P38: =P36*P39 -> 0 | ... NH38: =NH36*NH39 -> #N/A | NI38: x
B39: Spread over SOFR | E39: =Model!$I$38 -> 0.04 | G39: Rate (Monthly) | I39: =I34 -> 0.0067959833 | J39: =J34 -> 0.006671475 | K39: =K34 -> 0.00663525 | L39: =L34 -> 0.0064544833 | M39: =M34 -> 0.0064148 | N39: =N34 -> 0.0063772417 | O39: =O34 -> 0.0063346333 | P39: =P34 -> 0.0062816917 | ... NH39: =NH34 -> #N/A | NI39: x
B40: SOFR Ceiling | E40: =Model!$I$42 -> 1 | G40: Principal | I40: =I37-I38 -> 0 | J40: =J37-J38 -> 0 | K40: =K37-K38 -> 0 | L40: =L37-L38 -> 0 | M40: =M37-M38 -> 0 | N40: =N37-N38 -> 0 | O40: =O37-O38 -> 0 | P40: =P37-P38 -> 0 | ... NH40: =NH37-NH38 -> #N/A | NI40: x
B41: SOFR Floor | E41: =Model!$I$41 -> 0 | G41: Loan Funding | I41: =IF(I3=$E$43,$E$34,0) -> 0 | J41: =IF(J3=$E$43,$E$34,0) -> 0 | K41: =IF(K3=$E$43,$E$34,0) -> 0 | L41: =IF(L3=$E$43,$E$34,0) -> 0 | M41: =IF(M3=$E$43,$E$34,0) -> 0 | N41: =IF(N3=$E$43,$E$34,0) -> 0 | O41: =IF(O3=$E$43,$E$34,0) -> 0 | P41: =IF(P3=$E$43,$E$34,0) -> 0 | ... NH41: =IF(NH3=$E$43,$E$34,0) -> 0 | NI41: =IF(NI22=$D$3,$E$34,0) -> 51240548
B42: Amortization | D42: =$E$16/12 -> 30 | E42: =Model!$I$44*12 -> 360 | G42: Loan Payoff | I42: =IF(I3=$E$44,H43-I40,0) -> 0 | J42: =IF(J3=$E$44,I43-J40,0) -> 0 | K42: =IF(K3=$E$44,J43-K40,0) -> 0 | L42: =IF(L3=$E$44,K43-L40,0) -> 0 | M42: =IF(M3=$E$44,L43-M40,0) -> 0 | N42: =IF(N3=$E$44,M43-N40,0) -> 0 | O42: =IF(O3=$E$44,N43-O40,0) -> 0 | P42: =IF(P3=$E$44,O43-P40,0) -> 0 | ... NH42: =IF(NH3=$E$44,NG43-NH40,0) -> 0 | NI42: =IF(NI22=$E$44,NH43-NI40,0) -> 0
B43: Funding Month | E43: =Model!$O$29 -> 30 | G43: Ending Balance | I43: =I36-I40+I41-I42 -> 0 | J43: =J36-J40+J41-J42 -> 0 | K43: =K36-K40+K41-K42 -> 0 | L43: =L36-L40+L41-L42 -> 0 | M43: =M36-M40+M41-M42 -> 0 | N43: =N36-N40+N41-N42 -> 0 | O43: =O36-O40+O41-O42 -> 0 | P43: =P36-P40+P41-P42 -> 0 | ... NH43: =NH36-NH40+NH41-NH42 -> #N/A | NI43: x
B44: Payoff Month | E44: =Model!$O$37 -> 52 | NI44: x
B45: Interest-Only Period | D45: =$E$19/12 -> 4 | E45: =Model!$O$28 -> 48 | G45: Total Permanent Financing | NI45: x
B46: Fixed Amort. Payments (Monthly) | E46: =PMT(E38/12,E42,-E34) -> 223819.88 | G46: Beginning Balance | I46: =I13+I36 -> 0 | J46: =J13+J36 -> 23187000 | K46: =K13+K36 -> 23187000 | L46: =L13+L36 -> 23187000 | M46: =M13+M36 -> 23187000 | N46: =N13+N36 -> 23187000 | O46: =O13+O36 -> 23187000 | P46: =P13+P36 -> 23187000 | ... NH46: =NH13+NH36 -> #N/A | NI46: x
B47: Fixed IO Payments (Monthly) | E47: =E34*(E38/12) -> 140016.93 | G47: Payment | I47: =I14+I37 -> 0 | J47: =J14+J37 -> 145030.24 | K47: =K14+K37 -> 144190.29 | L47: =L14+L37 -> 139998.86 | M47: =M14+M37 -> 139078.72 | N47: =N14+N37 -> 138207.85 | O47: =O14+O37 -> 137219.89 | P47: =P14+P37 -> 135992.33 | ... NH47: =NH14+NH37 -> #N/A | NI47: x
B48: Payoff @ Loan Maturity | E48: =MAX(I42:NH42) -> 51088151 | G48: Interest | I48: =I15+I38 -> 0 | J48: =J15+J38 -> 145030.24 | K48: =K15+K38 -> 144190.29 | L48: =L15+L38 -> 139998.86 | M48: =M15+M38 -> 139078.72 | N48: =N15+N38 -> 138207.85 | O48: =O15+O38 -> 137219.89 | P48: =P15+P38 -> 135992.33 | ... NH48: =NH15+NH38 -> #N/A | NI48: x
B49: Capitalized Interest | E49: =SUM($I$40:$BF$40) -> 37894.508 | G49: Principal | I49: =I17+I40 -> 0 | J49: =J17+J40 -> 0 | K49: =K17+K40 -> 0 | L49: =L17+L40 -> 0 | M49: =M17+M40 -> 0 | N49: =N17+N40 -> 0 | O49: =O17+O40 -> 0 | P49: =P17+P40 -> 0 | ... NH49: =NH17+NH40 -> #N/A | NI49: x
G50: Loan Funding | I50: =I18+I41 -> 23187000 | J50: =J18+J41 -> 0 | K50: =K18+K41 -> 0 | L50: =L18+L41 -> 0 | M50: =M18+M41 -> 0 | N50: =N18+N41 -> 0 | O50: =O18+O41 -> 0 | P50: =P18+P41 -> 0 | ... NH50: =NH18+NH41 -> 0 | NI50: x
B51: SENIOR + REFI CAPITALIZED INTEREST | E51: =SUM($I$17:$BF$17) -> 0 | G51: Loan Payoff | I51: =I19+I42 -> 0 | J51: =J19+J42 -> 0 | K51: =K19+K42 -> 0 | L51: =L19+L42 -> 0 | M51: =M19+M42 -> 0 | N51: =N19+N42 -> 0 | O51: =O19+O42 -> 0 | P51: =P19+P42 -> 0 | ... NH51: =NH19+NH42 -> 0 | NI51: x
G52: Ending Balance | I52: =I20+I43 -> 23187000 | J52: =J20+J43 -> 23187000 | K52: =K20+K43 -> 23187000 | L52: =L20+L43 -> 23187000 | M52: =M20+M43 -> 23187000 | N52: =N20+N43 -> 23187000 | O52: =O20+O43 -> 23187000 | P52: =P20+P43 -> 23187000 | ... NH52: =NH20+NH43 -> #N/A | NI52: x

Sheet Debt Schedule
A1: =Model!C3 -> Kimpton Anglers | J1: =EOMONTH(TODAY(),1) -> 46081
B2: Borrower | C2: TBD | M2: Year | O2: ='Debt & Refi'!I2 -> 0 | P2: ='Debt & Refi'!J2 -> 1 | Q2: ='Debt & Refi'!K2 -> 1 | R2: ='Debt & Refi'!L2 -> 1 | S2: ='Debt & Refi'!M2 -> 1 | T2: ='Debt & Refi'!N2 -> 1 | U2: ='Debt & Refi'!O2 -> 1 | V2: ='Debt & Refi'!P2 -> 1 | ... NN2: ='Debt & Refi'!NH2 -> 31
B3: Lender | C3: TBD | M3: Month | O3: ='Debt & Refi'!I3 -> 0 | P3: ='Debt & Refi'!J3 -> 1 | Q3: ='Debt & Refi'!K3 -> 2 | R3: ='Debt & Refi'!L3 -> 3 | S3: ='Debt & Refi'!M3 -> 4 | T3: ='Debt & Refi'!N3 -> 5 | U3: ='Debt & Refi'!O3 -> 6 | V3: ='Debt & Refi'!P3 -> 7 | ... NN3: ='Debt & Refi'!NH3 -> 363
B4: Original Total Loan Amount | C4: =++SUM(C5:C6) -> 65000000 | M4: Date | O4: ='Debt & Refi'!I4 -> 45930 | P4: ='Debt & Refi'!J4 -> 45961 | Q4: ='Debt & Refi'!K4 -> 45991 | R4: ='Debt & Refi'!L4 -> 46022 | S4: ='Debt & Refi'!M4 -> 46053 | T4: ='Debt & Refi'!N4 -> 46081 | U4: ='Debt & Refi'!O4 -> 46112 | V4: ='Debt & Refi'!P4 -> 46142 | ... NN4: ='Debt & Refi'!NH4 -> 56979
B5: Senior Loan Amount | C5: 35000000 | E5: Rate: SOFR + | F5: 0.05 | M5: Senior Debt
B6: PACE Loan Amount | C6: 30000000 | E6: Rate: SOFR + | F6: 0.05 | M6: Interest Rate
B7: Current Total Loan Balance | C7: =SUM(C8:C9) -> #N/A | M7: SOFR Ceiling | O7: ='Debt & Refi'!I7 -> 0.083333333 | P7: ='Debt & Refi'!J7 -> 0.083333333 | Q7: ='Debt & Refi'!K7 -> 0.083333333 | R7: ='Debt & Refi'!L7 -> 0.083333333 | S7: ='Debt & Refi'!M7 -> 0.083333333 | T7: ='Debt & Refi'!N7 -> 0.083333333 | U7: ='Debt & Refi'!O7 -> 0.083333333 | V7: ='Debt & Refi'!P7 -> 0.083333333 | ... NN7: ='Debt & Refi'!NH7 -> 0.083333333
B8: Senior Loan Balance | C8: {=INDEX($J$45:$BK$45,MATCH($J$1,$J$42:$BK$42))} -> #N/A | E8: Rate: SOFR + | F8: =++F5 -> 0.05 | M8: Floating SOFR | O8: ='Debt & Refi'!I8 -> 0.00346265 | P8: ='Debt & Refi'!J8 -> 0.0033381417 | Q8: ='Debt & Refi'!K8 -> 0.0033019167 | R8: ='Debt & Refi'!L8 -> 0.00312115 | S8: ='Debt & Refi'!M8 -> 0.0030814667 | T8: ='Debt & Refi'!N8 -> 0.0030439083 | U8: ='Debt & Refi'!O8 -> 0.0030013 | V8: ='Debt & Refi'!P8 -> 0.0029483583 | ... NN8: ='Debt & Refi'!NH8 -> #N/A
B9: Construction Loan Balance | C9: {=INDEX(#REF!,MATCH($J$1,$J$42:$BK$42))} -> #N/A | E9: Rate: SOFR + | F9: =F5 -> 0.05 | M9: Spread over SOFR | O9: ='Debt & Refi'!I9 -> 0.0029166667 | P9: ='Debt & Refi'!J9 -> 0.0029166667 | Q9: ='Debt & Refi'!K9 -> 0.0029166667 | R9: ='Debt & Refi'!L9 -> 0.0029166667 | S9: ='Debt & Refi'!M9 -> 0.0029166667 | T9: ='Debt & Refi'!N9 -> 0.0029166667 | U9: ='Debt & Refi'!O9 -> 0.0029166667 | V9: ='Debt & Refi'!P9 -> 0.0029166667 | ... NN9: ='Debt & Refi'!NH9 -> 0.0029166667
B10: Origination Date | C10: 46112 | M10: SOFR Floor | O10: ='Debt & Refi'!I10 -> 0 | P10: ='Debt & Refi'!J10 -> 0 | Q10: ='Debt & Refi'!K10 -> 0 | R10: ='Debt & Refi'!L10 -> 0 | S10: ='Debt & Refi'!M10 -> 0 | T10: ='Debt & Refi'!N10 -> 0 | U10: ='Debt & Refi'!O10 -> 0 | V10: ='Debt & Refi'!P10 -> 0 | ... NN10: ='Debt & Refi'!NH10 -> 0
B11: Initial Maturity Date | C11: =++EDATE(C10,36) -> 47208 | E11: Current Maturity | F11: =++C11 -> 47208 | M11: Interest Rate Used | O11: ='Debt & Refi'!I11 -> 0.0063793167 | P11: ='Debt & Refi'!J11 -> 0.0062548083 | Q11: ='Debt & Refi'!K11 -> 0.0062185833 | R11: ='Debt & Refi'!L11 -> 0.0060378167 | S11: ='Debt & Refi'!M11 -> 0.0059981333 | T11: ='Debt & Refi'!N11 -> 0.005960575 | U11: ='Debt & Refi'!O11 -> 0.0059179667 | V11: ='Debt & Refi'!P11 -> 0.005865025 | ... NN11: ='Debt & Refi'!NH11 -> #N/A
B12: Extension Options | C12: Two one-year extension terms
B13: Rate Cap | C13: 0.06 | E13: Expiry Date: | F13: 46200 | M13: Beginning Balance | O13: ='Debt & Refi'!I13 | P13: ='Debt & Refi'!J13 -> 23187000 | Q13: ='Debt & Refi'!K13 -> 23187000 | R13: ='Debt & Refi'!L13 -> 23187000 | S13: ='Debt & Refi'!M13 -> 23187000 | T13: ='Debt & Refi'!N13 -> 23187000 | U13: ='Debt & Refi'!O13 -> 23187000 | V13: ='Debt & Refi'!P13 -> 23187000 | ... NN13: ='Debt & Refi'!NH13 -> #N/A
B14: Rate Ceiling | C14: N/A | E14: Rate Floor | F14: 0.03 | M14: Payment | O14: ='Debt & Refi'!I14 -> 0 | P14: ='Debt & Refi'!J14 -> 145030.24 | Q14: ='Debt & Refi'!K14 -> 144190.29 | R14: ='Debt & Refi'!L14 -> 139998.86 | S14: ='Debt & Refi'!M14 -> 139078.72 | T14: ='Debt & Refi'!N14 -> 138207.85 | U14: ='Debt & Refi'!O14 -> 137219.89 | V14: ='Debt & Refi'!P14 -> 135992.33 | ... NN14: ='Debt & Refi'!NH14 -> #N/A
B15: Current Blended Interest Rate | C15: N/A | M15: Interest | O15: ='Debt & Refi'!I15 -> 0 | P15: ='Debt & Refi'!J15 -> 145030.24 | Q15: ='Debt & Refi'!K15 -> 144190.29 | R15: ='Debt & Refi'!L15 -> 139998.86 | S15: ='Debt & Refi'!M15 -> 139078.72 | T15: ='Debt & Refi'!N15 -> 138207.85 | U15: ='Debt & Refi'!O15 -> 137219.89 | V15: ='Debt & Refi'!P15 -> 135992.33 | ... NN15: ='Debt & Refi'!NH15 -> #N/A
B16: Effective Rate (with Cap) | C16: =IFERROR(C13+F5,"N/A") -> 0.11 | M16: Rate (Monthly) | O16: ='Debt & Refi'!I16 -> 0.0063793167 | P16: ='Debt & Refi'!J16 -> 0.0062548083 | Q16: ='Debt & Refi'!K16 -> 0.0062185833 | R16: ='Debt & Refi'!L16 -> 0.0060378167 | S16: ='Debt & Refi'!M16 -> 0.0059981333 | T16: ='Debt & Refi'!N16 -> 0.005960575 | U16: ='Debt & Refi'!O16 -> 0.0059179667 | V16: ='Debt & Refi'!P16 -> 0.005865025 | ... NN16: ='Debt & Refi'!NH16
B17: Interest Only | C17: Yes | M17: Principal | O17: ='Debt & Refi'!I17 -> 0 | P17: ='Debt & Refi'!J17 -> 0 | Q17: ='Debt & Refi'!K17 -> 0 | R17: ='Debt & Refi'!L17 -> 0 | S17: ='Debt & Refi'!M17 -> 0 | T17: ='Debt & Refi'!N17 -> 0 | U17: ='Debt & Refi'!O17 -> 0 | V17: ='Debt & Refi'!P17 -> 0 | ... NN17: ='Debt & Refi'!NH17 -> #N/A
B18: Cap or Swap Expiry Date | C18: =++EDATE(C10,24) -> 46843 | M18: Loan Funding | O18: ='Debt & Refi'!I18 -> 23187000 | P18: ='Debt & Refi'!J18 -> 0 | Q18: ='Debt & Refi'!K18 -> 0 | R18: ='Debt & Refi'!L18 -> 0 | S18: ='Debt & Refi'!M18 -> 0 | T18: ='Debt & Refi'!N18 -> 0 | U18: ='Debt & Refi'!O18 -> 0 | V18: ='Debt & Refi'!P18 -> 0 | ... NN18: ='Debt & Refi'!NH18 -> 0
B19: Lockout Prepayment Date | C19: N/A | M19: Loan Payoff | O19: ='Debt & Refi'!I19 -> 0 | P19: ='Debt & Refi'!J19 -> 0 | Q19: ='Debt & Refi'!K19 -> 0 | R19: ='Debt & Refi'!L19 -> 0 | S19: ='Debt & Refi'!M19 -> 0 | T19: ='Debt & Refi'!N19 -> 0 | U19: ='Debt & Refi'!O19 -> 0 | V19: ='Debt & Refi'!P19 -> 0 | ... NN19: ='Debt & Refi'!NH19 -> 0
B20: Prepayment Fee | C20: Greater of (i) yield maintenance through thr 18th payment date and (II) 1% of loan amount | M20: Ending Balance | O20: ='Debt & Refi'!I20 -> 23187000 | P20: ='Debt & Refi'!J20 -> 23187000 | Q20: ='Debt & Refi'!K20 -> 23187000 | R20: ='Debt & Refi'!L20 -> 23187000 | S20: ='Debt & Refi'!M20 -> 23187000 | T20: ='Debt & Refi'!N20 -> 23187000 | U20: ='Debt & Refi'!O20 -> 23187000 | V20: ='Debt & Refi'!P20 -> 23187000 | ... NN20: ='Debt & Refi'!NH20 -> #N/A
B21: Open Prepayment Date | C21: =++EDATE(C10,18) -> 46660
B22: Debt Yield Threshold (i) | C22: 0.1 | D22: Until: | E22: =EOMONTH(C10,39) -> 47299 | G22: Test Frequency: | H22: Quarterly starting 12/31/2028 | M22: Senior Debt (Refinance) | NO22: x
B23: Debt Yield Threshold (ii) | C23: 0.11 | D23: Until: | E23: =EOMONTH(E22,6) -> 47483 | M23: Interest Rate | NO23: x
B24: Debt Yield Threshold (Senior + PACE) | C24: N/A | D24: Until: | E24: =E23 -> 47483 | G24: Test Frequency: | H24: Quarterly starting 6/30/2028 | M24: SOFR Ceiling | O24: ='Debt & Refi'!I30 -> 0.083333333 | P24: ='Debt & Refi'!J30 -> 0.083333333 | Q24: ='Debt & Refi'!K30 -> 0.083333333 | R24: ='Debt & Refi'!L30 -> 0.083333333 | S24: ='Debt & Refi'!M30 -> 0.083333333 | T24: ='Debt & Refi'!N30 -> 0.083333333 | U24: ='Debt & Refi'!O30 -> 0.083333333 | V24: ='Debt & Refi'!P30 -> 0.083333333 | ... NO24: ='Debt & Refi'!NI30 -> x
B25: DSCR Threshold (i) | C25: 1 | D25: Until: | E25: =E22 -> 47299 | G25: Test Frequency: | H25: Quarterly starting 12/31/2028 | M25: Floating SOFR | O25: ='Debt & Refi'!I31 -> 0.00346265 | P25: ='Debt & Refi'!J31 -> 0.0033381417 | Q25: ='Debt & Refi'!K31 -> 0.0033019167 | R25: ='Debt & Refi'!L31 -> 0.00312115 | S25: ='Debt & Refi'!M31 -> 0.0030814667 | T25: ='Debt & Refi'!N31 -> 0.0030439083 | U25: ='Debt & Refi'!O31 -> 0.0030013 | V25: ='Debt & Refi'!P31 -> 0.0029483583 | ... NO25: ='Debt & Refi'!NI31 -> #N/A
B26: DSCR Threshold (ii) | C26: 1.2 | D26: Until: | E26: =EOMONTH(E25,6) -> 47483 | M26: Spread over SOFR | O26: ='Debt & Refi'!I32 -> 0.0033333333 | P26: ='Debt & Refi'!J32 -> 0.0033333333 | Q26: ='Debt & Refi'!K32 -> 0.0033333333 | R26: ='Debt & Refi'!L32 -> 0.0033333333 | S26: ='Debt & Refi'!M32 -> 0.0033333333 | T26: ='Debt & Refi'!N32 -> 0.0033333333 | U26: ='Debt & Refi'!O32 -> 0.0033333333 | V26: ='Debt & Refi'!P32 -> 0.0033333333 | ... NO26: ='Debt & Refi'!NI32 -> x
B27: DSCR Threshold (Senior + PACE) | C27: 1.25 | D27: Until: | E27: =E26 -> 47483 | G27: Test Frequency: | H27: Quarterly starting 12/31/2028 | M27: SOFR Floor | O27: ='Debt & Refi'!I33 -> 0 | P27: ='Debt & Refi'!J33 -> 0 | Q27: ='Debt & Refi'!K33 -> 0 | R27: ='Debt & Refi'!L33 -> 0 | S27: ='Debt & Refi'!M33 -> 0 | T27: ='Debt & Refi'!N33 -> 0 | U27: ='Debt & Refi'!O33 -> 0 | V27: ='Debt & Refi'!P33 -> 0 | ... NO27: ='Debt & Refi'!NI33 -> x
B28: DY Cure / Carry Reserve (i) | C28: =++C22+0.25% -> 0.1025 | D28: For 2 consecutive quarters; 25 bps above applicable DY threshold | M28: Interest Rate Used | O28: ='Debt & Refi'!I34 -> 0.0067959833 | P28: ='Debt & Refi'!J34 -> 0.006671475 | Q28: ='Debt & Refi'!K34 -> 0.00663525 | R28: ='Debt & Refi'!L34 -> 0.0064544833 | S28: ='Debt & Refi'!M34 -> 0.0064148 | T28: ='Debt & Refi'!N34 -> 0.0063772417 | U28: ='Debt & Refi'!O34 -> 0.0063346333 | V28: ='Debt & Refi'!P34 -> 0.0062816917 | ... NO28: ='Debt & Refi'!NI34 -> x
B29: DY Cure / Carry Reserve (ii) | C29: =++C23+0.25% -> 0.1125 | D29: For 2 consecutive quarters; 25 bps above applicable DY threshold
B30: DSCR Cure / Carry Reserve | C30: N/A | M30: Beginning Balance | O30: ='Debt & Refi'!I36 | P30: ='Debt & Refi'!J36 -> 0 | Q30: ='Debt & Refi'!K36 -> 0 | R30: ='Debt & Refi'!L36 -> 0 | S30: ='Debt & Refi'!M36 -> 0 | T30: ='Debt & Refi'!N36 -> 0 | U30: ='Debt & Refi'!O36 -> 0 | V30: ='Debt & Refi'!P36 -> 0 | ... NO30: ='Debt & Refi'!NI36 -> x
B31: LTV Ratio Max | C31: 0.65 | M31: Payment | O31: ='Debt & Refi'!I37 -> 0 | P31: ='Debt & Refi'!J37 -> 0 | Q31: ='Debt & Refi'!K37 -> 0 | R31: ='Debt & Refi'!L37 -> 0 | S31: ='Debt & Refi'!M37 -> 0 | T31: ='Debt & Refi'!N37 -> 0 | U31: ='Debt & Refi'!O37 -> 0 | V31: ='Debt & Refi'!P37 -> 0 | ... NO31: ='Debt & Refi'!NI37
B32: Debt Yield - extension 1 | C32: 0.1025 | D32: Only for extension option | M32: Interest | O32: ='Debt & Refi'!I38 -> 0 | P32: ='Debt & Refi'!J38 -> 0 | Q32: ='Debt & Refi'!K38 -> 0 | R32: ='Debt & Refi'!L38 -> 0 | S32: ='Debt & Refi'!M38 -> 0 | T32: ='Debt & Refi'!N38 -> 0 | U32: ='Debt & Refi'!O38 -> 0 | V32: ='Debt & Refi'!P38 -> 0 | ... NO32: ='Debt & Refi'!NI38 -> x
B33: Debt Yield - extension 2 | C33: 0.115 | D33: Only for extension option | M33: Rate (Monthly) | O33: ='Debt & Refi'!I39 -> 0.0067959833 | P33: ='Debt & Refi'!J39 -> 0.006671475 | Q33: ='Debt & Refi'!K39 -> 0.00663525 | R33: ='Debt & Refi'!L39 -> 0.0064544833 | S33: ='Debt & Refi'!M39 -> 0.0064148 | T33: ='Debt & Refi'!N39 -> 0.0063772417 | U33: ='Debt & Refi'!O39 -> 0.0063346333 | V33: ='Debt & Refi'!P39 -> 0.0062816917 | ... NO33: ='Debt & Refi'!NI39 -> x
B34: Cash Trap | C34: Yes | D34: Two consecutive quarters of threshold failures | M34: Principal | O34: ='Debt & Refi'!I40 -> 0 | P34: ='Debt & Refi'!J40 -> 0 | Q34: ='Debt & Refi'!K40 -> 0 | R34: ='Debt & Refi'!L40 -> 0 | S34: ='Debt & Refi'!M40 -> 0 | T34: ='Debt & Refi'!N40 -> 0 | U34: ='Debt & Refi'!O40 -> 0 | V34: ='Debt & Refi'!P40 -> 0 | ... NO34: ='Debt & Refi'!NI40 -> x
B35: Distribution Blocker | C35: N/A | M35: Loan Funding | O35: ='Debt & Refi'!I41 -> 0 | P35: ='Debt & Refi'!J41 -> 0 | Q35: ='Debt & Refi'!K41 -> 0 | R35: ='Debt & Refi'!L41 -> 0 | S35: ='Debt & Refi'!M41 -> 0 | T35: ='Debt & Refi'!N41 -> 0 | U35: ='Debt & Refi'!O41 -> 0 | V35: ='Debt & Refi'!P41 -> 0 | ... NO35: ='Debt & Refi'!NI41 -> 51240548
B36: Exit Fee | C36: N/A | M36: Loan Payoff | O36: ='Debt & Refi'!I42 -> 0 | P36: ='Debt & Refi'!J42 -> 0 | Q36: ='Debt & Refi'!K42 -> 0 | R36: ='Debt & Refi'!L42 -> 0 | S36: ='Debt & Refi'!M42 -> 0 | T36: ='Debt & Refi'!N42 -> 0 | U36: ='Debt & Refi'!O42 -> 0 | V36: ='Debt & Refi'!P42 -> 0 | ... NO36: ='Debt & Refi'!NI42 -> 0
M37: Ending Balance | O37: ='Debt & Refi'!I43 -> 0 | P37: ='Debt & Refi'!J43 -> 0 | Q37: ='Debt & Refi'!K43 -> 0 | R37: ='Debt & Refi'!L43 -> 0 | S37: ='Debt & Refi'!M43 -> 0 | T37: ='Debt & Refi'!N43 -> 0 | U37: ='Debt & Refi'!O43 -> 0 | V37: ='Debt & Refi'!P43 -> 0 | ... NO37: ='Debt & Refi'!NI43 -> x
B41: Quarterly Analysis
C42: 47118 | D42: =EOMONTH(C42,3) -> 47208 | E42: =EOMONTH(D42,3) -> 47299 | F42: =EOMONTH(E42,3) -> 47391 | G42: =EOMONTH(F42,3) -> 47483 | H42: =EOMONTH(G42,3) -> 47573 | J42: 46783 | K42: =EOMONTH(J42,1) -> 46812 | L42: =EOMONTH(K42,1) -> 46843 | M42: =EOMONTH(L42,1) -> 46873 | N42: =EOMONTH(M42,1) -> 46904 | O42: =EOMONTH(N42,1) -> 46934 | P42: =EOMONTH(O42,1) -> 46965 | Q42: =EOMONTH(P42,1) -> 46996 | R42: =EOMONTH(Q42,1) -> 47026 | ... BK42: =EOMONTH(BJ42,1) -> 48395
C43: Forecast | D43: Forecast | E43: Forecast | F43: Forecast | G43: Forecast | H43: Forecast | J43: Forecast | K43: Forecast | L43: Forecast | M43: Forecast | N43: Forecast | O43: Forecast | P43: Forecast | Q43: Forecast | R43: Forecast | S43: Forecast | T43: Forecast | U43: Forecast | V43: Forecast | W43: Forecast | X43: Forecast | Y43: Forecast | Z43: Forecast | AA43: Forecast | AB43: Forecast | AC43: Forecast | AD43: Forecast | AE43: Forecast | AF43: Forecast | AG43: Forecast | AH43: Forecast | AI43: Forecast | AJ43: Forecast | AK43: Forecast | AL43: Forecast | AM43: Forecast | AN43: Forecast | AO43: Forecast | AP43: Forecast | AQ43: Forecast | AR43: Forecast | AS43: Forecast | AT43: Forecast | AU43: Forecast | AV43: Forecast | AW43: Forecast | AX43: Forecast | AY43: Forecast | AZ43: Forecast | BA43: Forecast | BB43: Forecast | BC43: Forecast | BD43: Forecast | BE43: Forecast | BF43: Forecast | BG43: Forecast | BH43: Forecast | BI43: Forecast | BJ43: Forecast | BK43: Forecast
B44: Loan Balance | C44: =SUM(C45) -> 51240548 | D44: =SUM(D45) -> 51240548 | E44: =SUM(E45) -> 51240548 | F44: =SUM(F45) -> 51240548 | G44: =SUM(G45) -> 51164622 | H44: =SUM(H45) -> 0 | J44: =SUM(J45) -> 23187000 | K44: =SUM(K45) -> 23187000 | L44: =SUM(L45) -> 23187000 | M44: =SUM(M45) -> 51240548 | N44: =SUM(N45) -> 51240548 | O44: =SUM(O45) -> 51240548 | P44: =SUM(P45) -> 51240548 | Q44: =SUM(Q45) -> 51240548 | ... BK44: =SUM(BK45) -> 0
B45: Senior Loan Balance | C45: =INDEX($J45:$BK45,MATCH(C$42,$J$42:$BK$42,0)) -> 51240548 | D45: =INDEX($J45:$BK45,MATCH(D$42,$J$42:$BK$42,0)) -> 51240548 | E45: =INDEX($J45:$BK45,MATCH(E$42,$J$42:$BK$42,0)) -> 51240548 | F45: =INDEX($J45:$BK45,MATCH(F$42,$J$42:$BK$42,0)) -> 51240548 | G45: =INDEX($J45:$BK45,MATCH(G$42,$J$42:$BK$42,0)) -> 51164622 | H45: =INDEX($J45:$BK45,MATCH(H$42,$J$42:$BK$42,0)) -> 0 | J45: {=IF(J42<='Debt & Refi'!$E$29,INDEX($N$13:$BV$13,MATCH(J42,$N$4:$BV$4)),INDEX($N$30:$BV$30,MATCH(J42,$N$4:$BV$4)))} -> 23187000 | K45: {=IF(K42<='Debt & Refi'!$E$29,INDEX($N$13:$BV$13,MATCH(K42,$N$4:$BV$4)),INDEX($N$30:$BV$30,MATCH(K42,$N$4:$BV$4)))} -> 23187000 | L45: {=IF(L42<='Debt & Refi'!$E$29,INDEX($N$13:$BV$13,MATCH(L42,$N$4:$BV$4)),INDEX($N$30:$BV$30,MATCH(L42,$N$4:$BV$4)))} -> 23187000 | M45: {=IF(M42<='Debt & Refi'!$E$29,INDEX($N$13:$BV$13,MATCH(M42,$N$4:$BV$4)),INDEX($N$30:$BV$30,MATCH(M42,$N$4:$BV$4)))} -> 51240548 | N45: {=IF(N42<='Debt & Refi'!$E$29,INDEX($N$13:$BV$13,MATCH(N42,$N$4:$BV$4)),INDEX($N$30:$BV$30,MATCH(N42,$N$4:$BV$4)))} -> 51240548 | O45: {=IF(O42<='Debt & Refi'!$E$29,INDEX($N$13:$BV$13,MATCH(O42,$N$4:$BV$4)),INDEX($N$30:$BV$30,MATCH(O42,$N$4:$BV$4)))} -> 51240548 | P45: {=IF(P42<='Debt & Refi'!$E$29,INDEX($N$13:$BV$13,MATCH(P42,$N$4:$BV$4)),INDEX($N$30:$BV$30,MATCH(P42,$N$4:$BV$4)))} -> 51240548 | Q45: {=IF(Q42<='Debt & Refi'!$E$29,INDEX($N$13:$BV$13,MATCH(Q42,$N$4:$BV$4)),INDEX($N$30:$BV$30,MATCH(Q42,$N$4:$BV$4)))} -> 51240548 | ... BK45: {=IF(BK42<='Debt & Refi'!$E$29,INDEX($N$13:$BV$13,MATCH(BK42,$N$4:$BV$4)),INDEX($N$30:$BV$30,MATCH(BK42,$N$4:$BV$4)))} -> 0
B47: NOI FTM | C47: =INDEX($J47:$BK47,MATCH(C$42,$J$42:$BK$42,0)) -> 3908256.8 | D47: =INDEX($J47:$BK47,MATCH(D$42,$J$42:$BK$42,0)) -> 3998523 | E47: =INDEX($J47:$BK47,MATCH(E$42,$J$42:$BK$42,0)) -> 4063114.5 | F47: =INDEX($J47:$BK47,MATCH(F$42,$J$42:$BK$42,0)) -> 4104845.2 | G47: =INDEX($J47:$BK47,MATCH(G$42,$J$42:$BK$42,0)) -> 4178064.7 | H47: =INDEX($J47:$BK47,MATCH(H$42,$J$42:$BK$42,0)) -> 4259388.6 | J47: =SUMIFS($E$91:$XFD$91,$E$90:$XFD$90,">="&EOMONTH(J$42,1),$E$90:$XFD$90,"<="&EOMONTH(J$42,12)) -> 2542267 | K47: =SUMIFS($E$91:$XFD$91,$E$90:$XFD$90,">="&EOMONTH(K$42,1),$E$90:$XFD$90,"<="&EOMONTH(K$42,12)) -> 2715760.5 | L47: =SUMIFS($E$91:$XFD$91,$E$90:$XFD$90,">="&EOMONTH(L$42,1),$E$90:$XFD$90,"<="&EOMONTH(L$42,12)) -> 2879114 | M47: =SUMIFS($E$91:$XFD$91,$E$90:$XFD$90,">="&EOMONTH(M$42,1),$E$90:$XFD$90,"<="&EOMONTH(M$42,12)) -> 3033916.9 | N47: =SUMIFS($E$91:$XFD$91,$E$90:$XFD$90,">="&EOMONTH(N$42,1),$E$90:$XFD$90,"<="&EOMONTH(N$42,12)) -> 3152988.1 | O47: =SUMIFS($E$91:$XFD$91,$E$90:$XFD$90,">="&EOMONTH(O$42,1),$E$90:$XFD$90,"<="&EOMONTH(O$42,12)) -> 3245266.2 | P47: =SUMIFS($E$91:$XFD$91,$E$90:$XFD$90,">="&EOMONTH(P$42,1),$E$90:$XFD$90,"<="&EOMONTH(P$42,12)) -> 3337864.5 | Q47: =SUMIFS($E$91:$XFD$91,$E$90:$XFD$90,">="&EOMONTH(Q$42,1),$E$90:$XFD$90,"<="&EOMONTH(Q$42,12)) -> 3423205.1 | ... BK47: =SUMIFS($E$91:$XFD$91,$E$90:$XFD$90,">="&EOMONTH(BK$42,1),$E$90:$XFD$90,"<="&EOMONTH(BK$42,12)) -> 4966398.4
B48: Debt Service FTM | C48: =INDEX($J48:$BK48,MATCH(C$42,$J$42:$BK$42,0)) -> -3942433 | D48: =INDEX($J48:$BK48,MATCH(D$42,$J$42:$BK$42,0)) -> -3352800.7 | E48: =INDEX($J48:$BK48,MATCH(E$42,$J$42:$BK$42,0)) -> -2398067.5 | F48: =INDEX($J48:$BK48,MATCH(F$42,$J$42:$BK$42,0)) -> -1438440.5 | G48: =INDEX($J48:$BK48,MATCH(G$42,$J$42:$BK$42,0)) -> -360333.71 | H48: =INDEX($J48:$BK48,MATCH(H$42,$J$42:$BK$42,0)) -> 0 | J48: =SUMIFS($E$92:$XFD$92,$E$90:$XFD$90,">="&EOMONTH(J$42,1),$E$90:$XFD$90,"<="&EOMONTH(J$42,12)) -> -3399850.6 | K48: =SUMIFS($E$92:$XFD$92,$E$90:$XFD$90,">="&EOMONTH(K$42,1),$E$90:$XFD$90,"<="&EOMONTH(K$42,12)) -> -3585756.2 | L48: =SUMIFS($E$92:$XFD$92,$E$90:$XFD$90,">="&EOMONTH(L$42,1),$E$90:$XFD$90,"<="&EOMONTH(L$42,12)) -> -3771932.9 | M48: =SUMIFS($E$92:$XFD$92,$E$90:$XFD$90,">="&EOMONTH(M$42,1),$E$90:$XFD$90,"<="&EOMONTH(M$42,12)) -> -3778285.9 | N48: =SUMIFS($E$92:$XFD$92,$E$90:$XFD$90,">="&EOMONTH(N$42,1),$E$90:$XFD$90,"<="&EOMONTH(N$42,12)) -> -3784615.4 | O48: =SUMIFS($E$92:$XFD$92,$E$90:$XFD$90,">="&EOMONTH(O$42,1),$E$90:$XFD$90,"<="&EOMONTH(O$42,12)) -> -3790894.5 | P48: =SUMIFS($E$92:$XFD$92,$E$90:$XFD$90,">="&EOMONTH(P$42,1),$E$90:$XFD$90,"<="&EOMONTH(P$42,12)) -> -3797158.6 | Q48: =SUMIFS($E$92:$XFD$92,$E$90:$XFD$90,">="&EOMONTH(Q$42,1),$E$90:$XFD$90,"<="&EOMONTH(Q$42,12)) -> -3803434.8 | ... BK48: =SUMIFS($E$92:$XFD$92,$E$90:$XFD$90,">="&EOMONTH(BK$42,1),$E$90:$XFD$90,"<="&EOMONTH(BK$42,12)) -> 0
B49: NOI TTM | C49: =INDEX($J49:$BK49,MATCH(C$42,$J$42:$BK$42,0)) -> 2387927.2 | D49: =INDEX($J49:$BK49,MATCH(D$42,$J$42:$BK$42,0)) -> 2879114 | E49: =INDEX($J49:$BK49,MATCH(E$42,$J$42:$BK$42,0)) -> 3245266.2 | F49: =INDEX($J49:$BK49,MATCH(F$42,$J$42:$BK$42,0)) -> 3500087.1 | G49: =INDEX($J49:$BK49,MATCH(G$42,$J$42:$BK$42,0)) -> 3908256.8 | H49: =INDEX($J49:$BK49,MATCH(H$42,$J$42:$BK$42,0)) -> 3998523 | J49: =SUMIFS($E$91:$XFD$91,$E$90:$XFD$90,">="&EOMONTH(J$42,-11),$E$90:$XFD$90,"<="&J$42) -> 271125.76 | K49: =SUMIFS($E$91:$XFD$91,$E$90:$XFD$90,">="&EOMONTH(K$42,-11),$E$90:$XFD$90,"<="&K$42) -> 592226.4 | L49: =SUMIFS($E$91:$XFD$91,$E$90:$XFD$90,">="&EOMONTH(L$42,-11),$E$90:$XFD$90,"<="&L$42) -> 886870.15 | M49: =SUMIFS($E$91:$XFD$91,$E$90:$XFD$90,">="&EOMONTH(M$42,-11),$E$90:$XFD$90,"<="&M$42) -> 1159204.2 | N49: =SUMIFS($E$91:$XFD$91,$E$90:$XFD$90,">="&EOMONTH(N$42,-11),$E$90:$XFD$90,"<="&N$42) -> 1338308.8 | O49: =SUMIFS($E$91:$XFD$91,$E$90:$XFD$90,">="&EOMONTH(O$42,-11),$E$90:$XFD$90,"<="&O$42) -> 1447505.8 | P49: =SUMIFS($E$91:$XFD$91,$E$90:$XFD$90,">="&EOMONTH(P$42,-11),$E$90:$XFD$90,"<="&P$42) -> 1557538.6 | Q49: =SUMIFS($E$91:$XFD$91,$E$90:$XFD$90,">="&EOMONTH(Q$42,-11),$E$90:$XFD$90,"<="&Q$42) -> 1648634.8 | ... BK49: =SUMIFS($E$91:$XFD$91,$E$90:$XFD$90,">="&EOMONTH(BK$42,-11),$E$90:$XFD$90,"<="&BK$42) -> 4693167.9
B50: Debt Service TTM | C50: =INDEX($J50:$BK50,MATCH(C$42,$J$42:$BK$42,0)) -> -3214165.3 | D50: =INDEX($J50:$BK50,MATCH(D$42,$J$42:$BK$42,0)) -> -3771932.9 | E50: =INDEX($J50:$BK50,MATCH(E$42,$J$42:$BK$42,0)) -> -3790894.5 | F50: =INDEX($J50:$BK50,MATCH(F$42,$J$42:$BK$42,0)) -> -3809754.8 | G50: =INDEX($J50:$BK50,MATCH(G$42,$J$42:$BK$42,0)) -> -3942433 | H50: =INDEX($J50:$BK50,MATCH(H$42,$J$42:$BK$42,0)) -> -3352800.7 | J50: =SUMIFS($E$92:$XFD$92,$E$90:$XFD$90,">="&EOMONTH(J$42,-11),$E$90:$XFD$90,"<="&J$42) -> -130476.15 | K50: =SUMIFS($E$92:$XFD$92,$E$90:$XFD$90,">="&EOMONTH(K$42,-11),$E$90:$XFD$90,"<="&K$42) -> -261210.25 | L50: =SUMIFS($E$92:$XFD$92,$E$90:$XFD$90,">="&EOMONTH(L$42,-11),$E$90:$XFD$90,"<="&L$42) -> -392198.44 | M50: =SUMIFS($E$92:$XFD$92,$E$90:$XFD$90,">="&EOMONTH(M$42,-11),$E$90:$XFD$90,"<="&M$42) -> -703561.64 | N50: =SUMIFS($E$92:$XFD$92,$E$90:$XFD$90,">="&EOMONTH(N$42,-11),$E$90:$XFD$90,"<="&N$42) -> -1015492.3 | O50: =SUMIFS($E$92:$XFD$92,$E$90:$XFD$90,">="&EOMONTH(O$42,-11),$E$90:$XFD$90,"<="&O$42) -> -1327970 | P50: =SUMIFS($E$92:$XFD$92,$E$90:$XFD$90,">="&EOMONTH(P$42,-11),$E$90:$XFD$90,"<="&P$42) -> -1641030.1 | Q50: =SUMIFS($E$92:$XFD$92,$E$90:$XFD$90,">="&EOMONTH(Q$42,-11),$E$90:$XFD$90,"<="&Q$42) -> -1954639.8 | ... BK50: =SUMIFS($E$92:$XFD$92,$E$90:$XFD$90,">="&EOMONTH(BK$42,-11),$E$90:$XFD$90,"<="&BK$42) -> 0
B51: Cap Payment TTM (SOFR Cap TBD) | C51: =INDEX($J51:$BK51,MATCH(C$42,$J$42:$BK$42,0)) | D51: =INDEX($J51:$BK51,MATCH(D$42,$J$42:$BK$42,0)) | E51: =INDEX($J51:$BK51,MATCH(E$42,$J$42:$BK$42,0)) | F51: =INDEX($J51:$BK51,MATCH(F$42,$J$42:$BK$42,0)) | G51: =INDEX($J51:$BK51,MATCH(G$42,$J$42:$BK$42,0)) | H51: =INDEX($J51:$BK51,MATCH(H$42,$J$42:$BK$42,0))
B52: Free Cash Flow TTM | C52: =INDEX($J52:$BK52,MATCH(C$42,$J$42:$BK$42,0)) -> -826238.16 | D52: =INDEX($J52:$BK52,MATCH(D$42,$J$42:$BK$42,0)) -> -892818.93 | E52: =INDEX($J52:$BK52,MATCH(E$42,$J$42:$BK$42,0)) -> -545628.32 | F52: =INDEX($J52:$BK52,MATCH(F$42,$J$42:$BK$42,0)) -> -309667.73 | G52: =INDEX($J52:$BK52,MATCH(G$42,$J$42:$BK$42,0)) -> -34176.172 | H52: =INDEX($J52:$BK52,MATCH(H$42,$J$42:$BK$42,0)) -> 645722.35 | J52: =SUM(J49:J51) -> 140649.61 | K52: =SUM(K49:K51) -> 331016.15 | L52: =SUM(L49:L51) -> 494671.7 | M52: =SUM(M49:M51) -> 455642.61 | N52: =SUM(N49:N51) -> 322816.5 | O52: =SUM(O49:O51) -> 119535.84 | P52: =SUM(P49:P51) -> -83491.532 | Q52: =SUM(Q49:Q51) -> -306004.94 | ... BK52: =SUM(BK49:BK51) -> 4693167.9
B53: Free Cash Flow FTM | C53: =INDEX($J53:$BK53,MATCH(C$42,$J$42:$BK$42,0)) -> -34176.172 | D53: =INDEX($J53:$BK53,MATCH(D$42,$J$42:$BK$42,0)) -> 645722.35 | E53: =INDEX($J53:$BK53,MATCH(E$42,$J$42:$BK$42,0)) -> 1665047 | F53: =INDEX($J53:$BK53,MATCH(F$42,$J$42:$BK$42,0)) -> 2666404.7 | G53: =INDEX($J53:$BK53,MATCH(G$42,$J$42:$BK$42,0)) -> 3817731 | H53: =INDEX($J53:$BK53,MATCH(H$42,$J$42:$BK$42,0)) -> 4259388.6 | J53: =SUM(J47:J48,J51) -> -857583.62 | K53: =SUM(K47:K48,K51) -> -869995.7 | L53: =SUM(L47:L48,L51) -> -892818.93 | M53: =SUM(M47:M48,M51) -> -744368.96 | N53: =SUM(N47:N48,N51) -> -631627.23 | O53: =SUM(O47:O48,O51) -> -545628.32 | P53: =SUM(P47:P48,P51) -> -459294.16 | Q53: =SUM(Q47:Q48,Q51) -> -380229.67 | ... BK53: =SUM(BK47:BK48,BK51) -> 4966398.4
B55: DSCR (Senior) * | C55: =INDEX($J55:$BK55,MATCH(C$42,$J$42:$BK$42,0)) -> 0.60569886 | D55: =INDEX($J55:$BK55,MATCH(D$42,$J$42:$BK$42,0)) -> 0.85871911 | E55: =INDEX($J55:$BK55,MATCH(E$42,$J$42:$BK$42,0)) -> 1.3532839 | F55: =INDEX($J55:$BK55,MATCH(F$42,$J$42:$BK$42,0)) -> 2.4332512 | G55: =INDEX($J55:$BK55,MATCH(G$42,$J$42:$BK$42,0)) -> 10.846215 | H55: =INDEX($J55:$BK55,MATCH(H$42,$J$42:$BK$42,0)) -> #DIV/0! | J55: =-(J49/J48) -> 0.079746375 | K55: =-(K49/K48) -> 0.16516081 | L55: =-(L49/L48) -> 0.23512352 | M55: =-(M49/M48) -> 0.30680692 | N55: =-(N49/N48) -> 0.35361818 | O55: =-(O49/O48) -> 0.38183754 | P55: =-(P49/P48) -> 0.41018528 | Q55: =-(Q49/Q48) -> 0.43345947 | ... BK55: =-(BK49/BK48) -> #DIV/0!
B56: DSCR Threshold | C56: =INDEX($J56:$BK56,MATCH(C$42,$J$42:$BK$42,0)) -> 1 | D56: =INDEX($J56:$BK56,MATCH(D$42,$J$42:$BK$42,0)) -> 1 | E56: =INDEX($J56:$BK56,MATCH(E$42,$J$42:$BK$42,0)) -> 1.2 | F56: =INDEX($J56:$BK56,MATCH(F$42,$J$42:$BK$42,0)) -> 1.2 | G56: =INDEX($J56:$BK56,MATCH(G$42,$J$42:$BK$42,0)) -> 1.2 | H56: =INDEX($J56:$BK56,MATCH(H$42,$J$42:$BK$42,0)) -> 1.2 | J56: N/A | K56: N/A | L56: N/A | M56: N/A | N56: N/A | O56: N/A | P56: N/A | Q56: N/A | R56: N/A | S56: N/A | T56: N/A | U56: 1 | V56: 1 | W56: 1 | X56: 1 | Y56: 1 | Z56: 1 | AA56: 1.2 | AB56: 1.2 | AC56: 1.2 | AD56: 1.2 | AE56: 1.2 | AF56: 1.2 | AG56: 1.2 | AH56: 1.2 | AI56: 1.2 | AJ56: 1.2 | AK56: 1.2 | AL56: 1.2 | AM56: 1.2 | AN56: 1.2 | AO56: 1.2 | AP56: 1.2 | AQ56: 1.2 | AR56: 1.2 | AS56: 1.2 | AT56: 1.2 | AU56: 1.2 | AV56: 1.2 | AW56: 1.2 | AX56: 1.2 | AY56: 1.2 | AZ56: 1.2 | BA56: 1.2 | BB56: 1.2 | BC56: 1.2 | BD56: 1.2 | BE56: 1.2 | BF56: 1.2 | BG56: 1.2 | BH56: 1.2 | BI56: 1.2 | BJ56: 1.2 | BK56: 1.2
B58: Debt Yield (Senior) | C58: =INDEX($J58:$BK58,MATCH(C$42,$J$42:$BK$42,0)) -> 0.046602295 | D58: =INDEX($J58:$BK58,MATCH(D$42,$J$42:$BK$42,0)) -> 0.056188196 | E58: =INDEX($J58:$BK58,MATCH(E$42,$J$42:$BK$42,0)) -> 0.063333947 | F58: =INDEX($J58:$BK58,MATCH(F$42,$J$42:$BK$42,0)) -> 0.06830698 | G58: =INDEX($J58:$BK58,MATCH(G$42,$J$42:$BK$42,0)) -> 0.076385922 | H58: =INDEX($J58:$BK58,MATCH(H$42,$J$42:$BK$42,0)) -> #DIV/0! | J58: =J49/J45 -> 0.011693007 | K58: =K49/K45 -> 0.025541312 | L58: =L49/L45 -> 0.038248594 | M58: =M49/M45 -> 0.022622791 | N58: =N49/N45 -> 0.026118159 | O58: =O49/O45 -> 0.028249226 | P58: =P49/P45 -> 0.030396602 | Q58: =Q49/Q45 -> 0.032174418 | ... BK58: =BK49/BK45 -> #DIV/0!
B59: Debt Yield Threshold | C59: =INDEX($J59:$BK59,MATCH(C$42,$J$42:$BK$42,0)) -> 0.1 | D59: =INDEX($J59:$BK59,MATCH(D$42,$J$42:$BK$42,0)) -> 0.1 | E59: =INDEX($J59:$BK59,MATCH(E$42,$J$42:$BK$42,0)) -> 0.1 | F59: =INDEX($J59:$BK59,MATCH(F$42,$J$42:$BK$42,0)) -> 0.11 | G59: =INDEX($J59:$BK59,MATCH(G$42,$J$42:$BK$42,0)) -> 0.11 | H59: =INDEX($J59:$BK59,MATCH(H$42,$J$42:$BK$42,0)) -> 0.11 | J59: N/A | K59: N/A | L59: N/A | M59: N/A | N59: N/A | O59: N/A | P59: N/A | Q59: N/A | R59: N/A | S59: N/A | T59: N/A | U59: 0.1 | V59: 0.1 | W59: 0.1 | X59: 0.1 | Y59: 0.1 | Z59: 0.1 | AA59: 0.1 | AB59: 0.11 | AC59: 0.11 | AD59: 0.11 | AE59: 0.11 | AF59: 0.11 | AG59: 0.11 | AH59: 0.11 | AI59: 0.11 | AJ59: 0.11 | AK59: 0.11 | AL59: 0.11 | AM59: 0.11 | AN59: 0.11 | AO59: 0.11 | AP59: 0.11 | AQ59: 0.11 | AR59: 0.11 | AS59: 0.11 | AT59: 0.11 | AU59: 0.11 | AV59: 0.11 | AW59: 0.11 | AX59: 0.11 | AY59: 0.11 | AZ59: 0.11 | BA59: 0.11 | BB59: 0.11 | BC59: 0.11 | BD59: 0.11 | BE59: 0.11 | BF59: 0.11 | BG59: 0.11 | BH59: 0.11 | BI59: 0.11 | BJ59: 0.11 | BK59: 0.11
B61: NOI Excess / (Shortfall) for DSCR (Senior) | C61: =INDEX($J61:$BK61,MATCH(C$42,$J$42:$BK$42,0)) -> -1554505.8 | D61: =INDEX($J61:$BK61,MATCH(D$42,$J$42:$BK$42,0)) -> -473686.66 | E61: =INDEX($J61:$BK61,MATCH(E$42,$J$42:$BK$42,0)) -> 367585.12 | F61: =INDEX($J61:$BK61,MATCH(F$42,$J$42:$BK$42,0)) -> 1773958.5 | G61: =INDEX($J61:$BK61,MATCH(G$42,$J$42:$BK$42,0)) -> 3475856.3 | H61: =INDEX($J61:$BK61,MATCH(H$42,$J$42:$BK$42,0)) -> N/A | J61: =IFERROR((-J48*J55)-(-J48*J56),"N/A") -> N/A | K61: =IFERROR((-K48*K55)-(-K48*K56),"N/A") -> N/A | L61: =IFERROR((-L48*L55)-(-L48*L56),"N/A") -> N/A | M61: =IFERROR((-M48*M55)-(-M48*M56),"N/A") -> N/A | N61: =IFERROR((-N48*N55)-(-N48*N56),"N/A") -> N/A | O61: =IFERROR((-O48*O55)-(-O48*O56),"N/A") -> N/A | P61: =IFERROR((-P48*P55)-(-P48*P56),"N/A") -> N/A | Q61: =IFERROR((-Q48*Q55)-(-Q48*Q56),"N/A") -> N/A | ... BK61: =IFERROR((-BK48*BK55)-(-BK48*BK56),"N/A") -> N/A
B62: NOI Excess / (Shortfall) for DY (Senior) | C62: =INDEX($J62:$BK62,MATCH(C$42,$J$42:$BK$42,0)) -> -2736127.7 | D62: =INDEX($J62:$BK62,MATCH(D$42,$J$42:$BK$42,0)) -> -2244940.9 | E62: =INDEX($J62:$BK62,MATCH(E$42,$J$42:$BK$42,0)) -> -1878788.7 | F62: =INDEX($J62:$BK62,MATCH(F$42,$J$42:$BK$42,0)) -> -2136373.2 | G62: =INDEX($J62:$BK62,MATCH(G$42,$J$42:$BK$42,0)) -> -1719851.6 | H62: =INDEX($J62:$BK62,MATCH(H$42,$J$42:$BK$42,0)) -> N/A | J62: =IFERROR((J45*J58)-(J45*J59),"N/A") -> N/A | K62: =IFERROR((K45*K58)-(K45*K59),"N/A") -> N/A | L62: =IFERROR((L45*L58)-(L45*L59),"N/A") -> N/A | M62: =IFERROR((M45*M58)-(M45*M59),"N/A") -> N/A | N62: =IFERROR((N45*N58)-(N45*N59),"N/A") -> N/A | O62: =IFERROR((O45*O58)-(O45*O59),"N/A") -> N/A | P62: =IFERROR((P45*P58)-(P45*P59),"N/A") -> N/A | Q62: =IFERROR((Q45*Q58)-(Q45*Q59),"N/A") -> N/A | ... BK62: =IFERROR((BK45*BK58)-(BK45*BK59),"N/A") -> N/A
B64: LTV | C64: =INDEX($J64:$BK64,MATCH(C$42,$J$42:$BK$42,0)) -> #N/A | D64: =INDEX($J64:$BK64,MATCH(D$42,$J$42:$BK$42,0)) -> #N/A | E64: =INDEX($J64:$BK64,MATCH(E$42,$J$42:$BK$42,0)) -> #N/A | F64: =INDEX($J64:$BK64,MATCH(F$42,$J$42:$BK$42,0)) -> #N/A | G64: =INDEX($J64:$BK64,MATCH(G$42,$J$42:$BK$42,0)) -> #N/A | H64: =INDEX($J64:$BK64,MATCH(H$42,$J$42:$BK$42,0)) -> #N/A | J64: #N/A | K64: #N/A | L64: #N/A | M64: #N/A | N64: #N/A | O64: #N/A | P64: #N/A | Q64: #N/A | R64: #N/A | S64: #N/A | T64: #N/A | U64: #N/A | V64: #N/A | W64: #N/A | X64: #N/A | Y64: #N/A | Z64: #N/A | AA64: #N/A | AB64: #N/A | AC64: #N/A | AD64: #N/A | AE64: #N/A | AF64: #N/A | AG64: #N/A | AH64: #N/A | AI64: #N/A | AJ64: #N/A | AK64: #N/A | AL64: #N/A | AM64: #N/A | AN64: #N/A | AO64: #N/A | AP64: #N/A | AQ64: #N/A | AR64: #N/A | AS64: #N/A | AT64: #N/A | AU64: #N/A | AV64: #N/A | AW64: #N/A | AX64: #N/A | AY64: #N/A | AZ64: #N/A | BA64: #N/A | BB64: #N/A | BC64: #N/A | BD64: #N/A | BE64: #N/A | BF64: #N/A | BG64: #N/A | BH64: #N/A | BI64: #N/A | BJ64: #N/A | BK64: #N/A
B65: LTV Ratio Max | C65: =INDEX($J65:$V65,MATCH(C$42,$J$42:$V$42,0)) -> 0.65 | D65: =INDEX($J65:$V65,MATCH(D$42,$J$42:$V$42,0)) -> #N/A | E65: =INDEX($J65:$V65,MATCH(E$42,$J$42:$V$42,0)) -> #N/A | F65: =INDEX($J65:$V65,MATCH(F$42,$J$42:$V$42,0)) -> #N/A | G65: =INDEX($J65:$V65,MATCH(G$42,$J$42:$V$42,0)) -> #N/A | H65: =INDEX($J65:$V65,MATCH(H$42,$J$42:$V$42,0)) -> #N/A | J65: =$C$31 -> 0.65 | K65: =$C$31 -> 0.65 | L65: =$C$31 -> 0.65 | M65: =$C$31 -> 0.65 | N65: =$C$31 -> 0.65 | O65: =$C$31 -> 0.65 | P65: =$C$31 -> 0.65 | Q65: =$C$31 -> 0.65 | ... BK65: =$C$31 -> 0.65
B66: *DSCR calculated on Debt service for next 12 months
B68: Definitions
B69: Debt Yield | C69: N/A
B70: NOI | C70: Excludes debt service and depreciation
B71: DSCR | C71: TTM NOI / Next TM Debt Service
D74: FOR COMPLIANCE
D75: Swish
D76: 46843
C77: Revenue | D77: =SUMIFS($E$96:$XFD$96,$E$90:$XFD$90,">="&EOMONTH(D$76,-11),$E$90:$XFD$90,"<="&D$76) -> 4492805.9
C78: OpEx | D78: =D77-SUMIFS($E$91:$XFD$91,$E$90:$XFD$90,">="&EOMONTH(D$76,-11),$E$90:$XFD$90,"<="&D$76) -> 3605935.7
C79: NOI | D79: =D77-D78 -> 886870.15 | E79: {=D79=INDEX($J49:$CV49,MATCH(D$76,$J$42:$CV$42,0))} -> TRUE
C81: Debt Service | D81: =-SUMIFS($E$92:$XFD$92,$E$90:$XFD$90,">="&EOMONTH(D$76,-11),$E$90:$XFD$90,"<="&D$76) -> 392198.44
C82: DSCR N/A | D82: =D79/D81 -> 2.2612791 | E82: {=D82=INDEX($J55:$CV55,MATCH(D$76,$J$42:$CV$42,0))} -> FALSE
C84: Loan Balance | D84: {=INDEX($J44:$CV44,MATCH(D$76,$J$42:$CV$42,0))} -> 23187000
C85: Debt Yield | D85: =D79/D84 -> 0.038248594 | E85: {=D85=INDEX($J58:$CV58,MATCH(D$76,$J$42:$CV$42,0))} -> TRUE
Q89: 2029 | AC89: 2030 | AO89: 2031 | BA89: 2032 | BM89: 2033 | BY89: 2034
E90: 46783 | F90: =EOMONTH(E90,1) -> 46812 | G90: =EOMONTH(F90,1) -> 46843 | H90: =EOMONTH(G90,1) -> 46873 | I90: =EOMONTH(H90,1) -> 46904 | J90: =EOMONTH(I90,1) -> 46934 | K90: =EOMONTH(J90,1) -> 46965 | L90: =EOMONTH(K90,1) -> 46996 | M90: =EOMONTH(L90,1) -> 47026 | ... CJ90: =EOMONTH(CI90,1) -> 49309
D91: NOI Calc. | E91: =E99-E101-E102-(3%*(E$96-E$108))-(4%*(E$96-E$108))+E106 -> 271125.76 | F91: =F99-F101-F102-(3%*(F$96-F$108))-(4%*(F$96-F$108))+F106 -> 321100.64 | G91: =G99-G101-G102-(3%*(G$96-G$108))-(4%*(G$96-G$108))+G106 -> 294643.74 | H91: =H99-H101-H102-(3%*(H$96-H$108))-(4%*(H$96-H$108))+H106 -> 272334.1 | I91: =I99-I101-I102-(3%*(I$96-I$108))-(4%*(I$96-I$108))+I106 -> 179104.57 | J91: =J99-J101-J102-(3%*(J$96-J$108))-(4%*(J$96-J$108))+J106 -> 109197.01 | K91: =K99-K101-K102-(3%*(K$96-K$108))-(4%*(K$96-K$108))+K106 -> 110032.74 | L91: =L99-L101-L102-(3%*(L$96-L$108))-(4%*(L$96-L$108))+L106 -> 91096.256 | ... CJ91: =CJ99-CJ101-CJ102-(3%*(CJ$96-CJ$108))-(4%*(CJ$96-CJ$108))+CJ106 -> 647376.65
D92: Senior Int. Payment | E92: {=IF(E90<='Debt & Refi'!$E$29,-INDEX($N$14:$BV$14,MATCH(E90,$N$4:$BV$4)),-INDEX($N$31:$BV$31,MATCH(E90,$N$4:$BV$4)))} -> -130476.15 | F92: {=IF(F90<='Debt & Refi'!$E$29,-INDEX($N$14:$BV$14,MATCH(F90,$N$4:$BV$4)),-INDEX($N$31:$BV$31,MATCH(F90,$N$4:$BV$4)))} -> -130734.1 | G92: {=IF(G90<='Debt & Refi'!$E$29,-INDEX($N$14:$BV$14,MATCH(G90,$N$4:$BV$4)),-INDEX($N$31:$BV$31,MATCH(G90,$N$4:$BV$4)))} -> -130988.19 | H92: {=IF(H90<='Debt & Refi'!$E$29,-INDEX($N$14:$BV$14,MATCH(H90,$N$4:$BV$4)),-INDEX($N$31:$BV$31,MATCH(H90,$N$4:$BV$4)))} -> -311363.19 | I92: {=IF(I90<='Debt & Refi'!$E$29,-INDEX($N$14:$BV$14,MATCH(I90,$N$4:$BV$4)),-INDEX($N$31:$BV$31,MATCH(I90,$N$4:$BV$4)))} -> -311930.68 | J92: {=IF(J90<='Debt & Refi'!$E$29,-INDEX($N$14:$BV$14,MATCH(J90,$N$4:$BV$4)),-INDEX($N$31:$BV$31,MATCH(J90,$N$4:$BV$4)))} -> -312477.67 | K92: {=IF(K90<='Debt & Refi'!$E$29,-INDEX($N$14:$BV$14,MATCH(K90,$N$4:$BV$4)),-INDEX($N$31:$BV$31,MATCH(K90,$N$4:$BV$4)))} -> -313060.11 | L92: {=IF(L90<='Debt & Refi'!$E$29,-INDEX($N$14:$BV$14,MATCH(L90,$N$4:$BV$4)),-INDEX($N$31:$BV$31,MATCH(L90,$N$4:$BV$4)))} -> -313609.66 | ... CJ92: {=IF(CJ90<='Debt & Refi'!$E$29,-INDEX($N$14:$BV$14,MATCH(CJ90,$N$4:$BV$4)),-INDEX($N$31:$BV$31,MATCH(CJ90,$N$4:$BV$4)))} -> 0
E95: =E90 -> 46783 | F95: =F90 -> 46812 | G95: =G90 -> 46843 | H95: =H90 -> 46873 | I95: =I90 -> 46904 | J95: =J90 -> 46934 | K95: =K90 -> 46965 | L95: =L90 -> 46996 | ... CJ95: =CJ90 -> 49309
D96: Total Revenue | E96: =Proforma!AR29 -> 1413910.2 | F96: =Proforma!AS29 -> 1584640.4 | G96: =Proforma!AT29 -> 1494255.2 | H96: =Proforma!AU29 -> 1418038.3 | I96: =Proforma!AV29 -> 1099536.4 | J96: =Proforma!AW29 -> 860709.78 | K96: =Proforma!AX29 -> 863564.9 | L96: =Proforma!AY29 -> 798871.8 | ... CJ96: =Proforma!DW29 -> 2092459.7
D97: Total Dept. Exp. | E97: =Proforma!AR38 -> 543737.97 | F97: =Proforma!AS38 -> 609394.54 | G97: =Proforma!AT38 -> 574635.69 | H97: =Proforma!AU38 -> 545325.47 | I97: =Proforma!AV38 -> 422841.33 | J97: =Proforma!AW38 -> 330997.38 | K97: =Proforma!AX38 -> 332095.36 | L97: =Proforma!AY38 -> 307216.77 | ... CJ97: =Proforma!DW38 -> 779199.26
D98: Total Undist. Exp. | E98: =Proforma!AR61 -> 357329.2 | F98: =Proforma!AS61 -> 400476.84 | G98: =Proforma!AT61 -> 377634.31 | H98: =Proforma!AU61 -> 358372.46 | I98: =Proforma!AV61 -> 277879.35 | J98: =Proforma!AW61 -> 217522.11 | K98: =Proforma!AX61 -> 218243.66 | L98: =Proforma!AY61 -> 201894.16 | ... CJ98: =Proforma!DW61 -> 353932.65
D99: GOP | E99: =E96-E97-E98 -> 512843.07 | F99: =F96-F97-F98 -> 574769.06 | G99: =G96-G97-G98 -> 541985.2 | H99: =H96-H97-H98 -> 514340.37 | I99: =I96-I97-I98 -> 398815.71 | J99: =J96-J97-J98 -> 312190.29 | K99: =K96-K97-K98 -> 313225.87 | L99: =L96-L97-L98 -> 289760.87 | ... CJ99: =CJ96-CJ97-CJ98 -> 959327.78
D101: Property Taxes | E101: =Proforma!$J$70/12 -> 45961.343 | F101: =Proforma!$J$70/12 -> 45961.343 | G101: =Proforma!$J$70/12 -> 45961.343 | H101: =Proforma!$J$70/12 -> 45961.343 | I101: =Proforma!$J$70/12 -> 45961.343 | J101: =Proforma!$J$70/12 -> 45961.343 | K101: =Proforma!$J$70/12 -> 45961.343 | L101: =Proforma!$J$70/12 -> 45961.343 | ... P101: =Proforma!$J$70/12 -> 45961.343 | Q101: =Proforma!$O$70/12 -> 47340.184 | R101: =Proforma!$O$70/12 -> 47340.184 | S101: =Proforma!$O$70/12 -> 47340.184 | T101: =Proforma!$O$70/12 -> 47340.184 | U101: =Proforma!$O$70/12 -> 47340.184 | V101: =Proforma!$O$70/12 -> 47340.184 | W101: =Proforma!$O$70/12 -> 47340.184 | X101: =Proforma!$O$70/12 -> 47340.184 | ... AB101: =Proforma!$O$70/12 -> 47340.184 | AC101: =Proforma!$T$70/12 -> 48760.389 | AD101: =Proforma!$T$70/12 -> 48760.389 | AE101: =Proforma!$T$70/12 -> 48760.389 | AF101: =Proforma!$T$70/12 -> 48760.389 | AG101: =Proforma!$T$70/12 -> 48760.389 | AH101: =Proforma!$T$70/12 -> 48760.389 | AI101: =Proforma!$T$70/12 -> 48760.389 | AJ101: =Proforma!$T$70/12 -> 48760.389 | ... AN101: =Proforma!$T$70/12 -> 48760.389 | AO101: =Proforma!$Y$70/12 -> 50223.201 | AP101: =Proforma!$Y$70/12 -> 50223.201 | AQ101: =Proforma!$Y$70/12 -> 50223.201 | AR101: =Proforma!$Y$70/12 -> 50223.201 | AS101: =Proforma!$Y$70/12 -> 50223.201 | AT101: =Proforma!$Y$70/12 -> 50223.201 | AU101: =Proforma!$Y$70/12 -> 50223.201 | AV101: =Proforma!$Y$70/12 -> 50223.201 | ... AZ101: =Proforma!$Y$70/12 -> 50223.201 | BA101: =Proforma!$AD$70/12 -> 51729.897 | BB101: =Proforma!$AD$70/12 -> 51729.897 | BC101: =Proforma!$AD$70/12 -> 51729.897 | BD101: =Proforma!$AD$70/12 -> 51729.897 | BE101: =Proforma!$AD$70/12 -> 51729.897 | BF101: =Proforma!$AD$70/12 -> 51729.897 | BG101: =Proforma!$AD$70/12 -> 51729.897 | BH101: =Proforma!$AD$70/12 -> 51729.897 | ... BL101: =Proforma!$AD$70/12 -> 51729.897 | BM101: =Proforma!$AI$70/12 -> 53281.794 | BN101: =Proforma!$AI$70/12 -> 53281.794 | BO101: =Proforma!$AI$70/12 -> 53281.794 | BP101: =Proforma!$AI$70/12 -> 53281.794 | BQ101: =Proforma!$AI$70/12 -> 53281.794 | BR101: =Proforma!$AI$70/12 -> 53281.794 | BS101: =Proforma!$AI$70/12 -> 53281.794 | BT101: =Proforma!$AI$70/12 -> 53281.794 | ... CJ101: =Proforma!$AI$70/12 -> 53281.794
D102: Insurance | E102: =Proforma!$J$71/12 -> 96782.247 | F102: =Proforma!$J$71/12 -> 96782.247 | G102: =Proforma!$J$71/12 -> 96782.247 | H102: =Proforma!$J$71/12 -> 96782.247 | I102: =Proforma!$J$71/12 -> 96782.247 | J102: =Proforma!$J$71/12 -> 96782.247 | K102: =Proforma!$J$71/12 -> 96782.247 | L102: =Proforma!$J$71/12 -> 96782.247 | ... P102: =Proforma!$J$71/12 -> 96782.247 | Q102: =Proforma!$O$71/12 -> 99685.715 | R102: =Proforma!$O$71/12 -> 99685.715 | S102: =Proforma!$O$71/12 -> 99685.715 | T102: =Proforma!$O$71/12 -> 99685.715 | U102: =Proforma!$O$71/12 -> 99685.715 | V102: =Proforma!$O$71/12 -> 99685.715 | W102: =Proforma!$O$71/12 -> 99685.715 | X102: =Proforma!$O$71/12 -> 99685.715 | ... AB102: =Proforma!$O$71/12 -> 99685.715 | AC102: =Proforma!$T$71/12 -> 102676.29 | AD102: =Proforma!$T$71/12 -> 102676.29 | AE102: =Proforma!$T$71/12 -> 102676.29 | AF102: =Proforma!$T$71/12 -> 102676.29 | AG102: =Proforma!$T$71/12 -> 102676.29 | AH102: =Proforma!$T$71/12 -> 102676.29 | AI102: =Proforma!$T$71/12 -> 102676.29 | AJ102: =Proforma!$T$71/12 -> 102676.29 | ... AN102: =Proforma!$T$71/12 -> 102676.29 | AO102: =Proforma!$Y$71/12 -> 105756.57 | AP102: =Proforma!$Y$71/12 -> 105756.57 | AQ102: =Proforma!$Y$71/12 -> 105756.57 | AR102: =Proforma!$Y$71/12 -> 105756.57 | AS102: =Proforma!$Y$71/12 -> 105756.57 | AT102: =Proforma!$Y$71/12 -> 105756.57 | AU102: =Proforma!$Y$71/12 -> 105756.57 | AV102: =Proforma!$Y$71/12 -> 105756.57 | ... AZ102: =Proforma!$Y$71/12 -> 105756.57 | BA102: =Proforma!$AD$71/12 -> 108929.27 | BB102: =Proforma!$AD$71/12 -> 108929.27 | BC102: =Proforma!$AD$71/12 -> 108929.27 | BD102: =Proforma!$AD$71/12 -> 108929.27 | BE102: =Proforma!$AD$71/12 -> 108929.27 | BF102: =Proforma!$AD$71/12 -> 108929.27 | BG102: =Proforma!$AD$71/12 -> 108929.27 | BH102: =Proforma!$AD$71/12 -> 108929.27 | ... BL102: =Proforma!$AD$71/12 -> 108929.27 | BM102: =Proforma!$AI$71/12 -> 112197.15 | BN102: =Proforma!$AI$71/12 -> 112197.15 | BO102: =Proforma!$AI$71/12 -> 112197.15 | BP102: =Proforma!$AI$71/12 -> 112197.15 | BQ102: =Proforma!$AI$71/12 -> 112197.15 | BR102: =Proforma!$AI$71/12 -> 112197.15 | BS102: =Proforma!$AI$71/12 -> 112197.15 | BT102: =Proforma!$AI$71/12 -> 112197.15 | ... CJ102: =Proforma!$AI$71/12 -> 112197.15
D103: Mgmt. Fees | E103: =Proforma!AR65 -> 42417.307 | F103: =Proforma!AS65 -> 47539.213 | G103: =Proforma!AT65 -> 44827.656 | H103: =Proforma!AU65 -> 42541.149 | I103: =Proforma!AV65 -> 32986.092 | J103: =Proforma!AW65 -> 25821.293 | K103: =Proforma!AX65 -> 25906.947 | L103: =Proforma!AY65 -> 23966.154 | ... CJ103: =Proforma!DW65 -> 62773.791
D104: FF&E | E104: =Proforma!AR79 -> 56556.41 | F104: =Proforma!AS79 -> 63385.618 | G104: =Proforma!AT79 -> 59770.208 | H104: =Proforma!AU79 -> 56721.532 | I104: =Proforma!AV79 -> 43981.456 | J104: =Proforma!AW79 -> 34428.391 | K104: =Proforma!AX79 -> 34542.596 | L104: =Proforma!AY79 -> 31954.872 | ... CJ104: =Proforma!DW79 -> 83698.388
D105: P&L NOI | E105: =E99-E101-E102-E103-E104 -> 271125.76 | F105: =F99-F101-F102-F103-F104 -> 321100.64 | G105: =G99-G101-G102-G103-G104 -> 294643.74 | H105: =H99-H101-H102-H103-H104 -> 272334.1 | I105: =I99-I101-I102-I103-I104 -> 179104.57 | J105: =J99-J101-J102-J103-J104 -> 109197.01 | K105: =K99-K101-K102-K103-K104 -> 110032.74 | L105: =L99-L101-L102-L103-L104 -> 91096.256 | ... CJ105: =CJ99-CJ101-CJ102-CJ103-CJ104 -> 647376.65
C106: If Applicable | D106: Lease Income
D107: Adj. P&L NOI | E107: =E105+E106 -> 271125.76 | F107: =F105+F106 -> 321100.64 | G107: =G105+G106 -> 294643.74 | H107: =H105+H106 -> 272334.1 | I107: =I105+I106 -> 179104.57 | J107: =J105+J106 -> 109197.01 | K107: =K105+K106 -> 110032.74 | L107: =L105+L106 -> 91096.256 | ... CJ107: =CJ105+CJ106 -> 647376.65
C108: If Applicable minus from Rev for Mgmt. and FF&E | D108: Parking Revenue TBD

Sheet Waterfall
C2: =Model!C3 -> Kimpton Anglers
C3: Waterfall Distribution
C5: Returns | F5: Profit | G5: IRR | H5: EM | J5: Equity Breakdown | M5: % | N5: Amount
C6: Deal Levered | F6: =SUM(F24:BY24) -> 29235441 | G6: =B24 -> 0.39585511 | H6: =B26 -> 2.4726538 | J6: Sponsor/GP | M6: 0.1 | N6: =M6*$M$12 -> 1938567.8
C7: LP | F7: =SUM(F96:BY96) -> 21302518 | G7: =B94 -> 0.36236156 | H7: =B96 -> 2.1922832 | J7: LP Investor | M7: =1-M6 -> 0.9 | N7: =M7*$M$12 -> 17447110
C8: GP | F8: =SUM(F101:BY101) -> 7932923.6 | G8: =B99 -> 0.57671394 | H8: =B101 -> 4.995989
J9: Transaction Sources
C10: Cash Flow Waterfall | F10: Return | G10: GP CF | H10: LP CF | M10: Amount | N10: Per Key | O10: %
C11: Pref Return | F11: 0.1 | G11: 0 | H11: =1-G11 -> 1 | J11: Debt | M11: =Model!$N$18 -> 23187000 | N11: =Model!$O$18 -> 175659.09 | O11: =Model!$P$18 -> 0.54464509
C12: Hurdle #2 | F12: 0.15 | G12: 0.2 | H12: =1-G12 -> 0.8 | J12: Equity | M12: =Model!$N$22 -> 19385678 | N12: =Model!$O$22 -> 146861.19 | O12: =Model!$P$22 -> 0.45535491
C13: Hurdle #3 | F13: 0.2 | G13: 0.25 | H13: =1-G13 -> 0.75 | J13: Total Sources | M13: =SUM(M11:M12) -> 42572678 | N13: =Model!O23 -> 322520.28 | O13: =SUM(O11:O12) -> 1
C14: Hurdle #4 | F14: 0.25 | G14: 0.25 | H14: =1-G14 -> 0.75
C15: Hurdle #5 | F15: 0.3 | G15: 0.25 | H15: =1-G15 -> 0.75
C16: Hurdle #6 | F16: >30% | G16: 0.5 | H16: =1-G16 -> 0.5
C18: Cash Flow Waterfall | DA18: x
C19: Year | F19: =YEAR(F22) -> 2025 | G19: =YEAR(G22) -> 2025 | H19: =YEAR(H22) -> 2025 | I19: =YEAR(I22) -> 2025 | J19: =YEAR(J22) -> 2026 | K19: =YEAR(K22) -> 2026 | L19: =YEAR(L22) -> 2026 | M19: =YEAR(M22) -> 2026 | ... CZ19: =YEAR(CZ22) -> 2033
C20: Year # | F20: =ROUNDUP(F21/12,0) -> 0 | G20: =ROUNDUP(G21/12,0) -> 1 | H20: =ROUNDUP(H21/12,0) -> 1 | I20: =ROUNDUP(I21/12,0) -> 1 | J20: =ROUNDUP(J21/12,0) -> 1 | K20: =ROUNDUP(K21/12,0) -> 1 | L20: =ROUNDUP(L21/12,0) -> 1 | M20: =ROUNDUP(M21/12,0) -> 1 | ... CZ20: =ROUNDUP(CZ21/12,0) -> 9
C21: Month | F21: 0 | G21: =F21+1 -> 1 | H21: =G21+1 -> 2 | I21: =H21+1 -> 3 | J21: =I21+1 -> 4 | K21: =J21+1 -> 5 | L21: =K21+1 -> 6 | M21: =L21+1 -> 7 | N21: =M21+1 -> 8 | ... CZ21: =CY21+1 -> 98
C22: Date | F22: =Model!S71 -> 45930 | G22: =EOMONTH(F22,1) -> 45961 | H22: =EOMONTH(G22,1) -> 45991 | I22: =EOMONTH(H22,1) -> 46022 | J22: =EOMONTH(I22,1) -> 46053 | K22: =EOMONTH(J22,1) -> 46081 | L22: =EOMONTH(K22,1) -> 46112 | M22: =EOMONTH(L22,1) -> 46142 | N22: =EOMONTH(M22,1) -> 46173 | ... CZ22: =EOMONTH(CY22,1) -> 48913
B23: IRR
B24: =XIRR($F$24:$CZ$24,$F$22:$CZ$22) -> 0.39585511 | C24: Levered Cash Flow | F24: =Model!S96 -> -14783049 | G24: =Model!T96 -> 126557.56 | H24: =Model!U96 -> 111906.6 | I24: =Model!V96 -> 103035.4 | J24: =Model!W96 -> -568556.76 | K24: =Model!X96 -> -608617.82 | L24: =Model!Y96 -> -607140.53 | M24: =Model!Z96 -> -617000.57 | ... CZ24: =Model!DM96 -> 0
B25: EM
B26: =-SUMIF(F24:BY24,">0",F24:BY24)/SUMIF(F24:BY24,"<0",F24:BY24) -> 2.4726538 | C26: Preferred Return
C27: Beginning Balance | F27: =E31 | G27: =F31 -> 13304744 | H27: =G31 -> 13286323 | I27: =H31 -> 13278907 | J27: =I31 -> 13283798 | K27: =J31 -> 13903466 | L27: =K31 -> 14553249 | M27: =L31 -> 15217960 | ... CZ27: =CY31 -> 0
C28: Preferred Return Accrual | F28: =F27*(1+$F$11)^((F$22-E$22)/365)-F27 -> 0 | G28: =G27*(1+$F$11)^((G$22-F$22)/365)-G27 -> 108136.82 | H28: =H27*(1+$F$11)^((H$22-G$22)/365)-H27 -> 104489.99 | I28: =I27*(1+$F$11)^((I$22-H$22)/365)-I27 -> 107926.82 | J28: =J27*(1+$F$11)^((J$22-I$22)/365)-J27 -> 107966.58 | K28: =K27*(1+$F$11)^((K$22-J$22)/365)-K27 -> 102027.25 | L28: =L27*(1+$F$11)^((L$22-K$22)/365)-L27 -> 118284.28 | M28: =M27*(1+$F$11)^((M$22-L$22)/365)-M27 -> 119681.3 | ... CZ28: =CZ27*(1+$F$11)^((CZ$22-CY$22)/365)-CZ27 -> 0
C29: LP Contributions | F29: =IF(F$24<0,F$24*$M$7,0) -> -13304744 | G29: =IF(G$24<0,G$24*$M$7,0) -> 0 | H29: =IF(H$24<0,H$24*$M$7,0) -> 0 | I29: =IF(I$24<0,I$24*$M$7,0) -> 0 | J29: =IF(J$24<0,J$24*$M$7,0) -> -511701.08 | K29: =IF(K$24<0,K$24*$M$7,0) -> -547756.04 | L29: =IF(L$24<0,L$24*$M$7,0) -> -546426.48 | M29: =IF(M$24<0,M$24*$M$7,0) -> -555300.52 | ... CZ29: =IF(CZ$24<0,CZ$24*$M$7,0) -> 0
C30: LP Distributions | F30: =MIN(SUM(F27:F28),MAX(F$24,0)*$H$11) -> 0 | G30: =MIN(SUM(G27:G28),MAX(G$24,0)*$H$11) -> 126557.56 | H30: =MIN(SUM(H27:H28),MAX(H$24,0)*$H$11) -> 111906.6 | I30: =MIN(SUM(I27:I28),MAX(I$24,0)*$H$11) -> 103035.4 | J30: =MIN(SUM(J27:J28),MAX(J$24,0)*$H$11) -> 0 | K30: =MIN(SUM(K27:K28),MAX(K$24,0)*$H$11) -> 0 | L30: =MIN(SUM(L27:L28),MAX(L$24,0)*$H$11) -> 0 | M30: =MIN(SUM(M27:M28),MAX(M$24,0)*$H$11) -> 0 | ... CZ30: =MIN(SUM(CZ27:CZ28),MAX(CZ$24,0)*$H$11) -> 0
B31: IRR Check | C31: Ending Balance | F31: =F27+F28-F29-F30 -> 13304744 | G31: =G27+G28-G29-G30 -> 13286323 | H31: =H27+H28-H29-H30 -> 13278907 | I31: =I27+I28-I29-I30 -> 13283798 | J31: =J27+J28-J29-J30 -> 13903466 | K31: =K27+K28-K29-K30 -> 14553249 | L31: =L27+L28-L29-L30 -> 15217960 | M31: =M27+M28-M29-M30 -> 15892942 | ... CZ31: =CZ27+CZ28-CZ29-CZ30 -> 0
B32: =XIRR(F32:CZ32,$F$22:$CZ$22) -> 0.1 | C32: Total LP Cash Flow | F32: =SUM(F29:F30) -> -13304744 | G32: =SUM(G29:G30) -> 126557.56 | H32: =SUM(H29:H30) -> 111906.6 | I32: =SUM(I29:I30) -> 103035.4 | J32: =SUM(J29:J30) -> -511701.08 | K32: =SUM(K29:K30) -> -547756.04 | L32: =SUM(L29:L30) -> -546426.48 | M32: =SUM(M29:M30) -> -555300.52 | ... CZ32: =SUM(CZ29:CZ30) -> 0
C33: GP Contributions | F33: =IF(F24<0,F24*$M$6,0) -> -1478304.9 | G33: =IF(G24<0,G24*$M$6,0) -> 0 | H33: =IF(H24<0,H24*$M$6,0) -> 0 | I33: =IF(I24<0,I24*$M$6,0) -> 0 | J33: =IF(J24<0,J24*$M$6,0) -> -56855.676 | K33: =IF(K24<0,K24*$M$6,0) -> -60861.782 | L33: =IF(L24<0,L24*$M$6,0) -> -60714.053 | M33: =IF(M24<0,M24*$M$6,0) -> -61700.057 | ... CZ33: =IF(CZ24<0,CZ24*$M$6,0) -> 0
C34: GP Distributions | F34: =(F30/$H$11)*$G$11 -> 0 | G34: =(G30/$H$11)*$G$11 -> 0 | H34: =(H30/$H$11)*$G$11 -> 0 | I34: =(I30/$H$11)*$G$11 -> 0 | J34: =(J30/$H$11)*$G$11 -> 0 | K34: =(K30/$H$11)*$G$11 -> 0 | L34: =(L30/$H$11)*$G$11 -> 0 | M34: =(M30/$H$11)*$G$11 -> 0 | ... CZ34: =(CZ30/$H$11)*$G$11 -> 0
C35: Total GP Cash Flow | F35: =SUM(F33:F34) -> -1478304.9 | G35: =SUM(G33:G34) -> 0 | H35: =SUM(H33:H34) -> 0 | I35: =SUM(I33:I34) -> 0 | J35: =SUM(J33:J34) -> -56855.676 | K35: =SUM(K33:K34) -> -60861.782 | L35: =SUM(L33:L34) -> -60714.053 | M35: =SUM(M33:M34) -> -61700.057 | ... CZ35: =SUM(CZ33:CZ34) -> 0
C36: Total Distributions | F36: =F30+F34 -> 0 | G36: =G30+G34 -> 126557.56 | H36: =H30+H34 -> 111906.6 | I36: =I30+I34 -> 103035.4 | J36: =J30+J34 -> 0 | K36: =K30+K34 -> 0 | L36: =L30+L34 -> 0 | M36: =M30+M34 -> 0 | ... CZ36: =CZ30+CZ34 -> 0
C37: Cash Flow Remaining | F37: =MAX(F24-F36,0) -> 0 | G37: =MAX(G24-G36,0) -> 0 | H37: =MAX(H24-H36,0) -> 0 | I37: =MAX(I24-I36,0) -> 0 | J37: =MAX(J24-J36,0) -> 0 | K37: =MAX(K24-K36,0) -> 0 | L37: =MAX(L24-L36,0) -> 0 | M37: =MAX(M24-M36,0) -> 0 | ... CZ37: =MAX(CZ24-CZ36,0) -> 0
C39: Hurdle #2
C40: Beginning Balance | F40: =E45 | G40: =F45 -> 13304744 | H40: =G45 -> 13337058 | I40: =H45 -> 13379241 | J40: =I45 -> 13435966 | K40: =J45 -> 14108105 | L40: =K45 -> 14807934 | M40: =L45 -> 15531181 | ... CZ40: =CY45 -> 0
C41: Hurdle #2 Accrual | F41: =F40*(1+$F$12)^((F$22-E$22)/365)-F40 -> 0 | G41: =G40*(1+$F$12)^((G$22-F$22)/365)-G40 -> 158870.92 | H41: =H40*(1+$F$12)^((H$22-G$22)/365)-H40 -> 154089.9 | I41: =I40*(1+$F$12)^((I$22-H$22)/365)-I40 -> 159760.48 | J41: =J40*(1+$F$12)^((J$22-I$22)/365)-J40 -> 160437.83 | K41: =K40*(1+$F$12)^((K$22-J$22)/365)-K40 -> 152073.31 | L41: =L40*(1+$F$12)^((L$22-K$22)/365)-L40 -> 176820.4 | M41: =M40*(1+$F$12)^((M$22-L$22)/365)-M40 -> 179439.74 | ... CZ41: =CZ40*(1+$F$12)^((CZ$22-CY$22)/365)-CZ40 -> 0
C42: LP Contributions | F42: =F29 -> -13304744 | G42: =G29 -> 0 | H42: =H29 -> 0 | I42: =I29 -> 0 | J42: =J29 -> -511701.08 | K42: =K29 -> -547756.04 | L42: =L29 -> -546426.48 | M42: =M29 -> -555300.52 | ... CZ42: =CZ29 -> 0
C43: Prior Distributions | F43: =F30 -> 0 | G43: =G30 -> 126557.56 | H43: =H30 -> 111906.6 | I43: =I30 -> 103035.4 | J43: =J30 -> 0 | K43: =K30 -> 0 | L43: =L30 -> 0 | M43: =M30 -> 0 | ... CZ43: =CZ30 -> 0
C44: LP Distributions | F44: =MIN(F40+F41-F42-F43,F37*$H$12) -> 0 | G44: =MIN(G40+G41-G42-G43,G37*$H$12) -> 0 | H44: =MIN(H40+H41-H42-H43,H37*$H$12) -> 0 | I44: =MIN(I40+I41-I42-I43,I37*$H$12) -> 0 | J44: =MIN(J40+J41-J42-J43,J37*$H$12) -> 0 | K44: =MIN(K40+K41-K42-K43,K37*$H$12) -> 0 | L44: =MIN(L40+L41-L42-L43,L37*$H$12) -> 0 | M44: =MIN(M40+M41-M42-M43,M37*$H$12) -> 0 | ... CZ44: =MIN(CZ40+CZ41-CZ42-CZ43,CZ37*$H$12) -> 0
B45: IRR Check | C45: Ending Balance | F45: =F40+F41-F42-F43-F44 -> 13304744 | G45: =G40+G41-G42-G43-G44 -> 13337058 | H45: =H40+H41-H42-H43-H44 -> 13379241 | I45: =I40+I41-I42-I43-I44 -> 13435966 | J45: =J40+J41-J42-J43-J44 -> 14108105 | K45: =K40+K41-K42-K43-K44 -> 14807934 | L45: =L40+L41-L42-L43-L44 -> 15531181 | M45: =M40+M41-M42-M43-M44 -> 16265921 | ... CZ45: =CZ40+CZ41-CZ42-CZ43-CZ44 -> 0 | DA45: x
B46: =XIRR(F46:CZ46,$F$22:$CZ$22) -> 0.15 | C46: Total LP Cash Flow | F46: =SUM(F42:F44) -> -13304744 | G46: =SUM(G42:G44) -> 126557.56 | H46: =SUM(H42:H44) -> 111906.6 | I46: =SUM(I42:I44) -> 103035.4 | J46: =SUM(J42:J44) -> -511701.08 | K46: =SUM(K42:K44) -> -547756.04 | L46: =SUM(L42:L44) -> -546426.48 | M46: =SUM(M42:M44) -> -555300.52 | ... CZ46: =SUM(CZ42:CZ44) -> 0 | DA46: x
C47: GP Distributions | F47: =(F44/$H$12)*$G$12 -> 0 | G47: =(G44/$H$12)*$G$12 -> 0 | H47: =(H44/$H$12)*$G$12 -> 0 | I47: =(I44/$H$12)*$G$12 -> 0 | J47: =(J44/$H$12)*$G$12 -> 0 | K47: =(K44/$H$12)*$G$12 -> 0 | L47: =(L44/$H$12)*$G$12 -> 0 | M47: =(M44/$H$12)*$G$12 -> 0 | ... CZ47: =(CZ44/$H$12)*$G$12 -> 0 | DA47: x
C48: Total Distributions | F48: =F44+F47 -> 0 | G48: =G44+G47 -> 0 | H48: =H44+H47 -> 0 | I48: =I44+I47 -> 0 | J48: =J44+J47 -> 0 | K48: =K44+K47 -> 0 | L48: =L44+L47 -> 0 | M48: =M44+M47 -> 0 | ... CZ48: =CZ44+CZ47 -> 0 | DA48: x
C49: Cash Flow Remaining | F49: =F37-F48 -> 0 | G49: =G37-G48 -> 0 | H49: =H37-H48 -> 0 | I49: =I37-I48 -> 0 | J49: =J37-J48 -> 0 | K49: =K37-K48 -> 0 | L49: =L37-L48 -> 0 | M49: =M37-M48 -> 0 | ... CZ49: =CZ37-CZ48 -> 0 | DA49: x
C51: Hurdle #3 | DA51: x
C52: Beginning Balance | F52: =E57 | G52: =F57 -> 13304744 | H52: =G57 -> 13385812 | I52: =H57 -> 13476007 | J52: =I57 -> 13583269 | K52: =J57 -> 14306942 | L52: =K57 -> 15056205 | M52: =L57 -> 15837589 | ... CZ52: =CY57 -> 0 | DA52: x
C53: Hurdle #3 Accrual | F53: =F52*(1+$F$13)^((F$22-E$22)/365)-F52 -> 0 | G53: =G52*(1+$F$13)^((G$22-F$22)/365)-G52 -> 207625.27 | H53: =H52*(1+$F$13)^((H$22-G$22)/365)-H52 -> 202101.35 | I53: =I52*(1+$F$13)^((I$22-H$22)/365)-I52 -> 210297.88 | J53: =J52*(1+$F$13)^((J$22-I$22)/365)-J52 -> 211971.75 | K53: =K52*(1+$F$13)^((K$22-J$22)/365)-K52 -> 201507.23 | L53: =L52*(1+$F$13)^((L$22-K$22)/365)-L52 -> 234957.44 | M53: =M52*(1+$F$13)^((M$22-L$22)/365)-M52 -> 239118.72 | ... CZ53: =CZ52*(1+$F$13)^((CZ$22-CY$22)/365)-CZ52 -> 0 | DA53: x
C54: LP Contributions | F54: =F42 -> -13304744 | G54: =G42 -> 0 | H54: =H42 -> 0 | I54: =I42 -> 0 | J54: =J42 -> -511701.08 | K54: =K42 -> -547756.04 | L54: =L42 -> -546426.48 | M54: =M42 -> -555300.52 | ... CZ54: =CZ42 -> 0 | DA54: x
C55: Prior Distributions | F55: =F30+F44 -> 0 | G55: =G30+G44 -> 126557.56 | H55: =H30+H44 -> 111906.6 | I55: =I30+I44 -> 103035.4 | J55: =J30+J44 -> 0 | K55: =K30+K44 -> 0 | L55: =L30+L44 -> 0 | M55: =M30+M44 -> 0 | ... CZ55: =CZ30+CZ44 -> 0 | DA55: x
C56: LP Distributions | F56: =MIN(F52+F53-F54-F55,F49*$H$13) -> 0 | G56: =MIN(G52+G53-G54-G55,G49*$H$13) -> 0 | H56: =MIN(H52+H53-H54-H55,H49*$H$13) -> 0 | I56: =MIN(I52+I53-I54-I55,I49*$H$13) -> 0 | J56: =MIN(J52+J53-J54-J55,J49*$H$13) -> 0 | K56: =MIN(K52+K53-K54-K55,K49*$H$13) -> 0 | L56: =MIN(L52+L53-L54-L55,L49*$H$13) -> 0 | M56: =MIN(M52+M53-M54-M55,M49*$H$13) -> 0 | ... CZ56: =MIN(CZ52+CZ53-CZ54-CZ55,CZ49*$H$13) -> 0 | DA56: x
B57: IRR Check | C57: Ending Balance | F57: =F52+F53-F54-F55-F56 -> 13304744 | G57: =G52+G53-G54-G55-G56 -> 13385812 | H57: =H52+H53-H54-H55-H56 -> 13476007 | I57: =I52+I53-I54-I55-I56 -> 13583269 | J57: =J52+J53-J54-J55-J56 -> 14306942 | K57: =K52+K53-K54-K55-K56 -> 15056205 | L57: =L52+L53-L54-L55-L56 -> 15837589 | M57: =M52+M53-M54-M55-M56 -> 16632008 | ... CZ57: =CZ52+CZ53-CZ54-CZ55-CZ56 -> 0 | DA57: x
B58: =XIRR(F58:CZ58,$F$22:$CZ$22) -> 0.2 | C58: Total LP Cash Flow | F58: =SUM(F54:F56) -> -13304744 | G58: =SUM(G54:G56) -> 126557.56 | H58: =SUM(H54:H56) -> 111906.6 | I58: =SUM(I54:I56) -> 103035.4 | J58: =SUM(J54:J56) -> -511701.08 | K58: =SUM(K54:K56) -> -547756.04 | L58: =SUM(L54:L56) -> -546426.48 | M58: =SUM(M54:M56) -> -555300.52 | ... CZ58: =SUM(CZ54:CZ56) -> 0 | DA58: x
C59: GP Distributions | F59: =(F56/$H$13)*$G$13 -> 0 | G59: =(G56/$H$13)*$G$13 -> 0 | H59: =(H56/$H$13)*$G$13 -> 0 | I59: =(I56/$H$13)*$G$13 -> 0 | J59: =(J56/$H$13)*$G$13 -> 0 | K59: =(K56/$H$13)*$G$13 -> 0 | L59: =(L56/$H$13)*$G$13 -> 0 | M59: =(M56/$H$13)*$G$13 -> 0 | ... CZ59: =(CZ56/$H$13)*$G$13 -> 0 | DA59: x
C60: Total Distributions | F60: =F59+F56 -> 0 | G60: =G59+G56 -> 0 | H60: =H59+H56 -> 0 | I60: =I59+I56 -> 0 | J60: =J59+J56 -> 0 | K60: =K59+K56 -> 0 | L60: =L59+L56 -> 0 | M60: =M59+M56 -> 0 | ... CZ60: =CZ59+CZ56 -> 0 | DA60: x
C61: Cash Flow Remaining | F61: =F49-F60 -> 0 | G61: =G49-G60 -> 0 | H61: =H49-H60 -> 0 | I61: =I49-I60 -> 0 | J61: =J49-J60 -> 0 | K61: =K49-K60 -> 0 | L61: =L49-L60 -> 0 | M61: =M49-M60 -> 0 | ... CZ61: =CZ49-CZ60 -> 0 | DA61: x
C63: Hurdle #4 | DA63: x
C64: Beginning Balance | F64: =E69 | G64: =F69 -> 13304744 | H64: =G69 -> 13306184 | I64: =H69 -> 13328665 | J64: =I69 -> 13377607 | K64: =J69 -> 14145257 | L64: =K69 -> 14937234 | M64: =L69 -> 15769450 | ... CZ64: =CY69 -> 0 | DA64: x
C65: Hurdle #4 Accrual | F65: =F64*(1+$F$14)^((F$22-E$22)/365)-F64 -> 0 | G65: =G64*(1+$F$14)^((G$22-F$22)/365)-G64 -> 254554.95 | H65: =H64*(1+$F$14)^((H$22-G$22)/365)-H64 -> 246294.63 | I65: =I64*(1+$F$14)^((I$22-H$22)/365)-I64 -> 255012.63 | J65: =J64*(1+$F$14)^((J$22-I$22)/365)-J64 -> 255949.02 | K65: =K64*(1+$F$14)^((K$22-J$22)/365)-K64 -> 244220.86 | L65: =L64*(1+$F$14)^((L$22-K$22)/365)-L64 -> 285788.81 | M65: =M64*(1+$F$14)^((M$22-L$22)/365)-M64 -> 291889.15 | ... CZ65: =CZ64*(1+$F$14)^((CZ$22-CY$22)/365)-CZ64 -> 0 | DA65: x
C66: LP Contributions | F66: =F54 -> -13304744 | G66: =G54 -> 0 | H66: =H54 -> 0 | I66: =I54 -> 0 | J66: =J54 -> -511701.08 | K66: =K54 -> -547756.04 | L66: =L54 -> -546426.48 | M66: =M54 -> -555300.52 | ... CZ66: =CZ54 -> 0 | DA66: x
C67: Prior Distributions | F67: =F30+F44+F56 -> 0 | G67: =G30+G43+G56 -> 253115.13 | H67: =H30+H43+H56 -> 223813.2 | I67: =I30+I43+I56 -> 206070.8 | J67: =J30+J43+J56 -> 0 | K67: =K30+K43+K56 -> 0 | L67: =L30+L43+L56 -> 0 | M67: =M30+M43+M56 -> 0 | N67: =N30+N43+N56 -> 0 | ... CZ67: =CZ30+CZ43+CZ56 -> 0 | DA67: x
C68: LP Distributions | F68: =MIN(F64+F65-F66-F67,F61*$H$14) -> 0 | G68: =MIN(G64+G65-G66-G67,G61*$H$14) -> 0 | H68: =MIN(H64+H65-H66-H67,H61*$H$14) -> 0 | I68: =MIN(I64+I65-I66-I67,I61*$H$14) -> 0 | J68: =MIN(J64+J65-J66-J67,J61*$H$14) -> 0 | K68: =MIN(K64+K65-K66-K67,K61*$H$14) -> 0 | L68: =MIN(L64+L65-L66-L67,L61*$H$14) -> 0 | M68: =MIN(M64+M65-M66-M67,M61*$H$14) -> 0 | ... CZ68: =MIN(CZ64+CZ65-CZ66-CZ67,CZ61*$H$14) -> 0 | DA68: x
B69: IRR Check | C69: Ending Balance | F69: =F64+F65-F66-F67-F68 -> 13304744 | G69: =G64+G65-G66-G67-G68 -> 13306184 | H69: =H64+H65-H66-H67-H68 -> 13328665 | I69: =I64+I65-I66-I67-I68 -> 13377607 | J69: =J64+J65-J66-J67-J68 -> 14145257 | K69: =K64+K65-K66-K67-K68 -> 14937234 | L69: =L64+L65-L66-L67-L68 -> 15769450 | M69: =M64+M65-M66-M67-M68 -> 16616639 | ... CZ69: =CZ64+CZ65-CZ66-CZ67-CZ68 -> 0 | DA69: x
B70: =XIRR(F70:CZ70,$F$22:$CZ$22) -> 0.25 | C70: Total LP Cash Flow | F70: =SUM(F66:F68) -> -13304744 | G70: =SUM(G66:G68) -> 253115.13 | H70: =SUM(H66:H68) -> 223813.2 | I70: =SUM(I66:I68) -> 206070.8 | J70: =SUM(J66:J68) -> -511701.08 | K70: =SUM(K66:K68) -> -547756.04 | L70: =SUM(L66:L68) -> -546426.48 | M70: =SUM(M66:M68) -> -555300.52 | ... CZ70: =SUM(CZ66:CZ68) -> 0 | DA70: x
C71: GP Distributions | F71: =(F68/$H$14)*$G$14 -> 0 | G71: =(G68/$H$14)*$G$14 -> 0 | H71: =(H68/$H$14)*$G$14 -> 0 | I71: =(I68/$H$14)*$G$14 -> 0 | J71: =(J68/$H$14)*$G$14 -> 0 | K71: =(K68/$H$14)*$G$14 -> 0 | L71: =(L68/$H$14)*$G$14 -> 0 | M71: =(M68/$H$14)*$G$14 -> 0 | ... CZ71: =(CZ68/$H$14)*$G$14 -> 0 | DA71: x
C72: Total Distributions | F72: =F71+F68 -> 0 | G72: =G71+G68 -> 0 | H72: =H71+H68 -> 0 | I72: =I71+I68 -> 0 | J72: =J71+J68 -> 0 | K72: =K71+K68 -> 0 | L72: =L71+L68 -> 0 | M72: =M71+M68 -> 0 | ... CZ72: =CZ71+CZ68 -> 0 | DA72: x
C73: Cash Flow Remaining | F73: =F61-F72 -> 0 | G73: =G61-G72 -> 0 | H73: =H61-H72 -> 0 | I73: =I61-I72 -> 0 | J73: =J61-J72 -> 0 | K73: =K61-K72 -> 0 | L73: =L61-L72 -> 0 | M73: =M61-M72 -> 0 | ... CZ73: =CZ61-CZ72 -> 0 | DA73: x
C75: Hurdle #5 | DA75: x
C76: Beginning Balance | F76: =E81 | G76: =F81 -> 13304744 | H76: =G81 -> 13477984 | I76: =H81 -> 13659875 | J76: =I81 -> 13864640 | K76: =J81 -> 14688754 | L76: =K81 -> 15535140 | M76: =L81 -> 16431621 | ... CZ76: =CY81 -> 0 | DA76: x
C77: Hurdle #5 Accrual | F77: =F76*(1+$F$15)^((F$22-E$22)/365)-F76 -> 0 | G77: =G76*(1+$F$15)^((G$22-F$22)/365)-G76 -> 299797.3 | H77: =H76*(1+$F$15)^((H$22-G$22)/365)-H76 -> 293798.13 | I77: =I76*(1+$F$15)^((I$22-H$22)/365)-I76 -> 307799.51 | J77: =J76*(1+$F$15)^((J$22-I$22)/365)-J76 -> 312413.48 | K77: =K76*(1+$F$15)^((K$22-J$22)/365)-K76 -> 298629.41 | L77: =L76*(1+$F$15)^((L$22-K$22)/365)-L76 -> 350055.05 | M77: =M76*(1+$F$15)^((M$22-L$22)/365)-M76 -> 358182.61 | ... CZ77: =CZ76*(1+$F$15)^((CZ$22-CY$22)/365)-CZ76 -> 0 | DA77: x
C78: LP Contributions | F78: =F66 -> -13304744 | G78: =G66 -> 0 | H78: =H66 -> 0 | I78: =I66 -> 0 | J78: =J66 -> -511701.08 | K78: =K66 -> -547756.04 | L78: =L66 -> -546426.48 | M78: =M66 -> -555300.52 | ... CZ78: =CZ66 -> 0 | DA78: x
C79: Prior Distributions | F79: =F30+F44+F56+F68 -> 0 | G79: =G30+G44+G56+G68 -> 126557.56 | H79: =H30+H44+H56+H68 -> 111906.6 | I79: =I30+I44+I56+I68 -> 103035.4 | J79: =J30+J44+J56+J68 -> 0 | K79: =K30+K44+K56+K68 -> 0 | L79: =L30+L44+L56+L68 -> 0 | M79: =M30+M44+M56+M68 -> 0 | ... CZ79: =CZ30+CZ44+CZ56+CZ68 -> 0 | DA79: x
C80: LP Distributions | F80: =MIN(F76+F77-F78-F79,F73*$H$15) -> 0 | G80: =MIN(G76+G77-G78-G79,G73*$H$15) -> 0 | H80: =MIN(H76+H77-H78-H79,H73*$H$15) -> 0 | I80: =MIN(I76+I77-I78-I79,I73*$H$15) -> 0 | J80: =MIN(J76+J77-J78-J79,J73*$H$15) -> 0 | K80: =MIN(K76+K77-K78-K79,K73*$H$15) -> 0 | L80: =MIN(L76+L77-L78-L79,L73*$H$15) -> 0 | M80: =MIN(M76+M77-M78-M79,M73*$H$15) -> 0 | ... CZ80: =MIN(CZ76+CZ77-CZ78-CZ79,CZ73*$H$15) -> 0 | DA80: x
B81: IRR Check | C81: Ending Balance | F81: =F76+F77-F78-F79-F80 -> 13304744 | G81: =G76+G77-G78-G79-G80 -> 13477984 | H81: =H76+H77-H78-H79-H80 -> 13659875 | I81: =I76+I77-I78-I79-I80 -> 13864640 | J81: =J76+J77-J78-J79-J80 -> 14688754 | K81: =K76+K77-K78-K79-K80 -> 15535140 | L81: =L76+L77-L78-L79-L80 -> 16431621 | M81: =M76+M77-M78-M79-M80 -> 17345104 | ... CZ81: =CZ76+CZ77-CZ78-CZ79-CZ80 -> 0 | DA81: x
B82: =XIRR(F82:CZ82,$F$22:$CZ$22) -> 0.3 | C82: Total LP Cash Flow | F82: =SUM(F78:F80) -> -13304744 | G82: =SUM(G78:G80) -> 126557.56 | H82: =SUM(H78:H80) -> 111906.6 | I82: =SUM(I78:I80) -> 103035.4 | J82: =SUM(J78:J80) -> -511701.08 | K82: =SUM(K78:K80) -> -547756.04 | L82: =SUM(L78:L80) -> -546426.48 | M82: =SUM(M78:M80) -> -555300.52 | ... CZ82: =SUM(CZ78:CZ80) -> 0 | DA82: x
C83: GP Distributions | F83: =(F80/$H$15)*$G$15 -> 0 | G83: =(G80/$H$15)*$G$15 -> 0 | H83: =(H80/$H$15)*$G$15 -> 0 | I83: =(I80/$H$15)*$G$15 -> 0 | J83: =(J80/$H$15)*$G$15 -> 0 | K83: =(K80/$H$15)*$G$15 -> 0 | L83: =(L80/$H$15)*$G$15 -> 0 | M83: =(M80/$H$15)*$G$15 -> 0 | ... CZ83: =(CZ80/$H$15)*$G$15 -> 0 | DA83: x
C84: Total Distributions | F84: =F80+F83 -> 0 | G84: =G83+G80 -> 0 | H84: =H83+H80 -> 0 | I84: =I83+I80 -> 0 | J84: =J83+J80 -> 0 | K84: =K83+K80 -> 0 | L84: =L83+L80 -> 0 | M84: =M83+M80 -> 0 | N84: =N83+N80 -> 0 | ... CZ84: =CZ83+CZ80 -> 0 | DA84: x
C85: Cash Flow Remaining | F85: =F73-F84 -> 0 | G85: =G73-G84 -> 0 | H85: =H73-H84 -> 0 | I85: =I73-I84 -> 0 | J85: =J73-J84 -> 0 | K85: =K73-K84 -> 0 | L85: =L73-L84 -> 0 | M85: =M73-M84 -> 0 | ... CZ85: =CZ73-CZ84 -> 0 | DA85: x
C87: Hurdle #6 | DA87: x
C88: LP Distributions | F88: =F85*$H$16 -> 0 | G88: =G85*$H$16 -> 0 | H88: =H85*$H$16 -> 0 | I88: =I85*$H$16 -> 0 | J88: =J85*$H$16 -> 0 | K88: =K85*$H$16 -> 0 | L88: =L85*$H$16 -> 0 | M88: =M85*$H$16 -> 0 | ... CZ88: =CZ85*$H$16 -> 0 | DA88: x
C89: GP Distributions | F89: =F85*$G$16 -> 0 | G89: =G85*$G$16 -> 0 | H89: =H85*$G$16 -> 0 | I89: =I85*$G$16 -> 0 | J89: =J85*$G$16 -> 0 | K89: =K85*$G$16 -> 0 | L89: =L85*$G$16 -> 0 | M89: =M85*$G$16 -> 0 | ... CZ89: =CZ85*$G$16 -> 0 | DA89: x
C90: Total Distributions | F90: =SUM(F88:F89) -> 0 | G90: =SUM(G88:G89) -> 0 | H90: =SUM(H88:H89) -> 0 | I90: =SUM(I88:I89) -> 0 | J90: =SUM(J88:J89) -> 0 | K90: =SUM(K88:K89) -> 0 | L90: =SUM(L88:L89) -> 0 | M90: =SUM(M88:M89) -> 0 | ... CZ90: =SUM(CZ88:CZ89) -> 0 | DA90: x
C91: Cash Flow Remaining | F91: =F85-F90 -> 0 | G91: =G85-G90 -> 0 | H91: =H85-H90 -> 0 | I91: =I85-I90 -> 0 | J91: =J85-J90 -> 0 | K91: =K85-K90 -> 0 | L91: =L85-L90 -> 0 | M91: =M85-M90 -> 0 | ... CZ91: =CZ85-CZ90 -> 0 | DA91: x
B93: IRR | C93: LP Cash Flows | DA93: x
B94: =XIRR(F96:CZ96,$F$22:$CZ$22) -> 0.36236156 | C94: LP Contributions | F94: =F29 -> -13304744 | G94: =G29 -> 0 | H94: =H29 -> 0 | I94: =I29 -> 0 | J94: =J29 -> -511701.08 | K94: =K29 -> -547756.04 | L94: =L29 -> -546426.48 | M94: =M29 -> -555300.52 | ... CZ94: =CZ29 -> 0 | DA94: x
B95: EM | C95: LP Distributions | F95: =SUMIF($C$19:$C$91,$C$95,F$19:F$91) -> 0 | G95: =SUMIF($C$19:$C$91,$C$95,G$19:G$91) -> 126557.56 | H95: =SUMIF($C$19:$C$91,$C$95,H$19:H$91) -> 111906.6 | I95: =SUMIF($C$19:$C$91,$C$95,I$19:I$91) -> 103035.4 | J95: =SUMIF($C$19:$C$91,$C$95,J$19:J$91) -> 0 | K95: =SUMIF($C$19:$C$91,$C$95,K$19:K$91) -> 0 | L95: =SUMIF($C$19:$C$91,$C$95,L$19:L$91) -> 0 | M95: =SUMIF($C$19:$C$91,$C$95,M$19:M$91) -> 0 | ... CZ95: =SUMIF($C$19:$C$91,$C$95,CZ$19:CZ$91) -> 0 | DA95: x
B96: =-SUMIF(F96:CZ96,">0",F96:CZ96)/SUMIF(F96:CZ96,"<0",F96:CZ96) -> 2.1922832 | C96: Total LP Cash Flow | F96: =SUM(F94:F95) -> -13304744 | G96: =SUM(G94:G95) -> 126557.56 | H96: =SUM(H94:H95) -> 111906.6 | I96: =SUM(I94:I95) -> 103035.4 | J96: =SUM(J94:J95) -> -511701.08 | K96: =SUM(K94:K95) -> -547756.04 | L96: =SUM(L94:L95) -> -546426.48 | M96: =SUM(M94:M95) -> -555300.52 | ... CZ96: =SUM(CZ94:CZ95) -> 0 | DA96: x
DA97: x
B98: IRR | C98: GP Cash Flows | DA98: x
B99: =XIRR(F101:CZ101,$F$22:$CZ$22) -> 0.57671394 | C99: GP Contributions | F99: =F33 -> -1478304.9 | G99: =G33 -> 0 | H99: =H33 -> 0 | I99: =I33 -> 0 | J99: =J33 -> -56855.676 | K99: =K33 -> -60861.782 | L99: =L33 -> -60714.053 | M99: =M33 -> -61700.057 | ... CZ99: =CZ33 -> 0 | DA99: x
B100: EM | C100: GP Distributions | F100: =SUMIF($C$19:$C$91,$C$100,F$19:F$91) -> 0 | G100: =SUMIF($C$19:$C$91,$C$100,G$19:G$91) -> 0 | H100: =SUMIF($C$19:$C$91,$C$100,H$19:H$91) -> 0 | I100: =SUMIF($C$19:$C$91,$C$100,I$19:I$91) -> 0 | J100: =SUMIF($C$19:$C$91,$C$100,J$19:J$91) -> 0 | K100: =SUMIF($C$19:$C$91,$C$100,K$19:K$91) -> 0 | L100: =SUMIF($C$19:$C$91,$C$100,L$19:L$91) -> 0 | M100: =SUMIF($C$19:$C$91,$C$100,M$19:M$91) -> 0 | ... CZ100: =SUMIF($C$19:$C$91,$C$100,CZ$19:CZ$91) -> 0 | DA100: x
B101: =-SUMIF(F101:CZ101,">0",F101:CZ101)/SUMIF(F101:CZ101,"<0",F101:CZ101) -> 4.995989 | C101: Total GP Cash Flow | F101: =SUM(F99:F100) -> -1478304.9 | G101: =SUM(G99:G100) -> 0 | H101: =SUM(H99:H100) -> 0 | I101: =SUM(I99:I100) -> 0 | J101: =SUM(J99:J100) -> -56855.676 | K101: =SUM(K99:K100) -> -60861.782 | L101: =SUM(L99:L100) -> -60714.053 | M101: =SUM(M99:M100) -> -61700.057 | ... CZ101: =SUM(CZ99:CZ100) -> 0 | DA101: x
DA102: x
D103: Check | E103: =SUM(F103:DA103) -> -1.3096724e-10 | F103: =F101+F96-F24 -> 0 | G103: =G101+G96-G24 -> 0 | H103: =H101+H96-H24 -> 0 | I103: =I101+I96-I24 -> 0 | J103: =J101+J96-J24 -> 0 | K103: =K101+K96-K24 -> 0 | L103: =L101+L96-L24 -> 0 | M103: =M101+M96-M24 -> 0 | ... CZ103: =CZ101+CZ96-CZ24 -> 0 | DA103: x

Sheet Waterfall LP
C2: =Model!C3 -> Kimpton Anglers
C3: Waterfall Distribution
C5: Returns | F5: Profit | G5: IRR | H5: EM | J5: Equity Breakdown | M5: % | N5: Amount
C6: Deal Levered | F6: =SUM(F24:BY24) -> 29235441 | G6: =B24 -> 0.39585511 | H6: =B26 -> 2.4726538 | J6: Sponsor/GP | M6: 0.1 | N6: =M6*$M$12 -> 1938567.8
C7: LP | F7: =SUM(F96:BY96) -> 21580731 | G7: =B94 -> 0.32806203 | H7: =B96 -> 2.0870691 | J7: LP Investor | M7: =1-M6 -> 0.9 | N7: =M7*$M$12 -> 17447110
C8: GP | F8: =SUM(F101:BY101) -> 7654710.6 | G8: N/A | H8: N/A
J9: Transaction Sources
C10: Cash Flow Waterfall | F10: Return | G10: GP CF | H10: LP CF | M10: Amount | N10: Per Key | O10: %
C11: Pref Return | F11: 0.1 | G11: 0 | H11: =1-G11 -> 1 | J11: Debt | M11: =Model!$N$18 -> 23187000 | N11: =Model!$O$18 -> 175659.09 | O11: =Model!$P$18 -> 0.54464509
C12: Hurdle #2 | F12: 0.15 | G12: 0.2 | H12: =1-G12 -> 0.8 | J12: Equity | M12: =Model!$N$22 -> 19385678 | N12: =Model!$O$22 -> 146861.19 | O12: =Model!$P$22 -> 0.45535491
C13: Hurdle #3 | F13: 0.2 | G13: 0.25 | H13: =1-G13 -> 0.75 | J13: Total Sources | M13: =SUM(M11:M12) -> 42572678 | N13: =Model!O23 -> 322520.28 | O13: =SUM(O11:O12) -> 1
C14: Hurdle #4 | F14: 0.25 | G14: 0.25 | H14: =1-G14 -> 0.75
C15: Hurdle #5 | F15: 0.3 | G15: 0.25 | H15: =1-G15 -> 0.75
C16: Hurdle #6 | F16: >30% | G16: 0.5 | H16: =1-G16 -> 0.5
C18: Cash Flow Waterfall | DA18: x
C19: Year | F19: =YEAR(F22) -> 2025 | G19: =YEAR(G22) -> 2025 | H19: =YEAR(H22) -> 2025 | I19: =YEAR(I22) -> 2025 | J19: =YEAR(J22) -> 2026 | K19: =YEAR(K22) -> 2026 | L19: =YEAR(L22) -> 2026 | M19: =YEAR(M22) -> 2026 | ... CZ19: =YEAR(CZ22) -> 2033
C20: Year # | F20: =ROUNDUP(F21/12,0) -> 0 | G20: =ROUNDUP(G21/12,0) -> 1 | H20: =ROUNDUP(H21/12,0) -> 1 | I20: =ROUNDUP(I21/12,0) -> 1 | J20: =ROUNDUP(J21/12,0) -> 1 | K20: =ROUNDUP(K21/12,0) -> 1 | L20: =ROUNDUP(L21/12,0) -> 1 | M20: =ROUNDUP(M21/12,0) -> 1 | ... CZ20: =ROUNDUP(CZ21/12,0) -> 9
C21: Month | F21: 0 | G21: =F21+1 -> 1 | H21: =G21+1 -> 2 | I21: =H21+1 -> 3 | J21: =I21+1 -> 4 | K21: =J21+1 -> 5 | L21: =K21+1 -> 6 | M21: =L21+1 -> 7 | N21: =M21+1 -> 8 | ... CZ21: =CY21+1 -> 98
C22: Date | F22: =Model!S71 -> 45930 | G22: =EOMONTH(F22,1) -> 45961 | H22: =EOMONTH(G22,1) -> 45991 | I22: =EOMONTH(H22,1) -> 46022 | J22: =EOMONTH(I22,1) -> 46053 | K22: =EOMONTH(J22,1) -> 46081 | L22: =EOMONTH(K22,1) -> 46112 | M22: =EOMONTH(L22,1) -> 46142 | N22: =EOMONTH(M22,1) -> 46173 | ... CZ22: =EOMONTH(CY22,1) -> 48913
B23: IRR
B24: =XIRR($F$24:$CZ$24,$F$22:$CZ$22) -> 0.39585511 | C24: Levered Cash Flow | F24: =Model!S96 -> -14783049 | G24: =Model!T96 -> 126557.56 | H24: =Model!U96 -> 111906.6 | I24: =Model!V96 -> 103035.4 | J24: =Model!W96 -> -568556.76 | K24: =Model!X96 -> -608617.82 | L24: =Model!Y96 -> -607140.53 | M24: =Model!Z96 -> -617000.57 | ... CZ24: =Model!DM96 -> 0
B25: EM
B26: =-SUMIF(F24:BY24,">0",F24:BY24)/SUMIF(F24:BY24,"<0",F24:BY24) -> 2.4726538 | C26: Preferred Return
C27: Beginning Balance | F27: =E31 | G27: =F31 -> 14783049 | H27: =G31 -> 14776644 | I27: =H31 -> 14780948 | J27: =I31 -> 14798047 | K27: =J31 -> 15486878 | L27: =K31 -> 16209142 | M27: =L31 -> 16948026 | ... CZ27: =CY31 -> 0
C28: Preferred Return Accrual | F28: =F27*(1+$F$11)^((F$22-E$22)/365)-F27 -> 0 | G28: =G27*(1+$F$11)^((G$22-F$22)/365)-G27 -> 120152.03 | H28: =H27*(1+$F$11)^((H$22-G$22)/365)-H27 -> 116210.58 | I28: =I27*(1+$F$11)^((I$22-H$22)/365)-I27 -> 120134.94 | J28: =J27*(1+$F$11)^((J$22-I$22)/365)-J27 -> 120273.92 | K28: =K27*(1+$F$11)^((K$22-J$22)/365)-K27 -> 113646.73 | L28: =L27*(1+$F$11)^((L$22-K$22)/365)-L27 -> 131742.87 | M28: =M27*(1+$F$11)^((M$22-L$22)/365)-M27 -> 133287.36 | ... CZ28: =CZ27*(1+$F$11)^((CZ$22-CY$22)/365)-CZ27 -> 0
C29: LP Contributions | F29: =IF(F$24<0,F$24,0) -> -14783049 | G29: =IF(G$24<0,G$24,0) -> 0 | H29: =IF(H$24<0,H$24,0) -> 0 | I29: =IF(I$24<0,I$24,0) -> 0 | J29: =IF(J$24<0,J$24,0) -> -568556.76 | K29: =IF(K$24<0,K$24,0) -> -608617.82 | L29: =IF(L$24<0,L$24,0) -> -607140.53 | M29: =IF(M$24<0,M$24,0) -> -617000.57 | ... CZ29: =IF(CZ$24<0,CZ$24,0) -> 0
C30: LP Distributions | F30: =MIN(SUM(F27:F28),MAX(F$24,0)*$H$11) -> 0 | G30: =MIN(SUM(G27:G28),MAX(G$24,0)*$H$11) -> 126557.56 | H30: =MIN(SUM(H27:H28),MAX(H$24,0)*$H$11) -> 111906.6 | I30: =MIN(SUM(I27:I28),MAX(I$24,0)*$H$11) -> 103035.4 | J30: =MIN(SUM(J27:J28),MAX(J$24,0)*$H$11) -> 0 | K30: =MIN(SUM(K27:K28),MAX(K$24,0)*$H$11) -> 0 | L30: =MIN(SUM(L27:L28),MAX(L$24,0)*$H$11) -> 0 | M30: =MIN(SUM(M27:M28),MAX(M$24,0)*$H$11) -> 0 | ... CZ30: =MIN(SUM(CZ27:CZ28),MAX(CZ$24,0)*$H$11) -> 0
B31: IRR Check | C31: Ending Balance | F31: =F27+F28-F29-F30 -> 14783049 | G31: =G27+G28-G29-G30 -> 14776644 | H31: =H27+H28-H29-H30 -> 14780948 | I31: =I27+I28-I29-I30 -> 14798047 | J31: =J27+J28-J29-J30 -> 15486878 | K31: =K27+K28-K29-K30 -> 16209142 | L31: =L27+L28-L29-L30 -> 16948026 | M31: =M27+M28-M29-M30 -> 17698314 | ... CZ31: =CZ27+CZ28-CZ29-CZ30 -> 0
B32: =XIRR(F32:CZ32,$F$22:$CZ$22) -> 0.1 | C32: Total LP Cash Flow | F32: =SUM(F29:F30) -> -14783049 | G32: =SUM(G29:G30) -> 126557.56 | H32: =SUM(H29:H30) -> 111906.6 | I32: =SUM(I29:I30) -> 103035.4 | J32: =SUM(J29:J30) -> -568556.76 | K32: =SUM(K29:K30) -> -608617.82 | L32: =SUM(L29:L30) -> -607140.53 | M32: =SUM(M29:M30) -> -617000.57 | ... CZ32: =SUM(CZ29:CZ30) -> 0
C33: GP Contributions | F33: =IF(F24<0,F24*0,0) -> 0 | G33: =IF(G24<0,G24*0,0) -> 0 | H33: =IF(H24<0,H24*0,0) -> 0 | I33: =IF(I24<0,I24*0,0) -> 0 | J33: =IF(J24<0,J24*0,0) -> 0 | K33: =IF(K24<0,K24*0,0) -> 0 | L33: =IF(L24<0,L24*0,0) -> 0 | M33: =IF(M24<0,M24*0,0) -> 0 | ... CZ33: =IF(CZ24<0,CZ24*0,0) -> 0
C34: GP Distributions | F34: =(F30/$H$11)*$G$11 -> 0 | G34: =(G30/$H$11)*$G$11 -> 0 | H34: =(H30/$H$11)*$G$11 -> 0 | I34: =(I30/$H$11)*$G$11 -> 0 | J34: =(J30/$H$11)*$G$11 -> 0 | K34: =(K30/$H$11)*$G$11 -> 0 | L34: =(L30/$H$11)*$G$11 -> 0 | M34: =(M30/$H$11)*$G$11 -> 0 | ... CZ34: =(CZ30/$H$11)*$G$11 -> 0
C35: Total GP Cash Flow | F35: =SUM(F33:F34) -> 0 | G35: =SUM(G33:G34) -> 0 | H35: =SUM(H33:H34) -> 0 | I35: =SUM(I33:I34) -> 0 | J35: =SUM(J33:J34) -> 0 | K35: =SUM(K33:K34) -> 0 | L35: =SUM(L33:L34) -> 0 | M35: =SUM(M33:M34) -> 0 | ... CZ35: =SUM(CZ33:CZ34) -> 0
C36: Total Distributions | F36: =F30+F34 -> 0 | G36: =G30+G34 -> 126557.56 | H36: =H30+H34 -> 111906.6 | I36: =I30+I34 -> 103035.4 | J36: =J30+J34 -> 0 | K36: =K30+K34 -> 0 | L36: =L30+L34 -> 0 | M36: =M30+M34 -> 0 | ... CZ36: =CZ30+CZ34 -> 0
C37: Cash Flow Remaining | F37: =MAX(F24-F36,0) -> 0 | G37: =MAX(G24-G36,0) -> 0 | H37: =MAX(H24-H36,0) -> 0 | I37: =MAX(I24-I36,0) -> 0 | J37: =MAX(J24-J36,0) -> 0 | K37: =MAX(K24-K36,0) -> 0 | L37: =MAX(L24-L36,0) -> 0 | M37: =MAX(M24-M36,0) -> 0 | ... CZ37: =MAX(CZ24-CZ36,0) -> 0
C39: Hurdle #2
C40: Beginning Balance | F40: =E45 | G40: =F45 -> 14783049 | H40: =G45 -> 14833015 | I40: =H45 -> 14892482 | J40: =I45 -> 14967276 | K40: =J45 -> 15714556 | L40: =K45 -> 16492563 | M40: =L45 -> 17296640 | ... CZ40: =CY45 -> 0
C41: Hurdle #2 Accrual | F41: =F40*(1+$F$12)^((F$22-E$22)/365)-F40 -> 0 | G41: =G40*(1+$F$12)^((G$22-F$22)/365)-G40 -> 176523.25 | H41: =H40*(1+$F$12)^((H$22-G$22)/365)-H40 -> 171373.46 | I41: =I40*(1+$F$12)^((I$22-H$22)/365)-I40 -> 177829.97 | J41: =J40*(1+$F$12)^((J$22-I$22)/365)-J40 -> 178723.09 | K41: =K40*(1+$F$12)^((K$22-J$22)/365)-K40 -> 169389.48 | L41: =L40*(1+$F$12)^((L$22-K$22)/365)-L40 -> 196936.42 | M41: =M40*(1+$F$12)^((M$22-L$22)/365)-M40 -> 199837 | ... CZ41: =CZ40*(1+$F$12)^((CZ$22-CY$22)/365)-CZ40 -> 0
C42: LP Contributions | F42: =F29 -> -14783049 | G42: =G29 -> 0 | H42: =H29 -> 0 | I42: =I29 -> 0 | J42: =J29 -> -568556.76 | K42: =K29 -> -608617.82 | L42: =L29 -> -607140.53 | M42: =M29 -> -617000.57 | ... CZ42: =CZ29 -> 0
C43: Prior Distributions | F43: =F30 -> 0 | G43: =G30 -> 126557.56 | H43: =H30 -> 111906.6 | I43: =I30 -> 103035.4 | J43: =J30 -> 0 | K43: =K30 -> 0 | L43: =L30 -> 0 | M43: =M30 -> 0 | ... CZ43: =CZ30 -> 0
C44: LP Distributions | F44: =MIN(F40+F41-F42-F43,F37*$H$12) -> 0 | G44: =MIN(G40+G41-G42-G43,G37*$H$12) -> 0 | H44: =MIN(H40+H41-H42-H43,H37*$H$12) -> 0 | I44: =MIN(I40+I41-I42-I43,I37*$H$12) -> 0 | J44: =MIN(J40+J41-J42-J43,J37*$H$12) -> 0 | K44: =MIN(K40+K41-K42-K43,K37*$H$12) -> 0 | L44: =MIN(L40+L41-L42-L43,L37*$H$12) -> 0 | M44: =MIN(M40+M41-M42-M43,M37*$H$12) -> 0 | ... CZ44: =MIN(CZ40+CZ41-CZ42-CZ43,CZ37*$H$12) -> 0
B45: IRR Check | C45: Ending Balance | F45: =F40+F41-F42-F43-F44 -> 14783049 | G45: =G40+G41-G42-G43-G44 -> 14833015 | H45: =H40+H41-H42-H43-H44 -> 14892482 | I45: =I40+I41-I42-I43-I44 -> 14967276 | J45: =J40+J41-J42-J43-J44 -> 15714556 | K45: =K40+K41-K42-K43-K44 -> 16492563 | L45: =L40+L41-L42-L43-L44 -> 17296640 | M45: =M40+M41-M42-M43-M44 -> 18113478 | ... CZ45: =CZ40+CZ41-CZ42-CZ43-CZ44 -> 0 | DA45: x
B46: =XIRR(F46:CZ46,$F$22:$CZ$22) -> 0.15 | C46: Total LP Cash Flow | F46: =SUM(F42:F44) -> -14783049 | G46: =SUM(G42:G44) -> 126557.56 | H46: =SUM(H42:H44) -> 111906.6 | I46: =SUM(I42:I44) -> 103035.4 | J46: =SUM(J42:J44) -> -568556.76 | K46: =SUM(K42:K44) -> -608617.82 | L46: =SUM(L42:L44) -> -607140.53 | M46: =SUM(M42:M44) -> -617000.57 | ... CZ46: =SUM(CZ42:CZ44) -> 0 | DA46: x
C47: GP Distributions | F47: =(F44/$H$12)*$G$12 -> 0 | G47: =(G44/$H$12)*$G$12 -> 0 | H47: =(H44/$H$12)*$G$12 -> 0 | I47: =(I44/$H$12)*$G$12 -> 0 | J47: =(J44/$H$12)*$G$12 -> 0 | K47: =(K44/$H$12)*$G$12 -> 0 | L47: =(L44/$H$12)*$G$12 -> 0 | M47: =(M44/$H$12)*$G$12 -> 0 | ... CZ47: =(CZ44/$H$12)*$G$12 -> 0 | DA47: x
C48: Total Distributions | F48: =F44+F47 -> 0 | G48: =G44+G47 -> 0 | H48: =H44+H47 -> 0 | I48: =I44+I47 -> 0 | J48: =J44+J47 -> 0 | K48: =K44+K47 -> 0 | L48: =L44+L47 -> 0 | M48: =M44+M47 -> 0 | ... CZ48: =CZ44+CZ47 -> 0 | DA48: x
C49: Cash Flow Remaining | F49: =F37-F48 -> 0 | G49: =G37-G48 -> 0 | H49: =H37-H48 -> 0 | I49: =I37-I48 -> 0 | J49: =J37-J48 -> 0 | K49: =K37-K48 -> 0 | L49: =L37-L48 -> 0 | M49: =M37-M48 -> 0 | ... CZ49: =CZ37-CZ48 -> 0 | DA49: x
C51: Hurdle #3 | DA51: x
C52: Beginning Balance | F52: =E57 | G52: =F57 -> 14783049 | H52: =G57 -> 14887186 | I52: =H57 -> 15000049 | J52: =I57 -> 15131095 | K52: =J57 -> 15935778 | L52: =K57 -> 16768844 | M52: =L57 -> 17637668 | ... CZ52: =CY57 -> 0 | DA52: x
C53: Hurdle #3 Accrual | F53: =F52*(1+$F$13)^((F$22-E$22)/365)-F52 -> 0 | G53: =G52*(1+$F$13)^((G$22-F$22)/365)-G52 -> 230694.74 | H53: =H52*(1+$F$13)^((H$22-G$22)/365)-H52 -> 224769.37 | I53: =I52*(1+$F$13)^((I$22-H$22)/365)-I52 -> 234081.11 | J53: =J52*(1+$F$13)^((J$22-I$22)/365)-J52 -> 236126.12 | K53: =K52*(1+$F$13)^((K$22-J$22)/365)-K52 -> 224448.69 | L53: =L52*(1+$F$13)^((L$22-K$22)/365)-L52 -> 261683.78 | M53: =M52*(1+$F$13)^((M$22-L$22)/365)-M52 -> 266296.63 | ... CZ53: =CZ52*(1+$F$13)^((CZ$22-CY$22)/365)-CZ52 -> 0 | DA53: x
C54: LP Contributions | F54: =F42 -> -14783049 | G54: =G42 -> 0 | H54: =H42 -> 0 | I54: =I42 -> 0 | J54: =J42 -> -568556.76 | K54: =K42 -> -608617.82 | L54: =L42 -> -607140.53 | M54: =M42 -> -617000.57 | ... CZ54: =CZ42 -> 0 | DA54: x
C55: Prior Distributions | F55: =F30+F44 -> 0 | G55: =G30+G44 -> 126557.56 | H55: =H30+H44 -> 111906.6 | I55: =I30+I44 -> 103035.4 | J55: =J30+J44 -> 0 | K55: =K30+K44 -> 0 | L55: =L30+L44 -> 0 | M55: =M30+M44 -> 0 | ... CZ55: =CZ30+CZ44 -> 0 | DA55: x
C56: LP Distributions | F56: =MIN(F52+F53-F54-F55,F49*$H$13) -> 0 | G56: =MIN(G52+G53-G54-G55,G49*$H$13) -> 0 | H56: =MIN(H52+H53-H54-H55,H49*$H$13) -> 0 | I56: =MIN(I52+I53-I54-I55,I49*$H$13) -> 0 | J56: =MIN(J52+J53-J54-J55,J49*$H$13) -> 0 | K56: =MIN(K52+K53-K54-K55,K49*$H$13) -> 0 | L56: =MIN(L52+L53-L54-L55,L49*$H$13) -> 0 | M56: =MIN(M52+M53-M54-M55,M49*$H$13) -> 0 | ... CZ56: =MIN(CZ52+CZ53-CZ54-CZ55,CZ49*$H$13) -> 0 | DA56: x
B57: IRR Check | C57: Ending Balance | F57: =F52+F53-F54-F55-F56 -> 14783049 | G57: =G52+G53-G54-G55-G56 -> 14887186 | H57: =H52+H53-H54-H55-H56 -> 15000049 | I57: =I52+I53-I54-I55-I56 -> 15131095 | J57: =J52+J53-J54-J55-J56 -> 15935778 | K57: =K52+K53-K54-K55-K56 -> 16768844 | L57: =L52+L53-L54-L55-L56 -> 17637668 | M57: =M52+M53-M54-M55-M56 -> 18520966 | ... CZ57: =CZ52+CZ53-CZ54-CZ55-CZ56 -> 0 | DA57: x
B58: =XIRR(F58:CZ58,$F$22:$CZ$22) -> 0.2 | C58: Total LP Cash Flow | F58: =SUM(F54:F56) -> -14783049 | G58: =SUM(G54:G56) -> 126557.56 | H58: =SUM(H54:H56) -> 111906.6 | I58: =SUM(I54:I56) -> 103035.4 | J58: =SUM(J54:J56) -> -568556.76 | K58: =SUM(K54:K56) -> -608617.82 | L58: =SUM(L54:L56) -> -607140.53 | M58: =SUM(M54:M56) -> -617000.57 | ... CZ58: =SUM(CZ54:CZ56) -> 0 | DA58: x
C59: GP Distributions | F59: =(F56/$H$13)*$G$13 -> 0 | G59: =(G56/$H$13)*$G$13 -> 0 | H59: =(H56/$H$13)*$G$13 -> 0 | I59: =(I56/$H$13)*$G$13 -> 0 | J59: =(J56/$H$13)*$G$13 -> 0 | K59: =(K56/$H$13)*$G$13 -> 0 | L59: =(L56/$H$13)*$G$13 -> 0 | M59: =(M56/$H$13)*$G$13 -> 0 | ... CZ59: =(CZ56/$H$13)*$G$13 -> 0 | DA59: x
C60: Total Distributions | F60: =F59+F56 -> 0 | G60: =G59+G56 -> 0 | H60: =H59+H56 -> 0 | I60: =I59+I56 -> 0 | J60: =J59+J56 -> 0 | K60: =K59+K56 -> 0 | L60: =L59+L56 -> 0 | M60: =M59+M56 -> 0 | ... CZ60: =CZ59+CZ56 -> 0 | DA60: x
C61: Cash Flow Remaining | F61: =F49-F60 -> 0 | G61: =G49-G60 -> 0 | H61: =H49-H60 -> 0 | I61: =I49-I60 -> 0 | J61: =J49-J60 -> 0 | K61: =K49-K60 -> 0 | L61: =L49-L60 -> 0 | M61: =M49-M60 -> 0 | ... CZ61: =CZ49-CZ60 -> 0 | DA61: x
C63: Hurdle #4 | DA63: x
C64: Beginning Balance | F64: =E69 | G64: =F69 -> 14783049 | H64: =G69 -> 14812773 | I64: =H69 -> 14863141 | J64: =I69 -> 14941441 | K64: =J69 -> 15795867 | L64: =K69 -> 16677204 | M64: =L69 -> 17603424 | ... CZ64: =CY69 -> 0 | DA64: x
C65: Hurdle #4 Accrual | F65: =F64*(1+$F$14)^((F$22-E$22)/365)-F64 -> 0 | G65: =G64*(1+$F$14)^((G$22-F$22)/365)-G64 -> 282838.84 | H65: =H64*(1+$F$14)^((H$22-G$22)/365)-H64 -> 274181.27 | I65: =I64*(1+$F$14)^((I$22-H$22)/365)-I64 -> 284371.21 | J65: =J64*(1+$F$14)^((J$22-I$22)/365)-J64 -> 285869.3 | K65: =K64*(1+$F$14)^((K$22-J$22)/365)-K64 -> 272718.99 | L65: =L64*(1+$F$14)^((L$22-K$22)/365)-L64 -> 319079.04 | M65: =M64*(1+$F$14)^((M$22-L$22)/365)-M64 -> 325835.62 | ... CZ65: =CZ64*(1+$F$14)^((CZ$22-CY$22)/365)-CZ64 -> 0 | DA65: x
C66: LP Contributions | F66: =F54 -> -14783049 | G66: =G54 -> 0 | H66: =H54 -> 0 | I66: =I54 -> 0 | J66: =J54 -> -568556.76 | K66: =K54 -> -608617.82 | L66: =L54 -> -607140.53 | M66: =M54 -> -617000.57 | ... CZ66: =CZ54 -> 0 | DA66: x
C67: Prior Distributions | F67: =F30+F44+F56 -> 0 | G67: =G30+G43+G56 -> 253115.13 | H67: =H30+H43+H56 -> 223813.2 | I67: =I30+I43+I56 -> 206070.8 | J67: =J30+J43+J56 -> 0 | K67: =K30+K43+K56 -> 0 | L67: =L30+L43+L56 -> 0 | M67: =M30+M43+M56 -> 0 | N67: =N30+N43+N56 -> 0 | ... CZ67: =CZ30+CZ43+CZ56 -> 0 | DA67: x
C68: LP Distributions | F68: =MIN(F64+F65-F66-F67,F61*$H$14) -> 0 | G68: =MIN(G64+G65-G66-G67,G61*$H$14) -> 0 | H68: =MIN(H64+H65-H66-H67,H61*$H$14) -> 0 | I68: =MIN(I64+I65-I66-I67,I61*$H$14) -> 0 | J68: =MIN(J64+J65-J66-J67,J61*$H$14) -> 0 | K68: =MIN(K64+K65-K66-K67,K61*$H$14) -> 0 | L68: =MIN(L64+L65-L66-L67,L61*$H$14) -> 0 | M68: =MIN(M64+M65-M66-M67,M61*$H$14) -> 0 | ... CZ68: =MIN(CZ64+CZ65-CZ66-CZ67,CZ61*$H$14) -> 0 | DA68: x
B69: IRR Check | C69: Ending Balance | F69: =F64+F65-F66-F67-F68 -> 14783049 | G69: =G64+G65-G66-G67-G68 -> 14812773 | H69: =H64+H65-H66-H67-H68 -> 14863141 | I69: =I64+I65-I66-I67-I68 -> 14941441 | J69: =J64+J65-J66-J67-J68 -> 15795867 | K69: =K64+K65-K66-K67-K68 -> 16677204 | L69: =L64+L65-L66-L67-L68 -> 17603424 | M69: =M64+M65-M66-M67-M68 -> 18546260 | ... CZ69: =CZ64+CZ65-CZ66-CZ67-CZ68 -> 0 | DA69: x
B70: =XIRR(F70:CZ70,$F$22:$CZ$22) -> 0.25 | C70: Total LP Cash Flow | F70: =SUM(F66:F68) -> -14783049 | G70: =SUM(G66:G68) -> 253115.13 | H70: =SUM(H66:H68) -> 223813.2 | I70: =SUM(I66:I68) -> 206070.8 | J70: =SUM(J66:J68) -> -568556.76 | K70: =SUM(K66:K68) -> -608617.82 | L70: =SUM(L66:L68) -> -607140.53 | M70: =SUM(M66:M68) -> -617000.57 | ... CZ70: =SUM(CZ66:CZ68) -> 0 | DA70: x
C71: GP Distributions | F71: =(F68/$H$14)*$G$14 -> 0 | G71: =(G68/$H$14)*$G$14 -> 0 | H71: =(H68/$H$14)*$G$14 -> 0 | I71: =(I68/$H$14)*$G$14 -> 0 | J71: =(J68/$H$14)*$G$14 -> 0 | K71: =(K68/$H$14)*$G$14 -> 0 | L71: =(L68/$H$14)*$G$14 -> 0 | M71: =(M68/$H$14)*$G$14 -> 0 | ... CZ71: =(CZ68/$H$14)*$G$14 -> 0 | DA71: x
C72: Total Distributions | F72: =F71+F68 -> 0 | G72: =G71+G68 -> 0 | H72: =H71+H68 -> 0 | I72: =I71+I68 -> 0 | J72: =J71+J68 -> 0 | K72: =K71+K68 -> 0 | L72: =L71+L68 -> 0 | M72: =M71+M68 -> 0 | ... CZ72: =CZ71+CZ68 -> 0 | DA72: x
C73: Cash Flow Remaining | F73: =F61-F72 -> 0 | G73: =G61-G72 -> 0 | H73: =H61-H72 -> 0 | I73: =I61-I72 -> 0 | J73: =J61-J72 -> 0 | K73: =K61-K72 -> 0 | L73: =L61-L72 -> 0 | M73: =M61-M72 -> 0 | ... CZ73: =CZ61-CZ72 -> 0 | DA73: x
C75: Hurdle #5 | DA75: x
C76: Beginning Balance | F76: =E81 | G76: =F81 -> 14783049 | H76: =G81 -> 14989600 | I76: =H81 -> 15204442 | J76: =I81 -> 15444010 | K76: =J81 -> 16360568 | L76: =K81 -> 17301804 | M76: =L81 -> 18298808 | ... CZ76: =CY81 -> 0 | DA76: x
C77: Hurdle #5 Accrual | F77: =F76*(1+$F$15)^((F$22-E$22)/365)-F76 -> 0 | G77: =G76*(1+$F$15)^((G$22-F$22)/365)-G76 -> 333108.11 | H77: =H76*(1+$F$15)^((H$22-G$22)/365)-H76 -> 326748.89 | I77: =I76*(1+$F$15)^((I$22-H$22)/365)-I76 -> 342603.4 | J77: =J76*(1+$F$15)^((J$22-I$22)/365)-J76 -> 348001.61 | K77: =K76*(1+$F$15)^((K$22-J$22)/365)-K76 -> 332618.19 | L77: =L76*(1+$F$15)^((L$22-K$22)/365)-L76 -> 389863.5 | M77: =M76*(1+$F$15)^((M$22-L$22)/365)-M76 -> 398884.26 | ... CZ77: =CZ76*(1+$F$15)^((CZ$22-CY$22)/365)-CZ76 -> 0 | DA77: x
C78: LP Contributions | F78: =F66 -> -14783049 | G78: =G66 -> 0 | H78: =H66 -> 0 | I78: =I66 -> 0 | J78: =J66 -> -568556.76 | K78: =K66 -> -608617.82 | L78: =L66 -> -607140.53 | M78: =M66 -> -617000.57 | ... CZ78: =CZ66 -> 0 | DA78: x
C79: Prior Distributions | F79: =F30+F44+F56+F68 -> 0 | G79: =G30+G44+G56+G68 -> 126557.56 | H79: =H30+H44+H56+H68 -> 111906.6 | I79: =I30+I44+I56+I68 -> 103035.4 | J79: =J30+J44+J56+J68 -> 0 | K79: =K30+K44+K56+K68 -> 0 | L79: =L30+L44+L56+L68 -> 0 | M79: =M30+M44+M56+M68 -> 0 | ... CZ79: =CZ30+CZ44+CZ56+CZ68 -> 0 | DA79: x
C80: LP Distributions | F80: =MIN(F76+F77-F78-F79,F73*$H$15) -> 0 | G80: =MIN(G76+G77-G78-G79,G73*$H$15) -> 0 | H80: =MIN(H76+H77-H78-H79,H73*$H$15) -> 0 | I80: =MIN(I76+I77-I78-I79,I73*$H$15) -> 0 | J80: =MIN(J76+J77-J78-J79,J73*$H$15) -> 0 | K80: =MIN(K76+K77-K78-K79,K73*$H$15) -> 0 | L80: =MIN(L76+L77-L78-L79,L73*$H$15) -> 0 | M80: =MIN(M76+M77-M78-M79,M73*$H$15) -> 0 | ... CZ80: =MIN(CZ76+CZ77-CZ78-CZ79,CZ73*$H$15) -> 0 | DA80: x
B81: IRR Check | C81: Ending Balance | F81: =F76+F77-F78-F79-F80 -> 14783049 | G81: =G76+G77-G78-G79-G80 -> 14989600 | H81: =H76+H77-H78-H79-H80 -> 15204442 | I81: =I76+I77-I78-I79-I80 -> 15444010 | J81: =J76+J77-J78-J79-J80 -> 16360568 | K81: =K76+K77-K78-K79-K80 -> 17301804 | L81: =L76+L77-L78-L79-L80 -> 18298808 | M81: =M76+M77-M78-M79-M80 -> 19314693 | ... CZ81: =CZ76+CZ77-CZ78-CZ79-CZ80 -> 0 | DA81: x
B82: =XIRR(F82:CZ82,$F$22:$CZ$22) -> 0.3 | C82: Total LP Cash Flow | F82: =SUM(F78:F80) -> -14783049 | G82: =SUM(G78:G80) -> 126557.56 | H82: =SUM(H78:H80) -> 111906.6 | I82: =SUM(I78:I80) -> 103035.4 | J82: =SUM(J78:J80) -> -568556.76 | K82: =SUM(K78:K80) -> -608617.82 | L82: =SUM(L78:L80) -> -607140.53 | M82: =SUM(M78:M80) -> -617000.57 | ... CZ82: =SUM(CZ78:CZ80) -> 0 | DA82: x
C83: GP Distributions | F83: =(F80/$H$15)*$G$15 -> 0 | G83: =(G80/$H$15)*$G$15 -> 0 | H83: =(H80/$H$15)*$G$15 -> 0 | I83: =(I80/$H$15)*$G$15 -> 0 | J83: =(J80/$H$15)*$G$15 -> 0 | K83: =(K80/$H$15)*$G$15 -> 0 | L83: =(L80/$H$15)*$G$15 -> 0 | M83: =(M80/$H$15)*$G$15 -> 0 | ... CZ83: =(CZ80/$H$15)*$G$15 -> 0 | DA83: x
C84: Total Distributions | F84: =F80+F83 -> 0 | G84: =G83+G80 -> 0 | H84: =H83+H80 -> 0 | I84: =I83+I80 -> 0 | J84: =J83+J80 -> 0 | K84: =K83+K80 -> 0 | L84: =L83+L80 -> 0 | M84: =M83+M80 -> 0 | N84: =N83+N80 -> 0 | ... CZ84: =CZ83+CZ80 -> 0 | DA84: x
C85: Cash Flow Remaining | F85: =F73-F84 -> 0 | G85: =G73-G84 -> 0 | H85: =H73-H84 -> 0 | I85: =I73-I84 -> 0 | J85: =J73-J84 -> 0 | K85: =K73-K84 -> 0 | L85: =L73-L84 -> 0 | M85: =M73-M84 -> 0 | ... CZ85: =CZ73-CZ84 -> 0 | DA85: x
C87: Hurdle #6 | DA87: x
C88: LP Distributions | F88: =F85*$H$16 -> 0 | G88: =G85*$H$16 -> 0 | H88: =H85*$H$16 -> 0 | I88: =I85*$H$16 -> 0 | J88: =J85*$H$16 -> 0 | K88: =K85*$H$16 -> 0 | L88: =L85*$H$16 -> 0 | M88: =M85*$H$16 -> 0 | ... CZ88: =CZ85*$H$16 -> 0 | DA88: x
C89: GP Distributions | F89: =F85*$G$16 -> 0 | G89: =G85*$G$16 -> 0 | H89: =H85*$G$16 -> 0 | I89: =I85*$G$16 -> 0 | J89: =J85*$G$16 -> 0 | K89: =K85*$G$16 -> 0 | L89: =L85*$G$16 -> 0 | M89: =M85*$G$16 -> 0 | ... CZ89: =CZ85*$G$16 -> 0 | DA89: x
C90: Total Distributions | F90: =SUM(F88:F89) -> 0 | G90: =SUM(G88:G89) -> 0 | H90: =SUM(H88:H89) -> 0 | I90: =SUM(I88:I89) -> 0 | J90: =SUM(J88:J89) -> 0 | K90: =SUM(K88:K89) -> 0 | L90: =SUM(L88:L89) -> 0 | M90: =SUM(M88:M89) -> 0 | ... CZ90: =SUM(CZ88:CZ89) -> 0 | DA90: x
C91: Cash Flow Remaining | F91: =F85-F90 -> 0 | G91: =G85-G90 -> 0 | H91: =H85-H90 -> 0 | I91: =I85-I90 -> 0 | J91: =J85-J90 -> 0 | K91: =K85-K90 -> 0 | L91: =L85-L90 -> 0 | M91: =M85-M90 -> 0 | ... CZ91: =CZ85-CZ90 -> 0 | DA91: x
B93: IRR | C93: LP Cash Flows | DA93: x
B94: =XIRR(F96:CZ96,$F$22:$CZ$22) -> 0.32806203 | C94: LP Contributions | F94: =F29 -> -14783049 | G94: =G29 -> 0 | H94: =H29 -> 0 | I94: =I29 -> 0 | J94: =J29 -> -568556.76 | K94: =K29 -> -608617.82 | L94: =L29 -> -607140.53 | M94: =M29 -> -617000.57 | ... CZ94: =CZ29 -> 0 | DA94: x
B95: EM | C95: LP Distributions | F95: =SUMIF($C$19:$C$91,$C$95,F$19:F$91) -> 0 | G95: =SUMIF($C$19:$C$91,$C$95,G$19:G$91) -> 126557.56 | H95: =SUMIF($C$19:$C$91,$C$95,H$19:H$91) -> 111906.6 | I95: =SUMIF($C$19:$C$91,$C$95,I$19:I$91) -> 103035.4 | J95: =SUMIF($C$19:$C$91,$C$95,J$19:J$91) -> 0 | K95: =SUMIF($C$19:$C$91,$C$95,K$19:K$91) -> 0 | L95: =SUMIF($C$19:$C$91,$C$95,L$19:L$91) -> 0 | M95: =SUMIF($C$19:$C$91,$C$95,M$19:M$91) -> 0 | ... CZ95: =SUMIF($C$19:$C$91,$C$95,CZ$19:CZ$91) -> 0 | DA95: x
B96: =-SUMIF(F96:CZ96,">0",F96:CZ96)/SUMIF(F96:CZ96,"<0",F96:CZ96) -> 2.0870691 | C96: Total LP Cash Flow | F96: =SUM(F94:F95) -> -14783049 | G96: =SUM(G94:G95) -> 126557.56 | H96: =SUM(H94:H95) -> 111906.6 | I96: =SUM(I94:I95) -> 103035.4 | J96: =SUM(J94:J95) -> -568556.76 | K96: =SUM(K94:K95) -> -608617.82 | L96: =SUM(L94:L95) -> -607140.53 | M96: =SUM(M94:M95) -> -617000.57 | ... CZ96: =SUM(CZ94:CZ95) -> 0 | DA96: x
DA97: x
B98: IRR | C98: GP Cash Flows | DA98: x
B99: =XIRR(F101:CZ101,$F$22:$CZ$22) -> #NUM! | C99: GP Contributions | F99: =F33 -> 0 | G99: =G33 -> 0 | H99: =H33 -> 0 | I99: =I33 -> 0 | J99: =J33 -> 0 | K99: =K33 -> 0 | L99: =L33 -> 0 | M99: =M33 -> 0 | ... CZ99: =CZ33 -> 0 | DA99: x
B100: EM | C100: GP Distributions | F100: =SUMIF($C$19:$C$91,$C$100,F$19:F$91) -> 0 | G100: =SUMIF($C$19:$C$91,$C$100,G$19:G$91) -> 0 | H100: =SUMIF($C$19:$C$91,$C$100,H$19:H$91) -> 0 | I100: =SUMIF($C$19:$C$91,$C$100,I$19:I$91) -> 0 | J100: =SUMIF($C$19:$C$91,$C$100,J$19:J$91) -> 0 | K100: =SUMIF($C$19:$C$91,$C$100,K$19:K$91) -> 0 | L100: =SUMIF($C$19:$C$91,$C$100,L$19:L$91) -> 0 | M100: =SUMIF($C$19:$C$91,$C$100,M$19:M$91) -> 0 | ... CZ100: =SUMIF($C$19:$C$91,$C$100,CZ$19:CZ$91) -> 0 | DA100: x
B101: =-SUMIF(F101:CZ101,">0",F101:CZ101)/SUMIF(F101:CZ101,"<0",F101:CZ101) -> #DIV/0! | C101: Total GP Cash Flow | F101: =SUM(F99:F100) -> 0 | G101: =SUM(G99:G100) -> 0 | H101: =SUM(H99:H100) -> 0 | I101: =SUM(I99:I100) -> 0 | J101: =SUM(J99:J100) -> 0 | K101: =SUM(K99:K100) -> 0 | L101: =SUM(L99:L100) -> 0 | M101: =SUM(M99:M100) -> 0 | ... CZ101: =SUM(CZ99:CZ100) -> 0 | DA101: x
DA102: x
D103: Check | E103: =SUM(F103:DA103) -> -3.7107384e-09 | F103: =F101+F96-F24 -> 0 | G103: =G101+G96-G24 -> 0 | H103: =H101+H96-H24 -> 0 | I103: =I101+I96-I24 -> 0 | J103: =J101+J96-J24 -> 0 | K103: =K101+K96-K24 -> 0 | L103: =L101+L96-L24 -> 0 | M103: =M101+M96-M24 -> 0 | ... CZ103: =CZ101+CZ96-CZ24 -> 0 | DA103: x

Sheet Index Analysis
B2: PRELIMINARY HOTEL UNDERWRITING
B3: Index Analysis
C5: Historical | I5: Forecast | J5: Forecast
B6: SUBJECT PROPERTY | C6: 2019 | D6: =+C6+1 -> 2020 | E6: =+D6+1 -> 2021 | F6: =+E6+1 -> 2022 | G6: =+F6+1 -> 2023 | H6: =+G6+1 -> 2024 | I6: =+H6+1 -> 2025 | J6: =+I6+1 -> 2026 | K6: =+J6+1 -> 2027 | ... R6: =+Q6+1 -> 2034
B7: Days | C7: 366 | D7: 365 | E7: 365 | F7: 365 | G7: 366 | H7: 366 | I7: 366 | J7: 365 | K7: 365 | L7: 365 | M7: 366 | N7: 365 | O7: 365 | P7: 365 | Q7: 366 | R7: 365
B8: Keys | C8: =Model!C10 -> 132 | D8: =+C8 -> 132 | E8: =+D8 -> 132 | F8: =+E8 -> 132 | G8: =+F8 -> 132 | H8: =+G8 -> 132 | I8: =+H8 -> 132 | J8: =+G8 -> 132 | K8: =+H8 -> 132 | L8: =+K8 -> 132 | M8: =+L8 -> 132 | N8: =+M8 -> 132 | O8: =+N8 -> 132 | P8: =+O8 -> 132 | Q8: =+P8 -> 132 | R8: =+Q8 -> 132
B9: Available Rooms | C9: =+IFERROR(C8*C7,"n/a") -> 48312 | D9: =+IFERROR(D8*D7,"n/a") -> 48180 | E9: =+IFERROR(E8*E7,"n/a") -> 48180 | F9: =+IFERROR(F8*F7,"n/a") -> 48180 | G9: =+IFERROR(G8*G7,"n/a") -> 48312 | H9: =+IFERROR(H8*H7,"n/a") -> 48312 | I9: =+IFERROR(I8*I7,"n/a") -> 48312 | J9: =+IFERROR(J8*J7,"n/a") -> 48180 | ... R9: =+IFERROR(R8*R7,"n/a") -> 48180
B10: Occupied Rooms | C10: =+IFERROR(C9*C12,"n/a") -> 32653.216 | D10: =+IFERROR(D9*D12,"n/a") -> 19808.73 | E10: =+IFERROR(E9*E12,"n/a") -> 40168 | F10: =+IFERROR(F9*F12,"n/a") -> 40967 | G10: =+IFERROR(G9*G12,"n/a") -> 39804.756 | H10: =+IFERROR(H9*H12,"n/a") -> 40223 | I10: =+IFERROR(I9*I12,"n/a") -> 39256.258 | J10: =+IFERROR(J9*J12,"n/a") -> 36375.9 | ... R10: =+IFERROR(R9*R12,"n/a") -> 37202.659
B12: Occupancy | C12: =Historical!G12 -> 0.67588211 | D12: =Historical!L12 -> 0.41114009 | E12: =Historical!Q12 -> 0.83370693 | F12: =Historical!V12 -> 0.85029058 | G12: =Historical!AA12 -> 0.82391034 | H12: =Historical!AF12 -> 0.83256748 | I12: =Historical!AK12 -> 0.81255708 | J12: =+J23*J31 -> 0.755 | K12: =+K23*K31 -> 0.755 | L12: =+L23*L31 -> 0.74594 | M12: =+M23*M31 -> 0.7683182 | N12: =+N23*N31 -> 0.77215979 | O12: =+O23*O31 -> 0.77215979 | P12: =+P23*P31 -> 0.77215979 | Q12: =+Q23*Q31 -> 0.77215979 | R12: =+R23*R31 -> 0.77215979
B13: ADR | C13: =Historical!G13 -> 194.69182 | D13: =Historical!L13 -> 204.82499 | E13: =Historical!Q13 -> 233.74963 | F13: =Historical!V13 -> 275.60042 | G13: =Historical!AA13 -> 247.07762 | H13: =Historical!AF13 -> 236.09396 | I13: =Historical!AK13 -> 239.78997 | J13: =+J24*J32 -> 295.42747 | K13: =+K24*K32 -> 296.68227 | L13: =+L24*L32 -> 311.09861 | M13: =+M24*M32 -> 323.03977 | N13: =+N24*N32 -> 329.50056 | O13: =+O24*O32 -> 343.50434 | P13: =+P24*P32 -> 357.24451 | Q13: =+Q24*Q32 -> 364.3894 | R13: =+R24*R32 -> 368.0333
B14: RevPAR | C14: =C12*C13 -> 131.58872 | D14: =D12*D13 -> 84.211765 | E14: =E12*E13 -> 194.87869 | F14: =F12*F13 -> 234.34044 | G14: =G12*G13 -> 203.56981 | H14: =H12*H13 -> 196.56415 | I14: =I12*I13 -> 194.84304 | J14: =J12*J13 -> 223.04774 | ... R14: =R12*R13 -> 284.18051
B16: Occupancy Growth | C16: =+IFERROR(C12/#REF!-1,"n/a") -> n/a | D16: =+IFERROR(D12/C12-1,"n/a") -> -0.39169852 | E16: =+IFERROR(E12/D12-1,"n/a") -> 1.0277928 | F16: =+IFERROR(F12/E12-1,"n/a") -> 0.019891456 | G16: =+IFERROR(G12/F12-1,"n/a") -> -0.031024971 | H16: =+IFERROR(H12/G12-1,"n/a") -> 0.010507383 | I16: =+IFERROR(I12/H12-1,"n/a") -> -0.024034569 | J16: =+IFERROR(J12/I12-1,"n/a") -> -0.070834504 | K16: =+IFERROR(K12/J12-1,"n/a") -> 0 | ... R16: =+IFERROR(R12/Q12-1,"n/a") -> 0
B17: ADR Growth | C17: =+IFERROR(C13/#REF!-1,"n/a") -> n/a | D17: =+IFERROR(D13/C13-1,"n/a") -> 0.05204722 | E17: =+IFERROR(E13/D13-1,"n/a") -> 0.14121635 | F17: =+IFERROR(F13/E13-1,"n/a") -> 0.17904111 | G17: =+IFERROR(G13/F13-1,"n/a") -> -0.10349331 | H17: =+IFERROR(H13/G13-1,"n/a") -> -0.044454315 | I17: =+IFERROR(I13/H13-1,"n/a") -> 0.015654853 | J17: =+IFERROR(J13/I13-1,"n/a") -> 0.23202595 | K17: =+IFERROR(K13/J13-1,"n/a") -> 0.0042474227 | ... R17: =+IFERROR(R13/Q13-1,"n/a") -> 0.01
B18: RevPAR Growth | C18: =+IFERROR(C14/#REF!-1,"n/a") -> n/a | D18: =+IFERROR(D14/C14-1,"n/a") -> -0.36003812 | E18: =+IFERROR(E14/D14-1,"n/a") -> 1.3141503 | F18: =+IFERROR(F14/E14-1,"n/a") -> 0.20249396 | G18: =+IFERROR(G14/F14-1,"n/a") -> -0.1313074 | H18: =+IFERROR(H14/G14-1,"n/a") -> -0.03441403 | I18: =+IFERROR(I14/H14-1,"n/a") -> -0.0087559734 | J18: =+IFERROR(J14/I14-1,"n/a") -> 0.144756 | K18: =+IFERROR(K14/J14-1,"n/a") -> 0.0042474227 | ... R18: =+IFERROR(R14/Q14-1,"n/a") -> 0.01
B20: COSTAR MARKET | C20: Historical | I20: May YTD | J20: Forecast
B21: COMPETITIVE SET | C21: 2019 | D21: =+C21+1 -> 2020 | E21: =+D21+1 -> 2021 | F21: =+E21+1 -> 2022 | G21: =+F21+1 -> 2023 | H21: =+G21+1 -> 2024 | I21: =+H21+1 -> 2025 | J21: =+I21+1 -> 2026 | K21: =+J21+1 -> 2027 | ... R21: =+Q21+1 -> 2034
B23: Occupancy | F23: 0.658 | G23: 0.695 | H23: 0.742 | I23: 0.755 | J23: =+I23*(1+J27) -> 0.755 | K23: =+J23*(1+K27) -> 0.755 | L23: =+K23*(1+L27) -> 0.74594 | M23: =+L23*(1+M27) -> 0.7683182 | N23: =+M23*(1+N27) -> 0.77215979 | O23: =+N23*(1+O27) -> 0.77215979 | P23: =+O23*(1+P27) -> 0.77215979 | Q23: =+P23*(1+Q27) -> 0.77215979 | R23: =+Q23*(1+R27) -> 0.77215979 | T23: Hotel Name | W23: Keys
B24: ADR | F24: 328.54293 | G24: 310.52 | H24: 284.79 | I24: 310.78 | J24: =+I24*(1+J28) -> 304.5644 | K24: =+J24*(1+K28) -> 302.73701 | L24: =+K24*(1+L28) -> 314.24102 | M24: =+L24*(1+M28) -> 323.03977 | N24: =+M24*(1+N28) -> 329.50056 | O24: =+N24*(1+O28) -> 343.50434 | P24: =+O24*(1+P28) -> 357.24451 | Q24: =+P24*(1+Q28) -> 364.3894 | R24: =+Q24*(1+R28) -> 368.0333 | T24: Z Ocean Hotel, Classico A Sonesta Collection | W24: 35
B25: RevPAR | C25: =C23*C24 -> 0 | D25: =D23*D24 -> 0 | E25: =E23*E24 -> 0 | F25: =F23*F24 -> 216.18125 | G25: =G23*G24 -> 215.8114 | H25: =H23*H24 -> 211.31418 | I25: =I23*I24 -> 234.6389 | J25: =J23*J24 -> 229.94612 | ... R25: =R23*R24 -> 284.18051 | T25: Blue Moon Hotel | W25: 75
T26: The Betsy South Beach | W26: 129
B27: Occupancy Growth | C27: =+IFERROR(C23/#REF!-1,"n/a") -> n/a | D27: =+IFERROR(D23/C23-1,"n/a") -> n/a | E27: =+IFERROR(E23/D23-1,"n/a") -> n/a | F27: =+IFERROR(F23/E23-1,"n/a") -> n/a | G27: =+IFERROR(G23/F23-1,"n/a") -> 0.056231003 | H27: =+IFERROR(H23/G23-1,"n/a") -> 0.067625899 | I27: =+IFERROR(I23/H23-1,"n/a") -> 0.017520216 | J27: 0 | K27: 0 | L27: -0.012 | M27: 0.03 | N27: 0.005 | O27: 0 | P27: 0 | Q27: 0 | R27: 0 | T27: The Tony Hotel of South Beach | W27: 73
B28: ADR Growth | C28: =+IFERROR(C24/#REF!-1,"n/a") -> n/a | D28: =+IFERROR(D24/C24-1,"n/a") -> n/a | E28: =+IFERROR(E24/D24-1,"n/a") -> n/a | F28: =+IFERROR(F24/E24-1,"n/a") -> n/a | G28: =+IFERROR(G24/F24-1,"n/a") -> -0.054857163 | H28: =+IFERROR(H24/G24-1,"n/a") -> -0.082861007 | I28: =+IFERROR(I24/H24-1,"n/a") -> 0.091260227 | J28: -0.02 | K28: -0.006 | L28: 0.038 | M28: 0.028 | N28: 0.02 | O28: 0.0425 | P28: 0.04 | Q28: 0.02 | R28: 0.01 | T28: Dream South Beach | W28: 107
B29: RevPAR Growth | C29: =+IFERROR(C25/#REF!-1,"n/a") -> n/a | D29: =+IFERROR(D25/C25-1,"n/a") -> n/a | E29: =+IFERROR(E25/D25-1,"n/a") -> n/a | F29: =+IFERROR(F25/E25-1,"n/a") -> n/a | G29: =+IFERROR(G25/F25-1,"n/a") -> -0.0017108337 | H29: =+IFERROR(H25/G25-1,"n/a") -> -0.020838658 | I29: =+IFERROR(I25/H25-1,"n/a") -> 0.11037934 | J29: =+IFERROR(J25/I25-1,"n/a") -> -0.02 | K29: =+IFERROR(K25/J25-1,"n/a") -> -0.006 | ... R29: =+IFERROR(R25/Q25-1,"n/a") -> 0.01 | T29: Total | W29: =SUM(W24:W28) -> 419
B31: Occupancy Penetration | C31: =+IFERROR(C12/C23,"n/a") -> n/a | D31: =+IFERROR(D12/D23,"n/a") -> n/a | E31: =+IFERROR(E12/E23,"n/a") -> n/a | F31: =+IFERROR(F12/F23,"n/a") -> 1.2922349 | G31: =+IFERROR(G12/G23,"n/a") -> 1.1854825 | H31: =+IFERROR(H12/H23,"n/a") -> 1.1220586 | I31: =+IFERROR(I12/I23,"n/a") -> 1.0762345 | J31: 1 | K31: 1 | L31: 1 | M31: 1 | N31: 1 | O31: =+N31 -> 1 | P31: =+O31 -> 1 | Q31: =+P31 -> 1 | R31: =+Q31 -> 1
B32: ADR Penetration | C32: =+IFERROR(C13/C24,"n/a") -> n/a | D32: =+IFERROR(D13/D24,"n/a") -> n/a | E32: =+IFERROR(E13/E24,"n/a") -> n/a | F32: =+IFERROR(F13/F24,"n/a") -> 0.83885664 | G32: =+IFERROR(G13/G24,"n/a") -> 0.79568989 | H32: =+IFERROR(H13/H24,"n/a") -> 0.8290107 | I32: =+IFERROR(I13/I24,"n/a") -> 0.77157466 | J32: 0.97 | K32: 0.98 | L32: 0.99 | M32: 1 | N32: 1 | O32: =N32 -> 1 | P32: =O32 -> 1 | Q32: =P32 -> 1 | R32: =Q32 -> 1
B33: RevPAR Penetration | C33: =+IFERROR(C14/C25,"n/a") -> n/a | D33: =+IFERROR(D14/D25,"n/a") -> n/a | E33: =+IFERROR(E14/E25,"n/a") -> n/a | F33: =+IFERROR(F14/F25,"n/a") -> 1.0839998 | G33: =+IFERROR(G14/G25,"n/a") -> 0.94327643 | H33: =+IFERROR(H14/H25,"n/a") -> 0.93019858 | I33: =+IFERROR(I14/I25,"n/a") -> 0.8303953 | J33: =+IFERROR(J14/J25,"n/a") -> 0.97 | ... R33: =+IFERROR(R14/R25,"n/a") -> 1
B35: Occ Variance to Subject | C35: =+IFERROR(C23-C12,"n/a") -> -0.67588211 | D35: =+IFERROR(D23-D12,"n/a") -> -0.41114009 | E35: =+IFERROR(E23-E12,"n/a") -> -0.83370693 | F35: =+IFERROR(F23-F12,"n/a") -> -0.19229058 | G35: =+IFERROR(G23-G12,"n/a") -> -0.12891034 | H35: =+IFERROR(H23-H12,"n/a") -> -0.090567478 | I35: =+IFERROR(I23-I12,"n/a") -> -0.057557078 | J35: =+IFERROR(J23-J12,"n/a") -> 0 | ... R35: =+IFERROR(R23-R12,"n/a") -> 0
B36: ADR Variance to Subject | C36: =+IFERROR(C24-C13,"n/a") -> -194.69182 | D36: =+IFERROR(D24-D13,"n/a") -> -204.82499 | E36: =+IFERROR(E24-E13,"n/a") -> -233.74963 | F36: =+IFERROR(F24-F13,"n/a") -> 52.942511 | G36: =+IFERROR(G24-G13,"n/a") -> 63.442377 | H36: =+IFERROR(H24-H13,"n/a") -> 48.696043 | I36: =+IFERROR(I24-I13,"n/a") -> 70.990027 | J36: =+IFERROR(J24-J13,"n/a") -> 9.136932 | ... R36: =+IFERROR(R24-R13,"n/a") -> 0
B37: RevPAR Variance to Subject | C37: =+IFERROR(C25-C14,"n/a") -> -131.58872 | D37: =+IFERROR(D25-D14,"n/a") -> -84.211765 | E37: =+IFERROR(E25-E14,"n/a") -> -194.87869 | F37: =+IFERROR(F25-F14,"n/a") -> -18.159192 | G37: =+IFERROR(G25-G14,"n/a") -> 12.241592 | H37: =+IFERROR(H25-H14,"n/a") -> 14.75003 | I37: =+IFERROR(I25-I14,"n/a") -> 39.79586 | J37: =+IFERROR(J25-J14,"n/a") -> 6.8983837 | ... R37: =+IFERROR(R25-R14,"n/a") -> 0
B39: COSTAR MARKET | C39: Historical | I39: Forecast | J39: Forecast
B40: Miami Beach Luxury & Upper Upscale | C40: 2019 | D40: =+C40+1 -> 2020 | E40: =+D40+1 -> 2021 | F40: =+E40+1 -> 2022 | G40: =+F40+1 -> 2023 | H40: =+G40+1 -> 2024 | I40: =+H40+1 -> 2025 | J40: =+I40+1 -> 2026 | K40: =+J40+1 -> 2027 | ... R40: =+Q40+1 -> 2034
B42: Occupancy | C42: 0.776 | D42: 0.443 | E42: 0.667 | F42: 0.706 | G42: 0.706 | H42: 0.71 | I42: 0.689 | J42: =+I42*(1+J46) -> 0.680732 | K42: =+J42*(1+K46) -> 0.680732 | L42: =+K42*(1+L46) -> 0.67256322 | M42: =+L42*(1+M46) -> 0.69274011 | N42: =+M42*(1+N46) -> 0.69620381 | O42: =+N42*(1+O46) -> 0.69620381 | P42: =+O42*(1+P46) -> 0.69620381 | Q42: =+P42*(1+Q46) -> 0.69620381 | R42: =+Q42*(1+R46) -> 0.69620381
B43: ADR | C43: 306.58 | D43: 334.43 | E43: 388.2 | F43: 430.41 | G43: 390.22 | H43: 392.11 | I43: 409.18 | J43: =+I43*(1+J47) -> 416.54524 | K43: =+J43*(1+K47) -> 414.04597 | L43: =+K43*(1+L47) -> 429.77972 | M43: =+L43*(1+M47) -> 441.81355 | N43: =+M43*(1+N47) -> 450.64982 | O43: =+N43*(1+O47) -> 459.66281 | P43: =+O43*(1+P47) -> 468.85607 | Q43: =+P43*(1+Q47) -> 478.23319 | R43: =+Q43*(1+R47) -> 487.79786
B44: RevPAR | C44: =C42*C43 -> 237.90608 | D44: =D42*D43 -> 148.15249 | E44: =E42*E43 -> 258.9294 | F44: =F42*F43 -> 303.86946 | G44: =G42*G43 -> 275.49532 | H44: =H42*H43 -> 278.3981 | I44: =I42*I43 -> 281.92502 | J44: =J42*J43 -> 283.55567 | ... R44: =R42*R43 -> 339.60673
B46: Occupancy Growth | C46: =+IFERROR(C42/#REF!-1,"n/a") -> n/a | D46: =+IFERROR(D42/C42-1,"n/a") -> -0.42912371 | E46: =+IFERROR(E42/D42-1,"n/a") -> 0.50564334 | F46: =+IFERROR(F42/E42-1,"n/a") -> 0.058470765 | G46: =+IFERROR(G42/F42-1,"n/a") -> 0 | H46: =+IFERROR(H42/G42-1,"n/a") -> 0.0056657224 | I46: =+IFERROR(I42/H42-1,"n/a") -> -0.029577465 | J46: -0.012 | K46: 0 | L46: -0.012 | M46: 0.03 | N46: 0.005 | O46: 0 | P46: 0 | Q46: 0 | R46: 0
B47: ADR Growth | C47: =+IFERROR(C43/#REF!-1,"n/a") -> n/a | D47: =+IFERROR(D43/C43-1,"n/a") -> 0.09084089 | E47: =+IFERROR(E43/D43-1,"n/a") -> 0.16078103 | F47: =+IFERROR(F43/E43-1,"n/a") -> 0.10873261 | G47: =+IFERROR(G43/F43-1,"n/a") -> -0.093376083 | H47: =+IFERROR(H43/G43-1,"n/a") -> 0.0048434217 | I47: =+IFERROR(I43/H43-1,"n/a") -> 0.043533702 | J47: 0.018 | K47: -0.006 | L47: 0.038 | M47: 0.028 | N47: 0.02 | O47: 0.02 | P47: 0.02 | Q47: 0.02 | R47: 0.02
B48: RevPAR Growth | C48: =+IFERROR(C44/#REF!-1,"n/a") -> n/a | D48: =+IFERROR(D44/C44-1,"n/a") -> -0.3772648 | E48: =+IFERROR(E44/D44-1,"n/a") -> 0.74772223 | F48: =+IFERROR(F44/E44-1,"n/a") -> 0.17356106 | G48: =+IFERROR(G44/F44-1,"n/a") -> -0.093376083 | H48: =+IFERROR(H44/G44-1,"n/a") -> 0.010536586 | I48: =+IFERROR(I44/H44-1,"n/a") -> 0.012668621 | J48: =+IFERROR(J44/I44-1,"n/a") -> 0.005784 | K48: =+IFERROR(K44/J44-1,"n/a") -> -0.006 | ... R48: =+IFERROR(R44/Q44-1,"n/a") -> 0.02
B50: Occupancy Penetration | C50: =+IFERROR(C12/C42,"n/a") -> 0.8709821 | D50: =+IFERROR(D12/D42,"n/a") -> 0.92808147 | E50: =+IFERROR(E12/E42,"n/a") -> 1.2499354 | F50: =+IFERROR(F12/F42,"n/a") -> 1.2043776 | G50: =+IFERROR(G12/G42,"n/a") -> 1.1670118 | H50: =+IFERROR(H12/H42,"n/a") -> 1.1726303 | I50: =+IFERROR(I12/I42,"n/a") -> 1.1793281 | J50: 0.9 | K50: 0.9 | L50: 0.95 | M50: 1 | N50: 1 | O50: =+N50 -> 1 | P50: =+O50 -> 1 | Q50: =+P50 -> 1 | R50: =+Q50 -> 1
B51: ADR Penetration | C51: =+IFERROR(C13/C43,"n/a") -> 0.63504411 | D51: =+IFERROR(D13/D43,"n/a") -> 0.61245998 | E51: =+IFERROR(E13/E43,"n/a") -> 0.60213712 | F51: =+IFERROR(F13/F43,"n/a") -> 0.64032068 | G51: =+IFERROR(G13/G43,"n/a") -> 0.63317519 | H51: =+IFERROR(H13/H43,"n/a") -> 0.60211154 | I51: =+IFERROR(I13/I43,"n/a") -> 0.58602564 | J51: 0.9 | K51: 0.9 | L51: 1 | M51: 1 | N51: 1 | O51: =N51 -> 1 | P51: =O51 -> 1 | Q51: =P51 -> 1 | R51: =Q51 -> 1
B52: RevPAR Penetration | C52: =+IFERROR(C14/C44,"n/a") -> 0.55311205 | D52: =+IFERROR(D14/D44,"n/a") -> 0.56841276 | E52: =+IFERROR(E14/E44,"n/a") -> 0.75263252 | F52: =+IFERROR(F14/F44,"n/a") -> 0.77118787 | G52: =+IFERROR(G14/G44,"n/a") -> 0.73892292 | H52: =+IFERROR(H14/H44,"n/a") -> 0.70605421 | I52: =+IFERROR(I14/I44,"n/a") -> 0.69111652 | J52: =+IFERROR(J32/J44,"n/a") -> 0.003420845 | K52: =+IFERROR(K32/K44,"n/a") -> 0.0034769732 | L52: =+IFERROR(L32/L44,"n/a") -> 0.0034249653 | M52: =+IFERROR(M32/M44,"n/a") -> 0.0032673122 | N52: =+IFERROR(N32/N44,"n/a") -> 0.0031873107 | O52: =+IFERROR(O32/O44,"n/a") -> 0.0031248144 | P52: =+IFERROR(P32/P44,"n/a") -> 0.0030635436 | Q52: =+IFERROR(Q32/Q44,"n/a") -> 0.0030034741 | R52: =+IFERROR(R32/R44,"n/a") -> 0.0029445824
B54: Occ Variance to Subject | C54: =+IFERROR(C42-C12,"n/a") -> 0.10011789 | D54: =+IFERROR(D42-D12,"n/a") -> 0.031859911 | E54: =+IFERROR(E42-E12,"n/a") -> -0.16670693 | F54: =+IFERROR(F42-F12,"n/a") -> -0.14429058 | G54: =+IFERROR(G42-G12,"n/a") -> -0.11791034 | H54: =+IFERROR(H42-H12,"n/a") -> -0.12256748 | I54: =+IFERROR(I42-I12,"n/a") -> -0.12355708 | J54: =+IFERROR(J42-J12,"n/a") -> -0.074268 | ... R54: =+IFERROR(R42-R12,"n/a") -> -0.075955978
B55: ADR Variance to Subject | C55: =+IFERROR(C43-C13,"n/a") -> 111.88818 | D55: =+IFERROR(D43-D13,"n/a") -> 129.60501 | E55: =+IFERROR(E43-E13,"n/a") -> 154.45037 | F55: =+IFERROR(F43-F13,"n/a") -> 154.80958 | G55: =+IFERROR(G43-G13,"n/a") -> 143.14238 | H55: =+IFERROR(H43-H13,"n/a") -> 156.01604 | I55: =+IFERROR(I43-I13,"n/a") -> 169.39003 | J55: =+IFERROR(J43-J13,"n/a") -> 121.11777 | ... R55: =+IFERROR(R43-R13,"n/a") -> 119.76456
B56: RevPAR Variance to Subject | C56: =+IFERROR(C44-C14,"n/a") -> 106.31736 | D56: =+IFERROR(D44-D14,"n/a") -> 63.940725 | E56: =+IFERROR(E44-E14,"n/a") -> 64.050714 | F56: =+IFERROR(F44-F14,"n/a") -> 69.529018 | G56: =+IFERROR(G44-G14,"n/a") -> 71.925512 | H56: =+IFERROR(H44-H14,"n/a") -> 81.83395 | I56: =+IFERROR(I44-I14,"n/a") -> 87.08198 | J56: =+IFERROR(J44-J14,"n/a") -> 60.507936 | ... R56: =+IFERROR(R44-R14,"n/a") -> 55.426215
B62: Notes:
B63: (1) Competitive Set RevPAR growth through 2020 is based on third-party projections. Assumed 3.0% growth thereafter.
B66: FAIR SHARE PERFORMANCE (REVPAR, OCC, ADR)
B67: Property Rooms | E67: =C8 -> 132
B68: Total Market Rooms (Comp Set Supply) | E68: =W29 -> 419
B69: Period Days (e.g., 365 for TTM, 30 for month) | E69: 365
B70: STR Comp Set Occ (%) | E70: =H23 -> 0.742 | F70: 2024
B71: STR Comp Set ADR ($) | E71: =H24 -> 284.79 | F71: 2024
B72: STR Property Occ (%) | E72: 0.829
B73: STR Property ADR ($) | E73: 233.45
B74: STR Property RevPAR ($) | E74: =E72*E73 -> 193.53005
B76: MARKET METRICS (BASED ON STR)
B77: Total Market Room Nights Available | E77: =E68*E69 -> 152935
B78: Total Market Demand (Room Nights) | E78: =E70*E77 -> 113477.77
B79: Total Market Rooms Revenue ($) | E79: =E78*E71 -> 32317334
B80: Market Occ (%) | E80: =E78/E77 -> 0.742
B81: Market ADR ($) | E81: =E71 -> 284.79
B82: Market RevPAR ($) | E82: =E80*E81 -> 211.31418
B84: FAIR SHARE EXPECTED (MARKET-EQUAL PERFORMANCE)
B85: Fair Share % (Room Share) | E85: =E67/E68 -> 0.3150358
B86: Fair Share Demand (Room Nights) | E86: =E85*E78 -> 35749.56
B87: Fair Share Room Revenue ($) | E87: =E85*E79 -> 10181117
B88: Fair Share Occ (%) | E88: =E86/(E67*E69) -> 0.742
B89: Fair Share ADR ($) | E89: =E87/E86 -> 284.79
B90: Fair Share RevPAR ($) | E90: =E88*E89 -> 211.31418
B92: PENETRATION INDEXES (ACTUAL VS FAIR SHARE)
B93: Occ Index | E93: =E72/E88 -> 1.1172507
B94: ADR Index | E94: =E73/E89 -> 0.81972682
B95: RevPAR Index | E95: =E74/E90 -> 0.91584034
B97: REVENUE OPPORTUNITY VS FAIR SHARE
B98: RevPAR Gap ($ vs Fair Share) | E98: =E90-E74 -> 17.78413
B99: Rooms Revenue Opportunity for Period ($) | E99: =E98*E67*E69 -> 856839.38

Sheet Proforma
B2: PRELIMINARY HOTEL UNDERWRITING
B3: Proforma Projections
E5: BASE YEAR | J5: 1 | O5: =+J5+1 -> 2 | T5: =+O5+1 -> 3 | Y5: =+T5+1 -> 4 | AD5: =+Y5+1 -> 5 | AI5: =+AD5+1 -> 6
E6: =+YEAR(H8) -> 2025 | J6: =+$E$6+M8 -> 2025 | O6: =+$E$6+R8 -> 2026 | T6: =+$E$6+W8 -> 2027 | Y6: =+$E$6+AB8 -> 2028 | AD6: =+$E$6+AG8 -> 2029 | AI6: =+$E$6+AL8 -> 2030
E8: Hotel Delivery | H8: =Model!I4 -> 45930 | J8: Year | M8: 0 | O8: Year | R8: =+M8+1 -> 1 | T8: Year | W8: =+R8+1 -> 2 | Y8: Year | AB8: =+W8+1 -> 3 | AD8: Year | AG8: =+AB8+1 -> 4 | AI8: Year | AL8: =+AG8+1 -> 5
E9: Days | H9: {=+INDEX('Index Analysis'!$C$7:$R$7,MATCH(Proforma!E$6,'Index Analysis'!$C$6:$R$6,0))} -> 366 | J9: Days | M9: {=+INDEX('Index Analysis'!$C$7:$R$7,MATCH(Proforma!J$6,'Index Analysis'!$C$6:$R$6,0))} -> 366 | O9: Days | R9: {=+INDEX('Index Analysis'!$C$7:$R$7,MATCH(Proforma!O$6,'Index Analysis'!$C$6:$R$6,0))} -> 365 | T9: Days | W9: {=+INDEX('Index Analysis'!$C$7:$R$7,MATCH(Proforma!T$6,'Index Analysis'!$C$6:$R$6,0))} -> 365 | Y9: Days | AB9: {=+INDEX('Index Analysis'!$C$7:$R$7,MATCH(Proforma!Y$6,'Index Analysis'!$C$6:$R$6,0))} -> 365 | AD9: Days | AG9: {=+INDEX('Index Analysis'!$C$7:$R$7,MATCH(Proforma!AD$6,'Index Analysis'!$C$6:$R$6,0))} -> 366 | AI9: Days | AL9: {=+INDEX('Index Analysis'!$C$7:$R$7,MATCH(Proforma!AI$6,'Index Analysis'!$C$6:$R$6,0))} -> 365
E10: Number of Rooms | H10: {=+INDEX('Index Analysis'!$C$8:$R$8,MATCH(Proforma!E$6,'Index Analysis'!$C$6:$R$6,0))} -> 132 | J10: Number of Rooms | M10: {=+INDEX('Index Analysis'!$C$8:$R$8,MATCH(Proforma!J$6,'Index Analysis'!$C$6:$R$6,0))} -> 132 | O10: Number of Rooms | R10: {=+INDEX('Index Analysis'!$C$8:$R$8,MATCH(Proforma!O$6,'Index Analysis'!$C$6:$R$6,0))} -> 132 | T10: Number of Rooms | W10: {=+INDEX('Index Analysis'!$C$8:$R$8,MATCH(Proforma!T$6,'Index Analysis'!$C$6:$R$6,0))} -> 132 | Y10: Number of Rooms | AB10: {=+INDEX('Index Analysis'!$C$8:$R$8,MATCH(Proforma!Y$6,'Index Analysis'!$C$6:$R$6,0))} -> 132 | AD10: Number of Rooms | AG10: {=+INDEX('Index Analysis'!$C$8:$R$8,MATCH(Proforma!AD$6,'Index Analysis'!$C$6:$R$6,0))} -> 132 | AI10: Number of Rooms | AL10: {=+INDEX('Index Analysis'!$C$8:$R$8,MATCH(Proforma!AI$6,'Index Analysis'!$C$6:$R$6,0))} -> 132
E11: Available Rooms | H11: =+H10*H9 -> 48312 | J11: Available Rooms | M11: =+M10*M9 -> 48312 | O11: Available Rooms | R11: =+R10*R9 -> 48180 | T11: Available Rooms | W11: =+W10*W9 -> 48180 | Y11: Available Rooms | AB11: =+AB10*AB9 -> 48180 | AD11: Available Rooms | AG11: =+AG10*AG9 -> 48312 | AI11: Available Rooms | AL11: =+AL10*AL9 -> 48180
E12: Occupied Rooms | H12: =+H11*H13 -> 39256.258 | J12: Occupied Rooms | M12: =+M11*M13 -> 39256.258 | O12: Occupied Rooms | R12: =+R11*R13 -> 36375.9 | T12: Occupied Rooms | W12: =+W11*W13 -> 36375.9 | Y12: Occupied Rooms | AB12: =+AB11*AB13 -> 35939.389 | AD12: Occupied Rooms | AG12: =+AG11*AG13 -> 37118.989 | AI12: Occupied Rooms | AL12: =+AL11*AL13 -> 37202.659
E13: Occupancy | H13: {=+INDEX('Index Analysis'!$C$12:$R$12,MATCH(Proforma!E$6,'Index Analysis'!$C$6:$R$6,0))} -> 0.81255708 | J13: Occupancy | M13: {=+INDEX('Index Analysis'!$C$12:$R$12,MATCH(Proforma!J$6,'Index Analysis'!$C$6:$R$6,0))} -> 0.81255708 | O13: Occupancy | R13: {=+INDEX('Index Analysis'!$C$12:$R$12,MATCH(Proforma!O$6,'Index Analysis'!$C$6:$R$6,0))} -> 0.755 | T13: Occupancy | W13: {=+INDEX('Index Analysis'!$C$12:$R$12,MATCH(Proforma!T$6,'Index Analysis'!$C$6:$R$6,0))} -> 0.755 | Y13: Occupancy | AB13: {=+INDEX('Index Analysis'!$C$12:$R$12,MATCH(Proforma!Y$6,'Index Analysis'!$C$6:$R$6,0))} -> 0.74594 | AD13: Occupancy | AG13: {=+INDEX('Index Analysis'!$C$12:$R$12,MATCH(Proforma!AD$6,'Index Analysis'!$C$6:$R$6,0))} -> 0.7683182 | AI13: Occupancy | AL13: {=+INDEX('Index Analysis'!$C$12:$R$12,MATCH(Proforma!AI$6,'Index Analysis'!$C$6:$R$6,0))} -> 0.77215979
E14: Average Rate | H14: =+H16/H13 -> 239.78997 | J14: Average Rate | M14: =+M16/M13 -> 239.78997 | O14: Average Rate | R14: =+R16/R13 -> 295.42747 | T14: Average Rate | W14: =+W16/W13 -> 296.68227 | Y14: Average Rate | AB14: =+AB16/AB13 -> 311.09861 | AD14: Average Rate | AG14: =+AG16/AG13 -> 323.03977 | AI14: Average Rate | AL14: =+AL16/AL13 -> 329.50056
E15: Annual ADR Growth | M15: N/A | R15: =(R14-M14)/M14 -> 0.23202595 | W15: =(W14-R14)/R14 -> 0.0042474227 | AB15: =(AB14-W14)/W14 -> 0.048591837 | AG15: =(AG14-AB14)/AB14 -> 0.038383838 | AL15: =(AL14-AG14)/AG14 -> 0.02
E16: RevPAR | H16: {=+INDEX('Index Analysis'!$C$14:$R$14,MATCH(Proforma!E$6,'Index Analysis'!$C$6:$R$6,0))} -> 194.84304 | J16: RevPAR | M16: {=+INDEX('Index Analysis'!$C$14:$R$14,MATCH(Proforma!J$6,'Index Analysis'!$C$6:$R$6,0))} -> 194.84304 | O16: RevPAR | R16: {=+INDEX('Index Analysis'!$C$14:$R$14,MATCH(Proforma!O$6,'Index Analysis'!$C$6:$R$6,0))} -> 223.04774 | T16: RevPAR | W16: {=+INDEX('Index Analysis'!$C$14:$R$14,MATCH(Proforma!T$6,'Index Analysis'!$C$6:$R$6,0))} -> 223.99512 | Y16: RevPAR | AB16: {=+INDEX('Index Analysis'!$C$14:$R$14,MATCH(Proforma!Y$6,'Index Analysis'!$C$6:$R$6,0))} -> 232.0609 | AD16: RevPAR | AG16: {=+INDEX('Index Analysis'!$C$14:$R$14,MATCH(Proforma!AD$6,'Index Analysis'!$C$6:$R$6,0))} -> 248.19733 | AI16: RevPAR | AL16: {=+INDEX('Index Analysis'!$C$14:$R$14,MATCH(Proforma!AI$6,'Index Analysis'!$C$6:$R$6,0))} -> 254.42709
E17: Annual RevPAR Growth | M17: N/A | R17: =(R16-M16)/M16 -> 0.144756 | W17: =(W16-R16)/R16 -> 0.0042474227 | AB17: =(AB16-W16)/W16 -> 0.036008735 | AG17: =(AG16-AB16)/AB16 -> 0.069535354 | AL17: =(AL16-AG16)/AG16 -> 0.0251
O18: Annual RevPAR Growth | R18: =+R16/M16-1 -> 0.144756 | T18: Annual RevPAR Growth | W18: =+W16/R16-1 -> 0.0042474227 | Y18: Annual RevPAR Growth | AB18: =+AB16/W16-1 -> 0.036008735 | AD18: Annual RevPAR Growth | AG18: =+AG16/AB16-1 -> 0.069535354 | AI18: Annual RevPAR Growth | AL18: =+AL16/AG16-1 -> 0.0251
F20: Amount | G20: Index | H20: $ / % | J20: Amount | K20: % Rev | L20: PAR | M20: POR | O20: Amount | P20: % Rev | Q20: PAR | R20: POR | T20: Amount | U20: % Rev | V20: PAR | W20: POR | Y20: Amount | Z20: % Rev | AA20: PAR | AB20: POR | AD20: Amount | AE20: % Rev | AF20: PAR | AG20: POR | AI20: Amount | AJ20: % Rev | AK20: PAR | AL20: POR
B21: REVENUES | AR21: Seasonality
B22: Rooms | J22: =Historical!AW21 -> 9322917.5 | K22: =+J22/J$29 -> 0.66545602 | L22: =+J22/M$11 -> 192.97312 | M22: =+J22/M$12 -> 237.4887 | O22: =+R14*R12 -> 10746440 | P22: =+O22/O$29 -> 0.67624137 | Q22: =+O22/R$11 -> 223.04774 | R22: =+O22/R$12 -> 295.42747 | T22: =+W14*W12 -> 10792085 | U22: =+T22/T$29 -> 0.66686883 | V22: =+T22/W$11 -> 223.99512 | W22: =+T22/W$12 -> 296.68227 | Y22: =+AB14*AB12 -> 11180694 | Z22: =+Y22/Y$29 -> 0.67379141 | AA22: =+Y22/AB$11 -> 232.0609 | AB22: =+Y22/AB$12 -> 311.09861 | AD22: =+AG14*AG12 -> 11990910 | AE22: =+AD22/AD$29 -> 0.67938602 | AF22: =+AD22/AG$11 -> 248.19733 | AG22: =+AD22/AG$12 -> 323.03977 | AI22: =+AL14*AL12 -> 12258297 | AJ22: =+AI22/AI$29 -> 0.68054178 | AK22: =+AI22/AL$11 -> 254.42709 | AL22: =+AI22/AL$12 -> 329.50056 | AR22: Jan | AS22: Feb | AT22: Mar | AU22: Apr | AV22: May | AW22: Jun | AX22: Jul | AY22: Aug | AZ22: Sep | BA22: Oct | BB22: Nov | BC22: Dec | BD22: Jan | BE22: Feb | BF22: Mar | BG22: Apr | BH22: May | BI22: Jun | BJ22: Jul | BK22: Aug | BL22: Sep | BM22: Oct | BN22: Nov | BO22: Dec | BP22: Jan | BQ22: Feb | BR22: Mar | BS22: Apr | BT22: May | BU22: Jun | BV22: Jul | BW22: Aug | BX22: Sep | BY22: Oct | BZ22: Nov | CA22: Dec | CB22: Jan | CC22: Feb | CD22: Mar | CE22: Apr | CF22: May | CG22: Jun | CH22: Jul | CI22: Aug | CJ22: Sep | CK22: Oct | CL22: Nov | CM22: Dec | CN22: Jan | CO22: Feb | CP22: Mar | CQ22: Apr | CR22: May | CS22: Jun | CT22: Jul | CU22: Aug | CV22: Sep | CW22: Oct | CX22: Nov | CY22: Dec | CZ22: Jan | DA22: Feb | DB22: Mar | DC22: Apr | DD22: May | DE22: Jun | DF22: Jul | DG22: Aug | DH22: Sep | DI22: Oct | DJ22: Nov | DK22: Dec | DL22: Jan | DM22: Feb | DN22: Mar | DO22: Apr | DP22: May | DQ22: Jun | DR22: Jul | DS22: Aug | DT22: Sep | DU22: Oct | DV22: Nov | DW22: Dec | DX22: Jan | DY22: Feb | DZ22: Mar | EA22: Apr | EB22: May | EC22: Jun | ED22: Jul | EE22: Aug | EF22: Sep | EG22: Oct | EH22: Nov | EI22: Dec | EJ22: Jan | EK22: Feb | EL22: Mar | EM22: Apr | EN22: May | EO22: Jun | EP22: Jul | EQ22: Aug | ER22: Sep | ES22: Oct | ET22: Nov | EU22: Dec
B23: Food & Beverage (2) | G23: POR | H23: 90 | J23: =Historical!AW22 -> 3394470.9 | K23: =+J23/J$29 -> 0.2422923 | L23: =+J23/M$11 -> 70.261444 | M23: =+J23/M$12 -> 86.469549 | O23: =+$H23*(1+$J$90)^R$8*R$12 -> 3322938.5 | P23: =+O23/O$29 -> 0.20910259 | Q23: =+O23/R$11 -> 68.96925 | R23: =+O23/R$12 -> 91.35 | T23: =+$H23*(1+$J$90)^W$8*W$12 -> 3372782.5 | U23: =+T23/T$29 -> 0.20841233 | V23: =+T23/W$11 -> 70.003789 | W23: =+T23/W$12 -> 92.72025 | Y23: =+$H23*(1+$J$90)^AB$8*AB$12 -> 3382293.8 | Z23: =+Y23/Y$29 -> 0.20382997 | AA23: =+Y23/AB$11 -> 70.201199 | AB23: =+Y23/AB$12 -> 94.111054 | AD23: =+$H23*(1+$J$90)^AG$8*AG$12 -> 3545706.8 | AE23: =+AD23/AD$29 -> 0.20089415 | AF23: =+AD23/AG$11 -> 73.391844 | AG23: =+AD23/AG$12 -> 95.52272 | AI23: =+$H23*(1+$J$90)^AL$8*AL$12 -> 3607004.6 | AJ23: =+AI23/AI$29 -> 0.20024946 | AK23: =+AI23/AL$11 -> 74.865185 | AL23: =+AI23/AL$12 -> 96.95556 | AR23: 0.10092282 | AS23: 0.11310928 | AT23: 0.10665772 | AU23: 0.10121747 | AV23: 0.078483276 | AW23: 0.061436187 | AX23: 0.061639981 | AY23: 0.057022284 | AZ23: 0.051640548 | BA23: 0.073364852 | BB23: 0.081722356 | BC23: 0.11278323 | BD23: =AR23 -> 0.10092282 | BE23: =AS23 -> 0.11310928 | BF23: =AT23 -> 0.10665772 | BG23: =AU23 -> 0.10121747 | BH23: =AV23 -> 0.078483276 | BI23: =AW23 -> 0.061436187 | BJ23: =AX23 -> 0.061639981 | BK23: =AY23 -> 0.057022284 | ... EU23: =EI23 -> 0.11278323
B24: Parking (3) | G24: POR | H24: 0 | K24: =+J24/J$29 -> 0 | L24: =+J24/M$11 -> 0 | M24: =+J24/M$12 -> 0 | O24: =+$H24*(1+$J$90)^R$8*R$12 -> 0 | P24: =+O24/O$29 -> 0 | Q24: =+O24/R$11 -> 0 | R24: =+O24/R$12 -> 0 | T24: =+$H24*(1+$J$90)^W$8*W$12 -> 0 | U24: =+T24/T$29 -> 0 | V24: =+T24/W$11 -> 0 | W24: =+T24/W$12 -> 0 | Y24: =+$H24*(1+$J$90)^AB$8*AB$12 -> 0 | Z24: =+Y24/Y$29 -> 0 | AA24: =+Y24/AB$11 -> 0 | AB24: =+Y24/AB$12 -> 0 | AD24: =+$H24*(1+$J$90)^AG$8*AG$12 -> 0 | AE24: =+AD24/AD$29 -> 0 | AF24: =+AD24/AG$11 -> 0 | AG24: =+AD24/AG$12 -> 0 | AI24: =+$H24*(1+$J$90)^AL$8*AL$12 -> 0 | AJ24: =+AI24/AI$29 -> 0 | AK24: =+AI24/AL$11 -> 0 | AL24: =+AI24/AL$12 -> 0 | AQ24: Month # | AR24: =Model!AO$70 -> 22 | AS24: =Model!AP$70 -> 23 | AT24: =Model!AQ$70 -> 24 | AU24: =Model!AR$70 -> 25 | AV24: =Model!AS$70 -> 26 | AW24: =Model!AT$70 -> 27 | AX24: =Model!AU$70 -> 28 | AY24: =Model!AV$70 -> 29 | ... EU24: =Model!ER$70 -> 129
B25: Misc. Income (4) | G25: POR | H25: 4 | J25: =Historical!AW23 -> 187073.84 | K25: =+J25/J$29 -> 0.013353053 | L25: =+J25/M$11 -> 3.8722024 | M25: =+J25/M$12 -> 4.7654528 | O25: =(+$H25*(1+$J$90)^R$8*R$12) -> 147686.15 | P25: =+O25/O$29 -> 0.0092934485 | Q25: =+O25/R$11 -> 3.0653 | R25: =+O25/R$12 -> 4.06 | T25: =(+$H25*(1+$J$90)^W$8*W$12) -> 149901.45 | U25: =+T25/T$29 -> 0.0092627703 | V25: =+T25/W$11 -> 3.1112795 | W25: =+T25/W$12 -> 4.1209 | Y25: =(+$H25*(1+$J$90)^AB$8*AB$12) -> 150324.17 | Z25: =+Y25/Y$29 -> 0.0090591097 | AA25: =+Y25/AB$11 -> 3.1200533 | AB25: =+Y25/AB$12 -> 4.1827135 | AD25: =(+$H25*(1+$J$90)^AG$8*AG$12) -> 157586.97 | AE25: =+AD25/AD$29 -> 0.0089286289 | AF25: =+AD25/AG$11 -> 3.2618597 | AG25: =+AD25/AG$12 -> 4.2454542 | AI25: =(+$H25*(1+$J$90)^AL$8*AL$12) -> 160311.32 | AJ25: =+AI25/AI$29 -> 0.0088999759 | AK25: =+AI25/AL$11 -> 3.3273416 | AL25: =+AI25/AL$12 -> 4.309136 | AR25: =H8 -> 45930 | AS25: =EOMONTH(AR25,1) -> 45961 | AT25: =EOMONTH(AS25,1) -> 45991 | AU25: =EOMONTH(AT25,1) -> 46022 | AV25: =EOMONTH(AU25,1) -> 46053 | AW25: =EOMONTH(AV25,1) -> 46081 | AX25: =EOMONTH(AW25,1) -> 46112 | AY25: =EOMONTH(AX25,1) -> 46142 | AZ25: =EOMONTH(AY25,1) -> 46173 | ... EU25: =EOMONTH(ET25,1) -> 49187
